Workbook
Name ABF_Legal_Form: #REF!
Name AccountPurpose: #REF!
Name AccountType: #REF!
Name CustomerType: #REF!
Name Energy_Infra: #REF!
Name IQ_CH: 110000
Name IQ_CQ: 5000
Name IQ_CY: 10000
Name IQ_DAILY: 500000
Name IQ_FH: 100000
Name IQ_FQ: 500
Name IQ_FY: 1000
Name IQ_LTM: 2000
Name IQ_MONTH: 15000
Name IQ_NTM: 6000
Name IQ_WEEK: 50000
Name IQ_YTD: 3000
Name Legal_Form_Asset_Type: #REF!
Name YesNo: #REF!

Sheet JS Lookup
B4: Property Type | C4: Collateral Type (from Position Report) | D4: Loan Type | E4: Investment Type | F4: Legal Form | G4: Legal Form (from Position Report) | H4: Subordinate Debt | I4: Position Leverage | J4: Capital Stack Position | K4: Reporting Type | L4: Insurance Reporting Schedule | M4: Fund Type
B5: Multifamily | C5: CRE Agriculture | D5: Acquisition | E5: Origination | F5: Mortgage | G5: Asset Purchase Levered | H5: B-Note | I5: Structural | J5: Senior Mortgage | K5: UW In-Place | L5: Schedule A - Real Estate | M5: FI+
B6: Industrial | C6: CRE Entitled Land | D6: Construction | E6: Loan Acquisition | F6: B-Note | G6: Asset Purchase Unlevered | H6: Mezzanine Loan | I6: Repo/Warehouse | J6: Repo/Warehouse | K6: UW Stabilized Untrended | L6: Schedule B - Commercial Mortgages | M6: Opportunistic
B7: Retail | C7: CRE Ground Lease | D7: Refinance | E7: Financing | F7: CUSIP | G7: CUSIP IG | H7: Preferred Equity | I7: Note on Note | J7: Note on Note | K7: UW Stabilized Trended | L7: Schedule B - Residential Mortgages | M7: Enhanced Core
B8: Hospitality | C8: CRE Hotel | D8: Bridge | E8: CUSIP - New Issue | F8: Mezzanine Loan | G8: CUSIP Non-IG | H8: HRR | I8: Senior Mortgage | J8: Senior Bonds | K8: Most Recent | L8: Schedule D - Non-Financial ABS | M8: FI+ / Opportunistic
B9: Data Center | C9: CRE Industrial | D9: Note-on-Note | E9: CUSIP - Secondary | F9: Preferred Equity | G9: Debt/Platform | H9: Other | I9: N/A - Unlevered | J9: Junior Bonds | K9: 2nd Most Recent | L9: Schedule D - Financial ABS
B10: Office | C10: CRE Mixed Asset Loan Pool | D10: Financing | E10: Syndication | F10: Structured Equity | G10: Equity/Platform | H10: N/A | J10: B-Note | K10: 3rd Most Recent | L10: Schedule D - Other
B11: Mixed Use | C11: CRE Mixed Use | D11: Recapitalization | E11: Levered Whole Loan | F11: Common Equity | G11: Financing Junior | J11: Retained WL Equity | L11: Schedule BA - Residual Tranche
B12: Student Housing | C12: CRE Multi Family | D12: Platform | E12: Forward Flow | F12: Other | G12: Financing Senior | J12: Mezzanine | L12: Schedule BA - Interest in JV, LP or LLC (Bonds)
B13: Senior Housing | C13: CRE Office | D13: Various | E13: Loan Pool Acquisition | G13: CRE Loan Senior | J13: Senior Mezzanine | L13: Schedule BA - Interest in JV, LP or LLC (Common Stocks)
B14: Condo | C14: CRE Retail | D14: N/A | E14: Preferred Equity | G14: CRE Loan Junior | J14: Junior Mezzanine | L14: Schedule BA - Interest in JV, LP or LLC (Preferred Stocks)
B15: Manufactured Housing | C15: CRE Senior Housing | E15: Equity | G15: Asset Purchase Levered -JV/Asset Co | J15: Preferred Equity | L15: Schedule BA - Interest in JV, LP or LLC (Real Estate)
B16: Residential - For Sale Development | C16: CRE Student Housing | E16: Mezzanine | G16: Asset Purchase Unlevered - JV/Asset Co | J16: Common Equity | L16: Schedule BA - Interest in JV, LP or LLC (Mortgage Loans)
B17: Single Family Rental (SFR) | C17: CRE Construction Loans | J17: Other | L17: Schedule BA - Other
B18: BTR | C18: CRE Storage | L18: Schedule DA - Short-Term Investments
B19: Horizontal Land Development | C19: CRE Mobile Home Parks | L19: Schedule DB- PART A - Options, Caps, Floors, Collars, Swaps and Forwards
B20: Agricultural Land | C20: CRE Portfolio | L20: Schedule DB- PART B - Futures Contracts
B21: Land | L21: Schedule DB - PART C - Replication (Synthetic Asset) Transactions Open as of Current Statement Date
B22: Land Banking | L22: Schedule E - (Cash Equivalents)
B23: Lot Servicing | L23: N/A
B24: Medical Office
B25: Life Science
B26: Self Storage
B27: Ground Lease
B28: NNN - Office
B29: NNN - Industrial
B30: NNN - Retail
B31: Various

Sheet Comment Summary
B3: Comment Detail
B4: # | C4: Tab | D4: Cell | E4: Header / Field | F4: Category | G4: Comment
B5: =ROW()-4 -> 1 | C5: Capital Stack | D5: D2 | E5: Debt Stack Type | F5: Suggestion | G5: Consider replacing with Investment Type to the right
B6: =ROW()-4 -> 2 | C6: Capital Stack | D6: E2 | E6: SSP Investment Type | F6: Suggestion | G6: Added what I think categories should be. Could replace Origination Type
B7: =ROW()-4 -> 3 | C7: Capital Stack | D7: F2 | E7: Legal Form | F7: Discussion Point | G7: Currently pulling my view on options for drop-down
B8: =ROW()-4 -> 4 | C8: Capital Stack | D8: G2 | E8: Legal Form (Position Report) | F8: Discussion Point | G8: Curren drop-down options from the position report, should discuss which to use or if to include both
B9: =ROW()-4 -> 5 | C9: Capital Stack | D9: M2 | E9: SSP Total Invested Capital | F9: Discussion Point | G9: Copied initial for now, but needs to be updated Need to discuss how to capture original invested amounts and current invested amounts over time
B10: =ROW()-4 -> 6 | C10: Capital Stack | D10: N2 | E10: SSP Total Invested Capital | F10: Discussion Point | G10: Copied initial for now, but needs to be updated Need to discuss how to capture original invested amounts and current invested amounts over time
B11: =ROW()-4 -> 7 | C11: Capital Stack | D11: O2 | E11: SSP Last Dollar Exposure | F11: Suggestion | G11: Could be calc'd so maybe doesn’t need to be in this tape but think it would be helpful to see at least
B12: =ROW()-4 -> 8 | C12: Capital Stack | D12: P2 | E12: Investment Level Leverage | F12: Definition / Guidance | G12: Meant to capture if there is leverage on our position, either structurally or through us borrowing
B13: =ROW()-4 -> 9 | C13: Capital Stack | D13: Q2 | E13: Leverage Provider | F13: Definition / Guidance | G13: Who is giving us the leverage? Like GS on BLT and Hearthstone, Apollo on Royalton Levered, Santander on anything on our warehouse line, etc.
B14: =ROW()-4 -> 10 | C14: Capital Stack | D14: R2 | E14: Total Deal Size | F14: Discussion Point | G14: Total deal capitalization. To discuss what layer to include down to for CML. Current thought is to include through collateral value which inherently includes borrower equity, thought being we can then calc subordination, etc. Or maybe have multiple columns that capture total cost, appraised value, underwritten value so we can look multiple ways
B15: =ROW()-4 -> 11 | C15: Capital Stack | D15: S2 | E15: Total Cost | F15: Discussion Point | G15: Same comment as R2 (Total Deal Size)
B16: =ROW()-4 -> 12 | C16: Capital Stack | D16: T2 | E16: Total Appraised Value | F16: Discussion Point | G16: Same comment as R2 (Total Deal Size)
... B71: =ROW()-4 -> 67 | C71: Allocations & Returns | D71: AS2 | E71: Capital Charge | F71: Question | G71: Can we have this calc automatically based on inputs?

Sheet INPUTS ->

Sheet Property UW
A2: Mash-ID | B2: Deal Code | C2: Loan Name | D2: Reporting Type | E2: As of | F2: Occupancy | G2: Revenues | H2: Expenses | I2: NOI | J2: Reporting Type | K2: As of | L2: Occupancy | M2: Revenues | N2: Expenses | O2: NOI | P2: Reporting Type | Q2: As of | R2: Occupancy | S2: Revenues | T2: Expenses | U2: NOI | V2: Reporting Type | W2: As of | X2: Occupancy | Y2: Revenues | Z2: Expenses | AA2: NOI | AB2: Reporting Type | AC2: As of | AD2: Occupancy | AE2: Revenues | AF2: Expenses | AG2: NOI | AH2: Reporting Type | AI2: As of | AJ2: Occupancy | AK2: Revenues | AL2: Expenses | AM2: NOI
A3: MaSH-3410443 | B3: 67692 | C3: Project Sequoia | D3: UW In-Place | E3: 45016 | F3: 0.92620307 | G3: 1.5991943e+08 | H3: 36199451 | I3: 1.2371998e+08 | J3: UW Stabilized Untrended | K3: 45016 | L3: 0.93412893 | M3: 1.8295511e+08 | N3: 38684138 | O3: 1.4427097e+08 | P3: UW Stabilized Trended | Q3: 45016 | R3: 0.93412893 | S3: 2.0591759e+08 | T3: 43539338 | U3: 1.6237825e+08 | V3: Most Recent | W3: 46203 | AB3: 2nd Most Recent | AC3: 46112 | AH3: 3rd Most Recent | AI3: 46022
A4: MaSH-3256633 | B4: 61883 | C4: Project Royale | D4: UW In-Place | E4: 44804 | F4: 0.97 | G4: 41792640 | H4: 21146929 | I4: 20645711 | J4: UW Stabilized Untrended | K4: 44804 | L4: 0.94 | M4: 41810031 | N4: 23644217 | O4: 18165814 | P4: UW Stabilized Trended | Q4: 44804 | R4: 0.94 | S4: 49070783 | T4: 23862039 | U4: 25208744 | V4: Most Recent | W4: 46203 | AB4: 2nd Most Recent | AC4: 46112 | AH4: 3rd Most Recent | AI4: 46022
A5: MaSH-3258016 | B5: 61973 | C5: Lakefront North | D5: UW In-Place | E5: 44865 | F5: =223920/258031 -> 0.86780271 | G5: 9822780 | H5: 4304747 | I5: =G5-H5 -> 5518033 | J5: UW Stabilized Untrended | P5: UW Stabilized Trended | Q5: 48518 | R5: 0.9 | S5: 12507327 | T5: 5607424 | U5: =S5-T5 -> 6899903 | V5: Most Recent | W5: 46203 | AB5: 2nd Most Recent | AC5: 46112 | AH5: 3rd Most Recent | AI5: 46022
A6: MaSH-3339577 | B6: 64734 | C6: Project Balboa | D6: UW In-Place | E6: 44896 | F6: 0.94742094 | G6: 6141504 | H6: 1978989 | I6: =G6-H6 -> 4162515 | J6: UW Stabilized Untrended | P6: UW Stabilized Trended | Q6: 47118 | R6: 0.9 | S6: 7387940 | T6: 2242930 | U6: =S6-T6 -> 5145010 | V6: Most Recent | W6: 46203 | AB6: 2nd Most Recent | AC6: 46112 | AH6: 3rd Most Recent | AI6: 46022
A7: MaSH-3534532 | B7: 102039 | C7: Project Cubic | D7: UW In-Place | E7: 45223 | F7: 0.94181037 | G7: 85629602 | H7: 18034079 | I7: 67595522 | J7: UW Stabilized Untrended | K7: =E7 -> 45223 | L7: 0.93059688 | M7: 96150116 | N7: 20062287 | O7: 76087829 | P7: UW Stabilized Trended | Q7: =E7 -> 45223 | R7: 0.93059688 | S7: 1.0633695e+08 | T7: 23285648 | U7: 83051307 | V7: Most Recent | W7: 46203 | AB7: 2nd Most Recent | AC7: 46112 | AH7: 3rd Most Recent | AI7: 46022
A8: MaSH-3337170 | B8: 64681 | C8: Project Eyas | D8: UW In-Place | E8: 44926 | F8: 0.8357 | G8: 38426648 | H8: 23123380 | I8: 15303268 | J8: UW Stabilized Untrended | K8: =E8 -> 44926 | L8: 0.9 | M8: 41091692 | N8: 25960832 | O8: 15130860 | P8: UW Stabilized Trended | Q8: 46752 | R8: 0.9 | S8: 48459755 | T8: 26181874 | U8: 22277881 | V8: Most Recent | W8: 46203 | AB8: 2nd Most Recent | AC8: 46112 | AH8: 3rd Most Recent | AI8: 46022
A9: MaSH-3340378 | B9: 64777 | C9: Project Stripe | D9: UW In-Place | E9: 44926 | F9: 0.938454 | G9: 51011504 | H9: 19135416 | I9: 31876088 | J9: UW Stabilized Untrended | K9: =E9 -> 44926 | L9: 0.945 | M9: 52118176 | N9: 21018433 | O9: 31099743 | P9: UW Stabilized Trended | Q9: 46752 | R9: 0.945 | S9: 60345855 | T9: 21244695 | U9: 39101160 | V9: Most Recent | W9: 46203 | AB9: 2nd Most Recent | AC9: 46112 | AH9: 3rd Most Recent | AI9: 46022
A10: MaSH-3687981 | B10: 255488 | C10: Project Bellevue | D10: UW In-Place | E10: 45688 | F10: 0.5054 | G10: 31282158 | H10: 22916597 | I10: 8365560.6 | J10: UW Stabilized Untrended | K10: =E10 -> 45688 | L10: 0.8114 | M10: 46759937 | N10: 27373488 | O10: 19386448 | P10: UW Stabilized Trended | Q10: 46387 | R10: 0.8001 | S10: 46980437 | T10: 27579522 | U10: 19400915 | V10: Most Recent | W10: 46203 | AB10: 2nd Most Recent | AC10: 46112 | AH10: 3rd Most Recent | AI10: 46022
A11: MaSH-3773167 | B11: 340674 | C11: Project Fayetteville 2-Pack | D11: UW In-Place | E11: 45991 | F11: 0.900641 | G11: 4804718.5 | H11: 1436022.5 | I11: 3368696 | J11: UW Stabilized Untrended | K11: 45991 | L11: 0.935 | M11: 4760346.5 | N11: 1434691.4 | O11: 3325655.1 | P11: UW Stabilized Trended | Q11: 47452 | R11: 0.93 | S11: 4881228.1 | T11: 1546115.1 | U11: 3335113 | V11: Most Recent | W11: 46203 | AB11: 2nd Most Recent | AC11: 46112 | AH11: 3rd Most Recent | AI11: 46022
A12: MaSH-3774814 | B12: 342321 | C12: Mosaic Apartments | D12: UW In-Place | E12: 45930 | F12: 0.90131579 | G12: 7037303.6 | H12: 2700684.3 | I12: 4336619.3 | J12: UW Stabilized Untrended | K12: 45930 | L12: 0.9 | M12: 6895728.7 | N12: 2700684.3 | O12: 4195044.4 | P12: UW Stabilized Trended | Q12: 47757 | R12: 0.9 | S12: 7322831.2 | T12: 3047156.6 | U12: 4275674.6 | V12: Most Recent | W12: 46203 | AB12: 2nd Most Recent | AC12: 46112 | AH12: 3rd Most Recent | AI12: 46022
A13: MaSH-3774820 | B13: 342327 | C13: Project Arista | D13: UW In-Place | E13: 45991 | F13: 0.91740882 | G13: 5673443.5 | H13: 1978718 | I13: 3694725.4 | J13: UW Stabilized Untrended | K13: 45991 | L13: 0.93592317 | M13: 5781629.4 | N13: 2399712.5 | O13: 3381916.9 | P13: UW Stabilized Trended | Q13: 46037 | R13: 0.945 | S13: 6606139.7 | T13: 2502369.6 | U13: 4103770.1 | V13: Most Recent | W13: 46203 | AB13: 2nd Most Recent | AC13: 46112 | AH13: 3rd Most Recent | AI13: 46022
A14: MaSH-3700986 | B14: 268493 | C14: Project Grand Bay Hotel San Francisco | D14: UW In-Place | E14: 45930 | F14: 0.5676439 | G14: 26141990 | H14: 22985235 | I14: 3156755.3 | J14: UW Stabilized Untrended | K14: 45930 | L14: 0.74867258 | M14: 39646844 | N14: 29818293 | O14: 9828550.7 | P14: UW Stabilized Trended | Q14: 47118 | R14: 0.78089457 | S14: 44901113 | T14: 33779704 | U14: 11121409 | V14: Most Recent | W14: 46203 | AB14: 2nd Most Recent | AC14: 46112 | AH14: 3rd Most Recent | AI14: 46022
A15: MaSH-3776991 | B15: 344498 | C15: Crystal Springs Resort | D15: UW In-Place | E15: 46022 | F15: 0.52007062 | G15: 1.0600131e+08 | H15: 80998881 | I15: 25002425 | J15: UW Stabilized Untrended | K15: 46163 | L15: 0.525 | M15: 1.0740813e+08 | N15: 82816119 | O15: 24592009 | P15: UW Stabilized Trended | Q15: 46538 | R15: 0.523 | S15: 1.0204269e+08 | T15: 81733834 | U15: 20308861 | V15: Most Recent | W15: 46203 | AB15: 2nd Most Recent | AC15: 46112 | AH15: 3rd Most Recent | AI15: 46022
A16: MaSH-3776993 | B16: 344500 | C16: Alpine Village | D16: UW In-Place | E16: 46216 | F16: 0.9522293 | G16: 7451883.4 | H16: 3609556.6 | I16: 3842326.8 | J16: UW Stabilized Untrended | K16: =E16 -> 46216 | L16: 0.94 | M16: 7682070.5 | N16: 3573497.6 | O16: 4108572.8 | P16: UW Stabilized Trended | Q16: 47695 | R16: 0.94 | S16: 8038033.6 | T16: 3831520.9 | U16: 4206512.7 | V16: Most Recent | W16: 46203 | AB16: 2nd Most Recent | AC16: 46112 | AH16: 3rd Most Recent | AI16: 46022
A17: MaSH-3773094 | B17: 340601 | C17: Project Highland Portfolio | D17: UW In-Place | E17: 46203 | F17: 0.68166557 | G17: 2.3383749e+08 | H17: 1.6855565e+08 | I17: 65281844 | J17: UW Stabilized Untrended | K17: 47483 | L17: 0.70030842 | M17: 2.687151e+08 | N17: 1.9101047e+08 | O17: 77704632 | P17: UW Stabilized Trended | Q17: 47848 | R17: 0.70030842 | S17: 2.7645728e+08 | T17: 1.9637732e+08 | U17: 80079959 | V17: Most Recent | W17: 46203 | AB17: 2nd Most Recent | AC17: 46112 | AH17: 3rd Most Recent | AI17: 46022
A18: MaSH-3780342 | B18: 347849 | C18: Project Prime Care Portfolio Senior Financing | D18: UW In-Place | E18: 46173 | F18: 0.872 | G18: 95712083 | H18: 75010856 | I18: 20701227 | J18: UW Stabilized Untrended | K18: 46265 | L18: 0.9236 | M18: 1.0391541e+08 | N18: 79291076 | O18: 24624335 | P18: UW Stabilized Trended | Q18: 47726 | R18: 0.9236 | S18: 1.1753539e+08 | T18: 87044257 | U18: 30491136 | V18: Most Recent | W18: 46203 | AB18: 2nd Most Recent | AC18: 46112 | AH18: 3rd Most Recent | AI18: 46022
A19: MaSH-3768501 | B19: 336008 | C19: Project Scarlet Bay | D19: UW In-Place | J19: UW Stabilized Untrended | K19: 45991 | L19: =(5216400*0.95+330470*0.9+10201200*0.94+813735*0.85)/(5216400+330470+10201200+813735) -> 0.93792952 | M19: =5626296+11414557 -> 17040853 | N19: =(1705478-33000)+(3640215-91500) -> 5221193 | O19: =M19-N19 -> 11819660 | P19: UW Stabilized Trended | Q19: 47634 | R19: =(5637471*0.95+357146*0.9+11188794*0.94+892514*0.85)/(5637471+357146+11188794+892514) -> 0.93788462 | S19: =6080453+12519618 -> 18600071 | T19: =(1846448-35664)+(4001946-100358) -> 5712372 | U19: =S19-T19 -> 12887699 | V19: Most Recent | W19: 46203 | AB19: 2nd Most Recent | AC19: 46112 | AH19: 3rd Most Recent | AI19: 46022
A20: MaSH-3773946 | B20: 342718 | C20: Project Royalton Whole Loan | D20: UW In-Place | E20: 46022 | F20: 0.8548 | G20: 37773260 | H20: 30524460 | I20: 7248800 | J20: UW Stabilized Untrended | K20: 46022 | L20: 0.8 | M20: 71751230 | N20: 51555820 | O20: 20195410 | P20: UW Stabilized Trended | Q20: 47483 | R20: 0.8 | S20: 86747820 | T20: 61305790 | U20: 25442030 | V20: Most Recent | W20: 46203 | AB20: 2nd Most Recent | AC20: 46112 | AH20: 3rd Most Recent | AI20: 46022
C21: Project Royalton Levered | D21: UW In-Place | E21: =E$20 -> 46022 | F21: =F$20 -> 0.8548 | G21: =G$20 -> 37773260 | H21: =H$20 -> 30524460 | I21: =I$20 -> 7248800 | J21: UW Stabilized Untrended | K21: =K$20 -> 46022 | L21: =L$20 -> 0.8 | M21: =M$20 -> 71751230 | N21: =N$20 -> 51555820 | O21: =O$20 -> 20195410 | P21: UW Stabilized Trended | Q21: =Q$20 -> 47483 | R21: =R$20 -> 0.8 | S21: =S$20 -> 86747820 | T21: =T$20 -> 61305790 | U21: =U$20 -> 25442030 | V21: Most Recent | W21: 46203 | AB21: 2nd Most Recent | AC21: 46112 | AH21: 3rd Most Recent | AI21: 46022
A22: MaSH-3570618 | B22: 138125 | C22: Project Hearthstone Land | D22: UW In-Place | J22: UW Stabilized Untrended | P22: UW Stabilized Trended | V22: Most Recent | W22: 46203 | AB22: 2nd Most Recent | AC22: 46112 | AH22: 3rd Most Recent | AI22: 46022
A23: MaSH-3777002 | B23: 344509 | C23: HLTN 2026-DPLO - Class B | D23: UW In-Place | E23: 46081 | F23: 0.65609589 | G23: 1.8180281e+08 | H23: 1.2889299e+08 | I23: 52909817 | J23: UW Stabilized Untrended | K23: 46081 | L23: 0.725 | M23: 2.1121719e+08 | N23: 1.4071191e+08 | O23: 70505283 | P23: UW Stabilized Trended | Q23: 46387 | R23: 0.74 | S23: 214165926 | T23: =214165926-70751619 -> 143414307 | U23: =S23-T23 -> 70751619 | V23: Most Recent | W23: 46203 | AB23: 2nd Most Recent | AC23: 46112 | AH23: 3rd Most Recent | AI23: 46022
A24: MaSH-3777002 | B24: 344509 | C24: HLTN 2026-DPLO - Class C | D24: UW In-Place | E24: =E$23 -> 46081 | F24: =F$23 -> 0.65609589 | G24: =G$23 -> 1.8180281e+08 | H24: =H$23 -> 1.2889299e+08 | I24: =I$23 -> 52909817 | J24: UW Stabilized Untrended | K24: =K$23 -> 46081 | L24: =L$23 -> 0.725 | M24: =M$23 -> 2.1121719e+08 | N24: =N$23 -> 1.4071191e+08 | O24: =O$23 -> 70505283 | P24: UW Stabilized Trended | Q24: =Q$23 -> 46387 | R24: =R$23 -> 0.74 | S24: =S$23 -> 214165926 | T24: =T$23 -> 143414307 | U24: =U$23 -> 70751619 | V24: Most Recent | W24: 46203 | AB24: 2nd Most Recent | AC24: 46112 | AH24: 3rd Most Recent | AI24: 46022
A25: MaSH-3777002 | B25: 344509 | C25: HLTN 2026-DPLO - Class D | D25: UW In-Place | E25: =E$23 -> 46081 | F25: =F$23 -> 0.65609589 | G25: =G$23 -> 1.8180281e+08 | H25: =H$23 -> 1.2889299e+08 | I25: =I$23 -> 52909817 | J25: UW Stabilized Untrended | K25: =K$23 -> 46081 | L25: =L$23 -> 0.725 | M25: =M$23 -> 2.1121719e+08 | N25: =N$23 -> 1.4071191e+08 | O25: =O$23 -> 70505283 | P25: UW Stabilized Trended | Q25: =Q$23 -> 46387 | R25: =R$23 -> 0.74 | S25: =S$23 -> 214165926 | T25: =T$23 -> 143414307 | U25: =U$23 -> 70751619 | V25: Most Recent | W25: 46203 | AB25: 2nd Most Recent | AC25: 46112 | AH25: 3rd Most Recent | AI25: 46022
A26: MaSH-3777674 | B26: 345181 | C26: KSL 2026-HT3 - Class B | D26: UW In-Place | E26: 46081 | F26: 0.78382656 | G26: 265516315 | H26: 1.7408766e+08 | I26: 91428653 | J26: UW Stabilized Untrended | K26: 46081 | L26: 0.78107338 | M26: 2.6518861e+08 | N26: 1.7563452e+08 | O26: 89554098 | P26: UW Stabilized Trended | Q26: 46387 | R26: 0.784 | S26: 272884617 | T26: =272884617-92323109 -> 180561508 | U26: =S26-T26 -> 92323109 | V26: Most Recent | W26: 46203 | AB26: 2nd Most Recent | AC26: 46112 | AH26: 3rd Most Recent | AI26: 46022
A27: MaSH-3777674 | B27: 345181 | C27: KSL 2026-HT3 - Class C | D27: UW In-Place | E27: =E$26 -> 46081 | F27: =F$26 -> 0.78382656 | G27: =G$26 -> 265516315 | H27: =H$26 -> 1.7408766e+08 | I27: =I$26 -> 91428653 | J27: UW Stabilized Untrended | K27: =K$26 -> 46081 | L27: =L$26 -> 0.78107338 | M27: =M$26 -> 2.6518861e+08 | N27: =N$26 -> 1.7563452e+08 | O27: =O$26 -> 89554098 | P27: UW Stabilized Trended | Q27: =Q$26 -> 46387 | R27: =R$26 -> 0.784 | S27: =S$26 -> 272884617 | T27: =T$26 -> 180561508 | U27: =U$26 -> 92323109 | V27: Most Recent | W27: 46203 | AB27: 2nd Most Recent | AC27: 46112 | AH27: 3rd Most Recent | AI27: 46022
A28: MaSH-3777674 | B28: 345181 | C28: KSL 2026-HT3 - Class D | D28: UW In-Place | E28: =E$26 -> 46081 | F28: =F$26 -> 0.78382656 | G28: =G$26 -> 265516315 | H28: =H$26 -> 1.7408766e+08 | I28: =I$26 -> 91428653 | J28: UW Stabilized Untrended | K28: =K$26 -> 46081 | L28: =L$26 -> 0.78107338 | M28: =M$26 -> 2.6518861e+08 | N28: =N$26 -> 1.7563452e+08 | O28: =O$26 -> 89554098 | P28: UW Stabilized Trended | Q28: =Q$26 -> 46387 | R28: =R$26 -> 0.784 | S28: =S$26 -> 272884617 | T28: =T$26 -> 180561508 | U28: =U$26 -> 92323109 | V28: Most Recent | W28: 46203 | AB28: 2nd Most Recent | AC28: 46112 | AH28: 3rd Most Recent | AI28: 46022
A29: MaSH-3779335 | B29: 346842 | C29: AHPT 2026-ATRM - Class B | D29: UW In-Place | E29: 46173 | F29: 0.73351356 | G29: 2.4117197e+08 | H29: 1.7166238e+08 | I29: 69509594 | J29: UW Stabilized Untrended | K29: 46173 | L29: 0.72504047 | M29: 2.3848107e+08 | N29: 1.7203549e+08 | O29: 66445578 | P29: UW Stabilized Trended | Q29: 46387 | R29: 0.733 | S29: 244421636 | T29: =244421636-70813368 -> 173608268 | U29: =S29-T29 -> 70813368 | V29: Most Recent | W29: 46203 | AB29: 2nd Most Recent | AC29: 46112 | AH29: 3rd Most Recent | AI29: 46022
A30: MaSH-3779335 | B30: 346842 | C30: AHPT 2026-ATRM - Class C | D30: UW In-Place | E30: =E$29 -> 46173 | F30: =F$29 -> 0.73351356 | G30: =G$29 -> 2.4117197e+08 | H30: =H$29 -> 1.7166238e+08 | I30: =I$29 -> 69509594 | J30: UW Stabilized Untrended | K30: =K$29 -> 46173 | L30: =L$29 -> 0.72504047 | M30: =M$29 -> 2.3848107e+08 | N30: =N$29 -> 1.7203549e+08 | O30: =O$29 -> 66445578 | P30: UW Stabilized Trended | Q30: =Q$29 -> 46387 | R30: =R$29 -> 0.733 | S30: =S$29 -> 244421636 | T30: =T$29 -> 173608268 | U30: =U$29 -> 70813368 | V30: Most Recent | W30: 46203 | AB30: 2nd Most Recent | AC30: 46112 | AH30: 3rd Most Recent | AI30: 46022
A31: MaSH-3779335 | B31: 346842 | C31: AHPT 2026-ATRM - Class D | D31: UW In-Place | E31: =E$29 -> 46173 | F31: =F$29 -> 0.73351356 | G31: =G$29 -> 2.4117197e+08 | H31: =H$29 -> 1.7166238e+08 | I31: =I$29 -> 69509594 | J31: UW Stabilized Untrended | K31: =K$29 -> 46173 | L31: =L$29 -> 0.72504047 | M31: =M$29 -> 2.3848107e+08 | N31: =N$29 -> 1.7203549e+08 | O31: =O$29 -> 66445578 | P31: UW Stabilized Trended | Q31: =Q$29 -> 46387 | R31: =R$29 -> 0.733 | S31: =S$29 -> 244421636 | T31: =T$29 -> 173608268 | U31: =U$29 -> 70813368 | V31: Most Recent | W31: 46203 | AB31: 2nd Most Recent | AC31: 46112 | AH31: 3rd Most Recent | AI31: 46022
A32: MaSH-3779335 | B32: 346842 | C32: AHPT 2026-ATRM - Class E | D32: UW In-Place | E32: =E$29 -> 46173 | F32: =F$29 -> 0.73351356 | G32: =G$29 -> 2.4117197e+08 | H32: =H$29 -> 1.7166238e+08 | I32: =I$29 -> 69509594 | J32: UW Stabilized Untrended | K32: =K$29 -> 46173 | L32: =L$29 -> 0.72504047 | M32: =M$29 -> 2.3848107e+08 | N32: =N$29 -> 1.7203549e+08 | O32: =O$29 -> 66445578 | P32: UW Stabilized Trended | Q32: =Q$29 -> 46387 | R32: =R$29 -> 0.733 | S32: =S$29 -> 244421636 | T32: =T$29 -> 173608268 | U32: =U$29 -> 70813368 | V32: Most Recent | W32: 46203 | AB32: 2nd Most Recent | AC32: 46112 | AH32: 3rd Most Recent | AI32: 46022
A33: MaSH-3748736 | B33: 316243 | C33: Bridge Loan Trust | D33: UW In-Place | E33: 45900 | F33: =(184*0.446+240*0.192+222*0.856+312*0.84+160*0.348+312*0.8+162*0.915+110*0.473+276*0.42+178*0.195+75*0.938+174*0.92+514*0.145+254*0.0819999999999999+150*0.695+96*0.89+56*0.62)/3475 -> 0.5141364 | G33: 36481903 | H33: 17328987 | I33: =G33-H33 -> 19152916 | J33: UW Stabilized Untrended | K33: 45900 | L33: =1-6780925/70125728 -> 0.90330332 | M33: 65663328 | N33: 30804297 | O33: =M33-N33 -> 34859031 | P33: UW Stabilized Trended | Q33: 47726 | R33: =1-7709037/79783992 -> 0.90337614 | S33: 74559759 | T33: 34599209 | U33: =S33-T33 -> 39960550 | V33: Most Recent | W33: 46203 | AB33: 2nd Most Recent | AC33: 46112 | AH33: 3rd Most Recent | AI33: 46022
A34: MaSH-3748736 | B34: 316243 | C34: Bridge Loan Trust - Residual Class B | D34: UW In-Place | E34: =E$33 -> 45900 | F34: =F$33 -> 0.5141364 | G34: =G$33 -> 36481903 | H34: =H$33 -> 17328987 | I34: =I$33 -> 19152916 | J34: UW Stabilized Untrended | K34: =K$33 -> 45900 | L34: =L$33 -> 0.90330332 | M34: =M$33 -> 65663328 | N34: =N$33 -> 30804297 | O34: =O$33 -> 34859031 | P34: UW Stabilized Trended | Q34: =Q$33 -> 47726 | R34: =R$33 -> 0.90337614 | S34: =S$33 -> 74559759 | T34: =T$33 -> 34599209 | U34: =U$33 -> 39960550 | V34: Most Recent | W34: 46203 | AB34: 2nd Most Recent | AC34: 46112 | AH34: 3rd Most Recent | AI34: 46022

Sheet Capital Stack
A2: Mash-ID | B2: Deal Code | C2: Loan Name | D2: Debt Stack Type | E2: SSP Investment Type | F2: Legal Form | G2: Legal Form (Position Report) | H2: SSP Commitment Amount | I2: SSP Initial Loan Balance | J2: Funding Program | K2: Purchase Price | L2: SSP Invested Capital at Close | M2: SSP Total Invested Capital | N2: SSP Total Future Funding | O2: SSP Last Dollar Exposure | P2: Investment Level Leverage | Q2: Leverage Provider | R2: Total Debt | S2: Total Cost | T2: Total Appraised Value | U2: Total Underwritten Value | V2: Most Senior Position | W2: Most Senior Commitment | X2: Most Senior Detachment Point | Y2: Most Senior Attachment Point | Z2: Most Senior Advance Rate | AA2: Most Senior LTV | AB2: Most Senior Spread | AC2: 2nd Most Senior Position | AD2: 2nd Most Senior Commitment | AE2: 2nd Most Senior Detachment Point | AF2: 2nd Most Senior Attachment Point | AG2: 2nd Most Senior Advance Rate | AH2: 2nd Most Senior LTV | AI2: 2nd Most Senior Spread | AJ2: 3rd Most Senior Position | AK2: 3rd Most Senior Commitment | AL2: 3rd Most Senior Detachment Point | AM2: 3rd Most Senior Attachment Point | AN2: 3rd Most Senior Advance Rate | AO2: 3rd Most Senior LTV | AP2: 3rd Most Senior Spread | AQ2: 4th Most Senior Position | AR2: 4th Most Senior Commitment | AS2: 4th Most Senior Detachment Point | AT2: 4th Most Senior Attachment Point | AU2: 4th Most Senior Advance Rate | AV2: 4thMost Senior LTV | AW2: 4th Most Senior Spread
A3: MaSH-3410443 | B3: 67692 | C3: Project Sequoia | D3: A Note | E3: Syndication | F3: Mortgage | G3: CRE Loan Senior | H3: 154500000 | I3: 149600000 | J3: Multiple Funding | K3: 0.9303 | L3: =I3*K3 -> 139172880 | M3: =L3+N3 -> 144072880 | N3: =H3-I3 -> 4900000 | O3: =W3 -> 1962073941 | P3: N/A - Unlevered | Q3: N/A | R3: =IF(OR(V3="",V3="N/A",V3="Common Equity",V3="Builder Deposit / Equity"),0,N(W3))+IF(OR(AC3="",AC3="N/A",AC3="Common Equity",AC3="Builder Deposit / Equity"),0,N(AD3))+IF(OR(AJ3="",AJ3="N/A",AJ3="Common Equity",AJ3="Builder Deposit / Equity"),0,N(AK3))+IF(OR(AQ3="",AQ3="N/A",AQ3="Common Equity",AQ3="Builder Deposit / Equity"),0,N(AR3)) -> 1962073941 | S3: 3065449030 | T3: 3199100000 | U3: 2412300000 | V3: Senior Mortgage | W3: 1962073941 | X3: 0 | Y3: =IF(OR(V3="",V3="N/A",V3="Common Equity",V3="Builder Deposit / Equity",N($R3)=0),"N/A",SUM($W3)/$R3*100) -> 100 | Z3: =IF(OR(V3="",V3="N/A",V3="Common Equity",V3="Builder Deposit / Equity",N($R3)=0),"N/A",SUM($W3)/$R3*100) -> 100 | AA3: =IF(OR(V3="",V3="N/A",N($T3)=0),"N/A",SUM($W3)/$T3*100) -> 61.33206 | AB3: 0.024 | AC3: Common Equity | AD3: =T3-W3 -> 1237026059 | AE3: =IF(OR(AC3="",AC3="N/A"),"N/A",Y3) -> 100 | AF3: =IF(OR(AC3="",AC3="N/A",AC3="Common Equity",AC3="Builder Deposit / Equity",N($R3)=0),"N/A",SUM($W3,$AD3)/$R3*100) -> N/A | AG3: =IF(OR(AC3="",AC3="N/A",AC3="Common Equity",AC3="Builder Deposit / Equity",N($R3)=0),"N/A",SUM($W3,$AD3)/$R3*100) -> N/A | AH3: =IF(OR(AC3="",AC3="N/A",N($T3)=0),"N/A",SUM($W3,$AD3)/$T3*100) -> 100 | AI3: N/A
A4: MaSH-3256633 | B4: 61883 | C4: Project Royale | D4: A Note | E4: Syndication | F4: Mortgage | G4: CRE Loan Senior | H4: 98100000 | I4: 98100000 | J4: Single Funding | K4: 0.99 | L4: =I4*K4 -> 97119000 | M4: =L4+N4 -> 97119000 | N4: =H4-I4 -> 0 | O4: =W4 -> 248100000 | P4: N/A - Unlevered | Q4: N/A | R4: =IF(OR(V4="",V4="N/A",V4="Common Equity",V4="Builder Deposit / Equity"),0,N(W4))+IF(OR(AC4="",AC4="N/A",AC4="Common Equity",AC4="Builder Deposit / Equity"),0,N(AD4))+IF(OR(AJ4="",AJ4="N/A",AJ4="Common Equity",AJ4="Builder Deposit / Equity"),0,N(AK4))+IF(OR(AQ4="",AQ4="N/A",AQ4="Common Equity",AQ4="Builder Deposit / Equity"),0,N(AR4)) -> 300100000 | S4: 394100000 | T4: 400000000 | U4: 407287722 | V4: Senior Mortgage | W4: 248100000 | X4: 0 | Y4: =IF(OR(V4="",V4="N/A",V4="Common Equity",V4="Builder Deposit / Equity",N($R4)=0),"N/A",SUM($W4)/$R4*100) -> 82.672443 | Z4: =IF(OR(V4="",V4="N/A",V4="Common Equity",V4="Builder Deposit / Equity",N($R4)=0),"N/A",SUM($W4)/$R4*100) -> 82.672443 | AA4: =IF(OR(V4="",V4="N/A",N($T4)=0),"N/A",SUM($W4)/$T4*100) -> 62.025 | AB4: 0.0233 | AC4: Mezzanine | AD4: 52000000 | AE4: =IF(OR(AC4="",AC4="N/A"),"N/A",Y4) -> 82.672443 | AF4: =IF(OR(AC4="",AC4="N/A",AC4="Common Equity",AC4="Builder Deposit / Equity",N($R4)=0),"N/A",SUM($W4,$AD4)/$R4*100) -> 100 | AG4: =IF(OR(AC4="",AC4="N/A",AC4="Common Equity",AC4="Builder Deposit / Equity",N($R4)=0),"N/A",SUM($W4,$AD4)/$R4*100) -> 100 | AH4: =IF(OR(AC4="",AC4="N/A",N($T4)=0),"N/A",SUM($W4,$AD4)/$T4*100) -> 75.025 | AI4: 0.0535 | AJ4: Common Equity | AK4: =T4-W4-AD4 -> 99900000 | AL4: =IF(OR(AJ4="",AJ4="N/A"),"N/A",AF4) -> 100 | AM4: =IF(OR(AJ4="",AJ4="N/A",AJ4="Common Equity",AJ4="Builder Deposit / Equity",N($R4)=0),"N/A",SUM($W4,$AD4,$AK4)/$R4*100) -> N/A | AN4: =IF(OR(AJ4="",AJ4="N/A",AJ4="Common Equity",AJ4="Builder Deposit / Equity",N($R4)=0),"N/A",SUM($W4,$AD4,$AK4)/$R4*100) -> N/A | AO4: =IF(OR(AJ4="",AJ4="N/A",N($T4)=0),"N/A",SUM($W4,$AD4,$AK4)/$T4*100) -> 100 | AP4: N/A
A5: MaSH-3258016 | B5: 61973 | C5: Lakefront North | D5: A Note | E5: Origination | F5: Mortgage | G5: CRE Loan Senior | H5: 50000000 | I5: 50000000 | J5: Single Funding | K5: 1 | L5: =I5*K5 -> 50000000 | M5: =L5+N5 -> 50000000 | N5: =H5-I5 -> 0 | O5: =W5 -> 50000000 | P5: N/A - Unlevered | Q5: N/A | R5: =IF(OR(V5="",V5="N/A",V5="Common Equity",V5="Builder Deposit / Equity"),0,N(W5))+IF(OR(AC5="",AC5="N/A",AC5="Common Equity",AC5="Builder Deposit / Equity"),0,N(AD5))+IF(OR(AJ5="",AJ5="N/A",AJ5="Common Equity",AJ5="Builder Deposit / Equity"),0,N(AK5))+IF(OR(AQ5="",AQ5="N/A",AQ5="Common Equity",AQ5="Builder Deposit / Equity"),0,N(AR5)) -> 50000000 | S5: 94400000 | T5: 92100000 | U5: 80133338 | V5: Senior Mortgage | W5: 50000000 | X5: 0 | Y5: =IF(OR(V5="",V5="N/A",V5="Common Equity",V5="Builder Deposit / Equity",N($R5)=0),"N/A",SUM($W5)/$R5*100) -> 100 | Z5: =IF(OR(V5="",V5="N/A",V5="Common Equity",V5="Builder Deposit / Equity",N($R5)=0),"N/A",SUM($W5)/$R5*100) -> 100 | AA5: =IF(OR(V5="",V5="N/A",N($T5)=0),"N/A",SUM($W5)/$T5*100) -> 54.288817 | AB5: N/A | AC5: Common Equity | AD5: =T5-W5 -> 42100000 | AE5: =IF(OR(AC5="",AC5="N/A"),"N/A",Y5) -> 100 | AF5: =IF(OR(AC5="",AC5="N/A",AC5="Common Equity",AC5="Builder Deposit / Equity",N($R5)=0),"N/A",SUM($W5,$AD5)/$R5*100) -> N/A | AG5: =IF(OR(AC5="",AC5="N/A",AC5="Common Equity",AC5="Builder Deposit / Equity",N($R5)=0),"N/A",SUM($W5,$AD5)/$R5*100) -> N/A | AH5: =IF(OR(AC5="",AC5="N/A",N($T5)=0),"N/A",SUM($W5,$AD5)/$T5*100) -> 100 | AI5: N/A
A6: MaSH-3339577 | B6: 64734 | C6: Project Balboa | D6: A Note | E6: Syndication | F6: Mortgage | G6: CRE Loan Senior | H6: 41250000 | I6: 31995000 | J6: Multiple Funding | K6: 0.995 | L6: =I6*K6 -> 31835025 | M6: =L6+N6 -> 41090025 | N6: =H6-I6 -> 9255000 | O6: =W6 -> 41250000 | P6: N/A - Unlevered | Q6: N/A | R6: =IF(OR(V6="",V6="N/A",V6="Common Equity",V6="Builder Deposit / Equity"),0,N(W6))+IF(OR(AC6="",AC6="N/A",AC6="Common Equity",AC6="Builder Deposit / Equity"),0,N(AD6))+IF(OR(AJ6="",AJ6="N/A",AJ6="Common Equity",AJ6="Builder Deposit / Equity"),0,N(AK6))+IF(OR(AQ6="",AQ6="N/A",AQ6="Common Equity",AQ6="Builder Deposit / Equity"),0,N(AR6)) -> 55000000 | S6: 86500000 | T6: 105800000 | U6: 67005112 | V6: Senior Mortgage | W6: 41250000 | X6: 0 | Y6: =IF(OR(V6="",V6="N/A",V6="Common Equity",V6="Builder Deposit / Equity",N($R6)=0),"N/A",SUM($W6)/$R6*100) -> 75 | Z6: =IF(OR(V6="",V6="N/A",V6="Common Equity",V6="Builder Deposit / Equity",N($R6)=0),"N/A",SUM($W6)/$R6*100) -> 75 | AA6: =IF(OR(V6="",V6="N/A",N($T6)=0),"N/A",SUM($W6)/$T6*100) -> 38.988658 | AB6: 0.035 | AC6: B-Note | AD6: 13750000 | AE6: =IF(OR(AC6="",AC6="N/A"),"N/A",Y6) -> 75 | AF6: =IF(OR(AC6="",AC6="N/A",AC6="Common Equity",AC6="Builder Deposit / Equity",N($R6)=0),"N/A",SUM($W6,$AD6)/$R6*100) -> 100 | AG6: =IF(OR(AC6="",AC6="N/A",AC6="Common Equity",AC6="Builder Deposit / Equity",N($R6)=0),"N/A",SUM($W6,$AD6)/$R6*100) -> 100 | AH6: =IF(OR(AC6="",AC6="N/A",N($T6)=0),"N/A",SUM($W6,$AD6)/$T6*100) -> 51.984877 | AI6: N/A | AJ6: Common Equity | AK6: =T6-W6-AD6 -> 50800000 | AL6: =IF(OR(AJ6="",AJ6="N/A"),"N/A",AF6) -> 100 | AM6: =IF(OR(AJ6="",AJ6="N/A",AJ6="Common Equity",AJ6="Builder Deposit / Equity",N($R6)=0),"N/A",SUM($W6,$AD6,$AK6)/$R6*100) -> N/A | AN6: =IF(OR(AJ6="",AJ6="N/A",AJ6="Common Equity",AJ6="Builder Deposit / Equity",N($R6)=0),"N/A",SUM($W6,$AD6,$AK6)/$R6*100) -> N/A | AO6: =IF(OR(AJ6="",AJ6="N/A",N($T6)=0),"N/A",SUM($W6,$AD6,$AK6)/$T6*100) -> 100 | AP6: N/A
A7: MaSH-3534532 | B7: 102039 | C7: Project Cubic | D7: A Note | E7: Syndication | F7: Mortgage | G7: CRE Loan Senior | H7: 50100000 | I7: 50100000 | J7: Single Funding | K7: 0.9465 | L7: =I7*K7 -> 47419650 | M7: =L7+N7 -> 47419650 | N7: =H7-I7 -> 0 | O7: =W7 -> 1435000000 | P7: N/A - Unlevered | Q7: N/A | R7: =IF(OR(V7="",V7="N/A",V7="Common Equity",V7="Builder Deposit / Equity"),0,N(W7))+IF(OR(AC7="",AC7="N/A",AC7="Common Equity",AC7="Builder Deposit / Equity"),0,N(AD7))+IF(OR(AJ7="",AJ7="N/A",AJ7="Common Equity",AJ7="Builder Deposit / Equity"),0,N(AK7))+IF(OR(AQ7="",AQ7="N/A",AQ7="Common Equity",AQ7="Builder Deposit / Equity"),0,N(AR7)) -> 1850000000 | S7: 1850000000 | T7: 2480000000 | U7: 1432900000 | V7: Senior Mortgage | W7: 1435000000 | X7: 0 | Y7: =IF(OR(V7="",V7="N/A",V7="Common Equity",V7="Builder Deposit / Equity",N($R7)=0),"N/A",SUM($W7)/$R7*100) -> 77.567568 | Z7: =IF(OR(V7="",V7="N/A",V7="Common Equity",V7="Builder Deposit / Equity",N($R7)=0),"N/A",SUM($W7)/$R7*100) -> 77.567568 | AA7: =IF(OR(V7="",V7="N/A",N($T7)=0),"N/A",SUM($W7)/$T7*100) -> 57.862903 | AB7: 0.0169809 | AC7: Mezzanine | AD7: 415000000 | AE7: =IF(OR(AC7="",AC7="N/A"),"N/A",Y7) -> 77.567568 | AF7: =IF(OR(AC7="",AC7="N/A",AC7="Common Equity",AC7="Builder Deposit / Equity",N($R7)=0),"N/A",SUM($W7,$AD7)/$R7*100) -> 100 | AG7: =IF(OR(AC7="",AC7="N/A",AC7="Common Equity",AC7="Builder Deposit / Equity",N($R7)=0),"N/A",SUM($W7,$AD7)/$R7*100) -> 100 | AH7: =IF(OR(AC7="",AC7="N/A",N($T7)=0),"N/A",SUM($W7,$AD7)/$T7*100) -> 74.596774 | AI7: 0.0505 | AJ7: Common Equity | AK7: =T7-W7-AD7 -> 630000000 | AL7: =IF(OR(AJ7="",AJ7="N/A"),"N/A",AF7) -> 100 | AM7: =IF(OR(AJ7="",AJ7="N/A",AJ7="Common Equity",AJ7="Builder Deposit / Equity",N($R7)=0),"N/A",SUM($W7,$AD7,$AK7)/$R7*100) -> N/A | AN7: =IF(OR(AJ7="",AJ7="N/A",AJ7="Common Equity",AJ7="Builder Deposit / Equity",N($R7)=0),"N/A",SUM($W7,$AD7,$AK7)/$R7*100) -> N/A | AO7: =IF(OR(AJ7="",AJ7="N/A",N($T7)=0),"N/A",SUM($W7,$AD7,$AK7)/$T7*100) -> 100 | AP7: N/A
A8: MaSH-3337170 | B8: 64681 | C8: Project Eyas | D8: A Note | E8: Syndication | F8: Mortgage | G8: CRE Loan Senior | H8: 70700000 | I8: 67217966 | J8: Multiple Funding | K8: 0.9575 | L8: =I8*K8 -> 64361202 | M8: =L8+N8 -> 67843236 | N8: =H8-I8 -> 3482034.2 | O8: =W8 -> 2.2070177e+08 | P8: N/A - Unlevered | Q8: N/A | R8: =IF(OR(V8="",V8="N/A",V8="Common Equity",V8="Builder Deposit / Equity"),0,N(W8))+IF(OR(AC8="",AC8="N/A",AC8="Common Equity",AC8="Builder Deposit / Equity"),0,N(AD8))+IF(OR(AJ8="",AJ8="N/A",AJ8="Common Equity",AJ8="Builder Deposit / Equity"),0,N(AK8))+IF(OR(AQ8="",AQ8="N/A",AQ8="Common Equity",AQ8="Builder Deposit / Equity"),0,N(AR8)) -> 2.75729e+08 | S8: 368328856 | T8: 353800000 | U8: 310343107 | V8: Senior Mortgage | W8: 2.2070177e+08 | X8: 0 | Y8: =IF(OR(V8="",V8="N/A",V8="Common Equity",V8="Builder Deposit / Equity",N($R8)=0),"N/A",SUM($W8)/$R8*100) -> 80.043002 | Z8: =IF(OR(V8="",V8="N/A",V8="Common Equity",V8="Builder Deposit / Equity",N($R8)=0),"N/A",SUM($W8)/$R8*100) -> 80.043002 | AA8: =IF(OR(V8="",V8="N/A",N($T8)=0),"N/A",SUM($W8)/$T8*100) -> 62.380376 | AB8: 0.0228 | AC8: Mezzanine | AD8: 55027230 | AE8: =IF(OR(AC8="",AC8="N/A"),"N/A",Y8) -> 80.043002 | AF8: =IF(OR(AC8="",AC8="N/A",AC8="Common Equity",AC8="Builder Deposit / Equity",N($R8)=0),"N/A",SUM($W8,$AD8)/$R8*100) -> 100 | AG8: =IF(OR(AC8="",AC8="N/A",AC8="Common Equity",AC8="Builder Deposit / Equity",N($R8)=0),"N/A",SUM($W8,$AD8)/$R8*100) -> 100 | AH8: =IF(OR(AC8="",AC8="N/A",N($T8)=0),"N/A",SUM($W8,$AD8)/$T8*100) -> 77.933578 | AI8: 0.0575 | AJ8: Common Equity | AK8: =T8-W8-AD8 -> 78071000 | AL8: =IF(OR(AJ8="",AJ8="N/A"),"N/A",AF8) -> 100 | AM8: =IF(OR(AJ8="",AJ8="N/A",AJ8="Common Equity",AJ8="Builder Deposit / Equity",N($R8)=0),"N/A",SUM($W8,$AD8,$AK8)/$R8*100) -> N/A | AN8: =IF(OR(AJ8="",AJ8="N/A",AJ8="Common Equity",AJ8="Builder Deposit / Equity",N($R8)=0),"N/A",SUM($W8,$AD8,$AK8)/$R8*100) -> N/A | AO8: =IF(OR(AJ8="",AJ8="N/A",N($T8)=0),"N/A",SUM($W8,$AD8,$AK8)/$T8*100) -> 100 | AP8: N/A
A9: MaSH-3340378 | B9: 64777 | C9: Project Stripe | D9: A Note | E9: Syndication | F9: Mortgage | G9: CRE Loan Senior | H9: 96000000 | I9: 96000000 | J9: Single Funding | K9: 0.9225 | L9: =I9*K9 -> 88560000 | M9: =L9+N9 -> 88560000 | N9: =H9-I9 -> 0 | O9: =W9 -> 550600000 | P9: N/A - Unlevered | Q9: N/A | R9: =IF(OR(V9="",V9="N/A",V9="Common Equity",V9="Builder Deposit / Equity"),0,N(W9))+IF(OR(AC9="",AC9="N/A",AC9="Common Equity",AC9="Builder Deposit / Equity"),0,N(AD9))+IF(OR(AJ9="",AJ9="N/A",AJ9="Common Equity",AJ9="Builder Deposit / Equity"),0,N(AK9))+IF(OR(AQ9="",AQ9="N/A",AQ9="Common Equity",AQ9="Builder Deposit / Equity"),0,N(AR9)) -> 696000000 | S9: 870450000 | T9: 825300000 | U9: 688775190 | V9: Senior Mortgage | W9: 550600000 | X9: 0 | Y9: =IF(OR(V9="",V9="N/A",V9="Common Equity",V9="Builder Deposit / Equity",N($R9)=0),"N/A",SUM($W9)/$R9*100) -> 79.109195 | Z9: =IF(OR(V9="",V9="N/A",V9="Common Equity",V9="Builder Deposit / Equity",N($R9)=0),"N/A",SUM($W9)/$R9*100) -> 79.109195 | AA9: =IF(OR(V9="",V9="N/A",N($T9)=0),"N/A",SUM($W9)/$T9*100) -> 66.715134 | AB9: 0.018 | AC9: Mezzanine | AD9: 145400000 | AE9: =IF(OR(AC9="",AC9="N/A"),"N/A",Y9) -> 79.109195 | AF9: =IF(OR(AC9="",AC9="N/A",AC9="Common Equity",AC9="Builder Deposit / Equity",N($R9)=0),"N/A",SUM($W9,$AD9)/$R9*100) -> 100 | AG9: =IF(OR(AC9="",AC9="N/A",AC9="Common Equity",AC9="Builder Deposit / Equity",N($R9)=0),"N/A",SUM($W9,$AD9)/$R9*100) -> 100 | AH9: =IF(OR(AC9="",AC9="N/A",N($T9)=0),"N/A",SUM($W9,$AD9)/$T9*100) -> 84.33297 | AI9: 0.0515 | AJ9: Common Equity | AK9: =T9-W9-AD9 -> 129300000 | AL9: =IF(OR(AJ9="",AJ9="N/A"),"N/A",AF9) -> 100 | AM9: =IF(OR(AJ9="",AJ9="N/A",AJ9="Common Equity",AJ9="Builder Deposit / Equity",N($R9)=0),"N/A",SUM($W9,$AD9,$AK9)/$R9*100) -> N/A | AN9: =IF(OR(AJ9="",AJ9="N/A",AJ9="Common Equity",AJ9="Builder Deposit / Equity",N($R9)=0),"N/A",SUM($W9,$AD9,$AK9)/$R9*100) -> N/A | AO9: =IF(OR(AJ9="",AJ9="N/A",N($T9)=0),"N/A",SUM($W9,$AD9,$AK9)/$T9*100) -> 100 | AP9: N/A
A10: MaSH-3687981 | B10: 255488 | C10: Project Bellevue | D10: A Note | E10: Syndication | F10: Mortgage | G10: CRE Loan Senior | H10: 40000000 | I10: 40000000 | J10: Single Funding | K10: 0.994 | L10: =I10*K10 -> 39760000 | M10: =L10+N10 -> 39760000 | N10: =H10-I10 -> 0 | O10: =W10 -> 156500000 | P10: N/A - Unlevered | Q10: N/A | R10: =IF(OR(V10="",V10="N/A",V10="Common Equity",V10="Builder Deposit / Equity"),0,N(W10))+IF(OR(AC10="",AC10="N/A",AC10="Common Equity",AC10="Builder Deposit / Equity"),0,N(AD10))+IF(OR(AJ10="",AJ10="N/A",AJ10="Common Equity",AJ10="Builder Deposit / Equity"),0,N(AK10))+IF(OR(AQ10="",AQ10="N/A",AQ10="Common Equity",AQ10="Builder Deposit / Equity"),0,N(AR10)) -> 168500000 | S10: 377585009 | T10: 269950000 | U10: 220400000 | V10: Senior Mortgage | W10: 156500000 | X10: 0 | Y10: =IF(OR(V10="",V10="N/A",V10="Common Equity",V10="Builder Deposit / Equity",N($R10)=0),"N/A",SUM($W10)/$R10*100) -> 92.878338 | Z10: =IF(OR(V10="",V10="N/A",V10="Common Equity",V10="Builder Deposit / Equity",N($R10)=0),"N/A",SUM($W10)/$R10*100) -> 92.878338 | AA10: =IF(OR(V10="",V10="N/A",N($T10)=0),"N/A",SUM($W10)/$T10*100) -> 57.973699 | AB10: 0.04 | AC10: Preferred Equity | AD10: 12000000 | AE10: =IF(OR(AC10="",AC10="N/A"),"N/A",Y10) -> 92.878338 | AF10: =IF(OR(AC10="",AC10="N/A",AC10="Common Equity",AC10="Builder Deposit / Equity",N($R10)=0),"N/A",SUM($W10,$AD10)/$R10*100) -> 100 | AG10: =IF(OR(AC10="",AC10="N/A",AC10="Common Equity",AC10="Builder Deposit / Equity",N($R10)=0),"N/A",SUM($W10,$AD10)/$R10*100) -> 100 | AH10: =IF(OR(AC10="",AC10="N/A",N($T10)=0),"N/A",SUM($W10,$AD10)/$T10*100) -> 62.418966 | AI10: N/A | AJ10: Common Equity | AK10: =T10-W10-AD10 -> 101450000 | AL10: =IF(OR(AJ10="",AJ10="N/A"),"N/A",AF10) -> 100 | AM10: =IF(OR(AJ10="",AJ10="N/A",AJ10="Common Equity",AJ10="Builder Deposit / Equity",N($R10)=0),"N/A",SUM($W10,$AD10,$AK10)/$R10*100) -> N/A | AN10: =IF(OR(AJ10="",AJ10="N/A",AJ10="Common Equity",AJ10="Builder Deposit / Equity",N($R10)=0),"N/A",SUM($W10,$AD10,$AK10)/$R10*100) -> N/A | AO10: =IF(OR(AJ10="",AJ10="N/A",N($T10)=0),"N/A",SUM($W10,$AD10,$AK10)/$T10*100) -> 100 | AP10: N/A
A11: MaSH-3773167 | B11: 340674 | C11: Project Fayetteville 2-Pack | D11: A Note | E11: Syndication | F11: Mortgage | G11: CRE Loan Senior | H11: 40000000 | I11: 40000000 | J11: Single Funding | K11: 1 | L11: =I11*K11 -> 40000000 | M11: =L11+N11 -> 40000000 | N11: =H11-I11 -> 0 | O11: =W11 -> 40000000 | P11: N/A - Unlevered | Q11: N/A | R11: =IF(OR(V11="",V11="N/A",V11="Common Equity",V11="Builder Deposit / Equity"),0,N(W11))+IF(OR(AC11="",AC11="N/A",AC11="Common Equity",AC11="Builder Deposit / Equity"),0,N(AD11))+IF(OR(AJ11="",AJ11="N/A",AJ11="Common Equity",AJ11="Builder Deposit / Equity"),0,N(AK11))+IF(OR(AQ11="",AQ11="N/A",AQ11="Common Equity",AQ11="Builder Deposit / Equity"),0,N(AR11)) -> 40000000 | S11: 40000000 | T11: 57300000 | U11: 54100000 | V11: Senior Mortgage | W11: 40000000 | X11: 0 | Y11: =IF(OR(V11="",V11="N/A",V11="Common Equity",V11="Builder Deposit / Equity",N($R11)=0),"N/A",SUM($W11)/$R11*100) -> 100 | Z11: =IF(OR(V11="",V11="N/A",V11="Common Equity",V11="Builder Deposit / Equity",N($R11)=0),"N/A",SUM($W11)/$R11*100) -> 100 | AA11: =IF(OR(V11="",V11="N/A",N($T11)=0),"N/A",SUM($W11)/$T11*100) -> 69.808028 | AB11: 0.0251 | AC11: Common Equity | AD11: =T11-W11 -> 17300000 | AE11: =IF(OR(AC11="",AC11="N/A"),"N/A",Y11) -> 100 | AF11: =IF(OR(AC11="",AC11="N/A",AC11="Common Equity",AC11="Builder Deposit / Equity",N($R11)=0),"N/A",SUM($W11,$AD11)/$R11*100) -> N/A | AG11: =IF(OR(AC11="",AC11="N/A",AC11="Common Equity",AC11="Builder Deposit / Equity",N($R11)=0),"N/A",SUM($W11,$AD11)/$R11*100) -> N/A | AH11: =IF(OR(AC11="",AC11="N/A",N($T11)=0),"N/A",SUM($W11,$AD11)/$T11*100) -> 100 | AI11: N/A
A12: MaSH-3774814 | B12: 342321 | C12: Mosaic Apartments | D12: A Note | E12: Syndication | F12: Mortgage | G12: CRE Loan Senior | H12: 48400000 | I12: 48400000 | J12: Single Funding | K12: 1 | L12: =I12*K12 -> 48400000 | M12: =L12+N12 -> 48400000 | N12: =H12-I12 -> 0 | O12: =W12 -> 48400000 | P12: N/A - Unlevered | Q12: N/A | R12: =IF(OR(V12="",V12="N/A",V12="Common Equity",V12="Builder Deposit / Equity"),0,N(W12))+IF(OR(AC12="",AC12="N/A",AC12="Common Equity",AC12="Builder Deposit / Equity"),0,N(AD12))+IF(OR(AJ12="",AJ12="N/A",AJ12="Common Equity",AJ12="Builder Deposit / Equity"),0,N(AK12))+IF(OR(AQ12="",AQ12="N/A",AQ12="Common Equity",AQ12="Builder Deposit / Equity"),0,N(AR12)) -> 48400000 | S12: 48400000 | T12: 78800000 | U12: 68000000 | V12: Senior Mortgage | W12: 48400000 | X12: 0 | Y12: =IF(OR(V12="",V12="N/A",V12="Common Equity",V12="Builder Deposit / Equity",N($R12)=0),"N/A",SUM($W12)/$R12*100) -> 100 | Z12: =IF(OR(V12="",V12="N/A",V12="Common Equity",V12="Builder Deposit / Equity",N($R12)=0),"N/A",SUM($W12)/$R12*100) -> 100 | AA12: =IF(OR(V12="",V12="N/A",N($T12)=0),"N/A",SUM($W12)/$T12*100) -> 61.42132 | AB12: 0.0251 | AC12: Common Equity | AD12: =T12-W12 -> 30400000 | AE12: =IF(OR(AC12="",AC12="N/A"),"N/A",Y12) -> 100 | AF12: =IF(OR(AC12="",AC12="N/A",AC12="Common Equity",AC12="Builder Deposit / Equity",N($R12)=0),"N/A",SUM($W12,$AD12)/$R12*100) -> N/A | AG12: =IF(OR(AC12="",AC12="N/A",AC12="Common Equity",AC12="Builder Deposit / Equity",N($R12)=0),"N/A",SUM($W12,$AD12)/$R12*100) -> N/A | AH12: =IF(OR(AC12="",AC12="N/A",N($T12)=0),"N/A",SUM($W12,$AD12)/$T12*100) -> 100 | AI12: N/A
A13: MaSH-3774820 | B13: 342327 | C13: Project Arista | D13: A Note | E13: Syndication | F13: Mortgage | G13: CRE Loan Senior | H13: 48000000 | I13: 48000000 | J13: Single Funding | K13: 1 | L13: =I13*K13 -> 48000000 | M13: =L13+N13 -> 48000000 | N13: =H13-I13 -> 0 | O13: =W13 -> 48000000 | P13: N/A - Unlevered | Q13: N/A | R13: =IF(OR(V13="",V13="N/A",V13="Common Equity",V13="Builder Deposit / Equity"),0,N(W13))+IF(OR(AC13="",AC13="N/A",AC13="Common Equity",AC13="Builder Deposit / Equity"),0,N(AD13))+IF(OR(AJ13="",AJ13="N/A",AJ13="Common Equity",AJ13="Builder Deposit / Equity"),0,N(AK13))+IF(OR(AQ13="",AQ13="N/A",AQ13="Common Equity",AQ13="Builder Deposit / Equity"),0,N(AR13)) -> 52000000 | S13: 52000000 | T13: 78910000 | U13: 66000000 | V13: Senior Mortgage | W13: 48000000 | X13: 0 | Y13: =IF(OR(V13="",V13="N/A",V13="Common Equity",V13="Builder Deposit / Equity",N($R13)=0),"N/A",SUM($W13)/$R13*100) -> 92.307692 | Z13: =IF(OR(V13="",V13="N/A",V13="Common Equity",V13="Builder Deposit / Equity",N($R13)=0),"N/A",SUM($W13)/$R13*100) -> 92.307692 | AA13: =IF(OR(V13="",V13="N/A",N($T13)=0),"N/A",SUM($W13)/$T13*100) -> 60.828792 | AB13: 0.0235 | AC13: B-Note | AD13: 4000000 | AE13: =IF(OR(AC13="",AC13="N/A"),"N/A",Y13) -> 92.307692 | AF13: =IF(OR(AC13="",AC13="N/A",AC13="Common Equity",AC13="Builder Deposit / Equity",N($R13)=0),"N/A",SUM($W13,$AD13)/$R13*100) -> 100 | AG13: =IF(OR(AC13="",AC13="N/A",AC13="Common Equity",AC13="Builder Deposit / Equity",N($R13)=0),"N/A",SUM($W13,$AD13)/$R13*100) -> 100 | AH13: =IF(OR(AC13="",AC13="N/A",N($T13)=0),"N/A",SUM($W13,$AD13)/$T13*100) -> 65.897858 | AI13: 0.12 | AJ13: Common Equity | AK13: =T13-W13-AD13 -> 26910000 | AL13: =IF(OR(AJ13="",AJ13="N/A"),"N/A",AF13) -> 100 | AM13: =IF(OR(AJ13="",AJ13="N/A",AJ13="Common Equity",AJ13="Builder Deposit / Equity",N($R13)=0),"N/A",SUM($W13,$AD13,$AK13)/$R13*100) -> N/A | AN13: =IF(OR(AJ13="",AJ13="N/A",AJ13="Common Equity",AJ13="Builder Deposit / Equity",N($R13)=0),"N/A",SUM($W13,$AD13,$AK13)/$R13*100) -> N/A | AO13: =IF(OR(AJ13="",AJ13="N/A",N($T13)=0),"N/A",SUM($W13,$AD13,$AK13)/$T13*100) -> 100 | AP13: N/A
A14: MaSH-3700986 | B14: 268493 | C14: Project Grand Bay Hotel San Francisco | D14: A Note | E14: Origination | F14: Mortgage | G14: CRE Loan Senior | H14: 69500000 | I14: 59500000 | J14: Multiple Funding | K14: 1 | L14: =I14*K14 -> 59500000 | M14: =L14+N14 -> 69500000 | N14: =H14-I14 -> 10000000 | O14: =W14+AD14 -> 69500000 | P14: Repo/Warehouse | Q14: Santander | R14: =IF(OR(V14="",V14="N/A",V14="Common Equity",V14="Builder Deposit / Equity"),0,N(W14))+IF(OR(AC14="",AC14="N/A",AC14="Common Equity",AC14="Builder Deposit / Equity"),0,N(AD14))+IF(OR(AJ14="",AJ14="N/A",AJ14="Common Equity",AJ14="Builder Deposit / Equity"),0,N(AK14))+IF(OR(AQ14="",AQ14="N/A",AQ14="Common Equity",AQ14="Builder Deposit / Equity"),0,N(AR14)) -> 91000000 | S14: 97000000 | T14: 1.9688385e+08 | U14: 122500000 | V14: Repo/Warehouse | W14: =41650000+7000000 -> 48650000 | X14: 0 | Y14: =IF(OR(V14="",V14="N/A",V14="Common Equity",V14="Builder Deposit / Equity",N($R14)=0),"N/A",SUM($W14)/$R14*100) -> 53.461538 | Z14: =IF(OR(V14="",V14="N/A",V14="Common Equity",V14="Builder Deposit / Equity",N($R14)=0),"N/A",SUM($W14)/$R14*100) -> 53.461538 | AA14: =IF(OR(V14="",V14="N/A",N($T14)=0),"N/A",SUM($W14)/$T14*100) -> 24.71 | AB14: 0.0175 | AC14: Whole Loan (SSP Retained) | AD14: =H14-W14 -> 20850000 | AE14: =IF(OR(AC14="",AC14="N/A"),"N/A",Y14) -> 53.461538 | AF14: =IF(OR(AC14="",AC14="N/A",AC14="Common Equity",AC14="Builder Deposit / Equity",N($R14)=0),"N/A",SUM($W14,$AD14)/$R14*100) -> 76.373626 | AG14: =IF(OR(AC14="",AC14="N/A",AC14="Common Equity",AC14="Builder Deposit / Equity",N($R14)=0),"N/A",SUM($W14,$AD14)/$R14*100) -> 76.373626 | AH14: =IF(OR(AC14="",AC14="N/A",N($T14)=0),"N/A",SUM($W14,$AD14)/$T14*100) -> 35.3 | AI14: 0.0515 | AJ14: Preferred Equity | AK14: =12500000+9000000 -> 21500000 | AL14: =IF(OR(AJ14="",AJ14="N/A"),"N/A",AF14) -> 76.373626 | AM14: =IF(OR(AJ14="",AJ14="N/A",AJ14="Common Equity",AJ14="Builder Deposit / Equity",N($R14)=0),"N/A",SUM($W14,$AD14,$AK14)/$R14*100) -> 100 | AN14: =IF(OR(AJ14="",AJ14="N/A",AJ14="Common Equity",AJ14="Builder Deposit / Equity",N($R14)=0),"N/A",SUM($W14,$AD14,$AK14)/$R14*100) -> 100 | AO14: =IF(OR(AJ14="",AJ14="N/A",N($T14)=0),"N/A",SUM($W14,$AD14,$AK14)/$T14*100) -> 46.220144 | AP14: 0.08 | AQ14: Common Equity | AR14: =T14-SUM(W14,AD14,AK14) -> 1.0588385e+08 | AS14: =IF(OR(AQ14="",AQ14="N/A"),"N/A",AM14) -> 100 | AT14: =IF(OR(AQ14="",AQ14="N/A",AQ14="Common Equity",AQ14="Builder Deposit / Equity",N($R14)=0),"N/A",SUM($W14,$AD14,$AK14,$AR14)/$R14*100) -> N/A | AU14: =IF(OR(AQ14="",AQ14="N/A",AQ14="Common Equity",AQ14="Builder Deposit / Equity",N($R14)=0),"N/A",SUM($W14,$AD14,$AK14,$AR14)/$R14*100) -> N/A | AV14: =IF(OR(AQ14="",AQ14="N/A",N($T14)=0),"N/A",SUM($W14,$AD14,$AK14,$AR14)/$T14*100) -> 100 | AW14: N/A
A15: MaSH-3776991 | B15: 344498 | C15: Crystal Springs Resort | D15: A Note | E15: Origination | F15: Mortgage | G15: CRE Loan Senior | H15: 131000000 | I15: =H15 -> 131000000 | J15: Single Funding | K15: 0.9925 | L15: =I15*K15 -> 130017500 | M15: =L15+N15 -> 130017500 | N15: =H15-I15 -> 0 | O15: =W15 -> 131000000 | P15: N/A - Unlevered | Q15: N/A | R15: =IF(OR(V15="",V15="N/A",V15="Common Equity",V15="Builder Deposit / Equity"),0,N(W15))+IF(OR(AC15="",AC15="N/A",AC15="Common Equity",AC15="Builder Deposit / Equity"),0,N(AD15))+IF(OR(AJ15="",AJ15="N/A",AJ15="Common Equity",AJ15="Builder Deposit / Equity"),0,N(AK15))+IF(OR(AQ15="",AQ15="N/A",AQ15="Common Equity",AQ15="Builder Deposit / Equity"),0,N(AR15)) -> 154000000 | S15: 268000000 | T15: 232000000 | U15: 204950000 | V15: Senior Mortgage | W15: 131000000 | X15: 0 | Y15: =IF(OR(V15="",V15="N/A",V15="Common Equity",V15="Builder Deposit / Equity",N($R15)=0),"N/A",SUM($W15)/$R15*100) -> 85.064935 | Z15: =IF(OR(V15="",V15="N/A",V15="Common Equity",V15="Builder Deposit / Equity",N($R15)=0),"N/A",SUM($W15)/$R15*100) -> 85.064935 | AA15: =IF(OR(V15="",V15="N/A",N($T15)=0),"N/A",SUM($W15)/$T15*100) -> 56.465517 | AB15: 0.024 | AC15: Mezzanine | AD15: 23000000 | AE15: =IF(OR(AC15="",AC15="N/A"),"N/A",Y15) -> 85.064935 | AF15: =IF(OR(AC15="",AC15="N/A",AC15="Common Equity",AC15="Builder Deposit / Equity",N($R15)=0),"N/A",SUM($W15,$AD15)/$R15*100) -> 100 | AG15: =IF(OR(AC15="",AC15="N/A",AC15="Common Equity",AC15="Builder Deposit / Equity",N($R15)=0),"N/A",SUM($W15,$AD15)/$R15*100) -> 100 | AH15: =IF(OR(AC15="",AC15="N/A",N($T15)=0),"N/A",SUM($W15,$AD15)/$T15*100) -> 66.37931 | AI15: 0.074 | AJ15: Common Equity | AK15: =T15-W15-AD15 -> 78000000 | AL15: =IF(OR(AJ15="",AJ15="N/A"),"N/A",AF15) -> 100 | AM15: =IF(OR(AJ15="",AJ15="N/A",AJ15="Common Equity",AJ15="Builder Deposit / Equity",N($R15)=0),"N/A",SUM($W15,$AD15,$AK15)/$R15*100) -> N/A | AN15: =IF(OR(AJ15="",AJ15="N/A",AJ15="Common Equity",AJ15="Builder Deposit / Equity",N($R15)=0),"N/A",SUM($W15,$AD15,$AK15)/$R15*100) -> N/A | AO15: =IF(OR(AJ15="",AJ15="N/A",N($T15)=0),"N/A",SUM($W15,$AD15,$AK15)/$T15*100) -> 100 | AP15: N/A
A16: MaSH-3776993 | B16: 344500 | C16: Alpine Village | D16: A Note | E16: Origination | F16: Mortgage | G16: CRE Loan Senior | H16: 54250000 | I16: =H16 -> 54250000 | J16: Single Funding | K16: 1 | L16: =I16*K16 -> 54250000 | M16: =L16+N16 -> 54250000 | N16: =H16-I16 -> 0 | O16: =W16 -> 54250000 | P16: N/A - Unlevered | Q16: N/A | R16: =IF(OR(V16="",V16="N/A",V16="Common Equity",V16="Builder Deposit / Equity"),0,N(W16))+IF(OR(AC16="",AC16="N/A",AC16="Common Equity",AC16="Builder Deposit / Equity"),0,N(AD16))+IF(OR(AJ16="",AJ16="N/A",AJ16="Common Equity",AJ16="Builder Deposit / Equity"),0,N(AK16))+IF(OR(AQ16="",AQ16="N/A",AQ16="Common Equity",AQ16="Builder Deposit / Equity"),0,N(AR16)) -> 69000000 | S16: 71020944 | T16: 83000000 | U16: 76900000 | V16: Senior Mortgage | W16: 54250000 | X16: 0 | Y16: =IF(OR(V16="",V16="N/A",V16="Common Equity",V16="Builder Deposit / Equity",N($R16)=0),"N/A",SUM($W16)/$R16*100) -> 78.623188 | Z16: =IF(OR(V16="",V16="N/A",V16="Common Equity",V16="Builder Deposit / Equity",N($R16)=0),"N/A",SUM($W16)/$R16*100) -> 78.623188 | AA16: =IF(OR(V16="",V16="N/A",N($T16)=0),"N/A",SUM($W16)/$T16*100) -> 65.361446 | AB16: 0.0235 | AC16: Mezzanine | AD16: 14750000 | AE16: =IF(OR(AC16="",AC16="N/A"),"N/A",Y16) -> 78.623188 | AF16: =IF(OR(AC16="",AC16="N/A",AC16="Common Equity",AC16="Builder Deposit / Equity",N($R16)=0),"N/A",SUM($W16,$AD16)/$R16*100) -> 100 | AG16: =IF(OR(AC16="",AC16="N/A",AC16="Common Equity",AC16="Builder Deposit / Equity",N($R16)=0),"N/A",SUM($W16,$AD16)/$R16*100) -> 100 | AH16: =IF(OR(AC16="",AC16="N/A",N($T16)=0),"N/A",SUM($W16,$AD16)/$T16*100) -> 83.13253 | AI16: 0.1125 | AJ16: Common Equity | AK16: =T16-W16-AD16 -> 14000000 | AL16: =IF(OR(AJ16="",AJ16="N/A"),"N/A",AF16) -> 100 | AM16: =IF(OR(AJ16="",AJ16="N/A",AJ16="Common Equity",AJ16="Builder Deposit / Equity",N($R16)=0),"N/A",SUM($W16,$AD16,$AK16)/$R16*100) -> N/A | AN16: =IF(OR(AJ16="",AJ16="N/A",AJ16="Common Equity",AJ16="Builder Deposit / Equity",N($R16)=0),"N/A",SUM($W16,$AD16,$AK16)/$R16*100) -> N/A | AO16: =IF(OR(AJ16="",AJ16="N/A",N($T16)=0),"N/A",SUM($W16,$AD16,$AK16)/$T16*100) -> 100 | AP16: N/A
A17: MaSH-3773094 | B17: 340601 | C17: Project Highland Portfolio | D17: Mezz | E17: Mezzanine | F17: Mezzanine Loan | G17: CRE Loan Junior | H17: 80000000 | I17: 80000000 | J17: Single Funding | K17: 0.98485302 | L17: =I17*K17 -> 78788241 | M17: =L17+N17 -> 78788241 | N17: =H17-I17 -> 0 | O17: =W17+H17 -> 525000000 | P17: N/A - Unlevered | Q17: N/A | R17: =IF(OR(V17="",V17="N/A",V17="Common Equity",V17="Builder Deposit / Equity"),0,N(W17))+IF(OR(AC17="",AC17="N/A",AC17="Common Equity",AC17="Builder Deposit / Equity"),0,N(AD17))+IF(OR(AJ17="",AJ17="N/A",AJ17="Common Equity",AJ17="Builder Deposit / Equity"),0,N(AK17))+IF(OR(AQ17="",AQ17="N/A",AQ17="Common Equity",AQ17="Builder Deposit / Equity"),0,N(AR17)) -> 525000000 | S17: 533751241 | T17: 807692000 | U17: 616000000 | V17: Senior Mortgage | W17: 445000000 | X17: 0 | Y17: =IF(OR(V17="",V17="N/A",V17="Common Equity",V17="Builder Deposit / Equity",N($R17)=0),"N/A",SUM($W17)/$R17*100) -> 84.761905 | Z17: =IF(OR(V17="",V17="N/A",V17="Common Equity",V17="Builder Deposit / Equity",N($R17)=0),"N/A",SUM($W17)/$R17*100) -> 84.761905 | AA17: =IF(OR(V17="",V17="N/A",N($T17)=0),"N/A",SUM($W17)/$T17*100) -> 55.095259 | AB17: 0.04 | AC17: Mezzanine | AD17: 80000000 | AE17: =IF(OR(AC17="",AC17="N/A"),"N/A",Y17) -> 84.761905 | AF17: =IF(OR(AC17="",AC17="N/A",AC17="Common Equity",AC17="Builder Deposit / Equity",N($R17)=0),"N/A",SUM($W17,$AD17)/$R17*100) -> 100 | AG17: =IF(OR(AC17="",AC17="N/A",AC17="Common Equity",AC17="Builder Deposit / Equity",N($R17)=0),"N/A",SUM($W17,$AD17)/$R17*100) -> 100 | AH17: =IF(OR(AC17="",AC17="N/A",N($T17)=0),"N/A",SUM($W17,$AD17)/$T17*100) -> 65.000025 | AI17: 0.125 | AJ17: Common Equity | AK17: =T17-W17-AD17 -> 282692000 | AL17: =IF(OR(AJ17="",AJ17="N/A"),"N/A",AF17) -> 100 | AM17: =IF(OR(AJ17="",AJ17="N/A",AJ17="Common Equity",AJ17="Builder Deposit / Equity",N($R17)=0),"N/A",SUM($W17,$AD17,$AK17)/$R17*100) -> N/A | AN17: =IF(OR(AJ17="",AJ17="N/A",AJ17="Common Equity",AJ17="Builder Deposit / Equity",N($R17)=0),"N/A",SUM($W17,$AD17,$AK17)/$R17*100) -> N/A | AO17: =IF(OR(AJ17="",AJ17="N/A",N($T17)=0),"N/A",SUM($W17,$AD17,$AK17)/$T17*100) -> 100 | AP17: N/A
A18: MaSH-3780342 | B18: 347849 | C18: Project Prime Care Portfolio Senior Financing | D18: A Note | E18: Syndication | F18: Mortgage | G18: CRE Loan Senior | H18: 55000000 | I18: 55000000 | J18: Single Funding | K18: 0.99 | L18: =I18*K18 -> 54450000 | M18: =L18+N18 -> 54450000 | N18: =H18-I18 -> 0 | O18: =W18 -> 205000000 | P18: N/A - Unlevered | Q18: N/A | R18: =IF(OR(V18="",V18="N/A",V18="Common Equity",V18="Builder Deposit / Equity"),0,N(W18))+IF(OR(AC18="",AC18="N/A",AC18="Common Equity",AC18="Builder Deposit / Equity"),0,N(AD18))+IF(OR(AJ18="",AJ18="N/A",AJ18="Common Equity",AJ18="Builder Deposit / Equity"),0,N(AK18))+IF(OR(AQ18="",AQ18="N/A",AQ18="Common Equity",AQ18="Builder Deposit / Equity"),0,N(AR18)) -> 300000000 | S18: 300000000 | T18: 355000000 | U18: 327000000 | V18: Senior Mortgage | W18: 205000000 | X18: 0 | Y18: =IF(OR(V18="",V18="N/A",V18="Common Equity",V18="Builder Deposit / Equity",N($R18)=0),"N/A",SUM($W18)/$R18*100) -> 68.333333 | Z18: =IF(OR(V18="",V18="N/A",V18="Common Equity",V18="Builder Deposit / Equity",N($R18)=0),"N/A",SUM($W18)/$R18*100) -> 68.333333 | AA18: =IF(OR(V18="",V18="N/A",N($T18)=0),"N/A",SUM($W18)/$T18*100) -> 57.746479 | AB18: 0.025 | AC18: Mezzanine | AD18: 95000000 | AE18: =IF(OR(AC18="",AC18="N/A"),"N/A",Y18) -> 68.333333 | AF18: =IF(OR(AC18="",AC18="N/A",AC18="Common Equity",AC18="Builder Deposit / Equity",N($R18)=0),"N/A",SUM($W18,$AD18)/$R18*100) -> 100 | AG18: =IF(OR(AC18="",AC18="N/A",AC18="Common Equity",AC18="Builder Deposit / Equity",N($R18)=0),"N/A",SUM($W18,$AD18)/$R18*100) -> 100 | AH18: =IF(OR(AC18="",AC18="N/A",N($T18)=0),"N/A",SUM($W18,$AD18)/$T18*100) -> 84.507042 | AI18: 0.07 | AJ18: Common Equity | AK18: =T18-W18-AD18 -> 55000000 | AL18: =IF(OR(AJ18="",AJ18="N/A"),"N/A",AF18) -> 100 | AM18: =IF(OR(AJ18="",AJ18="N/A",AJ18="Common Equity",AJ18="Builder Deposit / Equity",N($R18)=0),"N/A",SUM($W18,$AD18,$AK18)/$R18*100) -> N/A | AN18: =IF(OR(AJ18="",AJ18="N/A",AJ18="Common Equity",AJ18="Builder Deposit / Equity",N($R18)=0),"N/A",SUM($W18,$AD18,$AK18)/$R18*100) -> N/A | AO18: =IF(OR(AJ18="",AJ18="N/A",N($T18)=0),"N/A",SUM($W18,$AD18,$AK18)/$T18*100) -> 100 | AP18: N/A
A19: MaSH-3768501 | B19: 336008 | C19: Project Scarlet Bay | D19: Preferred Equity | E19: Preferred Equity | F19: Preferred Equity | G19: CRE Loan Junior | H19: 38651985 | I19: 0 | J19: Multiple Funding | K19: 1 | L19: =I19*K19 -> 0 | M19: =L19+N19 -> 38651985 | N19: =H19-I19 -> 38651985 | O19: =W19+H19 -> 172586435 | P19: Structural | Q19: N/A | R19: =IF(OR(V19="",V19="N/A",V19="Common Equity",V19="Builder Deposit / Equity"),0,N(W19))+IF(OR(AC19="",AC19="N/A",AC19="Common Equity",AC19="Builder Deposit / Equity"),0,N(AD19))+IF(OR(AJ19="",AJ19="N/A",AJ19="Common Equity",AJ19="Builder Deposit / Equity"),0,N(AK19))+IF(OR(AQ19="",AQ19="N/A",AQ19="Common Equity",AQ19="Builder Deposit / Equity"),0,N(AR19)) -> 172586435 | S19: 211900000 | T19: =162200000+76600000 -> 238800000 | U19: 2.1603059e+08 | V19: Senior Mortgage | W19: 133934450 | X19: 0 | Y19: =IF(OR(V19="",V19="N/A",V19="Common Equity",V19="Builder Deposit / Equity",N($R19)=0),"N/A",SUM($W19)/$R19*100) -> 77.604274 | Z19: =IF(OR(V19="",V19="N/A",V19="Common Equity",V19="Builder Deposit / Equity",N($R19)=0),"N/A",SUM($W19)/$R19*100) -> 77.604274 | AA19: =IF(OR(V19="",V19="N/A",N($T19)=0),"N/A",SUM($W19)/$T19*100) -> 56.086453 | AB19: 0.021915884 | AC19: Preferred Equity | AD19: 38651985 | AE19: =IF(OR(AC19="",AC19="N/A"),"N/A",Y19) -> 77.604274 | AF19: =IF(OR(AC19="",AC19="N/A",AC19="Common Equity",AC19="Builder Deposit / Equity",N($R19)=0),"N/A",SUM($W19,$AD19)/$R19*100) -> 100 | AG19: =IF(OR(AC19="",AC19="N/A",AC19="Common Equity",AC19="Builder Deposit / Equity",N($R19)=0),"N/A",SUM($W19,$AD19)/$R19*100) -> 100 | AH19: =IF(OR(AC19="",AC19="N/A",N($T19)=0),"N/A",SUM($W19,$AD19)/$T19*100) -> 72.272376 | AI19: 0.1435 | AJ19: Common Equity | AK19: =T19-W19-AD19 -> 66213565 | AL19: =IF(OR(AJ19="",AJ19="N/A"),"N/A",AF19) -> 100 | AM19: =IF(OR(AJ19="",AJ19="N/A",AJ19="Common Equity",AJ19="Builder Deposit / Equity",N($R19)=0),"N/A",SUM($W19,$AD19,$AK19)/$R19*100) -> N/A | AN19: =IF(OR(AJ19="",AJ19="N/A",AJ19="Common Equity",AJ19="Builder Deposit / Equity",N($R19)=0),"N/A",SUM($W19,$AD19,$AK19)/$R19*100) -> N/A | AO19: =IF(OR(AJ19="",AJ19="N/A",N($T19)=0),"N/A",SUM($W19,$AD19,$AK19)/$T19*100) -> 100 | AP19: N/A
A20: MaSH-3773946 | B20: 342718 | C20: Project Royalton Whole Loan | D20: Vertical Tranche | E20: Origination | F20: Mortgage | G20: CRE Loan Senior | H20: 35000000 | I20: 19391892 | J20: Multiple Funding | K20: 0.99 | L20: =I20*K20 -> 19197973 | M20: =L20+N20 -> 34806081 | N20: =H20-I20 -> 15608108 | O20: =W20+AD20 -> 222000000 | P20: N/A - Unlevered | Q20: N/A | R20: =IF(OR(V20="",V20="N/A",V20="Common Equity",V20="Builder Deposit / Equity"),0,N(W20))+IF(OR(AC20="",AC20="N/A",AC20="Common Equity",AC20="Builder Deposit / Equity"),0,N(AD20))+IF(OR(AJ20="",AJ20="N/A",AJ20="Common Equity",AJ20="Builder Deposit / Equity"),0,N(AK20))+IF(OR(AQ20="",AQ20="N/A",AQ20="Common Equity",AQ20="Builder Deposit / Equity"),0,N(AR20)) -> 222000000 | S20: 255399925 | T20: 3.8879159e+08 | U20: 287402000 | V20: Senior Mortgage | W20: 133200000 | X20: 0 | Y20: =IF(OR(V20="",V20="N/A",V20="Common Equity",V20="Builder Deposit / Equity",N($R20)=0),"N/A",SUM($W20)/$R20*100) -> 60 | Z20: =IF(OR(V20="",V20="N/A",V20="Common Equity",V20="Builder Deposit / Equity",N($R20)=0),"N/A",SUM($W20)/$R20*100) -> 60 | AA20: =IF(OR(V20="",V20="N/A",N($T20)=0),"N/A",SUM($W20)/$T20*100) -> 34.26 | AB20: 0.032 | AC20: B-Note | AD20: 88800000 | AE20: =IF(OR(AC20="",AC20="N/A"),"N/A",Y20) -> 60 | AF20: =IF(OR(AC20="",AC20="N/A",AC20="Common Equity",AC20="Builder Deposit / Equity",N($R20)=0),"N/A",SUM($W20,$AD20)/$R20*100) -> 100 | AG20: =IF(OR(AC20="",AC20="N/A",AC20="Common Equity",AC20="Builder Deposit / Equity",N($R20)=0),"N/A",SUM($W20,$AD20)/$R20*100) -> 100 | AH20: =IF(OR(AC20="",AC20="N/A",N($T20)=0),"N/A",SUM($W20,$AD20)/$T20*100) -> 57.1 | AI20: 0.142 | AJ20: Common Equity | AK20: =T20-W20-AD20 -> 1.6679159e+08 | AL20: =IF(OR(AJ20="",AJ20="N/A"),"N/A",AF20) -> 100 | AM20: =IF(OR(AJ20="",AJ20="N/A",AJ20="Common Equity",AJ20="Builder Deposit / Equity",N($R20)=0),"N/A",SUM($W20,$AD20,$AK20)/$R20*100) -> N/A | AN20: =IF(OR(AJ20="",AJ20="N/A",AJ20="Common Equity",AJ20="Builder Deposit / Equity",N($R20)=0),"N/A",SUM($W20,$AD20,$AK20)/$R20*100) -> N/A | AO20: =IF(OR(AJ20="",AJ20="N/A",N($T20)=0),"N/A",SUM($W20,$AD20,$AK20)/$T20*100) -> 100 | AP20: N/A
A21: MaSH-3773946 | B21: 341453 | C21: Project Royalton Levered | D21: B Note | E21: Origination | F21: Mortgage | G21: CRE Loan Junior | H21: =25000000+49800000 -> 74800000 | I21: =13851351.3513514+27591891.8918919 -> 41443243 | J21: Multiple Funding | K21: 0.99 | L21: =I21*K21 -> 41028811 | M21: =L21+N21 -> 74385568 | N21: =H21-I21 -> 33356757 | O21: =W21+AD21 -> 222000000 | P21: Senior Mortgage | Q21: Apollo | R21: =IF(OR(V21="",V21="N/A",V21="Common Equity",V21="Builder Deposit / Equity"),0,N(W21))+IF(OR(AC21="",AC21="N/A",AC21="Common Equity",AC21="Builder Deposit / Equity"),0,N(AD21))+IF(OR(AJ21="",AJ21="N/A",AJ21="Common Equity",AJ21="Builder Deposit / Equity"),0,N(AK21))+IF(OR(AQ21="",AQ21="N/A",AQ21="Common Equity",AQ21="Builder Deposit / Equity"),0,N(AR21)) -> 222000000 | S21: 255399925 | T21: 3.8879159e+08 | U21: 287402000 | V21: Senior Mortgage | W21: 133200000 | X21: 0 | Y21: =IF(OR(V21="",V21="N/A",V21="Common Equity",V21="Builder Deposit / Equity",N($R21)=0),"N/A",SUM($W21)/$R21*100) -> 60 | Z21: =IF(OR(V21="",V21="N/A",V21="Common Equity",V21="Builder Deposit / Equity",N($R21)=0),"N/A",SUM($W21)/$R21*100) -> 60 | AA21: =IF(OR(V21="",V21="N/A",N($T21)=0),"N/A",SUM($W21)/$T21*100) -> 34.26 | AB21: 0.032 | AC21: B-Note | AD21: 88800000 | AE21: =IF(OR(AC21="",AC21="N/A"),"N/A",Y21) -> 60 | AF21: =IF(OR(AC21="",AC21="N/A",AC21="Common Equity",AC21="Builder Deposit / Equity",N($R21)=0),"N/A",SUM($W21,$AD21)/$R21*100) -> 100 | AG21: =IF(OR(AC21="",AC21="N/A",AC21="Common Equity",AC21="Builder Deposit / Equity",N($R21)=0),"N/A",SUM($W21,$AD21)/$R21*100) -> 100 | AH21: =IF(OR(AC21="",AC21="N/A",N($T21)=0),"N/A",SUM($W21,$AD21)/$T21*100) -> 57.1 | AI21: 0.142 | AJ21: Common Equity | AK21: =T21-W21-AD21 -> 1.6679159e+08 | AL21: =IF(OR(AJ21="",AJ21="N/A"),"N/A",AF21) -> 100 | AM21: =IF(OR(AJ21="",AJ21="N/A",AJ21="Common Equity",AJ21="Builder Deposit / Equity",N($R21)=0),"N/A",SUM($W21,$AD21,$AK21)/$R21*100) -> N/A | AN21: =IF(OR(AJ21="",AJ21="N/A",AJ21="Common Equity",AJ21="Builder Deposit / Equity",N($R21)=0),"N/A",SUM($W21,$AD21,$AK21)/$R21*100) -> N/A | AO21: =IF(OR(AJ21="",AJ21="N/A",N($T21)=0),"N/A",SUM($W21,$AD21,$AK21)/$T21*100) -> 100 | AP21: N/A
A22: MaSH-3570618 | B22: 138125 | C22: Project Hearthstone Land | D22: Other | E22: Equity | F22: Structured Equity | G22: Asset Purchase Levered -JV/Asset Co | H22: 150248219 | I22: 5889270.7 | J22: Multiple Funding | K22: 1 | L22: =I22*K22 -> 5889270.7 | M22: =L22+N22 -> 150248219 | N22: =H22-I22 -> 1.4435895e+08 | O22: =W22+AD22 -> 492972368 | P22: Repo/Warehouse | Q22: Goldman Sachs | R22: =IF(OR(V22="",V22="N/A",V22="Common Equity",V22="Builder Deposit / Equity"),0,N(W22))+IF(OR(AC22="",AC22="N/A",AC22="Common Equity",AC22="Builder Deposit / Equity"),0,N(AD22))+IF(OR(AJ22="",AJ22="N/A",AJ22="Common Equity",AJ22="Builder Deposit / Equity"),0,N(AK22))+IF(OR(AQ22="",AQ22="N/A",AQ22="Common Equity",AQ22="Builder Deposit / Equity"),0,N(AR22)) -> 100400000 | T22: 544772368 | V22: Repo/Warehouse | W22: 100400000 | X22: 0 | Y22: =IF(OR(V22="",V22="N/A",V22="Common Equity",V22="Builder Deposit / Equity",N($R22)=0),"N/A",SUM($W22)/$R22*100) -> 100 | Z22: =IF(OR(V22="",V22="N/A",V22="Common Equity",V22="Builder Deposit / Equity",N($R22)=0),"N/A",SUM($W22)/$R22*100) -> 100 | AA22: =IF(OR(V22="",V22="N/A",N($T22)=0),"N/A",SUM($W22)/$T22*100) -> 18.429716 | AB22: 0.0365 | AC22: Common Equity | AD22: =T22-W22-AK22 -> 392572368 | AE22: =IF(OR(AC22="",AC22="N/A"),"N/A",Y22) -> 100 | AF22: =IF(OR(AC22="",AC22="N/A",AC22="Common Equity",AC22="Builder Deposit / Equity",N($R22)=0),"N/A",SUM($W22,$AD22)/$R22*100) -> N/A | AG22: =IF(OR(AC22="",AC22="N/A",AC22="Common Equity",AC22="Builder Deposit / Equity",N($R22)=0),"N/A",SUM($W22,$AD22)/$R22*100) -> N/A | AH22: =IF(OR(AC22="",AC22="N/A",N($T22)=0),"N/A",SUM($W22,$AD22)/$T22*100) -> 90.491441 | AI22: 0.107 | AJ22: Builder Deposit / Equity | AK22: 51800000 | AL22: =IF(OR(AJ22="",AJ22="N/A"),"N/A",AF22) -> N/A | AM22: =IF(OR(AJ22="",AJ22="N/A",AJ22="Common Equity",AJ22="Builder Deposit / Equity",N($R22)=0),"N/A",SUM($W22,$AD22,$AK22)/$R22*100) -> N/A | AN22: =IF(OR(AJ22="",AJ22="N/A",AJ22="Common Equity",AJ22="Builder Deposit / Equity",N($R22)=0),"N/A",SUM($W22,$AD22,$AK22)/$R22*100) -> N/A | AO22: =IF(OR(AJ22="",AJ22="N/A",N($T22)=0),"N/A",SUM($W22,$AD22,$AK22)/$T22*100) -> 100 | AP22: N/A
A23: MaSH-3777002 | B23: 344509 | C23: HLTN 2026-DPLO - Class B | D23: Securitization | E23: CUSIP - New Issue | F23: CUSIP | G23: CUSIP IG | H23: 10000000 | I23: 10000000 | J23: Single Funding | K23: 1 | L23: =I23*K23 -> 10000000 | M23: =L23+N23 -> 10000000 | N23: =H23-I23 -> 0 | O23: 325200000 | P23: Structural | Q23: N/A | R23: =IF(OR(V23="",V23="N/A",V23="Common Equity",V23="Builder Deposit / Equity"),0,N(W23))+IF(OR(AC23="",AC23="N/A",AC23="Common Equity",AC23="Builder Deposit / Equity"),0,N(AD23))+IF(OR(AJ23="",AJ23="N/A",AJ23="Common Equity",AJ23="Builder Deposit / Equity"),0,N(AK23))+IF(OR(AQ23="",AQ23="N/A",AQ23="Common Equity",AQ23="Builder Deposit / Equity"),0,N(AR23)) -> 600000000 | S23: 600000000 | T23: 958000000 | U23: 827420000 | V23: Senior Bonds | W23: 238900000 | X23: 0 | Y23: =IF(OR(V23="",V23="N/A",V23="Common Equity",V23="Builder Deposit / Equity",N($R23)=0),"N/A",SUM($W23)/$R23*100) -> 39.816667 | Z23: =IF(OR(V23="",V23="N/A",V23="Common Equity",V23="Builder Deposit / Equity",N($R23)=0),"N/A",SUM($W23)/$R23*100) -> 39.816667 | AA23: =IF(OR(V23="",V23="N/A",N($T23)=0),"N/A",SUM($W23)/$T23*100) -> 24.93737 | AB23: 0.017 | AC23: Senior Bonds | AD23: 86300000 | AE23: =IF(OR(AC23="",AC23="N/A"),"N/A",Y23) -> 39.816667 | AF23: =IF(OR(AC23="",AC23="N/A",AC23="Common Equity",AC23="Builder Deposit / Equity",N($R23)=0),"N/A",SUM($W23,$AD23)/$R23*100) -> 54.2 | AG23: =IF(OR(AC23="",AC23="N/A",AC23="Common Equity",AC23="Builder Deposit / Equity",N($R23)=0),"N/A",SUM($W23,$AD23)/$R23*100) -> 54.2 | AH23: =IF(OR(AC23="",AC23="N/A",N($T23)=0),"N/A",SUM($W23,$AD23)/$T23*100) -> 33.94572 | AI23: 0.02 | AJ23: Junior Bonds | AK23: 274800000 | AL23: =IF(OR(AJ23="",AJ23="N/A"),"N/A",AF23) -> 54.2 | AM23: =IF(OR(AJ23="",AJ23="N/A",AJ23="Common Equity",AJ23="Builder Deposit / Equity",N($R23)=0),"N/A",SUM($W23,$AD23,$AK23)/$R23*100) -> 100 | AN23: =IF(OR(AJ23="",AJ23="N/A",AJ23="Common Equity",AJ23="Builder Deposit / Equity",N($R23)=0),"N/A",SUM($W23,$AD23,$AK23)/$R23*100) -> 100 | AO23: =IF(OR(AJ23="",AJ23="N/A",N($T23)=0),"N/A",SUM($W23,$AD23,$AK23)/$T23*100) -> 62.63048 | AP23: 0.03680131 | AQ23: Common Equity | AR23: =T23-SUM(W23,AD23,AK23) -> 358000000 | AS23: =IF(OR(AQ23="",AQ23="N/A"),"N/A",AM23) -> 100 | AT23: =IF(OR(AQ23="",AQ23="N/A",AQ23="Common Equity",AQ23="Builder Deposit / Equity",N($R23)=0),"N/A",SUM($W23,$AD23,$AK23,$AR23)/$R23*100) -> N/A | AU23: =IF(OR(AQ23="",AQ23="N/A",AQ23="Common Equity",AQ23="Builder Deposit / Equity",N($R23)=0),"N/A",SUM($W23,$AD23,$AK23,$AR23)/$R23*100) -> N/A | AV23: =IF(OR(AQ23="",AQ23="N/A",N($T23)=0),"N/A",SUM($W23,$AD23,$AK23,$AR23)/$T23*100) -> 100 | AW23: N/A
A24: MaSH-3777002 | B24: 344509 | C24: HLTN 2026-DPLO - Class C | D24: Securitization | E24: CUSIP - New Issue | F24: CUSIP | G24: CUSIP IG | H24: 25000000 | I24: 25000000 | J24: Single Funding | K24: 1 | L24: =I24*K24 -> 25000000 | M24: =L24+N24 -> 25000000 | N24: =H24-I24 -> 0 | O24: 395200000 | P24: Structural | Q24: N/A | R24: =IF(OR(V24="",V24="N/A",V24="Common Equity",V24="Builder Deposit / Equity"),0,N(W24))+IF(OR(AC24="",AC24="N/A",AC24="Common Equity",AC24="Builder Deposit / Equity"),0,N(AD24))+IF(OR(AJ24="",AJ24="N/A",AJ24="Common Equity",AJ24="Builder Deposit / Equity"),0,N(AK24))+IF(OR(AQ24="",AQ24="N/A",AQ24="Common Equity",AQ24="Builder Deposit / Equity"),0,N(AR24)) -> 600000000 | S24: 600000000 | T24: 958000000 | U24: 827420000 | V24: Senior Bonds | W24: 325200000 | X24: 0 | Y24: =IF(OR(V24="",V24="N/A",V24="Common Equity",V24="Builder Deposit / Equity",N($R24)=0),"N/A",SUM($W24)/$R24*100) -> 54.2 | Z24: =IF(OR(V24="",V24="N/A",V24="Common Equity",V24="Builder Deposit / Equity",N($R24)=0),"N/A",SUM($W24)/$R24*100) -> 54.2 | AA24: =IF(OR(V24="",V24="N/A",N($T24)=0),"N/A",SUM($W24)/$T24*100) -> 33.94572 | AB24: 0.017796125 | AC24: Senior Bonds | AD24: 70000000 | AE24: =IF(OR(AC24="",AC24="N/A"),"N/A",Y24) -> 54.2 | AF24: =IF(OR(AC24="",AC24="N/A",AC24="Common Equity",AC24="Builder Deposit / Equity",N($R24)=0),"N/A",SUM($W24,$AD24)/$R24*100) -> 65.866667 | AG24: =IF(OR(AC24="",AC24="N/A",AC24="Common Equity",AC24="Builder Deposit / Equity",N($R24)=0),"N/A",SUM($W24,$AD24)/$R24*100) -> 65.866667 | AH24: =IF(OR(AC24="",AC24="N/A",N($T24)=0),"N/A",SUM($W24,$AD24)/$T24*100) -> 41.25261 | AI24: 0.0225 | AJ24: Junior Bonds | AK24: 204800000 | AL24: =IF(OR(AJ24="",AJ24="N/A"),"N/A",AF24) -> 65.866667 | AM24: =IF(OR(AJ24="",AJ24="N/A",AJ24="Common Equity",AJ24="Builder Deposit / Equity",N($R24)=0),"N/A",SUM($W24,$AD24,$AK24)/$R24*100) -> 100 | AN24: =IF(OR(AJ24="",AJ24="N/A",AJ24="Common Equity",AJ24="Builder Deposit / Equity",N($R24)=0),"N/A",SUM($W24,$AD24,$AK24)/$R24*100) -> 100 | AO24: =IF(OR(AJ24="",AJ24="N/A",N($T24)=0),"N/A",SUM($W24,$AD24,$AK24)/$T24*100) -> 62.63048 | AP24: 0.041689453 | AQ24: Common Equity | AR24: =T24-SUM(W24,AD24,AK24) -> 358000000 | AS24: =IF(OR(AQ24="",AQ24="N/A"),"N/A",AM24) -> 100 | AT24: =IF(OR(AQ24="",AQ24="N/A",AQ24="Common Equity",AQ24="Builder Deposit / Equity",N($R24)=0),"N/A",SUM($W24,$AD24,$AK24,$AR24)/$R24*100) -> N/A | AU24: =IF(OR(AQ24="",AQ24="N/A",AQ24="Common Equity",AQ24="Builder Deposit / Equity",N($R24)=0),"N/A",SUM($W24,$AD24,$AK24,$AR24)/$R24*100) -> N/A | AV24: =IF(OR(AQ24="",AQ24="N/A",N($T24)=0),"N/A",SUM($W24,$AD24,$AK24,$AR24)/$T24*100) -> 100 | AW24: N/A
A25: MaSH-3777002 | B25: 344509 | C25: HLTN 2026-DPLO - Class D | D25: Securitization | E25: CUSIP - New Issue | F25: CUSIP | G25: CUSIP IG | H25: 25000000 | I25: 25000000 | J25: Single Funding | K25: 1 | L25: =I25*K25 -> 25000000 | M25: =L25+N25 -> 25000000 | N25: =H25-I25 -> 0 | O25: 458200000 | P25: Structural | Q25: N/A | R25: =IF(OR(V25="",V25="N/A",V25="Common Equity",V25="Builder Deposit / Equity"),0,N(W25))+IF(OR(AC25="",AC25="N/A",AC25="Common Equity",AC25="Builder Deposit / Equity"),0,N(AD25))+IF(OR(AJ25="",AJ25="N/A",AJ25="Common Equity",AJ25="Builder Deposit / Equity"),0,N(AK25))+IF(OR(AQ25="",AQ25="N/A",AQ25="Common Equity",AQ25="Builder Deposit / Equity"),0,N(AR25)) -> 600000000 | S25: 600000000 | T25: 958000000 | U25: 827420000 | V25: Senior Bonds | W25: 395200000 | X25: 0 | Y25: =IF(OR(V25="",V25="N/A",V25="Common Equity",V25="Builder Deposit / Equity",N($R25)=0),"N/A",SUM($W25)/$R25*100) -> 65.866667 | Z25: =IF(OR(V25="",V25="N/A",V25="Common Equity",V25="Builder Deposit / Equity",N($R25)=0),"N/A",SUM($W25)/$R25*100) -> 65.866667 | AA25: =IF(OR(V25="",V25="N/A",N($T25)=0),"N/A",SUM($W25)/$T25*100) -> 41.25261 | AB25: 0.018629302 | AC25: Senior Bonds | AD25: 63000000 | AE25: =IF(OR(AC25="",AC25="N/A"),"N/A",Y25) -> 65.866667 | AF25: =IF(OR(AC25="",AC25="N/A",AC25="Common Equity",AC25="Builder Deposit / Equity",N($R25)=0),"N/A",SUM($W25,$AD25)/$R25*100) -> 76.366667 | AG25: =IF(OR(AC25="",AC25="N/A",AC25="Common Equity",AC25="Builder Deposit / Equity",N($R25)=0),"N/A",SUM($W25,$AD25)/$R25*100) -> 76.366667 | AH25: =IF(OR(AC25="",AC25="N/A",N($T25)=0),"N/A",SUM($W25,$AD25)/$T25*100) -> 47.82881 | AI25: 0.0275 | AJ25: Junior Bonds | AK25: 141800000 | AL25: =IF(OR(AJ25="",AJ25="N/A"),"N/A",AF25) -> 76.366667 | AM25: =IF(OR(AJ25="",AJ25="N/A",AJ25="Common Equity",AJ25="Builder Deposit / Equity",N($R25)=0),"N/A",SUM($W25,$AD25,$AK25)/$R25*100) -> 100 | AN25: =IF(OR(AJ25="",AJ25="N/A",AJ25="Common Equity",AJ25="Builder Deposit / Equity",N($R25)=0),"N/A",SUM($W25,$AD25,$AK25)/$R25*100) -> 100 | AO25: =IF(OR(AJ25="",AJ25="N/A",N($T25)=0),"N/A",SUM($W25,$AD25,$AK25)/$T25*100) -> 62.63048 | AP25: 0.047993653 | AQ25: Common Equity | AR25: =T25-SUM(W25,AD25,AK25) -> 358000000 | AS25: =IF(OR(AQ25="",AQ25="N/A"),"N/A",AM25) -> 100 | AT25: =IF(OR(AQ25="",AQ25="N/A",AQ25="Common Equity",AQ25="Builder Deposit / Equity",N($R25)=0),"N/A",SUM($W25,$AD25,$AK25,$AR25)/$R25*100) -> N/A | AU25: =IF(OR(AQ25="",AQ25="N/A",AQ25="Common Equity",AQ25="Builder Deposit / Equity",N($R25)=0),"N/A",SUM($W25,$AD25,$AK25,$AR25)/$R25*100) -> N/A | AV25: =IF(OR(AQ25="",AQ25="N/A",N($T25)=0),"N/A",SUM($W25,$AD25,$AK25,$AR25)/$T25*100) -> 100 | AW25: N/A
A26: MaSH-3777674 | B26: 345181 | C26: KSL 2026-HT3 - Class B | D26: Securitization | E26: CUSIP - New Issue | F26: CUSIP | G26: CUSIP IG | H26: 10000000 | I26: 10000000 | J26: Single Funding | K26: 1 | L26: =I26*K26 -> 10000000 | M26: =L26+N26 -> 10000000 | N26: =H26-I26 -> 0 | O26: 380700000 | P26: Structural | Q26: N/A | R26: =IF(OR(V26="",V26="N/A",V26="Common Equity",V26="Builder Deposit / Equity"),0,N(W26))+IF(OR(AC26="",AC26="N/A",AC26="Common Equity",AC26="Builder Deposit / Equity"),0,N(AD26))+IF(OR(AJ26="",AJ26="N/A",AJ26="Common Equity",AJ26="Builder Deposit / Equity"),0,N(AK26))+IF(OR(AQ26="",AQ26="N/A",AQ26="Common Equity",AQ26="Builder Deposit / Equity"),0,N(AR26)) -> 890000000 | S26: 890000000 | T26: 1182900000 | U26: 966190000 | V26: Senior Bonds | W26: 248000000 | X26: 0 | Y26: =IF(OR(V26="",V26="N/A",V26="Common Equity",V26="Builder Deposit / Equity",N($R26)=0),"N/A",SUM($W26)/$R26*100) -> 27.865169 | Z26: =IF(OR(V26="",V26="N/A",V26="Common Equity",V26="Builder Deposit / Equity",N($R26)=0),"N/A",SUM($W26)/$R26*100) -> 27.865169 | AA26: =IF(OR(V26="",V26="N/A",N($T26)=0),"N/A",SUM($W26)/$T26*100) -> 20.965424 | AB26: 0.015 | AC26: Senior Bonds | AD26: 132700000 | AE26: =IF(OR(AC26="",AC26="N/A"),"N/A",Y26) -> 27.865169 | AF26: =IF(OR(AC26="",AC26="N/A",AC26="Common Equity",AC26="Builder Deposit / Equity",N($R26)=0),"N/A",SUM($W26,$AD26)/$R26*100) -> 42.775281 | AG26: =IF(OR(AC26="",AC26="N/A",AC26="Common Equity",AC26="Builder Deposit / Equity",N($R26)=0),"N/A",SUM($W26,$AD26)/$R26*100) -> 42.775281 | AH26: =IF(OR(AC26="",AC26="N/A",N($T26)=0),"N/A",SUM($W26,$AD26)/$T26*100) -> 32.183617 | AI26: 0.018 | AJ26: Junior Bonds | AK26: 509300000 | AL26: =IF(OR(AJ26="",AJ26="N/A"),"N/A",AF26) -> 42.775281 | AM26: =IF(OR(AJ26="",AJ26="N/A",AJ26="Common Equity",AJ26="Builder Deposit / Equity",N($R26)=0),"N/A",SUM($W26,$AD26,$AK26)/$R26*100) -> 100 | AN26: =IF(OR(AJ26="",AJ26="N/A",AJ26="Common Equity",AJ26="Builder Deposit / Equity",N($R26)=0),"N/A",SUM($W26,$AD26,$AK26)/$R26*100) -> 100 | AO26: =IF(OR(AJ26="",AJ26="N/A",N($T26)=0),"N/A",SUM($W26,$AD26,$AK26)/$T26*100) -> 75.23882 | AP26: 0.037776654 | AQ26: Common Equity | AR26: =T26-SUM(W26,AD26,AK26) -> 292900000 | AS26: =IF(OR(AQ26="",AQ26="N/A"),"N/A",AM26) -> 100 | AT26: =IF(OR(AQ26="",AQ26="N/A",AQ26="Common Equity",AQ26="Builder Deposit / Equity",N($R26)=0),"N/A",SUM($W26,$AD26,$AK26,$AR26)/$R26*100) -> N/A | AU26: =IF(OR(AQ26="",AQ26="N/A",AQ26="Common Equity",AQ26="Builder Deposit / Equity",N($R26)=0),"N/A",SUM($W26,$AD26,$AK26,$AR26)/$R26*100) -> N/A | AV26: =IF(OR(AQ26="",AQ26="N/A",N($T26)=0),"N/A",SUM($W26,$AD26,$AK26,$AR26)/$T26*100) -> 100 | AW26: N/A
A27: MaSH-3777674 | B27: 345181 | C27: KSL 2026-HT3 - Class C | D27: Securitization | E27: CUSIP - New Issue | F27: CUSIP | G27: CUSIP IG | H27: 15000000 | I27: 15000000 | J27: Single Funding | K27: 1 | L27: =I27*K27 -> 15000000 | M27: =L27+N27 -> 15000000 | N27: =H27-I27 -> 0 | O27: 437000000 | P27: Structural | Q27: N/A | R27: =IF(OR(V27="",V27="N/A",V27="Common Equity",V27="Builder Deposit / Equity"),0,N(W27))+IF(OR(AC27="",AC27="N/A",AC27="Common Equity",AC27="Builder Deposit / Equity"),0,N(AD27))+IF(OR(AJ27="",AJ27="N/A",AJ27="Common Equity",AJ27="Builder Deposit / Equity"),0,N(AK27))+IF(OR(AQ27="",AQ27="N/A",AQ27="Common Equity",AQ27="Builder Deposit / Equity"),0,N(AR27)) -> 890000000 | S27: 890000000 | T27: 1182900000 | U27: 966190000 | V27: Senior Bonds | W27: 380700000 | X27: 0 | Y27: =IF(OR(V27="",V27="N/A",V27="Common Equity",V27="Builder Deposit / Equity",N($R27)=0),"N/A",SUM($W27)/$R27*100) -> 42.775281 | Z27: =IF(OR(V27="",V27="N/A",V27="Common Equity",V27="Builder Deposit / Equity",N($R27)=0),"N/A",SUM($W27)/$R27*100) -> 42.775281 | AA27: =IF(OR(V27="",V27="N/A",N($T27)=0),"N/A",SUM($W27)/$T27*100) -> 32.183617 | AB27: 0.016045705 | AC27: Senior Bonds | AD27: 56300000 | AE27: =IF(OR(AC27="",AC27="N/A"),"N/A",Y27) -> 42.775281 | AF27: =IF(OR(AC27="",AC27="N/A",AC27="Common Equity",AC27="Builder Deposit / Equity",N($R27)=0),"N/A",SUM($W27,$AD27)/$R27*100) -> 49.101124 | AG27: =IF(OR(AC27="",AC27="N/A",AC27="Common Equity",AC27="Builder Deposit / Equity",N($R27)=0),"N/A",SUM($W27,$AD27)/$R27*100) -> 49.101124 | AH27: =IF(OR(AC27="",AC27="N/A",N($T27)=0),"N/A",SUM($W27,$AD27)/$T27*100) -> 36.943106 | AI27: 0.0205 | AJ27: Junior Bonds | AK27: 453000000 | AL27: =IF(OR(AJ27="",AJ27="N/A"),"N/A",AF27) -> 49.101124 | AM27: =IF(OR(AJ27="",AJ27="N/A",AJ27="Common Equity",AJ27="Builder Deposit / Equity",N($R27)=0),"N/A",SUM($W27,$AD27,$AK27)/$R27*100) -> 100 | AN27: =IF(OR(AJ27="",AJ27="N/A",AJ27="Common Equity",AJ27="Builder Deposit / Equity",N($R27)=0),"N/A",SUM($W27,$AD27,$AK27)/$R27*100) -> 100 | AO27: =IF(OR(AJ27="",AJ27="N/A",N($T27)=0),"N/A",SUM($W27,$AD27,$AK27)/$T27*100) -> 75.23882 | AP27: 0.039923841 | AQ27: Common Equity | AR27: =T27-SUM(W27,AD27,AK27) -> 292900000 | AS27: =IF(OR(AQ27="",AQ27="N/A"),"N/A",AM27) -> 100 | AT27: =IF(OR(AQ27="",AQ27="N/A",AQ27="Common Equity",AQ27="Builder Deposit / Equity",N($R27)=0),"N/A",SUM($W27,$AD27,$AK27,$AR27)/$R27*100) -> N/A | AU27: =IF(OR(AQ27="",AQ27="N/A",AQ27="Common Equity",AQ27="Builder Deposit / Equity",N($R27)=0),"N/A",SUM($W27,$AD27,$AK27,$AR27)/$R27*100) -> N/A | AV27: =IF(OR(AQ27="",AQ27="N/A",N($T27)=0),"N/A",SUM($W27,$AD27,$AK27,$AR27)/$T27*100) -> 100 | AW27: N/A
A28: MaSH-3777674 | B28: 345181 | C28: KSL 2026-HT3 - Class D | D28: Securitization | E28: CUSIP - New Issue | F28: CUSIP | G28: CUSIP IG | H28: 35000000 | I28: 35000000 | J28: Single Funding | K28: 1 | L28: =I28*K28 -> 35000000 | M28: =L28+N28 -> 35000000 | N28: =H28-I28 -> 0 | O28: 614700000 | P28: Structural | Q28: N/A | R28: =IF(OR(V28="",V28="N/A",V28="Common Equity",V28="Builder Deposit / Equity"),0,N(W28))+IF(OR(AC28="",AC28="N/A",AC28="Common Equity",AC28="Builder Deposit / Equity"),0,N(AD28))+IF(OR(AJ28="",AJ28="N/A",AJ28="Common Equity",AJ28="Builder Deposit / Equity"),0,N(AK28))+IF(OR(AQ28="",AQ28="N/A",AQ28="Common Equity",AQ28="Builder Deposit / Equity"),0,N(AR28)) -> 890000000 | S28: 890000000 | T28: 1182900000 | U28: 966190000 | V28: Senior Bonds | W28: 437000000 | X28: 0 | Y28: =IF(OR(V28="",V28="N/A",V28="Common Equity",V28="Builder Deposit / Equity",N($R28)=0),"N/A",SUM($W28)/$R28*100) -> 49.101124 | Z28: =IF(OR(V28="",V28="N/A",V28="Common Equity",V28="Builder Deposit / Equity",N($R28)=0),"N/A",SUM($W28)/$R28*100) -> 49.101124 | AA28: =IF(OR(V28="",V28="N/A",N($T28)=0),"N/A",SUM($W28)/$T28*100) -> 36.943106 | AB28: 0.016619565 | AC28: Senior Bonds | AD28: 177700000 | AE28: =IF(OR(AC28="",AC28="N/A"),"N/A",Y28) -> 49.101124 | AF28: =IF(OR(AC28="",AC28="N/A",AC28="Common Equity",AC28="Builder Deposit / Equity",N($R28)=0),"N/A",SUM($W28,$AD28)/$R28*100) -> 69.067416 | AG28: =IF(OR(AC28="",AC28="N/A",AC28="Common Equity",AC28="Builder Deposit / Equity",N($R28)=0),"N/A",SUM($W28,$AD28)/$R28*100) -> 69.067416 | AH28: =IF(OR(AC28="",AC28="N/A",N($T28)=0),"N/A",SUM($W28,$AD28)/$T28*100) -> 51.965508 | AI28: 0.0275 | AJ28: Junior Bonds | AK28: 275300000 | AL28: =IF(OR(AJ28="",AJ28="N/A"),"N/A",AF28) -> 69.067416 | AM28: =IF(OR(AJ28="",AJ28="N/A",AJ28="Common Equity",AJ28="Builder Deposit / Equity",N($R28)=0),"N/A",SUM($W28,$AD28,$AK28)/$R28*100) -> 100 | AN28: =IF(OR(AJ28="",AJ28="N/A",AJ28="Common Equity",AJ28="Builder Deposit / Equity",N($R28)=0),"N/A",SUM($W28,$AD28,$AK28)/$R28*100) -> 100 | AO28: =IF(OR(AJ28="",AJ28="N/A",N($T28)=0),"N/A",SUM($W28,$AD28,$AK28)/$T28*100) -> 75.23882 | AP28: 0.047943153 | AQ28: Common Equity | AR28: =T28-SUM(W28,AD28,AK28) -> 292900000 | AS28: =IF(OR(AQ28="",AQ28="N/A"),"N/A",AM28) -> 100 | AT28: =IF(OR(AQ28="",AQ28="N/A",AQ28="Common Equity",AQ28="Builder Deposit / Equity",N($R28)=0),"N/A",SUM($W28,$AD28,$AK28,$AR28)/$R28*100) -> N/A | AU28: =IF(OR(AQ28="",AQ28="N/A",AQ28="Common Equity",AQ28="Builder Deposit / Equity",N($R28)=0),"N/A",SUM($W28,$AD28,$AK28,$AR28)/$R28*100) -> N/A | AV28: =IF(OR(AQ28="",AQ28="N/A",N($T28)=0),"N/A",SUM($W28,$AD28,$AK28,$AR28)/$T28*100) -> 100 | AW28: N/A
A29: MaSH-3779335 | B29: 346842 | C29: AHPT 2026-ATRM - Class B | D29: Securitization | E29: CUSIP - New Issue | F29: CUSIP | G29: CUSIP IG | H29: 13000000 | I29: 13000000 | J29: Single Funding | K29: 1 | L29: =I29*K29 -> 13000000 | M29: =L29+N29 -> 13000000 | N29: =H29-I29 -> 0 | O29: 233200000 | P29: Structural | Q29: N/A | R29: =IF(OR(V29="",V29="N/A",V29="Common Equity",V29="Builder Deposit / Equity"),0,N(W29))+IF(OR(AC29="",AC29="N/A",AC29="Common Equity",AC29="Builder Deposit / Equity"),0,N(AD29))+IF(OR(AJ29="",AJ29="N/A",AJ29="Common Equity",AJ29="Builder Deposit / Equity"),0,N(AK29))+IF(OR(AQ29="",AQ29="N/A",AQ29="Common Equity",AQ29="Builder Deposit / Equity"),0,N(AR29)) -> 565700000 | S29: 591594445 | T29: 810000000 | U29: 577050000 | V29: Senior Bonds | W29: 181900000 | X29: 0 | Y29: =IF(OR(V29="",V29="N/A",V29="Common Equity",V29="Builder Deposit / Equity",N($R29)=0),"N/A",SUM($W29)/$R29*100) -> 32.154852 | Z29: =IF(OR(V29="",V29="N/A",V29="Common Equity",V29="Builder Deposit / Equity",N($R29)=0),"N/A",SUM($W29)/$R29*100) -> 32.154852 | AA29: =IF(OR(V29="",V29="N/A",N($T29)=0),"N/A",SUM($W29)/$T29*100) -> 22.45679 | AB29: 0.0165 | AC29: Senior Bonds | AD29: 51300000 | AE29: =IF(OR(AC29="",AC29="N/A"),"N/A",Y29) -> 32.154852 | AF29: =IF(OR(AC29="",AC29="N/A",AC29="Common Equity",AC29="Builder Deposit / Equity",N($R29)=0),"N/A",SUM($W29,$AD29)/$R29*100) -> 41.223263 | AG29: =IF(OR(AC29="",AC29="N/A",AC29="Common Equity",AC29="Builder Deposit / Equity",N($R29)=0),"N/A",SUM($W29,$AD29)/$R29*100) -> 41.223263 | AH29: =IF(OR(AC29="",AC29="N/A",N($T29)=0),"N/A",SUM($W29,$AD29)/$T29*100) -> 28.790123 | AI29: 0.019 | AJ29: Junior Bonds | AK29: 332500000 | AL29: =IF(OR(AJ29="",AJ29="N/A"),"N/A",AF29) -> 41.223263 | AM29: =IF(OR(AJ29="",AJ29="N/A",AJ29="Common Equity",AJ29="Builder Deposit / Equity",N($R29)=0),"N/A",SUM($W29,$AD29,$AK29)/$R29*100) -> 100 | AN29: =IF(OR(AJ29="",AJ29="N/A",AJ29="Common Equity",AJ29="Builder Deposit / Equity",N($R29)=0),"N/A",SUM($W29,$AD29,$AK29)/$R29*100) -> 100 | AO29: =IF(OR(AJ29="",AJ29="N/A",N($T29)=0),"N/A",SUM($W29,$AD29,$AK29)/$T29*100) -> 69.839506 | AP29: 0.046541692 | AQ29: Common Equity | AR29: =T29-SUM(W29,AD29,AK29) -> 244300000 | AS29: =IF(OR(AQ29="",AQ29="N/A"),"N/A",AM29) -> 100 | AT29: =IF(OR(AQ29="",AQ29="N/A",AQ29="Common Equity",AQ29="Builder Deposit / Equity",N($R29)=0),"N/A",SUM($W29,$AD29,$AK29,$AR29)/$R29*100) -> N/A | AU29: =IF(OR(AQ29="",AQ29="N/A",AQ29="Common Equity",AQ29="Builder Deposit / Equity",N($R29)=0),"N/A",SUM($W29,$AD29,$AK29,$AR29)/$R29*100) -> N/A | AV29: =IF(OR(AQ29="",AQ29="N/A",N($T29)=0),"N/A",SUM($W29,$AD29,$AK29,$AR29)/$T29*100) -> 100 | AW29: N/A
A30: MaSH-3779335 | B30: 346842 | C30: AHPT 2026-ATRM - Class C | D30: Securitization | E30: CUSIP - New Issue | F30: CUSIP | G30: CUSIP IG | H30: 13500000 | I30: 13500000 | J30: Single Funding | K30: 1 | L30: =I30*K30 -> 13500000 | M30: =L30+N30 -> 13500000 | N30: =H30-I30 -> 0 | O30: 288700000 | P30: Structural | Q30: N/A | R30: =IF(OR(V30="",V30="N/A",V30="Common Equity",V30="Builder Deposit / Equity"),0,N(W30))+IF(OR(AC30="",AC30="N/A",AC30="Common Equity",AC30="Builder Deposit / Equity"),0,N(AD30))+IF(OR(AJ30="",AJ30="N/A",AJ30="Common Equity",AJ30="Builder Deposit / Equity"),0,N(AK30))+IF(OR(AQ30="",AQ30="N/A",AQ30="Common Equity",AQ30="Builder Deposit / Equity"),0,N(AR30)) -> 565700000 | S30: 591594445 | T30: 810000000 | U30: 577050000 | V30: Senior Bonds | W30: 233200000 | X30: 0 | Y30: =IF(OR(V30="",V30="N/A",V30="Common Equity",V30="Builder Deposit / Equity",N($R30)=0),"N/A",SUM($W30)/$R30*100) -> 41.223263 | Z30: =IF(OR(V30="",V30="N/A",V30="Common Equity",V30="Builder Deposit / Equity",N($R30)=0),"N/A",SUM($W30)/$R30*100) -> 41.223263 | AA30: =IF(OR(V30="",V30="N/A",N($T30)=0),"N/A",SUM($W30)/$T30*100) -> 28.790123 | AB30: 0.017049957 | AC30: Senior Bonds | AD30: 55500000 | AE30: =IF(OR(AC30="",AC30="N/A"),"N/A",Y30) -> 41.223263 | AF30: =IF(OR(AC30="",AC30="N/A",AC30="Common Equity",AC30="Builder Deposit / Equity",N($R30)=0),"N/A",SUM($W30,$AD30)/$R30*100) -> 51.034117 | AG30: =IF(OR(AC30="",AC30="N/A",AC30="Common Equity",AC30="Builder Deposit / Equity",N($R30)=0),"N/A",SUM($W30,$AD30)/$R30*100) -> 51.034117 | AH30: =IF(OR(AC30="",AC30="N/A",N($T30)=0),"N/A",SUM($W30,$AD30)/$T30*100) -> 35.641975 | AI30: 0.022 | AJ30: Junior Bonds | AK30: 277000000 | AL30: =IF(OR(AJ30="",AJ30="N/A"),"N/A",AF30) -> 51.034117 | AM30: =IF(OR(AJ30="",AJ30="N/A",AJ30="Common Equity",AJ30="Builder Deposit / Equity",N($R30)=0),"N/A",SUM($W30,$AD30,$AK30)/$R30*100) -> 100 | AN30: =IF(OR(AJ30="",AJ30="N/A",AJ30="Common Equity",AJ30="Builder Deposit / Equity",N($R30)=0),"N/A",SUM($W30,$AD30,$AK30)/$R30*100) -> 100 | AO30: =IF(OR(AJ30="",AJ30="N/A",N($T30)=0),"N/A",SUM($W30,$AD30,$AK30)/$T30*100) -> 69.839506 | AP30: 0.05145889 | AQ30: Common Equity | AR30: =T30-SUM(W30,AD30,AK30) -> 244300000 | AS30: =IF(OR(AQ30="",AQ30="N/A"),"N/A",AM30) -> 100 | AT30: =IF(OR(AQ30="",AQ30="N/A",AQ30="Common Equity",AQ30="Builder Deposit / Equity",N($R30)=0),"N/A",SUM($W30,$AD30,$AK30,$AR30)/$R30*100) -> N/A | AU30: =IF(OR(AQ30="",AQ30="N/A",AQ30="Common Equity",AQ30="Builder Deposit / Equity",N($R30)=0),"N/A",SUM($W30,$AD30,$AK30,$AR30)/$R30*100) -> N/A | AV30: =IF(OR(AQ30="",AQ30="N/A",N($T30)=0),"N/A",SUM($W30,$AD30,$AK30,$AR30)/$T30*100) -> 100 | AW30: N/A
A31: MaSH-3779335 | B31: 346842 | C31: AHPT 2026-ATRM - Class D | D31: Securitization | E31: CUSIP - New Issue | F31: CUSIP | G31: CUSIP IG | H31: 20000000 | I31: 20000000 | J31: Single Funding | K31: 1 | L31: =I31*K31 -> 20000000 | M31: =L31+N31 -> 20000000 | N31: =H31-I31 -> 0 | O31: 364700000 | P31: Structural | Q31: N/A | R31: =IF(OR(V31="",V31="N/A",V31="Common Equity",V31="Builder Deposit / Equity"),0,N(W31))+IF(OR(AC31="",AC31="N/A",AC31="Common Equity",AC31="Builder Deposit / Equity"),0,N(AD31))+IF(OR(AJ31="",AJ31="N/A",AJ31="Common Equity",AJ31="Builder Deposit / Equity"),0,N(AK31))+IF(OR(AQ31="",AQ31="N/A",AQ31="Common Equity",AQ31="Builder Deposit / Equity"),0,N(AR31)) -> 565700000 | S31: 591594445 | T31: 810000000 | U31: 577050000 | V31: Senior Bonds | W31: 288700000 | X31: 0 | Y31: =IF(OR(V31="",V31="N/A",V31="Common Equity",V31="Builder Deposit / Equity",N($R31)=0),"N/A",SUM($W31)/$R31*100) -> 51.034117 | Z31: =IF(OR(V31="",V31="N/A",V31="Common Equity",V31="Builder Deposit / Equity",N($R31)=0),"N/A",SUM($W31)/$R31*100) -> 51.034117 | AA31: =IF(OR(V31="",V31="N/A",N($T31)=0),"N/A",SUM($W31)/$T31*100) -> 35.641975 | AB31: 0.018001559 | AC31: Senior Bonds | AD31: 76000000 | AE31: =IF(OR(AC31="",AC31="N/A"),"N/A",Y31) -> 51.034117 | AF31: =IF(OR(AC31="",AC31="N/A",AC31="Common Equity",AC31="Builder Deposit / Equity",N($R31)=0),"N/A",SUM($W31,$AD31)/$R31*100) -> 64.4688 | AG31: =IF(OR(AC31="",AC31="N/A",AC31="Common Equity",AC31="Builder Deposit / Equity",N($R31)=0),"N/A",SUM($W31,$AD31)/$R31*100) -> 64.4688 | AH31: =IF(OR(AC31="",AC31="N/A",N($T31)=0),"N/A",SUM($W31,$AD31)/$T31*100) -> 45.024691 | AI31: 0.032 | AJ31: Junior Bonds | AK31: 201000000 | AL31: =IF(OR(AJ31="",AJ31="N/A"),"N/A",AF31) -> 64.4688 | AM31: =IF(OR(AJ31="",AJ31="N/A",AJ31="Common Equity",AJ31="Builder Deposit / Equity",N($R31)=0),"N/A",SUM($W31,$AD31,$AK31)/$R31*100) -> 100 | AN31: =IF(OR(AJ31="",AJ31="N/A",AJ31="Common Equity",AJ31="Builder Deposit / Equity",N($R31)=0),"N/A",SUM($W31,$AD31,$AK31)/$R31*100) -> 100 | AO31: =IF(OR(AJ31="",AJ31="N/A",N($T31)=0),"N/A",SUM($W31,$AD31,$AK31)/$T31*100) -> 69.839506 | AP31: 0.05881648 | AQ31: Common Equity | AR31: =T31-SUM(W31,AD31,AK31) -> 244300000 | AS31: =IF(OR(AQ31="",AQ31="N/A"),"N/A",AM31) -> 100 | AT31: =IF(OR(AQ31="",AQ31="N/A",AQ31="Common Equity",AQ31="Builder Deposit / Equity",N($R31)=0),"N/A",SUM($W31,$AD31,$AK31,$AR31)/$R31*100) -> N/A | AU31: =IF(OR(AQ31="",AQ31="N/A",AQ31="Common Equity",AQ31="Builder Deposit / Equity",N($R31)=0),"N/A",SUM($W31,$AD31,$AK31,$AR31)/$R31*100) -> N/A | AV31: =IF(OR(AQ31="",AQ31="N/A",N($T31)=0),"N/A",SUM($W31,$AD31,$AK31,$AR31)/$T31*100) -> 100 | AW31: N/A
A32: MaSH-3779335 | B32: 346842 | C32: AHPT 2026-ATRM - Class E | D32: Securitization | E32: CUSIP - New Issue | F32: CUSIP | G32: CUSIP Non-IG | H32: 4000000 | I32: 4000000 | J32: Single Funding | K32: 1 | L32: =I32*K32 -> 4000000 | M32: =L32+N32 -> 4000000 | N32: =H32-I32 -> 0 | O32: 439700000 | P32: Structural | Q32: N/A | R32: =IF(OR(V32="",V32="N/A",V32="Common Equity",V32="Builder Deposit / Equity"),0,N(W32))+IF(OR(AC32="",AC32="N/A",AC32="Common Equity",AC32="Builder Deposit / Equity"),0,N(AD32))+IF(OR(AJ32="",AJ32="N/A",AJ32="Common Equity",AJ32="Builder Deposit / Equity"),0,N(AK32))+IF(OR(AQ32="",AQ32="N/A",AQ32="Common Equity",AQ32="Builder Deposit / Equity"),0,N(AR32)) -> 565700000 | S32: 591594445 | T32: 810000000 | U32: 577050000 | V32: Senior Bonds | W32: 364700000 | X32: 0 | Y32: =IF(OR(V32="",V32="N/A",V32="Common Equity",V32="Builder Deposit / Equity",N($R32)=0),"N/A",SUM($W32)/$R32*100) -> 64.4688 | Z32: =IF(OR(V32="",V32="N/A",V32="Common Equity",V32="Builder Deposit / Equity",N($R32)=0),"N/A",SUM($W32)/$R32*100) -> 64.4688 | AA32: =IF(OR(V32="",V32="N/A",N($T32)=0),"N/A",SUM($W32)/$T32*100) -> 45.024691 | AB32: 0.0209187 | AC32: Senior Bonds | AD32: 75000000 | AE32: =IF(OR(AC32="",AC32="N/A"),"N/A",Y32) -> 64.4688 | AF32: =IF(OR(AC32="",AC32="N/A",AC32="Common Equity",AC32="Builder Deposit / Equity",N($R32)=0),"N/A",SUM($W32,$AD32)/$R32*100) -> 77.72671 | AG32: =IF(OR(AC32="",AC32="N/A",AC32="Common Equity",AC32="Builder Deposit / Equity",N($R32)=0),"N/A",SUM($W32,$AD32)/$R32*100) -> 77.72671 | AH32: =IF(OR(AC32="",AC32="N/A",N($T32)=0),"N/A",SUM($W32,$AD32)/$T32*100) -> 54.283951 | AI32: 0.045 | AJ32: Junior Bonds | AK32: 126000000 | AL32: =IF(OR(AJ32="",AJ32="N/A"),"N/A",AF32) -> 77.72671 | AM32: =IF(OR(AJ32="",AJ32="N/A",AJ32="Common Equity",AJ32="Builder Deposit / Equity",N($R32)=0),"N/A",SUM($W32,$AD32,$AK32)/$R32*100) -> 100 | AN32: =IF(OR(AJ32="",AJ32="N/A",AJ32="Common Equity",AJ32="Builder Deposit / Equity",N($R32)=0),"N/A",SUM($W32,$AD32,$AK32)/$R32*100) -> 100 | AO32: =IF(OR(AJ32="",AJ32="N/A",N($T32)=0),"N/A",SUM($W32,$AD32,$AK32)/$T32*100) -> 69.839506 | AP32: 0.067040575 | AQ32: Common Equity | AR32: =T32-SUM(W32,AD32,AK32) -> 244300000 | AS32: =IF(OR(AQ32="",AQ32="N/A"),"N/A",AM32) -> 100 | AT32: =IF(OR(AQ32="",AQ32="N/A",AQ32="Common Equity",AQ32="Builder Deposit / Equity",N($R32)=0),"N/A",SUM($W32,$AD32,$AK32,$AR32)/$R32*100) -> N/A | AU32: =IF(OR(AQ32="",AQ32="N/A",AQ32="Common Equity",AQ32="Builder Deposit / Equity",N($R32)=0),"N/A",SUM($W32,$AD32,$AK32,$AR32)/$R32*100) -> N/A | AV32: =IF(OR(AQ32="",AQ32="N/A",N($T32)=0),"N/A",SUM($W32,$AD32,$AK32,$AR32)/$T32*100) -> 100 | AW32: N/A
A33: MaSH-3748736 | B33: 316243 | C33: Bridge Loan Trust | D33: Preferred Equity | E33: Preferred Equity | F33: Preferred Equity | G33: CRE Loan Junior | H33: 70000000 | I33: 70000000 | J33: Single Funding | K33: =67500000/H33 -> 0.96428571 | L33: =I33*K33 -> 67500000 | M33: =L33+N33 -> 67500000 | N33: =H33-I33 -> 0 | O33: =W33+H33 -> 3.3355249e+08 | P33: Repo/Warehouse | Q33: Goldman Sachs | R33: =IF(OR(V33="",V33="N/A",V33="Common Equity",V33="Builder Deposit / Equity"),0,N(W33))+IF(OR(AC33="",AC33="N/A",AC33="Common Equity",AC33="Builder Deposit / Equity"),0,N(AD33))+IF(OR(AJ33="",AJ33="N/A",AJ33="Common Equity",AJ33="Builder Deposit / Equity"),0,N(AK33))+IF(OR(AQ33="",AQ33="N/A",AQ33="Common Equity",AQ33="Builder Deposit / Equity"),0,N(AR33)) -> 3.3355249e+08 | S33: 403558082 | T33: 567000000 | U33: 446200000 | V33: Repo/Warehouse | W33: 2.6355249e+08 | X33: 0 | Y33: =IF(OR(V33="",V33="N/A",V33="Common Equity",V33="Builder Deposit / Equity",N($R33)=0),"N/A",SUM($W33)/$R33*100) -> 79.013798 | Z33: =IF(OR(V33="",V33="N/A",V33="Common Equity",V33="Builder Deposit / Equity",N($R33)=0),"N/A",SUM($W33)/$R33*100) -> 79.013798 | AA33: =IF(OR(V33="",V33="N/A",N($T33)=0),"N/A",SUM($W33)/$T33*100) -> 46.481921 | AB33: 0.0320365 | AC33: Preferred Equity | AD33: =H33 -> 70000000 | AE33: =IF(OR(AC33="",AC33="N/A"),"N/A",Y33) -> 79.013798 | AF33: =IF(OR(AC33="",AC33="N/A",AC33="Common Equity",AC33="Builder Deposit / Equity",N($R33)=0),"N/A",SUM($W33,$AD33)/$R33*100) -> 100 | AG33: =IF(OR(AC33="",AC33="N/A",AC33="Common Equity",AC33="Builder Deposit / Equity",N($R33)=0),"N/A",SUM($W33,$AD33)/$R33*100) -> 100 | AH33: =IF(OR(AC33="",AC33="N/A",N($T33)=0),"N/A",SUM($W33,$AD33)/$T33*100) -> 58.8276 | AI33: 0.15 | AJ33: Common Equity | AK33: =T33-W33-AD33 -> 2.3344751e+08 | AL33: =IF(OR(AJ33="",AJ33="N/A"),"N/A",AF33) -> 100 | AM33: =IF(OR(AJ33="",AJ33="N/A",AJ33="Common Equity",AJ33="Builder Deposit / Equity",N($R33)=0),"N/A",SUM($W33,$AD33,$AK33)/$R33*100) -> N/A | AN33: =IF(OR(AJ33="",AJ33="N/A",AJ33="Common Equity",AJ33="Builder Deposit / Equity",N($R33)=0),"N/A",SUM($W33,$AD33,$AK33)/$R33*100) -> N/A | AO33: =IF(OR(AJ33="",AJ33="N/A",N($T33)=0),"N/A",SUM($W33,$AD33,$AK33)/$T33*100) -> 100 | AP33: N/A
A34: MaSH-3748736 | B34: 316243 | C34: Bridge Loan Trust - Residual Class B | D34: Common Equity | E34: Equity | F34: Common Equity | G34: Equity | H34: 9500000 | I34: 9500000 | J34: Single Funding | K34: =9500000/H34 -> 1 | L34: =I34*K34 -> 9500000 | M34: =L34+N34 -> 9500000 | N34: =H34-I34 -> 0 | O34: =W34+AD34+AK34 -> 567000000 | P34: Repo/Warehouse | Q34: Goldman Sachs | R34: =IF(OR(V34="",V34="N/A",V34="Common Equity",V34="Builder Deposit / Equity"),0,N(W34))+IF(OR(AC34="",AC34="N/A",AC34="Common Equity",AC34="Builder Deposit / Equity"),0,N(AD34))+IF(OR(AJ34="",AJ34="N/A",AJ34="Common Equity",AJ34="Builder Deposit / Equity"),0,N(AK34))+IF(OR(AQ34="",AQ34="N/A",AQ34="Common Equity",AQ34="Builder Deposit / Equity"),0,N(AR34)) -> 3.3355249e+08 | S34: 403558082 | T34: 567000000 | U34: 446200000 | V34: Repo/Warehouse | W34: 2.6355249e+08 | X34: 0 | Y34: =IF(OR(V34="",V34="N/A",V34="Common Equity",V34="Builder Deposit / Equity",N($R34)=0),"N/A",SUM($W34)/$R34*100) -> 79.013798 | Z34: =IF(OR(V34="",V34="N/A",V34="Common Equity",V34="Builder Deposit / Equity",N($R34)=0),"N/A",SUM($W34)/$R34*100) -> 79.013798 | AA34: =IF(OR(V34="",V34="N/A",N($T34)=0),"N/A",SUM($W34)/$T34*100) -> 46.481921 | AB34: 0.0320365 | AC34: Preferred Equity | AD34: =AD33 -> 70000000 | AE34: =IF(OR(AC34="",AC34="N/A"),"N/A",Y34) -> 79.013798 | AF34: =IF(OR(AC34="",AC34="N/A",AC34="Common Equity",AC34="Builder Deposit / Equity",N($R34)=0),"N/A",SUM($W34,$AD34)/$R34*100) -> 100 | AG34: =IF(OR(AC34="",AC34="N/A",AC34="Common Equity",AC34="Builder Deposit / Equity",N($R34)=0),"N/A",SUM($W34,$AD34)/$R34*100) -> 100 | AH34: =IF(OR(AC34="",AC34="N/A",N($T34)=0),"N/A",SUM($W34,$AD34)/$T34*100) -> 58.8276 | AI34: 0.15 | AJ34: Common Equity | AK34: =T34-W34-AD34 -> 2.3344751e+08 | AL34: =IF(OR(AJ34="",AJ34="N/A"),"N/A",AF34) -> 100 | AM34: =IF(OR(AJ34="",AJ34="N/A",AJ34="Common Equity",AJ34="Builder Deposit / Equity",N($R34)=0),"N/A",SUM($W34,$AD34,$AK34)/$R34*100) -> N/A | AN34: =IF(OR(AJ34="",AJ34="N/A",AJ34="Common Equity",AJ34="Builder Deposit / Equity",N($R34)=0),"N/A",SUM($W34,$AD34,$AK34)/$R34*100) -> N/A | AO34: =IF(OR(AJ34="",AJ34="N/A",N($T34)=0),"N/A",SUM($W34,$AD34,$AK34)/$T34*100) -> 100 | AP34: N/A
A35: MaSH-3765727 | B35: 333234 | C35: Project AXMF 2025-SBRR1 Class A | D35: Securitization | E35: CUSIP - Secondary | F35: CUSIP | G35: CUSIP IG | H35: 81250000 | I35: =H35 -> 81250000 | J35: Single Funding | K35: 0.9848 | L35: =I35*K35 -> 80015000 | M35: =L35+N35 -> 80015000 | N35: =H35-I35 -> 0 | O35: =W35+AD35 -> 4.816966e+09 | P35: Structural | Q35: N/A | R35: =IF(OR(V35="",V35="N/A",V35="Common Equity",V35="Builder Deposit / Equity"),0,N(W35))+IF(OR(AC35="",AC35="N/A",AC35="Common Equity",AC35="Builder Deposit / Equity"),0,N(AD35))+IF(OR(AJ35="",AJ35="N/A",AJ35="Common Equity",AJ35="Builder Deposit / Equity"),0,N(AK35))+IF(OR(AQ35="",AQ35="N/A",AQ35="Common Equity",AQ35="Builder Deposit / Equity"),0,N(AR35)) -> 5.113076e+09 | S35: 5.113076e+09 | T35: 8.2179316e+09 | U35: 6935900000 | V35: Senior Bonds | W35: =S35-(137518000+90710000+84153000+46114000+75133000) -> 4.679448e+09 | X35: 0 | Y35: =IF(OR(V35="",V35="N/A",V35="Common Equity",V35="Builder Deposit / Equity",N($R35)=0),"N/A",SUM($W35)/$R35*100) -> 91.519234 | Z35: =IF(OR(V35="",V35="N/A",V35="Common Equity",V35="Builder Deposit / Equity",N($R35)=0),"N/A",SUM($W35)/$R35*100) -> 91.519234 | AA35: =IF(OR(V35="",V35="N/A",N($T35)=0),"N/A",SUM($W35)/$T35*100) -> 56.941919 | AC35: Senior Bonds | AD35: 137518000 | AE35: =IF(OR(AC35="",AC35="N/A"),"N/A",Y35) -> 91.519234 | AF35: =IF(OR(AC35="",AC35="N/A",AC35="Common Equity",AC35="Builder Deposit / Equity",N($R35)=0),"N/A",SUM($W35,$AD35)/$R35*100) -> 94.20877 | AG35: =IF(OR(AC35="",AC35="N/A",AC35="Common Equity",AC35="Builder Deposit / Equity",N($R35)=0),"N/A",SUM($W35,$AD35)/$R35*100) -> 94.20877 | AH35: =IF(OR(AC35="",AC35="N/A",N($T35)=0),"N/A",SUM($W35,$AD35)/$T35*100) -> 58.615309 | AI35: 0.026 | AJ35: Junior Bonds | AK35: =90710000+84153000+46114000+75133000 -> 296110000 | AL35: =IF(OR(AJ35="",AJ35="N/A"),"N/A",AF35) -> 94.20877 | AM35: =IF(OR(AJ35="",AJ35="N/A",AJ35="Common Equity",AJ35="Builder Deposit / Equity",N($R35)=0),"N/A",SUM($W35,$AD35,$AK35)/$R35*100) -> 100 | AN35: =IF(OR(AJ35="",AJ35="N/A",AJ35="Common Equity",AJ35="Builder Deposit / Equity",N($R35)=0),"N/A",SUM($W35,$AD35,$AK35)/$R35*100) -> 100 | AO35: =IF(OR(AJ35="",AJ35="N/A",N($T35)=0),"N/A",SUM($W35,$AD35,$AK35)/$T35*100) -> 62.218527 | AP35: N/A | AQ35: Common Equity | AR35: =T35-SUM(W35,AD35,AK35) -> 3.1048556e+09 | AS35: =IF(OR(AQ35="",AQ35="N/A"),"N/A",AM35) -> 100 | AT35: =IF(OR(AQ35="",AQ35="N/A",AQ35="Common Equity",AQ35="Builder Deposit / Equity",N($R35)=0),"N/A",SUM($W35,$AD35,$AK35,$AR35)/$R35*100) -> N/A | AU35: =IF(OR(AQ35="",AQ35="N/A",AQ35="Common Equity",AQ35="Builder Deposit / Equity",N($R35)=0),"N/A",SUM($W35,$AD35,$AK35,$AR35)/$R35*100) -> N/A | AV35: =IF(OR(AQ35="",AQ35="N/A",N($T35)=0),"N/A",SUM($W35,$AD35,$AK35,$AR35)/$T35*100) -> 100 | AW35: N/A
A36: MaSH-3765727 | B36: 333234 | C36: Project AXMF 2025-SBRR1 Class B | D36: Securitization | E36: CUSIP - Secondary | F36: CUSIP | G36: CUSIP IG | H36: 43750000 | I36: =H36 -> 43750000 | J36: Single Funding | K36: 0.9749 | L36: =I36*K36 -> 42651875 | M36: =L36+N36 -> 42651875 | N36: =H36-I36 -> 0 | O36: =W36+AD36 -> 4.907676e+09 | P36: Structural | Q36: N/A | R36: =IF(OR(V36="",V36="N/A",V36="Common Equity",V36="Builder Deposit / Equity"),0,N(W36))+IF(OR(AC36="",AC36="N/A",AC36="Common Equity",AC36="Builder Deposit / Equity"),0,N(AD36))+IF(OR(AJ36="",AJ36="N/A",AJ36="Common Equity",AJ36="Builder Deposit / Equity"),0,N(AK36))+IF(OR(AQ36="",AQ36="N/A",AQ36="Common Equity",AQ36="Builder Deposit / Equity"),0,N(AR36)) -> 5.113076e+09 | S36: =S$35 -> 5.113076e+09 | T36: =T$35 -> 8.2179316e+09 | U36: =U$35 -> 6935900000 | V36: Senior Bonds | W36: =S36-(90710000+84153000+46114000+75133000) -> 4.816966e+09 | X36: 0 | Y36: =IF(OR(V36="",V36="N/A",V36="Common Equity",V36="Builder Deposit / Equity",N($R36)=0),"N/A",SUM($W36)/$R36*100) -> 94.20877 | Z36: =IF(OR(V36="",V36="N/A",V36="Common Equity",V36="Builder Deposit / Equity",N($R36)=0),"N/A",SUM($W36)/$R36*100) -> 94.20877 | AA36: =IF(OR(V36="",V36="N/A",N($T36)=0),"N/A",SUM($W36)/$T36*100) -> 58.615309 | AC36: Senior Bonds | AD36: 90710000 | AE36: =IF(OR(AC36="",AC36="N/A"),"N/A",Y36) -> 94.20877 | AF36: =IF(OR(AC36="",AC36="N/A",AC36="Common Equity",AC36="Builder Deposit / Equity",N($R36)=0),"N/A",SUM($W36,$AD36)/$R36*100) -> 95.982849 | AG36: =IF(OR(AC36="",AC36="N/A",AC36="Common Equity",AC36="Builder Deposit / Equity",N($R36)=0),"N/A",SUM($W36,$AD36)/$R36*100) -> 95.982849 | AH36: =IF(OR(AC36="",AC36="N/A",N($T36)=0),"N/A",SUM($W36,$AD36)/$T36*100) -> 59.719114 | AI36: 0.036 | AJ36: Junior Bonds | AK36: =84153000+46114000+75133000 -> 205400000 | AL36: =IF(OR(AJ36="",AJ36="N/A"),"N/A",AF36) -> 95.982849 | AM36: =IF(OR(AJ36="",AJ36="N/A",AJ36="Common Equity",AJ36="Builder Deposit / Equity",N($R36)=0),"N/A",SUM($W36,$AD36,$AK36)/$R36*100) -> 100 | AN36: =IF(OR(AJ36="",AJ36="N/A",AJ36="Common Equity",AJ36="Builder Deposit / Equity",N($R36)=0),"N/A",SUM($W36,$AD36,$AK36)/$R36*100) -> 100 | AO36: =IF(OR(AJ36="",AJ36="N/A",N($T36)=0),"N/A",SUM($W36,$AD36,$AK36)/$T36*100) -> 62.218527 | AP36: N/A | AQ36: Common Equity | AR36: =T36-SUM(W36,AD36,AK36) -> 3.1048556e+09 | AS36: =IF(OR(AQ36="",AQ36="N/A"),"N/A",AM36) -> 100 | AT36: =IF(OR(AQ36="",AQ36="N/A",AQ36="Common Equity",AQ36="Builder Deposit / Equity",N($R36)=0),"N/A",SUM($W36,$AD36,$AK36,$AR36)/$R36*100) -> N/A | AU36: =IF(OR(AQ36="",AQ36="N/A",AQ36="Common Equity",AQ36="Builder Deposit / Equity",N($R36)=0),"N/A",SUM($W36,$AD36,$AK36,$AR36)/$R36*100) -> N/A | AV36: =IF(OR(AQ36="",AQ36="N/A",N($T36)=0),"N/A",SUM($W36,$AD36,$AK36,$AR36)/$T36*100) -> 100 | AW36: N/A
A37: MaSH-3780241 | B37: 347748 | C37: Project AXMF 2025-SBRR1 Class C | D37: Securitization | E37: CUSIP - Secondary | F37: CUSIP | G37: CUSIP Non-IG | H37: =2525000+22475000 -> 25000000 | I37: =2525000+22475000 -> 25000000 | J37: Single Funding | K37: 0.895 | L37: =I37*K37 -> 22375000 | M37: =L37+N37 -> 22375000 | N37: =H37-I37 -> 0 | O37: =W37+AD37 -> 4.991829e+09 | P37: Structural | Q37: N/A | R37: =IF(OR(V37="",V37="N/A",V37="Common Equity",V37="Builder Deposit / Equity"),0,N(W37))+IF(OR(AC37="",AC37="N/A",AC37="Common Equity",AC37="Builder Deposit / Equity"),0,N(AD37))+IF(OR(AJ37="",AJ37="N/A",AJ37="Common Equity",AJ37="Builder Deposit / Equity"),0,N(AK37))+IF(OR(AQ37="",AQ37="N/A",AQ37="Common Equity",AQ37="Builder Deposit / Equity"),0,N(AR37)) -> 5.113076e+09 | S37: =S$35 -> 5.113076e+09 | T37: =T$35 -> 8.2179316e+09 | U37: =U$35 -> 6935900000 | V37: Senior Bonds | W37: =S37-(84153000+46114000+75133000) -> 4.907676e+09 | X37: 0 | Y37: =IF(OR(V37="",V37="N/A",V37="Common Equity",V37="Builder Deposit / Equity",N($R37)=0),"N/A",SUM($W37)/$R37*100) -> 95.982849 | Z37: =IF(OR(V37="",V37="N/A",V37="Common Equity",V37="Builder Deposit / Equity",N($R37)=0),"N/A",SUM($W37)/$R37*100) -> 95.982849 | AA37: =IF(OR(V37="",V37="N/A",N($T37)=0),"N/A",SUM($W37)/$T37*100) -> 59.719114 | AC37: Senior Bonds | AD37: 84153000 | AE37: =IF(OR(AC37="",AC37="N/A"),"N/A",Y37) -> 95.982849 | AF37: =IF(OR(AC37="",AC37="N/A",AC37="Common Equity",AC37="Builder Deposit / Equity",N($R37)=0),"N/A",SUM($W37,$AD37)/$R37*100) -> 97.628688 | AG37: =IF(OR(AC37="",AC37="N/A",AC37="Common Equity",AC37="Builder Deposit / Equity",N($R37)=0),"N/A",SUM($W37,$AD37)/$R37*100) -> 97.628688 | AH37: =IF(OR(AC37="",AC37="N/A",N($T37)=0),"N/A",SUM($W37,$AD37)/$T37*100) -> 60.743131 | AI37: 0.0532 | AJ37: Junior Bonds | AK37: =46114000+75133000 -> 121247000 | AL37: =IF(OR(AJ37="",AJ37="N/A"),"N/A",AF37) -> 97.628688 | AM37: =IF(OR(AJ37="",AJ37="N/A",AJ37="Common Equity",AJ37="Builder Deposit / Equity",N($R37)=0),"N/A",SUM($W37,$AD37,$AK37)/$R37*100) -> 100 | AN37: =IF(OR(AJ37="",AJ37="N/A",AJ37="Common Equity",AJ37="Builder Deposit / Equity",N($R37)=0),"N/A",SUM($W37,$AD37,$AK37)/$R37*100) -> 100 | AO37: =IF(OR(AJ37="",AJ37="N/A",N($T37)=0),"N/A",SUM($W37,$AD37,$AK37)/$T37*100) -> 62.218527 | AP37: N/A | AQ37: Common Equity | AR37: =T37-SUM(W37,AD37,AK37) -> 3.1048556e+09 | AS37: =IF(OR(AQ37="",AQ37="N/A"),"N/A",AM37) -> 100 | AT37: =IF(OR(AQ37="",AQ37="N/A",AQ37="Common Equity",AQ37="Builder Deposit / Equity",N($R37)=0),"N/A",SUM($W37,$AD37,$AK37,$AR37)/$R37*100) -> N/A | AU37: =IF(OR(AQ37="",AQ37="N/A",AQ37="Common Equity",AQ37="Builder Deposit / Equity",N($R37)=0),"N/A",SUM($W37,$AD37,$AK37,$AR37)/$R37*100) -> N/A | AV37: =IF(OR(AQ37="",AQ37="N/A",N($T37)=0),"N/A",SUM($W37,$AD37,$AK37,$AR37)/$T37*100) -> 100 | AW37: N/A
A38: MaSH-3275701 | B38: 62474 | C38: Chimera_Lake | D38: A Note | E38: Syndication | F38: Mortgage | G38: CRE Loan Senior | H38: 75000000 | I38: 75000000 | J38: Single Funding | K38: 0.965 | L38: =I38*K38 -> 72375000 | M38: =L38+N38 -> 72375000 | N38: =H38-I38 -> 0 | O38: =W38 -> 152000000 | P38: N/A - Unlevered | Q38: N/A | R38: =IF(OR(V38="",V38="N/A",V38="Common Equity",V38="Builder Deposit / Equity"),0,N(W38))+IF(OR(AC38="",AC38="N/A",AC38="Common Equity",AC38="Builder Deposit / Equity"),0,N(AD38))+IF(OR(AJ38="",AJ38="N/A",AJ38="Common Equity",AJ38="Builder Deposit / Equity"),0,N(AK38))+IF(OR(AQ38="",AQ38="N/A",AQ38="Common Equity",AQ38="Builder Deposit / Equity"),0,N(AR38)) -> 190000000 | S38: =278000000+8742525 -> 286742525 | T38: =24000000+24700000+26800000+17100000+25600000+26000000+39000000+35300000+34000000+25800000 -> 278300000 | U38: 177458866 | V38: Senior Mortgage | W38: =75000000+77000000 -> 152000000 | X38: 0 | Y38: =IF(OR(V38="",V38="N/A",V38="Common Equity",V38="Builder Deposit / Equity",N($R38)=0),"N/A",SUM($W38)/$R38*100) -> 80 | Z38: =IF(OR(V38="",V38="N/A",V38="Common Equity",V38="Builder Deposit / Equity",N($R38)=0),"N/A",SUM($W38)/$R38*100) -> 80 | AA38: =IF(OR(V38="",V38="N/A",N($T38)=0),"N/A",SUM($W38)/$T38*100) -> 54.617319 | AB38: 0.035 | AC38: B-Note | AD38: =18750000+19250000 -> 38000000 | AE38: =IF(OR(AC38="",AC38="N/A"),"N/A",Y38) -> 80 | AF38: =IF(OR(AC38="",AC38="N/A",AC38="Common Equity",AC38="Builder Deposit / Equity",N($R38)=0),"N/A",SUM($W38,$AD38)/$R38*100) -> 100 | AG38: =IF(OR(AC38="",AC38="N/A",AC38="Common Equity",AC38="Builder Deposit / Equity",N($R38)=0),"N/A",SUM($W38,$AD38)/$R38*100) -> 100 | AH38: =IF(OR(AC38="",AC38="N/A",N($T38)=0),"N/A",SUM($W38,$AD38)/$T38*100) -> 68.271649 | AI38: N/A | AJ38: Common Equity | AK38: =T38-W38-AD38 -> 88300000 | AL38: =IF(OR(AJ38="",AJ38="N/A"),"N/A",AF38) -> 100 | AM38: =IF(OR(AJ38="",AJ38="N/A",AJ38="Common Equity",AJ38="Builder Deposit / Equity",N($R38)=0),"N/A",SUM($W38,$AD38,$AK38)/$R38*100) -> N/A | AN38: =IF(OR(AJ38="",AJ38="N/A",AJ38="Common Equity",AJ38="Builder Deposit / Equity",N($R38)=0),"N/A",SUM($W38,$AD38,$AK38)/$R38*100) -> N/A | AO38: =IF(OR(AJ38="",AJ38="N/A",N($T38)=0),"N/A",SUM($W38,$AD38,$AK38)/$T38*100) -> 100 | AP38: N/A
A39: MaSH-3257025 | B39: 61923 | C39: Project 3700M | D39: A Note | E39: Syndication | F39: Mortgage | G39: CRE Loan Senior | H39: 46500000 | I39: =H39 -> 46500000 | J39: Single Funding | K39: 1 | L39: =I39*K39 -> 46500000 | M39: =L39+N39 -> 46500000 | N39: =H39-I39 -> 0 | O39: =W39 -> 121500000 | P39: N/A - Unlevered | Q39: N/A | R39: =IF(OR(V39="",V39="N/A",V39="Common Equity",V39="Builder Deposit / Equity"),0,N(W39))+IF(OR(AC39="",AC39="N/A",AC39="Common Equity",AC39="Builder Deposit / Equity"),0,N(AD39))+IF(OR(AJ39="",AJ39="N/A",AJ39="Common Equity",AJ39="Builder Deposit / Equity"),0,N(AK39))+IF(OR(AQ39="",AQ39="N/A",AQ39="Common Equity",AQ39="Builder Deposit / Equity"),0,N(AR39)) -> 121500000 | S39: 169140040 | T39: 144400000 | U39: 133030232 | V39: Senior Mortgage | W39: 121500000 | X39: 0 | Y39: =IF(OR(V39="",V39="N/A",V39="Common Equity",V39="Builder Deposit / Equity",N($R39)=0),"N/A",SUM($W39)/$R39*100) -> 100 | Z39: =IF(OR(V39="",V39="N/A",V39="Common Equity",V39="Builder Deposit / Equity",N($R39)=0),"N/A",SUM($W39)/$R39*100) -> 100 | AA39: =IF(OR(V39="",V39="N/A",N($T39)=0),"N/A",SUM($W39)/$T39*100) -> 84.141274 | AB39: 0.0325 | AC39: Common Equity | AD39: =T39-W39 -> 22900000 | AE39: =IF(OR(AC39="",AC39="N/A"),"N/A",Y39) -> 100 | AF39: =IF(OR(AC39="",AC39="N/A",AC39="Common Equity",AC39="Builder Deposit / Equity",N($R39)=0),"N/A",SUM($W39,$AD39)/$R39*100) -> N/A | AG39: =IF(OR(AC39="",AC39="N/A",AC39="Common Equity",AC39="Builder Deposit / Equity",N($R39)=0),"N/A",SUM($W39,$AD39)/$R39*100) -> N/A | AH39: =IF(OR(AC39="",AC39="N/A",N($T39)=0),"N/A",SUM($W39,$AD39)/$T39*100) -> 100 | AI39: N/A
A40: MaSH-3659094 | B40: 226601 | C40: Project Great Park Land Bank | D40: Other | E40: Equity | F40: Structured Equity | G40: Asset Purchase Levered -JV/Asset Co | H40: 69428848 | I40: 64474719 | J40: Multiple Funding | K40: 1 | L40: =I40*K40 -> 64474719 | M40: =L40+N40 -> 69428848 | N40: =H40-I40 -> 4954128.8 | O40: =W40+AD40 -> 2.9840806e+08 | P40: Senior Mortgage | Q40: CIBC / Western Alliance | R40: =IF(OR(V40="",V40="N/A",V40="Common Equity",V40="Builder Deposit / Equity"),0,N(W40))+IF(OR(AC40="",AC40="N/A",AC40="Common Equity",AC40="Builder Deposit / Equity"),0,N(AD40))+IF(OR(AJ40="",AJ40="N/A",AJ40="Common Equity",AJ40="Builder Deposit / Equity"),0,N(AK40))+IF(OR(AQ40="",AQ40="N/A",AQ40="Common Equity",AQ40="Builder Deposit / Equity"),0,N(AR40)) -> 190000000 | S40: =309752490+50597573 -> 360350063 | T40: =309070000+50597573 -> 359667573 | V40: Senior Mortgage | W40: 190000000 | X40: 0 | Y40: =IF(OR(V40="",V40="N/A",V40="Common Equity",V40="Builder Deposit / Equity",N($R40)=0),"N/A",SUM($W40)/$R40*100) -> 100 | Z40: =IF(OR(V40="",V40="N/A",V40="Common Equity",V40="Builder Deposit / Equity",N($R40)=0),"N/A",SUM($W40)/$R40*100) -> 100 | AA40: =IF(OR(V40="",V40="N/A",N($T40)=0),"N/A",SUM($W40)/$T40*100) -> 52.826558 | AB40: 0.0375 | AC40: Common Equity | AD40: =T40-W40-AK40 -> 1.0840806e+08 | AE40: =IF(OR(AC40="",AC40="N/A"),"N/A",Y40) -> 100 | AF40: =IF(OR(AC40="",AC40="N/A",AC40="Common Equity",AC40="Builder Deposit / Equity",N($R40)=0),"N/A",SUM($W40,$AD40)/$R40*100) -> N/A | AG40: =IF(OR(AC40="",AC40="N/A",AC40="Common Equity",AC40="Builder Deposit / Equity",N($R40)=0),"N/A",SUM($W40,$AD40)/$R40*100) -> N/A | AH40: =IF(OR(AC40="",AC40="N/A",N($T40)=0),"N/A",SUM($W40,$AD40)/$T40*100) -> 82.967742 | AI40: 0.1095 | AJ40: Builder Deposit / Equity | AK40: 61259511 | AL40: =IF(OR(AJ40="",AJ40="N/A"),"N/A",AF40) -> N/A | AM40: =IF(OR(AJ40="",AJ40="N/A",AJ40="Common Equity",AJ40="Builder Deposit / Equity",N($R40)=0),"N/A",SUM($W40,$AD40,$AK40)/$R40*100) -> N/A | AN40: =IF(OR(AJ40="",AJ40="N/A",AJ40="Common Equity",AJ40="Builder Deposit / Equity",N($R40)=0),"N/A",SUM($W40,$AD40,$AK40)/$R40*100) -> N/A | AO40: =IF(OR(AJ40="",AJ40="N/A",N($T40)=0),"N/A",SUM($W40,$AD40,$AK40)/$T40*100) -> 100 | AP40: N/A

Sheet Loan Data
BB1: x
A2: Mash-ID | B2: Deal Code | C2: Loan Name | D2: CUSIP | E2: Deal Lead | F2: Team Member | G2: IC Date | H2: Allocations Date | I2: SSP Pricing / Commitment Date | J2: Origination Date | K2: SSP Closing Date | L2: Sponsor | M2: Originator | N2: Seller | O2: Source | P2: Calculation Agent | Q2: Co-Lender | R2: Admin Agent | S2: Servicer | T2: Property Type | U2: Number of Properties | V2: Loan Type | W2: Debt Stack Type | X2: Original Loan Term | Y2: Maturity Date | Z2: Original Maturity Extension Times Allowed | AA2: Original Maturity Extension Term | AB2: Fully Extended Maturity Date | AC2: Remaining Loan Term | AD2: Next Contractual Maturity | AE2: Payment Type | AF2: Interest Only Flag | AG2: Original Interest Only Term | AH2: Amortization Start Date | AI2: Amortization Term | AJ2: Remaining Amort Term | AK2: Assumable Flag | AL2: Interest Type | AM2: Rate calc method | AN2: Original Index Rate | AO2: Interest Rate Index | AP2: Whole Loan Margin | AQ2: Upfront Fee | AR2: Unused Fee | AS2: Extension Fee #1 | AT2: Extension Fee #2 | AU2: Exit Fee | AV2: Index Rounding Code | AW2: Index Rounding Position | AX2: Holiday Calendar to be used for setting Rate | AY2: Index Determ Date prior to Effective Date | AZ2: Interest Paid to Date | BA2: Interest Accrual Begins Date | BB2: First Payment Due Date | BC2: Next Payment Due Date | BD2: Payment Frequency Type | BE2: Payment Frequency | BF2: Payment Date | BG2: Accrual Period | BH2: First Rate Adjustment | BI2: Rate Adjustment Frequency | BJ2: Interest Rate Ceiling | BK2: Benchmark Adjustment Rate | BL2: Late Charge Calc | BM2: Number of Grace Days | BN2: Rate Reset During Life of Loan | BO2: Effective Date of First Rate Reset | BP2: Index Rate Floor | BQ2: Insurance Cap Purchased Flag | BR2: Interest Rate Cap Strike Price | BS2: Interest Rate Cap Notional | BT2: Interest Rate Cap Term | BU2: Index Rate Trigger for Int Cap Contract strike price | BV2: Prepayment Option | BW2: Prepayment Calculation Description | BX2: Prepayment Start Date | BY2: Prepayment End Date | BZ2: Payment Method | CA2: Default Interest Rate | CB2: Future Additional Debt Permitted | CC2: Future Debt Permitted Type | CD2: Construction Loan | CE2: Purchase_Price_at_Closing | CF2: Closing_Costs_at_Closing | CG2: Soft_Costs_at_Closing | CH2: Hard_Costs_at_Closing | CI2: Capex_at_Closing | CJ2: TI_LC_at_Closing | CK2: Operating_Reserves_at_Closing | CL2: Other_at_Closing | CM2: SPONSOR_EQUITY_FUTURE_FUNDING | CN2: Property_Cash_Flow_Future_Funding | CO2: Preferred_Equity_Future_Funding | CP2: Other_Source_of_Future_Funding | CQ2: Soft_Costs_Future_Funding | CR2: Hard_Costs_Future_Funding | CS2: TI_LC_Future_Funding | CT2: Capex_Future_Funding | CU2: Operating _Reserves_Future_Funding | CV2: Other_Future_Funding | CW2: Cash Management | CX2: Trigger | CY2: Cash Management Cure | CZ2: Trustee | DA2: Counsel | DB2: In-Place NOI | DC2: In-Place DSCR | DD2: Untrended NOI | DE2: Untrended DSCR | DF2: Trended NOI | DG2: Trended DSCR
A3: MaSH-3410443 | B3: 67692 | C3: Project Sequoia | D3: N/A | E3: JS | F3: AR | G3: 45091 | H3: 45098 | I3: 45105 | J3: 44762 | K3: 45105 | L3: Blackstone | M3: Morgan Stanley | N3: Morgan Stanley | O3: Morgan Stanley | Q3: Morgan Stanley | R3: Morgan Stanley | S3: Keybank | T3: Industrial | U3: 68 | V3: Acquisition | W3: A Note | X3: 49 | Y3: 45513 | Z3: 3 | AA3: 12 | AB3: 46608 | AC3: 49 | AD3: =IF(NOT(ISNUMBER(Y3)),"N/A",IF(OR(Z3=0,Y3>=TODAY()),Y3,_xlfn.LET(_xlpm.ExtLen,DATEDIF(Y3,AB3,"m")/Z3,_xlpm.k,ROUNDUP(DATEDIF(Y3,TODAY(),"m")/_xlpm.ExtLen,0),_xlpm.d,EDATE(Y3,_xlpm.k*_xlpm.ExtLen),MIN(AB3,IF(_xlpm.d<TODAY(),EDATE(Y3,(_xlpm.k+1)*_xlpm.ExtLen),_xlpm.d))))) -> 46608 | AE3: Interest Only | AF3: 1 | AG3: 49 | AK3: 1 | AL3: Adjustable rate | AM3: Actual/360 | AN3: 0.0514 | AO3: SOFR Term 1 month | AP3: 0.024 | AQ3: N/A | AR3: N/A | AS3: 0 | AT3: 0 | AU3: 0 | AV3: No Rounding | AW3: N/A | AX3: SOFR - US Govt Securities | AY3: -2BD | AZ3: 45104 | BA3: 45105 | BB3: 45116 | BC3: 45116 | BD3: Monthly | BE3: 1 | BF3: 25 | BG3: 25th – 24th | BH3: 45119 | BI3: Monthly | BL3: 3.0% of Principal and Interest | BM3: 5 | BN3: Monthly | BP3: 0 | BQ3: 0 | BR3: 0.0385 | BS3: 1.4328208e+09 | BT3: 12 | BU3: N/A | BV3: Other | BW3: subject to minimum interest of $5,250,000 on our senior participation | BX3: 45127 | BY3: 45513 | BZ3: ACH | CA3: 0.03 | CB3: 1 | CC3: Mezzanine | CD3: 0 | CE3: 3003768270 | CS3: 61680760 | CY3: DY ≥ threshold for 2 consecutive quarters; or paydown of the DY Trigger Cure Prepayment Amount (immediate cure); or delivery of a DY Trigger Cure Guaranty for that amount. EoD trigger: cure of the EoD. | CZ3: N/A | DA3: Gibson Dunn
A4: MaSH-3256633 | B4: 61883 | C4: Project Royale | D4: N/A | E4: JS | F4: AR | G4: 44776 | I4: 44790 | J4: 44687 | K4: 44777 | L4: Blackstone and Vesper Holdings | M4: Morgan Stanley | N4: Morgan Stanley | O4: Morgan Stanley | Q4: Morgan Stanley | R4: Morgan Stanley | S4: CBRE | T4: Student Housing | U4: 7 | V4: Acquisition | W4: A Note | X4: 21.166667 | Y4: 45421 | Z4: 3 | AA4: 12 | AB4: 46516 | AC4: 21.166667 | AD4: =IF(NOT(ISNUMBER(Y4)),"N/A",IF(OR(Z4=0,Y4>=TODAY()),Y4,_xlfn.LET(_xlpm.ExtLen,DATEDIF(Y4,AB4,"m")/Z4,_xlpm.k,ROUNDUP(DATEDIF(Y4,TODAY(),"m")/_xlpm.ExtLen,0),_xlpm.d,EDATE(Y4,_xlpm.k*_xlpm.ExtLen),MIN(AB4,IF(_xlpm.d<TODAY(),EDATE(Y4,(_xlpm.k+1)*_xlpm.ExtLen),_xlpm.d))))) -> 46516 | AE4: Interest Only | AF4: 1 | AG4: 21.166667 | AK4: 1 | AL4: Adjustable rate | AM4: Actual/360 | AN4: 0.0153 | AO4: SOFR Term 1 month | AP4: 0.0233 | AQ4: N/A | AR4: N/A | AS4: 0 | AT4: 0 | AU4: 0 | AV4: Always Round Up | AW4: 0.001 | AX4: SOFR - US Govt Securities | AY4: -2BD | AZ4: 44776 | BA4: 44757 | BB4: 44782 | BC4: 44782 | BD4: Monthly | BE4: 1 | BF4: 31 | BG4: 1st – last day of month | BH4: 44785 | BI4: Monthly | BL4: 3% of amount due | BM4: 0 | BN4: Monthly | BO4: 44788 | BP4: 0 | BR4: 0.0387 | BS4: 125170404 | BT4: 12 | BU4: 0.025 | BV4: Other | BW4: 30% of loan amount open to prepay; remainder subject to yield maintenance if prepayed before open prepayment date | BX4: 44757 | BY4: 45055 | BZ4: ACH | CA4: 0.03 | CB4: 0 | CC4: N/A | CD4: 0 | CE4: 386500000 | CF4: 7600000 | CW4: Hard Lockbox | CX4: DY below 5.25% | CY4: DY ≥ threshold for 2 consecutive quarters; or paydown (pro rata mortgage/mezz) to restore the threshold (immediate cure); or posting cash/LC equal to that paydown amount as Debt Yield Cure Collateral. EoD trigger: cure of the EoD. | CZ4: N/A | DA4: Gibson Dunn
A5: MaSH-3258016 | B5: 61973 | C5: Lakefront North | D5: N/A | E5: JS | F5: DP | G5: 44881 | I5: 44915 | J5: 44915 | K5: 44910 | L5: Howard Hughes | M5: Sixth Street | N5: Sixth Street | O5: JLL Capital Markets | R5: Sixth Street | S5: Captial Crossing | T5: Office | U5: 1 | V5: Refinance | W5: A Note | X5: 119.76667 | Y5: 48556 | Z5: 0 | AA5: 0 | AB5: 48556 | AC5: 119.76667 | AD5: =IF(NOT(ISNUMBER(Y5)),"N/A",IF(OR(Z5=0,Y5>=TODAY()),Y5,_xlfn.LET(_xlpm.ExtLen,DATEDIF(Y5,AB5,"m")/Z5,_xlpm.k,ROUNDUP(DATEDIF(Y5,TODAY(),"m")/_xlpm.ExtLen,0),_xlpm.d,EDATE(Y5,_xlpm.k*_xlpm.ExtLen),MIN(AB5,IF(_xlpm.d<TODAY(),EDATE(Y5,(_xlpm.k+1)*_xlpm.ExtLen),_xlpm.d))))) -> 48556 | AE5: Interest Only | AF5: 1 | AG5: 119.76667 | AK5: 0 | AL5: Fixed Rate | AM5: Actual/360 | AN5: 0.0369 | AO5: 10 Year Treasury | AP5: N/A | AQ5: N/A | AR5: N/A | AS5: N/A | AT5: N/A | AU5: N/A | AV5: N/A | AW5: N/A | AX5: N/A | AY5: N/A | AZ5: 44927 | BA5: 44910 | BB5: 44962 | BC5: 44962 | BD5: Monthly | BE5: 1 | BF5: 8 | BG5: 8th – 7th | BH5: N/A | BI5: N/A | BL5: 5% of amount due | BM5: 0 | BN5: No Reset | BP5: N/A | BR5: N/A | BS5: N/A | BT5: N/A | BV5: Yield Maintenance | BW5: yield maintenance for first 102 months | BX5: 44910 | BY5: 48014 | BZ5: ACH | CA5: 0.05 | CB5: 0 | CC5: N/A | CD5: 0 | CE5: 47800000 | CF5: 780000 | CG5: 3908353 | CI5: 2578591 | CJ5: 16671766 | CK5: 2382748 | CN5: 20285364 | CS5: 15650152 | CU5: 4635211.6 | CW5: Hard Lockbox | CX5: DY below 8.00% | CY5: DY ≥ 10.0% for 2 consecutive quarters after the trigger (one-time option to cure with cash collateral sufficient to meet the DY); EoD: cure of the EoD to Lender's satisfaction; reserve shortfall: replenishment of the reserves. | CZ5: N/A | DA5: Brownstein
A6: MaSH-3339577 | B6: 64734 | C6: Project Balboa | D6: N/A | E6: JS | F6: DP | G6: 44929 | H6: 44606 | I6: 44924 | J6: 44936 | K6: 44936 | L6: Balboa Retail Partners | M6: PCCP | N6: PCCP | O6: PCCP | Q6: PCCP | R6: PCCP | S6: Situs | T6: Retail | U6: 2 | V6: Acquisition | W6: A Note | X6: 34.7 | Y6: 45992 | Z6: 2 | AA6: 12 | AB6: 46722 | AC6: 34.7 | AD6: =IF(NOT(ISNUMBER(Y6)),"N/A",IF(OR(Z6=0,Y6>=TODAY()),Y6,_xlfn.LET(_xlpm.ExtLen,DATEDIF(Y6,AB6,"m")/Z6,_xlpm.k,ROUNDUP(DATEDIF(Y6,TODAY(),"m")/_xlpm.ExtLen,0),_xlpm.d,EDATE(Y6,_xlpm.k*_xlpm.ExtLen),MIN(AB6,IF(_xlpm.d<TODAY(),EDATE(Y6,(_xlpm.k+1)*_xlpm.ExtLen),_xlpm.d))))) -> 46357 | AE6: Interest Only | AF6: 1 | AG6: 34.7 | AK6: 0 | AL6: Adjustable Rate | AM6: Actual/360 | AN6: 0.04 | AO6: SOFR Term 1 month | AP6: 0.035 | AQ6: N/A | AR6: N/A | AS6: 0.001857 | AT6: 0.001857 | AU6: 0.005 | AV6: No Rounding | AW6: N/A | AX6: SOFR - US Govt Securities | AY6: -2BD | AZ6: =BA6-1 -> 44935 | BA6: 44936 | BB6: 44958 | BC6: 44958 | BD6: Monthly | BE6: 1 | BF6: 1 | BG6: 1st – last day of month | BH6: 44956 | BI6: Monthly | BL6: 5% of amount due | BM6: 0 | BN6: Monthly | BO6: 44927 | BP6: 0.025 | BR6: 0.04 | BS6: 42660000 | BT6: 36 | BV6: Other | BW6: open prepayment, but subject to minimum interest of $5,250,000 on our senior participation | BX6: 44936 | BY6: 45992 | BZ6: ACH | CA6: 0.05 | CB6: 0 | CC6: N/A | CD6: 1 | CE6: 64546000 | CF6: 1594000 | CM6: 6495000 | CS6: 5870000 | CT6: 12990000 | CW6: N/A | CX6: N/A | CY6: N/A | CZ6: N/A | DA6: Brownstein
A7: MaSH-3534532 | B7: 102039 | C7: Project Cubic | D7: N/A | E7: JS | G7: 45315 | H7: 45350 | I7: 45358 | J7: 44589 | K7: 45358 | L7: Blackstone | M7: Citi | N7: Citi | O7: Citi | Q7: Clarion Partners | R7: Citi | S7: Keybank | T7: Industrial | U7: 78 | V7: Refinance | W7: A Note | X7: 34.7 | Y7: 45697 | Z7: 3 | AA7: 12 | AB7: 46792 | AC7: 11 | AD7: =IF(NOT(ISNUMBER(Y7)),"N/A",IF(OR(Z7=0,Y7>=TODAY()),Y7,_xlfn.LET(_xlpm.ExtLen,DATEDIF(Y7,AB7,"m")/Z7,_xlpm.k,ROUNDUP(DATEDIF(Y7,TODAY(),"m")/_xlpm.ExtLen,0),_xlpm.d,EDATE(Y7,_xlpm.k*_xlpm.ExtLen),MIN(AB7,IF(_xlpm.d<TODAY(),EDATE(Y7,(_xlpm.k+1)*_xlpm.ExtLen),_xlpm.d))))) -> 46427 | AE7: Interest Only | AF7: 1 | AG7: 35 | AK7: 1 | AL7: Adjustable rate | AM7: Actual/360 | AN7: 0.0532 | AO7: SOFR Term 1 month | AP7: 0.0169809 | AQ7: N/A | AR7: N/A | AS7: N/A | AT7: N/A | AU7: N/A | AV7: No Rounding | AW7: N/A | AX7: SOFR - US Govt Securities | AY7: -2BD | AZ7: 45365 | BA7: 45366 | BB7: 45391 | BC7: 45391 | BD7: Monthly | BE7: 1 | BF7: 9 | BG7: 9th – 8th | BH7: 45364 | BI7: Monthly | BK7: 0 | BL7: 3% of Principal and Interest | BM7: 5 | BN7: Monthly | BP7: 0 | BQ7: 0 | BR7: 0.045 | BS7: 5.6808504e+08 | BT7: 12 | BU7: 0.02 | BV7: Other | BW7: 30% of loan amount open to prepay; remainder subject to yield maintenance if prepayed before open prepayment date | BX7: 44589 | BY7: 44966 | BZ7: ACH | CA7: 0.03 | CB7: 0 | CC7: N/A | CD7: 0 | CF7: 23518178 | CL7: 1.0920877e+09 | CW7: Soft Lockbox | CX7: DY below 5.20% | CY7: DY ≥ threshold for 2 consecutive quarters; or paydown of the DY Trigger Cure Prepayment Amount (mortgage and mezz pro rata, immediate cure); or posting cash/LC as Debt Yield Cure Collateral. EoD trigger: cure of the EoD. | CZ7: N/A | DA7: Gibson Dunn
A8: MaSH-3337170 | B8: 64681 | C8: Project Eyas | D8: N/A | E8: JS | F8: AR | G8: 44916 | H8: 44909 | I8: 44924 | J8: 44705 | K8: 44922 | L8: Brookfield | M8: Goldman Sachs | N8: Goldman Sachs | O8: Goldman Sachs | Q8: Goldman Sachs | R8: Goldman Sachs | S8: Midland | T8: Student Housing | U8: 11 | V8: Acquisition | W8: A Note | X8: 29.133333 | Y8: 45809 | Z8: 2 | AA8: 12 | AB8: 46539 | AC8: 29.133333 | AD8: =IF(NOT(ISNUMBER(Y8)),"N/A",IF(OR(Z8=0,Y8>=TODAY()),Y8,_xlfn.LET(_xlpm.ExtLen,DATEDIF(Y8,AB8,"m")/Z8,_xlpm.k,ROUNDUP(DATEDIF(Y8,TODAY(),"m")/_xlpm.ExtLen,0),_xlpm.d,EDATE(Y8,_xlpm.k*_xlpm.ExtLen),MIN(AB8,IF(_xlpm.d<TODAY(),EDATE(Y8,(_xlpm.k+1)*_xlpm.ExtLen),_xlpm.d))))) -> 46539 | AE8: Interest Only | AF8: 1 | AG8: 29.133333 | AK8: 0 | AL8: Adjustable Rate | AM8: Actual/360 | AN8: 0.04 | AO8: SOFR Term 1 month | AP8: 0.0228 | AQ8: N/A | AR8: N/A | AS8: 0 | AT8: 0 | AU8: 0 | AV8: No Rounding | AW8: N/A | AX8: SOFR - US Govt Securities | AY8: -2BD | AZ8: 44922 | BA8: 44922 | BB8: 44927 | BC8: 44927 | BD8: Monthly | BE8: 1 | BF8: 9 | BG8: 9th – 8th | BH8: 44924 | BI8: Monthly | BL8: 3% of unpaid interest | BM8: 5 | BN8: Monthly | BO8: 44927 | BP8: 0 | BR8: 0.0525 | BS8: 220701770 | BT8: 12 | BU8: 0.0275 | BV8: Other | BW8: 12 months yield maintenance with the first 20% of the fully funded loan amount repaid at par. | BX8: 45078 | BY8: 45809 | BZ8: ACH | CA8: 0.03 | CB8: 0 | CC8: N/A | CD8: 1 | CE8: 346930000 | CF8: 6900000 | CM8: 3625000 | CT8: 14498856 | CW8: Soft Lockbox | CX8: DY below 4.50% | CY8: DY ≥ the Low Cash Flow Period Threshold for 2 consecutive fiscal quarters; or delivery of Low Cash Flow Period Threshold Collateral or Letter of Credit (§9.10). Default/Mezz Trigger Periods end on cure of the default. | CZ8: N/A | DA8: Gibson Dunn
A9: MaSH-3340378 | B9: 64777 | C9: Project Stripe | D9: N/A | E9: JS | F9: AR | G9: 44916 | H9: 44909 | I9: 44924 | J9: 44593 | K9: 44925 | L9: Blackstone | M9: Morgan Stanley | N9: Morgan Stanley | O9: Morgan Stanley | Q9: Morgan Stanley | R9: Morgan Stanley | S9: CBRE | T9: Multifamily | U9: 6 | V9: Acquisition | W9: A Note | X9: 13.3 | Y9: 45331 | Z9: 3 | AA9: 12 | AB9: 46427 | AC9: 13.3 | AD9: =IF(NOT(ISNUMBER(Y9)),"N/A",IF(OR(Z9=0,Y9>=TODAY()),Y9,_xlfn.LET(_xlpm.ExtLen,DATEDIF(Y9,AB9,"m")/Z9,_xlpm.k,ROUNDUP(DATEDIF(Y9,TODAY(),"m")/_xlpm.ExtLen,0),_xlpm.d,EDATE(Y9,_xlpm.k*_xlpm.ExtLen),MIN(AB9,IF(_xlpm.d<TODAY(),EDATE(Y9,(_xlpm.k+1)*_xlpm.ExtLen),_xlpm.d))))) -> 46427 | AE9: Interest Only | AF9: 1 | AG9: 13.3 | AK9: 0 | AL9: Adjustable Rate | AM9: Actual/360 | AN9: 0.04 | AO9: SOFR Term 1 month | AP9: 0.018 | AQ9: N/A | AR9: N/A | AS9: 0 | AT9: 0 | AU9: 0 | AV9: Always Round Up | AW9: 0.001 | AX9: SOFR - US Govt Securities | AY9: -2BD | AZ9: 44925 | BA9: 44925 | BB9: 44935 | BC9: 44935 | BD9: Monthly | BE9: 1 | BF9: 1 | BG9: 1st – last day of month | BH9: 44939 | BI9: Monthly | BL9: 3% of amount due | BM9: 0 | BN9: Monthly | BO9: 44941 | BP9: 0 | BR9: 0.05 | BS9: 550600000 | BT9: 12 | BU9: 0.02 | BV9: Other | BW9: 12 months yield maintenance with the first 30% of the fully funded loan amount repaid at par. | BX9: 44925 | BY9: 44966 | BZ9: ACH | CA9: 0.03 | CB9: 0 | CC9: N/A | CD9: 0 | CE9: 848850000 | CF9: 21600000 | CW9: Soft Lockbox | CX9: DY below 4.00% | CY9: DY ≥ threshold for 2 consecutive quarters; or paydown (pro rata mortgage/mezz) to restore the threshold (immediate cure); or posting cash/LC equal to that paydown amount as Debt Yield Cure Collateral. EoD trigger: cure of the EoD. | CZ9: N/A | DA9: Gibson Dunn
A10: MaSH-3687981 | B10: 255488 | C10: Project Bellevue | D10: N/A | E10: JS | F10: CR | G10: 45687 | H10: 45698 | I10: 45720 | J10: 45645 | K10: 45720 | L10: Lubert Adler | M10: Wells Fargo | N10: Wells Fargo | O10: Wells Fargo | Q10: Wells Fargo | R10: Wells Fargo | S10: Wells Fargo | T10: Mixed-Use | U10: 1 | V10: Refinance | W10: A Note | X10: 19 | Y10: 46295 | Z10: 1 | AA10: 12 | AB10: 46660 | AC10: 19 | AD10: =IF(NOT(ISNUMBER(Y10)),"N/A",IF(OR(Z10=0,Y10>=TODAY()),Y10,_xlfn.LET(_xlpm.ExtLen,DATEDIF(Y10,AB10,"m")/Z10,_xlpm.k,ROUNDUP(DATEDIF(Y10,TODAY(),"m")/_xlpm.ExtLen,0),_xlpm.d,EDATE(Y10,_xlpm.k*_xlpm.ExtLen),MIN(AB10,IF(_xlpm.d<TODAY(),EDATE(Y10,(_xlpm.k+1)*_xlpm.ExtLen),_xlpm.d))))) -> 46660 | AE10: I/O then Amortizing | AF10: 1 | AG10: 18 | AH10: 46143 | AI10: 18 | AJ10: 18 | AK10: 0 | AL10: Adjustable rate | AM10: Actual/360 | AN10: 0.0435235 | AO10: SOFR Term 1 month | AP10: 0.04 | AQ10: 0.006 | AR10: N/A | AS10: N/A | AT10: N/A | AU10: N/A | AV10: No Rounding | AW10: N/A | AX10: SOFR - US Govt Securities | AY10: -2BD | AZ10: 45720 | BA10: 45721 | BB10: 45748 | BC10: 45719 | BD10: Monthly | BE10: 1 | BF10: 1 | BG10: 1st – last day of month | BH10: 45744 | BI10: Monthly | BL10: 5% of amount due | BM10: 15 | BN10: Monthly | BP10: 0 | BQ10: 0 | BR10: 0.0416 | BS10: 80000000 | BT10: 19 | BV10: Full Payoff | BW10: No Partial Prepayment | BX10: 45720 | BY10: 46660 | BZ10: ACH | CA10: 0.05 | CB10: 0 | CC10: N/A | CD10: 1 | CE10: 1.2350658e+08 | CG10: 38654210 | CH10: 1.0514658e+08 | CJ10: 1384250.2 | CK10: 32938628 | CL10: 13336704 | CQ10: 15957028 | CR10: 24653578 | CS10: 19542763 | CU10: 2458889.2 | CV10: 5801.84 | CW10: Hard Lockbox | CX10: DSCR below 1.30x or DY below 14.00% | CY10: None – full cash flow sweep for the life of the loan into a Wells Fargo restricted account held as additional collateral (Borrower may request up to $500k aggregate for emergency capex). | CZ10: N/A | DA10: Latham Watkins
A11: MaSH-3773167 | B11: 340674 | C11: Project Fayetteville 2-Pack | D11: N/A | E11: JS | F11: CR | G11: 46008 | H11: 46008 | I11: 46020 | J11: 45968 | K11: 46020 | L11: Valor Residential | M11: Dwight Capital | N11: Dwight Capital | O11: Dwight Capital | R11: Dwight Capital | S11: Dwight Loan Servicing LLC | T11: Multifamily | U11: 2 | V11: Refinance | W11: A Note | X11: 60 | Y11: 47823 | Z11: 0 | AA11: 0 | AB11: 47823 | AC11: 59 | AD11: =IF(NOT(ISNUMBER(Y11)),"N/A",IF(OR(Z11=0,Y11>=TODAY()),Y11,_xlfn.LET(_xlpm.ExtLen,DATEDIF(Y11,AB11,"m")/Z11,_xlpm.k,ROUNDUP(DATEDIF(Y11,TODAY(),"m")/_xlpm.ExtLen,0),_xlpm.d,EDATE(Y11,_xlpm.k*_xlpm.ExtLen),MIN(AB11,IF(_xlpm.d<TODAY(),EDATE(Y11,(_xlpm.k+1)*_xlpm.ExtLen),_xlpm.d))))) -> 47823 | AE11: Interest Only | AF11: 1 | AG11: 60 | AK11: 0 | AL11: Fixed rate | AM11: Actual/360 | AN11: 0.0366 | AO11: 5 Year Treasury | AP11: 0.0251 | AQ11: N/A | AR11: N/A | AS11: N/A | AT11: N/A | AU11: N/A | AV11: N/A | AW11: N/A | AX11: N/A | AY11: N/A | AZ11: =BA11-1 -> 45996 | BA11: 45997 | BB11: 1/6/206 | BC11: 46028 | BD11: Monthly | BE11: 1 | BF11: 6 | BG11: 6th – 5th | BH11: N/A | BI11: N/A | BL11: 5.0% of Principal and Interest | BM11: 15 | BN11: No Reset | BP11: N/A | BQ11: 0 | BR11: N/A | BS11: N/A | BT11: N/A | BU11: N/A | BV11: Other | BW11: 5% (Months 1-12), 4% (Months 13-24), 3% (Months 25-36), 2% (Months 37-48), 1% (Months 49-54), 0% (Months 55-60) | BX11: 45968 | BY11: 46362 | BZ11: ACH | CA11: 0.08 | CB11: 0 | CC11: N/A | CD11: 0 | CE11: 38020000 | CF11: 617500 | CL11: 1362500 | CW11: Springing Lockbox | CX11: DSCR below 0.95x or DY below 7.00% | CY11: Excess cash released to Sponsor only while IO DSCR > 1.15x (~7.3% DY). DSCR < 0.95x covenant breach cured by depositing cash collateral so that (deposit + T3 NOI) / hypothetical debt service ≥ 0.95x. | CZ11: N/A | DA11: Cleary
A12: MaSH-3774814 | B12: 342321 | C12: Mosaic Apartments | D12: N/A | E12: JS | F12: CR | G12: 46008 | H12: 46008 | I12: 46013 | J12: 46013 | K12: 46013 | L12: YYM Partners | M12: Sixth Street | N12: N/A | O12: Dwight Capital | R12: Dwight Capital | S12: Dwight Loan Servicing LLC | T12: Multifamily | U12: 1 | V12: Refinance | W12: A Note | X12: 60 | Y12: 47854 | Z12: 0 | AA12: 0 | AB12: 47854 | AC12: 59 | AD12: =IF(NOT(ISNUMBER(Y12)),"N/A",IF(OR(Z12=0,Y12>=TODAY()),Y12,_xlfn.LET(_xlpm.ExtLen,DATEDIF(Y12,AB12,"m")/Z12,_xlpm.k,ROUNDUP(DATEDIF(Y12,TODAY(),"m")/_xlpm.ExtLen,0),_xlpm.d,EDATE(Y12,_xlpm.k*_xlpm.ExtLen),MIN(AB12,IF(_xlpm.d<TODAY(),EDATE(Y12,(_xlpm.k+1)*_xlpm.ExtLen),_xlpm.d))))) -> 47854 | AE12: Interest Only | AF12: 1 | AG12: 60 | AK12: 0 | AL12: Fixed rate | AM12: Actual/360 | AN12: 0.0366 | AO12: 5 Year Treasury | AP12: 0.0251 | AQ12: N/A | AR12: N/A | AS12: N/A | AT12: N/A | AU12: N/A | AV12: N/A | AW12: N/A | AX12: N/A | AY12: N/A | AZ12: =BA12-1 -> 46027 | BA12: 46028 | BB12: 46059 | BC12: 46059 | BD12: Monthly | BE12: 1 | BF12: 6 | BG12: 6th – 5th | BH12: N/A | BI12: N/A | BL12: 5.0% of Principal and Interest | BM12: 15 | BN12: No Reset | BP12: N/A | BQ12: 0 | BR12: N/A | BS12: N/A | BT12: N/A | BU12: N/A | BV12: Other | BW12: 5% (Months 1-12), 4% (Months 13-24), 3% (Months 25-36), 2% (Months 37-48), 1% (Months 49-54), 0% (Months 55-60) | BX12: 46010 | BY12: 46393 | BZ12: ACH | CA12: 0.1 | CB12: 0 | CC12: N/A | CD12: 0 | CE12: 36200000 | CF12: 1498000 | CL12: 10702000 | CW12: Springing Lockbox | CX12: DSCR below 0.95x or DY below 7.00% | CY12: Excess cash released to Sponsor only while IO DSCR > 1.15x (~7.3% DY). DSCR < 0.95x covenant breach cured by depositing cash collateral to restore the DSCR. | CZ12: N/A | DA12: Cleary
A13: MaSH-3774820 | B13: 342327 | C13: Project Arista | D13: N/A | E13: JS | F13: CR | G13: 46031 | H13: 46036 | I13: 46038 | J13: 46038 | K13: 46041 | L13: Octane Realty & Adept Development | M13: Sixth Street | N13: N/A | O13: Dwight Capital | Q13: Dwight Capital | R13: Dwight Capital | S13: Dwight Loan Servicing LLC | T13: Multifamily | U13: 1 | V13: Refinance | W13: A Note | X13: 60 | Y13: 47885 | Z13: 0 | AA13: 0 | AB13: 47885 | AC13: 59 | AD13: =IF(NOT(ISNUMBER(Y13)),"N/A",IF(OR(Z13=0,Y13>=TODAY()),Y13,_xlfn.LET(_xlpm.ExtLen,DATEDIF(Y13,AB13,"m")/Z13,_xlpm.k,ROUNDUP(DATEDIF(Y13,TODAY(),"m")/_xlpm.ExtLen,0),_xlpm.d,EDATE(Y13,_xlpm.k*_xlpm.ExtLen),MIN(AB13,IF(_xlpm.d<TODAY(),EDATE(Y13,(_xlpm.k+1)*_xlpm.ExtLen),_xlpm.d))))) -> 47885 | AE13: Interest Only | AF13: 1 | AG13: 60 | AK13: 0 | AL13: Fixed rate | AM13: Actual/360 | AN13: 0.0375 | AO13: 5 Year Treasury | AP13: 0.0235 | AQ13: N/A | AR13: N/A | AS13: N/A | AT13: N/A | AU13: N/A | AV13: N/A | AW13: N/A | AX13: N/A | AY13: N/A | AZ13: =BA13-1 -> 46053 | BA13: 46054 | BB13: 46087 | BC13: 46087 | BD13: Monthly | BE13: 1 | BF13: 6 | BG13: 6th – 5th | BH13: N/A | BI13: N/A | BL13: 5.0% of Principal and Interest | BM13: 9 | BN13: No Reset | BP13: N/A | BQ13: 0 | BR13: N/A | BS13: N/A | BT13: N/A | BU13: N/A | BV13: Other | BW13: 5% (Months 1-12), 4% (Months 13-24), 3% (Months 25-36), 0% (Months 37-60) | BX13: 46038 | BY13: 46424 | BZ13: ACH | CA13: 0.1 | CB13: 0 | CC13: N/A | CD13: 0 | CE13: 48225000 | CF13: 1709500 | CK13: 1420360 | CL13: 645140 | CW13: Springing Lockbox | CX13: DSCR below 0.95x or DY below 7.00% | CY13: Excess cash released to Sponsor only while IO DSCR > 1.15x (~7.3% DY). DSCR < 0.95x covenant breach cured by depositing cash collateral so DSCR ≥ 1.00x; collateral held until DSCR ≥ 1.00x for 2 consecutive testing periods. | CZ13: N/A | DA13: Cleary
A14: MaSH-3700986 | B14: 268493 | C14: Project Grand Bay Hotel San Francisco | D14: N/A | E14: AT | F14: CR | G14: 46003 | H14: 46008 | I14: 46021 | J14: 46021 | K14: 46021 | L14: Arden Group | M14: Sixth Street | N14: N/A | O14: Riller Capital | Q14: Riller Capital | R14: Sixth Street | S14: Captial Crossing | T14: Hospitality | U14: 1 | V14: Refinance | W14: A Note | X14: 36 | Y14: 47127 | Z14: 2 | AA14: 12 | AB14: 47857 | AC14: 35 | AD14: =IF(NOT(ISNUMBER(Y14)),"N/A",IF(OR(Z14=0,Y14>=TODAY()),Y14,_xlfn.LET(_xlpm.ExtLen,DATEDIF(Y14,AB14,"m")/Z14,_xlpm.k,ROUNDUP(DATEDIF(Y14,TODAY(),"m")/_xlpm.ExtLen,0),_xlpm.d,EDATE(Y14,_xlpm.k*_xlpm.ExtLen),MIN(AB14,IF(_xlpm.d<TODAY(),EDATE(Y14,(_xlpm.k+1)*_xlpm.ExtLen),_xlpm.d))))) -> 47127 | AE14: Interest Only | AF14: 1 | AG14: =3*12 -> 36 | AK14: 0 | AL14: Adjustable rate | AM14: Actual/360 | AO14: SOFR Term 1 month | AP14: 0.0515 | AQ14: 0.01 | AR14: N/A | AS14: 0.0025 | AT14: 0.005 | AU14: 0.0025 | AV14: Always Round Up | AW14: 0.0001 | AX14: SOFR - US Govt Securities | AY14: -2BD | AZ14: 46022 | BA14: 46023 | BB14: 46062 | BC14: 46090 | BD14: Monthly | BE14: 1 | BF14: 9 | BG14: 9th – 8th | BH14: 46058 | BI14: Monthly | BL14: 3% of Principal and Interest | BM14: 5 | BN14: Monthly | BP14: 0.0335 | BQ14: 0 | BR14: 0.0425 | BS14: 69500000 | BT14: 36 | BV14: Yield Maintenance | BW14: Subject to 24 months of minimum interest calculated on the fully funded loan proceeds | BX14: 46751 | BY14: 47127 | BZ14: ACH | CA14: 0.05 | CB14: 0 | CC14: N/A | CD14: 1 | CE14: 66401287 | CF14: 3398713 | CK14: 2200000 | CO14: 9000000 | CP14: 6000000 | CR14: 25000000 | CW14: Hard Lockbox | CY14: During the initial term, released from cash management once the Property achieves an 8.50% DY for 2 consecutive quarters. | CZ14: N/A | DA14: Simpson Thatcher
A15: MaSH-3776991 | B15: 344498 | C15: Crystal Springs Resort | D15: N/A | E15: JS | F15: CR/PJ | G15: 46128 | H15: 46161 | I15: 46163 | J15: 46163 | K15: =J15 -> 46163 | L15: South Street Partners | M15: Sixth Street | N15: N/A | O15: Blackstone | P15: N/A | Q15: Blackstone | R15: Sixth Street | S15: Keybank | T15: Hospitality | U15: 1 | V15: Acquisition | W15: A Note | X15: 36 | Y15: 47278 | Z15: 2 | AA15: 12 | AB15: 48008 | AC15: 60 | AD15: =IF(NOT(ISNUMBER(Y15)),"N/A",IF(OR(Z15=0,Y15>=TODAY()),Y15,_xlfn.LET(_xlpm.ExtLen,DATEDIF(Y15,AB15,"m")/Z15,_xlpm.k,ROUNDUP(DATEDIF(Y15,TODAY(),"m")/_xlpm.ExtLen,0),_xlpm.d,EDATE(Y15,_xlpm.k*_xlpm.ExtLen),MIN(AB15,IF(_xlpm.d<TODAY(),EDATE(Y15,(_xlpm.k+1)*_xlpm.ExtLen),_xlpm.d))))) -> 47278 | AE15: Interest Only | AF15: 1 | AG15: 36 | AK15: 0 | AL15: Adjustable Rate | AM15: Actual/360 | AN15: 0.0363 | AO15: SOFR Term 1 month | AP15: 0.024 | AQ15: 0.0075 | AR15: N/A | AS15: N/A | AT15: N/A | AU15: N/A | AV15: Always Round Up | AW15: 1e-05 | AX15: SOFR - US Govt Securities | AY15: -2BD | AZ15: =BA15-1 -> 46162 | BA15: =K15 -> 46163 | BB15: 46212 | BC15: =BB15 -> 46212 | BD15: Monthly | BE15: 1 | BF15: 9 | BG15: 9th – 8th | BH15: =BC15 -> 46212 | BI15: Monthly | BL15: 5% of amount due | BM15: 5 | BN15: Monthly | BO15: N/A | BP15: 0.0275 | BQ15: 0 | BR15: 0.04 | BS15: 154000000 | BT15: 36 | BU15: 0.04 | BV15: Yield Maintenance | BW15: 12mo YM upon sale, 18mo YM upon refi | BX15: =K15 -> 46163 | BY15: =AB15 -> 48008 | BZ15: ACH | CA15: 0.05 | CB15: 0 | CC15: N/A | CD15: 0 | CE15: 232000000 | CF15: 6000000 | CI15: 5000000 | CM15: 25000000 | CW15: Soft Lockbox | CX15: Mortgage DY falling below 14.1% during Months 1-12, 15.3% during Months 13-36, 17.0% during first extension term, or 18.5% during second extension term | CY15: Loan exits the cash management sweep upon achieving the applicable Mortgage DY hurdle plus 25 bps (EoD trigger: cure of the EoD). | CZ15: N/A | DA15: Cleary
A16: MaSH-3776993 | B16: 344500 | C16: Alpine Village | D16: N/A | E16: JS | F16: CR | G16: 46218 | H16: 46220 | I16: 46227 | J16: 46227 | K16: =J16 -> 46227 | L16: Alpine Start Development & Cypress Equity Investments | M16: Sixth Street | N16: N/A | O16: Red Cove Capital | Q16: Red Cove Capital | R16: Red Cove Capital | S16: Keybank | T16: Multifamily | U16: 1 | V16: Refinance | W16: A Note | X16: 36 | Y16: 47323 | Z16: 0 | AA16: 0 | AB16: =Y16 -> 47323 | AC16: 36 | AD16: =IF(NOT(ISNUMBER(Y16)),"N/A",IF(OR(Z16=0,Y16>=TODAY()),Y16,_xlfn.LET(_xlpm.ExtLen,DATEDIF(Y16,AB16,"m")/Z16,_xlpm.k,ROUNDUP(DATEDIF(Y16,TODAY(),"m")/_xlpm.ExtLen,0),_xlpm.d,EDATE(Y16,_xlpm.k*_xlpm.ExtLen),MIN(AB16,IF(_xlpm.d<TODAY(),EDATE(Y16,(_xlpm.k+1)*_xlpm.ExtLen),_xlpm.d))))) -> 47323 | AE16: Interest Only | AF16: 1 | AG16: 36 | AK16: 0 | AL16: Fixed Rate | AM16: Actual/360 | AN16: 0.044 | AO16: 3 Year Treasury | AP16: 0.0235 | AQ16: N/A | AR16: N/A | AS16: N/A | AT16: N/A | AU16: N/A | AV16: N/A | AW16: N/A | AX16: N/A | AY16: N/A | AZ16: =BA16-1 -> 46226 | BA16: =K16 -> 46227 | BB16: 46244 | BC16: =BB16 -> 46244 | BD16: Monthly | BE16: 1 | BF16: 9 | BG16: 9th – 8th | BH16: N/A | BI16: N/A | BL16: 0.05 | BM16: 5 | BN16: No Reset | BP16: N/A | BQ16: 0 | BR16: N/A | BS16: N/A | BT16: N/A | BV16: Prepayment Penalty | BW16: 3% (1-9 mo.), 2% (10-18 mo.), 1% (19-33 mo.) | BX16: =K16 -> 46227 | BY16: 47217 | BZ16: ACH | CA16: 0.05 | CB16: 0 | CC16: N/A | CD16: 0 | CW16: Soft Lockbox with springing cash management to begin six month post-closing | CX16: < 7.25% DY, < 1.00x 25-year Amortizing DSCR, EOD | CY16: DSCR < 1.00x (25-yr amort, T3 NOI) cured by depositing cash collateral to restore 1.00x; collateral held until DSCR ≥ 1.00x for 2 consecutive quarterly testing periods. Minimum 7.25% DY must be maintained at all times. | CZ16: CYRUS N. ANSARI, ESQ | DA16: Safarian Choi & Bolstad
A17: MaSH-3773094 | B17: 340601 | C17: Project Highland Portfolio | D17: N/A | E17: AT | F17: HC | G17: 46240 | H17: 46234 | I17: 46241 | J17: 46241 | K17: 46241 | L17: Ashford Hospitality Trust | M17: Sixth Street | N17: N/A | O17: Riller Capital | Q17: Riller Capital | R17: Sixth Street | S17: Keybank | T17: Hospitality | U17: 14 | V17: Refinance | W17: Mezz | X17: 24 | Y17: 46974 | Z17: 3 | AA17: 12 | AB17: 48069 | AC17: 60 | AD17: =IF(NOT(ISNUMBER(Y17)),"N/A",IF(OR(Z17=0,Y17>=TODAY()),Y17,_xlfn.LET(_xlpm.ExtLen,DATEDIF(Y17,AB17,"m")/Z17,_xlpm.k,ROUNDUP(DATEDIF(Y17,TODAY(),"m")/_xlpm.ExtLen,0),_xlpm.d,EDATE(Y17,_xlpm.k*_xlpm.ExtLen),MIN(AB17,IF(_xlpm.d<TODAY(),EDATE(Y17,(_xlpm.k+1)*_xlpm.ExtLen),_xlpm.d))))) -> 46974 | AE17: Interest Only | AF17: 1 | AG17: 60 | AK17: 0 | AL17: Adjustable rate | AM17: Actual/360 | AN17: 0.0365677 | AO17: SOFR Term 1 month | AP17: 0.125 | AQ17: 0.015 | AR17: N/A | AS17: 0.0025 | AT17: 0.0025 | AU17: N/A | AV17: No Rounding | AW17: N/A | AX17: SOFR - US Govt Securities | AY17: -2BD | AZ17: 46248 | BA17: 46249 | BB17: 46274 | BC17: 46274 | BD17: Monthly | BE17: 1 | BF17: 9 | BG17: 9th – 8th | BH17: 46247 | BI17: Monthly | BL17: 4% of Principal and Interest | BM17: 0 | BN17: Monthly | BP17: 0.0325 | BQ17: 0 | BR17: 0.05 | BS17: 80000000 | BT17: 24 | BU17: N/A | BV17: Other | BW17: Minimum Multiple of 1.365x | BX17: 46241 | BY17: 48069 | BZ17: ACH | CA17: 0.04 | CB17: 0 | CC17: N/A | CD17: 0 | CE17: 508059000 | CF17: 13932000 | CL17: 17000000 | CW17: Springing Lockbox | CX17: 9.5% DY for initial term and 10.0% during extension terms | CY17: DY Trigger: DY ≥ Cash Sweep Threshold (9.50% initial term / 10.0% extensions) for 2 consecutive quarters; or a Cash Sweep Cure Payment – cash deposit (incl. Excess Cash Reserve funds) or pro rata mortgage/mezz paydown sized to meet the threshold (plus any Spread Maintenance Premium). EoD / Mezz EoD: cure of the default. §5.11 reporting failure: delivery of compliant reporting showing DY ≥ threshold. | CZ17: N/A | DA17: Simpson Thatcher & Gibson Dunn
A18: MaSH-3780342 | B18: 347849 | C18: Project Prime Care Portfolio Senior Financing | D18: N/A | E18: JS | F18: CR | G18: 46262 | H18: 46259 | I18: 46266 | J18: 46266 | K18: 46266 | L18: Prime Care Properties LLC | M18: Sixth Street | N18: N/A | O18: Starwood Capital | Q18: Starwood Capital | R18: Starwood Capital | S18: Trimont | T18: Senior Housing | U18: 9 | V18: Refinance | W18: A Note | X18: 36 | Y18: 47362 | Z18: 2 | AA18: 12 | AB18: 48092 | AC18: 60 | AD18: =IF(NOT(ISNUMBER(Y18)),"N/A",IF(OR(Z18=0,Y18>=TODAY()),Y18,_xlfn.LET(_xlpm.ExtLen,DATEDIF(Y18,AB18,"m")/Z18,_xlpm.k,ROUNDUP(DATEDIF(Y18,TODAY(),"m")/_xlpm.ExtLen,0),_xlpm.d,EDATE(Y18,_xlpm.k*_xlpm.ExtLen),MIN(AB18,IF(_xlpm.d<TODAY(),EDATE(Y18,(_xlpm.k+1)*_xlpm.ExtLen),_xlpm.d))))) -> 47362 | AE18: Interest Only | AF18: 1 | AG18: 60 | AK18: 0 | AL18: Adjustable rate | AM18: Actual/360 | AN18: 0.0364 | AO18: SOFR Term 1 month | AP18: 0.025 | AQ18: 0.01 | AR18: N/A | AS18: 0.0025 | AT18: 0.0025 | AU18: 0.0015 | AV18: Always Round Up | AW18: 0.001 | AX18: SOFR - US Govt Securities | AY18: -2BD | AZ18: =BA18-1 -> 46265 | BA18: 46266 | BB18: 46296 | BC18: 46327 | BD18: Monthly | BE18: 1 | BF18: 1 | BG18: 1st – last day of month | BH18: 46262 | BI18: Monthly | BL18: 5% of amount due | BM18: 0 | BN18: Monthly | BO18: 46262 | BP18: 0.03 | BQ18: 0 | BR18: 0.06 | BS18: 205000000 | BT18: 36 | BU18: 0.06 | BV18: Yield Maintenance | BW18: 18 months of minimum interest | BX18: 46266 | BY18: 46813 | BZ18: ACH | CA18: 0.05 | CB18: 0 | CC18: N/A | CD18: 0 | CW18: Hard Lockbox | CY18: None – Sunrise-controlled waterfall with all excess cash applied to repay the Mortgage, then the Mezz; no excess cash returned to Borrower until the whole loan is repaid. | CZ18: N/A | DA18: Cleary
A19: MaSH-3768501 | B19: 336008 | C19: Project Scarlet Bay | D19: N/A | E19: JS | F19: CR | G19: 45868 | H19: 45924 | I19: 45926 | J19: 45926 | K19: 45926 | L19: Various | M19: Sixth Street | N19: N/A | O19: Red Cove Capital | Q19: Red Cove Capital | R19: Red Cove Capital | S19: Red Cove Capital | T19: Multifamily | U19: 2 | V19: Construction | W19: Preferred Equity | X19: 36 | Y19: 47438 | Z19: 0 | AA19: 0 | AB19: 48168 | AC19: 50 | AD19: =IF(NOT(ISNUMBER(Y19)),"N/A",IF(OR(Z19=0,Y19>=TODAY()),Y19,_xlfn.LET(_xlpm.ExtLen,DATEDIF(Y19,AB19,"m")/Z19,_xlpm.k,ROUNDUP(DATEDIF(Y19,TODAY(),"m")/_xlpm.ExtLen,0),_xlpm.d,EDATE(Y19,_xlpm.k*_xlpm.ExtLen),MIN(AB19,IF(_xlpm.d<TODAY(),EDATE(Y19,(_xlpm.k+1)*_xlpm.ExtLen),_xlpm.d))))) -> 47438 | AE19: N/A | AF19: N/A | AG19: N/A | AK19: 0 | AL19: N/A | AM19: N/A | AN19: N/A | AO19: N/A | AP19: N/A | AQ19: 0.01 | AR19: N/A | AS19: 0.005 | AT19: N/A | AU19: 0.005 | AV19: N/A | AW19: N/A | AX19: N/A | AY19: N/A | AZ19: N/A | BA19: N/A | BB19: N/A | BC19: N/A | BD19: Ad Hoc | BE19: Ad Hoc | BF19: Ad Hoc | BG19: Ad Hoc | BH19: N/A | BI19: N/A | BL19: N/A | BM19: N/A | BN19: No Reset | BP19: N/A | BQ19: 0 | BR19: N/A | BS19: N/A | BT19: N/A | BV19: Other | BW19: N/A | BX19: N/A | BY19: N/A | CB19: 0 | CC19: N/A | CD19: 1 | CW19: N/A | CX19: N/A | CY19: N/A | CZ19: N/A | DA19: Cleary
A20: MaSH-3773946 | B20: 342718 | C20: Project Royalton Whole Loan | D20: N/A | E20: JP/JS | F20: AR/JS | G20: 46045 | H20: 46036 | I20: 46057 | J20: 46057 | K20: 46057 | L20: Highgate | M20: Sixth Street | N20: N/A | O20: CBRE | Q20: Apollo | R20: Sixth Street | S20: Situs | T20: Hospitality | U20: 1 | V20: Refinance | W20: Vertical Tranche | X20: 36 | Y20: 47158 | Z20: 2 | AA20: 12 | AB20: 47888 | AC20: 60 | AD20: =IF(NOT(ISNUMBER(Y20)),"N/A",IF(OR(Z20=0,Y20>=TODAY()),Y20,_xlfn.LET(_xlpm.ExtLen,DATEDIF(Y20,AB20,"m")/Z20,_xlpm.k,ROUNDUP(DATEDIF(Y20,TODAY(),"m")/_xlpm.ExtLen,0),_xlpm.d,EDATE(Y20,_xlpm.k*_xlpm.ExtLen),MIN(AB20,IF(_xlpm.d<TODAY(),EDATE(Y20,(_xlpm.k+1)*_xlpm.ExtLen),_xlpm.d))))) -> 47158 | AE20: Interest Only | AF20: 1 | AG20: 60 | AK20: 0 | AL20: Adjustable rate | AM20: Actual/360 | AN20: 0.0366 | AO20: SOFR Term 1 month | AP20: 0.076 | AQ20: 0.01 | AR20: 0 | AS20: 0.0025 | AT20: 0.0025 | AU20: 0 | AV20: Always Round Up | AW20: 0.01 | AX20: SOFR - US Govt Securities | AY20: -2BD | AZ20: 46067 | BA20: 46068 | BB20: 46090 | BC20: 46121 | BD20: Monthly | BE20: 1 | BF20: 9 | BG20: 9th – 8th | BH20: 46065 | BI20: Monthly | BL20: 4.5% of amount due | BM20: 0 | BN20: Monthly | BO20: 46065 | BP20: 0.0315 | BQ20: 0 | BR20: 0.05 | BS20: 1.1662289e+08 | BT20: 24 | BU20: 0.05 | BV20: Yield Maintenance | BW20: Permitted at any time, subject to Minimum Interest equal to $46,500,000 less any fees and interest paid to date | BX20: 46057 | BY20: 47158 | BZ20: ACH | CA20: 0.045 | CB20: 0 | CC20: N/A | CD20: 1 | CF20: 7457015 | CG20: 2292752 | CH20: 7028560 | CL20: 120029850 | CM20: 19591748 | CQ20: 7174251 | CR20: 66965900 | CU20: 44291597 | CV20: 160000 | CW20: Hard Lockbox | CX20: DY below 9.0% during extended term | CY20: Pre-Stabilization: sweep in effect until Stabilization (DY > 10% for 2 consecutive fiscal quarters after Substantial Completion). Post-Stabilization DY trigger: DY ≥ Debt Yield Threshold (9% before initial maturity / 10% during extensions) for 2 consecutive fiscal quarters; no paydown or cash cure option. EoD / Mortgage EoD: no EoD continuing. Guarantor bankruptcy: Bankruptcy Event no longer continuing. | CZ20: N/A | DA20: Cleary
A21: MaSH-3773946 | B21: 341453 | C21: Project Royalton Levered | D21: N/A | E21: JP/JS | F21: AR/JS | G21: 46045 | H21: 46036 | I21: 46057 | J21: 46057 | K21: 46057 | L21: Highgate | M21: Sixth Street | N21: N/A | O21: CBRE | Q21: Apollo | R21: Sixth Street | S21: Situs | T21: Hospitality | U21: 1 | V21: Refinance | W21: B Note | X21: 36 | Y21: 47158 | Z21: 2 | AA21: 12 | AB21: 47888 | AC21: 60 | AD21: =IF(NOT(ISNUMBER(Y21)),"N/A",IF(OR(Z21=0,Y21>=TODAY()),Y21,_xlfn.LET(_xlpm.ExtLen,DATEDIF(Y21,AB21,"m")/Z21,_xlpm.k,ROUNDUP(DATEDIF(Y21,TODAY(),"m")/_xlpm.ExtLen,0),_xlpm.d,EDATE(Y21,_xlpm.k*_xlpm.ExtLen),MIN(AB21,IF(_xlpm.d<TODAY(),EDATE(Y21,(_xlpm.k+1)*_xlpm.ExtLen),_xlpm.d))))) -> 47158 | AE21: Interest Only | AF21: 1 | AG21: 60 | AK21: 0 | AL21: Adjustable rate | AM21: Actual/360 | AN21: 0.0366 | AO21: SOFR Term 1 month | AP21: 0.142 | AQ21: 0.01 | AR21: 0 | AS21: 0.0025 | AT21: 0.0025 | AU21: 0 | AV21: Always Round Up | AW21: 0.01 | AX21: SOFR - US Govt Securities | AY21: -2BD | AZ21: 46067 | BA21: 46068 | BB21: 46090 | BC21: 46121 | BD21: Monthly | BE21: 1 | BF21: 9 | BG21: 9th – 8th | BH21: 46065 | BI21: Monthly | BL21: 4.5% of amount due | BM21: 0 | BN21: Monthly | BO21: 46065 | BP21: 0.0315 | BQ21: 0 | BR21: =BR20 -> 0.05 | BS21: =BS20 -> 1.1662289e+08 | BT21: =BT20 -> 24 | BV21: Yield Maintenance | BW21: Permitted at any time, subject to Minimum Interest equal to $46,500,000 less any fees and interest paid to date | BX21: 46057 | BY21: 47158 | BZ21: ACH | CA21: 0.045 | CB21: 0 | CC21: N/A | CD21: 1 | CF21: 7457015 | CG21: 2292752 | CH21: 7028560 | CL21: 120029850 | CM21: 19591748 | CQ21: 7174251 | CR21: 66965900 | CU21: 44291597 | CV21: 160000 | CW21: Hard Lockbox | CX21: DY below 9.0% during extended term | CY21: Pre-Stabilization: sweep in effect until Stabilization (DY > 10% for 2 consecutive fiscal quarters after Substantial Completion). Post-Stabilization DY trigger: DY ≥ Debt Yield Threshold (9% before initial maturity / 10% during extensions) for 2 consecutive fiscal quarters; no paydown or cash cure option. EoD / Mortgage EoD: no EoD continuing. Guarantor bankruptcy: Bankruptcy Event no longer continuing. | CZ21: N/A | DA21: Cleary
A22: MaSH-3570618 | B22: 138125 | C22: Project Hearthstone Land | D22: N/A | E22: JS | G22: 45471 | H22: 45504 | I22: 45525 | J22: 45525 | K22: 45527 | L22: Various | M22: Hearthstone | N22: N/A | O22: Hearthstone | P22: Hearthstone | Q22: Hearthstone | R22: Hearthstone | S22: Hearthstone | T22: Land | U22: 13 | V22: Platform | W22: Common Equity | Y22: 47330 | Z22: 0 | AA22: 0 | AB22: =Y22 -> 47330 | AC22: 60 | AD22: =IF(NOT(ISNUMBER(Y22)),"N/A",IF(OR(Z22=0,Y22>=TODAY()),Y22,_xlfn.LET(_xlpm.ExtLen,DATEDIF(Y22,AB22,"m")/Z22,_xlpm.k,ROUNDUP(DATEDIF(Y22,TODAY(),"m")/_xlpm.ExtLen,0),_xlpm.d,EDATE(Y22,_xlpm.k*_xlpm.ExtLen),MIN(AB22,IF(_xlpm.d<TODAY(),EDATE(Y22,(_xlpm.k+1)*_xlpm.ExtLen),_xlpm.d))))) -> 47330 | AE22: N/A | AF22: N/A | AG22: N/A | AK22: 0 | AL22: Fixed | AM22: N/A | AN22: N/A | AO22: N/A | AP22: N/A | AQ22: N/A | AR22: N/A | AS22: N/A | AT22: N/A | AU22: N/A | AV22: N/A | AW22: N/A | AX22: N/A | AY22: N/A | AZ22: =BA22-1 -> 45897 | BA22: 45898 | BB22: 45910 | BC22: 45910 | BD22: Monthly | BE22: 1 | BF22: 10 | BG22: 10th – 9th | BH22: N/A | BI22: N/A | BL22: N/A | BM22: N/A | BN22: No Reset | BP22: N/A | BR22: N/A | BS22: N/A | BT22: N/A | BV22: Other | BW22: N/A | BX22: N/A | BY22: N/A | CD22: 0 | CW22: Hard Lockbox | CX22: DY below 9.0% during extended term | CY22: Pre-Stabilization: sweep in effect until Stabilization (DY > 10% for 2 consecutive fiscal quarters after Substantial Completion). Post-Stabilization DY trigger: DY ≥ Debt Yield Threshold (9% before initial maturity / 10% during extensions) for 2 consecutive fiscal quarters; no paydown or cash cure option. EoD / Mortgage EoD: no EoD continuing. Guarantor bankruptcy: Bankruptcy Event no longer continuing. | CZ22: N/A | DA22: Cleary
A23: MaSH-3777002 | B23: 344509 | C23: HLTN 2026-DPLO - Class B | D23: 40446RAC2 | E23: JS | F23: CR/PJ | G23: 46110 | H23: 46118 | I23: 46122 | J23: 46133 | K23: 46133 | L23: Trinity Real Estate Investment / UBS | M23: JP Morgan / Citi | N23: JP Morgan / Citi | O23: JP Morgan / Citi | P23: KeyBank / Green Loan Services | Q23: Various | R23: Computershare Trust Company, National Association. | S23: KeyBank | T23: Hospitality | U23: 1 | V23: Refinance | W23: Securitization | X23: 23.6 | Y23: 46852 | Z23: 3 | AA23: 12 | AB23: 47947 | AC23: 60 | AD23: =IF(NOT(ISNUMBER(Y23)),"N/A",IF(OR(Z23=0,Y23>=TODAY()),Y23,_xlfn.LET(_xlpm.ExtLen,DATEDIF(Y23,AB23,"m")/Z23,_xlpm.k,ROUNDUP(DATEDIF(Y23,TODAY(),"m")/_xlpm.ExtLen,0),_xlpm.d,EDATE(Y23,_xlpm.k*_xlpm.ExtLen),MIN(AB23,IF(_xlpm.d<TODAY(),EDATE(Y23,(_xlpm.k+1)*_xlpm.ExtLen),_xlpm.d))))) -> 46852 | AE23: Interest Only | AF23: 1 | AG23: 24 | AK23: 0 | AL23: Adjustable rate | AM23: Actual/360 | AN23: 0.0365 | AO23: SOFR Term 1 month | AP23: 0.02 | AQ23: N/A | AR23: N/A | AS23: N/A | AT23: N/A | AU23: N/A | AV23: No Rounding | AW23: N/A | AX23: SOFR - US Govt Securities | AY23: -2BD | AZ23: =BA23-1 -> 46132 | BA23: 46133 | BB23: 46151 | BC23: 46151 | BD23: Monthly | BE23: 1 | BF23: 15 | BG23: 15th – 14th | BH23: 46151 | BI23: Monthly | BL23: N/A | BM23: N/A | BN23: Monthly | BO23: 46151 | BP23: 0 | BR23: 0.0444 | BS23: 600000000 | BT23: 24 | BU23: N/A | BV23: Other | BW23: Spread maintenance for first 12 months | BX23: 46133 | BY23: 46486 | CA23: 0.03 | CB23: 0 | CC23: N/A | CD23: 0 | CW23: Springing Lockbox | CX23: <6.70% DY for two consecutive quarters over the first 12 months and ii) <7.50% DY for two consecutive quarters thereafter | CY23: DY Trigger: DY ≥ the Debt Yield Threshold (6.70% first 12 months / 7.50% thereafter) for 2 consecutive quarters; or immediate cure by prepayment (incl. any Prepayment Premium) and/or a letter of credit sized to meet the threshold. EoD: Lender accepts cure (sole discretion); Manager Trigger: replacement with a Qualified Manager. Bankruptcy Event: not curable. | CZ23: Computershare Trust Company, National Association. | DA23: N/A
A24: MaSH-3777002 | B24: 344509 | C24: HLTN 2026-DPLO - Class C | D24: 40446RAE8 | E24: JS | F24: CR/PJ | G24: 46110 | H24: 46118 | I24: 46122 | J24: 46133 | K24: 46133 | L24: Trinity Real Estate Investment / UBS | M24: JP Morgan / Citi | N24: JP Morgan / Citi | O24: JP Morgan / Citi | P24: KeyBank / Green Loan Services | Q24: Various | R24: Computershare Trust Company, National Association. | S24: KeyBank | T24: Hospitality | U24: 1 | V24: Refinance | W24: Securitization | X24: 23.6 | Y24: 46852 | Z24: 3 | AA24: 12 | AB24: 47947 | AC24: 60 | AD24: =IF(NOT(ISNUMBER(Y24)),"N/A",IF(OR(Z24=0,Y24>=TODAY()),Y24,_xlfn.LET(_xlpm.ExtLen,DATEDIF(Y24,AB24,"m")/Z24,_xlpm.k,ROUNDUP(DATEDIF(Y24,TODAY(),"m")/_xlpm.ExtLen,0),_xlpm.d,EDATE(Y24,_xlpm.k*_xlpm.ExtLen),MIN(AB24,IF(_xlpm.d<TODAY(),EDATE(Y24,(_xlpm.k+1)*_xlpm.ExtLen),_xlpm.d))))) -> 46852 | AE24: Interest Only | AF24: 1 | AG24: 24 | AK24: 0 | AL24: Adjustable rate | AM24: Actual/360 | AN24: 0.0365 | AO24: SOFR Term 1 month | AP24: 0.0225 | AQ24: N/A | AR24: N/A | AS24: N/A | AT24: N/A | AU24: N/A | AV24: No Rounding | AW24: N/A | AX24: SOFR - US Govt Securities | AY24: -2BD | AZ24: =BA24-1 -> 46132 | BA24: 46133 | BB24: 46151 | BC24: 46151 | BD24: Monthly | BE24: 1 | BF24: 15 | BG24: 15th – 14th | BH24: 46151 | BI24: Monthly | BL24: N/A | BM24: N/A | BN24: Monthly | BO24: 46151 | BP24: 0 | BR24: 0.0444 | BS24: 600000000 | BT24: 24 | BU24: N/A | BV24: Other | BW24: Spread maintenance for first 12 months | BX24: 46133 | BY24: 46486 | CA24: 0.03 | CB24: 0 | CC24: N/A | CD24: 0 | CW24: Springing Lockbox | CX24: <6.70% DY for two consecutive quarters over the first 12 months and ii) <7.50% DY for two consecutive quarters thereafter | CY24: =CY23 -> DY Trigger: DY ≥ the Debt Yield Threshold (6.70% first 12 months / 7.50% thereafter) for 2 consecutive quarters; or immediate cure by prepayment (incl. any Prepayment Premium) and/or a letter of credit sized to meet the threshold. EoD: Lender accepts cure (sole discretion); Manager Trigger: replacement with a Qualified Manager. Bankruptcy Event: not curable. | CZ24: Computershare Trust Company, National Association. | DA24: N/A
A25: MaSH-3777002 | B25: 344509 | C25: HLTN 2026-DPLO - Class D | D25: 40446RAG3 | E25: JS | F25: CR/PJ | G25: 46110 | H25: 46118 | I25: 46122 | J25: 46133 | K25: 46133 | L25: Trinity Real Estate Investment / UBS | M25: JP Morgan / Citi | N25: JP Morgan / Citi | O25: JP Morgan / Citi | P25: KeyBank / Green Loan Services | Q25: Various | R25: Computershare Trust Company, National Association. | S25: KeyBank | T25: Hospitality | U25: 1 | V25: Refinance | W25: Securitization | X25: 23.6 | Y25: 46852 | Z25: 3 | AA25: 12 | AB25: 47947 | AC25: 60 | AD25: =IF(NOT(ISNUMBER(Y25)),"N/A",IF(OR(Z25=0,Y25>=TODAY()),Y25,_xlfn.LET(_xlpm.ExtLen,DATEDIF(Y25,AB25,"m")/Z25,_xlpm.k,ROUNDUP(DATEDIF(Y25,TODAY(),"m")/_xlpm.ExtLen,0),_xlpm.d,EDATE(Y25,_xlpm.k*_xlpm.ExtLen),MIN(AB25,IF(_xlpm.d<TODAY(),EDATE(Y25,(_xlpm.k+1)*_xlpm.ExtLen),_xlpm.d))))) -> 46852 | AE25: Interest Only | AF25: 1 | AG25: 24 | AK25: 0 | AL25: Adjustable rate | AM25: Actual/360 | AN25: 0.0365 | AO25: SOFR Term 1 month | AP25: 0.0275 | AQ25: N/A | AR25: N/A | AS25: N/A | AT25: N/A | AU25: N/A | AV25: No Rounding | AW25: N/A | AX25: SOFR - US Govt Securities | AY25: -2BD | AZ25: =BA25-1 -> 46132 | BA25: 46133 | BB25: 46151 | BC25: 46151 | BD25: Monthly | BE25: 1 | BF25: 15 | BG25: 15th – 14th | BH25: 46151 | BI25: Monthly | BL25: N/A | BM25: N/A | BN25: Monthly | BO25: 46151 | BP25: 0 | BR25: 0.0444 | BS25: 600000000 | BT25: 24 | BU25: N/A | BV25: Other | BW25: Spread maintenance for first 12 months | BX25: 46133 | BY25: 46486 | CA25: 0.03 | CB25: 0 | CC25: N/A | CD25: 0 | CW25: Springing Lockbox | CX25: <6.70% DY for two consecutive quarters over the first 12 months and ii) <7.50% DY for two consecutive quarters thereafter | CY25: =CY23 -> DY Trigger: DY ≥ the Debt Yield Threshold (6.70% first 12 months / 7.50% thereafter) for 2 consecutive quarters; or immediate cure by prepayment (incl. any Prepayment Premium) and/or a letter of credit sized to meet the threshold. EoD: Lender accepts cure (sole discretion); Manager Trigger: replacement with a Qualified Manager. Bankruptcy Event: not curable. | CZ25: Computershare Trust Company, National Association. | DA25: N/A
A26: MaSH-3777674 | B26: 345181 | C26: KSL 2026-HT3 - Class B | D26: 48269AAC6 | E26: JS | F26: CR/PJ | G26: 46149 | H26: 46161 | I26: 46163 | J26: 46188 | K26: 46188 | L26: KSL Capital Partners | M26: Wells Fargo | N26: Wells Fargo | O26: Wells Fargo | Q26: Various | R26: Computershare Trust Company | S26: Trimont | T26: Hospitality | U26: 12 | V26: Refinance | W26: Securitization | X26: 23.8 | Y26: 46913 | Z26: 3 | AA26: 12 | AB26: 48008 | AC26: 60 | AD26: =IF(NOT(ISNUMBER(Y26)),"N/A",IF(OR(Z26=0,Y26>=TODAY()),Y26,_xlfn.LET(_xlpm.ExtLen,DATEDIF(Y26,AB26,"m")/Z26,_xlpm.k,ROUNDUP(DATEDIF(Y26,TODAY(),"m")/_xlpm.ExtLen,0),_xlpm.d,EDATE(Y26,_xlpm.k*_xlpm.ExtLen),MIN(AB26,IF(_xlpm.d<TODAY(),EDATE(Y26,(_xlpm.k+1)*_xlpm.ExtLen),_xlpm.d))))) -> 46913 | AE26: Interest Only | AF26: 1 | AG26: 24 | AK26: 0 | AL26: Adjustable rate | AM26: Actual/360 | AN26: 0.0362 | AO26: SOFR Term 1 month | AP26: 0.018 | AQ26: N/A | AR26: N/A | AS26: N/A | AT26: N/A | AU26: N/A | AV26: No Rounding | AW26: N/A | AX26: SOFR - US Govt Securities | AY26: -2BD | AZ26: =BA26-1 -> 46187 | BA26: 46188 | BB26: 46218 | BC26: 46218 | BD26: Monthly | BE26: 1 | BF26: 15 | BG26: 15th – 14th | BH26: 46218 | BI26: Monthly | BL26: N/A | BM26: N/A | BN26: Monthly | BO26: 46218 | BP26: 0 | BR26: 0.0486085 | BS26: 890000000 | BT26: 24 | BU26: N/A | BV26: Other | BW26: Spread maintenance for first 12 months | BX26: 46188 | BY26: 46553 | CA26: 0.03 | CB26: 0 | CC26: N/A | CD26: 0 | CW26: Springing Lockbox | CX26: i) <6.70% DY for two consecutive quarters over the first 12 months and ii) <7.50% DY for two consecutive quarters thereafter | CY26: DY ≥ the Required Debt Yield for 2 consecutive quarters; or paydown of the DY Trigger Cure Prepayment Amount (immediate cure); or posting cash/LC equal to that amount as Debt Yield Cure Collateral. Borrower may elect to cure early to avoid a Cash Trap Period. | CZ26: Computershare Trust Company | DA26: N/A
A27: MaSH-3777674 | B27: 345181 | C27: KSL 2026-HT3 - Class C | D27: 48269AAE2 | E27: JS | F27: CR/PJ | G27: 46149 | H27: 46161 | I27: 46163 | J27: 46188 | K27: 46188 | L27: KSL Capital Partners | M27: Wells Fargo | N27: Wells Fargo | O27: Wells Fargo | Q27: Various | R27: Computershare Trust Company | S27: Trimont | T27: Hospitality | U27: 12 | V27: Refinance | W27: Securitization | X27: 23.8 | Y27: 46913 | Z27: 3 | AA27: 12 | AB27: 48008 | AC27: 60 | AD27: =IF(NOT(ISNUMBER(Y27)),"N/A",IF(OR(Z27=0,Y27>=TODAY()),Y27,_xlfn.LET(_xlpm.ExtLen,DATEDIF(Y27,AB27,"m")/Z27,_xlpm.k,ROUNDUP(DATEDIF(Y27,TODAY(),"m")/_xlpm.ExtLen,0),_xlpm.d,EDATE(Y27,_xlpm.k*_xlpm.ExtLen),MIN(AB27,IF(_xlpm.d<TODAY(),EDATE(Y27,(_xlpm.k+1)*_xlpm.ExtLen),_xlpm.d))))) -> 46913 | AE27: Interest Only | AF27: 1 | AG27: 24 | AK27: 0 | AL27: Adjustable rate | AM27: Actual/360 | AN27: 0.0362 | AO27: SOFR Term 1 month | AP27: 0.0205 | AQ27: N/A | AR27: N/A | AS27: N/A | AT27: N/A | AU27: N/A | AV27: No Rounding | AW27: N/A | AX27: SOFR - US Govt Securities | AY27: -2BD | AZ27: =BA27-1 -> 46187 | BA27: 46188 | BB27: 46218 | BC27: 46218 | BD27: Monthly | BE27: 1 | BF27: 15 | BG27: 15th – 14th | BH27: 46218 | BI27: Monthly | BL27: N/A | BM27: N/A | BN27: Monthly | BO27: 46218 | BP27: 0 | BR27: 0.0486085 | BS27: 890000000 | BT27: 24 | BU27: N/A | BV27: Other | BW27: Spread maintenance for first 12 months | BX27: 46188 | BY27: 46553 | CA27: 0.03 | CB27: 0 | CC27: N/A | CD27: 0 | CW27: Springing Lockbox | CX27: i) <6.70% DY for two consecutive quarters over the first 12 months and ii) <7.50% DY for two consecutive quarters thereafter | CY27: =CY26 -> DY ≥ the Required Debt Yield for 2 consecutive quarters; or paydown of the DY Trigger Cure Prepayment Amount (immediate cure); or posting cash/LC equal to that amount as Debt Yield Cure Collateral. Borrower may elect to cure early to avoid a Cash Trap Period. | CZ27: Computershare Trust Company | DA27: N/A
A28: MaSH-3777674 | B28: 345181 | C28: KSL 2026-HT3 - Class D | D28: 48269AAG7 | E28: JS | F28: CR/PJ | G28: 46149 | H28: 46161 | I28: 46163 | J28: 46188 | K28: 46188 | L28: KSL Capital Partners | M28: Wells Fargo | N28: Wells Fargo | O28: Wells Fargo | Q28: Various | R28: Computershare Trust Company | S28: Trimont | T28: Hospitality | U28: 12 | V28: Refinance | W28: Securitization | X28: 23.8 | Y28: 46913 | Z28: 3 | AA28: 12 | AB28: 48008 | AC28: 60 | AD28: =IF(NOT(ISNUMBER(Y28)),"N/A",IF(OR(Z28=0,Y28>=TODAY()),Y28,_xlfn.LET(_xlpm.ExtLen,DATEDIF(Y28,AB28,"m")/Z28,_xlpm.k,ROUNDUP(DATEDIF(Y28,TODAY(),"m")/_xlpm.ExtLen,0),_xlpm.d,EDATE(Y28,_xlpm.k*_xlpm.ExtLen),MIN(AB28,IF(_xlpm.d<TODAY(),EDATE(Y28,(_xlpm.k+1)*_xlpm.ExtLen),_xlpm.d))))) -> 46913 | AE28: Interest Only | AF28: 1 | AG28: 24 | AK28: 0 | AL28: Adjustable rate | AM28: Actual/360 | AN28: 0.0362 | AO28: SOFR Term 1 month | AP28: 0.0275 | AQ28: N/A | AR28: N/A | AS28: N/A | AT28: N/A | AU28: N/A | AV28: No Rounding | AW28: N/A | AX28: SOFR - US Govt Securities | AY28: -2BD | AZ28: =BA28-1 -> 46187 | BA28: 46188 | BB28: 46218 | BC28: 46218 | BD28: Monthly | BE28: 1 | BF28: 15 | BG28: 15th – 14th | BH28: 46218 | BI28: Monthly | BL28: N/A | BM28: N/A | BN28: Monthly | BO28: 46218 | BP28: 0 | BR28: 0.0486085 | BS28: 890000000 | BT28: 24 | BU28: N/A | BV28: Other | BW28: Spread maintenance for first 12 months | BX28: 46188 | BY28: 46553 | CA28: 0.03 | CB28: 0 | CC28: N/A | CD28: 0 | CW28: Springing Lockbox | CX28: i) <6.70% DY for two consecutive quarters over the first 12 months and ii) <7.50% DY for two consecutive quarters thereafter | CY28: =CY26 -> DY ≥ the Required Debt Yield for 2 consecutive quarters; or paydown of the DY Trigger Cure Prepayment Amount (immediate cure); or posting cash/LC equal to that amount as Debt Yield Cure Collateral. Borrower may elect to cure early to avoid a Cash Trap Period. | CZ28: Computershare Trust Company | DA28: N/A
A29: MaSH-3779335 | B29: 346842 | C29: AHPT 2026-ATRM - Class B | D29: 00151BAC6 | E29: JS | F29: CR/PJ | G29: 46219 | H29: 46244 | I29: 46244 | J29: 46268 | K29: 46268 | L29: Atrium Hospitality | M29: Wells Fargo | N29: Wells Fargo & Co. | O29: Wells Fargo | Q29: Various | R29: Computershare Trust Company, National Association | S29: Trimont | T29: Hospitality | U29: 18 | V29: Refinance | W29: Securitization | X29: 24.2 | Y29: 47005 | Z29: 3 | AA29: 12 | AB29: 48100 | AC29: 60 | AD29: =IF(NOT(ISNUMBER(Y29)),"N/A",IF(OR(Z29=0,Y29>=TODAY()),Y29,_xlfn.LET(_xlpm.ExtLen,DATEDIF(Y29,AB29,"m")/Z29,_xlpm.k,ROUNDUP(DATEDIF(Y29,TODAY(),"m")/_xlpm.ExtLen,0),_xlpm.d,EDATE(Y29,_xlpm.k*_xlpm.ExtLen),MIN(AB29,IF(_xlpm.d<TODAY(),EDATE(Y29,(_xlpm.k+1)*_xlpm.ExtLen),_xlpm.d))))) -> 47005 | AE29: Interest Only | AF29: 1 | AG29: 24 | AK29: 0 | AL29: Adjustable rate | AM29: Actual/360 | AN29: 0.0363 | AO29: SOFR Term 1 month | AP29: 0.019 | AQ29: N/A | AR29: N/A | AS29: N/A | AT29: N/A | AU29: N/A | AV29: No Rounding | AW29: N/A | AX29: SOFR - US Govt Securities | AY29: -2BD | AZ29: =BA29-1 -> 46267 | BA29: 46268 | BB29: 46310 | BC29: 46310 | BD29: Monthly | BE29: 1 | BF29: 15 | BG29: 15th – 14th | BH29: 46310 | BI29: Monthly | BL29: N/A | BM29: N/A | BN29: Monthly | BO29: 46310 | BP29: 0 | BR29: 0.0603712 | BS29: 565700000 | BT29: 24 | BU29: N/A | BV29: Other | BW29: Spread maintenance for first 12 months | BX29: 46268 | BY29: 46633 | CA29: 0.03 | CB29: 0 | CC29: N/A | CD29: 0 | CW29: Springing Lockbox | CX29: i) <8.25% DY and ii) one or more properties are no longer compliant with respective flag or brand requirements | CY29: DY Trigger: DY ≥ 8.25% as of the prior quarter-end (may be achieved by voluntary paydown); no trigger exists while the Excess Cash Flow Reserve ≥ the DY Trigger Cure Amount. EoD: Lender accepts cure; Manager bankruptcy: replacement manager or dismissal within 90 days; franchise trigger: Replacement Franchise Agreement. | CZ29: Deutsche Bank National Trust Company | DA29: N/A
A30: MaSH-3779335 | B30: 346842 | C30: AHPT 2026-ATRM - Class C | D30: 00151BAE2 | E30: JS | F30: CR/PJ | G30: 46219 | H30: 46244 | I30: 46244 | J30: 46268 | K30: 46268 | L30: Atrium Hospitality | M30: Wells Fargo | N30: Wells Fargo & Co. | O30: Wells Fargo | Q30: Various | R30: Computershare Trust Company, National Association | S30: Trimont | T30: Hospitality | U30: 18 | V30: Refinance | W30: Securitization | X30: 24.2 | Y30: 47005 | Z30: 3 | AA30: 12 | AB30: 48100 | AC30: 60 | AD30: =IF(NOT(ISNUMBER(Y30)),"N/A",IF(OR(Z30=0,Y30>=TODAY()),Y30,_xlfn.LET(_xlpm.ExtLen,DATEDIF(Y30,AB30,"m")/Z30,_xlpm.k,ROUNDUP(DATEDIF(Y30,TODAY(),"m")/_xlpm.ExtLen,0),_xlpm.d,EDATE(Y30,_xlpm.k*_xlpm.ExtLen),MIN(AB30,IF(_xlpm.d<TODAY(),EDATE(Y30,(_xlpm.k+1)*_xlpm.ExtLen),_xlpm.d))))) -> 47005 | AE30: Interest Only | AF30: 1 | AG30: 24 | AK30: 0 | AL30: Adjustable rate | AM30: Actual/360 | AN30: 0.0363 | AO30: SOFR Term 1 month | AP30: 0.022 | AQ30: N/A | AR30: N/A | AS30: N/A | AT30: N/A | AU30: N/A | AV30: No Rounding | AW30: N/A | AX30: SOFR - US Govt Securities | AY30: -2BD | AZ30: =BA30-1 -> 46267 | BA30: 46268 | BB30: 46310 | BC30: 46310 | BD30: Monthly | BE30: 1 | BF30: 15 | BG30: 15th – 14th | BH30: 46310 | BI30: Monthly | BL30: N/A | BM30: N/A | BN30: Monthly | BO30: 46310 | BP30: 0 | BR30: 0.0603712 | BS30: 565700000 | BT30: 24 | BU30: N/A | BV30: Other | BW30: Spread maintenance for first 12 months | BX30: 46268 | BY30: 46633 | CA30: 0.03 | CB30: 0 | CC30: N/A | CD30: 0 | CW30: Springing Lockbox | CX30: i) <8.25% DY and ii) one or more properties are no longer compliant with respective flag or brand requirements | CY30: =CY29 -> DY Trigger: DY ≥ 8.25% as of the prior quarter-end (may be achieved by voluntary paydown); no trigger exists while the Excess Cash Flow Reserve ≥ the DY Trigger Cure Amount. EoD: Lender accepts cure; Manager bankruptcy: replacement manager or dismissal within 90 days; franchise trigger: Replacement Franchise Agreement. | CZ30: Deutsche Bank National Trust Company | DA30: N/A
A31: MaSH-3779335 | B31: 346842 | C31: AHPT 2026-ATRM - Class D | D31: 00151BAG7 | E31: JS | F31: CR/PJ | G31: 46219 | H31: 46244 | I31: 46244 | J31: 46268 | K31: 46268 | L31: Atrium Hospitality | M31: Wells Fargo | N31: Wells Fargo & Co. | O31: Wells Fargo | Q31: Various | R31: Computershare Trust Company, National Association | S31: Trimont | T31: Hospitality | U31: 18 | V31: Refinance | W31: Securitization | X31: 24.2 | Y31: 47005 | Z31: 3 | AA31: 12 | AB31: 48100 | AC31: 60 | AD31: =IF(NOT(ISNUMBER(Y31)),"N/A",IF(OR(Z31=0,Y31>=TODAY()),Y31,_xlfn.LET(_xlpm.ExtLen,DATEDIF(Y31,AB31,"m")/Z31,_xlpm.k,ROUNDUP(DATEDIF(Y31,TODAY(),"m")/_xlpm.ExtLen,0),_xlpm.d,EDATE(Y31,_xlpm.k*_xlpm.ExtLen),MIN(AB31,IF(_xlpm.d<TODAY(),EDATE(Y31,(_xlpm.k+1)*_xlpm.ExtLen),_xlpm.d))))) -> 47005 | AE31: Interest Only | AF31: 1 | AG31: 24 | AK31: 0 | AL31: Adjustable rate | AM31: Actual/360 | AN31: 0.0363 | AO31: SOFR Term 1 month | AP31: 0.032 | AQ31: N/A | AR31: N/A | AS31: N/A | AT31: N/A | AU31: N/A | AV31: No Rounding | AW31: N/A | AX31: SOFR - US Govt Securities | AY31: -2BD | AZ31: =BA31-1 -> 46267 | BA31: 46268 | BB31: 46310 | BC31: 46310 | BD31: Monthly | BE31: 1 | BF31: 15 | BG31: 15th – 14th | BH31: 46310 | BI31: Monthly | BL31: N/A | BM31: N/A | BN31: Monthly | BO31: 46310 | BP31: 0 | BR31: 0.0603712 | BS31: 565700000 | BT31: 24 | BU31: N/A | BV31: Other | BW31: Spread maintenance for first 12 months | BX31: 46268 | BY31: 46633 | CA31: 0.03 | CB31: 0 | CC31: N/A | CD31: 0 | CW31: Springing Lockbox | CX31: i) <8.25% DY and ii) one or more properties are no longer compliant with respective flag or brand requirements | CY31: =CY29 -> DY Trigger: DY ≥ 8.25% as of the prior quarter-end (may be achieved by voluntary paydown); no trigger exists while the Excess Cash Flow Reserve ≥ the DY Trigger Cure Amount. EoD: Lender accepts cure; Manager bankruptcy: replacement manager or dismissal within 90 days; franchise trigger: Replacement Franchise Agreement. | CZ31: Deutsche Bank National Trust Company | DA31: N/A
A32: MaSH-3779335 | B32: 346842 | C32: AHPT 2026-ATRM - Class E | D32: 00151BAJ1 | E32: JS | F32: CR/PJ | G32: 46219 | H32: 46244 | I32: 46244 | J32: 46268 | K32: 46268 | L32: Atrium Hospitality | M32: Wells Fargo | N32: Wells Fargo & Co. | O32: Wells Fargo | Q32: Various | R32: Computershare Trust Company, National Association | S32: Trimont | T32: Hospitality | U32: 18 | V32: Refinance | W32: Securitization | X32: 24.2 | Y32: 47005 | Z32: 3 | AA32: 12 | AB32: 48100 | AC32: 60 | AD32: =IF(NOT(ISNUMBER(Y32)),"N/A",IF(OR(Z32=0,Y32>=TODAY()),Y32,_xlfn.LET(_xlpm.ExtLen,DATEDIF(Y32,AB32,"m")/Z32,_xlpm.k,ROUNDUP(DATEDIF(Y32,TODAY(),"m")/_xlpm.ExtLen,0),_xlpm.d,EDATE(Y32,_xlpm.k*_xlpm.ExtLen),MIN(AB32,IF(_xlpm.d<TODAY(),EDATE(Y32,(_xlpm.k+1)*_xlpm.ExtLen),_xlpm.d))))) -> 47005 | AE32: Interest Only | AF32: 1 | AG32: 24 | AK32: 0 | AL32: Adjustable rate | AM32: Actual/360 | AN32: 0.0363 | AO32: SOFR Term 1 month | AP32: 0.045 | AQ32: N/A | AR32: N/A | AS32: N/A | AT32: N/A | AU32: N/A | AV32: No Rounding | AW32: N/A | AX32: SOFR - US Govt Securities | AY32: -2BD | AZ32: =BA32-1 -> 46267 | BA32: 46268 | BB32: 46310 | BC32: 46310 | BD32: Monthly | BE32: 1 | BF32: 15 | BG32: 15th – 14th | BH32: 46310 | BI32: Monthly | BL32: N/A | BM32: N/A | BN32: Monthly | BO32: 46310 | BP32: 0 | BR32: 0.0603712 | BS32: 565700000 | BT32: 24 | BU32: N/A | BV32: Other | BW32: Spread maintenance for first 12 months | BX32: 46268 | BY32: 46633 | CA32: 0.03 | CB32: 0 | CC32: N/A | CD32: 0 | CW32: Springing Lockbox | CX32: i) <8.25% DY and ii) one or more properties are no longer compliant with respective flag or brand requirements | CY32: =CY29 -> DY Trigger: DY ≥ 8.25% as of the prior quarter-end (may be achieved by voluntary paydown); no trigger exists while the Excess Cash Flow Reserve ≥ the DY Trigger Cure Amount. EoD: Lender accepts cure; Manager bankruptcy: replacement manager or dismissal within 90 days; franchise trigger: Replacement Franchise Agreement. | CZ32: Deutsche Bank National Trust Company | DA32: N/A
A33: MaSH-3748736 | B33: 316243 | C33: Bridge Loan Trust | D33: N/A | E33: JS | F33: CR | G33: 45925 | H33: 45924 | I33: 45930 | J33: 45930 | K33: 45930 | L33: Redwood Trust, Inc. | M33: Redwood Trust, Inc. | N33: Redwood Trust, Inc. | O33: Goldman Sachs | P33: Goldman Sachs | Q33: Goldman Sachs | R33: Goldman Sachs | S33: CoreVest Finance | T33: Multifamily | U33: 20 | V33: Recapitalization | W33: Preferred Equity | X33: N/A | Y33: N/A | Z33: 0 | AA33: 0 | AB33: N/A | AC33: N/A | AD33: =IF(NOT(ISNUMBER(Y33)),"N/A",IF(OR(Z33=0,Y33>=TODAY()),Y33,_xlfn.LET(_xlpm.ExtLen,DATEDIF(Y33,AB33,"m")/Z33,_xlpm.k,ROUNDUP(DATEDIF(Y33,TODAY(),"m")/_xlpm.ExtLen,0),_xlpm.d,EDATE(Y33,_xlpm.k*_xlpm.ExtLen),MIN(AB33,IF(_xlpm.d<TODAY(),EDATE(Y33,(_xlpm.k+1)*_xlpm.ExtLen),_xlpm.d))))) -> N/A | AE33: N/A | AF33: N/A | AG33: N/A | AK33: 0 | AL33: N/A | AM33: N/A | AN33: N/A | AO33: N/A | AP33: N/A | AQ33: =2500000/70000000 -> 0.035714286 | AR33: N/A | AS33: N/A | AT33: N/A | AU33: N/A | AV33: N/A | AW33: N/A | AX33: N/A | AY33: N/A | AZ33: N/A | BA33: N/A | BB33: N/A | BC33: N/A | BD33: Ad Hoc | BE33: Ad Hoc | BF33: Ad Hoc | BG33: Ad Hoc | BH33: N/A | BI33: N/A | BL33: N/A | BM33: N/A | BN33: No Reset | BO33: No Reset | BP33: N/A | BR33: N/A | BS33: N/A | BT33: N/A | BV33: Other | BW33: N/A | BX33: N/A | BY33: N/A | CA33: 0.2 | CB33: 1 | CC33: Senior - GS Purchase Price Increases for Renovation Advances (Committed Amount) | CD33: 0 | CW33: Hard Lockbox and Waterfall in Effect | CX33: N/A | CY33: N/A | CZ33: Wilmington Trust | DA33: Sidley Austin LLP
A34: MaSH-3748736 | B34: 316243 | C34: Bridge Loan Trust - Residual Class B | D34: N/A | E34: JS | F34: CR | G34: 45925 | H34: 45924 | I34: 45930 | J34: 45930 | K34: 45930 | L34: Redwood Trust, Inc. | M34: Redwood Trust, Inc. | N34: Redwood Trust, Inc. | O34: Goldman Sachs | P34: Goldman Sachs | Q34: Goldman Sachs | R34: Goldman Sachs | S34: CoreVest Finance | T34: Multifamily | U34: 20 | V34: Recapitalization | W34: Common Equity | X34: N/A | Y34: N/A | Z34: 0 | AA34: 0 | AB34: N/A | AC34: N/A | AD34: =IF(NOT(ISNUMBER(Y34)),"N/A",IF(OR(Z34=0,Y34>=TODAY()),Y34,_xlfn.LET(_xlpm.ExtLen,DATEDIF(Y34,AB34,"m")/Z34,_xlpm.k,ROUNDUP(DATEDIF(Y34,TODAY(),"m")/_xlpm.ExtLen,0),_xlpm.d,EDATE(Y34,_xlpm.k*_xlpm.ExtLen),MIN(AB34,IF(_xlpm.d<TODAY(),EDATE(Y34,(_xlpm.k+1)*_xlpm.ExtLen),_xlpm.d))))) -> N/A | AE34: N/A | AF34: N/A | AG34: N/A | AK34: 0 | AL34: N/A | AM34: N/A | AN34: N/A | AO34: N/A | AP34: N/A | AQ34: N/A | AR34: N/A | AS34: N/A | AT34: N/A | AU34: N/A | AV34: N/A | AW34: N/A | AX34: N/A | AY34: N/A | AZ34: N/A | BA34: N/A | BB34: N/A | BC34: N/A | BD34: Ad Hoc | BE34: Ad Hoc | BF34: Ad Hoc | BG34: Ad Hoc | BH34: N/A | BI34: N/A | BL34: N/A | BM34: N/A | BN34: No Reset | BO34: No Reset | BP34: N/A | BR34: N/A | BS34: N/A | BT34: N/A | BV34: Other | BW34: N/A | BX34: N/A | BY34: N/A | CA34: 0.2 | CB34: 1 | CC34: Senior - GS Purchase Price Increases for Renovation Advances (Committed Amount) | CD34: 0 | CW34: Hard Lockbox and Waterfall in Effect | CX34: N/A | CY34: N/A | CZ34: Wilmington Trust | DA34: Sidley Austin LLP
A35: MaSH-3765727 | B35: 333234 | C35: Project AXMF 2025-SBRR1 Class A | D35: 00249HAA1 | E35: JS | F35: CR | G35: 45796 | H35: 45826 | I35: 45826 | J35: =$K$35 -> 45831 | K35: 45831 | L35: Axonic | M35: Axonic | N35: Axonic Special Opportunities SBL Master Fund, LP | O35: Performance Trust | P35: N/A | Q35: N/A | R35: Computershare Trust Company, National Association | S35: Freddie Mac | T35: Multifamily | U35: 1872 | V35: Refinance | W35: Securitization | X35: =IF(AND(ISNUMBER(Y35),ISNUMBER(K35)),ROUND((Y35-K35)/(365/12),1),"N/A") -> 394.5 | Y35: 57829 | Z35: 0 | AA35: 0 | AB35: 57829 | AC35: =X35 -> 394.5 | AD35: =IF(NOT(ISNUMBER(Y35)),"N/A",IF(OR(Z35=0,Y35>=TODAY()),Y35,_xlfn.LET(_xlpm.ExtLen,DATEDIF(Y35,AB35,"m")/Z35,_xlpm.k,ROUNDUP(DATEDIF(Y35,TODAY(),"m")/_xlpm.ExtLen,0),_xlpm.d,EDATE(Y35,_xlpm.k*_xlpm.ExtLen),MIN(AB35,IF(_xlpm.d<TODAY(),EDATE(Y35,(_xlpm.k+1)*_xlpm.ExtLen),_xlpm.d))))) -> 57829 | AE35: Amortizing | AF35: 0 | AG35: 0 | AH35: Various | AI35: Various | AJ35: Various | AK35: 0 | AL35: Fixed rate | AM35: 30/360 | AN35: N/A | AO35: N/A | AP35: N/A | AQ35: N/A | AR35: N/A | AS35: N/A | AT35: N/A | AU35: N/A | AV35: N/A | AW35: N/A | AX35: N/A | AY35: N/A | AZ35: =BA35-1 -> 45777 | BA35: 45778 | BB35: 45838 | BC35: 46323 | BD35: Monthly | BE35: 1 | BF35: 2nd Business Day after the 25th | BG35: Calendar month preceding Distribution Date (1st - 30th, deemed 30 days) | BH35: N/A | BI35: N/A | BL35: N/A | BM35: N/A | BN35: No Reset | BO35: No Reset | BP35: N/A | BQ35: 0 | BR35: N/A | BS35: N/A | BT35: N/A | BU35: N/A | BV35: Other | BW35: Depositor (Axonic) purchase option, one-time, all Certificates at aggregate Certificate Principal Balance (par) plus Trustee/CA expenses: (a) any Distribution Date while a Waterfall Trigger Event is in effect, or (b) any Distribution Date after the 5th anniversary of Closing (after 6/23/2030); 45 days' notice. Depositor may also repurchase individual Underlying CMBS in trigger. Clean-up: 100% holder may exchange for Underlying CMBS. | BX35: 47661 | BY35: N/A | CA35: N/A | CB35: 0 | CC35: N/A | CD35: 0 | CW35: N/A – Re-REMIC (sequential-pay triggers) | CX35: Pro-rata to sequential on: 40% deal factor, >4.00% 60+ day DQ, >1.50% CNL, or 8+ underlying deals in trigger | CY35: Automatic: trigger ceases when none of conditions (a)-(d) continues on a subsequent Distribution Date | CZ35: Computershare Trust Company, National Association. | DA35: N/A
A36: MaSH-3765727 | B36: 333234 | C36: Project AXMF 2025-SBRR1 Class B | D36: 00249HAC7 | E36: JS | F36: CR | G36: 45796 | H36: 45826 | I36: 45826 | J36: =$K$35 -> 45831 | K36: 45831 | L36: Axonic | M36: Axonic | N36: Axonic Special Opportunities SBL Master Fund, LP | O36: Performance Trust | P36: N/A | Q36: N/A | R36: Computershare Trust Company, National Association | S36: Freddie Mac | T36: Multifamily | U36: 1872 | V36: Refinance | W36: Securitization | X36: =IF(AND(ISNUMBER(Y36),ISNUMBER(K36)),ROUND((Y36-K36)/(365/12),1),"N/A") -> 394.5 | Y36: 57829 | Z36: 0 | AA36: 0 | AB36: 57829 | AC36: =X36 -> 394.5 | AD36: =IF(NOT(ISNUMBER(Y36)),"N/A",IF(OR(Z36=0,Y36>=TODAY()),Y36,_xlfn.LET(_xlpm.ExtLen,DATEDIF(Y36,AB36,"m")/Z36,_xlpm.k,ROUNDUP(DATEDIF(Y36,TODAY(),"m")/_xlpm.ExtLen,0),_xlpm.d,EDATE(Y36,_xlpm.k*_xlpm.ExtLen),MIN(AB36,IF(_xlpm.d<TODAY(),EDATE(Y36,(_xlpm.k+1)*_xlpm.ExtLen),_xlpm.d))))) -> 57829 | AE36: Amortizing | AF36: 0 | AG36: 0 | AH36: Various | AI36: Various | AJ36: Various | AK36: 0 | AL36: Fixed rate | AM36: 30/360 | AN36: N/A | AO36: N/A | AP36: N/A | AQ36: N/A | AR36: N/A | AS36: N/A | AT36: N/A | AU36: N/A | AV36: N/A | AW36: N/A | AX36: N/A | AY36: N/A | AZ36: =BA36-1 -> 45777 | BA36: 45778 | BB36: 45838 | BC36: 46323 | BD36: Monthly | BE36: 1 | BF36: 2nd Business Day after the 25th | BG36: Calendar month preceding Distribution Date (1st - 30th, deemed 30 days) | BH36: N/A | BI36: N/A | BL36: N/A | BM36: N/A | BN36: No Reset | BO36: No Reset | BP36: N/A | BQ36: 0 | BR36: N/A | BS36: N/A | BT36: N/A | BU36: N/A | BV36: Other | BW36: Depositor (Axonic) purchase option, one-time, all Certificates at aggregate Certificate Principal Balance (par) plus Trustee/CA expenses: (a) any Distribution Date while a Waterfall Trigger Event is in effect, or (b) any Distribution Date after the 5th anniversary of Closing (after 6/23/2030); 45 days' notice. Depositor may also repurchase individual Underlying CMBS in trigger. Clean-up: 100% holder may exchange for Underlying CMBS. | BX36: 47661 | BY36: N/A | CA36: N/A | CB36: 0 | CC36: N/A | CD36: 0 | CW36: N/A – Re-REMIC (sequential-pay triggers) | CX36: Pro-rata to sequential on: 40% deal factor, >4.00% 60+ day DQ, >1.50% CNL, or 8+ underlying deals in trigger | CY36: Automatic: trigger ceases when none of conditions (a)-(d) continues on a subsequent Distribution Date | CZ36: Computershare Trust Company, National Association. | DA36: N/A
A37: MaSH-3780241 | B37: 347748 | C37: Project AXMF 2025-SBRR1 Class C | D37: 00249HAE3 | E37: JS | F37: CR/PJ | G37: 46218 | H37: 46224 | I37: 46225 | J37: =$K$35 -> 45831 | K37: 46227 | L37: Axonic | M37: Axonic | N37: Axonic Special Opportunities SBL Master Fund, LP | O37: Performance Trust | P37: N/A | Q37: N/A | R37: Computershare Trust Company, National Association | S37: Freddie Mac | T37: Multifamily | U37: 1872 | V37: Refinance | W37: Securitization | X37: =IF(AND(ISNUMBER(Y37),ISNUMBER(K37)),ROUND((Y37-K37)/(365/12),1),"N/A") -> 381.4 | Y37: 57829 | Z37: 0 | AA37: 0 | AB37: 57829 | AC37: =X37 -> 381.4 | AD37: =IF(NOT(ISNUMBER(Y37)),"N/A",IF(OR(Z37=0,Y37>=TODAY()),Y37,_xlfn.LET(_xlpm.ExtLen,DATEDIF(Y37,AB37,"m")/Z37,_xlpm.k,ROUNDUP(DATEDIF(Y37,TODAY(),"m")/_xlpm.ExtLen,0),_xlpm.d,EDATE(Y37,_xlpm.k*_xlpm.ExtLen),MIN(AB37,IF(_xlpm.d<TODAY(),EDATE(Y37,(_xlpm.k+1)*_xlpm.ExtLen),_xlpm.d))))) -> 57829 | AE37: Amortizing | AF37: 0 | AG37: 0 | AH37: Various | AI37: Various | AJ37: Various | AK37: 0 | AL37: Fixed rate | AM37: 30/360 | AN37: N/A | AO37: N/A | AP37: N/A | AQ37: N/A | AR37: N/A | AS37: N/A | AT37: N/A | AU37: N/A | AV37: N/A | AW37: N/A | AX37: N/A | AY37: N/A | AZ37: =BA37-1 -> 46203 | BA37: 46204 | BB37: 46261 | BC37: 46323 | BD37: Monthly | BE37: 1 | BF37: 2nd Business Day after the 25th | BG37: Calendar month preceding Distribution Date (1st - 30th, deemed 30 days) | BH37: N/A | BI37: N/A | BL37: N/A | BM37: N/A | BN37: No Reset | BO37: No Reset | BP37: N/A | BQ37: 0 | BR37: N/A | BS37: N/A | BT37: N/A | BU37: N/A | BV37: Other | BW37: Depositor (Axonic) purchase option, one-time, all Certificates at aggregate Certificate Principal Balance (par) plus Trustee/CA expenses: (a) any Distribution Date while a Waterfall Trigger Event is in effect, or (b) any Distribution Date after the 5th anniversary of Closing (after 6/23/2030); 45 days' notice. Depositor may also repurchase individual Underlying CMBS in trigger. Clean-up: 100% holder may exchange for Underlying CMBS. | BX37: 47661 | BY37: N/A | CA37: N/A | CB37: 0 | CC37: N/A | CD37: 0 | CW37: N/A – Re-REMIC (sequential-pay triggers) | CX37: Pro-rata to sequential on: 40% deal factor, >4.00% 60+ day DQ, >1.50% CNL, or 8+ underlying deals in trigger | CY37: Automatic: trigger ceases when none of conditions (a)-(d) continues on a subsequent Distribution Date | CZ37: Computershare Trust Company, National Association. | DA37: N/A
A38: MaSH-3275701 | B38: 62474 | C38: Chimera_Lake | D38: N/A | E38: JS | F38: AR | G38: 44833 | I38: 44834 | J38: 44407 | K38: 44845 | L38: Lone Star Real Estate Fund VI, L.P. | M38: Credit Suisse | N38: Credit Suisse | O38: Credit Suisse | P38: N/A | Q38: Credit Suisse | R38: Column Financial, Inc. | S38: KeyBank | T38: Senior Housing | U38: 10 | V38: Acquisition | W38: A Note | X38: =IF(AND(ISNUMBER(Y38),ISNUMBER(K38)),ROUND((Y38-K38)/(365/12),1),"N/A") -> 9.9 | Y38: 45147 | Z38: 3 | AA38: 12 | AB38: 46243 | AC38: =X38 -> 9.9 | AD38: =IF(NOT(ISNUMBER(Y38)),"N/A",IF(OR(Z38=0,Y38>=TODAY()),Y38,_xlfn.LET(_xlpm.ExtLen,DATEDIF(Y38,AB38,"m")/Z38,_xlpm.k,ROUNDUP(DATEDIF(Y38,TODAY(),"m")/_xlpm.ExtLen,0),_xlpm.d,EDATE(Y38,_xlpm.k*_xlpm.ExtLen),MIN(AB38,IF(_xlpm.d<TODAY(),EDATE(Y38,(_xlpm.k+1)*_xlpm.ExtLen),_xlpm.d))))) -> 46243 | AE38: Interest Only | AF38: 1 | AG38: =X38 -> 9.9 | AK38: 0 | AL38: Adjustable rate | AM38: Actual/360 | AN38: 0.02846 | AO38: SOFR Term 1 month | AP38: 0.035 | AQ38: N/A | AR38: N/A | AS38: N/A | AT38: N/A | AU38: 0 | AV38: Always Round Up | AW38: 0.001 | AX38: SOFR - US Govt Securities | AY38: -2BD | AZ38: =BA38-1 -> 44848 | BA38: 44849 | BB38: 44874 | BC38: N/A | BD38: Monthly | BE38: 1 | BF38: 9 | BG38: 15th – 14th | BH38: 44874 | BI38: Monthly | BL38: Lesser of 5% of unpaid sum or Maximum Legal Rate | BM38: 0 | BN38: Monthly | BO38: =BH38 -> 44874 | BP38: 0.0025 | BQ38: 1 | BR38: 0.025 | BS38: 190000000 | BT38: 24 | BU38: N/A | BV38: Other | BW38: Open to prepay; spread maintenance expired 9/14/2022 | BX38: 44407 | BY38: 44818 | CA38: 0.04 | CB38: 1 | CC38: Mezzanine | CD38: 0 | CW38: Soft Lockbox | CX38: EoD; Debt Yield < 7.5% (8.75% in final extension); bankruptcy of Borrower or manager | CY38: EoD cured or waived; bankruptcy dismissed; DY >= 7.50% (8.75% 3rd ext.) for 2 consecutive quarters, or paydown to threshold | CZ38: N/A | DA38: N/A
A39: MaSH-3257025 | B39: 61923 | C39: Project 3700M | D39: N/A | E39: JS | F39: AR | G39: 44739 | H39: 44755 | I39: 44742 | J39: 44614 | K39: 44742 | L39: US Living | M39: Credit Suisse | N39: Credit Suisse | O39: Credit Suisse | P39: N/A | Q39: MF1 | R39: Column Financial, Inc. | S39: CBRE | T39: Multifamily | U39: 1 | V39: Acquisition | W39: A Note | X39: =IF(AND(ISNUMBER(Y39),ISNUMBER(K39)),ROUND((Y39-K39)/(365/12),1),"N/A") -> 20.3 | Y39: 45360 | Z39: 0 | AA39: 0 | AB39: 45360 | AC39: =X39 -> 20.3 | AD39: =IF(NOT(ISNUMBER(Y39)),"N/A",IF(OR(Z39=0,Y39>=TODAY()),Y39,_xlfn.LET(_xlpm.ExtLen,DATEDIF(Y39,AB39,"m")/Z39,_xlpm.k,ROUNDUP(DATEDIF(Y39,TODAY(),"m")/_xlpm.ExtLen,0),_xlpm.d,EDATE(Y39,_xlpm.k*_xlpm.ExtLen),MIN(AB39,IF(_xlpm.d<TODAY(),EDATE(Y39,(_xlpm.k+1)*_xlpm.ExtLen),_xlpm.d))))) -> 45360 | AE39: Interest Only | AF39: 1 | AG39: =X39 -> 20.3 | AK39: 0 | AL39: Adjustable rate | AM39: Actual/360 | AN39: 0.0267 | AO39: SOFR Term 1 month | AP39: 0.0325 | AQ39: N/A | AR39: N/A | AS39: N/A | AT39: N/A | AU39: 0.0025 | AV39: Always Round Up | AW39: 0.001 | AX39: SOFR - US Govt Securities | AY39: -2BD | AZ39: =BA39-1 -> 44726 | BA39: 44727 | BB39: 44751 | BC39: N/A | BD39: Monthly | BE39: 1 | BF39: 9 | BG39: 15th – 14th | BH39: 45116 | BI39: Monthly | BL39: Lesser of 5% of unpaid sum or Maximum Legal Rate | BM39: 3 | BN39: Monthly | BO39: =BH39 -> 45116 | BP39: 0 | BQ39: 1 | BR39: 0.025 | BS39: 121500000 | BT39: 25 | BU39: N/A | BV39: Yield Maintenance | BW39: Spread maintenance through 3/9/2023; open thereafter on 30 to 90 days' notice; 0.25% exit fee | BX39: 44614 | BY39: 44994 | CA39: 0.04 | CB39: 1 | CC39: Mezzanine | CD39: 0 | CW39: Soft Lockbox | CX39: EoD; Debt Yield < 5.00% | CY39: EoD cured or waived; DY >= 5.00% for one calendar quarter or deposit of Debt Yield Cure Amount | CZ39: N/A | DA39: Gibson Dunn
A40: MaSH-3659094 | B40: 226601 | C40: Project Great Park Land Bank | D40: N/A | E40: JS | F40: GD | G40: 45616 | H40: 45574 | I40: 45623 | J40: =K40 -> 45623 | K40: 45623 | L40: Hearthstone / Toll Brothers | M40: Hearthstone | N40: N/A | O40: Hearthstone | P40: Hearthstone | Q40: Hearthstone | R40: Hearthstone | S40: Hearthstone | T40: Land | U40: 1 | V40: Acquisition | W40: Common Equity | X40: =IF(AND(ISNUMBER(Y40),ISNUMBER(K40)),ROUND((Y40-K40)/(365/12),1),"N/A") -> 35.8 | Y40: 46711 | Z40: 3 | AA40: 1 | AB40: 46803 | AC40: =X40 -> 35.8 | AD40: =IF(NOT(ISNUMBER(Y40)),"N/A",IF(OR(Z40=0,Y40>=TODAY()),Y40,_xlfn.LET(_xlpm.ExtLen,DATEDIF(Y40,AB40,"m")/Z40,_xlpm.k,ROUNDUP(DATEDIF(Y40,TODAY(),"m")/_xlpm.ExtLen,0),_xlpm.d,EDATE(Y40,_xlpm.k*_xlpm.ExtLen),MIN(AB40,IF(_xlpm.d<TODAY(),EDATE(Y40,(_xlpm.k+1)*_xlpm.ExtLen),_xlpm.d))))) -> 46711 | AE40: Interest Only | AF40: 1 | AG40: =X40 -> 35.8 | AK40: 0 | AL40: Fixed | AM40: N/A | AN40: N/A | AO40: N/A | AP40: N/A | AQ40: N/A | AR40: N/A | AS40: N/A | AT40: N/A | AU40: N/A | AV40: N/A | AW40: N/A | AX40: N/A | AY40: N/A | AZ40: =BA40-1 -> 45622 | BA40: 45623 | BB40: 45636 | BC40: 46336 | BD40: Monthly | BE40: 1 | BF40: 10 | BG40: 1st – last day of month | BH40: N/A | BI40: N/A | BL40: N/A | BM40: 5 | BN40: Event Driven | BO40: N/A | BP40: N/A | BQ40: 0 | BR40: N/A | BS40: N/A | BT40: N/A | BU40: N/A | BV40: Other | BW40: Builder may accelerate lot takedowns subject to an Accelerated Exercise Fee of 10% of the Purchase Price of accelerated lots, reduced by 1% per month starting 7 months after the Effective Date (0% after 10 months); no fee for Market Supported Acceleration or the 50 lot Builder Spec Allowance | BX40: 45623 | BY40: 46139 | CA40: 0.0405 | CD40: 0 | CW40: N/A | CX40: N/A | CY40: N/A | CZ40: N/A | DA40: Gibson Dunn

Sheet Collateral Data
A2: Mash-ID | B2: Deal Code | C2: Loan Name | D2: Property Name | E2: Property Type | F2: Location | G2: Street Address | H2: City | I2: State | J2: Zip | K2: County | L2: Parcel # | M2: ACLI Region | N2: Submarket | O2: MSA | P2: Country | Q2: As of Date | R2: Number of Units | S2: Gross Square Feet | T2: Net Rentable Square Feet | U2: Lien Position | V2: Ownership Interest | W2: Year Built | X2: Year Renovated | Y2: Allocated Loan Amount | Z2: SSP Allocated Loan Amount | AA2: MAI Land Value | AB2: MAI As-Is Property Value | AC2: MAI Stabilized Property Value | AD2: MAI Property Valuation Date | AE2: MAI Stabilized Cap Rate | AF2: Stabilized LTV | AG2: Occupancy as of Date | AH2: Percent Occupied | AI2: Tenancy | AJ2: Largest Tenant SF | AK2: Largest Tenant % of NRA | AL2: Largest Tenant Lease Expiration Date | AM2: Largest Tenant | AN2: Second Largest Tenant SF | AO2: Second Largest Tenant % of NRA | AP2: Second Largest Tenant Lease Expiration Date | AQ2: Second Largest Tenant | AR2: Third Largest Tenant SF | AS2: Third Largest Tenant % of NRA | AT2: Third Largest Tenant Lease Expiration Date | AU2: Third Largest Tenant | AV2: Avg. In Place Rents - PSF Com, Per Bed/Mo Multi | AW2: Ground Lease Expiration Date | AX2: Ground Lease Extension Terms | AY2: Annual Ground Lease Payment as of the Cut-off Date | AZ2: Annual Ground Rent Increases Flag | BA2: Statement Date | BB2: Total Revenues | BC2: Total Expenses | BD2: Net Operating Income | BE2: Net Cash Flow | BF2: Financial Statement Type | BG2: Underwritten Replacement / FF&E Reserve | BH2: Underwritten NOI | BI2: Underwritten Statement Type
A3: MaSH-3256633 | B3: 61883 | C3: Project Royale | D3: The Wyatt | University of Kentucky | E3: Student Housing | F3: Central Business District - Urban | G3: 497 Angliana Ave | H3: Lexington | I3: KY | J3: 40508 | K3: Fayette | L3: 38256250 38256240 16084500 14094200 | M3: =_xlfn.XLOOKUP(I3,Dropdowns!$U$2:$U$53,Dropdowns!$W$2:$W$53,"",0,1) -> East South Central | N3: Lexington-Fayette | O3: Lexington-Fayette, KY Metro Area | P3: USA | Q3: 44777 | R3: 278 | S3: =T3 -> 308342 | T3: 308342 | U3: 1 | V3: Leased Fee | W3: 2013 | X3: N/A | Y3: 31200000 | Z3: 12336638 | AA3: 4370000 | AB3: 48500000 | AC3: =AB3 -> 48500000 | AD3: 44656 | AE3: 0.0575 | AF3: =Y3/AB3 -> 0.64329897 | AG3: 44656 | AH3: 0.934 | AI3: Multiple Tenants | AV3: 1.4852357
A4: MaSH-3256633 | B4: 61883 | C4: Project Royale | D4: The Blake | Kennesaw State University | E4: Student Housing | F4: Suburban | G4: 3453 Busbee Dr NW | H4: Kennesaw | I4: GA | J4: 30144 | K4: Cobb | L4: 16-0361-0-002-0 | M4: =_xlfn.XLOOKUP(I4,Dropdowns!$U$2:$U$53,Dropdowns!$W$2:$W$53,"",0,1) -> South Atlantic | N4: Atlanta | O4: Atlanta-Sandy Springs-Roswell, GA Metro Area | P4: USA | Q4: 44777 | R4: 274 | S4: =T4 -> 326118 | T4: 326118 | U4: 1 | V4: Leased Fee | W4: 2013 | X4: N/A | Y4: 54200000 | Z4: 21430955 | AA4: 10450000 | AB4: 86700000 | AC4: =AB4 -> 86700000 | AD4: 44657 | AE4: 0.0475 | AF4: =Y4/AB4 -> 0.62514418 | AG4: 46118 | AH4: 0.99 | AI4: Multiple Tenants | AV4: 1.832105
A5: MaSH-3256633 | B5: 61883 | C5: Project Royale | D5: The James | Virginia Commonwealth University | E5: Student Housing | F5: Central Business District - Urban | G5: 601 W. Bacon St | H5: Richmond | I5: VA | J5: 23222 | K5: Richmond | L5: N000-0317-017 | M5: =_xlfn.XLOOKUP(I5,Dropdowns!$U$2:$U$53,Dropdowns!$W$2:$W$53,"",0,1) -> South Atlantic | N5: Richmond | O5: Richmond, VA Metro Area | P5: USA | Q5: 44777 | R5: 270 | S5: =T5 -> 295748 | T5: 295748 | U5: 1 | V5: Leased Fee | W5: 2012 | X5: N/A | Y5: 36000000 | Z5: 14234583 | AA5: 6750000 | AB5: 57400000 | AC5: =AB5 -> 57400000 | AD5: 44656 | AE5: 0.05 | AF5: =Y5/AB5 -> 0.6271777 | AG5: 44656 | AH5: 0.974 | AI5: Multiple Tenants | AV5: 1.7391471
A6: MaSH-3256633 | B6: 61883 | C6: Project Royale | D6: The Dillon | Indiana University | E6: Student Housing | F6: Urban (non-Central Business District) | G6: 525 S. Patterson Dr | H6: Bloomington | I6: IN | J6: 47403 | K6: McLean | L6: 53-08-05-200-043-000-009 53-08-05-200-048-000-009 53-08-05-200-050-000-009 | M6: =_xlfn.XLOOKUP(I6,Dropdowns!$U$2:$U$53,Dropdowns!$W$2:$W$53,"",0,1) -> East North Central | N6: Bloomington | O6: Bloomington, IN Metro Area | P6: USA | Q6: 44777 | R6: 204 | S6: =T6 -> 238125 | T6: 238125 | U6: 1 | V6: Leased Fee | W6: 2014 | X6: N/A | Y6: 36300000 | Z6: 14353204 | AA6: 12830000 | AB6: 58400000 | AC6: =AB6 -> 58400000 | AD6: 44656 | AE6: 0.053 | AF6: =Y6/AB6 -> 0.62157534 | AG6: 44656 | AH6: 0.986 | AI6: Multiple Tenants | AV6: 1.8079172
A7: MaSH-3256633 | B7: 61883 | C7: Project Royale | D7: The Indy | Kennesaw State University | E7: Student Housing | F7: Suburban | G7: 3011 Hidden Forest Ct | H7: Marietta | I7: GA | J7: 30066 | K7: Cobb | L7: 16-0507-0-047-0 | M7: =_xlfn.XLOOKUP(I7,Dropdowns!$U$2:$U$53,Dropdowns!$W$2:$W$53,"",0,1) -> South Atlantic | N7: Atlanta | O7: Atlanta-Sandy Springs-Roswell, GA Metro Area | P7: USA | Q7: 44777 | R7: 172 | S7: =T7 -> 221835 | T7: 221835 | U7: 1 | V7: Leasehold | W7: 2020 | X7: N/A | Y7: 30900000 | Z7: 12218017 | AA7: 6536000 | AB7: 49300000 | AC7: =AB7 -> 49300000 | AD7: 44657 | AE7: 0.05 | AF7: =Y7/AB7 -> 0.62677485 | AG7: 46118 | AH7: 0.994 | AI7: Multiple Tenants | AV7: 2.8517355
A8: MaSH-3256633 | B8: 61883 | C8: Project Royale | D8: 4050 Lofts | University of South Florida | E8: Student Housing | F8: Urban (non-Central Business District) | G8: 4050 Rocky Cir | H8: Tampa | I8: FL | J8: 33613 | K8: Hillsborough | L8: 034835-0100 | M8: =_xlfn.XLOOKUP(I8,Dropdowns!$U$2:$U$53,Dropdowns!$W$2:$W$53,"",0,1) -> South Atlantic | N8: Tampa | O8: Tampa-St. Petersburg-Clearwater, FL Metro Area | P8: USA | Q8: 44777 | R8: 196 | S8: =T8 -> 248615 | T8: 248615 | U8: 1 | V8: Leasehold | W8: 2009 | X8: N/A | Y8: 33000000 | Z8: 13048368 | AA8: 21500000 | AB8: 52500000 | AC8: =AB8 -> 52500000 | AD8: 44287 | AE8: 0.048 | AF8: =Y8/AB8 -> 0.62857143 | AG8: 44656 | AH8: 0.988 | AI8: Multiple Tenants | AV8: 2.1138066
A9: MaSH-3256633 | B9: 61883 | C9: Project Royale | D9: The Scarlet | Texas Tech University | E9: Student Housing | F9: Central Business District - Urban | G9: 2202 Mac Davis Ln | H9: Lubbock | I9: TX | J9: 79401 | K9: Lubbock | L9: R303917 | M9: =_xlfn.XLOOKUP(I9,Dropdowns!$U$2:$U$53,Dropdowns!$W$2:$W$53,"",0,1) -> West South Central | N9: Lubbock | O9: Lubbock, TX Metro Area | P9: USA | Q9: 44777 | R9: 228 | S9: =T9 -> 284129 | T9: 284129 | U9: 1 | V9: Leased Fee | W9: 2005 | X9: N/A | Y9: 26500000 | Z9: 10478235 | AA9: 3010000 | AB9: 42300000 | AC9: =AB9 -> 42300000 | AD9: 44657 | AE9: 0.048 | AF9: =Y9/AB9 -> 0.62647754 | AG9: 44656 | AH9: 0.956 | AI9: Multiple Tenants | AV9: 1.4673635
A10: MaSH-3258016 | B10: 61973 | C10: Lakefront North | D10: Lakefront North | E10: Office - Office Building | F10: Suburban | G10: 2103 and 2107 Research Forest Drive | H10: Spring | I10: TX | J10: 77380 | K10: Montgomery | L10: R313767 R313765 | M10: =_xlfn.XLOOKUP(I10,Dropdowns!$U$2:$U$53,Dropdowns!$W$2:$W$53,"",0,1) -> West South Central | N10: Houston | O10: Houston-Pasadena-The Woodlands, TX Metro Area | P10: USA | Q10: 44832 | R10: N/A | S10: 258031 | T10: 258031 | U10: 1 | V10: Leased Fee | W10: 2002 | X10: 2014 | Y10: 50000000 | Z10: 50000000 | AB10: 92100000 | AC10: =AB10 -> 92100000 | AD10: 44832 | AF10: =Y10/AB10 -> 0.54288817 | AG10: 44832 | AH10: 0.868 | AI10: Multiple Tenants | AJ10: 111324 | AK10: 0.43143653 | AL10: 46630 | AM10: ENTERGY SERVICES | AN10: 87231 | AO10: 0.33806403 | AP10: 47831 | AQ10: ARENA ENERGY | AR10: 9887 | AS10: 0.038317101 | AT10: 48944 | AU10: HL AMENITIES HOLDINGS | AV10: 27.53
A11: MaSH-3339577 | B11: 64734 | C11: Project Balboa | D11: Carmel Rancho | E11: Retail - Anchored | F11: Suburban | G11: 26135 Carmel Rancho Boulevard | H11: Carmel | I11: CA | J11: 93923 | K11: Durham | L11: 015-012-073 | M11: =_xlfn.XLOOKUP(I11,Dropdowns!$U$2:$U$53,Dropdowns!$W$2:$W$53,"",0,1) -> Pacific | N11: Salinas | O11: Salinas, CA Metro Area | P11: USA | Q11: 44851 | R11: N/A | S11: 77002 | T11: 77002 | U11: 1 | V11: Leased Fee | W11: 1961 | X11: 1998 | Y11: 21400000 | Z11: 16050000 | AB11: 30700000 | AC11: 43700000 | AD11: 44838 | AE11: 0.0625 | AF11: =Y11/AB11 -> 0.6970684 | AG11: 44851 | AH11: 0.973 | AI11: Multiple Tenants | AJ11: 17082 | AK11: 0.22183839 | AL11: 45382 | AM11: Prim's Carmel | AN11: 9160 | AO11: 0.11895795 | AP11: 44957 | AQ11: Wells Fargo | AR11: 5940 | AS11: 0.077140853 | AT11: 45961 | AU11: Keller Williams | AV11: 30.36
A12: MaSH-3339577 | B12: 64734 | C12: Project Balboa | D12: Gateway Plaza | E12: Retail - Anchored | F12: Urban (non-Central Business District) | G12: 650 River St | H12: Santa Cruz | I12: CA | J12: 95060 | K12: Honolulu | L12: 008-601-01 | M12: =_xlfn.XLOOKUP(I12,Dropdowns!$U$2:$U$53,Dropdowns!$W$2:$W$53,"",0,1) -> Pacific | N12: Santa Cruz | O12: Santa Cruz-Watsonville, CA Metro Area | P12: USA | Q12: 44851 | R12: N/A | S12: 119407 | T12: 119407 | U12: 1 | V12: Leased Fee | W12: 2012 | X12: N/A | Y12: 33600000 | Z12: 25200000 | AB12: 44000000 | AC12: 62100000 | AD12: 44838 | AE12: 0.0675 | AF12: =Y12/AB12 -> 0.76363636 | AG12: 44851 | AH12: 0.98 | AI12: Multiple Tenants | AJ12: 29063 | AK12: 0.24339444 | AL12: 45322 | AM12: Ross | AN12: 25941 | AO12: 0.21724857 | AP12: 45351 | AQ12: Petsmart | AR12: 23475 | AS12: 0.19659651 | AT12: 45230 | AU12: OfficeMax | AV12: 25.69
A13: MaSH-3337170 | B13: 64681 | C13: Project Eyas | D13: 18-Seventy Nine | Sam Houston State | E13: Student Housing | F13: Suburban | G13: 5020 Sam Houston Ave | H13: Huntsville | I13: TX | J13: 77340 | K13: Denver | L13: 24058 & 100428 | M13: =_xlfn.XLOOKUP(I13,Dropdowns!$U$2:$U$53,Dropdowns!$W$2:$W$53,"",0,1) -> West South Central | N13: Houston | O13: Houston-Pasadena-The Woodlands, TX Metro Area | P13: USA | Q13: 44922 | R13: 179 | S13: 245784 | T13: 234080 | U13: 1 | V13: Leased Fee | W13: 2005 | X13: N/A | Y13: 14465114 | Z13: 4633780.5 | AA13: 2440000 | AB13: 23000000 | AC13: 23000000 | AD13: 44686 | AE13: 0.0525 | AF13: =Y13/AB13 -> 0.62891801 | AG13: 44858 | AH13: 0.8109 | AI13: Multiple Tenants | AV13: 508
A14: MaSH-3337170 | B14: 64681 | C14: Project Eyas | D14: Chapel Ridge | UNC-Chapel Hill | E14: Student Housing | F14: Suburban | G14: 101 Legacy Terrace | H14: Chapel Hill | I14: NC | J14: 27516 | K14: Fulton | L14: 9789197059 & 9789292752 & 9789198723 | M14: =_xlfn.XLOOKUP(I14,Dropdowns!$U$2:$U$53,Dropdowns!$W$2:$W$53,"",0,1) -> South Atlantic | N14: Durham-Chapel Hill | O14: Durham-Chapel Hill, NC Metro Area | P14: USA | Q14: 44922 | R14: 180 | S14: 236528 | T14: 214244 | U14: 1 | V14: Leased Fee | W14: 2003 | X14: N/A | Y14: 32395812 | Z14: 10377733 | AA14: 5400000 | AB14: 52300000 | AC14: 52300000 | AD14: 44680 | AE14: 0.0475 | AF14: =Y14/AB14 -> 0.6194228 | AG14: 44858 | AH14: 0.9869 | AI14: Multiple Tenants | AV14: 760
A15: MaSH-3337170 | B15: 64681 | C15: Project Eyas | D15: First Street Place | East Carolina University | E15: Student Housing | F15: Suburban | G15: 400 W 1st St | H15: Greenville | I15: NC | J15: 27834 | K15: Fulton | L15: 013500 & 029030 | M15: =_xlfn.XLOOKUP(I15,Dropdowns!$U$2:$U$53,Dropdowns!$W$2:$W$53,"",0,1) -> South Atlantic | N15: Greenville | O15: Greenville, NC Metro Area | P15: USA | Q15: 44922 | R15: 193 | S15: 158400 | T15: 133865 | U15: 1 | V15: Leased Fee | W15: 2009 | X15: N/A | Y15: 12649902 | Z15: 4052292.1 | AA15: 2500000 | AB15: 20900000 | AC15: 20900000 | AD15: 44680 | AE15: 0.05 | AF15: =Y15/AB15 -> 0.60525845 | AG15: 44858 | AH15: 0.9821 | AI15: Multiple Tenants | AV15: 709
