Workbook

Sheet Cover
C20: HOSPITALITY SOFTWARE VENTURE
C22: Market Sizing, Unit Economics and Competitive Assessment
C24: Owner-Side Capex and Asset Performance Intelligence
C27: Prepared 10 September 2026
C28: Illustrative model. All assumptions are estimates to be validated in primary diligence.
C31: LEGEND
C33: Blue text | E33: Hardcoded input or scenario lever. Edit these.
C34: Black text | E34: Formula. Do not overwrite.
C35: Green text | E35: Link to another tab.
C36: Light green fill | E36: Favourable outcome in sensitivity tables.
C37: Light red fill | E37: Unfavourable outcome in sensitivity tables.
C38: Dashed box | E38: Base case cell.

Sheet Assumptions
B2: ASSUMPTIONS AND SCENARIO LEVERS
B4: Blue cells are inputs. The Active column resolves to the scenario named in cell C6.
B6: SCENARIO SELECTOR | C6: Base
B8: Assumption | C8: Active | D8: Downside | E8: Base | F8: Upside | G8: Unit | H8: Note / Basis
B9: PRICING AND CUSTOMER ACQUISITION
B10: Blended ACV, new logo (Year 1) | C10: =INDEX($D10:$F10,MATCH($C$6,$D$8:$F$8,0)) -> 32000 | D10: 26000 | E10: 32000 | F10: 38000 | G10: $/yr | H10: Benchmarked to hotel BI and data subscriptions at $18k to $60k per year depending on portfolio size.
B11: ACV escalator on new logos | C11: =INDEX($D11:$F11,MATCH($C$6,$D$8:$F$8,0)) -> 0.04 | D11: 0.02 | E11: 0.04 | F11: 0.06 | G11: % p.a. | H11: Annual increase in new-logo price as the dataset deepens and coverage improves.
B12: New logos added, Year 1 | C12: =INDEX($D12:$F12,MATCH($C$6,$D$8:$F$8,0)) -> 8 | D12: 5 | E12: 8 | F12: 12 | G12: # | H12: Founder-led sales only. Assumes design partners convert to paid.
B13: New logos added, Year 2 | C13: =INDEX($D13:$F13,MATCH($C$6,$D$8:$F$8,0)) -> 28 | D13: 18 | E13: 28 | F13: 38 | G13: # | H13: First two account executives hired in Year 2.
B14: New logos added, Year 3 | C14: =INDEX($D14:$F14,MATCH($C$6,$D$8:$F$8,0)) -> 48 | D14: 32 | E14: 48 | F14: 68 | G14: # | H14: Four-person sales team at roughly 12 logos per rep per year.
B15: New logos added, Year 4 | C15: =INDEX($D15:$F15,MATCH($C$6,$D$8:$F$8,0)) -> 70 | D15: 45 | E15: 70 | F15: 100 | G15: # | H15: Six-person team plus channel via brokerage and lender referrals.
B16: New logos added, Year 5 | C16: =INDEX($D16:$F16,MATCH($C$6,$D$8:$F$8,0)) -> 95 | D16: 55 | E16: 95 | F16: 140 | G16: # | H16: Eight-person team. Assumes no international expansion.
B17: RETENTION AND MARGIN
B18: Gross logo retention | C18: =INDEX($D18:$F18,MATCH($C$6,$D$8:$F$8,0)) -> 0.88 | D18: 0.82 | E18: 0.88 | F18: 0.92 | G18: % p.a. | H18: Data subscriptions in real assets typically retain 85% to 92%. Downside reflects a nice-to-have budget line.
B19: Net revenue retention | C19: =INDEX($D19:$F19,MATCH($C$6,$D$8:$F$8,0)) -> 1.12 | D19: 1 | E19: 1.12 | F19: 1.22 | G19: % p.a. | H19: Expansion from seat growth and added modules. NRR includes the effect of logo churn.
B20: Gross margin | C20: =INDEX($D20:$F20,MATCH($C$6,$D$8:$F$8,0)) -> 0.78 | D20: 0.7 | E20: 0.78 | F20: 0.84 | G20: % | H20: Net of data acquisition, third-party licences, hosting and the data operations team.
B21: COST AND CAPITAL
B22: CAC per new logo | C22: =INDEX($D22:$F22,MATCH($C$6,$D$8:$F$8,0)) -> 28000 | D22: 40000 | E22: 28000 | F22: 20000 | G22: $ | H22: Fully loaded sales and marketing spend divided by new logos. Founder-led selling is cheaper in Year 1.
B23: Discount rate | C23: =INDEX($D23:$F23,MATCH($C$6,$D$8:$F$8,0)) -> 0.12 | D23: 0.12 | E23: 0.12 | F23: 0.12 | G23: % | H23: Used to discount the five-year customer gross profit stream in the LTV calculation.
B24: LTV horizon | C24: =INDEX($D24:$F24,MATCH($C$6,$D$8:$F$8,0)) -> 5 | D24: 5 | E24: 5 | F24: 5 | G24: yrs | H24: LTV is capped at five years rather than taken to perpetuity, because NRR at or above the discount rate makes a perpetuity formula diverge.
B26: Source: assumption set constructed for this analysis. Pricing benchmarks informed by publicly disclosed hotel BI deployments (Otelier, Actabl). PIP cost ranges per Matthews Real Estate and HVS / Nehmer 2025 Hotel Cost Estimating Guide. All figures require primary validation.

Sheet Market Sizing
B2: MARKET SIZING (1 OF 2)
B4: Bottom-up build. US only. Entity counts are estimates and are the single largest source of error in this model.
B6: CONCEPT A: OWNER-SIDE CAPEX AND PIP COST INTELLIGENCE
B8: Buyer Segment | C8: Entities (#) | D8: Addressable (%) | E8: Addressable (#) | F8: ACV ($) | G8: TAM ($) | H8: SAM ($) | I8: Basis
B9: Institutional owners (10+ hotels) | C9: 900 | D9: 0.7 | E9: =C9*D9 -> 630 | F9: 60000 | G9: =C9*F9 -> 54000000 | H9: =E9*F9 -> 37800000 | I9: Includes REITs, PE-backed platforms and family offices. Highest willingness to pay; capex is their largest discretionary line.
B10: Mid-market owners (3 to 9 hotels) | C10: 4500 | D10: 0.35 | E10: =C10*D10 -> 1575 | F10: 18000 | G10: =C10*F10 -> 81000000 | H10: =E10*F10 -> 28350000 | I10: Large in count, thin in budget. Addressability discounted heavily; likely a self-serve tier rather than enterprise sales.
B11: Hotel lenders and debt funds | C11: 350 | D11: 0.6 | E11: =C11*D11 -> 210 | F11: 75000 | G11: =C11*F11 -> 26250000 | H11: =E11*F11 -> 15750000 | I11: Underwrite PIP reserves on every loan. Pay for third-party data today via appraisal and consulting spend.
B12: Brokerage and valuation advisory | C12: 300 | D12: 0.55 | E12: =C12*D12 -> 165 | F12: 45000 | G12: =C12*F12 -> 13500000 | H12: =E12*F12 -> 7425000 | I12: JLL, CBRE, HVS, Newmark and regional shops. Data becomes an input to every BOV and appraisal.
B13: Third-party management companies | C13: 700 | D13: 0.3 | E13: =C13*D13 -> 210 | F13: 30000 | G13: =C13*F13 -> 21000000 | H13: =E13*F13 -> 6300000 | I13: Buy to defend capex recommendations to owners. Lower urgency; they do not fund the capex.
B14: Brands and franchisors | C14: 40 | D14: 0.5 | E14: =C14*D14 -> 20 | F14: 150000 | G14: =C14*F14 -> 6000000 | H14: =E14*F14 -> 3000000 | I14: Small count, large contracts. Long sales cycles and potential channel conflict with their own PIP function.
B15: Total / Wtd. Avg. | C15: =SUM(C9:C14) -> 6790 | E15: =SUM(E9:E14) -> 2810 | F15: =IFERROR(G15/C15,0) -> 29712.813 | G15: =SUM(G9:G14) -> 201750000 | H15: =SUM(H9:H14) -> 98625000
B18: SERVICEABLE OBTAINABLE MARKET
B19: Metric | C19: Value | I19: Note
B20: Total addressable market (TAM) | C20: ='Market Sizing'!$G$15 -> 201750000 | I20: All US entities in the six segments at full ACV.
B21: Serviceable addressable market (SAM) | C21: ='Market Sizing'!$H$15 -> 98625000 | I21: TAM filtered by the addressability haircut in column D.
B22: Addressable entities | C22: ='Market Sizing'!$E$15 -> 2810 | I22: The realistic buyer universe. Note how small this is: this is a few-thousand-account market, not a long-tail one.
B23: Year 5 share of SAM captured | C23: 0.055 | I23: Blue input. Cross-check against the customer count in the Financial Build tab.
B24: Implied Year 5 revenue (SOM) | C24: =C21*C23 -> 5424375 | I24: SAM multiplied by the share captured.
B26: KEY TAKEAWAY
B27: The TAM is modest. A roughly $200M US TAM supports a $30M to $60M revenue business at full maturity, which clears a seed and Series A but is thin for a venture outcome that requires a $1B exit. Two responses are available: expand internationally, where the same brand PIP dynamic exists across roughly 100,000 additional hotels, or expand the product from capex benchmarking into full owner-side asset performance, which roughly triples ACV. The second is the stronger path and is why Concept B on the next section is treated as an adjacency rather than an alternative.
B32: CONCEPT B: OWNER-SIDE ASSET PERFORMANCE INTELLIGENCE (ADJACENCY)
B33: Buyer Segment | C33: Entities (#) | D33: Addressable (%) | E33: Addressable (#) | F33: ACV ($) | G33: TAM ($) | H33: SAM ($) | I33: Basis
B34: Mid-market owners (3 to 9 hotels) | C34: 4500 | D34: 0.3 | E34: =C34*D34 -> 1350 | F34: 42000 | G34: =C34*F34 -> 189000000 | H34: =E34*F34 -> 56700000 | I34: The genuine white space. Too small for an Actabl or Otelier enterprise deployment, too large to run on spreadsheets.
B35: Institutional owners (10+ hotels) | C35: 900 | D35: 0.25 | E35: =C35*D35 -> 225 | F35: 110000 | G35: =C35*F35 -> 99000000 | H35: =E35*F35 -> 24750000 | I35: Mostly served or in an active process. Addressability discounted to reflect incumbent penetration.
B36: Owners with 3+ third-party managers | C36: 600 | D36: 0.55 | E36: =C36*D36 -> 330 | F36: 75000 | G36: =C36*F36 -> 45000000 | H36: =E36*F36 -> 24750000 | I36: The sharpest wedge: no single manager's BI system can see across the portfolio, so the owner is structurally unserved.
B37: Total / Wtd. Avg. | C37: =SUM(C34:C36) -> 6000 | E37: =SUM(E34:E36) -> 1905 | G37: =SUM(G34:G36) -> 333000000 | H37: =SUM(H34:H36) -> 106200000
B39: Note on overlap: the two concepts share buyers, so the TAMs are not additive. Concept B entity counts are a subset of Concept A. Sources: US hotel supply of 91,797 properties and 5.8M rooms per AHLA State of the Industry 2024. Owner entity counts are estimates derived from STR and Lodging Econometrics ownership concentration data and require primary validation.

Sheet Unit Economics
B2: CUSTOMER UNIT ECONOMICS
B4: Driven by the Assumptions tab. Change the scenario selector there to reprice this page.
B6: ACTIVE SCENARIO | C6: =Assumptions!$C$6 -> Base
B8: INPUTS (LINKED)
B9: Blended ACV, new logo | C9: =Assumptions!$C$10 -> 32000
B10: Gross margin | C10: =Assumptions!$C$20 -> 0.78
B11: Net revenue retention | C11: =Assumptions!$C$19 -> 1.12
B12: Gross logo retention | C12: =Assumptions!$C$18 -> 0.88
B13: CAC per new logo | C13: =Assumptions!$C$22 -> 28000
B14: Discount rate | C14: =Assumptions!$C$23 -> 0.12
B16: FIVE-YEAR DISCOUNTED GROSS PROFIT PER CUSTOMER
B17: Line | C17: Year 1 | D17: Year 2 | E17: Year 3 | F17: Year 4 | G17: Year 5 | H17: Total
B18: Revenue per retained customer | C18: =$C$9 -> 32000 | D18: =C18*$C$11 -> 35840 | E18: =D18*$C$11 -> 40140.8 | F18: =E18*$C$11 -> 44957.696 | G18: =F18*$C$11 -> 50352.62
B19: Gross profit per customer | C19: =C18*$C$10 -> 24960 | D19: =D18*$C$10 -> 27955.2 | E19: =E18*$C$10 -> 31309.824 | F19: =F18*$C$10 -> 35067.003 | G19: =G18*$C$10 -> 39275.043
B20: Discount factor | C20: =1/(1+$C$14)^1 -> 0.89285714 | D20: =1/(1+$C$14)^2 -> 0.79719388 | E20: =1/(1+$C$14)^3 -> 0.71178025 | F20: =1/(1+$C$14)^4 -> 0.63551808 | G20: =1/(1+$C$14)^5 -> 0.56742686
B21: PV of gross profit | C21: =C19*C20 -> 22285.714 | D21: =D19*D20 -> 22285.714 | E21: =E19*E20 -> 22285.714 | F21: =F19*F20 -> 22285.714 | G21: =G19*G20 -> 22285.714 | H21: =SUM(C21:G21) -> 111428.57
B23: HEADLINE METRICS
B24: Metric | C24: Value | H24: Benchmark
B25: Lifetime value (5-yr, discounted) | C25: =$H$21 -> 111428.57 | H25: Capped at five years. A perpetuity formula diverges when NRR meets or exceeds the discount rate.
B26: Customer acquisition cost | C26: =$C$13 -> 28000 | H26: Fully loaded sales and marketing per new logo.
B27: LTV / CAC | C27: =IFERROR($H$21/$C$13,0) -> 3.9795918 | H27: Venture bar is 3.0x. Below 2.0x the model does not fund its own growth.
B28: CAC payback | C28: =IFERROR($C$13/(C19/12),0) -> 13.461538 | H28: Months. Best-in-class vertical SaaS is 12 to 18 months; above 24 months is a financing problem.
B29: Year 1 gross profit per customer | C29: =C19 -> 24960 | H29: Annual contribution before sales, engineering and overhead.
B30: Implied average customer life | C30: =IFERROR(1/(1-$C$12),0) -> 8.3333333 | H30: Years. Shown for reference only; the LTV above deliberately ignores it and stops at five years.
B32: Note: LTV is deliberately conservative. It assumes no customer survives beyond five years and applies a 12% discount rate to the gross profit stream. A perpetuity-based LTV on the base case would be unbounded, which is why that convention is rejected here.

Sheet Financial Build
B2: FIVE-YEAR FINANCIAL BUILD
B4: ARR bridge, profit and loss and capital requirement. All operating cost lines are blue inputs on this page.
B6: ACTIVE SCENARIO | C6: =Assumptions!$C$6 -> Base
B8: Line Item | C8: Year 1 | D8: Year 2 | E8: Year 3 | F8: Year 4 | G8: Year 5 | H8: Note
B9: CUSTOMER COUNT
B10: New logos added | C10: =Assumptions!$C$12 -> 8 | D10: =Assumptions!$C$13 -> 28 | E10: =Assumptions!$C$14 -> 48 | F10: =Assumptions!$C$15 -> 70 | G10: =Assumptions!$C$16 -> 95 | H10: From the Assumptions tab; scenario driven.
B11: Beginning customers | C11: 0 | D11: =C13 -> 8 | E11: =D13 -> 35.04 | F11: =E13 -> 78.8352 | G11: =F13 -> 139.37498 | H11: Prior year ending balance.
B12: Churned customers | C12: =-C11*(1-Assumptions!$C$18) -> 0 | D12: =-D11*(1-Assumptions!$C$18) -> -0.96 | E12: =-E11*(1-Assumptions!$C$18) -> -4.2048 | F12: =-F11*(1-Assumptions!$C$18) -> -9.460224 | G12: =-G11*(1-Assumptions!$C$18) -> -16.724997 | H12: Beginning balance multiplied by one minus gross logo retention.
B13: Ending customers | C13: =C11+C10+C12 -> 8 | D13: =D11+D10+D12 -> 35.04 | E13: =E11+E10+E12 -> 78.8352 | F13: =F11+F10+F12 -> 139.37498 | G13: =G11+G10+G12 -> 217.64998 | H13: Drives the ARR bridge below.
B14: ARR BRIDGE
B15: New-logo ACV | C15: =Assumptions!$C$10*(1+Assumptions!$C$11)^0 -> 32000 | D15: =Assumptions!$C$10*(1+Assumptions!$C$11)^1 -> 33280 | E15: =Assumptions!$C$10*(1+Assumptions!$C$11)^2 -> 34611.2 | F15: =Assumptions!$C$10*(1+Assumptions!$C$11)^3 -> 35995.648 | G15: =Assumptions!$C$10*(1+Assumptions!$C$11)^4 -> 37435.474 | H15: Escalates annually on new logos only, to avoid double counting expansion.
B16: Beginning ARR | C16: 0 | D16: =C20 -> 256000 | E16: =D20 -> 1218560 | F16: =E20 -> 3026124.8 | G16: =F20 -> 5908955.1 | H16: Prior year ending ARR.
B17: New ARR | C17: =C10*C15 -> 256000 | D17: =D10*D15 -> 931840 | E17: =E10*E15 -> 1661337.6 | F17: =F10*F15 -> 2519695.4 | G17: =G10*G15 -> 3556370 | H17: New logos multiplied by that year's new-logo ACV.
B18: Expansion ARR | C18: =C16*(Assumptions!$C$19-Assumptions!$C$18) -> 0 | D18: =D16*(Assumptions!$C$19-Assumptions!$C$18) -> 61440 | E18: =E16*(Assumptions!$C$19-Assumptions!$C$18) -> 292454.4 | F18: =F16*(Assumptions!$C$19-Assumptions!$C$18) -> 726269.95 | G18: =G16*(Assumptions!$C$19-Assumptions!$C$18) -> 1418149.2 | H18: NRR less gross logo retention isolates upsell on the surviving base.
B19: Churned ARR | C19: =-C16*(1-Assumptions!$C$18) -> 0 | D19: =-D16*(1-Assumptions!$C$18) -> -30720 | E19: =-E16*(1-Assumptions!$C$18) -> -146227.2 | F19: =-F16*(1-Assumptions!$C$18) -> -363134.98 | G19: =-G16*(1-Assumptions!$C$18) -> -709074.62 | H19: Revenue lost to logo churn.
B20: Ending ARR | C20: =C16+C17+C18+C19 -> 256000 | D20: =D16+D17+D18+D19 -> 1218560 | E20: =E16+E17+E18+E19 -> 3026124.8 | F20: =F16+F17+F18+F19 -> 5908955.1 | G20: =G16+G17+G18+G19 -> 10174400 | H20: The headline number a Series A investor will index on.
B21: PROFIT AND LOSS
B22: Revenue (recognised) | C22: =AVERAGE(C16,C20) -> 128000 | D22: =AVERAGE(D16,D20) -> 737280 | E22: =AVERAGE(E16,E20) -> 2122342.4 | F22: =AVERAGE(F16,F20) -> 4467540 | G22: =AVERAGE(G16,G20) -> 8041677.5 | H22: Approximated as the average of beginning and ending ARR, reflecting mid-year contract starts.
B23: Cost of revenue | C23: =-C22*(1-Assumptions!$C$20) -> -28160 | D23: =-D22*(1-Assumptions!$C$20) -> -162201.6 | E23: =-E22*(1-Assumptions!$C$20) -> -466915.33 | F23: =-F22*(1-Assumptions!$C$20) -> -982858.79 | G23: =-G22*(1-Assumptions!$C$20) -> -1769169 | H23: Data acquisition, third-party licences, hosting and the data operations team.
B24: Gross profit | C24: =C22+C23 -> 99840 | D24: =D22+D23 -> 575078.4 | E24: =E22+E23 -> 1655427.1 | F24: =F22+F23 -> 3484681.2 | G24: =G22+G23 -> 6272508.4
B25: Sales and marketing: new-logo CAC | C25: =-C10*Assumptions!$C$22 -> -224000 | D25: =-D10*Assumptions!$C$22 -> -784000 | E25: =-E10*Assumptions!$C$22 -> -1344000 | F25: =-F10*Assumptions!$C$22 -> -1960000 | G25: =-G10*Assumptions!$C$22 -> -2660000 | H25: New logos multiplied by CAC. Excludes customer success, which sits in cost of revenue.
B26: Sales and marketing: overhead | C26: -150000 | D26: -500000 | E26: -900000 | F26: -1300000 | G26: -1700000 | H26: Blue input. Sales leadership, marketing programmes, conferences and the expansion-selling motion, none of which are captured in new-logo CAC.
B27: Total sales and marketing | C27: =C25+C26 -> -374000 | D27: =D25+D26 -> -1284000 | E27: =E25+E26 -> -2244000 | F27: =F25+F26 -> -3260000 | G27: =G25+G26 -> -4360000
B28: Research and development | C28: -900000 | D28: -1600000 | E28: -2400000 | F28: -3200000 | G28: -4000000 | H28: Blue input. Assumes 4 engineers in Year 1 rising to 16 by Year 5, fully loaded at roughly $225k.
B29: General and administrative | C29: -400000 | D29: -700000 | E29: -1000000 | F29: -1400000 | G29: -1800000 | H29: Blue input. Finance, legal, insurance, facilities and founder compensation.
B30: EBITDA | C30: =C24+C27+C28+C29 -> -1574160 | D30: =D24+D27+D28+D29 -> -3008921.6 | E30: =E24+E27+E28+E29 -> -3988572.9 | F30: =F24+F27+F28+F29 -> -4375318.8 | G30: =G24+G27+G28+G29 -> -3887491.6
B31: EBITDA margin | C31: =IFERROR(C30/C22,0) -> -12.298125 | D31: =IFERROR(D30/D22,0) -> -4.0811111 | E31: =IFERROR(E30/E22,0) -> -1.8793258 | F31: =IFERROR(F30/F22,0) -> -0.97935751 | G31: =IFERROR(G30/G22,0) -> -0.48341799 | H31: Negative through the investment period, as expected for this stage.
B32: CAPITAL AND EFFICIENCY
B33: Cumulative EBITDA | C33: =C30 -> -1574160 | D33: =C33+D30 -> -4583081.6 | E33: =D33+E30 -> -8571654.5 | F33: =E33+F30 -> -12946973 | G33: =F33+G30 -> -16834465 | H33: Peak negative value is the approximate equity requirement before profitability.
B34: Peak equity requirement | C34: =-MIN($C33:C33) -> 1574160 | D34: =-MIN($C33:D33) -> 4583081.6 | E34: =-MIN($C33:E33) -> 8571654.5 | F34: =-MIN($C33:F33) -> 12946973 | G34: =-MIN($C33:G33) -> 16834465 | H34: Running low-water mark of cumulative EBITDA. This is the approximate equity the plan consumes before it turns.
B35: Magic number | C35: 0 | D35: =IFERROR((D20-C20)/-C27,0) -> 2.5736898 | E35: =IFERROR((E20-D20)/-D27,0) -> 1.4077607 | F35: =IFERROR((F20-E20)/-E27,0) -> 1.2846838 | G35: =IFERROR((G20-F20)/-F27,0) -> 1.3084186 | H35: Net new ARR divided by prior-year total sales and marketing. Above 0.75 justifies accelerating spend; above 1.5 usually means the CAC assumption is too optimistic.
B36: Headcount (period end) | C36: 9 | D36: 18 | E36: 30 | F36: 44 | G36: 60 | H36: Blue input. Engineering, data operations, sales and administration combined.
B37: Ending ARR per employee | C37: =IFERROR(C20/C36,0) -> 28444.444 | D37: =IFERROR(D20/D36,0) -> 67697.778 | E37: =IFERROR(E20/E36,0) -> 100870.83 | F37: =IFERROR(F20/F36,0) -> 134294.43 | G37: =IFERROR(G20/G36,0) -> 169573.33 | H37: Efficiency check. Vertical SaaS at scale targets $150k to $250k.
B39: Note: revenue recognition is approximated rather than cohort-modelled, which understates Year 1 and overstates nothing material thereafter. Operating cost lines are entered directly rather than derived from headcount, so headcount is a memo line and does not drive the profit and loss.

Sheet Sensitivity
B2: SENSITIVITY ANALYSIS
B4: Computed on the Base scenario inputs for ACV, gross margin and discount rate. Base-case cell is outlined.
B6: LTV / CAC: NET REVENUE RETENTION VERSUS CUSTOMER ACQUISITION COST
B7: NRR \ CAC | C7: 20000 | D7: 24000 | E7: 28000 | F7: 32000 | G7: 36000 | H7: 40000
B8: 1 | C8: =(Assumptions!$E$10*Assumptions!$E$20*(1/(1+Assumptions!$E$23)+$B8/(1+Assumptions!$E$23)^2+$B8^2/(1+Assumptions!$E$23)^3+$B8^3/(1+Assumptions!$E$23)^4+$B8^4/(1+Assumptions!$E$23)^5))/C$7 -> 4.4987607 | D8: =(Assumptions!$E$10*Assumptions!$E$20*(1/(1+Assumptions!$E$23)+$B8/(1+Assumptions!$E$23)^2+$B8^2/(1+Assumptions!$E$23)^3+$B8^3/(1+Assumptions!$E$23)^4+$B8^4/(1+Assumptions!$E$23)^5))/D$7 -> 3.7489673 | E8: =(Assumptions!$E$10*Assumptions!$E$20*(1/(1+Assumptions!$E$23)+$B8/(1+Assumptions!$E$23)^2+$B8^2/(1+Assumptions!$E$23)^3+$B8^3/(1+Assumptions!$E$23)^4+$B8^4/(1+Assumptions!$E$23)^5))/E$7 -> 3.2134005 | F8: =(Assumptions!$E$10*Assumptions!$E$20*(1/(1+Assumptions!$E$23)+$B8/(1+Assumptions!$E$23)^2+$B8^2/(1+Assumptions!$E$23)^3+$B8^3/(1+Assumptions!$E$23)^4+$B8^4/(1+Assumptions!$E$23)^5))/F$7 -> 2.8117254 | G8: =(Assumptions!$E$10*Assumptions!$E$20*(1/(1+Assumptions!$E$23)+$B8/(1+Assumptions!$E$23)^2+$B8^2/(1+Assumptions!$E$23)^3+$B8^3/(1+Assumptions!$E$23)^4+$B8^4/(1+Assumptions!$E$23)^5))/G$7 -> 2.4993115 | H8: =(Assumptions!$E$10*Assumptions!$E$20*(1/(1+Assumptions!$E$23)+$B8/(1+Assumptions!$E$23)^2+$B8^2/(1+Assumptions!$E$23)^3+$B8^3/(1+Assumptions!$E$23)^4+$B8^4/(1+Assumptions!$E$23)^5))/H$7 -> 2.2493804
B9: 1.06 | C9: =(Assumptions!$E$10*Assumptions!$E$20*(1/(1+Assumptions!$E$23)+$B9/(1+Assumptions!$E$23)^2+$B9^2/(1+Assumptions!$E$23)^3+$B9^3/(1+Assumptions!$E$23)^4+$B9^4/(1+Assumptions!$E$23)^5))/C$7 -> 5.0056213 | D9: =(Assumptions!$E$10*Assumptions!$E$20*(1/(1+Assumptions!$E$23)+$B9/(1+Assumptions!$E$23)^2+$B9^2/(1+Assumptions!$E$23)^3+$B9^3/(1+Assumptions!$E$23)^4+$B9^4/(1+Assumptions!$E$23)^5))/D$7 -> 4.171351 | E9: =(Assumptions!$E$10*Assumptions!$E$20*(1/(1+Assumptions!$E$23)+$B9/(1+Assumptions!$E$23)^2+$B9^2/(1+Assumptions!$E$23)^3+$B9^3/(1+Assumptions!$E$23)^4+$B9^4/(1+Assumptions!$E$23)^5))/E$7 -> 3.5754438 | F9: =(Assumptions!$E$10*Assumptions!$E$20*(1/(1+Assumptions!$E$23)+$B9/(1+Assumptions!$E$23)^2+$B9^2/(1+Assumptions!$E$23)^3+$B9^3/(1+Assumptions!$E$23)^4+$B9^4/(1+Assumptions!$E$23)^5))/F$7 -> 3.1285133 | G9: =(Assumptions!$E$10*Assumptions!$E$20*(1/(1+Assumptions!$E$23)+$B9/(1+Assumptions!$E$23)^2+$B9^2/(1+Assumptions!$E$23)^3+$B9^3/(1+Assumptions!$E$23)^4+$B9^4/(1+Assumptions!$E$23)^5))/G$7 -> 2.7809007 | H9: =(Assumptions!$E$10*Assumptions!$E$20*(1/(1+Assumptions!$E$23)+$B9/(1+Assumptions!$E$23)^2+$B9^2/(1+Assumptions!$E$23)^3+$B9^3/(1+Assumptions!$E$23)^4+$B9^4/(1+Assumptions!$E$23)^5))/H$7 -> 2.5028106
B10: 1.12 | C10: =(Assumptions!$E$10*Assumptions!$E$20*(1/(1+Assumptions!$E$23)+$B10/(1+Assumptions!$E$23)^2+$B10^2/(1+Assumptions!$E$23)^3+$B10^3/(1+Assumptions!$E$23)^4+$B10^4/(1+Assumptions!$E$23)^5))/C$7 -> 5.5714286 | D10: =(Assumptions!$E$10*Assumptions!$E$20*(1/(1+Assumptions!$E$23)+$B10/(1+Assumptions!$E$23)^2+$B10^2/(1+Assumptions!$E$23)^3+$B10^3/(1+Assumptions!$E$23)^4+$B10^4/(1+Assumptions!$E$23)^5))/D$7 -> 4.6428571 | E10: =(Assumptions!$E$10*Assumptions!$E$20*(1/(1+Assumptions!$E$23)+$B10/(1+Assumptions!$E$23)^2+$B10^2/(1+Assumptions!$E$23)^3+$B10^3/(1+Assumptions!$E$23)^4+$B10^4/(1+Assumptions!$E$23)^5))/E$7 -> 3.9795918 | F10: =(Assumptions!$E$10*Assumptions!$E$20*(1/(1+Assumptions!$E$23)+$B10/(1+Assumptions!$E$23)^2+$B10^2/(1+Assumptions!$E$23)^3+$B10^3/(1+Assumptions!$E$23)^4+$B10^4/(1+Assumptions!$E$23)^5))/F$7 -> 3.4821429 | G10: =(Assumptions!$E$10*Assumptions!$E$20*(1/(1+Assumptions!$E$23)+$B10/(1+Assumptions!$E$23)^2+$B10^2/(1+Assumptions!$E$23)^3+$B10^3/(1+Assumptions!$E$23)^4+$B10^4/(1+Assumptions!$E$23)^5))/G$7 -> 3.0952381 | H10: =(Assumptions!$E$10*Assumptions!$E$20*(1/(1+Assumptions!$E$23)+$B10/(1+Assumptions!$E$23)^2+$B10^2/(1+Assumptions!$E$23)^3+$B10^3/(1+Assumptions!$E$23)^4+$B10^4/(1+Assumptions!$E$23)^5))/H$7 -> 2.7857143
B11: 1.18 | C11: =(Assumptions!$E$10*Assumptions!$E$20*(1/(1+Assumptions!$E$23)+$B11/(1+Assumptions!$E$23)^2+$B11^2/(1+Assumptions!$E$23)^3+$B11^3/(1+Assumptions!$E$23)^4+$B11^4/(1+Assumptions!$E$23)^5))/C$7 -> 6.201212 | D11: =(Assumptions!$E$10*Assumptions!$E$20*(1/(1+Assumptions!$E$23)+$B11/(1+Assumptions!$E$23)^2+$B11^2/(1+Assumptions!$E$23)^3+$B11^3/(1+Assumptions!$E$23)^4+$B11^4/(1+Assumptions!$E$23)^5))/D$7 -> 5.1676766 | E11: =(Assumptions!$E$10*Assumptions!$E$20*(1/(1+Assumptions!$E$23)+$B11/(1+Assumptions!$E$23)^2+$B11^2/(1+Assumptions!$E$23)^3+$B11^3/(1+Assumptions!$E$23)^4+$B11^4/(1+Assumptions!$E$23)^5))/E$7 -> 4.4294371 | F11: =(Assumptions!$E$10*Assumptions!$E$20*(1/(1+Assumptions!$E$23)+$B11/(1+Assumptions!$E$23)^2+$B11^2/(1+Assumptions!$E$23)^3+$B11^3/(1+Assumptions!$E$23)^4+$B11^4/(1+Assumptions!$E$23)^5))/F$7 -> 3.8757575 | G11: =(Assumptions!$E$10*Assumptions!$E$20*(1/(1+Assumptions!$E$23)+$B11/(1+Assumptions!$E$23)^2+$B11^2/(1+Assumptions!$E$23)^3+$B11^3/(1+Assumptions!$E$23)^4+$B11^4/(1+Assumptions!$E$23)^5))/G$7 -> 3.4451178 | H11: =(Assumptions!$E$10*Assumptions!$E$20*(1/(1+Assumptions!$E$23)+$B11/(1+Assumptions!$E$23)^2+$B11^2/(1+Assumptions!$E$23)^3+$B11^3/(1+Assumptions!$E$23)^4+$B11^4/(1+Assumptions!$E$23)^5))/H$7 -> 3.100606
B12: 1.24 | C12: =(Assumptions!$E$10*Assumptions!$E$20*(1/(1+Assumptions!$E$23)+$B12/(1+Assumptions!$E$23)^2+$B12^2/(1+Assumptions!$E$23)^3+$B12^3/(1+Assumptions!$E$23)^4+$B12^4/(1+Assumptions!$E$23)^5))/C$7 -> 6.900221 | D12: =(Assumptions!$E$10*Assumptions!$E$20*(1/(1+Assumptions!$E$23)+$B12/(1+Assumptions!$E$23)^2+$B12^2/(1+Assumptions!$E$23)^3+$B12^3/(1+Assumptions!$E$23)^4+$B12^4/(1+Assumptions!$E$23)^5))/D$7 -> 5.7501842 | E12: =(Assumptions!$E$10*Assumptions!$E$20*(1/(1+Assumptions!$E$23)+$B12/(1+Assumptions!$E$23)^2+$B12^2/(1+Assumptions!$E$23)^3+$B12^3/(1+Assumptions!$E$23)^4+$B12^4/(1+Assumptions!$E$23)^5))/E$7 -> 4.9287293 | F12: =(Assumptions!$E$10*Assumptions!$E$20*(1/(1+Assumptions!$E$23)+$B12/(1+Assumptions!$E$23)^2+$B12^2/(1+Assumptions!$E$23)^3+$B12^3/(1+Assumptions!$E$23)^4+$B12^4/(1+Assumptions!$E$23)^5))/F$7 -> 4.3126381 | G12: =(Assumptions!$E$10*Assumptions!$E$20*(1/(1+Assumptions!$E$23)+$B12/(1+Assumptions!$E$23)^2+$B12^2/(1+Assumptions!$E$23)^3+$B12^3/(1+Assumptions!$E$23)^4+$B12^4/(1+Assumptions!$E$23)^5))/G$7 -> 3.8334561 | H12: =(Assumptions!$E$10*Assumptions!$E$20*(1/(1+Assumptions!$E$23)+$B12/(1+Assumptions!$E$23)^2+$B12^2/(1+Assumptions!$E$23)^3+$B12^3/(1+Assumptions!$E$23)^4+$B12^4/(1+Assumptions!$E$23)^5))/H$7 -> 3.4501105
B14: Reads: the base case clears the 3.0x venture bar with limited headroom. LTV/CAC falls below 3.0x whenever CAC exceeds roughly $32k at base retention, which makes sales efficiency the single most important operating discipline in the plan.
B18: YEAR 5 ENDING ARR: CUSTOMER COUNT VERSUS BLENDED ACV
B19: Customers \ ACV | C19: 28000 | D19: 32000 | E19: 36000 | F19: 40000 | G19: 44000
B20: 150 | C20: =$B20*C$19 -> 4200000 | D20: =$B20*D$19 -> 4800000 | E20: =$B20*E$19 -> 5400000 | F20: =$B20*F$19 -> 6000000 | G20: =$B20*G$19 -> 6600000
B21: 185 | C21: =$B21*C$19 -> 5180000 | D21: =$B21*D$19 -> 5920000 | E21: =$B21*E$19 -> 6660000 | F21: =$B21*F$19 -> 7400000 | G21: =$B21*G$19 -> 8140000
B22: 220 | C22: =$B22*C$19 -> 6160000 | D22: =$B22*D$19 -> 7040000 | E22: =$B22*E$19 -> 7920000 | F22: =$B22*F$19 -> 8800000 | G22: =$B22*G$19 -> 9680000
B23: 255 | C23: =$B23*C$19 -> 7140000 | D23: =$B23*D$19 -> 8160000 | E23: =$B23*E$19 -> 9180000 | F23: =$B23*F$19 -> 10200000 | G23: =$B23*G$19 -> 11220000
B24: 290 | C24: =$B24*C$19 -> 8120000 | D24: =$B24*D$19 -> 9280000 | E24: =$B24*E$19 -> 10440000 | F24: =$B24*F$19 -> 11600000 | G24: =$B24*G$19 -> 12760000
B26: Reads: an $8M to $9M Year 5 ARR is the realistic base outcome and is an independent cross-check on the Financial Build tab, which arrives at a similar figure by a different route. Clearing $12M by Year 5 requires either 290 customers, which is 12% of the entire addressable universe, or a $44k ACV, which implies selling the full asset performance product rather than capex data alone.

Sheet Competitive Map
B2: COMPETITIVE MAP
B4: Overlap rated High, Medium or Low. Shading: red denotes a crowded lane, green denotes open space.
B6: Player | C6: Primary Buyer | D6: What It Does | E6: Overlap: Capex Data | F6: Overlap: Owner Reporting | G6: Implication
B7: Actabl (ProfitSword, Transcendent, Hotel Effectiveness) | C7: Management companies; large owners | D7: Portfolio budgeting, business intelligence, labour management and enterprise asset management including capex planning. The most complete suite in the market. | E7: Medium | F7: High | G7: The incumbent to beat on reporting. Transcendent gives them a capex adjacency, but it manages a single owner's capex, it does not benchmark across owners.
B8: Otelier (IntelliSight) | C8: Management companies; institutional owners | D8: Data centralisation and normalisation across PMS and accounting systems, with more than 100 prebuilt hospitality dashboards. | E8: Low | F8: High | G8: Directly sells the owner normalisation use case. Highline Hospitality, a 21-hotel $1.7B owner, deployed it for exactly that. This closes the door on a pure normalisation pitch.
B9: Inn-Flow | C9: Small and mid-market operators | D9: Accounting, payroll, labour and procurement with embedded BI. Number one ranked hotel accounting product in the 2026 HotelTechAwards. | E9: Low | F9: Medium | G9: Owns the mid-market back office. A partner rather than a competitor if the product sits above the ledger.
B10: M3 / Aptech | C10: Management companies | D10: Hospitality-specific accounting and financial reporting. Deep installed base. | E10: Low | F10: Medium | G10: System of record, not system of insight. The natural integration target.
B11: HVS and Nehmer Cost Estimating Guide | C11: Owners, appraisers, contractors | D11: Annual published guide to hotel construction and renovation cost tiers by category and scope. | E11: High | F11: Low | G11: The closest thing to a capex benchmark today, and it is a static annual publication rather than a queryable dataset tied to actual outcomes.
B12: ISHC CapEx Study (with HAMA) | C12: Owners and asset managers | D12: Periodic industry study of hotel capital expenditure, described as the industry's exclusive capex resource. | E12: High | F12: Low | G12: Confirms the demand and confirms the gap. A study published every few years is not a product.
B13: STR / CoStar | C13: Everyone | D13: Benchmarking of occupancy, ADR and RevPAR. The industry's revenue-side data standard. | E13: Low | F13: Medium | G13: The proof that a hospitality data monopoly can be built and defended. Also the most credible acquirer, and the most dangerous entrant if they move to the cost side.
B14: CBRE, JLL and Newmark hotels advisory | C14: Owners and lenders | D14: Transaction advisory, valuation and consulting. Hold significant proprietary capex data inside deal files. | E14: High | F14: Low | G14: Sit on the data but monetise it as billable hours. Structurally unlikely to productise it, and plausible design partners.
B15: Lodging Econometrics | C15: Developers, brands, lenders | D15: Construction pipeline and development tracking data. | E15: Medium | F15: Low | G15: Adjacent dataset. Pipeline, not cost. A partnership or data-swap candidate.
B17: CONCLUSION
B18: The owner reporting lane reads red because it is red. Otelier and Actabl are both funded, both shipping, and at least one has publicly landed the exact institutional-owner normalisation use case. Entering that lane head-on means competing on features against companies with a five-year head start and no differentiated access. The capex and PIP benchmarking lane reads green because the only participants are a consulting firm publishing an annual book, an industry association publishing a periodic study, and brokerages sitting on the data while billing hours against it. None of them are building a live, queryable dataset, and none of them are structurally motivated to. That asymmetry, not the software, is the business.
B24: Sources: Actabl product pages (actabl.com); Otelier press release, Highline Hospitality Partners deployment, 21 hotels and $1.7B AUM; Otelier and Stonebridge partnership, 160 hotels; Inn-Flow, 2026 HotelTechAwards; ISHC CapEx 2023 study with HAMA; HVS / Nehmer 2025 Hotel Cost Estimating Guide. Accessed 10 September 2026.
