Workbook
Name \a: #N/A
Name \b: #REF!
Name \c: #REF!
Name \d: #N/A
Name \e: #REF!
Name \F: #REF!
Name \i: #REF!
Name \m: #REF!
Name \o: #REF!
Name \p: #REF!
Name \q: #REF!
Name \R: #REF!
Name \s: #REF!
Name \T: #REF!
Name \x: #REF!
Name \Z: #REF!
Name ___CO_PROJ: #REF!
Name __blg300: #REF!
Name __Dumpster: 0
Name _001_LOC_APPLICATION_SOURCE: #REF!
Name _010_LETTER_OF_CREDIT_SOURCE: #REF!
Name _1_: #REF!
Name _1_1: #REF!
Name _10AC: #REF!
Name _11AUG_98: #REF!
Name _12CASH_REC: #REF!
Name _13CSH: #REF!
Name _14DECEMBER_98: #REF!
Name _15E: #REF!
Name _16NOVEMBER_98: #REF!
Name _17OCTOBER_98: #REF!
Name _18PL: #REF!
Name _19Module2_.PRINT_BCCAM: #N/A
Name _19SEPTEMBER_98: #REF!
Name _1Module2_.PRINT_BCCAM: #N/A
Name _1REPLA: #REF!
Name _2_: #REF!
Name _20__GS_Margin: #REF!
Name _2004: #REF!
Name _2005: #REF!
Name _2006: #REF!
Name _2007: #REF!
Name _2008: #REF!
Name _2009: #REF!
Name _2010: #REF!
Name _2011: #REF!
Name _2012: #REF!
Name _2013: #REF!
Name _2013_: #REF!
Name _2014: #REF!
Name _2015: #REF!
Name _20SUBPL: #REF!
Name _22505.5471: #REF!
Name _22505.5472: #REF!
Name _22505.5473: #REF!
Name _22505.5474: #REF!
Name _22505.5475: #REF!
Name _22505.5477: #REF!
Name _22505.5479: #REF!
Name _22510.5471: #REF!

Sheet Cover
D10: Private and Confidential
D20: KKR RECOP I LP Secondary Opportunity

Sheet Fwd Returns
N1: Projected Investment Returns(A)
B3: Cutoff Month | I3: ='HTM Output'!G2 -> 46203
B4: Projected Transaction Date | I4: ='HTM Output'!G3 -> 46388
B6: Promote Assumed | C6: =IF(D6=0,"UW life of fund cash flows do not meet "&TEXT('HTM WF'!$D$28,"0.0%")&" promote hurdle","") -> UW life of fund cash flows do not meet 8.0% promote hurdle | I6: ='HTM WF'!$GS$84 -> 0
B7: IM Fee Assumed | C7: Fees are offset from SS fees received | I7: =Assumptions!$E$8 -> 0.0125
B8: Selling Investor % of Fund | I8: =Assumptions!$D$5 -> 0.3539823
U9: =SUMIFS('HTM Output'!$K$37:$GS$37,'HTM Output'!$K$6:$GS$6,">"&'HTM Output'!$G$3)*$I$8=SUM(U42:HB42) -> FALSE
C10: Bpiece Curr UPB | D10: Current Mark Px | U10: =YEAR(U11) -> 2027 | V10: =YEAR(V11) -> 2027 | W10: =YEAR(W11) -> 2027 | X10: =YEAR(X11) -> 2027 | Y10: =YEAR(Y11) -> 2027 | Z10: =YEAR(Z11) -> 2027 | AA10: =YEAR(AA11) -> 2027 | AB10: =YEAR(AB11) -> 2027 | ... HB10: =YEAR(HB11) -> 2042
B11: Investment | C11: Current Face | D11: KRR Mark Px | E11: KKR Current Mark | F11: Cash & Receivables | G11: KKR Current NAV | H11: Weighted Avg. Hold Period | I11: Investor NAV | J11: Purch Px | K11: Purchase Price | L11: Gross Distros During Cutoff Period | M11: Fees/Expenses During Cutoff Period | N11: Net Distros During Cutoff Period | O11: Adjusted Price | Q11: Fwd. IRR(B)(D) | R11: Fwd. MOIC(C)(E) | T11: =$I$4 -> 46388 | U11: =EOMONTH(I4+1,0) -> 46418 | V11: =EOMONTH(U11,1) -> 46446 | W11: =EOMONTH(V11,1) -> 46477 | X11: =EOMONTH(W11,1) -> 46507 | Y11: =EOMONTH(X11,1) -> 46538 | Z11: =EOMONTH(Y11,1) -> 46568 | AA11: =EOMONTH(Z11,1) -> 46599 | AB11: =EOMONTH(AA11,1) -> 46630 | AC11: =EOMONTH(AB11,1) -> 46660 | ... HB11: =EOMONTH(HA11,1) -> 52170 | HD11: =TEXT($I$4,"m/d/yyyy")&" Acquisition" -> 1/1/2027 Acquisition | HE11: =YEAR(U11) -> 2027 | HF11: =HE11+1 -> 2028 | HG11: =HF11+1 -> 2029 | HH11: =HG11+1 -> 2030 | HI11: =HH11+1 -> 2031 | HJ11: =HI11+1 -> 2032 | HK11: Total
B12: Valuation | Q12: ="Projected Cash Flows ("&TEXT($I$8,"0.0%")&" stake acquired)" -> Projected Cash Flows (35.4% stake acquired)
A14: UBSCM 2017-C2 B-Piece Cashflows | B14: UBSCM 2017-C2 | C14: =OFFSET(Strats!$B$3,MATCH($B14,Strats!$B$4:$B$31,0),MATCH(C$10,Strats!$C$3:$BS$3,0)) -> 85566944 | D14: =OFFSET(Strats!$B$3,MATCH($B14,Strats!$B$4:$B$31,0),MATCH(D$10,Strats!$C$3:$BS$3,0)) -> 0.83725914 | E14: =C14*D14 -> 71641706 | F14: =$F$42*$E14/$E$42 -> 1171339.2 | G14: =F14+E14 -> 72813045 | H14: =IFERROR(SUMPRODUCT('HTM Output'!$K73:$GS73,'HTM Output'!$K$6:$GS$6)/SUM('HTM Output'!$K73:$GS73),_xlfn.MAXIFS($U$11:$HB$11,$U$14:$HB$14,">"&0)) -> 47326.871 | I14: =G14*$I$8 -> 25774529 | J14: =$J$42 -> 0.5 | K14: =I14*J14 -> 12887265 | L14: =-SUMIFS('HTM Output'!$K9:$GS9,'HTM Output'!$K$6:$GS$6,">"&'HTM Output'!$G$2,'HTM Output'!$K$6:$GS$6,"<="&'HTM Output'!$G$3)*$I$8 -> -676020.86 | M14: =M$42*K14/$K$42 -> 36029.299 | N14: =L14+M14 -> -639991.56 | O14: =SUM(K14:M14) -> 12247273 | Q14: =IFERROR(XIRR($T14:$HB14,$T$11:$HB$11),"N/A") -> 0.47247028 | R14: =IFERROR((HK14+O14)/O14,"N/A") -> 2.522879 | T14: =IF(T$11>$I$4,SUMIFS('Pooled CF'!$E:$E,'Pooled CF'!$A:$A,$A14,'Pooled CF'!$G:$G,T$11),0)+IF(T$11=$I$4,-$O14) -> -12247273 | U14: =IFERROR(OFFSET('HTM Output'!$J$6,MATCH($B14,'HTM Output'!$B$7:$B$37,0),MATCH(U$11,'HTM Output'!$K$6:$GS$6,0)),0)*$I$8 -> 111958.62 | V14: =IFERROR(OFFSET('HTM Output'!$J$6,MATCH($B14,'HTM Output'!$B$7:$B$37,0),MATCH(V$11,'HTM Output'!$K$6:$GS$6,0)),0)*$I$8 -> 111945.12 | W14: =IFERROR(OFFSET('HTM Output'!$J$6,MATCH($B14,'HTM Output'!$B$7:$B$37,0),MATCH(W$11,'HTM Output'!$K$6:$GS$6,0)),0)*$I$8 -> 111857.09 | X14: =IFERROR(OFFSET('HTM Output'!$J$6,MATCH($B14,'HTM Output'!$B$7:$B$37,0),MATCH(X$11,'HTM Output'!$K$6:$GS$6,0)),0)*$I$8 -> 115063.6 | Y14: =IFERROR(OFFSET('HTM Output'!$J$6,MATCH($B14,'HTM Output'!$B$7:$B$37,0),MATCH(Y$11,'HTM Output'!$K$6:$GS$6,0)),0)*$I$8 -> 111338.41 | Z14: =IFERROR(OFFSET('HTM Output'!$J$6,MATCH($B14,'HTM Output'!$B$7:$B$37,0),MATCH(Z$11,'HTM Output'!$K$6:$GS$6,0)),0)*$I$8 -> 107229.35 | AA14: =IFERROR(OFFSET('HTM Output'!$J$6,MATCH($B14,'HTM Output'!$B$7:$B$37,0),MATCH(AA$11,'HTM Output'!$K$6:$GS$6,0)),0)*$I$8 -> 110115.03 | AB14: =IFERROR(OFFSET('HTM Output'!$J$6,MATCH($B14,'HTM Output'!$B$7:$B$37,0),MATCH(AB$11,'HTM Output'!$K$6:$GS$6,0)),0)*$I$8 -> 111175.12 | ... HB14: =IFERROR(OFFSET('HTM Output'!$J$6,MATCH($B14,'HTM Output'!$B$7:$B$37,0),MATCH(HB$11,'HTM Output'!$K$6:$GS$6,0)),0)*$I$8 -> 0 | HD14: =T14 -> -12247273 | HE14: =SUMIFS($T14:$HB14,$T$10:$HB$10,HE$11) -> 1290223.9 | HF14: =SUMIFS($T14:$HB14,$T$10:$HB$10,HF$11) -> 1180142.5 | HG14: =SUMIFS($T14:$HB14,$T$10:$HB$10,HG$11) -> 28428021 | HH14: =SUMIFS($T14:$HB14,$T$10:$HB$10,HH$11) -> 0 | HI14: =SUMIFS($T14:$HB14,$T$10:$HB$10,HI$11) -> 0 | HJ14: =SUMIFS($T14:$HB14,$T$10:$HB$10,HJ$11) -> 0 | HK14: =SUM(HD14:HJ14) -> 18651115
A15: CGCMT 2017-C4 B-Piece Cashflows | B15: CGCMT 2017-C4 | C15: =OFFSET(Strats!$B$3,MATCH($B15,Strats!$B$4:$B$31,0),MATCH(C$10,Strats!$C$3:$BS$3,0)) -> 105034893 | D15: =OFFSET(Strats!$B$3,MATCH($B15,Strats!$B$4:$B$31,0),MATCH(D$10,Strats!$C$3:$BS$3,0)) -> 0.65106574 | E15: =C15*D15 -> 68384620 | F15: =$F$42*$E15/$E$42 -> 1118086 | G15: =F15+E15 -> 69502706 | H15: =IFERROR(SUMPRODUCT('HTM Output'!$K74:$GS74,'HTM Output'!$K$6:$GS$6)/SUM('HTM Output'!$K74:$GS74),_xlfn.MAXIFS($U$11:$HB$11,$U$14:$HB$14,">"&0)) -> 47774.733 | I15: =G15*$I$8 -> 24602728 | J15: =$J$42 -> 0.5 | K15: =I15*J15 -> 12301364 | L15: =-SUMIFS('HTM Output'!$K10:$GS10,'HTM Output'!$K$6:$GS$6,">"&'HTM Output'!$G$2,'HTM Output'!$K$6:$GS$6,"<="&'HTM Output'!$G$3)*$I$8 -> -842771.53 | M15: =M$42*K15/$K$42 -> 34391.279 | N15: =L15+M15 -> -808380.25 | O15: =SUM(K15:M15) -> 11492984 | Q15: =IFERROR(XIRR($T15:$HB15,$T$11:$HB$11),"N/A") -> 0.23411383 | R15: =IFERROR((HK15+O15)/O15,"N/A") -> 2.0448715 | T15: =IF(T$11>$I$4,SUMIFS('Pooled CF'!$E:$E,'Pooled CF'!$A:$A,$A15,'Pooled CF'!$G:$G,T$11),0)+IF(T$11=$I$4,-$O15) -> -11492984 | U15: =IFERROR(OFFSET('HTM Output'!$J$6,MATCH($B15,'HTM Output'!$B$7:$B$37,0),MATCH(U$11,'HTM Output'!$K$6:$GS$6,0)),0)*$I$8 -> 135425.99 | V15: =IFERROR(OFFSET('HTM Output'!$J$6,MATCH($B15,'HTM Output'!$B$7:$B$37,0),MATCH(V$11,'HTM Output'!$K$6:$GS$6,0)),0)*$I$8 -> 135420.62 | W15: =IFERROR(OFFSET('HTM Output'!$J$6,MATCH($B15,'HTM Output'!$B$7:$B$37,0),MATCH(W$11,'HTM Output'!$K$6:$GS$6,0)),0)*$I$8 -> 126140.98 | X15: =IFERROR(OFFSET('HTM Output'!$J$6,MATCH($B15,'HTM Output'!$B$7:$B$37,0),MATCH(X$11,'HTM Output'!$K$6:$GS$6,0)),0)*$I$8 -> 129641.59 | Y15: =IFERROR(OFFSET('HTM Output'!$J$6,MATCH($B15,'HTM Output'!$B$7:$B$37,0),MATCH(Y$11,'HTM Output'!$K$6:$GS$6,0)),0)*$I$8 -> 125456.36 | Z15: =IFERROR(OFFSET('HTM Output'!$J$6,MATCH($B15,'HTM Output'!$B$7:$B$37,0),MATCH(Z$11,'HTM Output'!$K$6:$GS$6,0)),0)*$I$8 -> 129634.63 | AA15: =IFERROR(OFFSET('HTM Output'!$J$6,MATCH($B15,'HTM Output'!$B$7:$B$37,0),MATCH(AA$11,'HTM Output'!$K$6:$GS$6,0)),0)*$I$8 -> 126669.99 | AB15: =IFERROR(OFFSET('HTM Output'!$J$6,MATCH($B15,'HTM Output'!$B$7:$B$37,0),MATCH(AB$11,'HTM Output'!$K$6:$GS$6,0)),0)*$I$8 -> 131570.93 | ... HB15: =IFERROR(OFFSET('HTM Output'!$J$6,MATCH($B15,'HTM Output'!$B$7:$B$37,0),MATCH(HB$11,'HTM Output'!$K$6:$GS$6,0)),0)*$I$8 -> 0 | HD15: =T15 -> -11492984 | HE15: =SUMIFS($T15:$HB15,$T$10:$HB$10,HE$11) -> 1402180 | HF15: =SUMIFS($T15:$HB15,$T$10:$HB$10,HF$11) -> 782553.05 | HG15: =SUMIFS($T15:$HB15,$T$10:$HB$10,HG$11) -> 3445700.2 | HH15: =SUMIFS($T15:$HB15,$T$10:$HB$10,HH$11) -> 9225187.7 | HI15: =SUMIFS($T15:$HB15,$T$10:$HB$10,HI$11) -> 8646054.1 | HJ15: =SUMIFS($T15:$HB15,$T$10:$HB$10,HJ$11) -> 0 | HK15: =SUM(HD15:HJ15) -> 12008691
A16: WFCM 2018-C47 B-Piece Cashflows | B16: WFCM 2018-C47 | C16: =OFFSET(Strats!$B$3,MATCH($B16,Strats!$B$4:$B$31,0),MATCH(C$10,Strats!$C$3:$BS$3,0)) -> 91373439 | D16: =OFFSET(Strats!$B$3,MATCH($B16,Strats!$B$4:$B$31,0),MATCH(D$10,Strats!$C$3:$BS$3,0)) -> 0.57207853 | E16: =C16*D16 -> 52272783 | F16: =$F$42*$E16/$E$42 -> 854658.02 | G16: =F16+E16 -> 53127441 | H16: =IFERROR(SUMPRODUCT('HTM Output'!$K75:$GS75,'HTM Output'!$K$6:$GS$6)/SUM('HTM Output'!$K75:$GS75),_xlfn.MAXIFS($U$11:$HB$11,$U$14:$HB$14,">"&0)) -> 47781.407 | I16: =G16*$I$8 -> 18806174 | J16: =$J$42 -> 0.5 | K16: =I16*J16 -> 9403086.8 | L16: =-SUMIFS('HTM Output'!$K11:$GS11,'HTM Output'!$K$6:$GS$6,">"&'HTM Output'!$G$2,'HTM Output'!$K$6:$GS$6,"<="&'HTM Output'!$G$3)*$I$8 -> -759147.17 | M16: =M$42*K16/$K$42 -> 26288.482 | N16: =L16+M16 -> -732858.69 | O16: =SUM(K16:M16) -> 8670228.1 | Q16: =IFERROR(XIRR($T16:$HB16,$T$11:$HB$11),"N/A") -> 0.27767276 | R16: =IFERROR((HK16+O16)/O16,"N/A") -> 2.1959625 | T16: =IF(T$11>$I$4,SUMIFS('Pooled CF'!$E:$E,'Pooled CF'!$A:$A,$A16,'Pooled CF'!$G:$G,T$11),0)+IF(T$11=$I$4,-$O16) -> -8670228.1 | U16: =IFERROR(OFFSET('HTM Output'!$J$6,MATCH($B16,'HTM Output'!$B$7:$B$37,0),MATCH(U$11,'HTM Output'!$K$6:$GS$6,0)),0)*$I$8 -> 126386.91 | V16: =IFERROR(OFFSET('HTM Output'!$J$6,MATCH($B16,'HTM Output'!$B$7:$B$37,0),MATCH(V$11,'HTM Output'!$K$6:$GS$6,0)),0)*$I$8 -> 126384.38 | W16: =IFERROR(OFFSET('HTM Output'!$J$6,MATCH($B16,'HTM Output'!$B$7:$B$37,0),MATCH(W$11,'HTM Output'!$K$6:$GS$6,0)),0)*$I$8 -> 126979.72 | X16: =IFERROR(OFFSET('HTM Output'!$J$6,MATCH($B16,'HTM Output'!$B$7:$B$37,0),MATCH(X$11,'HTM Output'!$K$6:$GS$6,0)),0)*$I$8 -> 130793.04 | Y16: =IFERROR(OFFSET('HTM Output'!$J$6,MATCH($B16,'HTM Output'!$B$7:$B$37,0),MATCH(Y$11,'HTM Output'!$K$6:$GS$6,0)),0)*$I$8 -> 126571.32 | Z16: =IFERROR(OFFSET('HTM Output'!$J$6,MATCH($B16,'HTM Output'!$B$7:$B$37,0),MATCH(Z$11,'HTM Output'!$K$6:$GS$6,0)),0)*$I$8 -> 130787.46 | AA16: =IFERROR(OFFSET('HTM Output'!$J$6,MATCH($B16,'HTM Output'!$B$7:$B$37,0),MATCH(AA$11,'HTM Output'!$K$6:$GS$6,0)),0)*$I$8 -> 126565.88 | AB16: =IFERROR(OFFSET('HTM Output'!$J$6,MATCH($B16,'HTM Output'!$B$7:$B$37,0),MATCH(AB$11,'HTM Output'!$K$6:$GS$6,0)),0)*$I$8 -> 130781.79 | ... HB16: =IFERROR(OFFSET('HTM Output'!$J$6,MATCH($B16,'HTM Output'!$B$7:$B$37,0),MATCH(HB$11,'HTM Output'!$K$6:$GS$6,0)),0)*$I$8 -> 0 | HD16: =T16 -> -8670228.1 | HE16: =SUMIFS($T16:$HB16,$T$10:$HB$10,HE$11) -> 1520149.8 | HF16: =SUMIFS($T16:$HB16,$T$10:$HB$10,HF$11) -> 1087955.2 | HG16: =SUMIFS($T16:$HB16,$T$10:$HB$10,HG$11) -> 710415.19 | HH16: =SUMIFS($T16:$HB16,$T$10:$HB$10,HH$11) -> 15720976 | HI16: =SUMIFS($T16:$HB16,$T$10:$HB$10,HI$11) -> 0 | HJ16: =SUMIFS($T16:$HB16,$T$10:$HB$10,HJ$11) -> 0 | HK16: =SUM(HD16:HJ16) -> 10369268
A17: BBCMS 2019-C3 B-Piece Cashflows | B17: BBCMS 2019-C3 | C17: =OFFSET(Strats!$B$3,MATCH($B17,Strats!$B$4:$B$31,0),MATCH(C$10,Strats!$C$3:$BS$3,0)) -> 94541101 | D17: =OFFSET(Strats!$B$3,MATCH($B17,Strats!$B$4:$B$31,0),MATCH(D$10,Strats!$C$3:$BS$3,0)) -> 0.5321654 | E17: =C17*D17 -> 50311503 | F17: =$F$42*$E17/$E$42 -> 822591.17 | G17: =F17+E17 -> 51134094 | H17: =IFERROR(SUMPRODUCT('HTM Output'!$K76:$GS76,'HTM Output'!$K$6:$GS$6)/SUM('HTM Output'!$K76:$GS76),_xlfn.MAXIFS($U$11:$HB$11,$U$14:$HB$14,">"&0)) -> 48342.458 | I17: =G17*$I$8 -> 18100564 | J17: =$J$42 -> 0.5 | K17: =I17*J17 -> 9050282.1 | L17: =-SUMIFS('HTM Output'!$K12:$GS12,'HTM Output'!$K$6:$GS$6,">"&'HTM Output'!$G$2,'HTM Output'!$K$6:$GS$6,"<="&'HTM Output'!$G$3)*$I$8 -> -678276.99 | M17: =M$42*K17/$K$42 -> 25302.136 | N17: =L17+M17 -> -652974.86 | O17: =SUM(K17:M17) -> 8397307.3 | Q17: =IFERROR(XIRR($T17:$HB17,$T$11:$HB$11),"N/A") -> 0.2409211 | R17: =IFERROR((HK17+O17)/O17,"N/A") -> 2.4982331 | T17: =IF(T$11>$I$4,SUMIFS('Pooled CF'!$E:$E,'Pooled CF'!$A:$A,$A17,'Pooled CF'!$G:$G,T$11),0)+IF(T$11=$I$4,-$O17) -> -8397307.3 | U17: =IFERROR(OFFSET('HTM Output'!$J$6,MATCH($B17,'HTM Output'!$B$7:$B$37,0),MATCH(U$11,'HTM Output'!$K$6:$GS$6,0)),0)*$I$8 -> 111942.28 | V17: =IFERROR(OFFSET('HTM Output'!$J$6,MATCH($B17,'HTM Output'!$B$7:$B$37,0),MATCH(V$11,'HTM Output'!$K$6:$GS$6,0)),0)*$I$8 -> 111940.97 | W17: =IFERROR(OFFSET('HTM Output'!$J$6,MATCH($B17,'HTM Output'!$B$7:$B$37,0),MATCH(W$11,'HTM Output'!$K$6:$GS$6,0)),0)*$I$8 -> 113981.74 | X17: =IFERROR(OFFSET('HTM Output'!$J$6,MATCH($B17,'HTM Output'!$B$7:$B$37,0),MATCH(X$11,'HTM Output'!$K$6:$GS$6,0)),0)*$I$8 -> 116369.23 | Y17: =IFERROR(OFFSET('HTM Output'!$J$6,MATCH($B17,'HTM Output'!$B$7:$B$37,0),MATCH(Y$11,'HTM Output'!$K$6:$GS$6,0)),0)*$I$8 -> 112614.04 | Z17: =IFERROR(OFFSET('HTM Output'!$J$6,MATCH($B17,'HTM Output'!$B$7:$B$37,0),MATCH(Z$11,'HTM Output'!$K$6:$GS$6,0)),0)*$I$8 -> 116366.33 | AA17: =IFERROR(OFFSET('HTM Output'!$J$6,MATCH($B17,'HTM Output'!$B$7:$B$37,0),MATCH(AA$11,'HTM Output'!$K$6:$GS$6,0)),0)*$I$8 -> 112611.2 | AB17: =IFERROR(OFFSET('HTM Output'!$J$6,MATCH($B17,'HTM Output'!$B$7:$B$37,0),MATCH(AB$11,'HTM Output'!$K$6:$GS$6,0)),0)*$I$8 -> 116363.38 | ... HB17: =IFERROR(OFFSET('HTM Output'!$J$6,MATCH($B17,'HTM Output'!$B$7:$B$37,0),MATCH(HB$11,'HTM Output'!$K$6:$GS$6,0)),0)*$I$8 -> 0 | HD17: =T17 -> -8397307.3 | HE17: =SUMIFS($T17:$HB17,$T$10:$HB$10,HE$11) -> 1370121 | HF17: =SUMIFS($T17:$HB17,$T$10:$HB$10,HF$11) -> 1348993.2 | HG17: =SUMIFS($T17:$HB17,$T$10:$HB$10,HG$11) -> 993802.28 | HH17: =SUMIFS($T17:$HB17,$T$10:$HB$10,HH$11) -> 879672.54 | HI17: =SUMIFS($T17:$HB17,$T$10:$HB$10,HI$11) -> 2690784.1 | HJ17: =SUMIFS($T17:$HB17,$T$10:$HB$10,HJ$11) -> 13695058 | HK17: =SUM(HD17:HJ17) -> 12581124
A18: GSMS 2019-GC38 B-Piece Cashflow | B18: GSMS 2019-GC38 | C18: =OFFSET(Strats!$B$3,MATCH($B18,Strats!$B$4:$B$31,0),MATCH(C$10,Strats!$C$3:$BS$3,0)) -> 73640365 | D18: =OFFSET(Strats!$B$3,MATCH($B18,Strats!$B$4:$B$31,0),MATCH(D$10,Strats!$C$3:$BS$3,0)) -> 0.66377783 | E18: =C18*D18 -> 48880842 | F18: =$F$42*$E18/$E$42 -> 799199.92 | G18: =F18+E18 -> 49680042 | H18: =IFERROR(SUMPRODUCT('HTM Output'!$K77:$GS77,'HTM Output'!$K$6:$GS$6)/SUM('HTM Output'!$K77:$GS77),_xlfn.MAXIFS($U$11:$HB$11,$U$14:$HB$14,">"&0)) -> 48273 | I18: =G18*$I$8 -> 17585855 | J18: =$J$42 -> 0.5 | K18: =I18*J18 -> 8792927.7 | L18: =-SUMIFS('HTM Output'!$K13:$GS13,'HTM Output'!$K$6:$GS$6,">"&'HTM Output'!$G$2,'HTM Output'!$K$6:$GS$6,"<="&'HTM Output'!$G$3)*$I$8 -> -699234.32 | M18: =M$42*K18/$K$42 -> 24582.643 | N18: =L18+M18 -> -674651.68 | O18: =SUM(K18:M18) -> 8118276.1 | Q18: =IFERROR(XIRR($T18:$HB18,$T$11:$HB$11),"N/A") -> 0.18022459 | R18: =IFERROR((HK18+O18)/O18,"N/A") -> 1.9623536 | T18: =IF(T$11>$I$4,SUMIFS('Pooled CF'!$E:$E,'Pooled CF'!$A:$A,$A18,'Pooled CF'!$G:$G,T$11),0)+IF(T$11=$I$4,-$O18) -> -8118276.1 | U18: =IFERROR(OFFSET('HTM Output'!$J$6,MATCH($B18,'HTM Output'!$B$7:$B$37,0),MATCH(U$11,'HTM Output'!$K$6:$GS$6,0)),0)*$I$8 -> 106247.28 | V18: =IFERROR(OFFSET('HTM Output'!$J$6,MATCH($B18,'HTM Output'!$B$7:$B$37,0),MATCH(V$11,'HTM Output'!$K$6:$GS$6,0)),0)*$I$8 -> 106245.03 | W18: =IFERROR(OFFSET('HTM Output'!$J$6,MATCH($B18,'HTM Output'!$B$7:$B$37,0),MATCH(W$11,'HTM Output'!$K$6:$GS$6,0)),0)*$I$8 -> 106247.69 | X18: =IFERROR(OFFSET('HTM Output'!$J$6,MATCH($B18,'HTM Output'!$B$7:$B$37,0),MATCH(X$11,'HTM Output'!$K$6:$GS$6,0)),0)*$I$8 -> 109781.25 | Y18: =IFERROR(OFFSET('HTM Output'!$J$6,MATCH($B18,'HTM Output'!$B$7:$B$37,0),MATCH(Y$11,'HTM Output'!$K$6:$GS$6,0)),0)*$I$8 -> 106237.63 | Z18: =IFERROR(OFFSET('HTM Output'!$J$6,MATCH($B18,'HTM Output'!$B$7:$B$37,0),MATCH(Z$11,'HTM Output'!$K$6:$GS$6,0)),0)*$I$8 -> 109776.31 | AA18: =IFERROR(OFFSET('HTM Output'!$J$6,MATCH($B18,'HTM Output'!$B$7:$B$37,0),MATCH(AA$11,'HTM Output'!$K$6:$GS$6,0)),0)*$I$8 -> 106232.83 | AB18: =IFERROR(OFFSET('HTM Output'!$J$6,MATCH($B18,'HTM Output'!$B$7:$B$37,0),MATCH(AB$11,'HTM Output'!$K$6:$GS$6,0)),0)*$I$8 -> 109771.32 | ... HB18: =IFERROR(OFFSET('HTM Output'!$J$6,MATCH($B18,'HTM Output'!$B$7:$B$37,0),MATCH(HB$11,'HTM Output'!$K$6:$GS$6,0)),0)*$I$8 -> 0 | HD18: =T18 -> -8118276.1 | HE18: =SUMIFS($T18:$HB18,$T$10:$HB$10,HE$11) -> 1292518.4 | HF18: =SUMIFS($T18:$HB18,$T$10:$HB$10,HF$11) -> 1291264.7 | HG18: =SUMIFS($T18:$HB18,$T$10:$HB$10,HG$11) -> 889854.14 | HH18: =SUMIFS($T18:$HB18,$T$10:$HB$10,HH$11) -> 343646.55 | HI18: =SUMIFS($T18:$HB18,$T$10:$HB$10,HI$11) -> 7504.3841 | HJ18: =SUMIFS($T18:$HB18,$T$10:$HB$10,HJ$11) -> 12106140 | HK18: =SUM(HD18:HJ18) -> 7812652
A19: GSMS 2017-GS8 B-Piece Cashflow | B19: GSMS 2017-GS8 | C19: =OFFSET(Strats!$B$3,MATCH($B19,Strats!$B$4:$B$31,0),MATCH(C$10,Strats!$C$3:$BS$3,0)) -> 106223386 | D19: =OFFSET(Strats!$B$3,MATCH($B19,Strats!$B$4:$B$31,0),MATCH(D$10,Strats!$C$3:$BS$3,0)) -> 0.43273164 | E19: =C19*D19 -> 45966220 | F19: =$F$42*$E19/$E$42 -> 751545.96 | G19: =F19+E19 -> 46717766 | H19: =IFERROR(SUMPRODUCT('HTM Output'!$K78:$GS78,'HTM Output'!$K$6:$GS$6)/SUM('HTM Output'!$K78:$GS78),_xlfn.MAXIFS($U$11:$HB$11,$U$14:$HB$14,">"&0)) -> 47787 | I19: =G19*$I$8 -> 16537262 | J19: =$J$42 -> 0.5 | K19: =I19*J19 -> 8268631.1 | L19: =-SUMIFS('HTM Output'!$K14:$GS14,'HTM Output'!$K$6:$GS$6,">"&'HTM Output'!$G$2,'HTM Output'!$K$6:$GS$6,"<="&'HTM Output'!$G$3)*$I$8 -> -451077.88 | M19: =M$42*K19/$K$42 -> 23116.851 | N19: =L19+M19 -> -427961.03 | O19: =SUM(K19:M19) -> 7840670.1 | Q19: =IFERROR(XIRR($T19:$HB19,$T$11:$HB$11),"N/A") -> 0.25317426 | R19: =IFERROR((HK19+O19)/O19,"N/A") -> 2.1681846 | T19: =IF(T$11>$I$4,SUMIFS('Pooled CF'!$E:$E,'Pooled CF'!$A:$A,$A19,'Pooled CF'!$G:$G,T$11),0)+IF(T$11=$I$4,-$O19) -> -7840670.1 | U19: =IFERROR(OFFSET('HTM Output'!$J$6,MATCH($B19,'HTM Output'!$B$7:$B$37,0),MATCH(U$11,'HTM Output'!$K$6:$GS$6,0)),0)*$I$8 -> 69322.44 | V19: =IFERROR(OFFSET('HTM Output'!$J$6,MATCH($B19,'HTM Output'!$B$7:$B$37,0),MATCH(V$11,'HTM Output'!$K$6:$GS$6,0)),0)*$I$8 -> 69315.183 | W19: =IFERROR(OFFSET('HTM Output'!$J$6,MATCH($B19,'HTM Output'!$B$7:$B$37,0),MATCH(W$11,'HTM Output'!$K$6:$GS$6,0)),0)*$I$8 -> 75566.871 | X19: =IFERROR(OFFSET('HTM Output'!$J$6,MATCH($B19,'HTM Output'!$B$7:$B$37,0),MATCH(X$11,'HTM Output'!$K$6:$GS$6,0)),0)*$I$8 -> 73244.522 | Y19: =IFERROR(OFFSET('HTM Output'!$J$6,MATCH($B19,'HTM Output'!$B$7:$B$37,0),MATCH(Y$11,'HTM Output'!$K$6:$GS$6,0)),0)*$I$8 -> 79422.098 | Z19: =IFERROR(OFFSET('HTM Output'!$J$6,MATCH($B19,'HTM Output'!$B$7:$B$37,0),MATCH(Z$11,'HTM Output'!$K$6:$GS$6,0)),0)*$I$8 -> 81290.264 | AA19: =IFERROR(OFFSET('HTM Output'!$J$6,MATCH($B19,'HTM Output'!$B$7:$B$37,0),MATCH(AA$11,'HTM Output'!$K$6:$GS$6,0)),0)*$I$8 -> 78885.804 | AB19: =IFERROR(OFFSET('HTM Output'!$J$6,MATCH($B19,'HTM Output'!$B$7:$B$37,0),MATCH(AB$11,'HTM Output'!$K$6:$GS$6,0)),0)*$I$8 -> 83044.242 | ... HB19: =IFERROR(OFFSET('HTM Output'!$J$6,MATCH($B19,'HTM Output'!$B$7:$B$37,0),MATCH(HB$11,'HTM Output'!$K$6:$GS$6,0)),0)*$I$8 -> 0 | HD19: =T19 -> -7840670.1 | HE19: =SUMIFS($T19:$HB19,$T$10:$HB$10,HE$11) -> 931572.49 | HF19: =SUMIFS($T19:$HB19,$T$10:$HB$10,HF$11) -> 760448.2 | HG19: =SUMIFS($T19:$HB19,$T$10:$HB$10,HG$11) -> 136501.51 | HH19: =SUMIFS($T19:$HB19,$T$10:$HB$10,HH$11) -> 15171498 | HI19: =SUMIFS($T19:$HB19,$T$10:$HB$10,HI$11) -> 0 | HJ19: =SUMIFS($T19:$HB19,$T$10:$HB$10,HJ$11) -> 0 | HK19: =SUM(HD19:HJ19) -> 9159349.9
A20: UBSCM 2018-C8 B-Piece Cashflows | B20: UBSCM 2018-C8 | C20: =OFFSET(Strats!$B$3,MATCH($B20,Strats!$B$4:$B$31,0),MATCH(C$10,Strats!$C$3:$BS$3,0)) -> 1.0628505e+08 | D20: =OFFSET(Strats!$B$3,MATCH($B20,Strats!$B$4:$B$31,0),MATCH(D$10,Strats!$C$3:$BS$3,0)) -> 0.43494577 | E20: =C20*D20 -> 46228232 | F20: =$F$42*$E20/$E$42 -> 755829.85 | G20: =F20+E20 -> 46984062 | H20: =IFERROR(SUMPRODUCT('HTM Output'!$K79:$GS79,'HTM Output'!$K$6:$GS$6)/SUM('HTM Output'!$K79:$GS79),_xlfn.MAXIFS($U$11:$HB$11,$U$14:$HB$14,">"&0)) -> 47361 | I20: =G20*$I$8 -> 16631526 | J20: =$J$42 -> 0.5 | K20: =I20*J20 -> 8315763.2 | L20: =-SUMIFS('HTM Output'!$K15:$GS15,'HTM Output'!$K$6:$GS$6,">"&'HTM Output'!$G$2,'HTM Output'!$K$6:$GS$6,"<="&'HTM Output'!$G$3)*$I$8 -> -870312.17 | M20: =M$42*K20/$K$42 -> 23248.62 | N20: =L20+M20 -> -847063.55 | O20: =SUM(K20:M20) -> 7468699.7 | Q20: =IFERROR(XIRR($T20:$HB20,$T$11:$HB$11),"N/A") -> -0.74124408 | R20: =IFERROR((HK20+O20)/O20,"N/A") -> 0.31259237 | T20: =IF(T$11>$I$4,SUMIFS('Pooled CF'!$E:$E,'Pooled CF'!$A:$A,$A20,'Pooled CF'!$G:$G,T$11),0)+IF(T$11=$I$4,-$O20) -> -7468699.7 | U20: =IFERROR(OFFSET('HTM Output'!$J$6,MATCH($B20,'HTM Output'!$B$7:$B$37,0),MATCH(U$11,'HTM Output'!$K$6:$GS$6,0)),0)*$I$8 -> 146740.66 | V20: =IFERROR(OFFSET('HTM Output'!$J$6,MATCH($B20,'HTM Output'!$B$7:$B$37,0),MATCH(V$11,'HTM Output'!$K$6:$GS$6,0)),0)*$I$8 -> 146738.13 | W20: =IFERROR(OFFSET('HTM Output'!$J$6,MATCH($B20,'HTM Output'!$B$7:$B$37,0),MATCH(W$11,'HTM Output'!$K$6:$GS$6,0)),0)*$I$8 -> 146744.71 | X20: =IFERROR(OFFSET('HTM Output'!$J$6,MATCH($B20,'HTM Output'!$B$7:$B$37,0),MATCH(X$11,'HTM Output'!$K$6:$GS$6,0)),0)*$I$8 -> 151623.5 | Y20: =IFERROR(OFFSET('HTM Output'!$J$6,MATCH($B20,'HTM Output'!$B$7:$B$37,0),MATCH(Y$11,'HTM Output'!$K$6:$GS$6,0)),0)*$I$8 -> 146729.84 | Z20: =IFERROR(OFFSET('HTM Output'!$J$6,MATCH($B20,'HTM Output'!$B$7:$B$37,0),MATCH(Z$11,'HTM Output'!$K$6:$GS$6,0)),0)*$I$8 -> 151617.95 | AA20: =IFERROR(OFFSET('HTM Output'!$J$6,MATCH($B20,'HTM Output'!$B$7:$B$37,0),MATCH(AA$11,'HTM Output'!$K$6:$GS$6,0)),0)*$I$8 -> 146657.13 | AB20: =IFERROR(OFFSET('HTM Output'!$J$6,MATCH($B20,'HTM Output'!$B$7:$B$37,0),MATCH(AB$11,'HTM Output'!$K$6:$GS$6,0)),0)*$I$8 -> 151542.89 | ... HB20: =IFERROR(OFFSET('HTM Output'!$J$6,MATCH($B20,'HTM Output'!$B$7:$B$37,0),MATCH(HB$11,'HTM Output'!$K$6:$GS$6,0)),0)*$I$8 -> 0 | HD20: =T20 -> -7468699.7 | HE20: =SUMIFS($T20:$HB20,$T$10:$HB$10,HE$11) -> 1784723.1 | HF20: =SUMIFS($T20:$HB20,$T$10:$HB$10,HF$11) -> 549935.49 | HG20: =SUMIFS($T20:$HB20,$T$10:$HB$10,HG$11) -> 0 | HH20: =SUMIFS($T20:$HB20,$T$10:$HB$10,HH$11) -> 0 | HI20: =SUMIFS($T20:$HB20,$T$10:$HB$10,HI$11) -> 0 | HJ20: =SUMIFS($T20:$HB20,$T$10:$HB$10,HJ$11) -> 0 | HK20: =SUM(HD20:HJ20) -> -5134041.1
A21: UBSCM 2017-C3 B-Piece Cashflows | B21: UBSCM 2017-C3 | C21: =OFFSET(Strats!$B$3,MATCH($B21,Strats!$B$4:$B$31,0),MATCH(C$10,Strats!$C$3:$BS$3,0)) -> 67393694 | D21: =OFFSET(Strats!$B$3,MATCH($B21,Strats!$B$4:$B$31,0),MATCH(D$10,Strats!$C$3:$BS$3,0)) -> 0.65732392 | E21: =C21*D21 -> 44299487 | F21: =$F$42*$E21/$E$42 -> 724294.94 | G21: =F21+E21 -> 45023782 | H21: =IFERROR(SUMPRODUCT('HTM Output'!$K80:$GS80,'HTM Output'!$K$6:$GS$6)/SUM('HTM Output'!$K80:$GS80),_xlfn.MAXIFS($U$11:$HB$11,$U$14:$HB$14,">"&0)) -> 47813.309 | I21: =G21*$I$8 -> 15937622 | J21: =$J$42 -> 0.5 | K21: =I21*J21 -> 7968811 | L21: =-SUMIFS('HTM Output'!$K16:$GS16,'HTM Output'!$K$6:$GS$6,">"&'HTM Output'!$G$2,'HTM Output'!$K$6:$GS$6,"<="&'HTM Output'!$G$3)*$I$8 -> -385067.49 | M21: =M$42*K21/$K$42 -> 22278.636 | N21: =L21+M21 -> -362788.85 | O21: =SUM(K21:M21) -> 7606022.1 | Q21: =IFERROR(XIRR($T21:$HB21,$T$11:$HB$11),"N/A") -> 0.18671796 | R21: =IFERROR((HK21+O21)/O21,"N/A") -> 1.7637253 | T21: =IF(T$11>$I$4,SUMIFS('Pooled CF'!$E:$E,'Pooled CF'!$A:$A,$A21,'Pooled CF'!$G:$G,T$11),0)+IF(T$11=$I$4,-$O21) -> -7606022.1 | U21: =IFERROR(OFFSET('HTM Output'!$J$6,MATCH($B21,'HTM Output'!$B$7:$B$37,0),MATCH(U$11,'HTM Output'!$K$6:$GS$6,0)),0)*$I$8 -> 66984.399 | V21: =IFERROR(OFFSET('HTM Output'!$J$6,MATCH($B21,'HTM Output'!$B$7:$B$37,0),MATCH(V$11,'HTM Output'!$K$6:$GS$6,0)),0)*$I$8 -> 66998.324 | W21: =IFERROR(OFFSET('HTM Output'!$J$6,MATCH($B21,'HTM Output'!$B$7:$B$37,0),MATCH(W$11,'HTM Output'!$K$6:$GS$6,0)),0)*$I$8 -> 68879.226 | X21: =IFERROR(OFFSET('HTM Output'!$J$6,MATCH($B21,'HTM Output'!$B$7:$B$37,0),MATCH(X$11,'HTM Output'!$K$6:$GS$6,0)),0)*$I$8 -> 69903.119 | Y21: =IFERROR(OFFSET('HTM Output'!$J$6,MATCH($B21,'HTM Output'!$B$7:$B$37,0),MATCH(Y$11,'HTM Output'!$K$6:$GS$6,0)),0)*$I$8 -> 67661.331 | Z21: =IFERROR(OFFSET('HTM Output'!$J$6,MATCH($B21,'HTM Output'!$B$7:$B$37,0),MATCH(Z$11,'HTM Output'!$K$6:$GS$6,0)),0)*$I$8 -> 69779.897 | AA21: =IFERROR(OFFSET('HTM Output'!$J$6,MATCH($B21,'HTM Output'!$B$7:$B$37,0),MATCH(AA$11,'HTM Output'!$K$6:$GS$6,0)),0)*$I$8 -> 70378.865 | AB21: =IFERROR(OFFSET('HTM Output'!$J$6,MATCH($B21,'HTM Output'!$B$7:$B$37,0),MATCH(AB$11,'HTM Output'!$K$6:$GS$6,0)),0)*$I$8 -> 63969.085 | ... HB21: =IFERROR(OFFSET('HTM Output'!$J$6,MATCH($B21,'HTM Output'!$B$7:$B$37,0),MATCH(HB$11,'HTM Output'!$K$6:$GS$6,0)),0)*$I$8 -> 0 | HD21: =T21 -> -7606022.1 | HE21: =SUMIFS($T21:$HB21,$T$10:$HB$10,HE$11) -> 884860.63 | HF21: =SUMIFS($T21:$HB21,$T$10:$HB$10,HF$11) -> 908213.75 | HG21: =SUMIFS($T21:$HB21,$T$10:$HB$10,HG$11) -> 731450.57 | HH21: =SUMIFS($T21:$HB21,$T$10:$HB$10,HH$11) -> 6445286.3 | HI21: =SUMIFS($T21:$HB21,$T$10:$HB$10,HI$11) -> 4445122.4 | HJ21: =SUMIFS($T21:$HB21,$T$10:$HB$10,HJ$11) -> 0 | HK21: =SUM(HD21:HJ21) -> 5808911.6
A22: UBSCM 2017-C5 B-Piece Cashflows | B22: UBSCM 2017-C5 | C22: =OFFSET(Strats!$B$3,MATCH($B22,Strats!$B$4:$B$31,0),MATCH(C$10,Strats!$C$3:$BS$3,0)) -> 63221086 | D22: =OFFSET(Strats!$B$3,MATCH($B22,Strats!$B$4:$B$31,0),MATCH(D$10,Strats!$C$3:$BS$3,0)) -> 0.69324 | E22: =C22*D22 -> 43827385 | F22: =$F$42*$E22/$E$42 -> 716576.1 | G22: =F22+E22 -> 44543962 | H22: =IFERROR(SUMPRODUCT('HTM Output'!$K81:$GS81,'HTM Output'!$K$6:$GS$6)/SUM('HTM Output'!$K81:$GS81),_xlfn.MAXIFS($U$11:$HB$11,$U$14:$HB$14,">"&0)) -> 47647.709 | I22: =G22*$I$8 -> 15767774 | J22: =$J$42 -> 0.5 | K22: =I22*J22 -> 7883887 | L22: =-SUMIFS('HTM Output'!$K17:$GS17,'HTM Output'!$K$6:$GS$6,">"&'HTM Output'!$G$2,'HTM Output'!$K$6:$GS$6,"<="&'HTM Output'!$G$3)*$I$8 -> -457325.32 | M22: =M$42*K22/$K$42 -> 22041.211 | N22: =L22+M22 -> -435284.11 | O22: =SUM(K22:M22) -> 7448602.8 | Q22: =IFERROR(XIRR($T22:$HB22,$T$11:$HB$11),"N/A") -> 0.17445292 | R22: =IFERROR((HK22+O22)/O22,"N/A") -> 1.6531662 | T22: =IF(T$11>$I$4,SUMIFS('Pooled CF'!$E:$E,'Pooled CF'!$A:$A,$A22,'Pooled CF'!$G:$G,T$11),0)+IF(T$11=$I$4,-$O22) -> -7448602.8 | U22: =IFERROR(OFFSET('HTM Output'!$J$6,MATCH($B22,'HTM Output'!$B$7:$B$37,0),MATCH(U$11,'HTM Output'!$K$6:$GS$6,0)),0)*$I$8 -> 67832.056 | V22: =IFERROR(OFFSET('HTM Output'!$J$6,MATCH($B22,'HTM Output'!$B$7:$B$37,0),MATCH(V$11,'HTM Output'!$K$6:$GS$6,0)),0)*$I$8 -> 67827.072 | W22: =IFERROR(OFFSET('HTM Output'!$J$6,MATCH($B22,'HTM Output'!$B$7:$B$37,0),MATCH(W$11,'HTM Output'!$K$6:$GS$6,0)),0)*$I$8 -> 69324.621 | X22: =IFERROR(OFFSET('HTM Output'!$J$6,MATCH($B22,'HTM Output'!$B$7:$B$37,0),MATCH(X$11,'HTM Output'!$K$6:$GS$6,0)),0)*$I$8 -> 70590.536 | Y22: =IFERROR(OFFSET('HTM Output'!$J$6,MATCH($B22,'HTM Output'!$B$7:$B$37,0),MATCH(Y$11,'HTM Output'!$K$6:$GS$6,0)),0)*$I$8 -> 68308.324 | Z22: =IFERROR(OFFSET('HTM Output'!$J$6,MATCH($B22,'HTM Output'!$B$7:$B$37,0),MATCH(Z$11,'HTM Output'!$K$6:$GS$6,0)),0)*$I$8 -> 70579.613 | AA22: =IFERROR(OFFSET('HTM Output'!$J$6,MATCH($B22,'HTM Output'!$B$7:$B$37,0),MATCH(AA$11,'HTM Output'!$K$6:$GS$6,0)),0)*$I$8 -> 68648.638 | AB22: =IFERROR(OFFSET('HTM Output'!$J$6,MATCH($B22,'HTM Output'!$B$7:$B$37,0),MATCH(AB$11,'HTM Output'!$K$6:$GS$6,0)),0)*$I$8 -> 70930.411 | ... HB22: =IFERROR(OFFSET('HTM Output'!$J$6,MATCH($B22,'HTM Output'!$B$7:$B$37,0),MATCH(HB$11,'HTM Output'!$K$6:$GS$6,0)),0)*$I$8 -> 0 | HD22: =T22 -> -7448602.8 | HE22: =SUMIFS($T22:$HB22,$T$10:$HB$10,HE$11) -> 673575.85 | HF22: =SUMIFS($T22:$HB22,$T$10:$HB$10,HF$11) -> 298629.78 | HG22: =SUMIFS($T22:$HB22,$T$10:$HB$10,HG$11) -> 6924619.6 | HH22: =SUMIFS($T22:$HB22,$T$10:$HB$10,HH$11) -> 121145.21 | HI22: =SUMIFS($T22:$HB22,$T$10:$HB$10,HI$11) -> 4295807.7 | HJ22: =SUMIFS($T22:$HB22,$T$10:$HB$10,HJ$11) -> 0 | HK22: =SUM(HD22:HJ22) -> 4865175.3
A23: MSC 2019-H6 B-Piece Cashflows | B23: MSC 2019-H6 | C23: =OFFSET(Strats!$B$3,MATCH($B23,Strats!$B$4:$B$31,0),MATCH(C$10,Strats!$C$3:$BS$3,0)) -> 62736698 | D23: =OFFSET(Strats!$B$3,MATCH($B23,Strats!$B$4:$B$31,0),MATCH(D$10,Strats!$C$3:$BS$3,0)) -> 0.69759483 | E23: =C23*D23 -> 43764796 | F23: =$F$42*$E23/$E$42 -> 715552.76 | G23: =F23+E23 -> 44480348 | H23: =IFERROR(SUMPRODUCT('HTM Output'!$K82:$GS82,'HTM Output'!$K$6:$GS$6)/SUM('HTM Output'!$K82:$GS82),_xlfn.MAXIFS($U$11:$HB$11,$U$14:$HB$14,">"&0)) -> 48008.549 | I23: =G23*$I$8 -> 15745256 | J23: =$J$42 -> 0.5 | K23: =I23*J23 -> 7872628 | L23: =-SUMIFS('HTM Output'!$K18:$GS18,'HTM Output'!$K$6:$GS$6,">"&'HTM Output'!$G$2,'HTM Output'!$K$6:$GS$6,"<="&'HTM Output'!$G$3)*$I$8 -> -470124.49 | M23: =M$42*K23/$K$42 -> 22009.734 | N23: =L23+M23 -> -448114.76 | O23: =SUM(K23:M23) -> 7424513.3 | Q23: =IFERROR(XIRR($T23:$HB23,$T$11:$HB$11),"N/A") -> 0.31284388 | R23: =IFERROR((HK23+O23)/O23,"N/A") -> 2.8239946 | T23: =IF(T$11>$I$4,SUMIFS('Pooled CF'!$E:$E,'Pooled CF'!$A:$A,$A23,'Pooled CF'!$G:$G,T$11),0)+IF(T$11=$I$4,-$O23) -> -7424513.3 | U23: =IFERROR(OFFSET('HTM Output'!$J$6,MATCH($B23,'HTM Output'!$B$7:$B$37,0),MATCH(U$11,'HTM Output'!$K$6:$GS$6,0)),0)*$I$8 -> 81021.367 | V23: =IFERROR(OFFSET('HTM Output'!$J$6,MATCH($B23,'HTM Output'!$B$7:$B$37,0),MATCH(V$11,'HTM Output'!$K$6:$GS$6,0)),0)*$I$8 -> 81018.839 | W23: =IFERROR(OFFSET('HTM Output'!$J$6,MATCH($B23,'HTM Output'!$B$7:$B$37,0),MATCH(W$11,'HTM Output'!$K$6:$GS$6,0)),0)*$I$8 -> 81298.144 | X23: =IFERROR(OFFSET('HTM Output'!$J$6,MATCH($B23,'HTM Output'!$B$7:$B$37,0),MATCH(X$11,'HTM Output'!$K$6:$GS$6,0)),0)*$I$8 -> 83808.115 | Y23: =IFERROR(OFFSET('HTM Output'!$J$6,MATCH($B23,'HTM Output'!$B$7:$B$37,0),MATCH(Y$11,'HTM Output'!$K$6:$GS$6,0)),0)*$I$8 -> 81102.017 | Z23: =IFERROR(OFFSET('HTM Output'!$J$6,MATCH($B23,'HTM Output'!$B$7:$B$37,0),MATCH(Z$11,'HTM Output'!$K$6:$GS$6,0)),0)*$I$8 -> 83802.45 | AA23: =IFERROR(OFFSET('HTM Output'!$J$6,MATCH($B23,'HTM Output'!$B$7:$B$37,0),MATCH(AA$11,'HTM Output'!$K$6:$GS$6,0)),0)*$I$8 -> 81096.499 | AB23: =IFERROR(OFFSET('HTM Output'!$J$6,MATCH($B23,'HTM Output'!$B$7:$B$37,0),MATCH(AB$11,'HTM Output'!$K$6:$GS$6,0)),0)*$I$8 -> 83796.71 | ... HB23: =IFERROR(OFFSET('HTM Output'!$J$6,MATCH($B23,'HTM Output'!$B$7:$B$37,0),MATCH(HB$11,'HTM Output'!$K$6:$GS$6,0)),0)*$I$8 -> 0 | HD23: =T23 -> -7424513.3 | HE23: =SUMIFS($T23:$HB23,$T$10:$HB$10,HE$11) -> 986696.87 | HF23: =SUMIFS($T23:$HB23,$T$10:$HB$10,HF$11) -> 965189.39 | HG23: =SUMIFS($T23:$HB23,$T$10:$HB$10,HG$11) -> 864238.05 | HH23: =SUMIFS($T23:$HB23,$T$10:$HB$10,HH$11) -> 845319.98 | HI23: =SUMIFS($T23:$HB23,$T$10:$HB$10,HI$11) -> 17305341 | HJ23: =SUMIFS($T23:$HB23,$T$10:$HB$10,HJ$11) -> 0 | HK23: =SUM(HD23:HJ23) -> 13542272
A24: WFCM 2019-C49 B-Piece Cashflows | B24: WFCM 2019-C49 | C24: =OFFSET(Strats!$B$3,MATCH($B24,Strats!$B$4:$B$31,0),MATCH(C$10,Strats!$C$3:$BS$3,0)) -> 72155021 | D24: =OFFSET(Strats!$B$3,MATCH($B24,Strats!$B$4:$B$31,0),MATCH(D$10,Strats!$C$3:$BS$3,0)) -> 0.59472576 | E24: =C24*D24 -> 42912450 | F24: =$F$42*$E24/$E$42 -> 701616.93 | G24: =F24+E24 -> 43614067 | H24: =IFERROR(SUMPRODUCT('HTM Output'!$K83:$GS83,'HTM Output'!$K$6:$GS$6)/SUM('HTM Output'!$K83:$GS83),_xlfn.MAXIFS($U$11:$HB$11,$U$14:$HB$14,">"&0)) -> 47962.226 | I24: =G24*$I$8 -> 15438608 | J24: =$J$42 -> 0.5 | K24: =I24*J24 -> 7719303.8 | L24: =-SUMIFS('HTM Output'!$K19:$GS19,'HTM Output'!$K$6:$GS$6,">"&'HTM Output'!$G$2,'HTM Output'!$K$6:$GS$6,"<="&'HTM Output'!$G$3)*$I$8 -> -617437.33 | M24: =M$42*K24/$K$42 -> 21581.081 | N24: =L24+M24 -> -595856.25 | O24: =SUM(K24:M24) -> 7123447.6 | Q24: =IFERROR(XIRR($T24:$HB24,$T$11:$HB$11),"N/A") -> 0.25744733 | R24: =IFERROR((HK24+O24)/O24,"N/A") -> 2.2735136 | T24: =IF(T$11>$I$4,SUMIFS('Pooled CF'!$E:$E,'Pooled CF'!$A:$A,$A24,'Pooled CF'!$G:$G,T$11),0)+IF(T$11=$I$4,-$O24) -> -7123447.6 | U24: =IFERROR(OFFSET('HTM Output'!$J$6,MATCH($B24,'HTM Output'!$B$7:$B$37,0),MATCH(U$11,'HTM Output'!$K$6:$GS$6,0)),0)*$I$8 -> 97610.002 | V24: =IFERROR(OFFSET('HTM Output'!$J$6,MATCH($B24,'HTM Output'!$B$7:$B$37,0),MATCH(V$11,'HTM Output'!$K$6:$GS$6,0)),0)*$I$8 -> 97607.829 | W24: =IFERROR(OFFSET('HTM Output'!$J$6,MATCH($B24,'HTM Output'!$B$7:$B$37,0),MATCH(W$11,'HTM Output'!$K$6:$GS$6,0)),0)*$I$8 -> 98727.373 | X24: =IFERROR(OFFSET('HTM Output'!$J$6,MATCH($B24,'HTM Output'!$B$7:$B$37,0),MATCH(X$11,'HTM Output'!$K$6:$GS$6,0)),0)*$I$8 -> 101239.6 | Y24: =IFERROR(OFFSET('HTM Output'!$J$6,MATCH($B24,'HTM Output'!$B$7:$B$37,0),MATCH(Y$11,'HTM Output'!$K$6:$GS$6,0)),0)*$I$8 -> 97971.583 | Z24: =IFERROR(OFFSET('HTM Output'!$J$6,MATCH($B24,'HTM Output'!$B$7:$B$37,0),MATCH(Z$11,'HTM Output'!$K$6:$GS$6,0)),0)*$I$8 -> 101234.81 | AA24: =IFERROR(OFFSET('HTM Output'!$J$6,MATCH($B24,'HTM Output'!$B$7:$B$37,0),MATCH(AA$11,'HTM Output'!$K$6:$GS$6,0)),0)*$I$8 -> 97966.914 | AB24: =IFERROR(OFFSET('HTM Output'!$J$6,MATCH($B24,'HTM Output'!$B$7:$B$37,0),MATCH(AB$11,'HTM Output'!$K$6:$GS$6,0)),0)*$I$8 -> 101229.95 | ... HB24: =IFERROR(OFFSET('HTM Output'!$J$6,MATCH($B24,'HTM Output'!$B$7:$B$37,0),MATCH(HB$11,'HTM Output'!$K$6:$GS$6,0)),0)*$I$8 -> 0 | HD24: =T24 -> -7123447.6 | HE24: =SUMIFS($T24:$HB24,$T$10:$HB$10,HE$11) -> 1191953.2 | HF24: =SUMIFS($T24:$HB24,$T$10:$HB$10,HF$11) -> 1194762.7 | HG24: =SUMIFS($T24:$HB24,$T$10:$HB$10,HG$11) -> 406393.64 | HH24: =SUMIFS($T24:$HB24,$T$10:$HB$10,HH$11) -> 322193.64 | HI24: =SUMIFS($T24:$HB24,$T$10:$HB$10,HI$11) -> 10509971 | HJ24: =SUMIFS($T24:$HB24,$T$10:$HB$10,HJ$11) -> 2569980.8 | HK24: =SUM(HD24:HJ24) -> 9071807.5
A25: UBSCM 2018-C13 B-Piece Cashflow | B25: UBSCM 2018-C13 | C25: =OFFSET(Strats!$B$3,MATCH($B25,Strats!$B$4:$B$31,0),MATCH(C$10,Strats!$C$3:$BS$3,0)) -> 69343649 | D25: =OFFSET(Strats!$B$3,MATCH($B25,Strats!$B$4:$B$31,0),MATCH(D$10,Strats!$C$3:$BS$3,0)) -> 0.58764012 | E25: =C25*D25 -> 40749110 | F25: =$F$42*$E25/$E$42 -> 666246.41 | G25: =F25+E25 -> 41415356 | H25: =IFERROR(SUMPRODUCT('HTM Output'!$K84:$GS84,'HTM Output'!$K$6:$GS$6)/SUM('HTM Output'!$K84:$GS84),_xlfn.MAXIFS($U$11:$HB$11,$U$14:$HB$14,">"&0)) -> 47787 | I25: =G25*$I$8 -> 14660303 | J25: =$J$42 -> 0.5 | K25: =I25*J25 -> 7330151.5 | L25: =-SUMIFS('HTM Output'!$K20:$GS20,'HTM Output'!$K$6:$GS$6,">"&'HTM Output'!$G$2,'HTM Output'!$K$6:$GS$6,"<="&'HTM Output'!$G$3)*$I$8 -> -517850.17 | M25: =M$42*K25/$K$42 -> 20493.117 | N25: =L25+M25 -> -497357.05 | O25: =SUM(K25:M25) -> 6832794.5 | Q25: =IFERROR(XIRR($T25:$HB25,$T$11:$HB$11),"N/A") -> 0.24700417 | R25: =IFERROR((HK25+O25)/O25,"N/A") -> 2.066532 | T25: =IF(T$11>$I$4,SUMIFS('Pooled CF'!$E:$E,'Pooled CF'!$A:$A,$A25,'Pooled CF'!$G:$G,T$11),0)+IF(T$11=$I$4,-$O25) -> -6832794.5 | U25: =IFERROR(OFFSET('HTM Output'!$J$6,MATCH($B25,'HTM Output'!$B$7:$B$37,0),MATCH(U$11,'HTM Output'!$K$6:$GS$6,0)),0)*$I$8 -> 85690.165 | V25: =IFERROR(OFFSET('HTM Output'!$J$6,MATCH($B25,'HTM Output'!$B$7:$B$37,0),MATCH(V$11,'HTM Output'!$K$6:$GS$6,0)),0)*$I$8 -> 85687.798 | W25: =IFERROR(OFFSET('HTM Output'!$J$6,MATCH($B25,'HTM Output'!$B$7:$B$37,0),MATCH(W$11,'HTM Output'!$K$6:$GS$6,0)),0)*$I$8 -> 87448.044 | X25: =IFERROR(OFFSET('HTM Output'!$J$6,MATCH($B25,'HTM Output'!$B$7:$B$37,0),MATCH(X$11,'HTM Output'!$K$6:$GS$6,0)),0)*$I$8 -> 89142.154 | Y25: =IFERROR(OFFSET('HTM Output'!$J$6,MATCH($B25,'HTM Output'!$B$7:$B$37,0),MATCH(Y$11,'HTM Output'!$K$6:$GS$6,0)),0)*$I$8 -> 86264.177 | Z25: =IFERROR(OFFSET('HTM Output'!$J$6,MATCH($B25,'HTM Output'!$B$7:$B$37,0),MATCH(Z$11,'HTM Output'!$K$6:$GS$6,0)),0)*$I$8 -> 89136.944 | AA25: =IFERROR(OFFSET('HTM Output'!$J$6,MATCH($B25,'HTM Output'!$B$7:$B$37,0),MATCH(AA$11,'HTM Output'!$K$6:$GS$6,0)),0)*$I$8 -> 86259.098 | AB25: =IFERROR(OFFSET('HTM Output'!$J$6,MATCH($B25,'HTM Output'!$B$7:$B$37,0),MATCH(AB$11,'HTM Output'!$K$6:$GS$6,0)),0)*$I$8 -> 89131.657 | ... HB25: =IFERROR(OFFSET('HTM Output'!$J$6,MATCH($B25,'HTM Output'!$B$7:$B$37,0),MATCH(HB$11,'HTM Output'!$K$6:$GS$6,0)),0)*$I$8 -> 0 | HD25: =T25 -> -6832794.5 | HE25: =SUMIFS($T25:$HB25,$T$10:$HB$10,HE$11) -> 1012512.1 | HF25: =SUMIFS($T25:$HB25,$T$10:$HB$10,HF$11) -> 769495.65 | HG25: =SUMIFS($T25:$HB25,$T$10:$HB$10,HG$11) -> 459343.46 | HH25: =SUMIFS($T25:$HB25,$T$10:$HB$10,HH$11) -> 11878837 | HI25: =SUMIFS($T25:$HB25,$T$10:$HB$10,HI$11) -> 0 | HJ25: =SUMIFS($T25:$HB25,$T$10:$HB$10,HJ$11) -> 0 | HK25: =SUM(HD25:HJ25) -> 7287394
... A40: CD 2017-CD3 B-Piece Hist Cashfl | B40: CD 2017-CD3 | C40: =OFFSET(Strats!$B$3,MATCH($B40,Strats!$B$4:$B$31,0),MATCH(C$10,Strats!$C$3:$BS$3,0)) -> 0 | D40: =OFFSET(Strats!$B$3,MATCH($B40,Strats!$B$4:$B$31,0),MATCH(D$10,Strats!$C$3:$BS$3,0)) -> 0 | E40: =C40*D40 -> 0 | F40: =$F$42*$E40/$E$42 -> 0 | G40: =F40+E40 -> 0 | H40: =IFERROR(SUMPRODUCT('HTM Output'!$K99:$GS99,'HTM Output'!$K$6:$GS$6)/SUM('HTM Output'!$K99:$GS99),_xlfn.MAXIFS($U$11:$HB$11,$U$14:$HB$14,">"&0)) -> 47361 | I40: =G40*$I$8 -> 0 | J40: =$J$42 -> 0.5 | K40: =I40*J40 -> 0 | L40: =-SUMIFS('HTM Output'!$K35:$GS35,'HTM Output'!$K$6:$GS$6,">"&'HTM Output'!$G$2,'HTM Output'!$K$6:$GS$6,"<="&'HTM Output'!$G$3)*$I$8 -> 0 | M40: =M$42*K40/$K$42 -> 0 | N40: =L40+M40 -> 0 | O40: =SUM(K40:M40) -> 0 | Q40: =IFERROR(XIRR($T40:$HB40,$T$11:$HB$11),"N/A") -> N/A | R40: =IFERROR((HK40+O40)/O40,"N/A") -> N/A | T40: =IF(T$11>$I$4,SUMIFS('Pooled CF'!$E:$E,'Pooled CF'!$A:$A,$A40,'Pooled CF'!$G:$G,T$11),0)+IF(T$11=$I$4,-$O40) -> 0 | U40: =IFERROR(OFFSET('HTM Output'!$J$6,MATCH($B40,'HTM Output'!$B$7:$B$37,0),MATCH(U$11,'HTM Output'!$K$6:$GS$6,0)),0)*$I$8 -> 0 | V40: =IFERROR(OFFSET('HTM Output'!$J$6,MATCH($B40,'HTM Output'!$B$7:$B$37,0),MATCH(V$11,'HTM Output'!$K$6:$GS$6,0)),0)*$I$8 -> 0 | W40: =IFERROR(OFFSET('HTM Output'!$J$6,MATCH($B40,'HTM Output'!$B$7:$B$37,0),MATCH(W$11,'HTM Output'!$K$6:$GS$6,0)),0)*$I$8 -> 0 | X40: =IFERROR(OFFSET('HTM Output'!$J$6,MATCH($B40,'HTM Output'!$B$7:$B$37,0),MATCH(X$11,'HTM Output'!$K$6:$GS$6,0)),0)*$I$8 -> 0 | Y40: =IFERROR(OFFSET('HTM Output'!$J$6,MATCH($B40,'HTM Output'!$B$7:$B$37,0),MATCH(Y$11,'HTM Output'!$K$6:$GS$6,0)),0)*$I$8 -> 0 | Z40: =IFERROR(OFFSET('HTM Output'!$J$6,MATCH($B40,'HTM Output'!$B$7:$B$37,0),MATCH(Z$11,'HTM Output'!$K$6:$GS$6,0)),0)*$I$8 -> 0 | AA40: =IFERROR(OFFSET('HTM Output'!$J$6,MATCH($B40,'HTM Output'!$B$7:$B$37,0),MATCH(AA$11,'HTM Output'!$K$6:$GS$6,0)),0)*$I$8 -> 0 | AB40: =IFERROR(OFFSET('HTM Output'!$J$6,MATCH($B40,'HTM Output'!$B$7:$B$37,0),MATCH(AB$11,'HTM Output'!$K$6:$GS$6,0)),0)*$I$8 -> 0 | ... HB40: =IFERROR(OFFSET('HTM Output'!$J$6,MATCH($B40,'HTM Output'!$B$7:$B$37,0),MATCH(HB$11,'HTM Output'!$K$6:$GS$6,0)),0)*$I$8 -> 0 | HD40: =T40 -> 0 | HE40: =SUMIFS($T40:$HB40,$T$10:$HB$10,HE$11) -> 0 | HF40: =SUMIFS($T40:$HB40,$T$10:$HB$10,HF$11) -> 0 | HG40: =SUMIFS($T40:$HB40,$T$10:$HB$10,HG$11) -> 0 | HH40: =SUMIFS($T40:$HB40,$T$10:$HB$10,HH$11) -> 0 | HI40: =SUMIFS($T40:$HB40,$T$10:$HB$10,HI$11) -> 0 | HJ40: =SUMIFS($T40:$HB40,$T$10:$HB$10,HJ$11) -> 0 | HK40: =SUM(HD40:HJ40) -> 0
B42: RECOP I Opportunity | C42: =SUM(C13:C41) -> 1.8620571e+09 | D42: =E42/C42 -> 0.50362429 | E42: =SUM(E13:E41) -> 9.377772e+08 | F42: =Assumptions!$D$32 -> 15332622 | G42: =SUM(G13:G41) -> 9.5310983e+08 | H42: =IFERROR(SUMPRODUCT('HTM Output'!$K101:$GS101,'HTM Output'!$K$6:$GS$6)/SUM('HTM Output'!$K101:$GS101),_xlfn.MAXIFS($U$11:$HB$11,$U$14:$HB$14,">"&0)) -> 47792.681 | I42: =SUM(I13:I41) -> 3.3738401e+08 | J42: =HD50 -> 0.5 | K42: =SUM(K13:K41) -> 1.68692e+08 | L42: =SUM(L13:L41) -> -12348779 | M42: =-SUMIFS('HTM Output'!$K216:$GS216,'HTM Output'!$K$6:$GS$6,">"&'HTM Output'!$G$2,'HTM Output'!$K$6:$GS$6,"<="&'HTM Output'!$G$3)*$I$8 -> 471617.12 | N42: =L42+M42 -> -11877162 | O42: =SUM(O13:O41) -> 1.5681484e+08 | Q42: =IFERROR(XIRR($T42:$HB42,$T$11:$HB$11),"N/A") -> 0.17426575 | R42: =IFERROR((HK42+O42)/O42,"N/A") -> 1.6843486 | T42: =SUM(T13:T41) -> -1.5681484e+08 | U42: =SUM(U13:U41) -> 1959220.2 | V42: =SUM(V13:V41) -> 1959533.8 | W42: =SUM(W13:W41) -> 1889089.8 | X42: =SUM(X13:X41) -> 1887977.7 | Y42: =SUM(Y13:Y41) -> 1826362.4 | Z42: =SUM(Z13:Z41) -> 1835149.9 | AA42: =SUM(AA13:AA41) -> 1789431.1 | ... HB42: =SUM(HB13:HB41) -> 0 | HD42: =T42 -> -1.5681484e+08 | HE42: =SUMIFS($T42:$HB42,$T$10:$HB$10,HE$11) -> 21516084 | HF42: =SUMIFS($T42:$HB42,$T$10:$HB$10,HF$11) -> 15728410 | HG42: =SUMIFS($T42:$HB42,$T$10:$HB$10,HG$11) -> 62289110 | HH42: =SUMIFS($T42:$HB42,$T$10:$HB$10,HH$11) -> 76755499 | HI42: =SUMIFS($T42:$HB42,$T$10:$HB$10,HI$11) -> 59470579 | HJ42: =SUMIFS($T42:$HB42,$T$10:$HB$10,HJ$11) -> 28371179 | HK42: =SUM(HD42:HJ42) -> 1.0731602e+08
N44: Purchase Price Calculation
N46: Asset Fair Value | T46: =$E$42*$I$8 -> 3.3195653e+08 | HD46: =T46 -> 3.3195653e+08
N47: Cash & Receivables | T47: =$F$42*$I$8 -> 5427476.7 | HD47: =T47 -> 5427476.7
N48: Investor NAV | T48: =SUM(T46:T47) -> 3.3738401e+08 | HD48: =T48 -> 3.3738401e+08
N50: Purch Px | T50: =$J$42 -> 0.5 | HD50: 0.5
N51: Purchase Price | T51: =T48*T50 -> 1.68692e+08 | HD51: =T51 -> 1.68692e+08
N52: Net Distros During Cutoff Period | T52: =N42 -> -11877162 | HD52: =T52 -> -11877162
N53: Adjusted Price | T53: =T51+T52 -> 1.5681484e+08 | HD53: =T53 -> 1.5681484e+08
Q55: Fwd. IRR(B)(D) | R55: Fwd. MOIC(C)(E) | T55: =$I$4 -> 46388 | U55: =EOMONTH(T55,1) -> 46446 | V55: =EOMONTH(U55,1) -> 46477 | W55: =EOMONTH(V55,1) -> 46507 | X55: =EOMONTH(W55,1) -> 46538 | Y55: =EOMONTH(X55,1) -> 46568 | Z55: =EOMONTH(Y55,1) -> 46599 | AA55: =EOMONTH(Z55,1) -> 46630 | AB55: =EOMONTH(AA55,1) -> 46660 | ... HB55: =EOMONTH(HA55,1) -> 52200 | HD55: =TEXT($I$4,"m/d/yyyy")&" Acquisition" -> 1/1/2027 Acquisition | HE55: =YEAR(U55) -> 2027 | HF55: =HE55+1 -> 2028 | HG55: =HF55+1 -> 2029 | HH55: =HG55+1 -> 2030 | HI55: =HH55+1 -> 2031 | HJ55: =HI55+1 -> 2032 | HK55: Total
N56: Gross Cash Flows
N58: Interest Collections | U58: =IFERROR(OFFSET('HTM Output'!$J$169,0,MATCH(U$11,'HTM Output'!$K$6:$GS$6,0)),0)*$I$8 -> 1959220.2 | V58: =IFERROR(OFFSET('HTM Output'!$J$169,0,MATCH(V$11,'HTM Output'!$K$6:$GS$6,0)),0)*$I$8 -> 1959533.8 | W58: =IFERROR(OFFSET('HTM Output'!$J$169,0,MATCH(W$11,'HTM Output'!$K$6:$GS$6,0)),0)*$I$8 -> 1889089.8 | X58: =IFERROR(OFFSET('HTM Output'!$J$169,0,MATCH(X$11,'HTM Output'!$K$6:$GS$6,0)),0)*$I$8 -> 1887977.7 | Y58: =IFERROR(OFFSET('HTM Output'!$J$169,0,MATCH(Y$11,'HTM Output'!$K$6:$GS$6,0)),0)*$I$8 -> 1826362.4 | Z58: =IFERROR(OFFSET('HTM Output'!$J$169,0,MATCH(Z$11,'HTM Output'!$K$6:$GS$6,0)),0)*$I$8 -> 1835149.9 | AA58: =IFERROR(OFFSET('HTM Output'!$J$169,0,MATCH(AA$11,'HTM Output'!$K$6:$GS$6,0)),0)*$I$8 -> 1789431.1 | AB58: =IFERROR(OFFSET('HTM Output'!$J$169,0,MATCH(AB$11,'HTM Output'!$K$6:$GS$6,0)),0)*$I$8 -> 1819182.7 | ... HB58: =IFERROR(OFFSET('HTM Output'!$J$169,0,MATCH(HB$11,'HTM Output'!$K$6:$GS$6,0)),0)*$I$8 -> 0 | HD58: =T58 -> 0 | HE58: =SUMIFS($T58:$HB58,$T$10:$HB$10,HE$11) -> 21516084 | HF58: =SUMIFS($T58:$HB58,$T$10:$HB$10,HF$11) -> 15728410 | HG58: =SUMIFS($T58:$HB58,$T$10:$HB$10,HG$11) -> 10119095 | HH58: =SUMIFS($T58:$HB58,$T$10:$HB$10,HH$11) -> 8757548.1 | HI58: =SUMIFS($T58:$HB58,$T$10:$HB$10,HI$11) -> 3398347.8 | HJ58: =SUMIFS($T58:$HB58,$T$10:$HB$10,HJ$11) -> 967349.52 | HK58: =SUM(HD58:HJ58) -> 60486835
N59: Principal Collections | U59: =IFERROR(OFFSET('HTM Output'!$J$170,0,MATCH(U$11,'HTM Output'!$K$6:$GS$6,0)),0)*$I$8 -> 0 | V59: =IFERROR(OFFSET('HTM Output'!$J$170,0,MATCH(V$11,'HTM Output'!$K$6:$GS$6,0)),0)*$I$8 -> 0 | W59: =IFERROR(OFFSET('HTM Output'!$J$170,0,MATCH(W$11,'HTM Output'!$K$6:$GS$6,0)),0)*$I$8 -> 0 | X59: =IFERROR(OFFSET('HTM Output'!$J$170,0,MATCH(X$11,'HTM Output'!$K$6:$GS$6,0)),0)*$I$8 -> 0 | Y59: =IFERROR(OFFSET('HTM Output'!$J$170,0,MATCH(Y$11,'HTM Output'!$K$6:$GS$6,0)),0)*$I$8 -> 0 | Z59: =IFERROR(OFFSET('HTM Output'!$J$170,0,MATCH(Z$11,'HTM Output'!$K$6:$GS$6,0)),0)*$I$8 -> 0 | AA59: =IFERROR(OFFSET('HTM Output'!$J$170,0,MATCH(AA$11,'HTM Output'!$K$6:$GS$6,0)),0)*$I$8 -> 0 | AB59: =IFERROR(OFFSET('HTM Output'!$J$170,0,MATCH(AB$11,'HTM Output'!$K$6:$GS$6,0)),0)*$I$8 -> 0 | ... HB59: =IFERROR(OFFSET('HTM Output'!$J$170,0,MATCH(HB$11,'HTM Output'!$K$6:$GS$6,0)),0)*$I$8 -> 0 | HD59: =T59 -> 0 | HE59: =SUMIFS($T59:$HB59,$T$10:$HB$10,HE$11) -> 0 | HF59: =SUMIFS($T59:$HB59,$T$10:$HB$10,HF$11) -> 0 | HG59: =SUMIFS($T59:$HB59,$T$10:$HB$10,HG$11) -> 52170016 | HH59: =SUMIFS($T59:$HB59,$T$10:$HB$10,HH$11) -> 67997950 | HI59: =SUMIFS($T59:$HB59,$T$10:$HB$10,HI$11) -> 56072231 | HJ59: =SUMIFS($T59:$HB59,$T$10:$HB$10,HJ$11) -> 27403829 | HK59: =SUM(HD59:HJ59) -> 2.0364403e+08
N60: Distribution of Fund Cash & Receivables | U60: =IFERROR(OFFSET('HTM Output'!$J$225,0,MATCH(U$11,'HTM Output'!$K$6:$GS$6,0))-OFFSET('HTM Output'!$J$224,0,MATCH(U$11,'HTM Output'!$K$6:$GS$6,0)),0)*$I$8 -> -1888151.2 | V60: =IFERROR(OFFSET('HTM Output'!$J$225,0,MATCH(V$11,'HTM Output'!$K$6:$GS$6,0))-OFFSET('HTM Output'!$J$224,0,MATCH(V$11,'HTM Output'!$K$6:$GS$6,0)),0)*$I$8 -> -1888754.8 | W60: =IFERROR(OFFSET('HTM Output'!$J$225,0,MATCH(W$11,'HTM Output'!$K$6:$GS$6,0))-OFFSET('HTM Output'!$J$224,0,MATCH(W$11,'HTM Output'!$K$6:$GS$6,0)),0)*$I$8 -> 4131816.3 | X60: =IFERROR(OFFSET('HTM Output'!$J$225,0,MATCH(X$11,'HTM Output'!$K$6:$GS$6,0))-OFFSET('HTM Output'!$J$224,0,MATCH(X$11,'HTM Output'!$K$6:$GS$6,0)),0)*$I$8 -> -1818963.1 | Y60: =IFERROR(OFFSET('HTM Output'!$J$225,0,MATCH(Y$11,'HTM Output'!$K$6:$GS$6,0))-OFFSET('HTM Output'!$J$224,0,MATCH(Y$11,'HTM Output'!$K$6:$GS$6,0)),0)*$I$8 -> -1757347.8 | Z60: =IFERROR(OFFSET('HTM Output'!$J$225,0,MATCH(Z$11,'HTM Output'!$K$6:$GS$6,0))-OFFSET('HTM Output'!$J$224,0,MATCH(Z$11,'HTM Output'!$K$6:$GS$6,0)),0)*$I$8 -> 3583390.6 | AA60: =IFERROR(OFFSET('HTM Output'!$J$225,0,MATCH(AA$11,'HTM Output'!$K$6:$GS$6,0))-OFFSET('HTM Output'!$J$224,0,MATCH(AA$11,'HTM Output'!$K$6:$GS$6,0)),0)*$I$8 -> -1720416.5 | AB60: =IFERROR(OFFSET('HTM Output'!$J$225,0,MATCH(AB$11,'HTM Output'!$K$6:$GS$6,0))-OFFSET('HTM Output'!$J$224,0,MATCH(AB$11,'HTM Output'!$K$6:$GS$6,0)),0)*$I$8 -> -1750168 | ... HB60: =IFERROR(OFFSET('HTM Output'!$J$225,0,MATCH(HB$11,'HTM Output'!$K$6:$GS$6,0))-OFFSET('HTM Output'!$J$224,0,MATCH(HB$11,'HTM Output'!$K$6:$GS$6,0)),0)*$I$8 -> 0 | HD60: =T60 -> 0 | HE60: =SUMIFS($T60:$HB60,$T$10:$HB$10,HE$11) -> 524821.9 | HF60: =SUMIFS($T60:$HB60,$T$10:$HB$10,HF$11) -> 1341592.9 | HG60: =SUMIFS($T60:$HB60,$T$10:$HB$10,HG$11) -> 1235398.2 | HH60: =SUMIFS($T60:$HB60,$T$10:$HB$10,HH$11) -> 1196460.2 | HI60: =SUMIFS($T60:$HB60,$T$10:$HB$10,HI$11) -> 821238.93 | HJ60: =SUMIFS($T60:$HB60,$T$10:$HB$10,HJ$11) -> 307964.6 | HK60: =SUM(HD60:HJ60) -> 5427476.7
N61: Gross Distributions | U61: =SUM(U58:U60) -> 71069.076 | V61: =SUM(V58:V60) -> 70779.08 | W61: =SUM(W58:W60) -> 6020906.1 | X61: =SUM(X58:X60) -> 69014.62 | Y61: =SUM(Y58:Y60) -> 69014.62 | Z61: =SUM(Z58:Z60) -> 5418540.5 | AA61: =SUM(AA58:AA60) -> 69014.62 | AB61: =SUM(AB58:AB60) -> 69014.62 | ... HB61: =SUM(HB58:HB60) -> 0 | HD61: =T61 -> 0 | HE61: =SUMIFS($T61:$HB61,$T$10:$HB$10,HE$11) -> 22040906 | HF61: =SUMIFS($T61:$HB61,$T$10:$HB$10,HF$11) -> 17070003 | HG61: =SUMIFS($T61:$HB61,$T$10:$HB$10,HG$11) -> 63524509 | HH61: =SUMIFS($T61:$HB61,$T$10:$HB$10,HH$11) -> 77951959 | HI61: =SUMIFS($T61:$HB61,$T$10:$HB$10,HI$11) -> 60291818 | HJ61: =SUMIFS($T61:$HB61,$T$10:$HB$10,HJ$11) -> 28679143 | HK61: =SUM(HD61:HJ61) -> 2.6955834e+08
N63: Gross B-Piece Cash Flows | Q63: =IFERROR(XIRR($T63:$HB63,$T$11:$HB$11),"N/A") -> 0.17801564 | R63: =-HK61/HD63 -> 1.7189593 | T63: =-T53 -> -1.5681484e+08 | U63: =U61 -> 71069.076 | V63: =V61 -> 70779.08 | W63: =W61 -> 6020906.1 | X63: =X61 -> 69014.62 | Y63: =Y61 -> 69014.62 | Z63: =Z61 -> 5418540.5 | AA63: =AA61 -> 69014.62 | AB63: =AB61 -> 69014.62 | ... HB63: =HB61 -> 0 | HD63: =T63 -> -1.5681484e+08 | HE63: =SUMIFS($T63:$HB63,$T$10:$HB$10,HE$11) -> 22040906 | HF63: =SUMIFS($T63:$HB63,$T$10:$HB$10,HF$11) -> 17070003 | HG63: =SUMIFS($T63:$HB63,$T$10:$HB$10,HG$11) -> 63524509 | HH63: =SUMIFS($T63:$HB63,$T$10:$HB$10,HH$11) -> 77951959 | HI63: =SUMIFS($T63:$HB63,$T$10:$HB$10,HI$11) -> 60291818 | HJ63: =SUMIFS($T63:$HB63,$T$10:$HB$10,HJ$11) -> 28679143 | HK63: =SUM(HD63:HJ63) -> 1.127435e+08
N65: Fees & Expenses | T65: Fees & Expenses
N67: KKR Fee Basis | T67: =IFERROR(OFFSET('HTM Output'!$J$209,0,MATCH(T$11,'HTM Output'!$K$6:$GS$6,0)),0)*$I$8 -> 0 | U67: =IFERROR(OFFSET('HTM Output'!$J$209,0,MATCH(U$11,'HTM Output'!$K$6:$GS$6,0)),0)*$I$8 -> 3.0037234e+08 | V67: =IFERROR(OFFSET('HTM Output'!$J$209,0,MATCH(V$11,'HTM Output'!$K$6:$GS$6,0)),0)*$I$8 -> 2.9882569e+08 | W67: =IFERROR(OFFSET('HTM Output'!$J$209,0,MATCH(W$11,'HTM Output'!$K$6:$GS$6,0)),0)*$I$8 -> 2.8990629e+08 | X67: =IFERROR(OFFSET('HTM Output'!$J$209,0,MATCH(X$11,'HTM Output'!$K$6:$GS$6,0)),0)*$I$8 -> 2.8941524e+08 | Y67: =IFERROR(OFFSET('HTM Output'!$J$209,0,MATCH(Y$11,'HTM Output'!$K$6:$GS$6,0)),0)*$I$8 -> 2.8941524e+08 | Z67: =IFERROR(OFFSET('HTM Output'!$J$209,0,MATCH(Z$11,'HTM Output'!$K$6:$GS$6,0)),0)*$I$8 -> 2.8941524e+08 | AA67: =IFERROR(OFFSET('HTM Output'!$J$209,0,MATCH(AA$11,'HTM Output'!$K$6:$GS$6,0)),0)*$I$8 -> 2.8941524e+08 | ... HB67: =IFERROR(OFFSET('HTM Output'!$J$209,0,MATCH(HB$11,'HTM Output'!$K$6:$GS$6,0)),0)*$I$8 -> 0 | HE67: =AVERAGEIFS($T67:$HB67,$T$10:$HB$10,HE$11) -> 2.8881503e+08 | HF67: =AVERAGEIFS($T67:$HB67,$T$10:$HB$10,HF$11) -> 2.4479033e+08 | HG67: =AVERAGEIFS($T67:$HB67,$T$10:$HB$10,HG$11) -> 1.6823175e+08 | HH67: =AVERAGEIFS($T67:$HB67,$T$10:$HB$10,HH$11) -> 1.0867926e+08 | HI67: =AVERAGEIFS($T67:$HB67,$T$10:$HB$10,HI$11) -> 33717203 | HJ67: =AVERAGEIFS($T67:$HB67,$T$10:$HB$10,HJ$11) -> 3121532.4
N69: Investment Management Fee | U69: =IFERROR(OFFSET('HTM Output'!$J$211,0,MATCH(U$11,'HTM Output'!$K$6:$GS$6,0)),0)*$I$8 -> -312887.85 | V69: =IFERROR(OFFSET('HTM Output'!$J$211,0,MATCH(V$11,'HTM Output'!$K$6:$GS$6,0)),0)*$I$8 -> -311276.76 | W69: =IFERROR(OFFSET('HTM Output'!$J$211,0,MATCH(W$11,'HTM Output'!$K$6:$GS$6,0)),0)*$I$8 -> -301985.72 | X69: =IFERROR(OFFSET('HTM Output'!$J$211,0,MATCH(X$11,'HTM Output'!$K$6:$GS$6,0)),0)*$I$8 -> -301474.21 | Y69: =IFERROR(OFFSET('HTM Output'!$J$211,0,MATCH(Y$11,'HTM Output'!$K$6:$GS$6,0)),0)*$I$8 -> -301474.21 | Z69: =IFERROR(OFFSET('HTM Output'!$J$211,0,MATCH(Z$11,'HTM Output'!$K$6:$GS$6,0)),0)*$I$8 -> -301474.21 | AA69: =IFERROR(OFFSET('HTM Output'!$J$211,0,MATCH(AA$11,'HTM Output'!$K$6:$GS$6,0)),0)*$I$8 -> -301474.21 | AB69: =IFERROR(OFFSET('HTM Output'!$J$211,0,MATCH(AB$11,'HTM Output'!$K$6:$GS$6,0)),0)*$I$8 -> -301474.21 | ... HB69: =IFERROR(OFFSET('HTM Output'!$J$211,0,MATCH(HB$11,'HTM Output'!$K$6:$GS$6,0)),0)*$I$8 -> 0 | HD69: =SUMIFS($T69:$HB69,$T$10:$HB$10,HD$11) -> 0 | HE69: =SUMIFS($T69:$HB69,$T$10:$HB$10,HE$11) -> -3610187.8 | HF69: =SUMIFS($T69:$HB69,$T$10:$HB$10,HF$11) -> -3059879.1 | HG69: =SUMIFS($T69:$HB69,$T$10:$HB$10,HG$11) -> -2102896.9 | HH69: =SUMIFS($T69:$HB69,$T$10:$HB$10,HH$11) -> -1358490.8 | HI69: =SUMIFS($T69:$HB69,$T$10:$HB$10,HI$11) -> -421465.03 | HJ69: =SUMIFS($T69:$HB69,$T$10:$HB$10,HJ$11) -> -39019.155 | HK69: =SUM(HD69:HJ69) -> -10591939
N70: Special Servicing Offset* | U70: =IFERROR(OFFSET('HTM Output'!$J$212,0,MATCH(U$11,'HTM Output'!$K$6:$GS$6,0)),0)*$I$8 -> 281599.07 | V70: =IFERROR(OFFSET('HTM Output'!$J$212,0,MATCH(V$11,'HTM Output'!$K$6:$GS$6,0)),0)*$I$8 -> 280149.09 | W70: =IFERROR(OFFSET('HTM Output'!$J$212,0,MATCH(W$11,'HTM Output'!$K$6:$GS$6,0)),0)*$I$8 -> 271787.15 | X70: =IFERROR(OFFSET('HTM Output'!$J$212,0,MATCH(X$11,'HTM Output'!$K$6:$GS$6,0)),0)*$I$8 -> 271326.79 | Y70: =IFERROR(OFFSET('HTM Output'!$J$212,0,MATCH(Y$11,'HTM Output'!$K$6:$GS$6,0)),0)*$I$8 -> 271326.79 | Z70: =IFERROR(OFFSET('HTM Output'!$J$212,0,MATCH(Z$11,'HTM Output'!$K$6:$GS$6,0)),0)*$I$8 -> 271326.79 | AA70: =IFERROR(OFFSET('HTM Output'!$J$212,0,MATCH(AA$11,'HTM Output'!$K$6:$GS$6,0)),0)*$I$8 -> 271326.79 | AB70: =IFERROR(OFFSET('HTM Output'!$J$212,0,MATCH(AB$11,'HTM Output'!$K$6:$GS$6,0)),0)*$I$8 -> 271326.79 | ... HB70: =IFERROR(OFFSET('HTM Output'!$J$212,0,MATCH(HB$11,'HTM Output'!$K$6:$GS$6,0)),0)*$I$8 -> 0 | HD70: =SUMIFS($T70:$HB70,$T$10:$HB$10,HD$11) -> 0 | HE70: =SUMIFS($T70:$HB70,$T$10:$HB$10,HE$11) -> 3249169.1 | HF70: =SUMIFS($T70:$HB70,$T$10:$HB$10,HF$11) -> 2753891.2 | HG70: =SUMIFS($T70:$HB70,$T$10:$HB$10,HG$11) -> 1892607.2 | HH70: =SUMIFS($T70:$HB70,$T$10:$HB$10,HH$11) -> 1222641.7 | HI70: =SUMIFS($T70:$HB70,$T$10:$HB$10,HI$11) -> 379318.53 | HJ70: =SUMIFS($T70:$HB70,$T$10:$HB$10,HJ$11) -> 35117.24 | HK70: =SUM(HD70:HJ70) -> 9532745
N71: Fund Admin. Expense | U71: =IFERROR(OFFSET('HTM Output'!$J$213,0,MATCH(U$11,'HTM Output'!$K$6:$GS$6,0)),0)*$I$8 -> -25031.028 | V71: =IFERROR(OFFSET('HTM Output'!$J$213,0,MATCH(V$11,'HTM Output'!$K$6:$GS$6,0)),0)*$I$8 -> -24902.141 | W71: =IFERROR(OFFSET('HTM Output'!$J$213,0,MATCH(W$11,'HTM Output'!$K$6:$GS$6,0)),0)*$I$8 -> -24158.858 | X71: =IFERROR(OFFSET('HTM Output'!$J$213,0,MATCH(X$11,'HTM Output'!$K$6:$GS$6,0)),0)*$I$8 -> -24117.937 | Y71: =IFERROR(OFFSET('HTM Output'!$J$213,0,MATCH(Y$11,'HTM Output'!$K$6:$GS$6,0)),0)*$I$8 -> -24117.937 | Z71: =IFERROR(OFFSET('HTM Output'!$J$213,0,MATCH(Z$11,'HTM Output'!$K$6:$GS$6,0)),0)*$I$8 -> -24117.937 | AA71: =IFERROR(OFFSET('HTM Output'!$J$213,0,MATCH(AA$11,'HTM Output'!$K$6:$GS$6,0)),0)*$I$8 -> -24117.937 | AB71: =IFERROR(OFFSET('HTM Output'!$J$213,0,MATCH(AB$11,'HTM Output'!$K$6:$GS$6,0)),0)*$I$8 -> -24117.937 | ... HB71: =IFERROR(OFFSET('HTM Output'!$J$213,0,MATCH(HB$11,'HTM Output'!$K$6:$GS$6,0)),0)*$I$8 -> 0 | HD71: =SUMIFS($T71:$HB71,$T$10:$HB$10,HD$11) -> 0 | HE71: =SUMIFS($T71:$HB71,$T$10:$HB$10,HE$11) -> -288815.03 | HF71: =SUMIFS($T71:$HB71,$T$10:$HB$10,HF$11) -> -244790.33 | HG71: =SUMIFS($T71:$HB71,$T$10:$HB$10,HG$11) -> -168231.75 | HH71: =SUMIFS($T71:$HB71,$T$10:$HB$10,HH$11) -> -108679.26 | HI71: =SUMIFS($T71:$HB71,$T$10:$HB$10,HI$11) -> -33717.203 | HJ71: =SUMIFS($T71:$HB71,$T$10:$HB$10,HJ$11) -> -3121.5324 | HK71: =SUM(HD71:HJ71) -> -847355.11
N72: Fund G&A Expenses | U72: =IFERROR(OFFSET('HTM Output'!$J$214,0,MATCH(U$11,'HTM Output'!$K$6:$GS$6,0)),0)*$I$8 -> -14749.262 | V72: =IFERROR(OFFSET('HTM Output'!$J$214,0,MATCH(V$11,'HTM Output'!$K$6:$GS$6,0)),0)*$I$8 -> -14749.262 | W72: =IFERROR(OFFSET('HTM Output'!$J$214,0,MATCH(W$11,'HTM Output'!$K$6:$GS$6,0)),0)*$I$8 -> -14749.262 | X72: =IFERROR(OFFSET('HTM Output'!$J$214,0,MATCH(X$11,'HTM Output'!$K$6:$GS$6,0)),0)*$I$8 -> -14749.262 | Y72: =IFERROR(OFFSET('HTM Output'!$J$214,0,MATCH(Y$11,'HTM Output'!$K$6:$GS$6,0)),0)*$I$8 -> -14749.262 | Z72: =IFERROR(OFFSET('HTM Output'!$J$214,0,MATCH(Z$11,'HTM Output'!$K$6:$GS$6,0)),0)*$I$8 -> -14749.262 | AA72: =IFERROR(OFFSET('HTM Output'!$J$214,0,MATCH(AA$11,'HTM Output'!$K$6:$GS$6,0)),0)*$I$8 -> -14749.262 | AB72: =IFERROR(OFFSET('HTM Output'!$J$214,0,MATCH(AB$11,'HTM Output'!$K$6:$GS$6,0)),0)*$I$8 -> -14749.262 | ... HB72: =IFERROR(OFFSET('HTM Output'!$J$214,0,MATCH(HB$11,'HTM Output'!$K$6:$GS$6,0)),0)*$I$8 -> 0 | HD72: =SUMIFS($T72:$HB72,$T$10:$HB$10,HD$11) -> 0 | HE72: =SUMIFS($T72:$HB72,$T$10:$HB$10,HE$11) -> -176991.15 | HF72: =SUMIFS($T72:$HB72,$T$10:$HB$10,HF$11) -> -176991.15 | HG72: =SUMIFS($T72:$HB72,$T$10:$HB$10,HG$11) -> -176991.15 | HH72: =SUMIFS($T72:$HB72,$T$10:$HB$10,HH$11) -> -176991.15 | HI72: =SUMIFS($T72:$HB72,$T$10:$HB$10,HI$11) -> -176991.15 | HJ72: =SUMIFS($T72:$HB72,$T$10:$HB$10,HJ$11) -> -176991.15 | HK72: =SUM(HD72:HJ72) -> -1061946.9
N73: Fund Org. Costs | U73: 0 | V73: 0 | W73: 0 | X73: 0 | Y73: 0 | Z73: 0 | AA73: 0 | AB73: 0 | AC73: 0 | AD73: 0 | AE73: 0 | AF73: 0 | AG73: 0 | AH73: 0 | AI73: 0 | AJ73: 0 | AK73: 0 | AL73: 0 | AM73: 0 | AN73: 0 | AO73: 0 | AP73: 0 | AQ73: 0 | AR73: 0 | AS73: 0 | AT73: 0 | AU73: 0 | AV73: 0 | AW73: 0 | AX73: 0 | AY73: 0 | AZ73: 0 | BA73: 0 | BB73: 0 | BC73: 0 | BD73: 0 | BE73: 0 | BF73: 0 | BG73: 0 | BH73: 0 | BI73: 0 | BJ73: 0 | BK73: 0 | BL73: 0 | BM73: 0 | BN73: 0 | BO73: 0 | BP73: 0 | BQ73: 0 | BR73: 0 | BS73: 0 | BT73: 0 | BU73: 0 | BV73: 0 | BW73: 0 | BX73: 0 | BY73: 0 | BZ73: 0 | CA73: 0 | CB73: 0 | CC73: 0 | CD73: 0 | CE73: 0 | CF73: 0 | CG73: 0 | CH73: 0 | CI73: 0 | CJ73: 0 | CK73: 0 | CL73: 0 | CM73: 0 | CN73: 0 | CO73: 0 | CP73: 0 | CQ73: 0 | CR73: 0 | CS73: 0 | CT73: 0 | CU73: 0 | CV73: 0 | CW73: 0 | CX73: 0 | CY73: 0 | CZ73: 0 | DA73: 0 | DB73: 0 | DC73: 0 | DD73: 0 | DE73: 0 | DF73: 0 | DG73: 0 | DH73: 0 | DI73: 0 | DJ73: 0 | DK73: 0 | DL73: 0 | DM73: 0 | DN73: 0 | DO73: 0 | DP73: 0 | DQ73: 0 | DR73: 0 | DS73: 0 | DT73: 0 | DU73: 0 | DV73: 0 | DW73: 0 | DX73: 0 | DY73: 0 | DZ73: 0 | EA73: 0 | EB73: 0 | EC73: 0 | ED73: 0 | EE73: 0 | EF73: 0 | EG73: 0 | EH73: 0 | EI73: 0 | EJ73: 0 | EK73: 0 | EL73: 0 | EM73: 0 | EN73: 0 | EO73: 0 | EP73: 0 | EQ73: 0 | ER73: 0 | ES73: 0 | ET73: 0 | EU73: 0 | EV73: 0 | EW73: 0 | EX73: 0 | EY73: 0 | EZ73: 0 | FA73: 0 | FB73: 0 | FC73: 0 | FD73: 0 | FE73: 0 | FF73: 0 | FG73: 0 | FH73: 0 | FI73: 0 | FJ73: 0 | FK73: 0 | FL73: 0 | FM73: 0 | FN73: 0 | FO73: 0 | FP73: 0 | FQ73: 0 | FR73: 0 | FS73: 0 | FT73: 0 | FU73: 0 | FV73: 0 | FW73: 0 | FX73: 0 | FY73: 0 | FZ73: 0 | GA73: 0 | GB73: 0 | GC73: 0 | GD73: 0 | GE73: 0 | GF73: 0 | GG73: 0 | GH73: 0 | GI73: 0 | GJ73: 0 | GK73: 0 | GL73: 0 | GM73: 0 | GN73: 0 | GO73: 0 | GP73: 0 | GQ73: 0 | GR73: 0 | GS73: 0 | GT73: 0 | GU73: 0 | GV73: 0 | GW73: 0 | GX73: 0 | GY73: 0 | GZ73: 0 | HA73: 0 | HB73: 0 | HD73: =SUMIFS($T73:$HB73,$T$10:$HB$10,HD$11) -> 0 | HE73: =SUMIFS($T73:$HB73,$T$10:$HB$10,HE$11) -> 0 | HF73: =SUMIFS($T73:$HB73,$T$10:$HB$10,HF$11) -> 0 | HG73: =SUMIFS($T73:$HB73,$T$10:$HB$10,HG$11) -> 0 | HH73: =SUMIFS($T73:$HB73,$T$10:$HB$10,HH$11) -> 0 | HI73: =SUMIFS($T73:$HB73,$T$10:$HB$10,HI$11) -> 0 | HJ73: =SUMIFS($T73:$HB73,$T$10:$HB$10,HJ$11) -> 0 | HK73: =SUM(HD73:HJ73) -> 0
N74: Fund Fees / Expenses | U74: =SUM(U69:U73) -> -71069.076 | V74: =SUM(V69:V73) -> -70779.08 | W74: =SUM(W69:W73) -> -69106.692 | X74: =SUM(X69:X73) -> -69014.62 | Y74: =SUM(Y69:Y73) -> -69014.62 | Z74: =SUM(Z69:Z73) -> -69014.62 | AA74: =SUM(AA69:AA73) -> -69014.62 | AB74: =SUM(AB69:AB73) -> -69014.62 | ... HB74: =SUM(HB69:HB73) -> 0 | HD74: =SUMIFS($T74:$HB74,$T$10:$HB$10,HD$11) -> 0 | HE74: =SUMIFS($T74:$HB74,$T$10:$HB$10,HE$11) -> -826824.96 | HF74: =SUMIFS($T74:$HB74,$T$10:$HB$10,HF$11) -> -727769.4 | HG74: =SUMIFS($T74:$HB74,$T$10:$HB$10,HG$11) -> -555512.59 | HH74: =SUMIFS($T74:$HB74,$T$10:$HB$10,HH$11) -> -421519.49 | HI74: =SUMIFS($T74:$HB74,$T$10:$HB$10,HI$11) -> -252854.86 | HJ74: =SUMIFS($T74:$HB74,$T$10:$HB$10,HJ$11) -> -184014.6 | HK74: =SUM(HD74:HJ74) -> -2968495.9
N76: Special Servicing Offset Curve | T76: =IFERROR(OFFSET('HTM Output'!$J$218,0,MATCH(T$11,'HTM Output'!$K$6:$GS$6,0)),0) -> 0 | U76: =IFERROR(OFFSET('HTM Output'!$J$218,0,MATCH(U$11,'HTM Output'!$K$6:$GS$6,0)),0) -> 0.9 | V76: =IFERROR(OFFSET('HTM Output'!$J$218,0,MATCH(V$11,'HTM Output'!$K$6:$GS$6,0)),0) -> 0.9 | W76: =IFERROR(OFFSET('HTM Output'!$J$218,0,MATCH(W$11,'HTM Output'!$K$6:$GS$6,0)),0) -> 0.9 | X76: =IFERROR(OFFSET('HTM Output'!$J$218,0,MATCH(X$11,'HTM Output'!$K$6:$GS$6,0)),0) -> 0.9 | Y76: =IFERROR(OFFSET('HTM Output'!$J$218,0,MATCH(Y$11,'HTM Output'!$K$6:$GS$6,0)),0) -> 0.9 | Z76: =IFERROR(OFFSET('HTM Output'!$J$218,0,MATCH(Z$11,'HTM Output'!$K$6:$GS$6,0)),0) -> 0.9 | AA76: =IFERROR(OFFSET('HTM Output'!$J$218,0,MATCH(AA$11,'HTM Output'!$K$6:$GS$6,0)),0) -> 0.9 | ... HB76: =IFERROR(OFFSET('HTM Output'!$J$218,0,MATCH(HB$11,'HTM Output'!$K$6:$GS$6,0)),0) -> 0 | HE76: =AVERAGEIFS($T76:$HB76,$T$10:$HB$10,HE$11) -> 0.9 | HF76: =AVERAGEIFS($T76:$HB76,$T$10:$HB$10,HF$11) -> 0.9 | HG76: =AVERAGEIFS($T76:$HB76,$T$10:$HB$10,HG$11) -> 0.9 | HH76: =AVERAGEIFS($T76:$HB76,$T$10:$HB$10,HH$11) -> 0.9 | HI76: =AVERAGEIFS($T76:$HB76,$T$10:$HB$10,HI$11) -> 0.9 | HJ76: =AVERAGEIFS($T76:$HB76,$T$10:$HB$10,HJ$11) -> 0.9
N78: GP Promote | U78: =IFERROR(OFFSET('HTM Output'!$J$231,0,MATCH(U$11,'HTM Output'!$K$6:$GS$6,0)),0)*$I$8 -> 0 | V78: =IFERROR(OFFSET('HTM Output'!$J$231,0,MATCH(V$11,'HTM Output'!$K$6:$GS$6,0)),0)*$I$8 -> 0 | W78: =IFERROR(OFFSET('HTM Output'!$J$231,0,MATCH(W$11,'HTM Output'!$K$6:$GS$6,0)),0)*$I$8 -> 0 | X78: =IFERROR(OFFSET('HTM Output'!$J$231,0,MATCH(X$11,'HTM Output'!$K$6:$GS$6,0)),0)*$I$8 -> 0 | Y78: =IFERROR(OFFSET('HTM Output'!$J$231,0,MATCH(Y$11,'HTM Output'!$K$6:$GS$6,0)),0)*$I$8 -> 0 | Z78: =IFERROR(OFFSET('HTM Output'!$J$231,0,MATCH(Z$11,'HTM Output'!$K$6:$GS$6,0)),0)*$I$8 -> 0 | AA78: =IFERROR(OFFSET('HTM Output'!$J$231,0,MATCH(AA$11,'HTM Output'!$K$6:$GS$6,0)),0)*$I$8 -> 0 | AB78: =IFERROR(OFFSET('HTM Output'!$J$231,0,MATCH(AB$11,'HTM Output'!$K$6:$GS$6,0)),0)*$I$8 -> 0 | ... HB78: =IFERROR(OFFSET('HTM Output'!$J$231,0,MATCH(HB$11,'HTM Output'!$K$6:$GS$6,0)),0)*$I$8 -> 0 | HD78: =T78 -> 0 | HE78: =SUMIFS($T78:$HB78,$T$10:$HB$10,HE$11) -> 0 | HF78: =SUMIFS($T78:$HB78,$T$10:$HB$10,HF$11) -> 0 | HG78: =SUMIFS($T78:$HB78,$T$10:$HB$10,HG$11) -> 0 | HH78: =SUMIFS($T78:$HB78,$T$10:$HB$10,HH$11) -> 0 | HI78: =SUMIFS($T78:$HB78,$T$10:$HB$10,HI$11) -> 0 | HJ78: =SUMIFS($T78:$HB78,$T$10:$HB$10,HJ$11) -> 0 | HK78: =SUM(HD78:HJ78) -> 0
N79: Net Distributions | U79: =IFERROR(OFFSET('HTM Output'!$J$232,0,MATCH(U$11,'HTM Output'!$K$6:$GS$6,0)),0)*$I$8 -> 0 | V79: =IFERROR(OFFSET('HTM Output'!$J$232,0,MATCH(V$11,'HTM Output'!$K$6:$GS$6,0)),0)*$I$8 -> 0 | W79: =IFERROR(OFFSET('HTM Output'!$J$232,0,MATCH(W$11,'HTM Output'!$K$6:$GS$6,0)),0)*$I$8 -> 5951799.4 | X79: =IFERROR(OFFSET('HTM Output'!$J$232,0,MATCH(X$11,'HTM Output'!$K$6:$GS$6,0)),0)*$I$8 -> 0 | Y79: =IFERROR(OFFSET('HTM Output'!$J$232,0,MATCH(Y$11,'HTM Output'!$K$6:$GS$6,0)),0)*$I$8 -> 0 | Z79: =IFERROR(OFFSET('HTM Output'!$J$232,0,MATCH(Z$11,'HTM Output'!$K$6:$GS$6,0)),0)*$I$8 -> 5349525.9 | AA79: =IFERROR(OFFSET('HTM Output'!$J$232,0,MATCH(AA$11,'HTM Output'!$K$6:$GS$6,0)),0)*$I$8 -> 0 | AB79: =IFERROR(OFFSET('HTM Output'!$J$232,0,MATCH(AB$11,'HTM Output'!$K$6:$GS$6,0)),0)*$I$8 -> 0 | ... HB79: =IFERROR(OFFSET('HTM Output'!$J$232,0,MATCH(HB$11,'HTM Output'!$K$6:$GS$6,0)),0)*$I$8 -> 0 | HD79: =T79 -> 0 | HE79: =SUMIFS($T79:$HB79,$T$10:$HB$10,HE$11) -> 21214081 | HF79: =SUMIFS($T79:$HB79,$T$10:$HB$10,HF$11) -> 16342234 | HG79: =SUMIFS($T79:$HB79,$T$10:$HB$10,HG$11) -> 62968996 | HH79: =SUMIFS($T79:$HB79,$T$10:$HB$10,HH$11) -> 77530439 | HI79: =SUMIFS($T79:$HB79,$T$10:$HB$10,HI$11) -> 60038963 | HJ79: =SUMIFS($T79:$HB79,$T$10:$HB$10,HJ$11) -> 28495129 | HK79: =SUM(HD79:HJ79) -> 2.6658984e+08
N81: Cash Flow to KKR LP | Q81: =IFERROR(XIRR($T81:$HB81,$T$11:$HB$11),"N/A") -> 0.1729451 | R81: =HK79/-T81 -> 1.7000294 | T81: =T42 -> -1.5681484e+08 | U81: =U79 -> 0 | V81: =V79 -> 0 | W81: =W79 -> 5951799.4 | X81: =X79 -> 0 | Y81: =Y79 -> 0 | Z81: =Z79 -> 5349525.9 | AA81: =AA79 -> 0 | AB81: =AB79 -> 0 | ... HB81: =HB79 -> 0 | HD81: =T81 -> -1.5681484e+08 | HE81: =SUMIFS($T81:$HB81,$T$10:$HB$10,HE$11) -> 21214081 | HF81: =SUMIFS($T81:$HB81,$T$10:$HB$10,HF$11) -> 16342234 | HG81: =SUMIFS($T81:$HB81,$T$10:$HB$10,HG$11) -> 62968996 | HH81: =SUMIFS($T81:$HB81,$T$10:$HB$10,HH$11) -> 77530439 | HI81: =SUMIFS($T81:$HB81,$T$10:$HB$10,HI$11) -> 60038963 | HJ81: =SUMIFS($T81:$HB81,$T$10:$HB$10,HJ$11) -> 28495129 | HK81: =SUM(HD81:HJ81) -> 1.09775e+08 | HL81: =ROUND(HK81,2)=ROUND(HK61+HK74+HK78+HD81,2) -> TRUE
N83: Rialto Fee Basis | T83: =-T81 -> 1.5681484e+08 | U83: =-$T$81*U67/$U$67 -> 1.5681484e+08 | V83: =-$T$81*V67/$U$67 -> 1.5600739e+08 | W83: =-$T$81*W67/$U$67 -> 1.5135085e+08 | X83: =-$T$81*X67/$U$67 -> 1.5109449e+08 | Y83: =-$T$81*Y67/$U$67 -> 1.5109449e+08 | Z83: =-$T$81*Z67/$U$67 -> 1.5109449e+08 | AA83: =-$T$81*AA67/$U$67 -> 1.5109449e+08 | AB83: =-$T$81*AB67/$U$67 -> 1.5109449e+08 | ... HB83: =-$T$81*HB67/$U$67 -> 0 | HD83: =T83 -> 1.5681484e+08 | HE83: =AVERAGEIFS($T83:$HB83,$T$10:$HB$10,HE$11) -> 1.5078114e+08 | HF83: =AVERAGEIFS($T83:$HB83,$T$10:$HB$10,HF$11) -> 1.2779725e+08 | HG83: =AVERAGEIFS($T83:$HB83,$T$10:$HB$10,HG$11) -> 87828447 | HH83: =AVERAGEIFS($T83:$HB83,$T$10:$HB$10,HH$11) -> 56737985 | HI83: =AVERAGEIFS($T83:$HB83,$T$10:$HB$10,HI$11) -> 17602679 | HJ83: =AVERAGEIFS($T83:$HB83,$T$10:$HB$10,HJ$11) -> 1629652.8
N85: DD Fee (on Cost Basis) | O85: =Assumptions!$D$35 -> 0.0075 | T85: =-T$83*$O85 -> -1176111.3 | HD85: =T85 -> -1176111.3 | HE85: =SUMIFS($T85:$HB85,$T$10:$HB$10,HE$11) -> 0 | HF85: =SUMIFS($T85:$HB85,$T$10:$HB$10,HF$11) -> 0 | HG85: =SUMIFS($T85:$HB85,$T$10:$HB$10,HG$11) -> 0 | HH85: =SUMIFS($T85:$HB85,$T$10:$HB$10,HH$11) -> 0 | HI85: =SUMIFS($T85:$HB85,$T$10:$HB$10,HI$11) -> 0 | HJ85: =SUMIFS($T85:$HB85,$T$10:$HB$10,HJ$11) -> 0 | HK85: =SUM(HD85:HJ85) -> -1176111.3
N86: IHPS Fee (on Cost Basis) | O86: =Assumptions!$D$36 -> 0.001 | U86: =-U$83*$O86/12 -> -13067.904 | V86: =-V$83*$O86/12 -> -13000.616 | W86: =-W$83*$O86/12 -> -12612.571 | X86: =-X$83*$O86/12 -> -12591.208 | Y86: =-Y$83*$O86/12 -> -12591.208 | Z86: =-Z$83*$O86/12 -> -12591.208 | AA86: =-AA$83*$O86/12 -> -12591.208 | AB86: =-AB$83*$O86/12 -> -12591.208 | ... HB86: =-HB$83*$O86/12 -> 0 | HD86: =T86 -> 0 | HE86: =SUMIFS($T86:$HB86,$T$10:$HB$10,HE$11) -> -150781.14 | HF86: =SUMIFS($T86:$HB86,$T$10:$HB$10,HF$11) -> -127797.25 | HG86: =SUMIFS($T86:$HB86,$T$10:$HB$10,HG$11) -> -87828.447 | HH86: =SUMIFS($T86:$HB86,$T$10:$HB$10,HH$11) -> -56737.985 | HI86: =SUMIFS($T86:$HB86,$T$10:$HB$10,HI$11) -> -17602.679 | HJ86: =SUMIFS($T86:$HB86,$T$10:$HB$10,HJ$11) -> -1629.6528 | HK86: =SUM(HD86:HJ86) -> -442377.15
N88: Net Cash Flows | Q88: =IFERROR(XIRR($T88:$HB88,$T$11:$HB$11),"N/A") -> 0.16939822 | R88: =-(HK79+HK85+HK86)/T81 -> 1.6897084 | T88: =T81+T85+T86 -> -1.5799095e+08 | U88: =U81+U85+U86 -> -13067.904 | V88: =V81+V85+V86 -> -13000.616 | W88: =W81+W85+W86 -> 5939186.8 | X88: =X81+X85+X86 -> -12591.208 | Y88: =Y81+Y85+Y86 -> -12591.208 | Z88: =Z81+Z85+Z86 -> 5336934.7 | AA88: =AA81+AA85+AA86 -> -12591.208 | ... HB88: =HB81+HB85+HB86 -> 0 | HD88: =T88 -> -1.5799095e+08 | HE88: =SUMIFS($T88:$HB88,$T$10:$HB$10,HE$11) -> 21063300 | HF88: =SUMIFS($T88:$HB88,$T$10:$HB$10,HF$11) -> 16214437 | HG88: =SUMIFS($T88:$HB88,$T$10:$HB$10,HG$11) -> 62881168 | HH88: =SUMIFS($T88:$HB88,$T$10:$HB$10,HH$11) -> 77473701 | HI88: =SUMIFS($T88:$HB88,$T$10:$HB$10,HI$11) -> 60021361 | HJ88: =SUMIFS($T88:$HB88,$T$10:$HB$10,HJ$11) -> 28493499 | HK88: =SUM(HD88:HJ88) -> 1.0815651e+08 | HL88: =HK81+HK85+HK86=HK88 -> TRUE
N89: *Capped at IM Fee,with full ITD refund at end | U89: =SUMIFS('HTM Output'!$K$236:$GS$236,'HTM Output'!$K$6:$GS$6,">"&'HTM Output'!$G$3)*$I$8=SUM(U81:HB81) -> TRUE
N91: Disclaimer: This model is being presented for the limited purpose of illustrating cash flows from the KKR RECOP I LP Secondary Opportunity (the "Opportunity"). The returns, cash flows, and other figures included herein are purely hypothetical and are not a guarantee or a prediction of the future of the Opportunity, which may be negative. This model is for illustrative purposes only and should only be used for the limited purpose set forth above. Please refer to the endnotes for more information.

Sheet Assumptions
C1: Selling Investor Contributions | D1: 358713131
C2: Net of Capital Returned | D2: -1956490
C3: Selling Investor Net Capital | D3: =SUM(D1:D2) -> 356756641
C4: Total Capital Called | D4: 1.0078375e+09
C5: % of total | D5: =D3/D4 -> 0.3539823
C7: Fee Assumptions | D7: Historical | E7: Forward
C8: Investment Management Fee | D8: 0 | E8: 0
C9: Fund Admin. Expense | D9: 0 | E9: 0
C10: Fund G&A Expenses | D10: 0 | E10: 0
C11: Fund Org. Costs | D11: 0
C14: SS Curve Offset
C15: 42794 | D15: 0
C16: 43830 | D16: 0
C17: =EOMONTH(C16,12) -> 44196 | D17: 0.1
C18: =EOMONTH(C17,12) -> 44561 | D18: 0.2
C19: =EOMONTH(C18,12) -> 44926 | D19: 0.3
C20: =EOMONTH(C19,12) -> 45291 | D20: 0.4
C21: =EOMONTH(C20,12) -> 45657 | D21: 0.5
C22: =EOMONTH(C21,12) -> 46022 | D22: 0.9
C23: =EOMONTH(C22,12) -> 46387 | D23: 0.9
C24: =EOMONTH(C23,12) -> 46752 | D24: 0.9
C25: =EOMONTH(C24,12) -> 47118 | D25: 0.9
C26: =EOMONTH(C25,12) -> 47483 | D26: 0.9
C27: =EOMONTH(C26,12) -> 47848 | D27: 0.9
C28: =EOMONTH(C27,12) -> 48213 | D28: 0.9
C29: =EOMONTH(C28,12) -> 48579 | D29: 0.9
C32: Cash on Hand at Cutoff Month | D32: 15332622
C33: Running Cash Bal. (% of Rem. Eq.) | D33: 0.0175
C35: DD Fee | D35: 0
C36: IHPS Fee | D36: 0

Sheet Endnotes and Disclaimers
B1: Private and Confidential
B3: Endnotes
B5: (A) | C5: Any targets, forecasts, and projections contained herein have been prepared and are set out for illustrative purposes only and are based on hypothetical assumptions and current intentions with respect to the intended operation of the portfolio. The assumptions, forecasts and estimates used to generate this illustrative data are not all described herein, but include assumptions, forecasts and estimates currently deemed reasonable by Rialto relating to existing leases and contracts in place, anticipated collection of rental payments, absorption pace, leasing costs and concessions, operating expenses, development and capital costs, potential capital structures, debt financing, capitalization rates, sales proceeds, timing of dispositions, transaction costs, hold periods, credit of sponsor and borrower recourse, loss and default assumptions with respect to CMBS, current income, and legal risks, costs and timing. No representation or warranty is made as to the reasonableness of such assumptions or that such illustrations are accurate of completer or do not contain errors, or that alternative modeling techniques would not be more appropriate or would not produce significantly different results. None of the targets, assumptions, forecasts or estimates is meant to be a historical description or a prediction of future performance, and each has inherent limitations. Target returns are aspirational only. The forecasts are subject to uncertainties, changes (including changes in economic, operational, political, or other circumstances) and other risks, including broad trends in business and finance, legislation and regulation, interest rates, inflation, currency values, real estate market conditions, the availability and cost of short-term or long term funding and capital, all of which are beyond Rialto’s control and any of which may cause the relevant actual, financial and other results to be materially different from the results expressed or implied by such forecasts or projections. Industry experts may disagree with the forecasts, the estimations and assumptions used in preparing the targets. Different assumptions may also be reasonable and would yield different returns. No assurance, representation or warranty is made by any person that any targets, forecasts and projections will be achieved, and no prospective investor should rely on such targets, forecasts or projections. Projections are based on (a) capital funded by (and reinvested proceeds) and distributed to investors (for portfolio level returns) or the portfolio (for asset level returns) through the stated as of date, (b) projected cash to be distributed to investors (for portfolio level returns) or the portfolio (for asset level returns) during the remaining term, and (c) estimated investment expenses, management and service costs (including for property services and due diligence and asset management services) and capital expenditures (collectively, “Component Cash Flows”). The assumptions and projected returns may have under- or over-compensated for the effect, if any, of certain market factors and other events, including but not limited to the availability of suitable investments. Projected returns may be based in whole or in part on unaudited data that is subject to adjustment.
B6: (B) | C6: “Projected Gross IRR” is the projected compound internal rate of return (on a leveraged basis, if applicable) using a standard formula (XIRR), based on Component Cash Flows from the portfolio through the stated as of date. Project Gross IRR is calculated before deductions for portfolio level costs, investment management fees and incentive allocation, which would reduce returns if taken into account.
B7: (C) | C7: “Projected Gross Equity Multiple (MOIC)” or “Gross MOIC” is calculated by dividing (a) the sum of the (i) actual distributions to investors through the stated as of date, net of recalled capital, through the stated as of date, and (ii) the projected cash to be distributed to investors during the remaining term, by (b) capital funded by investors through the stated as of date. Project Gross MOIC is calculated before deductions for portfolio level costs, investment management fees and incentive allocation, which would reduce returns if taken into account.
B8: (D) | C8: “Projected Net IRR” is the projected compound internal rate of return, on a leveraged basis, if applicable, using a standard formula (XIRR) based on Component Cash Flows from the portfolio through the stated as of date and after taking into account estimated portfolio level costs, investment management fees and incentive allocation.
B9: (E) | C9: “Projected Net Equity Multiple (MOIC)” or “Net MOIC” is calculated by dividing (a) the sum of the (i) actual distributions to investors, net of recalled capital, through the stated as of date, and (ii) the projected cash to be distributed to investors during the remaining term, assuming the current invested portfolio, in each case, net of estimated investment expenses, management and service costs (including for due diligence and asset level accounting, legal and tax services), fund level costs, investment management fees and incentive allocation, and after adjustments for fund level indebtedness, if applicable, by (b) capital funded by investors through the stated as of date.
B11: Disclaimers and Risk Factors
C12: This presentation is for discussion purposes only and does not constitute an offer to sell or the solicitation of an offer to purchase any security or investment product described herein. Any offer or solicitation to purchase an interest in a fund managed by Rialto (a “Fund”) may only be made by means of delivery of an approved confidential offering memorandum, which must be received and reviewed prior to investing. You may not rely on this presentation as the basis upon which to make an investment decision. This presentation does not purport to be complete on any topic addressed. The information, opinions and estimates provided in this presentation are provided to you as of the dates indicated and Rialto does not undertake to update the information after its distribution. These materials are not intended for distribution to, or use by, any person or entity in any jurisdiction or country where such distribution or use would be contrary to applicable law or regulations. If there is any inconsistency between this presentation and the terms and disclosures in a Fund’s offering documents, the offering documents will govern. Certain information in this document might constitute material non-public information and therefore, potentially could impose certain trading restrictions on the recipient.
C13: An investment with Rialto is highly speculative, and there can be no assurance that a Fund’s investment objective will be achieved. Investors must be prepared to bear the risk of a total loss of their investment. An investment in a Fund is suitable only for certain financially sophisticated investors who meet applicable eligibility requirements, have no need for immediate liquidity in their investment and can bear the risk of an investment for an extended period of time. Before deciding to invest, prospective investors should carefully read the Fund’s offering memorandum and pay particular attention to the risk factors and conflicts of interest described therein. Some or all alternative investment programs may not be suitable for certain investors. Investors in a Fund may lose all or a significant portion of their investment. This presentation is not intended to provide, and should not be relied upon for, tax, legal, accounting or investment advice.
C14: PAST PERFORMANCE IS NOT INDICATIVE OF FUTURE RESULTS. Performance data is net of fees and assumes reinvestment of income and dividends except to the extent otherwise indicated. The performance data for certain periods has not been audited. There can be no assurance that a Fund will achieve results that are referenced in this presentation. There is no guarantee that a Fund or future offerings by Rialto will have access to similar types of investments or opportunities to achieve comparable results. Calculations of returns are based on the payment date of investors’ capital contributions. Returns of any individual investor may vary from the returns shown due to the timing of capital transactions and other items. Portfolio level performance reflects the reinvestment of a portion of the investment income and investment proceeds as a result of recycling (to the extent permitted under a portfolio’s governing documents, which is the case for each of Rialto’s flagship Funds). Internal Rate of Return (“IRR”) calculations may be favorably impacted by the short-term use of a line of credit facility to bridge capital calls, into which certain Funds and accounts have entered. Under the terms of the applicable line of credit facilities agreements, Rialto typically has the discretion to carry an investment on the line of credit facilities for an extended period. There are instances where the Fund utilizes borrowings under its subscription-based credit facility in advance of or in lieu of receiving investors’ capital contributions. The use of a subscription-based credit facility will result in higher or lower reported returns than if investors’ capital had been contributed at the inception of an investment. In addition, the Fund pays all related expenses, including interest, on its subscription-based credit facility and investors will bear such costs.
C15: Gross returns are presented before deduction for investment management fees and performance compensation but are net of all operating expenses. Actual net returns to investors are reduced by such investment management fees and performance compensation.
C16: Rialto’s investment program involves investing in real estate debt, and as such, the portfolio may experience more volatility and be exposed to greater risk than a more diversified investment portfolio. The investments will be subject to the risks incident to debt investments, including, among other things, (i) mismanagement or decline in value of collateral; (ii) risks arising out of a borrower default; (iii) changes in availability of replacement “takeout” financing upon maturity of loans; (iv) changes in interest rates; (v) risks of underlying commercial mortgage loans; and (vi) the risk that investments in mezzanine loans may become unsecured upon a foreclosure by a senior lender.
C17: This presentation contains statements, estimates and projections that are forward-looking (collectively, “forward-looking statements”). When used in this presentation, the words “anticipate,” “assume,” “become,” “believe,” “contemplate,” “continue,” “could,” “designed,” “estimate,” “expect,” “going forward,” “future,” “hopeful,” “intend,” “look forward,” “may,” “might,” “opportunity,” “pending,” “plan,” “potential,” “project,” “scheduled,” “shall,” “should,” “target,” “think,” “to be,” “upcoming,” “well-positioned,” “will,” “wish,” “would,” other variations on such words and similar terminology, if and to the extent used, are intended to identify such forward-looking statements . All forward-looking statements are based on the current expectations and beliefs of Rialto management concerning future events that are subject to substantial risks and uncertainties which may cause the actual results, performance or achievements of a Fund and/or its investments to be materially different from any future results, performance or achievements expressed or implied by such forward-looking statements. Factors that may cause or contribute to those potential differences include, but are not limited to, the following: national and local economic conditions; the terms of governmental laws, rules and regulations (including tax regulations) that affect a Fund and/or its investments and interpretations of those laws, rules and regulations; changes in the rate of inflation and interest rates; real estate risks, including variations of real estate values and the general economic climate in local markets; competition for tenants, imposition of rent controls, unfavorable enactments of zoning and other governmental laws, possible environmental liabilities, the prohibitive cost of casualty, windstorm, flood and other insurance, the occurrence of natural disasters, possible vandalism and competition; a Fund’s ability or inability to acquire investments on the terms or at the costs currently contemplated and the timing of such investments; as well as other risks and uncertainties, some of which may not currently be foreseeable. Predictions, opinions and other information contained in this document are subject to change continually and without notice of any kind and may no longer be true after the date indicated.
C18: Any opinion expressed herein may not be shared by all directors, officers, employees, or representatives of Rialto and may be subject to change without notice.
C19: The case studies and representative transactions disclosed in this presentation are presented to show examples of Rialto’s investment approach. No representation is made (i) regarding whether any named transaction currently is held in a Fund or account managed by Rialto or will continue to be held in the future, or (ii) that any investment will or may be profitable. The case studies and representative transactions listed in this presentation do not represent all of the transactions effected for a Fund. A complete list of each transaction effected for a Fund is available upon request.
C20: Certain information contained in this presentation has been obtained from published and non-published sources prepared by third parties, which, in certain cases, have not been updated through the date hereof. While such information is believed to be reliable, Rialto has not independently verified such information, nor does it assume any responsibility for the accuracy or completeness of such information. The information contained in this presentation should not be construed as research or investment advice.
C21: This presentation contains select images of certain investments and/or underlying properties of investments that are provided for illustrative purposes only and may be digital renderings of investments and/or underlying properties of investments rather than actual photos. The images contained herein are not representative of the Fund’s entire portfolio. All rights to the trademarks and/or logos belong to their respective owners and Rialto’s use hereof does not imply an affiliation with, or endorsement by, the owners of these trademarks and/or logos.

Sheet Existing LP->

Sheet HTM Output
B1: Start Date | G1: 42794
B2: Cutoff Month | G2: 46203
B3: Transaction Date | G3: 46388
C5: Closing Date | D5: Bpiece UPB | E5: Bpiece Purch Px | K5: =YEAR(K6) -> 2017 | L5: =YEAR(L6) -> 2017 | M5: =YEAR(M6) -> 2017 | N5: =YEAR(N6) -> 2017 | O5: =YEAR(O6) -> 2017 | P5: =YEAR(P6) -> 2017 | Q5: =YEAR(Q6) -> 2017 | R5: =YEAR(R6) -> 2017 | ... GS5: =YEAR(GS6) -> 2032
B6: Investment | C6: Acq. Date | D6: Face Acquired | E6: Purch Px | F6: Purchase Proceeds | G6: Inception to Date | H6: Pro. IRR | I6: Proj. MOIC | K6: =$G$1 -> 42794 | L6: =EOMONTH(K6,1) -> 42825 | M6: =EOMONTH(L6,1) -> 42855 | N6: =EOMONTH(M6,1) -> 42886 | O6: =EOMONTH(N6,1) -> 42916 | P6: =EOMONTH(O6,1) -> 42947 | Q6: =EOMONTH(P6,1) -> 42978 | R6: =EOMONTH(Q6,1) -> 43008 | S6: =EOMONTH(R6,1) -> 43039 | ... GS6: =EOMONTH(GR6,1) -> 48579 | GU6: =YEAR($G$1) -> 2017 | GV6: =GU6+1 -> 2018 | GW6: =GV6+1 -> 2019 | GX6: =GW6+1 -> 2020 | GY6: =GX6+1 -> 2021 | GZ6: =GY6+1 -> 2022 | HA6: =GZ6+1 -> 2023 | HB6: =HA6+1 -> 2024 | HC6: =HB6+1 -> 2025 | ... HJ6: =HI6+1 -> 2032 | HK6: Total
B7: Gross B-Piece Cash Flows
A9: UBSCM 2017-C2 B-Piece Cashflows | B9: UBSCM 2017-C2 | C9: =EOMONTH(OFFSET(Strats!$B$3,MATCH($B9,Strats!$B$4:$B$31,0),MATCH(C$5,Strats!$C$3:$BS$3,0)),0) -> 42978 | D9: =OFFSET(Strats!$B$3,MATCH($B9,Strats!$B$4:$B$31,0),MATCH(D$5,Strats!$C$3:$BS$3,0)) -> 94272591 | E9: =OFFSET(Strats!$B$3,MATCH($B9,Strats!$B$4:$B$31,0),MATCH(E$5,Strats!$C$3:$BS$3,0)) -> 0.4965497 | F9: =D9*E9 -> 46811027 | G9: =SUMIFS($K9:$GS9,$K$6:$GS$6,"<="&$G$2)+F9 -> 36957950 | H9: =IFERROR(XIRR(OFFSET($J9,0,MATCH($C9,$K$6:$GS$6,0)):$GS9,OFFSET($J$6,0,MATCH($C9,$K$6:$GS$6,0)):$GS$6),"N/A") -> 0.12011396 | I9: =(HK9+F9)/F9 -> 2.6949987 | K9: =SUMIFS('Pooled CF'!$E:$E,'Pooled CF'!$A:$A,$A9,'Pooled CF'!$G:$G,K$6) -> 0 | L9: =SUMIFS('Pooled CF'!$E:$E,'Pooled CF'!$A:$A,$A9,'Pooled CF'!$G:$G,L$6) -> 0 | M9: =SUMIFS('Pooled CF'!$E:$E,'Pooled CF'!$A:$A,$A9,'Pooled CF'!$G:$G,M$6) -> 0 | N9: =SUMIFS('Pooled CF'!$E:$E,'Pooled CF'!$A:$A,$A9,'Pooled CF'!$G:$G,N$6) -> 0 | O9: =SUMIFS('Pooled CF'!$E:$E,'Pooled CF'!$A:$A,$A9,'Pooled CF'!$G:$G,O$6) -> 0 | P9: =SUMIFS('Pooled CF'!$E:$E,'Pooled CF'!$A:$A,$A9,'Pooled CF'!$G:$G,P$6) -> 0 | Q9: =SUMIFS('Pooled CF'!$E:$E,'Pooled CF'!$A:$A,$A9,'Pooled CF'!$G:$G,Q$6) -> -46811027 | R9: =SUMIFS('Pooled CF'!$E:$E,'Pooled CF'!$A:$A,$A9,'Pooled CF'!$G:$G,R$6) -> 357876.26 | ... GS9: =SUMIFS('Pooled CF'!$E:$E,'Pooled CF'!$A:$A,$A9,'Pooled CF'!$G:$G,GS$6) -> 0 | GU9: =SUMIFS($K9:$GS9,$K$5:$GS$5,GU$6) -> -45402691 | GV9: =SUMIFS($K9:$GS9,$K$5:$GS$5,GV$6) -> 4191244.9 | GW9: =SUMIFS($K9:$GS9,$K$5:$GS$5,GW$6) -> 4015034 | GX9: =SUMIFS($K9:$GS9,$K$5:$GS$5,GX$6) -> 4101918.7 | GY9: =SUMIFS($K9:$GS9,$K$5:$GS$5,GY$6) -> 4075098.8 | GZ9: =SUMIFS($K9:$GS9,$K$5:$GS$5,GZ$6) -> 4483008.7 | HA9: =SUMIFS($K9:$GS9,$K$5:$GS$5,HA$6) -> 4179770.6 | HB9: =SUMIFS($K9:$GS9,$K$5:$GS$5,HB$6) -> 4091775 | ... HJ9: =SUMIFS($K9:$GS9,$K$5:$GS$5,HJ$6) -> 0 | HK9: =SUM(GU9:HJ9) -> 79344628
A10: CGCMT 2017-C4 B-Piece Cashflows | B10: CGCMT 2017-C4 | C10: =EOMONTH(OFFSET(Strats!$B$3,MATCH($B10,Strats!$B$4:$B$31,0),MATCH(C$5,Strats!$C$3:$BS$3,0)),0) -> 43039 | D10: =OFFSET(Strats!$B$3,MATCH($B10,Strats!$B$4:$B$31,0),MATCH(D$5,Strats!$C$3:$BS$3,0)) -> 105034893 | E10: =OFFSET(Strats!$B$3,MATCH($B10,Strats!$B$4:$B$31,0),MATCH(E$5,Strats!$C$3:$BS$3,0)) -> 0.47738817 | F10: =D10*E10 -> 50142415 | G10: =SUMIFS($K10:$GS10,$K$6:$GS$6,"<="&$G$2)+F10 -> 40597940 | H10: =IFERROR(XIRR(OFFSET($J10,0,MATCH($C10,$K$6:$GS$6,0)):$GS10,OFFSET($J$6,0,MATCH($C10,$K$6:$GS$6,0)):$GS$6),"N/A") -> 0.095026019 | I10: =(HK10+F10)/F10 -> 2.1812073 | K10: =SUMIFS('Pooled CF'!$E:$E,'Pooled CF'!$A:$A,$A10,'Pooled CF'!$G:$G,K$6) -> 0 | L10: =SUMIFS('Pooled CF'!$E:$E,'Pooled CF'!$A:$A,$A10,'Pooled CF'!$G:$G,L$6) -> 0 | M10: =SUMIFS('Pooled CF'!$E:$E,'Pooled CF'!$A:$A,$A10,'Pooled CF'!$G:$G,M$6) -> 0 | N10: =SUMIFS('Pooled CF'!$E:$E,'Pooled CF'!$A:$A,$A10,'Pooled CF'!$G:$G,N$6) -> 0 | O10: =SUMIFS('Pooled CF'!$E:$E,'Pooled CF'!$A:$A,$A10,'Pooled CF'!$G:$G,O$6) -> 0 | P10: =SUMIFS('Pooled CF'!$E:$E,'Pooled CF'!$A:$A,$A10,'Pooled CF'!$G:$G,P$6) -> 0 | Q10: =SUMIFS('Pooled CF'!$E:$E,'Pooled CF'!$A:$A,$A10,'Pooled CF'!$G:$G,Q$6) -> 0 | R10: =SUMIFS('Pooled CF'!$E:$E,'Pooled CF'!$A:$A,$A10,'Pooled CF'!$G:$G,R$6) -> 0 | ... GS10: =SUMIFS('Pooled CF'!$E:$E,'Pooled CF'!$A:$A,$A10,'Pooled CF'!$G:$G,GS$6) -> 0 | GU10: =SUMIFS($K10:$GS10,$K$5:$GS$5,GU$6) -> -49351125 | GV10: =SUMIFS($K10:$GS10,$K$5:$GS$5,GV$6) -> 4733753.9 | GW10: =SUMIFS($K10:$GS10,$K$5:$GS$5,GW$6) -> 4730459.7 | GX10: =SUMIFS($K10:$GS10,$K$5:$GS$5,GX$6) -> 4680816.7 | GY10: =SUMIFS($K10:$GS10,$K$5:$GS$5,GY$6) -> 4560268.8 | GZ10: =SUMIFS($K10:$GS10,$K$5:$GS$5,GZ$6) -> 4749699.6 | HA10: =SUMIFS($K10:$GS10,$K$5:$GS$5,HA$6) -> 4669785 | HB10: =SUMIFS($K10:$GS10,$K$5:$GS$5,HB$6) -> 4733893.4 | ... HJ10: =SUMIFS($K10:$GS10,$K$5:$GS$5,HJ$6) -> 0 | HK10: =SUM(GU10:HJ10) -> 59228587
A11: WFCM 2018-C47 B-Piece Cashflows | B11: WFCM 2018-C47 | C11: =EOMONTH(OFFSET(Strats!$B$3,MATCH($B11,Strats!$B$4:$B$31,0),MATCH(C$5,Strats!$C$3:$BS$3,0)),0) -> 43404 | D11: =OFFSET(Strats!$B$3,MATCH($B11,Strats!$B$4:$B$31,0),MATCH(D$5,Strats!$C$3:$BS$3,0)) -> 93057654 | E11: =OFFSET(Strats!$B$3,MATCH($B11,Strats!$B$4:$B$31,0),MATCH(E$5,Strats!$C$3:$BS$3,0)) -> 0.522843 | F11: =D11*E11 -> 48654543 | G11: =SUMIFS($K11:$GS11,$K$6:$GS$6,"<="&$G$2)+F11 -> 35131826 | H11: =IFERROR(XIRR(OFFSET($J11,0,MATCH($C11,$K$6:$GS$6,0)):$GS11,OFFSET($J$6,0,MATCH($C11,$K$6:$GS$6,0)):$GS$6),"N/A") -> 0.083670142 | I11: =(HK11+F11)/F11 -> 1.8716236 | K11: =SUMIFS('Pooled CF'!$E:$E,'Pooled CF'!$A:$A,$A11,'Pooled CF'!$G:$G,K$6) -> 0 | L11: =SUMIFS('Pooled CF'!$E:$E,'Pooled CF'!$A:$A,$A11,'Pooled CF'!$G:$G,L$6) -> 0 | M11: =SUMIFS('Pooled CF'!$E:$E,'Pooled CF'!$A:$A,$A11,'Pooled CF'!$G:$G,M$6) -> 0 | N11: =SUMIFS('Pooled CF'!$E:$E,'Pooled CF'!$A:$A,$A11,'Pooled CF'!$G:$G,N$6) -> 0 | O11: =SUMIFS('Pooled CF'!$E:$E,'Pooled CF'!$A:$A,$A11,'Pooled CF'!$G:$G,O$6) -> 0 | P11: =SUMIFS('Pooled CF'!$E:$E,'Pooled CF'!$A:$A,$A11,'Pooled CF'!$G:$G,P$6) -> 0 | Q11: =SUMIFS('Pooled CF'!$E:$E,'Pooled CF'!$A:$A,$A11,'Pooled CF'!$G:$G,Q$6) -> 0 | R11: =SUMIFS('Pooled CF'!$E:$E,'Pooled CF'!$A:$A,$A11,'Pooled CF'!$G:$G,R$6) -> 0 | ... GS11: =SUMIFS('Pooled CF'!$E:$E,'Pooled CF'!$A:$A,$A11,'Pooled CF'!$G:$G,GS$6) -> 0 | GU11: =SUMIFS($K11:$GS11,$K$5:$GS$5,GU$6) -> 0 | GV11: =SUMIFS($K11:$GS11,$K$5:$GS$5,GV$6) -> -47876050 | GW11: =SUMIFS($K11:$GS11,$K$5:$GS$5,GW$6) -> 4657681.8 | GX11: =SUMIFS($K11:$GS11,$K$5:$GS$5,GX$6) -> 4598861.8 | GY11: =SUMIFS($K11:$GS11,$K$5:$GS$5,GY$6) -> 4512174.6 | GZ11: =SUMIFS($K11:$GS11,$K$5:$GS$5,GZ$6) -> 4604272.8 | HA11: =SUMIFS($K11:$GS11,$K$5:$GS$5,HA$6) -> 4611924.8 | HB11: =SUMIFS($K11:$GS11,$K$5:$GS$5,HB$6) -> 4478663.4 | ... HJ11: =SUMIFS($K11:$GS11,$K$5:$GS$5,HJ$6) -> 0 | HK11: =SUM(GU11:HJ11) -> 42408450
A12: BBCMS 2019-C3 B-Piece Cashflows | B12: BBCMS 2019-C3 | C12: =EOMONTH(OFFSET(Strats!$B$3,MATCH($B12,Strats!$B$4:$B$31,0),MATCH(C$5,Strats!$C$3:$BS$3,0)),0) -> 43646 | D12: =OFFSET(Strats!$B$3,MATCH($B12,Strats!$B$4:$B$31,0),MATCH(D$5,Strats!$C$3:$BS$3,0)) -> 95220542 | E12: =OFFSET(Strats!$B$3,MATCH($B12,Strats!$B$4:$B$31,0),MATCH(E$5,Strats!$C$3:$BS$3,0)) -> 0.520688 | F12: =D12*E12 -> 49580194 | G12: =SUMIFS($K12:$GS12,$K$6:$GS$6,"<="&$G$2)+F12 -> 31550771 | H12: =IFERROR(XIRR(OFFSET($J12,0,MATCH($C12,$K$6:$GS$6,0)):$GS12,OFFSET($J$6,0,MATCH($C12,$K$6:$GS$6,0)):$GS$6),"N/A") -> 0.07862626 | I12: =(HK12+F12)/F12 -> 1.8703229 | K12: =SUMIFS('Pooled CF'!$E:$E,'Pooled CF'!$A:$A,$A12,'Pooled CF'!$G:$G,K$6) -> 0 | L12: =SUMIFS('Pooled CF'!$E:$E,'Pooled CF'!$A:$A,$A12,'Pooled CF'!$G:$G,L$6) -> 0 | M12: =SUMIFS('Pooled CF'!$E:$E,'Pooled CF'!$A:$A,$A12,'Pooled CF'!$G:$G,M$6) -> 0 | N12: =SUMIFS('Pooled CF'!$E:$E,'Pooled CF'!$A:$A,$A12,'Pooled CF'!$G:$G,N$6) -> 0 | O12: =SUMIFS('Pooled CF'!$E:$E,'Pooled CF'!$A:$A,$A12,'Pooled CF'!$G:$G,O$6) -> 0 | P12: =SUMIFS('Pooled CF'!$E:$E,'Pooled CF'!$A:$A,$A12,'Pooled CF'!$G:$G,P$6) -> 0 | Q12: =SUMIFS('Pooled CF'!$E:$E,'Pooled CF'!$A:$A,$A12,'Pooled CF'!$G:$G,Q$6) -> 0 | R12: =SUMIFS('Pooled CF'!$E:$E,'Pooled CF'!$A:$A,$A12,'Pooled CF'!$G:$G,R$6) -> 0 | ... GS12: =SUMIFS('Pooled CF'!$E:$E,'Pooled CF'!$A:$A,$A12,'Pooled CF'!$G:$G,GS$6) -> 0 | GU12: =SUMIFS($K12:$GS12,$K$5:$GS$5,GU$6) -> 0 | GV12: =SUMIFS($K12:$GS12,$K$5:$GS$5,GV$6) -> 0 | GW12: =SUMIFS($K12:$GS12,$K$5:$GS$5,GW$6) -> -47263675 | GX12: =SUMIFS($K12:$GS12,$K$5:$GS$5,GX$6) -> 4603799.3 | GY12: =SUMIFS($K12:$GS12,$K$5:$GS$5,GY$6) -> 4644741.4 | GZ12: =SUMIFS($K12:$GS12,$K$5:$GS$5,GZ$6) -> 4617206.9 | HA12: =SUMIFS($K12:$GS12,$K$5:$GS$5,HA$6) -> 4572758.8 | HB12: =SUMIFS($K12:$GS12,$K$5:$GS$5,HB$6) -> 4394372.1 | ... HJ12: =SUMIFS($K12:$GS12,$K$5:$GS$5,HJ$6) -> 38688538 | HK12: =SUM(GU12:HJ12) -> 43150778
A13: GSMS 2019-GC38 B-Piece Cashflow | B13: GSMS 2019-GC38 | C13: =EOMONTH(OFFSET(Strats!$B$3,MATCH($B13,Strats!$B$4:$B$31,0),MATCH(C$5,Strats!$C$3:$BS$3,0)),0) -> 43524 | D13: =OFFSET(Strats!$B$3,MATCH($B13,Strats!$B$4:$B$31,0),MATCH(D$5,Strats!$C$3:$BS$3,0)) -> 73640365 | E13: =OFFSET(Strats!$B$3,MATCH($B13,Strats!$B$4:$B$31,0),MATCH(E$5,Strats!$C$3:$BS$3,0)) -> 0.53415699 | F13: =D13*E13 -> 39335516 | G13: =SUMIFS($K13:$GS13,$K$6:$GS$6,"<="&$G$2)+F13 -> 26432556 | H13: =IFERROR(XIRR(OFFSET($J13,0,MATCH($C13,$K$6:$GS$6,0)):$GS13,OFFSET($J$6,0,MATCH($C13,$K$6:$GS$6,0)):$GS$6),"N/A") -> 0.078893694 | I13: =(HK13+F13)/F13 -> 1.8663227 | K13: =SUMIFS('Pooled CF'!$E:$E,'Pooled CF'!$A:$A,$A13,'Pooled CF'!$G:$G,K$6) -> 0 | L13: =SUMIFS('Pooled CF'!$E:$E,'Pooled CF'!$A:$A,$A13,'Pooled CF'!$G:$G,L$6) -> 0 | M13: =SUMIFS('Pooled CF'!$E:$E,'Pooled CF'!$A:$A,$A13,'Pooled CF'!$G:$G,M$6) -> 0 | N13: =SUMIFS('Pooled CF'!$E:$E,'Pooled CF'!$A:$A,$A13,'Pooled CF'!$G:$G,N$6) -> 0 | O13: =SUMIFS('Pooled CF'!$E:$E,'Pooled CF'!$A:$A,$A13,'Pooled CF'!$G:$G,O$6) -> 0 | P13: =SUMIFS('Pooled CF'!$E:$E,'Pooled CF'!$A:$A,$A13,'Pooled CF'!$G:$G,P$6) -> 0 | Q13: =SUMIFS('Pooled CF'!$E:$E,'Pooled CF'!$A:$A,$A13,'Pooled CF'!$G:$G,Q$6) -> 0 | R13: =SUMIFS('Pooled CF'!$E:$E,'Pooled CF'!$A:$A,$A13,'Pooled CF'!$G:$G,R$6) -> 0 | ... GS13: =SUMIFS('Pooled CF'!$E:$E,'Pooled CF'!$A:$A,$A13,'Pooled CF'!$G:$G,GS$6) -> 0 | GU13: =SUMIFS($K13:$GS13,$K$5:$GS$5,GU$6) -> 0 | GV13: =SUMIFS($K13:$GS13,$K$5:$GS$5,GV$6) -> 0 | GW13: =SUMIFS($K13:$GS13,$K$5:$GS$5,GW$6) -> -36318208 | GX13: =SUMIFS($K13:$GS13,$K$5:$GS$5,GX$6) -> 3617014.1 | GY13: =SUMIFS($K13:$GS13,$K$5:$GS$5,GY$6) -> 3603252.5 | GZ13: =SUMIFS($K13:$GS13,$K$5:$GS$5,GZ$6) -> 3607093 | HA13: =SUMIFS($K13:$GS13,$K$5:$GS$5,HA$6) -> 3602358.4 | HB13: =SUMIFS($K13:$GS13,$K$5:$GS$5,HB$6) -> 3643851.3 | ... HJ13: =SUMIFS($K13:$GS13,$K$5:$GS$5,HJ$6) -> 34199846 | HK13: =SUM(GU13:HJ13) -> 34077249
A14: GSMS 2017-GS8 B-Piece Cashflow | B14: GSMS 2017-GS8 | C14: =EOMONTH(OFFSET(Strats!$B$3,MATCH($B14,Strats!$B$4:$B$31,0),MATCH(C$5,Strats!$C$3:$BS$3,0)),0) -> 43069 | D14: =OFFSET(Strats!$B$3,MATCH($B14,Strats!$B$4:$B$31,0),MATCH(D$5,Strats!$C$3:$BS$3,0)) -> 106223386 | E14: =OFFSET(Strats!$B$3,MATCH($B14,Strats!$B$4:$B$31,0),MATCH(E$5,Strats!$C$3:$BS$3,0)) -> 0.4930507 | F14: =D14*E14 -> 52373515 | G14: =SUMIFS($K14:$GS14,$K$6:$GS$6,"<="&$G$2)+F14 -> 39237817 | H14: =IFERROR(XIRR(OFFSET($J14,0,MATCH($C14,$K$6:$GS$6,0)):$GS14,OFFSET($J$6,0,MATCH($C14,$K$6:$GS$6,0)):$GS$6),"N/A") -> 0.066182342 | I14: =(HK14+F14)/F14 -> 1.6904951 | K14: =SUMIFS('Pooled CF'!$E:$E,'Pooled CF'!$A:$A,$A14,'Pooled CF'!$G:$G,K$6) -> 0 | L14: =SUMIFS('Pooled CF'!$E:$E,'Pooled CF'!$A:$A,$A14,'Pooled CF'!$G:$G,L$6) -> 0 | M14: =SUMIFS('Pooled CF'!$E:$E,'Pooled CF'!$A:$A,$A14,'Pooled CF'!$G:$G,M$6) -> 0 | N14: =SUMIFS('Pooled CF'!$E:$E,'Pooled CF'!$A:$A,$A14,'Pooled CF'!$G:$G,N$6) -> 0 | O14: =SUMIFS('Pooled CF'!$E:$E,'Pooled CF'!$A:$A,$A14,'Pooled CF'!$G:$G,O$6) -> 0 | P14: =SUMIFS('Pooled CF'!$E:$E,'Pooled CF'!$A:$A,$A14,'Pooled CF'!$G:$G,P$6) -> 0 | Q14: =SUMIFS('Pooled CF'!$E:$E,'Pooled CF'!$A:$A,$A14,'Pooled CF'!$G:$G,Q$6) -> 0 | R14: =SUMIFS('Pooled CF'!$E:$E,'Pooled CF'!$A:$A,$A14,'Pooled CF'!$G:$G,R$6) -> 0 | ... GS14: =SUMIFS('Pooled CF'!$E:$E,'Pooled CF'!$A:$A,$A14,'Pooled CF'!$G:$G,GS$6) -> 0 | GU14: =SUMIFS($K14:$GS14,$K$5:$GS$5,GU$6) -> -51989557 | GV14: =SUMIFS($K14:$GS14,$K$5:$GS$5,GV$6) -> 4671356.2 | GW14: =SUMIFS($K14:$GS14,$K$5:$GS$5,GW$6) -> 4670868.5 | GX14: =SUMIFS($K14:$GS14,$K$5:$GS$5,GX$6) -> 4638465.7 | GY14: =SUMIFS($K14:$GS14,$K$5:$GS$5,GY$6) -> 4713313 | GZ14: =SUMIFS($K14:$GS14,$K$5:$GS$5,GZ$6) -> 4668587.5 | HA14: =SUMIFS($K14:$GS14,$K$5:$GS$5,HA$6) -> 4656689.1 | HB14: =SUMIFS($K14:$GS14,$K$5:$GS$5,HB$6) -> 4540535.8 | ... HJ14: =SUMIFS($K14:$GS14,$K$5:$GS$5,HJ$6) -> 0 | HK14: =SUM(GU14:HJ14) -> 36163653
A15: UBSCM 2018-C8 B-Piece Cashflows | B15: UBSCM 2018-C8 | C15: =EOMONTH(OFFSET(Strats!$B$3,MATCH($B15,Strats!$B$4:$B$31,0),MATCH(C$5,Strats!$C$3:$BS$3,0)),0) -> 43159 | D15: =OFFSET(Strats!$B$3,MATCH($B15,Strats!$B$4:$B$31,0),MATCH(D$5,Strats!$C$3:$BS$3,0)) -> 107046891 | E15: =OFFSET(Strats!$B$3,MATCH($B15,Strats!$B$4:$B$31,0),MATCH(E$5,Strats!$C$3:$BS$3,0)) -> 0.4970166 | F15: =D15*E15 -> 53204082 | G15: =SUMIFS($K15:$GS15,$K$6:$GS$6,"<="&$G$2)+F15 -> 41900237 | H15: =IFERROR(XIRR(OFFSET($J15,0,MATCH($C15,$K$6:$GS$6,0)):$GS15,OFFSET($J$6,0,MATCH($C15,$K$6:$GS$6,0)):$GS$6),"N/A") -> -0.0083879441 | I15: =(HK15+F15)/F15 -> 0.95771373 | K15: =SUMIFS('Pooled CF'!$E:$E,'Pooled CF'!$A:$A,$A15,'Pooled CF'!$G:$G,K$6) -> 0 | L15: =SUMIFS('Pooled CF'!$E:$E,'Pooled CF'!$A:$A,$A15,'Pooled CF'!$G:$G,L$6) -> 0 | M15: =SUMIFS('Pooled CF'!$E:$E,'Pooled CF'!$A:$A,$A15,'Pooled CF'!$G:$G,M$6) -> 0 | N15: =SUMIFS('Pooled CF'!$E:$E,'Pooled CF'!$A:$A,$A15,'Pooled CF'!$G:$G,N$6) -> 0 | O15: =SUMIFS('Pooled CF'!$E:$E,'Pooled CF'!$A:$A,$A15,'Pooled CF'!$G:$G,O$6) -> 0 | P15: =SUMIFS('Pooled CF'!$E:$E,'Pooled CF'!$A:$A,$A15,'Pooled CF'!$G:$G,P$6) -> 0 | Q15: =SUMIFS('Pooled CF'!$E:$E,'Pooled CF'!$A:$A,$A15,'Pooled CF'!$G:$G,Q$6) -> 0 | R15: =SUMIFS('Pooled CF'!$E:$E,'Pooled CF'!$A:$A,$A15,'Pooled CF'!$G:$G,R$6) -> 0 | ... GS15: =SUMIFS('Pooled CF'!$E:$E,'Pooled CF'!$A:$A,$A15,'Pooled CF'!$G:$G,GS$6) -> 0 | GU15: =SUMIFS($K15:$GS15,$K$5:$GS$5,GU$6) -> 0 | GV15: =SUMIFS($K15:$GS15,$K$5:$GS$5,GV$6) -> -48937122 | GW15: =SUMIFS($K15:$GS15,$K$5:$GS$5,GW$6) -> 5104713.5 | GX15: =SUMIFS($K15:$GS15,$K$5:$GS$5,GX$6) -> 5046393.8 | GY15: =SUMIFS($K15:$GS15,$K$5:$GS$5,GY$6) -> 4947355.7 | GZ15: =SUMIFS($K15:$GS15,$K$5:$GS$5,GZ$6) -> 5235916.4 | HA15: =SUMIFS($K15:$GS15,$K$5:$GS$5,HA$6) -> 4971306.6 | HB15: =SUMIFS($K15:$GS15,$K$5:$GS$5,HB$6) -> 5045604.8 | ... HJ15: =SUMIFS($K15:$GS15,$K$5:$GS$5,HJ$6) -> 0 | HK15: =SUM(GU15:HJ15) -> -2249802.3
A16: UBSCM 2017-C3 B-Piece Cashflows | B16: UBSCM 2017-C3 | C16: =EOMONTH(OFFSET(Strats!$B$3,MATCH($B16,Strats!$B$4:$B$31,0),MATCH(C$5,Strats!$C$3:$BS$3,0)),0) -> 42978 | D16: =OFFSET(Strats!$B$3,MATCH($B16,Strats!$B$4:$B$31,0),MATCH(D$5,Strats!$C$3:$BS$3,0)) -> 77063195 | E16: =OFFSET(Strats!$B$3,MATCH($B16,Strats!$B$4:$B$31,0),MATCH(E$5,Strats!$C$3:$BS$3,0)) -> 0.4951454 | F16: =D16*E16 -> 38157487 | G16: =SUMIFS($K16:$GS16,$K$6:$GS$6,"<="&$G$2)+F16 -> 28663917 | H16: =IFERROR(XIRR(OFFSET($J16,0,MATCH($C16,$K$6:$GS$6,0)):$GS16,OFFSET($J$6,0,MATCH($C16,$K$6:$GS$6,0)):$GS$6),"N/A") -> 0.070259783 | I16: =(HK16+F16)/F16 -> 1.7728872 | K16: =SUMIFS('Pooled CF'!$E:$E,'Pooled CF'!$A:$A,$A16,'Pooled CF'!$G:$G,K$6) -> 0 | L16: =SUMIFS('Pooled CF'!$E:$E,'Pooled CF'!$A:$A,$A16,'Pooled CF'!$G:$G,L$6) -> 0 | M16: =SUMIFS('Pooled CF'!$E:$E,'Pooled CF'!$A:$A,$A16,'Pooled CF'!$G:$G,M$6) -> 0 | N16: =SUMIFS('Pooled CF'!$E:$E,'Pooled CF'!$A:$A,$A16,'Pooled CF'!$G:$G,N$6) -> 0 | O16: =SUMIFS('Pooled CF'!$E:$E,'Pooled CF'!$A:$A,$A16,'Pooled CF'!$G:$G,O$6) -> 0 | P16: =SUMIFS('Pooled CF'!$E:$E,'Pooled CF'!$A:$A,$A16,'Pooled CF'!$G:$G,P$6) -> 0 | Q16: =SUMIFS('Pooled CF'!$E:$E,'Pooled CF'!$A:$A,$A16,'Pooled CF'!$G:$G,Q$6) -> -38157487 | R16: =SUMIFS('Pooled CF'!$E:$E,'Pooled CF'!$A:$A,$A16,'Pooled CF'!$G:$G,R$6) -> 286626.28 | ... GS16: =SUMIFS('Pooled CF'!$E:$E,'Pooled CF'!$A:$A,$A16,'Pooled CF'!$G:$G,GS$6) -> 0 | GU16: =SUMIFS($K16:$GS16,$K$5:$GS$5,GU$6) -> -37029541 | GV16: =SUMIFS($K16:$GS16,$K$5:$GS$5,GV$6) -> 3373456.5 | GW16: =SUMIFS($K16:$GS16,$K$5:$GS$5,GW$6) -> 3180114.5 | GX16: =SUMIFS($K16:$GS16,$K$5:$GS$5,GX$6) -> 3227163.2 | GY16: =SUMIFS($K16:$GS16,$K$5:$GS$5,GY$6) -> 3341183 | GZ16: =SUMIFS($K16:$GS16,$K$5:$GS$5,GZ$6) -> 3392360.8 | HA16: =SUMIFS($K16:$GS16,$K$5:$GS$5,HA$6) -> 3582287.2 | HB16: =SUMIFS($K16:$GS16,$K$5:$GS$5,HB$6) -> 3145563.1 | ... HJ16: =SUMIFS($K16:$GS16,$K$5:$GS$5,HJ$6) -> 0 | HK16: =SUM(GU16:HJ16) -> 29491434
A17: UBSCM 2017-C5 B-Piece Cashflows | B17: UBSCM 2017-C5 | C17: =EOMONTH(OFFSET(Strats!$B$3,MATCH($B17,Strats!$B$4:$B$31,0),MATCH(C$5,Strats!$C$3:$BS$3,0)),0) -> 43069 | D17: =OFFSET(Strats!$B$3,MATCH($B17,Strats!$B$4:$B$31,0),MATCH(D$5,Strats!$C$3:$BS$3,0)) -> 78392651 | E17: =OFFSET(Strats!$B$3,MATCH($B17,Strats!$B$4:$B$31,0),MATCH(E$5,Strats!$C$3:$BS$3,0)) -> 0.4885777 | F17: =D17*E17 -> 38300901 | G17: =SUMIFS($K17:$GS17,$K$6:$GS$6,"<="&$G$2)+F17 -> 28502802 | H17: =IFERROR(XIRR(OFFSET($J17,0,MATCH($C17,$K$6:$GS$6,0)):$GS17,OFFSET($J$6,0,MATCH($C17,$K$6:$GS$6,0)):$GS$6),"N/A") -> 0.067069897 | I17: =(HK17+F17)/F17 -> 1.6861527 | K17: =SUMIFS('Pooled CF'!$E:$E,'Pooled CF'!$A:$A,$A17,'Pooled CF'!$G:$G,K$6) -> 0 | L17: =SUMIFS('Pooled CF'!$E:$E,'Pooled CF'!$A:$A,$A17,'Pooled CF'!$G:$G,L$6) -> 0 | M17: =SUMIFS('Pooled CF'!$E:$E,'Pooled CF'!$A:$A,$A17,'Pooled CF'!$G:$G,M$6) -> 0 | N17: =SUMIFS('Pooled CF'!$E:$E,'Pooled CF'!$A:$A,$A17,'Pooled CF'!$G:$G,N$6) -> 0 | O17: =SUMIFS('Pooled CF'!$E:$E,'Pooled CF'!$A:$A,$A17,'Pooled CF'!$G:$G,O$6) -> 0 | P17: =SUMIFS('Pooled CF'!$E:$E,'Pooled CF'!$A:$A,$A17,'Pooled CF'!$G:$G,P$6) -> 0 | Q17: =SUMIFS('Pooled CF'!$E:$E,'Pooled CF'!$A:$A,$A17,'Pooled CF'!$G:$G,Q$6) -> 0 | R17: =SUMIFS('Pooled CF'!$E:$E,'Pooled CF'!$A:$A,$A17,'Pooled CF'!$G:$G,R$6) -> 0 | ... GS17: =SUMIFS('Pooled CF'!$E:$E,'Pooled CF'!$A:$A,$A17,'Pooled CF'!$G:$G,GS$6) -> 0 | GU17: =SUMIFS($K17:$GS17,$K$5:$GS$5,GU$6) -> -38018559 | GV17: =SUMIFS($K17:$GS17,$K$5:$GS$5,GV$6) -> 3434140 | GW17: =SUMIFS($K17:$GS17,$K$5:$GS$5,GW$6) -> 3431632.1 | GX17: =SUMIFS($K17:$GS17,$K$5:$GS$5,GX$6) -> 3415386.3 | GY17: =SUMIFS($K17:$GS17,$K$5:$GS$5,GY$6) -> 3296344 | GZ17: =SUMIFS($K17:$GS17,$K$5:$GS$5,GZ$6) -> 3407017.9 | HA17: =SUMIFS($K17:$GS17,$K$5:$GS$5,HA$6) -> 3246912.4 | HB17: =SUMIFS($K17:$GS17,$K$5:$GS$5,HB$6) -> 3163581.9 | ... HJ17: =SUMIFS($K17:$GS17,$K$5:$GS$5,HJ$6) -> 0 | HK17: =SUM(GU17:HJ17) -> 26280268
A18: MSC 2019-H6 B-Piece Cashflows | B18: MSC 2019-H6 | C18: =EOMONTH(OFFSET(Strats!$B$3,MATCH($B18,Strats!$B$4:$B$31,0),MATCH(C$5,Strats!$C$3:$BS$3,0)),0) -> 43646 | D18: =OFFSET(Strats!$B$3,MATCH($B18,Strats!$B$4:$B$31,0),MATCH(D$5,Strats!$C$3:$BS$3,0)) -> 70915759 | E18: =OFFSET(Strats!$B$3,MATCH($B18,Strats!$B$4:$B$31,0),MATCH(E$5,Strats!$C$3:$BS$3,0)) -> 0.5111145 | F18: =D18*E18 -> 36246073 | G18: =SUMIFS($K18:$GS18,$K$6:$GS$6,"<="&$G$2)+F18 -> 21688743 | H18: =IFERROR(XIRR(OFFSET($J18,0,MATCH($C18,$K$6:$GS$6,0)):$GS18,OFFSET($J$6,0,MATCH($C18,$K$6:$GS$6,0)):$GS$6),"N/A") -> 0.10091996 | I18: =(HK18+F18)/F18 -> 2.2691566 | K18: =SUMIFS('Pooled CF'!$E:$E,'Pooled CF'!$A:$A,$A18,'Pooled CF'!$G:$G,K$6) -> 0 | L18: =SUMIFS('Pooled CF'!$E:$E,'Pooled CF'!$A:$A,$A18,'Pooled CF'!$G:$G,L$6) -> 0 | M18: =SUMIFS('Pooled CF'!$E:$E,'Pooled CF'!$A:$A,$A18,'Pooled CF'!$G:$G,M$6) -> 0 | N18: =SUMIFS('Pooled CF'!$E:$E,'Pooled CF'!$A:$A,$A18,'Pooled CF'!$G:$G,N$6) -> 0 | O18: =SUMIFS('Pooled CF'!$E:$E,'Pooled CF'!$A:$A,$A18,'Pooled CF'!$G:$G,O$6) -> 0 | P18: =SUMIFS('Pooled CF'!$E:$E,'Pooled CF'!$A:$A,$A18,'Pooled CF'!$G:$G,P$6) -> 0 | Q18: =SUMIFS('Pooled CF'!$E:$E,'Pooled CF'!$A:$A,$A18,'Pooled CF'!$G:$G,Q$6) -> 0 | R18: =SUMIFS('Pooled CF'!$E:$E,'Pooled CF'!$A:$A,$A18,'Pooled CF'!$G:$G,R$6) -> 0 | ... GS18: =SUMIFS('Pooled CF'!$E:$E,'Pooled CF'!$A:$A,$A18,'Pooled CF'!$G:$G,GS$6) -> 0 | GU18: =SUMIFS($K18:$GS18,$K$5:$GS$5,GU$6) -> 0 | GV18: =SUMIFS($K18:$GS18,$K$5:$GS$5,GV$6) -> 0 | GW18: =SUMIFS($K18:$GS18,$K$5:$GS$5,GW$6) -> -34595024 | GX18: =SUMIFS($K18:$GS18,$K$5:$GS$5,GX$6) -> 3300685.6 | GY18: =SUMIFS($K18:$GS18,$K$5:$GS$5,GY$6) -> 3235169.7 | GZ18: =SUMIFS($K18:$GS18,$K$5:$GS$5,GZ$6) -> 3212897.7 | HA18: =SUMIFS($K18:$GS18,$K$5:$GS$5,HA$6) -> 3207449.8 | HB18: =SUMIFS($K18:$GS18,$K$5:$GS$5,HB$6) -> 3078782.3 | ... HJ18: =SUMIFS($K18:$GS18,$K$5:$GS$5,HJ$6) -> 0 | HK18: =SUM(GU18:HJ18) -> 46001941
A19: WFCM 2019-C49 B-Piece Cashflows | B19: WFCM 2019-C49 | C19: =EOMONTH(OFFSET(Strats!$B$3,MATCH($B19,Strats!$B$4:$B$31,0),MATCH(C$5,Strats!$C$3:$BS$3,0)),0) -> 43555 | D19: =OFFSET(Strats!$B$3,MATCH($B19,Strats!$B$4:$B$31,0),MATCH(D$5,Strats!$C$3:$BS$3,0)) -> 80442767 | E19: =OFFSET(Strats!$B$3,MATCH($B19,Strats!$B$4:$B$31,0),MATCH(E$5,Strats!$C$3:$BS$3,0)) -> 0.503839 | F19: =D19*E19 -> 40530203 | G19: =SUMIFS($K19:$GS19,$K$6:$GS$6,"<="&$G$2)+F19 -> 28498620 | H19: =IFERROR(XIRR(OFFSET($J19,0,MATCH($C19,$K$6:$GS$6,0)):$GS19,OFFSET($J$6,0,MATCH($C19,$K$6:$GS$6,0)):$GS$6),"N/A") -> 0.084309992 | I19: =(HK19+F19)/F19 -> 1.8750085 | K19: =SUMIFS('Pooled CF'!$E:$E,'Pooled CF'!$A:$A,$A19,'Pooled CF'!$G:$G,K$6) -> 0 | L19: =SUMIFS('Pooled CF'!$E:$E,'Pooled CF'!$A:$A,$A19,'Pooled CF'!$G:$G,L$6) -> 0 | M19: =SUMIFS('Pooled CF'!$E:$E,'Pooled CF'!$A:$A,$A19,'Pooled CF'!$G:$G,M$6) -> 0 | N19: =SUMIFS('Pooled CF'!$E:$E,'Pooled CF'!$A:$A,$A19,'Pooled CF'!$G:$G,N$6) -> 0 | O19: =SUMIFS('Pooled CF'!$E:$E,'Pooled CF'!$A:$A,$A19,'Pooled CF'!$G:$G,O$6) -> 0 | P19: =SUMIFS('Pooled CF'!$E:$E,'Pooled CF'!$A:$A,$A19,'Pooled CF'!$G:$G,P$6) -> 0 | Q19: =SUMIFS('Pooled CF'!$E:$E,'Pooled CF'!$A:$A,$A19,'Pooled CF'!$G:$G,Q$6) -> 0 | R19: =SUMIFS('Pooled CF'!$E:$E,'Pooled CF'!$A:$A,$A19,'Pooled CF'!$G:$G,R$6) -> 0 | ... GS19: =SUMIFS('Pooled CF'!$E:$E,'Pooled CF'!$A:$A,$A19,'Pooled CF'!$G:$G,GS$6) -> 0 | GU19: =SUMIFS($K19:$GS19,$K$5:$GS$5,GU$6) -> 0 | GV19: =SUMIFS($K19:$GS19,$K$5:$GS$5,GV$6) -> 0 | GW19: =SUMIFS($K19:$GS19,$K$5:$GS$5,GW$6) -> -37373522 | GX19: =SUMIFS($K19:$GS19,$K$5:$GS$5,GX$6) -> 4107102.3 | GY19: =SUMIFS($K19:$GS19,$K$5:$GS$5,GY$6) -> 3836613.3 | GZ19: =SUMIFS($K19:$GS19,$K$5:$GS$5,GZ$6) -> 3736726.7 | HA19: =SUMIFS($K19:$GS19,$K$5:$GS$5,HA$6) -> 3899287.2 | HB19: =SUMIFS($K19:$GS19,$K$5:$GS$5,HB$6) -> 3669158 | ... HJ19: =SUMIFS($K19:$GS19,$K$5:$GS$5,HJ$6) -> 7260195.9 | HK19: =SUM(GU19:HJ19) -> 35464273
A20: UBSCM 2018-C13 B-Piece Cashflow | B20: UBSCM 2018-C13 | C20: =EOMONTH(OFFSET(Strats!$B$3,MATCH($B20,Strats!$B$4:$B$31,0),MATCH(C$5,Strats!$C$3:$BS$3,0)),0) -> 43404 | D20: =OFFSET(Strats!$B$3,MATCH($B20,Strats!$B$4:$B$31,0),MATCH(D$5,Strats!$C$3:$BS$3,0)) -> 69344367 | E20: =OFFSET(Strats!$B$3,MATCH($B20,Strats!$B$4:$B$31,0),MATCH(E$5,Strats!$C$3:$BS$3,0)) -> 0.5290941 | F20: =D20*E20 -> 36689695 | G20: =SUMIFS($K20:$GS20,$K$6:$GS$6,"<="&$G$2)+F20 -> 26144941 | H20: =IFERROR(XIRR(OFFSET($J20,0,MATCH($C20,$K$6:$GS$6,0)):$GS20,OFFSET($J$6,0,MATCH($C20,$K$6:$GS$6,0)):$GS$6),"N/A") -> 0.08102676 | I20: =(HK20+F20)/F20 -> 1.8396828 | K20: =SUMIFS('Pooled CF'!$E:$E,'Pooled CF'!$A:$A,$A20,'Pooled CF'!$G:$G,K$6) -> 0 | L20: =SUMIFS('Pooled CF'!$E:$E,'Pooled CF'!$A:$A,$A20,'Pooled CF'!$G:$G,L$6) -> 0 | M20: =SUMIFS('Pooled CF'!$E:$E,'Pooled CF'!$A:$A,$A20,'Pooled CF'!$G:$G,M$6) -> 0 | N20: =SUMIFS('Pooled CF'!$E:$E,'Pooled CF'!$A:$A,$A20,'Pooled CF'!$G:$G,N$6) -> 0 | O20: =SUMIFS('Pooled CF'!$E:$E,'Pooled CF'!$A:$A,$A20,'Pooled CF'!$G:$G,O$6) -> 0 | P20: =SUMIFS('Pooled CF'!$E:$E,'Pooled CF'!$A:$A,$A20,'Pooled CF'!$G:$G,P$6) -> 0 | Q20: =SUMIFS('Pooled CF'!$E:$E,'Pooled CF'!$A:$A,$A20,'Pooled CF'!$G:$G,Q$6) -> 0 | R20: =SUMIFS('Pooled CF'!$E:$E,'Pooled CF'!$A:$A,$A20,'Pooled CF'!$G:$G,R$6) -> 0 | ... GS20: =SUMIFS('Pooled CF'!$E:$E,'Pooled CF'!$A:$A,$A20,'Pooled CF'!$G:$G,GS$6) -> 0 | GU20: =SUMIFS($K20:$GS20,$K$5:$GS$5,GU$6) -> 0 | GV20: =SUMIFS($K20:$GS20,$K$5:$GS$5,GV$6) -> -36101955 | GW20: =SUMIFS($K20:$GS20,$K$5:$GS$5,GW$6) -> 3510493.4 | GX20: =SUMIFS($K20:$GS20,$K$5:$GS$5,GX$6) -> 3320036.6 | GY20: =SUMIFS($K20:$GS20,$K$5:$GS$5,GY$6) -> 3334711.8 | GZ20: =SUMIFS($K20:$GS20,$K$5:$GS$5,GZ$6) -> 3740418.3 | HA20: =SUMIFS($K20:$GS20,$K$5:$GS$5,HA$6) -> 3377314.8 | HB20: =SUMIFS($K20:$GS20,$K$5:$GS$5,HB$6) -> 3430881.6 | ... HJ20: =SUMIFS($K20:$GS20,$K$5:$GS$5,HJ$6) -> 0 | HK20: =SUM(GU20:HJ20) -> 30807705
... A35: CD 2017-CD3 B-Piece Hist Cashfl | B35: CD 2017-CD3 | C35: =EOMONTH(OFFSET(Strats!$B$3,MATCH($B35,Strats!$B$4:$B$31,0),MATCH(C$5,Strats!$C$3:$BS$3,0)),0) -> 42794 | D35: =OFFSET(Strats!$B$3,MATCH($B35,Strats!$B$4:$B$31,0),MATCH(D$5,Strats!$C$3:$BS$3,0)) -> 110692959 | E35: =OFFSET(Strats!$B$3,MATCH($B35,Strats!$B$4:$B$31,0),MATCH(E$5,Strats!$C$3:$BS$3,0)) -> 0.3916008 | F35: =D35*E35 -> 43347451 | G35: =SUMIFS($K35:$GS35,$K$6:$GS$6,"<="&$G$2)+F35 -> 23338051 | H35: =IFERROR(XIRR(OFFSET($J35,0,MATCH($C35,$K$6:$GS$6,0)):$GS35,OFFSET($J$6,0,MATCH($C35,$K$6:$GS$6,0)):$GS$6),"N/A") -> -0.19452752 | I35: =(HK35+F35)/F35 -> 0.53839501 | K35: =SUMIFS('Pooled CF'!$E:$E,'Pooled CF'!$A:$A,$A35,'Pooled CF'!$G:$G,K$6) -> -43347451 | L35: =SUMIFS('Pooled CF'!$E:$E,'Pooled CF'!$A:$A,$A35,'Pooled CF'!$G:$G,L$6) -> 420938.93 | M35: =SUMIFS('Pooled CF'!$E:$E,'Pooled CF'!$A:$A,$A35,'Pooled CF'!$G:$G,M$6) -> 434961.51 | N35: =SUMIFS('Pooled CF'!$E:$E,'Pooled CF'!$A:$A,$A35,'Pooled CF'!$G:$G,N$6) -> 420924.57 | O35: =SUMIFS('Pooled CF'!$E:$E,'Pooled CF'!$A:$A,$A35,'Pooled CF'!$G:$G,O$6) -> 434948.35 | P35: =SUMIFS('Pooled CF'!$E:$E,'Pooled CF'!$A:$A,$A35,'Pooled CF'!$G:$G,P$6) -> 420911.76 | Q35: =SUMIFS('Pooled CF'!$E:$E,'Pooled CF'!$A:$A,$A35,'Pooled CF'!$G:$G,Q$6) -> 434935.06 | R35: =SUMIFS('Pooled CF'!$E:$E,'Pooled CF'!$A:$A,$A35,'Pooled CF'!$G:$G,R$6) -> 434928.8 | ... GS35: =SUMIFS('Pooled CF'!$E:$E,'Pooled CF'!$A:$A,$A35,'Pooled CF'!$G:$G,GS$6) -> 0 | GU35: =SUMIFS($K35:$GS35,$K$5:$GS$5,GU$6) -> -39068215 | GV35: =SUMIFS($K35:$GS35,$K$5:$GS$5,GV$6) -> 5119608.6 | GW35: =SUMIFS($K35:$GS35,$K$5:$GS$5,GW$6) -> 5117933.7 | GX35: =SUMIFS($K35:$GS35,$K$5:$GS$5,GX$6) -> 4167228.7 | GY35: =SUMIFS($K35:$GS35,$K$5:$GS$5,GY$6) -> 1864904.7 | GZ35: =SUMIFS($K35:$GS35,$K$5:$GS$5,GZ$6) -> 1566228.1 | HA35: =SUMIFS($K35:$GS35,$K$5:$GS$5,HA$6) -> 1157418.4 | HB35: =SUMIFS($K35:$GS35,$K$5:$GS$5,HB$6) -> 65493.24 | ... HJ35: =SUMIFS($K35:$GS35,$K$5:$GS$5,HJ$6) -> 0 | HK35: =SUM(GU35:HJ35) -> -20009400
B37: Gross B-Piece Cash Flows | C37: =MIN(C8:C36) -> 42794 | D37: =SUM(D8:D36) -> 2.1059857e+09 | E37: =F37/D37 -> 0.47855858 | F37: =SUM(F8:F36) -> 1.0078375e+09 | G37: =SUM(G8:G36) -> 7.486876e+08 | H37: =IFERROR(XIRR(OFFSET($J37,0,MATCH($C37,$K$6:$GS$6,0)):$GS37,OFFSET($J$6,0,MATCH($C37,$K$6:$GS$6,0)):$GS$6),"N/A") -> 0.057775828 | I37: =(HK37+F37)/F37 -> 1.5178464 | K37: =SUM(K8:K36) -> -43347451 | L37: =SUM(L8:L36) -> 420938.93 | M37: =SUM(M8:M36) -> 434961.51 | N37: =SUM(N8:N36) -> -44765636 | O37: =SUM(O8:O36) -> -48772922 | P37: =SUM(P8:P36) -> 1308032.3 | Q37: =SUM(Q8:Q36) -> -83616206 | R37: =SUM(R8:R36) -> 1996791.5 | ... GS37: =SUM(GS8:GS36) -> 0 | GU37: =SUM(GU8:GU36) -> -4.1081245e+08 | GV37: =SUM(GV8:GV36) -> -3.2475224e+08 | GW37: =SUM(GW8:GW36) -> -1.1019743e+08 | GX37: =SUM(GX8:GX36) -> 96447721 | GY37: =SUM(GY8:GY36) -> 92127051 | GZ37: =SUM(GZ8:GZ36) -> 94729508 | HA37: =SUM(HA8:HA36) -> 91916222 | HB37: =SUM(HB8:HB36) -> 86688186 | ... HJ37: =SUM(HJ8:HJ36) -> 80148580 | HK37: =SUM(GU37:HJ37) -> 5.2190507e+08
B39: Contributions
B41: =B9 -> UBSCM 2017-C2 | K41: =IF(K$6=$C9,-$F9,0) -> 0 | L41: =IF(L$6=$C9,-$F9,0) -> 0 | M41: =IF(M$6=$C9,-$F9,0) -> 0 | N41: =IF(N$6=$C9,-$F9,0) -> 0 | O41: =IF(O$6=$C9,-$F9,0) -> 0 | P41: =IF(P$6=$C9,-$F9,0) -> 0 | Q41: =IF(Q$6=$C9,-$F9,0) -> -46811027 | R41: =IF(R$6=$C9,-$F9,0) -> 0 | ... GS41: =IF(GS$6=$C9,-$F9,0) -> 0 | GU41: =SUMIFS($K41:$GS41,$K$5:$GS$5,GU$6) -> -46811027 | GV41: =SUMIFS($K41:$GS41,$K$5:$GS$5,GV$6) -> 0 | GW41: =SUMIFS($K41:$GS41,$K$5:$GS$5,GW$6) -> 0 | GX41: =SUMIFS($K41:$GS41,$K$5:$GS$5,GX$6) -> 0 | GY41: =SUMIFS($K41:$GS41,$K$5:$GS$5,GY$6) -> 0 | GZ41: =SUMIFS($K41:$GS41,$K$5:$GS$5,GZ$6) -> 0 | HA41: =SUMIFS($K41:$GS41,$K$5:$GS$5,HA$6) -> 0 | HB41: =SUMIFS($K41:$GS41,$K$5:$GS$5,HB$6) -> 0 | ... HJ41: =SUMIFS($K41:$GS41,$K$5:$GS$5,HJ$6) -> 0 | HK41: =SUM(GU41:HJ41) -> -46811027
B42: =B10 -> CGCMT 2017-C4 | K42: =IF(K$6=$C10,-$F10,0) -> 0 | L42: =IF(L$6=$C10,-$F10,0) -> 0 | M42: =IF(M$6=$C10,-$F10,0) -> 0 | N42: =IF(N$6=$C10,-$F10,0) -> 0 | O42: =IF(O$6=$C10,-$F10,0) -> 0 | P42: =IF(P$6=$C10,-$F10,0) -> 0 | Q42: =IF(Q$6=$C10,-$F10,0) -> 0 | R42: =IF(R$6=$C10,-$F10,0) -> 0 | ... GS42: =IF(GS$6=$C10,-$F10,0) -> 0 | GU42: =SUMIFS($K42:$GS42,$K$5:$GS$5,GU$6) -> -50142415 | GV42: =SUMIFS($K42:$GS42,$K$5:$GS$5,GV$6) -> 0 | GW42: =SUMIFS($K42:$GS42,$K$5:$GS$5,GW$6) -> 0 | GX42: =SUMIFS($K42:$GS42,$K$5:$GS$5,GX$6) -> 0 | GY42: =SUMIFS($K42:$GS42,$K$5:$GS$5,GY$6) -> 0 | GZ42: =SUMIFS($K42:$GS42,$K$5:$GS$5,GZ$6) -> 0 | HA42: =SUMIFS($K42:$GS42,$K$5:$GS$5,HA$6) -> 0 | HB42: =SUMIFS($K42:$GS42,$K$5:$GS$5,HB$6) -> 0 | ... HJ42: =SUMIFS($K42:$GS42,$K$5:$GS$5,HJ$6) -> 0 | HK42: =SUM(GU42:HJ42) -> -50142415
B43: =B11 -> WFCM 2018-C47 | K43: =IF(K$6=$C11,-$F11,0) -> 0 | L43: =IF(L$6=$C11,-$F11,0) -> 0 | M43: =IF(M$6=$C11,-$F11,0) -> 0 | N43: =IF(N$6=$C11,-$F11,0) -> 0 | O43: =IF(O$6=$C11,-$F11,0) -> 0 | P43: =IF(P$6=$C11,-$F11,0) -> 0 | Q43: =IF(Q$6=$C11,-$F11,0) -> 0 | R43: =IF(R$6=$C11,-$F11,0) -> 0 | ... GS43: =IF(GS$6=$C11,-$F11,0) -> 0 | GU43: =SUMIFS($K43:$GS43,$K$5:$GS$5,GU$6) -> 0 | GV43: =SUMIFS($K43:$GS43,$K$5:$GS$5,GV$6) -> -48654543 | GW43: =SUMIFS($K43:$GS43,$K$5:$GS$5,GW$6) -> 0 | GX43: =SUMIFS($K43:$GS43,$K$5:$GS$5,GX$6) -> 0 | GY43: =SUMIFS($K43:$GS43,$K$5:$GS$5,GY$6) -> 0 | GZ43: =SUMIFS($K43:$GS43,$K$5:$GS$5,GZ$6) -> 0 | HA43: =SUMIFS($K43:$GS43,$K$5:$GS$5,HA$6) -> 0 | HB43: =SUMIFS($K43:$GS43,$K$5:$GS$5,HB$6) -> 0 | ... HJ43: =SUMIFS($K43:$GS43,$K$5:$GS$5,HJ$6) -> 0 | HK43: =SUM(GU43:HJ43) -> -48654543
B44: =B12 -> BBCMS 2019-C3 | K44: =IF(K$6=$C12,-$F12,0) -> 0 | L44: =IF(L$6=$C12,-$F12,0) -> 0 | M44: =IF(M$6=$C12,-$F12,0) -> 0 | N44: =IF(N$6=$C12,-$F12,0) -> 0 | O44: =IF(O$6=$C12,-$F12,0) -> 0 | P44: =IF(P$6=$C12,-$F12,0) -> 0 | Q44: =IF(Q$6=$C12,-$F12,0) -> 0 | R44: =IF(R$6=$C12,-$F12,0) -> 0 | ... GS44: =IF(GS$6=$C12,-$F12,0) -> 0 | GU44: =SUMIFS($K44:$GS44,$K$5:$GS$5,GU$6) -> 0 | GV44: =SUMIFS($K44:$GS44,$K$5:$GS$5,GV$6) -> 0 | GW44: =SUMIFS($K44:$GS44,$K$5:$GS$5,GW$6) -> -49580194 | GX44: =SUMIFS($K44:$GS44,$K$5:$GS$5,GX$6) -> 0 | GY44: =SUMIFS($K44:$GS44,$K$5:$GS$5,GY$6) -> 0 | GZ44: =SUMIFS($K44:$GS44,$K$5:$GS$5,GZ$6) -> 0 | HA44: =SUMIFS($K44:$GS44,$K$5:$GS$5,HA$6) -> 0 | HB44: =SUMIFS($K44:$GS44,$K$5:$GS$5,HB$6) -> 0 | ... HJ44: =SUMIFS($K44:$GS44,$K$5:$GS$5,HJ$6) -> 0 | HK44: =SUM(GU44:HJ44) -> -49580194
B45: =B13 -> GSMS 2019-GC38 | K45: =IF(K$6=$C13,-$F13,0) -> 0 | L45: =IF(L$6=$C13,-$F13,0) -> 0 | M45: =IF(M$6=$C13,-$F13,0) -> 0 | N45: =IF(N$6=$C13,-$F13,0) -> 0 | O45: =IF(O$6=$C13,-$F13,0) -> 0 | P45: =IF(P$6=$C13,-$F13,0) -> 0 | Q45: =IF(Q$6=$C13,-$F13,0) -> 0 | R45: =IF(R$6=$C13,-$F13,0) -> 0 | ... GS45: =IF(GS$6=$C13,-$F13,0) -> 0 | GU45: =SUMIFS($K45:$GS45,$K$5:$GS$5,GU$6) -> 0 | GV45: =SUMIFS($K45:$GS45,$K$5:$GS$5,GV$6) -> 0 | GW45: =SUMIFS($K45:$GS45,$K$5:$GS$5,GW$6) -> -39335516 | GX45: =SUMIFS($K45:$GS45,$K$5:$GS$5,GX$6) -> 0 | GY45: =SUMIFS($K45:$GS45,$K$5:$GS$5,GY$6) -> 0 | GZ45: =SUMIFS($K45:$GS45,$K$5:$GS$5,GZ$6) -> 0 | HA45: =SUMIFS($K45:$GS45,$K$5:$GS$5,HA$6) -> 0 | HB45: =SUMIFS($K45:$GS45,$K$5:$GS$5,HB$6) -> 0 | ... HJ45: =SUMIFS($K45:$GS45,$K$5:$GS$5,HJ$6) -> 0 | HK45: =SUM(GU45:HJ45) -> -39335516
B46: =B14 -> GSMS 2017-GS8 | K46: =IF(K$6=$C14,-$F14,0) -> 0 | L46: =IF(L$6=$C14,-$F14,0) -> 0 | M46: =IF(M$6=$C14,-$F14,0) -> 0 | N46: =IF(N$6=$C14,-$F14,0) -> 0 | O46: =IF(O$6=$C14,-$F14,0) -> 0 | P46: =IF(P$6=$C14,-$F14,0) -> 0 | Q46: =IF(Q$6=$C14,-$F14,0) -> 0 | R46: =IF(R$6=$C14,-$F14,0) -> 0 | ... GS46: =IF(GS$6=$C14,-$F14,0) -> 0 | GU46: =SUMIFS($K46:$GS46,$K$5:$GS$5,GU$6) -> -52373515 | GV46: =SUMIFS($K46:$GS46,$K$5:$GS$5,GV$6) -> 0 | GW46: =SUMIFS($K46:$GS46,$K$5:$GS$5,GW$6) -> 0 | GX46: =SUMIFS($K46:$GS46,$K$5:$GS$5,GX$6) -> 0 | GY46: =SUMIFS($K46:$GS46,$K$5:$GS$5,GY$6) -> 0 | GZ46: =SUMIFS($K46:$GS46,$K$5:$GS$5,GZ$6) -> 0 | HA46: =SUMIFS($K46:$GS46,$K$5:$GS$5,HA$6) -> 0 | HB46: =SUMIFS($K46:$GS46,$K$5:$GS$5,HB$6) -> 0 | ... HJ46: =SUMIFS($K46:$GS46,$K$5:$GS$5,HJ$6) -> 0 | HK46: =SUM(GU46:HJ46) -> -52373515
B47: =B15 -> UBSCM 2018-C8 | K47: =IF(K$6=$C15,-$F15,0) -> 0 | L47: =IF(L$6=$C15,-$F15,0) -> 0 | M47: =IF(M$6=$C15,-$F15,0) -> 0 | N47: =IF(N$6=$C15,-$F15,0) -> 0 | O47: =IF(O$6=$C15,-$F15,0) -> 0 | P47: =IF(P$6=$C15,-$F15,0) -> 0 | Q47: =IF(Q$6=$C15,-$F15,0) -> 0 | R47: =IF(R$6=$C15,-$F15,0) -> 0 | ... GS47: =IF(GS$6=$C15,-$F15,0) -> 0 | GU47: =SUMIFS($K47:$GS47,$K$5:$GS$5,GU$6) -> 0 | GV47: =SUMIFS($K47:$GS47,$K$5:$GS$5,GV$6) -> -53204082 | GW47: =SUMIFS($K47:$GS47,$K$5:$GS$5,GW$6) -> 0 | GX47: =SUMIFS($K47:$GS47,$K$5:$GS$5,GX$6) -> 0 | GY47: =SUMIFS($K47:$GS47,$K$5:$GS$5,GY$6) -> 0 | GZ47: =SUMIFS($K47:$GS47,$K$5:$GS$5,GZ$6) -> 0 | HA47: =SUMIFS($K47:$GS47,$K$5:$GS$5,HA$6) -> 0 | HB47: =SUMIFS($K47:$GS47,$K$5:$GS$5,HB$6) -> 0 | ... HJ47: =SUMIFS($K47:$GS47,$K$5:$GS$5,HJ$6) -> 0 | HK47: =SUM(GU47:HJ47) -> -53204082
B48: =B16 -> UBSCM 2017-C3 | K48: =IF(K$6=$C16,-$F16,0) -> 0 | L48: =IF(L$6=$C16,-$F16,0) -> 0 | M48: =IF(M$6=$C16,-$F16,0) -> 0 | N48: =IF(N$6=$C16,-$F16,0) -> 0 | O48: =IF(O$6=$C16,-$F16,0) -> 0 | P48: =IF(P$6=$C16,-$F16,0) -> 0 | Q48: =IF(Q$6=$C16,-$F16,0) -> -38157487 | R48: =IF(R$6=$C16,-$F16,0) -> 0 | ... GS48: =IF(GS$6=$C16,-$F16,0) -> 0 | GU48: =SUMIFS($K48:$GS48,$K$5:$GS$5,GU$6) -> -38157487 | GV48: =SUMIFS($K48:$GS48,$K$5:$GS$5,GV$6) -> 0 | GW48: =SUMIFS($K48:$GS48,$K$5:$GS$5,GW$6) -> 0 | GX48: =SUMIFS($K48:$GS48,$K$5:$GS$5,GX$6) -> 0 | GY48: =SUMIFS($K48:$GS48,$K$5:$GS$5,GY$6) -> 0 | GZ48: =SUMIFS($K48:$GS48,$K$5:$GS$5,GZ$6) -> 0 | HA48: =SUMIFS($K48:$GS48,$K$5:$GS$5,HA$6) -> 0 | HB48: =SUMIFS($K48:$GS48,$K$5:$GS$5,HB$6) -> 0 | ... HJ48: =SUMIFS($K48:$GS48,$K$5:$GS$5,HJ$6) -> 0 | HK48: =SUM(GU48:HJ48) -> -38157487
B49: =B17 -> UBSCM 2017-C5 | K49: =IF(K$6=$C17,-$F17,0) -> 0 | L49: =IF(L$6=$C17,-$F17,0) -> 0 | M49: =IF(M$6=$C17,-$F17,0) -> 0 | N49: =IF(N$6=$C17,-$F17,0) -> 0 | O49: =IF(O$6=$C17,-$F17,0) -> 0 | P49: =IF(P$6=$C17,-$F17,0) -> 0 | Q49: =IF(Q$6=$C17,-$F17,0) -> 0 | R49: =IF(R$6=$C17,-$F17,0) -> 0 | ... GS49: =IF(GS$6=$C17,-$F17,0) -> 0 | GU49: =SUMIFS($K49:$GS49,$K$5:$GS$5,GU$6) -> -38300901 | GV49: =SUMIFS($K49:$GS49,$K$5:$GS$5,GV$6) -> 0 | GW49: =SUMIFS($K49:$GS49,$K$5:$GS$5,GW$6) -> 0 | GX49: =SUMIFS($K49:$GS49,$K$5:$GS$5,GX$6) -> 0 | GY49: =SUMIFS($K49:$GS49,$K$5:$GS$5,GY$6) -> 0 | GZ49: =SUMIFS($K49:$GS49,$K$5:$GS$5,GZ$6) -> 0 | HA49: =SUMIFS($K49:$GS49,$K$5:$GS$5,HA$6) -> 0 | HB49: =SUMIFS($K49:$GS49,$K$5:$GS$5,HB$6) -> 0 | ... HJ49: =SUMIFS($K49:$GS49,$K$5:$GS$5,HJ$6) -> 0 | HK49: =SUM(GU49:HJ49) -> -38300901
B50: =B18 -> MSC 2019-H6 | K50: =IF(K$6=$C18,-$F18,0) -> 0 | L50: =IF(L$6=$C18,-$F18,0) -> 0 | M50: =IF(M$6=$C18,-$F18,0) -> 0 | N50: =IF(N$6=$C18,-$F18,0) -> 0 | O50: =IF(O$6=$C18,-$F18,0) -> 0 | P50: =IF(P$6=$C18,-$F18,0) -> 0 | Q50: =IF(Q$6=$C18,-$F18,0) -> 0 | R50: =IF(R$6=$C18,-$F18,0) -> 0 | ... GS50: =IF(GS$6=$C18,-$F18,0) -> 0 | GU50: =SUMIFS($K50:$GS50,$K$5:$GS$5,GU$6) -> 0 | GV50: =SUMIFS($K50:$GS50,$K$5:$GS$5,GV$6) -> 0 | GW50: =SUMIFS($K50:$GS50,$K$5:$GS$5,GW$6) -> -36246073 | GX50: =SUMIFS($K50:$GS50,$K$5:$GS$5,GX$6) -> 0 | GY50: =SUMIFS($K50:$GS50,$K$5:$GS$5,GY$6) -> 0 | GZ50: =SUMIFS($K50:$GS50,$K$5:$GS$5,GZ$6) -> 0 | HA50: =SUMIFS($K50:$GS50,$K$5:$GS$5,HA$6) -> 0 | HB50: =SUMIFS($K50:$GS50,$K$5:$GS$5,HB$6) -> 0 | ... HJ50: =SUMIFS($K50:$GS50,$K$5:$GS$5,HJ$6) -> 0 | HK50: =SUM(GU50:HJ50) -> -36246073
B51: =B19 -> WFCM 2019-C49 | K51: =IF(K$6=$C19,-$F19,0) -> 0 | L51: =IF(L$6=$C19,-$F19,0) -> 0 | M51: =IF(M$6=$C19,-$F19,0) -> 0 | N51: =IF(N$6=$C19,-$F19,0) -> 0 | O51: =IF(O$6=$C19,-$F19,0) -> 0 | P51: =IF(P$6=$C19,-$F19,0) -> 0 | Q51: =IF(Q$6=$C19,-$F19,0) -> 0 | R51: =IF(R$6=$C19,-$F19,0) -> 0 | ... GS51: =IF(GS$6=$C19,-$F19,0) -> 0 | GU51: =SUMIFS($K51:$GS51,$K$5:$GS$5,GU$6) -> 0 | GV51: =SUMIFS($K51:$GS51,$K$5:$GS$5,GV$6) -> 0 | GW51: =SUMIFS($K51:$GS51,$K$5:$GS$5,GW$6) -> -40530203 | GX51: =SUMIFS($K51:$GS51,$K$5:$GS$5,GX$6) -> 0 | GY51: =SUMIFS($K51:$GS51,$K$5:$GS$5,GY$6) -> 0 | GZ51: =SUMIFS($K51:$GS51,$K$5:$GS$5,GZ$6) -> 0 | HA51: =SUMIFS($K51:$GS51,$K$5:$GS$5,HA$6) -> 0 | HB51: =SUMIFS($K51:$GS51,$K$5:$GS$5,HB$6) -> 0 | ... HJ51: =SUMIFS($K51:$GS51,$K$5:$GS$5,HJ$6) -> 0 | HK51: =SUM(GU51:HJ51) -> -40530203
B52: =B20 -> UBSCM 2018-C13 | K52: =IF(K$6=$C20,-$F20,0) -> 0 | L52: =IF(L$6=$C20,-$F20,0) -> 0 | M52: =IF(M$6=$C20,-$F20,0) -> 0 | N52: =IF(N$6=$C20,-$F20,0) -> 0 | O52: =IF(O$6=$C20,-$F20,0) -> 0 | P52: =IF(P$6=$C20,-$F20,0) -> 0 | Q52: =IF(Q$6=$C20,-$F20,0) -> 0 | R52: =IF(R$6=$C20,-$F20,0) -> 0 | ... GS52: =IF(GS$6=$C20,-$F20,0) -> 0 | GU52: =SUMIFS($K52:$GS52,$K$5:$GS$5,GU$6) -> 0 | GV52: =SUMIFS($K52:$GS52,$K$5:$GS$5,GV$6) -> -36689695 | GW52: =SUMIFS($K52:$GS52,$K$5:$GS$5,GW$6) -> 0 | GX52: =SUMIFS($K52:$GS52,$K$5:$GS$5,GX$6) -> 0 | GY52: =SUMIFS($K52:$GS52,$K$5:$GS$5,GY$6) -> 0 | GZ52: =SUMIFS($K52:$GS52,$K$5:$GS$5,GZ$6) -> 0 | HA52: =SUMIFS($K52:$GS52,$K$5:$GS$5,HA$6) -> 0 | HB52: =SUMIFS($K52:$GS52,$K$5:$GS$5,HB$6) -> 0 | ... HJ52: =SUMIFS($K52:$GS52,$K$5:$GS$5,HJ$6) -> 0 | HK52: =SUM(GU52:HJ52) -> -36689695
... B67: =B35 -> CD 2017-CD3 | K67: =IF(K$6=$C35,-$F35,0) -> -43347451 | L67: =IF(L$6=$C35,-$F35,0) -> 0 | M67: =IF(M$6=$C35,-$F35,0) -> 0 | N67: =IF(N$6=$C35,-$F35,0) -> 0 | O67: =IF(O$6=$C35,-$F35,0) -> 0 | P67: =IF(P$6=$C35,-$F35,0) -> 0 | Q67: =IF(Q$6=$C35,-$F35,0) -> 0 | R67: =IF(R$6=$C35,-$F35,0) -> 0 | ... GS67: =IF(GS$6=$C35,-$F35,0) -> 0 | GU67: =SUMIFS($K67:$GS67,$K$5:$GS$5,GU$6) -> -43347451 | GV67: =SUMIFS($K67:$GS67,$K$5:$GS$5,GV$6) -> 0 | GW67: =SUMIFS($K67:$GS67,$K$5:$GS$5,GW$6) -> 0 | GX67: =SUMIFS($K67:$GS67,$K$5:$GS$5,GX$6) -> 0 | GY67: =SUMIFS($K67:$GS67,$K$5:$GS$5,GY$6) -> 0 | GZ67: =SUMIFS($K67:$GS67,$K$5:$GS$5,GZ$6) -> 0 | HA67: =SUMIFS($K67:$GS67,$K$5:$GS$5,HA$6) -> 0 | HB67: =SUMIFS($K67:$GS67,$K$5:$GS$5,HB$6) -> 0 | ... HJ67: =SUMIFS($K67:$GS67,$K$5:$GS$5,HJ$6) -> 0 | HK67: =SUM(GU67:HJ67) -> -43347451
B69: Total | K69: =SUM(K40:K68) -> -43347451 | L69: =SUM(L40:L68) -> 0 | M69: =SUM(M40:M68) -> 0 | N69: =SUM(N40:N68) -> -45186561 | O69: =SUM(O40:O68) -> -49225235 | P69: =SUM(P40:P68) -> 0 | Q69: =SUM(Q40:Q68) -> -84968513 | R69: =SUM(R40:R68) -> 0 | ... GS69: =SUM(GS40:GS68) -> 0 | GU69: =SUMIFS($K69:$GS69,$K$5:$GS$5,GU$6) -> -4.2527688e+08 | GV69: =SUMIFS($K69:$GS69,$K$5:$GS$5,GV$6) -> -3.8022976e+08 | GW69: =SUMIFS($K69:$GS69,$K$5:$GS$5,GW$6) -> -2.0233087e+08 | GX69: =SUMIFS($K69:$GS69,$K$5:$GS$5,GX$6) -> 0 | GY69: =SUMIFS($K69:$GS69,$K$5:$GS$5,GY$6) -> 0 | GZ69: =SUMIFS($K69:$GS69,$K$5:$GS$5,GZ$6) -> 0 | HA69: =SUMIFS($K69:$GS69,$K$5:$GS$5,HA$6) -> 0 | HB69: =SUMIFS($K69:$GS69,$K$5:$GS$5,HB$6) -> 0 | ... HJ69: =SUMIFS($K69:$GS69,$K$5:$GS$5,HJ$6) -> 0 | HK69: =SUM(GU69:HJ69) -> -1.0078375e+09
B71: Projected Principal
A73: =A9 -> UBSCM 2017-C2 B-Piece Cashflows | B73: =B9 -> UBSCM 2017-C2 | K73: =SUMIFS('Pooled CF'!$I:$I,'Pooled CF'!$A:$A,$A73,'Pooled CF'!$G:$G,K$6) -> 0 | L73: =SUMIFS('Pooled CF'!$I:$I,'Pooled CF'!$A:$A,$A73,'Pooled CF'!$G:$G,L$6) -> 0 | M73: =SUMIFS('Pooled CF'!$I:$I,'Pooled CF'!$A:$A,$A73,'Pooled CF'!$G:$G,M$6) -> 0 | N73: =SUMIFS('Pooled CF'!$I:$I,'Pooled CF'!$A:$A,$A73,'Pooled CF'!$G:$G,N$6) -> 0 | O73: =SUMIFS('Pooled CF'!$I:$I,'Pooled CF'!$A:$A,$A73,'Pooled CF'!$G:$G,O$6) -> 0 | P73: =SUMIFS('Pooled CF'!$I:$I,'Pooled CF'!$A:$A,$A73,'Pooled CF'!$G:$G,P$6) -> 0 | Q73: =SUMIFS('Pooled CF'!$I:$I,'Pooled CF'!$A:$A,$A73,'Pooled CF'!$G:$G,Q$6) -> 0 | R73: =SUMIFS('Pooled CF'!$I:$I,'Pooled CF'!$A:$A,$A73,'Pooled CF'!$G:$G,R$6) -> 0 | ... GS73: =SUMIFS('Pooled CF'!$I:$I,'Pooled CF'!$A:$A,$A73,'Pooled CF'!$G:$G,GS$6) -> 0 | GU73: =SUMIFS($K73:$GS73,$K$5:$GS$5,GU$6) -> 0 | GV73: =SUMIFS($K73:$GS73,$K$5:$GS$5,GV$6) -> 0 | GW73: =SUMIFS($K73:$GS73,$K$5:$GS$5,GW$6) -> 0 | GX73: =SUMIFS($K73:$GS73,$K$5:$GS$5,GX$6) -> 0 | GY73: =SUMIFS($K73:$GS73,$K$5:$GS$5,GY$6) -> 0 | GZ73: =SUMIFS($K73:$GS73,$K$5:$GS$5,GZ$6) -> 0 | HA73: =SUMIFS($K73:$GS73,$K$5:$GS$5,HA$6) -> 0 | HB73: =SUMIFS($K73:$GS73,$K$5:$GS$5,HB$6) -> 0 | ... HJ73: =SUMIFS($K73:$GS73,$K$5:$GS$5,HJ$6) -> 0 | HK73: =SUM(GU73:HJ73) -> 77710247
A74: =A10 -> CGCMT 2017-C4 B-Piece Cashflows | B74: =B10 -> CGCMT 2017-C4 | K74: =SUMIFS('Pooled CF'!$I:$I,'Pooled CF'!$A:$A,$A74,'Pooled CF'!$G:$G,K$6) -> 0 | L74: =SUMIFS('Pooled CF'!$I:$I,'Pooled CF'!$A:$A,$A74,'Pooled CF'!$G:$G,L$6) -> 0 | M74: =SUMIFS('Pooled CF'!$I:$I,'Pooled CF'!$A:$A,$A74,'Pooled CF'!$G:$G,M$6) -> 0 | N74: =SUMIFS('Pooled CF'!$I:$I,'Pooled CF'!$A:$A,$A74,'Pooled CF'!$G:$G,N$6) -> 0 | O74: =SUMIFS('Pooled CF'!$I:$I,'Pooled CF'!$A:$A,$A74,'Pooled CF'!$G:$G,O$6) -> 0 | P74: =SUMIFS('Pooled CF'!$I:$I,'Pooled CF'!$A:$A,$A74,'Pooled CF'!$G:$G,P$6) -> 0 | Q74: =SUMIFS('Pooled CF'!$I:$I,'Pooled CF'!$A:$A,$A74,'Pooled CF'!$G:$G,Q$6) -> 0 | R74: =SUMIFS('Pooled CF'!$I:$I,'Pooled CF'!$A:$A,$A74,'Pooled CF'!$G:$G,R$6) -> 0 | ... GS74: =SUMIFS('Pooled CF'!$I:$I,'Pooled CF'!$A:$A,$A74,'Pooled CF'!$G:$G,GS$6) -> 0 | GU74: =SUMIFS($K74:$GS74,$K$5:$GS$5,GU$6) -> 0 | GV74: =SUMIFS($K74:$GS74,$K$5:$GS$5,GV$6) -> 0 | GW74: =SUMIFS($K74:$GS74,$K$5:$GS$5,GW$6) -> 0 | GX74: =SUMIFS($K74:$GS74,$K$5:$GS$5,GX$6) -> 0 | GY74: =SUMIFS($K74:$GS74,$K$5:$GS$5,GY$6) -> 0 | GZ74: =SUMIFS($K74:$GS74,$K$5:$GS$5,GZ$6) -> 0 | HA74: =SUMIFS($K74:$GS74,$K$5:$GS$5,HA$6) -> 0 | HB74: =SUMIFS($K74:$GS74,$K$5:$GS$5,HB$6) -> 0 | ... HJ74: =SUMIFS($K74:$GS74,$K$5:$GS$5,HJ$6) -> 0 | HK74: =SUM(GU74:HJ74) -> 54906448
A75: =A11 -> WFCM 2018-C47 B-Piece Cashflows | B75: =B11 -> WFCM 2018-C47 | K75: =SUMIFS('Pooled CF'!$I:$I,'Pooled CF'!$A:$A,$A75,'Pooled CF'!$G:$G,K$6) -> 0 | L75: =SUMIFS('Pooled CF'!$I:$I,'Pooled CF'!$A:$A,$A75,'Pooled CF'!$G:$G,L$6) -> 0 | M75: =SUMIFS('Pooled CF'!$I:$I,'Pooled CF'!$A:$A,$A75,'Pooled CF'!$G:$G,M$6) -> 0 | N75: =SUMIFS('Pooled CF'!$I:$I,'Pooled CF'!$A:$A,$A75,'Pooled CF'!$G:$G,N$6) -> 0 | O75: =SUMIFS('Pooled CF'!$I:$I,'Pooled CF'!$A:$A,$A75,'Pooled CF'!$G:$G,O$6) -> 0 | P75: =SUMIFS('Pooled CF'!$I:$I,'Pooled CF'!$A:$A,$A75,'Pooled CF'!$G:$G,P$6) -> 0 | Q75: =SUMIFS('Pooled CF'!$I:$I,'Pooled CF'!$A:$A,$A75,'Pooled CF'!$G:$G,Q$6) -> 0 | R75: =SUMIFS('Pooled CF'!$I:$I,'Pooled CF'!$A:$A,$A75,'Pooled CF'!$G:$G,R$6) -> 0 | ... GS75: =SUMIFS('Pooled CF'!$I:$I,'Pooled CF'!$A:$A,$A75,'Pooled CF'!$G:$G,GS$6) -> 0 | GU75: =SUMIFS($K75:$GS75,$K$5:$GS$5,GU$6) -> 0 | GV75: =SUMIFS($K75:$GS75,$K$5:$GS$5,GV$6) -> 0 | GW75: =SUMIFS($K75:$GS75,$K$5:$GS$5,GW$6) -> 0 | GX75: =SUMIFS($K75:$GS75,$K$5:$GS$5,GX$6) -> 0 | GY75: =SUMIFS($K75:$GS75,$K$5:$GS$5,GY$6) -> 0 | GZ75: =SUMIFS($K75:$GS75,$K$5:$GS$5,GZ$6) -> 0 | HA75: =SUMIFS($K75:$GS75,$K$5:$GS$5,HA$6) -> 0 | HB75: =SUMIFS($K75:$GS75,$K$5:$GS$5,HB$6) -> 0 | ... HJ75: =SUMIFS($K75:$GS75,$K$5:$GS$5,HJ$6) -> 0 | HK75: =SUM(GU75:HJ75) -> 42501933
A76: =A12 -> BBCMS 2019-C3 B-Piece Cashflows | B76: =B12 -> BBCMS 2019-C3 | K76: =SUMIFS('Pooled CF'!$I:$I,'Pooled CF'!$A:$A,$A76,'Pooled CF'!$G:$G,K$6) -> 0 | L76: =SUMIFS('Pooled CF'!$I:$I,'Pooled CF'!$A:$A,$A76,'Pooled CF'!$G:$G,L$6) -> 0 | M76: =SUMIFS('Pooled CF'!$I:$I,'Pooled CF'!$A:$A,$A76,'Pooled CF'!$G:$G,M$6) -> 0 | N76: =SUMIFS('Pooled CF'!$I:$I,'Pooled CF'!$A:$A,$A76,'Pooled CF'!$G:$G,N$6) -> 0 | O76: =SUMIFS('Pooled CF'!$I:$I,'Pooled CF'!$A:$A,$A76,'Pooled CF'!$G:$G,O$6) -> 0 | P76: =SUMIFS('Pooled CF'!$I:$I,'Pooled CF'!$A:$A,$A76,'Pooled CF'!$G:$G,P$6) -> 0 | Q76: =SUMIFS('Pooled CF'!$I:$I,'Pooled CF'!$A:$A,$A76,'Pooled CF'!$G:$G,Q$6) -> 0 | R76: =SUMIFS('Pooled CF'!$I:$I,'Pooled CF'!$A:$A,$A76,'Pooled CF'!$G:$G,R$6) -> 0 | ... GS76: =SUMIFS('Pooled CF'!$I:$I,'Pooled CF'!$A:$A,$A76,'Pooled CF'!$G:$G,GS$6) -> 0 | GU76: =SUMIFS($K76:$GS76,$K$5:$GS$5,GU$6) -> 0 | GV76: =SUMIFS($K76:$GS76,$K$5:$GS$5,GV$6) -> 0 | GW76: =SUMIFS($K76:$GS76,$K$5:$GS$5,GW$6) -> 0 | GX76: =SUMIFS($K76:$GS76,$K$5:$GS$5,GX$6) -> 0 | GY76: =SUMIFS($K76:$GS76,$K$5:$GS$5,GY$6) -> 0 | GZ76: =SUMIFS($K76:$GS76,$K$5:$GS$5,GZ$6) -> 0 | HA76: =SUMIFS($K76:$GS76,$K$5:$GS$5,HA$6) -> 0 | HB76: =SUMIFS($K76:$GS76,$K$5:$GS$5,HB$6) -> 0 | ... HJ76: =SUMIFS($K76:$GS76,$K$5:$GS$5,HJ$6) -> 37640522 | HK76: =SUM(GU76:HJ76) -> 42928577
A77: =A13 -> GSMS 2019-GC38 B-Piece Cashflow | B77: =B13 -> GSMS 2019-GC38 | K77: =SUMIFS('Pooled CF'!$I:$I,'Pooled CF'!$A:$A,$A77,'Pooled CF'!$G:$G,K$6) -> 0 | L77: =SUMIFS('Pooled CF'!$I:$I,'Pooled CF'!$A:$A,$A77,'Pooled CF'!$G:$G,L$6) -> 0 | M77: =SUMIFS('Pooled CF'!$I:$I,'Pooled CF'!$A:$A,$A77,'Pooled CF'!$G:$G,M$6) -> 0 | N77: =SUMIFS('Pooled CF'!$I:$I,'Pooled CF'!$A:$A,$A77,'Pooled CF'!$G:$G,N$6) -> 0 | O77: =SUMIFS('Pooled CF'!$I:$I,'Pooled CF'!$A:$A,$A77,'Pooled CF'!$G:$G,O$6) -> 0 | P77: =SUMIFS('Pooled CF'!$I:$I,'Pooled CF'!$A:$A,$A77,'Pooled CF'!$G:$G,P$6) -> 0 | Q77: =SUMIFS('Pooled CF'!$I:$I,'Pooled CF'!$A:$A,$A77,'Pooled CF'!$G:$G,Q$6) -> 0 | R77: =SUMIFS('Pooled CF'!$I:$I,'Pooled CF'!$A:$A,$A77,'Pooled CF'!$G:$G,R$6) -> 0 | ... GS77: =SUMIFS('Pooled CF'!$I:$I,'Pooled CF'!$A:$A,$A77,'Pooled CF'!$G:$G,GS$6) -> 0 | GU77: =SUMIFS($K77:$GS77,$K$5:$GS$5,GU$6) -> 0 | GV77: =SUMIFS($K77:$GS77,$K$5:$GS$5,GV$6) -> 0 | GW77: =SUMIFS($K77:$GS77,$K$5:$GS$5,GW$6) -> 0 | GX77: =SUMIFS($K77:$GS77,$K$5:$GS$5,GX$6) -> 0 | GY77: =SUMIFS($K77:$GS77,$K$5:$GS$5,GY$6) -> 0 | GZ77: =SUMIFS($K77:$GS77,$K$5:$GS$5,GZ$6) -> 0 | HA77: =SUMIFS($K77:$GS77,$K$5:$GS$5,HA$6) -> 0 | HB77: =SUMIFS($K77:$GS77,$K$5:$GS$5,HB$6) -> 0 | ... HJ77: =SUMIFS($K77:$GS77,$K$5:$GS$5,HJ$6) -> 34199846 | HK77: =SUM(GU77:HJ77) -> 34199846
A78: =A14 -> GSMS 2017-GS8 B-Piece Cashflow | B78: =B14 -> GSMS 2017-GS8 | K78: =SUMIFS('Pooled CF'!$I:$I,'Pooled CF'!$A:$A,$A78,'Pooled CF'!$G:$G,K$6) -> 0 | L78: =SUMIFS('Pooled CF'!$I:$I,'Pooled CF'!$A:$A,$A78,'Pooled CF'!$G:$G,L$6) -> 0 | M78: =SUMIFS('Pooled CF'!$I:$I,'Pooled CF'!$A:$A,$A78,'Pooled CF'!$G:$G,M$6) -> 0 | N78: =SUMIFS('Pooled CF'!$I:$I,'Pooled CF'!$A:$A,$A78,'Pooled CF'!$G:$G,N$6) -> 0 | O78: =SUMIFS('Pooled CF'!$I:$I,'Pooled CF'!$A:$A,$A78,'Pooled CF'!$G:$G,O$6) -> 0 | P78: =SUMIFS('Pooled CF'!$I:$I,'Pooled CF'!$A:$A,$A78,'Pooled CF'!$G:$G,P$6) -> 0 | Q78: =SUMIFS('Pooled CF'!$I:$I,'Pooled CF'!$A:$A,$A78,'Pooled CF'!$G:$G,Q$6) -> 0 | R78: =SUMIFS('Pooled CF'!$I:$I,'Pooled CF'!$A:$A,$A78,'Pooled CF'!$G:$G,R$6) -> 0 | ... GS78: =SUMIFS('Pooled CF'!$I:$I,'Pooled CF'!$A:$A,$A78,'Pooled CF'!$G:$G,GS$6) -> 0 | GU78: =SUMIFS($K78:$GS78,$K$5:$GS$5,GU$6) -> 0 | GV78: =SUMIFS($K78:$GS78,$K$5:$GS$5,GV$6) -> 0 | GW78: =SUMIFS($K78:$GS78,$K$5:$GS$5,GW$6) -> 0 | GX78: =SUMIFS($K78:$GS78,$K$5:$GS$5,GX$6) -> 0 | GY78: =SUMIFS($K78:$GS78,$K$5:$GS$5,GY$6) -> 0 | GZ78: =SUMIFS($K78:$GS78,$K$5:$GS$5,GZ$6) -> 0 | HA78: =SUMIFS($K78:$GS78,$K$5:$GS$5,HA$6) -> 0 | HB78: =SUMIFS($K78:$GS78,$K$5:$GS$5,HB$6) -> 0 | ... HJ78: =SUMIFS($K78:$GS78,$K$5:$GS$5,HJ$6) -> 0 | HK78: =SUM(GU78:HJ78) -> 36163932
A79: =A15 -> UBSCM 2018-C8 B-Piece Cashflows | B79: =B15 -> UBSCM 2018-C8 | K79: =SUMIFS('Pooled CF'!$I:$I,'Pooled CF'!$A:$A,$A79,'Pooled CF'!$G:$G,K$6) -> 0 | L79: =SUMIFS('Pooled CF'!$I:$I,'Pooled CF'!$A:$A,$A79,'Pooled CF'!$G:$G,L$6) -> 0 | M79: =SUMIFS('Pooled CF'!$I:$I,'Pooled CF'!$A:$A,$A79,'Pooled CF'!$G:$G,M$6) -> 0 | N79: =SUMIFS('Pooled CF'!$I:$I,'Pooled CF'!$A:$A,$A79,'Pooled CF'!$G:$G,N$6) -> 0 | O79: =SUMIFS('Pooled CF'!$I:$I,'Pooled CF'!$A:$A,$A79,'Pooled CF'!$G:$G,O$6) -> 0 | P79: =SUMIFS('Pooled CF'!$I:$I,'Pooled CF'!$A:$A,$A79,'Pooled CF'!$G:$G,P$6) -> 0 | Q79: =SUMIFS('Pooled CF'!$I:$I,'Pooled CF'!$A:$A,$A79,'Pooled CF'!$G:$G,Q$6) -> 0 | R79: =SUMIFS('Pooled CF'!$I:$I,'Pooled CF'!$A:$A,$A79,'Pooled CF'!$G:$G,R$6) -> 0 | ... GS79: =SUMIFS('Pooled CF'!$I:$I,'Pooled CF'!$A:$A,$A79,'Pooled CF'!$G:$G,GS$6) -> 0 | GU79: =SUMIFS($K79:$GS79,$K$5:$GS$5,GU$6) -> 0 | GV79: =SUMIFS($K79:$GS79,$K$5:$GS$5,GV$6) -> 0 | GW79: =SUMIFS($K79:$GS79,$K$5:$GS$5,GW$6) -> 0 | GX79: =SUMIFS($K79:$GS79,$K$5:$GS$5,GX$6) -> 0 | GY79: =SUMIFS($K79:$GS79,$K$5:$GS$5,GY$6) -> 0 | GZ79: =SUMIFS($K79:$GS79,$K$5:$GS$5,GZ$6) -> 0 | HA79: =SUMIFS($K79:$GS79,$K$5:$GS$5,HA$6) -> 0 | HB79: =SUMIFS($K79:$GS79,$K$5:$GS$5,HB$6) -> 0 | ... HJ79: =SUMIFS($K79:$GS79,$K$5:$GS$5,HJ$6) -> 0 | HK79: =SUM(GU79:HJ79) -> 0
A80: =A16 -> UBSCM 2017-C3 B-Piece Cashflows | B80: =B16 -> UBSCM 2017-C3 | K80: =SUMIFS('Pooled CF'!$I:$I,'Pooled CF'!$A:$A,$A80,'Pooled CF'!$G:$G,K$6) -> 0 | L80: =SUMIFS('Pooled CF'!$I:$I,'Pooled CF'!$A:$A,$A80,'Pooled CF'!$G:$G,L$6) -> 0 | M80: =SUMIFS('Pooled CF'!$I:$I,'Pooled CF'!$A:$A,$A80,'Pooled CF'!$G:$G,M$6) -> 0 | N80: =SUMIFS('Pooled CF'!$I:$I,'Pooled CF'!$A:$A,$A80,'Pooled CF'!$G:$G,N$6) -> 0 | O80: =SUMIFS('Pooled CF'!$I:$I,'Pooled CF'!$A:$A,$A80,'Pooled CF'!$G:$G,O$6) -> 0 | P80: =SUMIFS('Pooled CF'!$I:$I,'Pooled CF'!$A:$A,$A80,'Pooled CF'!$G:$G,P$6) -> 0 | Q80: =SUMIFS('Pooled CF'!$I:$I,'Pooled CF'!$A:$A,$A80,'Pooled CF'!$G:$G,Q$6) -> 0 | R80: =SUMIFS('Pooled CF'!$I:$I,'Pooled CF'!$A:$A,$A80,'Pooled CF'!$G:$G,R$6) -> 0 | ... GS80: =SUMIFS('Pooled CF'!$I:$I,'Pooled CF'!$A:$A,$A80,'Pooled CF'!$G:$G,GS$6) -> 0 | GU80: =SUMIFS($K80:$GS80,$K$5:$GS$5,GU$6) -> 0 | GV80: =SUMIFS($K80:$GS80,$K$5:$GS$5,GV$6) -> 0 | GW80: =SUMIFS($K80:$GS80,$K$5:$GS$5,GW$6) -> 0 | GX80: =SUMIFS($K80:$GS80,$K$5:$GS$5,GX$6) -> 0 | GY80: =SUMIFS($K80:$GS80,$K$5:$GS$5,GY$6) -> 0 | GZ80: =SUMIFS($K80:$GS80,$K$5:$GS$5,GZ$6) -> 0 | HA80: =SUMIFS($K80:$GS80,$K$5:$GS$5,HA$6) -> 0 | HB80: =SUMIFS($K80:$GS80,$K$5:$GS$5,HB$6) -> 0 | ... HJ80: =SUMIFS($K80:$GS80,$K$5:$GS$5,HJ$6) -> 0 | HK80: =SUM(GU80:HJ80) -> 28863654
A81: =A17 -> UBSCM 2017-C5 B-Piece Cashflows | B81: =B17 -> UBSCM 2017-C5 | K81: =SUMIFS('Pooled CF'!$I:$I,'Pooled CF'!$A:$A,$A81,'Pooled CF'!$G:$G,K$6) -> 0 | L81: =SUMIFS('Pooled CF'!$I:$I,'Pooled CF'!$A:$A,$A81,'Pooled CF'!$G:$G,L$6) -> 0 | M81: =SUMIFS('Pooled CF'!$I:$I,'Pooled CF'!$A:$A,$A81,'Pooled CF'!$G:$G,M$6) -> 0 | N81: =SUMIFS('Pooled CF'!$I:$I,'Pooled CF'!$A:$A,$A81,'Pooled CF'!$G:$G,N$6) -> 0 | O81: =SUMIFS('Pooled CF'!$I:$I,'Pooled CF'!$A:$A,$A81,'Pooled CF'!$G:$G,O$6) -> 0 | P81: =SUMIFS('Pooled CF'!$I:$I,'Pooled CF'!$A:$A,$A81,'Pooled CF'!$G:$G,P$6) -> 0 | Q81: =SUMIFS('Pooled CF'!$I:$I,'Pooled CF'!$A:$A,$A81,'Pooled CF'!$G:$G,Q$6) -> 0 | R81: =SUMIFS('Pooled CF'!$I:$I,'Pooled CF'!$A:$A,$A81,'Pooled CF'!$G:$G,R$6) -> 0 | ... GS81: =SUMIFS('Pooled CF'!$I:$I,'Pooled CF'!$A:$A,$A81,'Pooled CF'!$G:$G,GS$6) -> 0 | GU81: =SUMIFS($K81:$GS81,$K$5:$GS$5,GU$6) -> 0 | GV81: =SUMIFS($K81:$GS81,$K$5:$GS$5,GV$6) -> 0 | GW81: =SUMIFS($K81:$GS81,$K$5:$GS$5,GW$6) -> 0 | GX81: =SUMIFS($K81:$GS81,$K$5:$GS$5,GX$6) -> 0 | GY81: =SUMIFS($K81:$GS81,$K$5:$GS$5,GY$6) -> 0 | GZ81: =SUMIFS($K81:$GS81,$K$5:$GS$5,GZ$6) -> 0 | HA81: =SUMIFS($K81:$GS81,$K$5:$GS$5,HA$6) -> 0 | HB81: =SUMIFS($K81:$GS81,$K$5:$GS$5,HB$6) -> 0 | ... HJ81: =SUMIFS($K81:$GS81,$K$5:$GS$5,HJ$6) -> 0 | HK81: =SUM(GU81:HJ81) -> 29303245
A82: =A18 -> MSC 2019-H6 B-Piece Cashflows | B82: =B18 -> MSC 2019-H6 | K82: =SUMIFS('Pooled CF'!$I:$I,'Pooled CF'!$A:$A,$A82,'Pooled CF'!$G:$G,K$6) -> 0 | L82: =SUMIFS('Pooled CF'!$I:$I,'Pooled CF'!$A:$A,$A82,'Pooled CF'!$G:$G,L$6) -> 0 | M82: =SUMIFS('Pooled CF'!$I:$I,'Pooled CF'!$A:$A,$A82,'Pooled CF'!$G:$G,M$6) -> 0 | N82: =SUMIFS('Pooled CF'!$I:$I,'Pooled CF'!$A:$A,$A82,'Pooled CF'!$G:$G,N$6) -> 0 | O82: =SUMIFS('Pooled CF'!$I:$I,'Pooled CF'!$A:$A,$A82,'Pooled CF'!$G:$G,O$6) -> 0 | P82: =SUMIFS('Pooled CF'!$I:$I,'Pooled CF'!$A:$A,$A82,'Pooled CF'!$G:$G,P$6) -> 0 | Q82: =SUMIFS('Pooled CF'!$I:$I,'Pooled CF'!$A:$A,$A82,'Pooled CF'!$G:$G,Q$6) -> 0 | R82: =SUMIFS('Pooled CF'!$I:$I,'Pooled CF'!$A:$A,$A82,'Pooled CF'!$G:$G,R$6) -> 0 | ... GS82: =SUMIFS('Pooled CF'!$I:$I,'Pooled CF'!$A:$A,$A82,'Pooled CF'!$G:$G,GS$6) -> 0 | GU82: =SUMIFS($K82:$GS82,$K$5:$GS$5,GU$6) -> 0 | GV82: =SUMIFS($K82:$GS82,$K$5:$GS$5,GV$6) -> 0 | GW82: =SUMIFS($K82:$GS82,$K$5:$GS$5,GW$6) -> 0 | GX82: =SUMIFS($K82:$GS82,$K$5:$GS$5,GX$6) -> 0 | GY82: =SUMIFS($K82:$GS82,$K$5:$GS$5,GY$6) -> 0 | GZ82: =SUMIFS($K82:$GS82,$K$5:$GS$5,GZ$6) -> 0 | HA82: =SUMIFS($K82:$GS82,$K$5:$GS$5,HA$6) -> 0 | HB82: =SUMIFS($K82:$GS82,$K$5:$GS$5,HB$6) -> 0 | ... HJ82: =SUMIFS($K82:$GS82,$K$5:$GS$5,HJ$6) -> 0 | HK82: =SUM(GU82:HJ82) -> 47735000
A83: =A19 -> WFCM 2019-C49 B-Piece Cashflows | B83: =B19 -> WFCM 2019-C49 | K83: =SUMIFS('Pooled CF'!$I:$I,'Pooled CF'!$A:$A,$A83,'Pooled CF'!$G:$G,K$6) -> 0 | L83: =SUMIFS('Pooled CF'!$I:$I,'Pooled CF'!$A:$A,$A83,'Pooled CF'!$G:$G,L$6) -> 0 | M83: =SUMIFS('Pooled CF'!$I:$I,'Pooled CF'!$A:$A,$A83,'Pooled CF'!$G:$G,M$6) -> 0 | N83: =SUMIFS('Pooled CF'!$I:$I,'Pooled CF'!$A:$A,$A83,'Pooled CF'!$G:$G,N$6) -> 0 | O83: =SUMIFS('Pooled CF'!$I:$I,'Pooled CF'!$A:$A,$A83,'Pooled CF'!$G:$G,O$6) -> 0 | P83: =SUMIFS('Pooled CF'!$I:$I,'Pooled CF'!$A:$A,$A83,'Pooled CF'!$G:$G,P$6) -> 0 | Q83: =SUMIFS('Pooled CF'!$I:$I,'Pooled CF'!$A:$A,$A83,'Pooled CF'!$G:$G,Q$6) -> 0 | R83: =SUMIFS('Pooled CF'!$I:$I,'Pooled CF'!$A:$A,$A83,'Pooled CF'!$G:$G,R$6) -> 0 | ... GS83: =SUMIFS('Pooled CF'!$I:$I,'Pooled CF'!$A:$A,$A83,'Pooled CF'!$G:$G,GS$6) -> 0 | GU83: =SUMIFS($K83:$GS83,$K$5:$GS$5,GU$6) -> 0 | GV83: =SUMIFS($K83:$GS83,$K$5:$GS$5,GV$6) -> 0 | GW83: =SUMIFS($K83:$GS83,$K$5:$GS$5,GW$6) -> 0 | GX83: =SUMIFS($K83:$GS83,$K$5:$GS$5,GX$6) -> 0 | GY83: =SUMIFS($K83:$GS83,$K$5:$GS$5,GY$6) -> 0 | GZ83: =SUMIFS($K83:$GS83,$K$5:$GS$5,GZ$6) -> 0 | HA83: =SUMIFS($K83:$GS83,$K$5:$GS$5,HA$6) -> 0 | HB83: =SUMIFS($K83:$GS83,$K$5:$GS$5,HB$6) -> 0 | ... HJ83: =SUMIFS($K83:$GS83,$K$5:$GS$5,HJ$6) -> 5575450.3 | HK83: =SUM(GU83:HJ83) -> 34032602
A84: =A20 -> UBSCM 2018-C13 B-Piece Cashflow | B84: =B20 -> UBSCM 2018-C13 | K84: =SUMIFS('Pooled CF'!$I:$I,'Pooled CF'!$A:$A,$A84,'Pooled CF'!$G:$G,K$6) -> 0 | L84: =SUMIFS('Pooled CF'!$I:$I,'Pooled CF'!$A:$A,$A84,'Pooled CF'!$G:$G,L$6) -> 0 | M84: =SUMIFS('Pooled CF'!$I:$I,'Pooled CF'!$A:$A,$A84,'Pooled CF'!$G:$G,M$6) -> 0 | N84: =SUMIFS('Pooled CF'!$I:$I,'Pooled CF'!$A:$A,$A84,'Pooled CF'!$G:$G,N$6) -> 0 | O84: =SUMIFS('Pooled CF'!$I:$I,'Pooled CF'!$A:$A,$A84,'Pooled CF'!$G:$G,O$6) -> 0 | P84: =SUMIFS('Pooled CF'!$I:$I,'Pooled CF'!$A:$A,$A84,'Pooled CF'!$G:$G,P$6) -> 0 | Q84: =SUMIFS('Pooled CF'!$I:$I,'Pooled CF'!$A:$A,$A84,'Pooled CF'!$G:$G,Q$6) -> 0 | R84: =SUMIFS('Pooled CF'!$I:$I,'Pooled CF'!$A:$A,$A84,'Pooled CF'!$G:$G,R$6) -> 0 | ... GS84: =SUMIFS('Pooled CF'!$I:$I,'Pooled CF'!$A:$A,$A84,'Pooled CF'!$G:$G,GS$6) -> 0 | GU84: =SUMIFS($K84:$GS84,$K$5:$GS$5,GU$6) -> 0 | GV84: =SUMIFS($K84:$GS84,$K$5:$GS$5,GV$6) -> 0 | GW84: =SUMIFS($K84:$GS84,$K$5:$GS$5,GW$6) -> 0 | GX84: =SUMIFS($K84:$GS84,$K$5:$GS$5,GX$6) -> 0 | GY84: =SUMIFS($K84:$GS84,$K$5:$GS$5,GY$6) -> 0 | GZ84: =SUMIFS($K84:$GS84,$K$5:$GS$5,GZ$6) -> 0 | HA84: =SUMIFS($K84:$GS84,$K$5:$GS$5,HA$6) -> 0 | HB84: =SUMIFS($K84:$GS84,$K$5:$GS$5,HB$6) -> 0 | ... HJ84: =SUMIFS($K84:$GS84,$K$5:$GS$5,HJ$6) -> 0 | HK84: =SUM(GU84:HJ84) -> 31327645
... A99: =A35 -> CD 2017-CD3 B-Piece Hist Cashfl | B99: =B35 -> CD 2017-CD3 | K99: =SUMIFS('Pooled CF'!$I:$I,'Pooled CF'!$A:$A,$A99,'Pooled CF'!$G:$G,K$6) -> 0 | L99: =SUMIFS('Pooled CF'!$I:$I,'Pooled CF'!$A:$A,$A99,'Pooled CF'!$G:$G,L$6) -> 0 | M99: =SUMIFS('Pooled CF'!$I:$I,'Pooled CF'!$A:$A,$A99,'Pooled CF'!$G:$G,M$6) -> 0 | N99: =SUMIFS('Pooled CF'!$I:$I,'Pooled CF'!$A:$A,$A99,'Pooled CF'!$G:$G,N$6) -> 0 | O99: =SUMIFS('Pooled CF'!$I:$I,'Pooled CF'!$A:$A,$A99,'Pooled CF'!$G:$G,O$6) -> 0 | P99: =SUMIFS('Pooled CF'!$I:$I,'Pooled CF'!$A:$A,$A99,'Pooled CF'!$G:$G,P$6) -> 0 | Q99: =SUMIFS('Pooled CF'!$I:$I,'Pooled CF'!$A:$A,$A99,'Pooled CF'!$G:$G,Q$6) -> 0 | R99: =SUMIFS('Pooled CF'!$I:$I,'Pooled CF'!$A:$A,$A99,'Pooled CF'!$G:$G,R$6) -> 0 | ... GS99: =SUMIFS('Pooled CF'!$I:$I,'Pooled CF'!$A:$A,$A99,'Pooled CF'!$G:$G,GS$6) -> 0 | GU99: =SUMIFS($K99:$GS99,$K$5:$GS$5,GU$6) -> 0 | GV99: =SUMIFS($K99:$GS99,$K$5:$GS$5,GV$6) -> 0 | GW99: =SUMIFS($K99:$GS99,$K$5:$GS$5,GW$6) -> 0 | GX99: =SUMIFS($K99:$GS99,$K$5:$GS$5,GX$6) -> 0 | GY99: =SUMIFS($K99:$GS99,$K$5:$GS$5,GY$6) -> 0 | GZ99: =SUMIFS($K99:$GS99,$K$5:$GS$5,GZ$6) -> 0 | HA99: =SUMIFS($K99:$GS99,$K$5:$GS$5,HA$6) -> 0 | HB99: =SUMIFS($K99:$GS99,$K$5:$GS$5,HB$6) -> 0 | ... HJ99: =SUMIFS($K99:$GS99,$K$5:$GS$5,HJ$6) -> 0 | HK99: =SUM(GU99:HJ99) -> 0
B101: Total | K101: =SUM(K72:K100) -> 0 | L101: =SUM(L72:L100) -> 0 | M101: =SUM(M72:M100) -> 0 | N101: =SUM(N72:N100) -> 0 | O101: =SUM(O72:O100) -> 0 | P101: =SUM(P72:P100) -> 0 | Q101: =SUM(Q72:Q100) -> 0 | R101: =SUM(R72:R100) -> 0 | ... GS101: =SUM(GS72:GS100) -> 0 | GU101: =SUMIFS($K101:$GS101,$K$5:$GS$5,GU$6) -> 0 | GV101: =SUMIFS($K101:$GS101,$K$5:$GS$5,GV$6) -> 0 | GW101: =SUMIFS($K101:$GS101,$K$5:$GS$5,GW$6) -> 0 | GX101: =SUMIFS($K101:$GS101,$K$5:$GS$5,GX$6) -> 0 | GY101: =SUMIFS($K101:$GS101,$K$5:$GS$5,GY$6) -> 0 | GZ101: =SUMIFS($K101:$GS101,$K$5:$GS$5,GZ$6) -> 0 | HA101: =SUMIFS($K101:$GS101,$K$5:$GS$5,HA$6) -> 0 | HB101: =SUMIFS($K101:$GS101,$K$5:$GS$5,HB$6) -> 0 | ... HJ101: =SUMIFS($K101:$GS101,$K$5:$GS$5,HJ$6) -> 77415817 | HK101: =SUM(GU101:HJ101) -> 5.7529438e+08
B103: Principal Writedown
A105: =A9 -> UBSCM 2017-C2 B-Piece Cashflows | B105: =B9 -> UBSCM 2017-C2 | K105: =SUMIF('Combined B-Piece P&I CF'!$A:$A,K$6,INDEX('Combined B-Piece P&I CF'!$BN:$CN,0,MATCH($B105,'Combined B-Piece P&I CF'!$BN$7:$CN$7,0))) -> 0 | L105: =SUMIF('Combined B-Piece P&I CF'!$A:$A,L$6,INDEX('Combined B-Piece P&I CF'!$BN:$CN,0,MATCH($B105,'Combined B-Piece P&I CF'!$BN$7:$CN$7,0))) -> 0 | M105: =SUMIF('Combined B-Piece P&I CF'!$A:$A,M$6,INDEX('Combined B-Piece P&I CF'!$BN:$CN,0,MATCH($B105,'Combined B-Piece P&I CF'!$BN$7:$CN$7,0))) -> 0 | N105: =SUMIF('Combined B-Piece P&I CF'!$A:$A,N$6,INDEX('Combined B-Piece P&I CF'!$BN:$CN,0,MATCH($B105,'Combined B-Piece P&I CF'!$BN$7:$CN$7,0))) -> 0 | O105: =SUMIF('Combined B-Piece P&I CF'!$A:$A,O$6,INDEX('Combined B-Piece P&I CF'!$BN:$CN,0,MATCH($B105,'Combined B-Piece P&I CF'!$BN$7:$CN$7,0))) -> 0 | P105: =SUMIF('Combined B-Piece P&I CF'!$A:$A,P$6,INDEX('Combined B-Piece P&I CF'!$BN:$CN,0,MATCH($B105,'Combined B-Piece P&I CF'!$BN$7:$CN$7,0))) -> 0 | Q105: =SUMIF('Combined B-Piece P&I CF'!$A:$A,Q$6,INDEX('Combined B-Piece P&I CF'!$BN:$CN,0,MATCH($B105,'Combined B-Piece P&I CF'!$BN$7:$CN$7,0))) -> 0 | R105: =SUMIF('Combined B-Piece P&I CF'!$A:$A,R$6,INDEX('Combined B-Piece P&I CF'!$BN:$CN,0,MATCH($B105,'Combined B-Piece P&I CF'!$BN$7:$CN$7,0))) -> 0 | ... GS105: =SUMIF('Combined B-Piece P&I CF'!$A:$A,GS$6,INDEX('Combined B-Piece P&I CF'!$BN:$CN,0,MATCH($B105,'Combined B-Piece P&I CF'!$BN$7:$CN$7,0))) -> 0 | GU105: =SUMIFS($K105:$GS105,$K$5:$GS$5,GU$6) -> 0 | GV105: =SUMIFS($K105:$GS105,$K$5:$GS$5,GV$6) -> 0 | GW105: =SUMIFS($K105:$GS105,$K$5:$GS$5,GW$6) -> 0 | GX105: =SUMIFS($K105:$GS105,$K$5:$GS$5,GX$6) -> 0 | GY105: =SUMIFS($K105:$GS105,$K$5:$GS$5,GY$6) -> 0 | GZ105: =SUMIFS($K105:$GS105,$K$5:$GS$5,GZ$6) -> 830403.35 | HA105: =SUMIFS($K105:$GS105,$K$5:$GS$5,HA$6) -> -830403.35 | HB105: =SUMIFS($K105:$GS105,$K$5:$GS$5,HB$6) -> 289.22 | ... HJ105: =SUMIFS($K105:$GS105,$K$5:$GS$5,HJ$6) -> 0 | HK105: =SUM(GU105:HJ105) -> 17469651
A106: =A10 -> CGCMT 2017-C4 B-Piece Cashflows | B106: =B10 -> CGCMT 2017-C4 | K106: =SUMIF('Combined B-Piece P&I CF'!$A:$A,K$6,INDEX('Combined B-Piece P&I CF'!$BN:$CN,0,MATCH($B106,'Combined B-Piece P&I CF'!$BN$7:$CN$7,0))) -> 0 | L106: =SUMIF('Combined B-Piece P&I CF'!$A:$A,L$6,INDEX('Combined B-Piece P&I CF'!$BN:$CN,0,MATCH($B106,'Combined B-Piece P&I CF'!$BN$7:$CN$7,0))) -> 0 | M106: =SUMIF('Combined B-Piece P&I CF'!$A:$A,M$6,INDEX('Combined B-Piece P&I CF'!$BN:$CN,0,MATCH($B106,'Combined B-Piece P&I CF'!$BN$7:$CN$7,0))) -> 0 | N106: =SUMIF('Combined B-Piece P&I CF'!$A:$A,N$6,INDEX('Combined B-Piece P&I CF'!$BN:$CN,0,MATCH($B106,'Combined B-Piece P&I CF'!$BN$7:$CN$7,0))) -> 0 | O106: =SUMIF('Combined B-Piece P&I CF'!$A:$A,O$6,INDEX('Combined B-Piece P&I CF'!$BN:$CN,0,MATCH($B106,'Combined B-Piece P&I CF'!$BN$7:$CN$7,0))) -> 0 | P106: =SUMIF('Combined B-Piece P&I CF'!$A:$A,P$6,INDEX('Combined B-Piece P&I CF'!$BN:$CN,0,MATCH($B106,'Combined B-Piece P&I CF'!$BN$7:$CN$7,0))) -> 0 | Q106: =SUMIF('Combined B-Piece P&I CF'!$A:$A,Q$6,INDEX('Combined B-Piece P&I CF'!$BN:$CN,0,MATCH($B106,'Combined B-Piece P&I CF'!$BN$7:$CN$7,0))) -> 0 | R106: =SUMIF('Combined B-Piece P&I CF'!$A:$A,R$6,INDEX('Combined B-Piece P&I CF'!$BN:$CN,0,MATCH($B106,'Combined B-Piece P&I CF'!$BN$7:$CN$7,0))) -> 0 | ... GS106: =SUMIF('Combined B-Piece P&I CF'!$A:$A,GS$6,INDEX('Combined B-Piece P&I CF'!$BN:$CN,0,MATCH($B106,'Combined B-Piece P&I CF'!$BN$7:$CN$7,0))) -> 0 | GU106: =SUMIFS($K106:$GS106,$K$5:$GS$5,GU$6) -> 0 | GV106: =SUMIFS($K106:$GS106,$K$5:$GS$5,GV$6) -> 0 | GW106: =SUMIFS($K106:$GS106,$K$5:$GS$5,GW$6) -> 0 | GX106: =SUMIFS($K106:$GS106,$K$5:$GS$5,GX$6) -> 0 | GY106: =SUMIFS($K106:$GS106,$K$5:$GS$5,GY$6) -> 0 | GZ106: =SUMIFS($K106:$GS106,$K$5:$GS$5,GZ$6) -> 0 | HA106: =SUMIFS($K106:$GS106,$K$5:$GS$5,HA$6) -> 0 | HB106: =SUMIFS($K106:$GS106,$K$5:$GS$5,HB$6) -> 0 | ... HJ106: =SUMIFS($K106:$GS106,$K$5:$GS$5,HJ$6) -> 0 | HK106: =SUM(GU106:HJ106) -> 50128445
A107: =A11 -> WFCM 2018-C47 B-Piece Cashflows | B107: =B11 -> WFCM 2018-C47 | K107: =SUMIF('Combined B-Piece P&I CF'!$A:$A,K$6,INDEX('Combined B-Piece P&I CF'!$BN:$CN,0,MATCH($B107,'Combined B-Piece P&I CF'!$BN$7:$CN$7,0))) -> 0 | L107: =SUMIF('Combined B-Piece P&I CF'!$A:$A,L$6,INDEX('Combined B-Piece P&I CF'!$BN:$CN,0,MATCH($B107,'Combined B-Piece P&I CF'!$BN$7:$CN$7,0))) -> 0 | M107: =SUMIF('Combined B-Piece P&I CF'!$A:$A,M$6,INDEX('Combined B-Piece P&I CF'!$BN:$CN,0,MATCH($B107,'Combined B-Piece P&I CF'!$BN$7:$CN$7,0))) -> 0 | N107: =SUMIF('Combined B-Piece P&I CF'!$A:$A,N$6,INDEX('Combined B-Piece P&I CF'!$BN:$CN,0,MATCH($B107,'Combined B-Piece P&I CF'!$BN$7:$CN$7,0))) -> 0 | O107: =SUMIF('Combined B-Piece P&I CF'!$A:$A,O$6,INDEX('Combined B-Piece P&I CF'!$BN:$CN,0,MATCH($B107,'Combined B-Piece P&I CF'!$BN$7:$CN$7,0))) -> 0 | P107: =SUMIF('Combined B-Piece P&I CF'!$A:$A,P$6,INDEX('Combined B-Piece P&I CF'!$BN:$CN,0,MATCH($B107,'Combined B-Piece P&I CF'!$BN$7:$CN$7,0))) -> 0 | Q107: =SUMIF('Combined B-Piece P&I CF'!$A:$A,Q$6,INDEX('Combined B-Piece P&I CF'!$BN:$CN,0,MATCH($B107,'Combined B-Piece P&I CF'!$BN$7:$CN$7,0))) -> 0 | R107: =SUMIF('Combined B-Piece P&I CF'!$A:$A,R$6,INDEX('Combined B-Piece P&I CF'!$BN:$CN,0,MATCH($B107,'Combined B-Piece P&I CF'!$BN$7:$CN$7,0))) -> 0 | ... GS107: =SUMIF('Combined B-Piece P&I CF'!$A:$A,GS$6,INDEX('Combined B-Piece P&I CF'!$BN:$CN,0,MATCH($B107,'Combined B-Piece P&I CF'!$BN$7:$CN$7,0))) -> 0 | GU107: =SUMIFS($K107:$GS107,$K$5:$GS$5,GU$6) -> 0 | GV107: =SUMIFS($K107:$GS107,$K$5:$GS$5,GV$6) -> 0 | GW107: =SUMIFS($K107:$GS107,$K$5:$GS$5,GW$6) -> 0 | GX107: =SUMIFS($K107:$GS107,$K$5:$GS$5,GX$6) -> 0 | GY107: =SUMIFS($K107:$GS107,$K$5:$GS$5,GY$6) -> 0 | GZ107: =SUMIFS($K107:$GS107,$K$5:$GS$5,GZ$6) -> 0 | HA107: =SUMIFS($K107:$GS107,$K$5:$GS$5,HA$6) -> 0 | HB107: =SUMIFS($K107:$GS107,$K$5:$GS$5,HB$6) -> 0 | ... HJ107: =SUMIFS($K107:$GS107,$K$5:$GS$5,HJ$6) -> 0 | HK107: =SUM(GU107:HJ107) -> 58936272
A108: =A12 -> BBCMS 2019-C3 B-Piece Cashflows | B108: =B12 -> BBCMS 2019-C3 | K108: =SUMIF('Combined B-Piece P&I CF'!$A:$A,K$6,INDEX('Combined B-Piece P&I CF'!$BN:$CN,0,MATCH($B108,'Combined B-Piece P&I CF'!$BN$7:$CN$7,0))) -> 0 | L108: =SUMIF('Combined B-Piece P&I CF'!$A:$A,L$6,INDEX('Combined B-Piece P&I CF'!$BN:$CN,0,MATCH($B108,'Combined B-Piece P&I CF'!$BN$7:$CN$7,0))) -> 0 | M108: =SUMIF('Combined B-Piece P&I CF'!$A:$A,M$6,INDEX('Combined B-Piece P&I CF'!$BN:$CN,0,MATCH($B108,'Combined B-Piece P&I CF'!$BN$7:$CN$7,0))) -> 0 | N108: =SUMIF('Combined B-Piece P&I CF'!$A:$A,N$6,INDEX('Combined B-Piece P&I CF'!$BN:$CN,0,MATCH($B108,'Combined B-Piece P&I CF'!$BN$7:$CN$7,0))) -> 0 | O108: =SUMIF('Combined B-Piece P&I CF'!$A:$A,O$6,INDEX('Combined B-Piece P&I CF'!$BN:$CN,0,MATCH($B108,'Combined B-Piece P&I CF'!$BN$7:$CN$7,0))) -> 0 | P108: =SUMIF('Combined B-Piece P&I CF'!$A:$A,P$6,INDEX('Combined B-Piece P&I CF'!$BN:$CN,0,MATCH($B108,'Combined B-Piece P&I CF'!$BN$7:$CN$7,0))) -> 0 | Q108: =SUMIF('Combined B-Piece P&I CF'!$A:$A,Q$6,INDEX('Combined B-Piece P&I CF'!$BN:$CN,0,MATCH($B108,'Combined B-Piece P&I CF'!$BN$7:$CN$7,0))) -> 0 | R108: =SUMIF('Combined B-Piece P&I CF'!$A:$A,R$6,INDEX('Combined B-Piece P&I CF'!$BN:$CN,0,MATCH($B108,'Combined B-Piece P&I CF'!$BN$7:$CN$7,0))) -> 0 | ... GS108: =SUMIF('Combined B-Piece P&I CF'!$A:$A,GS$6,INDEX('Combined B-Piece P&I CF'!$BN:$CN,0,MATCH($B108,'Combined B-Piece P&I CF'!$BN$7:$CN$7,0))) -> 0 | GU108: =SUMIFS($K108:$GS108,$K$5:$GS$5,GU$6) -> 0 | GV108: =SUMIFS($K108:$GS108,$K$5:$GS$5,GV$6) -> 0 | GW108: =SUMIFS($K108:$GS108,$K$5:$GS$5,GW$6) -> 0 | GX108: =SUMIFS($K108:$GS108,$K$5:$GS$5,GX$6) -> 0 | GY108: =SUMIFS($K108:$GS108,$K$5:$GS$5,GY$6) -> 0 | GZ108: =SUMIFS($K108:$GS108,$K$5:$GS$5,GZ$6) -> 0 | HA108: =SUMIFS($K108:$GS108,$K$5:$GS$5,HA$6) -> 0 | HB108: =SUMIFS($K108:$GS108,$K$5:$GS$5,HB$6) -> 0 | ... HJ108: =SUMIFS($K108:$GS108,$K$5:$GS$5,HJ$6) -> 9731845 | HK108: =SUM(GU108:HJ108) -> 58910042
A109: =A13 -> GSMS 2019-GC38 B-Piece Cashflow | B109: =B13 -> GSMS 2019-GC38 | K109: =SUMIF('Combined B-Piece P&I CF'!$A:$A,K$6,INDEX('Combined B-Piece P&I CF'!$BN:$CN,0,MATCH($B109,'Combined B-Piece P&I CF'!$BN$7:$CN$7,0))) -> 0 | L109: =SUMIF('Combined B-Piece P&I CF'!$A:$A,L$6,INDEX('Combined B-Piece P&I CF'!$BN:$CN,0,MATCH($B109,'Combined B-Piece P&I CF'!$BN$7:$CN$7,0))) -> 0 | M109: =SUMIF('Combined B-Piece P&I CF'!$A:$A,M$6,INDEX('Combined B-Piece P&I CF'!$BN:$CN,0,MATCH($B109,'Combined B-Piece P&I CF'!$BN$7:$CN$7,0))) -> 0 | N109: =SUMIF('Combined B-Piece P&I CF'!$A:$A,N$6,INDEX('Combined B-Piece P&I CF'!$BN:$CN,0,MATCH($B109,'Combined B-Piece P&I CF'!$BN$7:$CN$7,0))) -> 0 | O109: =SUMIF('Combined B-Piece P&I CF'!$A:$A,O$6,INDEX('Combined B-Piece P&I CF'!$BN:$CN,0,MATCH($B109,'Combined B-Piece P&I CF'!$BN$7:$CN$7,0))) -> 0 | P109: =SUMIF('Combined B-Piece P&I CF'!$A:$A,P$6,INDEX('Combined B-Piece P&I CF'!$BN:$CN,0,MATCH($B109,'Combined B-Piece P&I CF'!$BN$7:$CN$7,0))) -> 0 | Q109: =SUMIF('Combined B-Piece P&I CF'!$A:$A,Q$6,INDEX('Combined B-Piece P&I CF'!$BN:$CN,0,MATCH($B109,'Combined B-Piece P&I CF'!$BN$7:$CN$7,0))) -> 0 | R109: =SUMIF('Combined B-Piece P&I CF'!$A:$A,R$6,INDEX('Combined B-Piece P&I CF'!$BN:$CN,0,MATCH($B109,'Combined B-Piece P&I CF'!$BN$7:$CN$7,0))) -> 0 | ... GS109: =SUMIF('Combined B-Piece P&I CF'!$A:$A,GS$6,INDEX('Combined B-Piece P&I CF'!$BN:$CN,0,MATCH($B109,'Combined B-Piece P&I CF'!$BN$7:$CN$7,0))) -> 0 | GU109: =SUMIFS($K109:$GS109,$K$5:$GS$5,GU$6) -> 0 | GV109: =SUMIFS($K109:$GS109,$K$5:$GS$5,GV$6) -> 0 | GW109: =SUMIFS($K109:$GS109,$K$5:$GS$5,GW$6) -> 0 | GX109: =SUMIFS($K109:$GS109,$K$5:$GS$5,GX$6) -> 0 | GY109: =SUMIFS($K109:$GS109,$K$5:$GS$5,GY$6) -> 0 | GZ109: =SUMIFS($K109:$GS109,$K$5:$GS$5,GZ$6) -> 0 | HA109: =SUMIFS($K109:$GS109,$K$5:$GS$5,HA$6) -> 0 | HB109: =SUMIFS($K109:$GS109,$K$5:$GS$5,HB$6) -> 0 | ... HJ109: =SUMIFS($K109:$GS109,$K$5:$GS$5,HJ$6) -> 5000000 | HK109: =SUM(GU109:HJ109) -> 39440519
A110: =A14 -> GSMS 2017-GS8 B-Piece Cashflow | B110: =B14 -> GSMS 2017-GS8 | K110: =SUMIF('Combined B-Piece P&I CF'!$A:$A,K$6,INDEX('Combined B-Piece P&I CF'!$BN:$CN,0,MATCH($B110,'Combined B-Piece P&I CF'!$BN$7:$CN$7,0))) -> 0 | L110: =SUMIF('Combined B-Piece P&I CF'!$A:$A,L$6,INDEX('Combined B-Piece P&I CF'!$BN:$CN,0,MATCH($B110,'Combined B-Piece P&I CF'!$BN$7:$CN$7,0))) -> 0 | M110: =SUMIF('Combined B-Piece P&I CF'!$A:$A,M$6,INDEX('Combined B-Piece P&I CF'!$BN:$CN,0,MATCH($B110,'Combined B-Piece P&I CF'!$BN$7:$CN$7,0))) -> 0 | N110: =SUMIF('Combined B-Piece P&I CF'!$A:$A,N$6,INDEX('Combined B-Piece P&I CF'!$BN:$CN,0,MATCH($B110,'Combined B-Piece P&I CF'!$BN$7:$CN$7,0))) -> 0 | O110: =SUMIF('Combined B-Piece P&I CF'!$A:$A,O$6,INDEX('Combined B-Piece P&I CF'!$BN:$CN,0,MATCH($B110,'Combined B-Piece P&I CF'!$BN$7:$CN$7,0))) -> 0 | P110: =SUMIF('Combined B-Piece P&I CF'!$A:$A,P$6,INDEX('Combined B-Piece P&I CF'!$BN:$CN,0,MATCH($B110,'Combined B-Piece P&I CF'!$BN$7:$CN$7,0))) -> 0 | Q110: =SUMIF('Combined B-Piece P&I CF'!$A:$A,Q$6,INDEX('Combined B-Piece P&I CF'!$BN:$CN,0,MATCH($B110,'Combined B-Piece P&I CF'!$BN$7:$CN$7,0))) -> 0 | R110: =SUMIF('Combined B-Piece P&I CF'!$A:$A,R$6,INDEX('Combined B-Piece P&I CF'!$BN:$CN,0,MATCH($B110,'Combined B-Piece P&I CF'!$BN$7:$CN$7,0))) -> 0 | ... GS110: =SUMIF('Combined B-Piece P&I CF'!$A:$A,GS$6,INDEX('Combined B-Piece P&I CF'!$BN:$CN,0,MATCH($B110,'Combined B-Piece P&I CF'!$BN$7:$CN$7,0))) -> 0 | GU110: =SUMIFS($K110:$GS110,$K$5:$GS$5,GU$6) -> 0 | GV110: =SUMIFS($K110:$GS110,$K$5:$GS$5,GV$6) -> 0 | GW110: =SUMIFS($K110:$GS110,$K$5:$GS$5,GW$6) -> 0 | GX110: =SUMIFS($K110:$GS110,$K$5:$GS$5,GX$6) -> 0 | GY110: =SUMIFS($K110:$GS110,$K$5:$GS$5,GY$6) -> 0 | GZ110: =SUMIFS($K110:$GS110,$K$5:$GS$5,GZ$6) -> 0 | HA110: =SUMIFS($K110:$GS110,$K$5:$GS$5,HA$6) -> 0 | HB110: =SUMIFS($K110:$GS110,$K$5:$GS$5,HB$6) -> 0 | ... HJ110: =SUMIFS($K110:$GS110,$K$5:$GS$5,HJ$6) -> 0 | HK110: =SUM(GU110:HJ110) -> 70059454
A111: =A15 -> UBSCM 2018-C8 B-Piece Cashflows | B111: =B15 -> UBSCM 2018-C8 | K111: =SUMIF('Combined B-Piece P&I CF'!$A:$A,K$6,INDEX('Combined B-Piece P&I CF'!$BN:$CN,0,MATCH($B111,'Combined B-Piece P&I CF'!$BN$7:$CN$7,0))) -> 0 | L111: =SUMIF('Combined B-Piece P&I CF'!$A:$A,L$6,INDEX('Combined B-Piece P&I CF'!$BN:$CN,0,MATCH($B111,'Combined B-Piece P&I CF'!$BN$7:$CN$7,0))) -> 0 | M111: =SUMIF('Combined B-Piece P&I CF'!$A:$A,M$6,INDEX('Combined B-Piece P&I CF'!$BN:$CN,0,MATCH($B111,'Combined B-Piece P&I CF'!$BN$7:$CN$7,0))) -> 0 | N111: =SUMIF('Combined B-Piece P&I CF'!$A:$A,N$6,INDEX('Combined B-Piece P&I CF'!$BN:$CN,0,MATCH($B111,'Combined B-Piece P&I CF'!$BN$7:$CN$7,0))) -> 0 | O111: =SUMIF('Combined B-Piece P&I CF'!$A:$A,O$6,INDEX('Combined B-Piece P&I CF'!$BN:$CN,0,MATCH($B111,'Combined B-Piece P&I CF'!$BN$7:$CN$7,0))) -> 0 | P111: =SUMIF('Combined B-Piece P&I CF'!$A:$A,P$6,INDEX('Combined B-Piece P&I CF'!$BN:$CN,0,MATCH($B111,'Combined B-Piece P&I CF'!$BN$7:$CN$7,0))) -> 0 | Q111: =SUMIF('Combined B-Piece P&I CF'!$A:$A,Q$6,INDEX('Combined B-Piece P&I CF'!$BN:$CN,0,MATCH($B111,'Combined B-Piece P&I CF'!$BN$7:$CN$7,0))) -> 0 | R111: =SUMIF('Combined B-Piece P&I CF'!$A:$A,R$6,INDEX('Combined B-Piece P&I CF'!$BN:$CN,0,MATCH($B111,'Combined B-Piece P&I CF'!$BN$7:$CN$7,0))) -> 0 | ... GS111: =SUMIF('Combined B-Piece P&I CF'!$A:$A,GS$6,INDEX('Combined B-Piece P&I CF'!$BN:$CN,0,MATCH($B111,'Combined B-Piece P&I CF'!$BN$7:$CN$7,0))) -> 0 | GU111: =SUMIFS($K111:$GS111,$K$5:$GS$5,GU$6) -> 0 | GV111: =SUMIFS($K111:$GS111,$K$5:$GS$5,GV$6) -> 0 | GW111: =SUMIFS($K111:$GS111,$K$5:$GS$5,GW$6) -> 0 | GX111: =SUMIFS($K111:$GS111,$K$5:$GS$5,GX$6) -> 0 | GY111: =SUMIFS($K111:$GS111,$K$5:$GS$5,GY$6) -> 0 | GZ111: =SUMIFS($K111:$GS111,$K$5:$GS$5,GZ$6) -> 770190.06 | HA111: =SUMIFS($K111:$GS111,$K$5:$GS$5,HA$6) -> -8347.47 | HB111: =SUMIFS($K111:$GS111,$K$5:$GS$5,HB$6) -> 0 | ... HJ111: =SUMIFS($K111:$GS111,$K$5:$GS$5,HJ$6) -> 0 | HK111: =SUM(GU111:HJ111) -> 1.0704689e+08
A112: =A16 -> UBSCM 2017-C3 B-Piece Cashflows | B112: =B16 -> UBSCM 2017-C3 | K112: =SUMIF('Combined B-Piece P&I CF'!$A:$A,K$6,INDEX('Combined B-Piece P&I CF'!$BN:$CN,0,MATCH($B112,'Combined B-Piece P&I CF'!$BN$7:$CN$7,0))) -> 0 | L112: =SUMIF('Combined B-Piece P&I CF'!$A:$A,L$6,INDEX('Combined B-Piece P&I CF'!$BN:$CN,0,MATCH($B112,'Combined B-Piece P&I CF'!$BN$7:$CN$7,0))) -> 0 | M112: =SUMIF('Combined B-Piece P&I CF'!$A:$A,M$6,INDEX('Combined B-Piece P&I CF'!$BN:$CN,0,MATCH($B112,'Combined B-Piece P&I CF'!$BN$7:$CN$7,0))) -> 0 | N112: =SUMIF('Combined B-Piece P&I CF'!$A:$A,N$6,INDEX('Combined B-Piece P&I CF'!$BN:$CN,0,MATCH($B112,'Combined B-Piece P&I CF'!$BN$7:$CN$7,0))) -> 0 | O112: =SUMIF('Combined B-Piece P&I CF'!$A:$A,O$6,INDEX('Combined B-Piece P&I CF'!$BN:$CN,0,MATCH($B112,'Combined B-Piece P&I CF'!$BN$7:$CN$7,0))) -> 0 | P112: =SUMIF('Combined B-Piece P&I CF'!$A:$A,P$6,INDEX('Combined B-Piece P&I CF'!$BN:$CN,0,MATCH($B112,'Combined B-Piece P&I CF'!$BN$7:$CN$7,0))) -> 0 | Q112: =SUMIF('Combined B-Piece P&I CF'!$A:$A,Q$6,INDEX('Combined B-Piece P&I CF'!$BN:$CN,0,MATCH($B112,'Combined B-Piece P&I CF'!$BN$7:$CN$7,0))) -> 0 | R112: =SUMIF('Combined B-Piece P&I CF'!$A:$A,R$6,INDEX('Combined B-Piece P&I CF'!$BN:$CN,0,MATCH($B112,'Combined B-Piece P&I CF'!$BN$7:$CN$7,0))) -> 0 | ... GS112: =SUMIF('Combined B-Piece P&I CF'!$A:$A,GS$6,INDEX('Combined B-Piece P&I CF'!$BN:$CN,0,MATCH($B112,'Combined B-Piece P&I CF'!$BN$7:$CN$7,0))) -> 0 | GU112: =SUMIFS($K112:$GS112,$K$5:$GS$5,GU$6) -> 0 | GV112: =SUMIFS($K112:$GS112,$K$5:$GS$5,GV$6) -> 0 | GW112: =SUMIFS($K112:$GS112,$K$5:$GS$5,GW$6) -> 0 | GX112: =SUMIFS($K112:$GS112,$K$5:$GS$5,GX$6) -> 0 | GY112: =SUMIFS($K112:$GS112,$K$5:$GS$5,GY$6) -> 0 | GZ112: =SUMIFS($K112:$GS112,$K$5:$GS$5,GZ$6) -> 0 | HA112: =SUMIFS($K112:$GS112,$K$5:$GS$5,HA$6) -> 0 | HB112: =SUMIFS($K112:$GS112,$K$5:$GS$5,HB$6) -> 0 | ... HJ112: =SUMIFS($K112:$GS112,$K$5:$GS$5,HJ$6) -> 0 | HK112: =SUM(GU112:HJ112) -> 45606980
A113: =A17 -> UBSCM 2017-C5 B-Piece Cashflows | B113: =B17 -> UBSCM 2017-C5 | K113: =SUMIF('Combined B-Piece P&I CF'!$A:$A,K$6,INDEX('Combined B-Piece P&I CF'!$BN:$CN,0,MATCH($B113,'Combined B-Piece P&I CF'!$BN$7:$CN$7,0))) -> 0 | L113: =SUMIF('Combined B-Piece P&I CF'!$A:$A,L$6,INDEX('Combined B-Piece P&I CF'!$BN:$CN,0,MATCH($B113,'Combined B-Piece P&I CF'!$BN$7:$CN$7,0))) -> 0 | M113: =SUMIF('Combined B-Piece P&I CF'!$A:$A,M$6,INDEX('Combined B-Piece P&I CF'!$BN:$CN,0,MATCH($B113,'Combined B-Piece P&I CF'!$BN$7:$CN$7,0))) -> 0 | N113: =SUMIF('Combined B-Piece P&I CF'!$A:$A,N$6,INDEX('Combined B-Piece P&I CF'!$BN:$CN,0,MATCH($B113,'Combined B-Piece P&I CF'!$BN$7:$CN$7,0))) -> 0 | O113: =SUMIF('Combined B-Piece P&I CF'!$A:$A,O$6,INDEX('Combined B-Piece P&I CF'!$BN:$CN,0,MATCH($B113,'Combined B-Piece P&I CF'!$BN$7:$CN$7,0))) -> 0 | P113: =SUMIF('Combined B-Piece P&I CF'!$A:$A,P$6,INDEX('Combined B-Piece P&I CF'!$BN:$CN,0,MATCH($B113,'Combined B-Piece P&I CF'!$BN$7:$CN$7,0))) -> 0 | Q113: =SUMIF('Combined B-Piece P&I CF'!$A:$A,Q$6,INDEX('Combined B-Piece P&I CF'!$BN:$CN,0,MATCH($B113,'Combined B-Piece P&I CF'!$BN$7:$CN$7,0))) -> 0 | R113: =SUMIF('Combined B-Piece P&I CF'!$A:$A,R$6,INDEX('Combined B-Piece P&I CF'!$BN:$CN,0,MATCH($B113,'Combined B-Piece P&I CF'!$BN$7:$CN$7,0))) -> 0 | ... GS113: =SUMIF('Combined B-Piece P&I CF'!$A:$A,GS$6,INDEX('Combined B-Piece P&I CF'!$BN:$CN,0,MATCH($B113,'Combined B-Piece P&I CF'!$BN$7:$CN$7,0))) -> 0 | GU113: =SUMIFS($K113:$GS113,$K$5:$GS$5,GU$6) -> 0 | GV113: =SUMIFS($K113:$GS113,$K$5:$GS$5,GV$6) -> 0 | GW113: =SUMIFS($K113:$GS113,$K$5:$GS$5,GW$6) -> 0 | GX113: =SUMIFS($K113:$GS113,$K$5:$GS$5,GX$6) -> 0 | GY113: =SUMIFS($K113:$GS113,$K$5:$GS$5,GY$6) -> 0 | GZ113: =SUMIFS($K113:$GS113,$K$5:$GS$5,GZ$6) -> 0 | HA113: =SUMIFS($K113:$GS113,$K$5:$GS$5,HA$6) -> 0 | HB113: =SUMIFS($K113:$GS113,$K$5:$GS$5,HB$6) -> 10050324 | ... HJ113: =SUMIFS($K113:$GS113,$K$5:$GS$5,HJ$6) -> 0 | HK113: =SUM(GU113:HJ113) -> 49089406
A114: =A18 -> MSC 2019-H6 B-Piece Cashflows | B114: =B18 -> MSC 2019-H6 | K114: =SUMIF('Combined B-Piece P&I CF'!$A:$A,K$6,INDEX('Combined B-Piece P&I CF'!$BN:$CN,0,MATCH($B114,'Combined B-Piece P&I CF'!$BN$7:$CN$7,0))) -> 0 | L114: =SUMIF('Combined B-Piece P&I CF'!$A:$A,L$6,INDEX('Combined B-Piece P&I CF'!$BN:$CN,0,MATCH($B114,'Combined B-Piece P&I CF'!$BN$7:$CN$7,0))) -> 0 | M114: =SUMIF('Combined B-Piece P&I CF'!$A:$A,M$6,INDEX('Combined B-Piece P&I CF'!$BN:$CN,0,MATCH($B114,'Combined B-Piece P&I CF'!$BN$7:$CN$7,0))) -> 0 | N114: =SUMIF('Combined B-Piece P&I CF'!$A:$A,N$6,INDEX('Combined B-Piece P&I CF'!$BN:$CN,0,MATCH($B114,'Combined B-Piece P&I CF'!$BN$7:$CN$7,0))) -> 0 | O114: =SUMIF('Combined B-Piece P&I CF'!$A:$A,O$6,INDEX('Combined B-Piece P&I CF'!$BN:$CN,0,MATCH($B114,'Combined B-Piece P&I CF'!$BN$7:$CN$7,0))) -> 0 | P114: =SUMIF('Combined B-Piece P&I CF'!$A:$A,P$6,INDEX('Combined B-Piece P&I CF'!$BN:$CN,0,MATCH($B114,'Combined B-Piece P&I CF'!$BN$7:$CN$7,0))) -> 0 | Q114: =SUMIF('Combined B-Piece P&I CF'!$A:$A,Q$6,INDEX('Combined B-Piece P&I CF'!$BN:$CN,0,MATCH($B114,'Combined B-Piece P&I CF'!$BN$7:$CN$7,0))) -> 0 | R114: =SUMIF('Combined B-Piece P&I CF'!$A:$A,R$6,INDEX('Combined B-Piece P&I CF'!$BN:$CN,0,MATCH($B114,'Combined B-Piece P&I CF'!$BN$7:$CN$7,0))) -> 0 | ... GS114: =SUMIF('Combined B-Piece P&I CF'!$A:$A,GS$6,INDEX('Combined B-Piece P&I CF'!$BN:$CN,0,MATCH($B114,'Combined B-Piece P&I CF'!$BN$7:$CN$7,0))) -> 0 | GU114: =SUMIFS($K114:$GS114,$K$5:$GS$5,GU$6) -> 0 | GV114: =SUMIFS($K114:$GS114,$K$5:$GS$5,GV$6) -> 0 | GW114: =SUMIFS($K114:$GS114,$K$5:$GS$5,GW$6) -> 0 | GX114: =SUMIFS($K114:$GS114,$K$5:$GS$5,GX$6) -> 0 | GY114: =SUMIFS($K114:$GS114,$K$5:$GS$5,GY$6) -> 0 | GZ114: =SUMIFS($K114:$GS114,$K$5:$GS$5,GZ$6) -> 0 | HA114: =SUMIFS($K114:$GS114,$K$5:$GS$5,HA$6) -> 0 | HB114: =SUMIFS($K114:$GS114,$K$5:$GS$5,HB$6) -> 8259342 | ... HJ114: =SUMIFS($K114:$GS114,$K$5:$GS$5,HJ$6) -> 0 | HK114: =SUM(GU114:HJ114) -> 24839471
A115: =A19 -> WFCM 2019-C49 B-Piece Cashflows | B115: =B19 -> WFCM 2019-C49 | K115: =SUMIF('Combined B-Piece P&I CF'!$A:$A,K$6,INDEX('Combined B-Piece P&I CF'!$BN:$CN,0,MATCH($B115,'Combined B-Piece P&I CF'!$BN$7:$CN$7,0))) -> 0 | L115: =SUMIF('Combined B-Piece P&I CF'!$A:$A,L$6,INDEX('Combined B-Piece P&I CF'!$BN:$CN,0,MATCH($B115,'Combined B-Piece P&I CF'!$BN$7:$CN$7,0))) -> 0 | M115: =SUMIF('Combined B-Piece P&I CF'!$A:$A,M$6,INDEX('Combined B-Piece P&I CF'!$BN:$CN,0,MATCH($B115,'Combined B-Piece P&I CF'!$BN$7:$CN$7,0))) -> 0 | N115: =SUMIF('Combined B-Piece P&I CF'!$A:$A,N$6,INDEX('Combined B-Piece P&I CF'!$BN:$CN,0,MATCH($B115,'Combined B-Piece P&I CF'!$BN$7:$CN$7,0))) -> 0 | O115: =SUMIF('Combined B-Piece P&I CF'!$A:$A,O$6,INDEX('Combined B-Piece P&I CF'!$BN:$CN,0,MATCH($B115,'Combined B-Piece P&I CF'!$BN$7:$CN$7,0))) -> 0 | P115: =SUMIF('Combined B-Piece P&I CF'!$A:$A,P$6,INDEX('Combined B-Piece P&I CF'!$BN:$CN,0,MATCH($B115,'Combined B-Piece P&I CF'!$BN$7:$CN$7,0))) -> 0 | Q115: =SUMIF('Combined B-Piece P&I CF'!$A:$A,Q$6,INDEX('Combined B-Piece P&I CF'!$BN:$CN,0,MATCH($B115,'Combined B-Piece P&I CF'!$BN$7:$CN$7,0))) -> 0 | R115: =SUMIF('Combined B-Piece P&I CF'!$A:$A,R$6,INDEX('Combined B-Piece P&I CF'!$BN:$CN,0,MATCH($B115,'Combined B-Piece P&I CF'!$BN$7:$CN$7,0))) -> 0 | ... GS115: =SUMIF('Combined B-Piece P&I CF'!$A:$A,GS$6,INDEX('Combined B-Piece P&I CF'!$BN:$CN,0,MATCH($B115,'Combined B-Piece P&I CF'!$BN$7:$CN$7,0))) -> 0 | GU115: =SUMIFS($K115:$GS115,$K$5:$GS$5,GU$6) -> 0 | GV115: =SUMIFS($K115:$GS115,$K$5:$GS$5,GV$6) -> 0 | GW115: =SUMIFS($K115:$GS115,$K$5:$GS$5,GW$6) -> 0 | GX115: =SUMIFS($K115:$GS115,$K$5:$GS$5,GX$6) -> 0 | GY115: =SUMIFS($K115:$GS115,$K$5:$GS$5,GY$6) -> 0 | GZ115: =SUMIFS($K115:$GS115,$K$5:$GS$5,GZ$6) -> 0 | HA115: =SUMIFS($K115:$GS115,$K$5:$GS$5,HA$6) -> 0 | HB115: =SUMIFS($K115:$GS115,$K$5:$GS$5,HB$6) -> 0 | ... HJ115: =SUMIFS($K115:$GS115,$K$5:$GS$5,HJ$6) -> 8927010.2 | HK115: =SUM(GU115:HJ115) -> 46410165
A116: =A20 -> UBSCM 2018-C13 B-Piece Cashflow | B116: =B20 -> UBSCM 2018-C13 | K116: =SUMIF('Combined B-Piece P&I CF'!$A:$A,K$6,INDEX('Combined B-Piece P&I CF'!$BN:$CN,0,MATCH($B116,'Combined B-Piece P&I CF'!$BN$7:$CN$7,0))) -> 0 | L116: =SUMIF('Combined B-Piece P&I CF'!$A:$A,L$6,INDEX('Combined B-Piece P&I CF'!$BN:$CN,0,MATCH($B116,'Combined B-Piece P&I CF'!$BN$7:$CN$7,0))) -> 0 | M116: =SUMIF('Combined B-Piece P&I CF'!$A:$A,M$6,INDEX('Combined B-Piece P&I CF'!$BN:$CN,0,MATCH($B116,'Combined B-Piece P&I CF'!$BN$7:$CN$7,0))) -> 0 | N116: =SUMIF('Combined B-Piece P&I CF'!$A:$A,N$6,INDEX('Combined B-Piece P&I CF'!$BN:$CN,0,MATCH($B116,'Combined B-Piece P&I CF'!$BN$7:$CN$7,0))) -> 0 | O116: =SUMIF('Combined B-Piece P&I CF'!$A:$A,O$6,INDEX('Combined B-Piece P&I CF'!$BN:$CN,0,MATCH($B116,'Combined B-Piece P&I CF'!$BN$7:$CN$7,0))) -> 0 | P116: =SUMIF('Combined B-Piece P&I CF'!$A:$A,P$6,INDEX('Combined B-Piece P&I CF'!$BN:$CN,0,MATCH($B116,'Combined B-Piece P&I CF'!$BN$7:$CN$7,0))) -> 0 | Q116: =SUMIF('Combined B-Piece P&I CF'!$A:$A,Q$6,INDEX('Combined B-Piece P&I CF'!$BN:$CN,0,MATCH($B116,'Combined B-Piece P&I CF'!$BN$7:$CN$7,0))) -> 0 | R116: =SUMIF('Combined B-Piece P&I CF'!$A:$A,R$6,INDEX('Combined B-Piece P&I CF'!$BN:$CN,0,MATCH($B116,'Combined B-Piece P&I CF'!$BN$7:$CN$7,0))) -> 0 | ... GS116: =SUMIF('Combined B-Piece P&I CF'!$A:$A,GS$6,INDEX('Combined B-Piece P&I CF'!$BN:$CN,0,MATCH($B116,'Combined B-Piece P&I CF'!$BN$7:$CN$7,0))) -> 0 | GU116: =SUMIFS($K116:$GS116,$K$5:$GS$5,GU$6) -> 0 | GV116: =SUMIFS($K116:$GS116,$K$5:$GS$5,GV$6) -> 0 | GW116: =SUMIFS($K116:$GS116,$K$5:$GS$5,GW$6) -> 0 | GX116: =SUMIFS($K116:$GS116,$K$5:$GS$5,GX$6) -> 0 | GY116: =SUMIFS($K116:$GS116,$K$5:$GS$5,GY$6) -> 0 | GZ116: =SUMIFS($K116:$GS116,$K$5:$GS$5,GZ$6) -> 0 | HA116: =SUMIFS($K116:$GS116,$K$5:$GS$5,HA$6) -> 0 | HB116: =SUMIFS($K116:$GS116,$K$5:$GS$5,HB$6) -> 0 | ... HJ116: =SUMIFS($K116:$GS116,$K$5:$GS$5,HJ$6) -> 0 | HK116: =SUM(GU116:HJ116) -> 39390280
... A131: =A35 -> CD 2017-CD3 B-Piece Hist Cashfl | B131: =B35 -> CD 2017-CD3 | K131: =SUMIF('Combined B-Piece P&I CF'!$A:$A,K$6,INDEX('Combined B-Piece P&I CF'!$BN:$CN,0,MATCH($B131,'Combined B-Piece P&I CF'!$BN$7:$CN$7,0))) -> 0 | L131: =SUMIF('Combined B-Piece P&I CF'!$A:$A,L$6,INDEX('Combined B-Piece P&I CF'!$BN:$CN,0,MATCH($B131,'Combined B-Piece P&I CF'!$BN$7:$CN$7,0))) -> 0 | M131: =SUMIF('Combined B-Piece P&I CF'!$A:$A,M$6,INDEX('Combined B-Piece P&I CF'!$BN:$CN,0,MATCH($B131,'Combined B-Piece P&I CF'!$BN$7:$CN$7,0))) -> 0 | N131: =SUMIF('Combined B-Piece P&I CF'!$A:$A,N$6,INDEX('Combined B-Piece P&I CF'!$BN:$CN,0,MATCH($B131,'Combined B-Piece P&I CF'!$BN$7:$CN$7,0))) -> 0 | O131: =SUMIF('Combined B-Piece P&I CF'!$A:$A,O$6,INDEX('Combined B-Piece P&I CF'!$BN:$CN,0,MATCH($B131,'Combined B-Piece P&I CF'!$BN$7:$CN$7,0))) -> 0 | P131: =SUMIF('Combined B-Piece P&I CF'!$A:$A,P$6,INDEX('Combined B-Piece P&I CF'!$BN:$CN,0,MATCH($B131,'Combined B-Piece P&I CF'!$BN$7:$CN$7,0))) -> 0 | Q131: =SUMIF('Combined B-Piece P&I CF'!$A:$A,Q$6,INDEX('Combined B-Piece P&I CF'!$BN:$CN,0,MATCH($B131,'Combined B-Piece P&I CF'!$BN$7:$CN$7,0))) -> 0 | R131: =SUMIF('Combined B-Piece P&I CF'!$A:$A,R$6,INDEX('Combined B-Piece P&I CF'!$BN:$CN,0,MATCH($B131,'Combined B-Piece P&I CF'!$BN$7:$CN$7,0))) -> 0 | ... GS131: =SUMIF('Combined B-Piece P&I CF'!$A:$A,GS$6,INDEX('Combined B-Piece P&I CF'!$BN:$CN,0,MATCH($B131,'Combined B-Piece P&I CF'!$BN$7:$CN$7,0))) -> 0 | GU131: =SUMIFS($K131:$GS131,$K$5:$GS$5,GU$6) -> 0 | GV131: =SUMIFS($K131:$GS131,$K$5:$GS$5,GV$6) -> 0 | GW131: =SUMIFS($K131:$GS131,$K$5:$GS$5,GW$6) -> 0 | GX131: =SUMIFS($K131:$GS131,$K$5:$GS$5,GX$6) -> 0 | GY131: =SUMIFS($K131:$GS131,$K$5:$GS$5,GY$6) -> 0 | GZ131: =SUMIFS($K131:$GS131,$K$5:$GS$5,GZ$6) -> 0 | HA131: =SUMIFS($K131:$GS131,$K$5:$GS$5,HA$6) -> 0 | HB131: =SUMIFS($K131:$GS131,$K$5:$GS$5,HB$6) -> 0 | ... HJ131: =SUMIFS($K131:$GS131,$K$5:$GS$5,HJ$6) -> 0 | HK131: =SUM(GU131:HJ131) -> 110692959
B133: Total | K133: =SUM(K104:K132) -> 0 | L133: =SUM(L104:L132) -> 0 | M133: =SUM(M104:M132) -> 0 | N133: =SUM(N104:N132) -> 0 | O133: =SUM(O104:O132) -> 0 | P133: =SUM(P104:P132) -> 0 | Q133: =SUM(Q104:Q132) -> 0 | R133: =SUM(R104:R132) -> 0 | ... GS133: =SUM(GS104:GS132) -> 0 | GU133: =SUMIFS($K133:$GS133,$K$5:$GS$5,GU$6) -> 0 | GV133: =SUMIFS($K133:$GS133,$K$5:$GS$5,GV$6) -> 0 | GW133: =SUMIFS($K133:$GS133,$K$5:$GS$5,GW$6) -> 0 | GX133: =SUMIFS($K133:$GS133,$K$5:$GS$5,GX$6) -> 3239452.4 | GY133: =SUMIFS($K133:$GS133,$K$5:$GS$5,GY$6) -> 44663.75 | GZ133: =SUMIFS($K133:$GS133,$K$5:$GS$5,GZ$6) -> 10640139 | HA133: =SUMIFS($K133:$GS133,$K$5:$GS$5,HA$6) -> -600672.63 | HB133: =SUMIFS($K133:$GS133,$K$5:$GS$5,HB$6) -> 48610522 | ... HJ133: =SUMIFS($K133:$GS133,$K$5:$GS$5,HJ$6) -> 23658855 | HK133: =SUM(GU133:HJ133) -> 1.5607676e+09
B135: Remaining Principal | D135: Face Acquired
B137: =B9 -> UBSCM 2017-C2 | D137: =D9 -> 94272591 | K137: =IF(K$6=$C9,$D137,IF(SUM(L9:$GS9)=0,0,MAX(J137-K73-K105,0))) -> 0 | L137: =IF(L$6=$C9,$D137,IF(SUM(M9:$GS9)=0,0,MAX(K137-L73-L105,0))) -> 0 | M137: =IF(M$6=$C9,$D137,IF(SUM(N9:$GS9)=0,0,MAX(L137-M73-M105,0))) -> 0 | N137: =IF(N$6=$C9,$D137,IF(SUM(O9:$GS9)=0,0,MAX(M137-N73-N105,0))) -> 0 | O137: =IF(O$6=$C9,$D137,IF(SUM(P9:$GS9)=0,0,MAX(N137-O73-O105,0))) -> 0 | P137: =IF(P$6=$C9,$D137,IF(SUM(Q9:$GS9)=0,0,MAX(O137-P73-P105,0))) -> 0 | Q137: =IF(Q$6=$C9,$D137,IF(SUM(R9:$GS9)=0,0,MAX(P137-Q73-Q105,0))) -> 94272591 | R137: =IF(R$6=$C9,$D137,IF(SUM(S9:$GS9)=0,0,MAX(Q137-R73-R105,0))) -> 94272591 | ... GR137: =IF(GR$6=$C9,$D137,IF(SUM(GS9:$GS9)=0,0,MAX(GQ137-GR73-GR105,0))) -> 0 | GS137: =IF(GS$6=$C9,$D137,IF(SUM($GS9:GT9)=0,0,MAX(GR137-GS73-GS105,0))) -> 0
B138: =B10 -> CGCMT 2017-C4 | D138: =D10 -> 105034893 | K138: =IF(K$6=$C10,$D138,IF(SUM(L10:$GS10)=0,0,MAX(J138-K74-K106,0))) -> 0 | L138: =IF(L$6=$C10,$D138,IF(SUM(M10:$GS10)=0,0,MAX(K138-L74-L106,0))) -> 0 | M138: =IF(M$6=$C10,$D138,IF(SUM(N10:$GS10)=0,0,MAX(L138-M74-M106,0))) -> 0 | N138: =IF(N$6=$C10,$D138,IF(SUM(O10:$GS10)=0,0,MAX(M138-N74-N106,0))) -> 0 | O138: =IF(O$6=$C10,$D138,IF(SUM(P10:$GS10)=0,0,MAX(N138-O74-O106,0))) -> 0 | P138: =IF(P$6=$C10,$D138,IF(SUM(Q10:$GS10)=0,0,MAX(O138-P74-P106,0))) -> 0 | Q138: =IF(Q$6=$C10,$D138,IF(SUM(R10:$GS10)=0,0,MAX(P138-Q74-Q106,0))) -> 0 | R138: =IF(R$6=$C10,$D138,IF(SUM(S10:$GS10)=0,0,MAX(Q138-R74-R106,0))) -> 0 | ... GR138: =IF(GR$6=$C10,$D138,IF(SUM(GS10:$GS10)=0,0,MAX(GQ138-GR74-GR106,0))) -> 0 | GS138: =IF(GS$6=$C10,$D138,IF(SUM($GS10:GT10)=0,0,MAX(GR138-GS74-GS106,0))) -> 0
B139: =B11 -> WFCM 2018-C47 | D139: =D11 -> 93057654 | K139: =IF(K$6=$C11,$D139,IF(SUM(L11:$GS11)=0,0,MAX(J139-K75-K107,0))) -> 0 | L139: =IF(L$6=$C11,$D139,IF(SUM(M11:$GS11)=0,0,MAX(K139-L75-L107,0))) -> 0 | M139: =IF(M$6=$C11,$D139,IF(SUM(N11:$GS11)=0,0,MAX(L139-M75-M107,0))) -> 0 | N139: =IF(N$6=$C11,$D139,IF(SUM(O11:$GS11)=0,0,MAX(M139-N75-N107,0))) -> 0 | O139: =IF(O$6=$C11,$D139,IF(SUM(P11:$GS11)=0,0,MAX(N139-O75-O107,0))) -> 0 | P139: =IF(P$6=$C11,$D139,IF(SUM(Q11:$GS11)=0,0,MAX(O139-P75-P107,0))) -> 0 | Q139: =IF(Q$6=$C11,$D139,IF(SUM(R11:$GS11)=0,0,MAX(P139-Q75-Q107,0))) -> 0 | R139: =IF(R$6=$C11,$D139,IF(SUM(S11:$GS11)=0,0,MAX(Q139-R75-R107,0))) -> 0 | ... GR139: =IF(GR$6=$C11,$D139,IF(SUM(GS11:$GS11)=0,0,MAX(GQ139-GR75-GR107,0))) -> 0 | GS139: =IF(GS$6=$C11,$D139,IF(SUM($GS11:GT11)=0,0,MAX(GR139-GS75-GS107,0))) -> 0
B140: =B12 -> BBCMS 2019-C3 | D140: =D12 -> 95220542 | K140: =IF(K$6=$C12,$D140,IF(SUM(L12:$GS12)=0,0,MAX(J140-K76-K108,0))) -> 0 | L140: =IF(L$6=$C12,$D140,IF(SUM(M12:$GS12)=0,0,MAX(K140-L76-L108,0))) -> 0 | M140: =IF(M$6=$C12,$D140,IF(SUM(N12:$GS12)=0,0,MAX(L140-M76-M108,0))) -> 0 | N140: =IF(N$6=$C12,$D140,IF(SUM(O12:$GS12)=0,0,MAX(M140-N76-N108,0))) -> 0 | O140: =IF(O$6=$C12,$D140,IF(SUM(P12:$GS12)=0,0,MAX(N140-O76-O108,0))) -> 0 | P140: =IF(P$6=$C12,$D140,IF(SUM(Q12:$GS12)=0,0,MAX(O140-P76-P108,0))) -> 0 | Q140: =IF(Q$6=$C12,$D140,IF(SUM(R12:$GS12)=0,0,MAX(P140-Q76-Q108,0))) -> 0 | R140: =IF(R$6=$C12,$D140,IF(SUM(S12:$GS12)=0,0,MAX(Q140-R76-R108,0))) -> 0 | ... GR140: =IF(GR$6=$C12,$D140,IF(SUM(GS12:$GS12)=0,0,MAX(GQ140-GR76-GR108,0))) -> 0 | GS140: =IF(GS$6=$C12,$D140,IF(SUM($GS12:GT12)=0,0,MAX(GR140-GS76-GS108,0))) -> 0
B141: =B13 -> GSMS 2019-GC38 | D141: =D13 -> 73640365 | K141: =IF(K$6=$C13,$D141,IF(SUM(L13:$GS13)=0,0,MAX(J141-K77-K109,0))) -> 0 | L141: =IF(L$6=$C13,$D141,IF(SUM(M13:$GS13)=0,0,MAX(K141-L77-L109,0))) -> 0 | M141: =IF(M$6=$C13,$D141,IF(SUM(N13:$GS13)=0,0,MAX(L141-M77-M109,0))) -> 0 | N141: =IF(N$6=$C13,$D141,IF(SUM(O13:$GS13)=0,0,MAX(M141-N77-N109,0))) -> 0 | O141: =IF(O$6=$C13,$D141,IF(SUM(P13:$GS13)=0,0,MAX(N141-O77-O109,0))) -> 0 | P141: =IF(P$6=$C13,$D141,IF(SUM(Q13:$GS13)=0,0,MAX(O141-P77-P109,0))) -> 0 | Q141: =IF(Q$6=$C13,$D141,IF(SUM(R13:$GS13)=0,0,MAX(P141-Q77-Q109,0))) -> 0 | R141: =IF(R$6=$C13,$D141,IF(SUM(S13:$GS13)=0,0,MAX(Q141-R77-R109,0))) -> 0 | ... GR141: =IF(GR$6=$C13,$D141,IF(SUM(GS13:$GS13)=0,0,MAX(GQ141-GR77-GR109,0))) -> 0 | GS141: =IF(GS$6=$C13,$D141,IF(SUM($GS13:GT13)=0,0,MAX(GR141-GS77-GS109,0))) -> 0
B142: =B14 -> GSMS 2017-GS8 | D142: =D14 -> 106223386 | K142: =IF(K$6=$C14,$D142,IF(SUM(L14:$GS14)=0,0,MAX(J142-K78-K110,0))) -> 0 | L142: =IF(L$6=$C14,$D142,IF(SUM(M14:$GS14)=0,0,MAX(K142-L78-L110,0))) -> 0 | M142: =IF(M$6=$C14,$D142,IF(SUM(N14:$GS14)=0,0,MAX(L142-M78-M110,0))) -> 0 | N142: =IF(N$6=$C14,$D142,IF(SUM(O14:$GS14)=0,0,MAX(M142-N78-N110,0))) -> 0 | O142: =IF(O$6=$C14,$D142,IF(SUM(P14:$GS14)=0,0,MAX(N142-O78-O110,0))) -> 0 | P142: =IF(P$6=$C14,$D142,IF(SUM(Q14:$GS14)=0,0,MAX(O142-P78-P110,0))) -> 0 | Q142: =IF(Q$6=$C14,$D142,IF(SUM(R14:$GS14)=0,0,MAX(P142-Q78-Q110,0))) -> 0 | R142: =IF(R$6=$C14,$D142,IF(SUM(S14:$GS14)=0,0,MAX(Q142-R78-R110,0))) -> 0 | ... GR142: =IF(GR$6=$C14,$D142,IF(SUM(GS14:$GS14)=0,0,MAX(GQ142-GR78-GR110,0))) -> 0 | GS142: =IF(GS$6=$C14,$D142,IF(SUM($GS14:GT14)=0,0,MAX(GR142-GS78-GS110,0))) -> 0
B143: =B15 -> UBSCM 2018-C8 | D143: =D15 -> 107046891 | K143: =IF(K$6=$C15,$D143,IF(SUM(L15:$GS15)=0,0,MAX(J143-K79-K111,0))) -> 0 | L143: =IF(L$6=$C15,$D143,IF(SUM(M15:$GS15)=0,0,MAX(K143-L79-L111,0))) -> 0 | M143: =IF(M$6=$C15,$D143,IF(SUM(N15:$GS15)=0,0,MAX(L143-M79-M111,0))) -> 0 | N143: =IF(N$6=$C15,$D143,IF(SUM(O15:$GS15)=0,0,MAX(M143-N79-N111,0))) -> 0 | O143: =IF(O$6=$C15,$D143,IF(SUM(P15:$GS15)=0,0,MAX(N143-O79-O111,0))) -> 0 | P143: =IF(P$6=$C15,$D143,IF(SUM(Q15:$GS15)=0,0,MAX(O143-P79-P111,0))) -> 0 | Q143: =IF(Q$6=$C15,$D143,IF(SUM(R15:$GS15)=0,0,MAX(P143-Q79-Q111,0))) -> 0 | R143: =IF(R$6=$C15,$D143,IF(SUM(S15:$GS15)=0,0,MAX(Q143-R79-R111,0))) -> 0 | ... GR143: =IF(GR$6=$C15,$D143,IF(SUM(GS15:$GS15)=0,0,MAX(GQ143-GR79-GR111,0))) -> 0 | GS143: =IF(GS$6=$C15,$D143,IF(SUM($GS15:GT15)=0,0,MAX(GR143-GS79-GS111,0))) -> 0
B144: =B16 -> UBSCM 2017-C3 | D144: =D16 -> 77063195 | K144: =IF(K$6=$C16,$D144,IF(SUM(L16:$GS16)=0,0,MAX(J144-K80-K112,0))) -> 0 | L144: =IF(L$6=$C16,$D144,IF(SUM(M16:$GS16)=0,0,MAX(K144-L80-L112,0))) -> 0 | M144: =IF(M$6=$C16,$D144,IF(SUM(N16:$GS16)=0,0,MAX(L144-M80-M112,0))) -> 0 | N144: =IF(N$6=$C16,$D144,IF(SUM(O16:$GS16)=0,0,MAX(M144-N80-N112,0))) -> 0 | O144: =IF(O$6=$C16,$D144,IF(SUM(P16:$GS16)=0,0,MAX(N144-O80-O112,0))) -> 0 | P144: =IF(P$6=$C16,$D144,IF(SUM(Q16:$GS16)=0,0,MAX(O144-P80-P112,0))) -> 0 | Q144: =IF(Q$6=$C16,$D144,IF(SUM(R16:$GS16)=0,0,MAX(P144-Q80-Q112,0))) -> 77063195 | R144: =IF(R$6=$C16,$D144,IF(SUM(S16:$GS16)=0,0,MAX(Q144-R80-R112,0))) -> 77063195 | ... GR144: =IF(GR$6=$C16,$D144,IF(SUM(GS16:$GS16)=0,0,MAX(GQ144-GR80-GR112,0))) -> 0 | GS144: =IF(GS$6=$C16,$D144,IF(SUM($GS16:GT16)=0,0,MAX(GR144-GS80-GS112,0))) -> 0
B145: =B17 -> UBSCM 2017-C5 | D145: =D17 -> 78392651 | K145: =IF(K$6=$C17,$D145,IF(SUM(L17:$GS17)=0,0,MAX(J145-K81-K113,0))) -> 0 | L145: =IF(L$6=$C17,$D145,IF(SUM(M17:$GS17)=0,0,MAX(K145-L81-L113,0))) -> 0 | M145: =IF(M$6=$C17,$D145,IF(SUM(N17:$GS17)=0,0,MAX(L145-M81-M113,0))) -> 0 | N145: =IF(N$6=$C17,$D145,IF(SUM(O17:$GS17)=0,0,MAX(M145-N81-N113,0))) -> 0 | O145: =IF(O$6=$C17,$D145,IF(SUM(P17:$GS17)=0,0,MAX(N145-O81-O113,0))) -> 0 | P145: =IF(P$6=$C17,$D145,IF(SUM(Q17:$GS17)=0,0,MAX(O145-P81-P113,0))) -> 0 | Q145: =IF(Q$6=$C17,$D145,IF(SUM(R17:$GS17)=0,0,MAX(P145-Q81-Q113,0))) -> 0 | R145: =IF(R$6=$C17,$D145,IF(SUM(S17:$GS17)=0,0,MAX(Q145-R81-R113,0))) -> 0 | ... GR145: =IF(GR$6=$C17,$D145,IF(SUM(GS17:$GS17)=0,0,MAX(GQ145-GR81-GR113,0))) -> 0 | GS145: =IF(GS$6=$C17,$D145,IF(SUM($GS17:GT17)=0,0,MAX(GR145-GS81-GS113,0))) -> 0
B146: =B18 -> MSC 2019-H6 | D146: =D18 -> 70915759 | K146: =IF(K$6=$C18,$D146,IF(SUM(L18:$GS18)=0,0,MAX(J146-K82-K114,0))) -> 0 | L146: =IF(L$6=$C18,$D146,IF(SUM(M18:$GS18)=0,0,MAX(K146-L82-L114,0))) -> 0 | M146: =IF(M$6=$C18,$D146,IF(SUM(N18:$GS18)=0,0,MAX(L146-M82-M114,0))) -> 0 | N146: =IF(N$6=$C18,$D146,IF(SUM(O18:$GS18)=0,0,MAX(M146-N82-N114,0))) -> 0 | O146: =IF(O$6=$C18,$D146,IF(SUM(P18:$GS18)=0,0,MAX(N146-O82-O114,0))) -> 0 | P146: =IF(P$6=$C18,$D146,IF(SUM(Q18:$GS18)=0,0,MAX(O146-P82-P114,0))) -> 0 | Q146: =IF(Q$6=$C18,$D146,IF(SUM(R18:$GS18)=0,0,MAX(P146-Q82-Q114,0))) -> 0 | R146: =IF(R$6=$C18,$D146,IF(SUM(S18:$GS18)=0,0,MAX(Q146-R82-R114,0))) -> 0 | ... GR146: =IF(GR$6=$C18,$D146,IF(SUM(GS18:$GS18)=0,0,MAX(GQ146-GR82-GR114,0))) -> 0 | GS146: =IF(GS$6=$C18,$D146,IF(SUM($GS18:GT18)=0,0,MAX(GR146-GS82-GS114,0))) -> 0
B147: =B19 -> WFCM 2019-C49 | D147: =D19 -> 80442767 | K147: =IF(K$6=$C19,$D147,IF(SUM(L19:$GS19)=0,0,MAX(J147-K83-K115,0))) -> 0 | L147: =IF(L$6=$C19,$D147,IF(SUM(M19:$GS19)=0,0,MAX(K147-L83-L115,0))) -> 0 | M147: =IF(M$6=$C19,$D147,IF(SUM(N19:$GS19)=0,0,MAX(L147-M83-M115,0))) -> 0 | N147: =IF(N$6=$C19,$D147,IF(SUM(O19:$GS19)=0,0,MAX(M147-N83-N115,0))) -> 0 | O147: =IF(O$6=$C19,$D147,IF(SUM(P19:$GS19)=0,0,MAX(N147-O83-O115,0))) -> 0 | P147: =IF(P$6=$C19,$D147,IF(SUM(Q19:$GS19)=0,0,MAX(O147-P83-P115,0))) -> 0 | Q147: =IF(Q$6=$C19,$D147,IF(SUM(R19:$GS19)=0,0,MAX(P147-Q83-Q115,0))) -> 0 | R147: =IF(R$6=$C19,$D147,IF(SUM(S19:$GS19)=0,0,MAX(Q147-R83-R115,0))) -> 0 | ... GR147: =IF(GR$6=$C19,$D147,IF(SUM(GS19:$GS19)=0,0,MAX(GQ147-GR83-GR115,0))) -> 0 | GS147: =IF(GS$6=$C19,$D147,IF(SUM($GS19:GT19)=0,0,MAX(GR147-GS83-GS115,0))) -> 0
B148: =B20 -> UBSCM 2018-C13 | D148: =D20 -> 69344367 | K148: =IF(K$6=$C20,$D148,IF(SUM(L20:$GS20)=0,0,MAX(J148-K84-K116,0))) -> 0 | L148: =IF(L$6=$C20,$D148,IF(SUM(M20:$GS20)=0,0,MAX(K148-L84-L116,0))) -> 0 | M148: =IF(M$6=$C20,$D148,IF(SUM(N20:$GS20)=0,0,MAX(L148-M84-M116,0))) -> 0 | N148: =IF(N$6=$C20,$D148,IF(SUM(O20:$GS20)=0,0,MAX(M148-N84-N116,0))) -> 0 | O148: =IF(O$6=$C20,$D148,IF(SUM(P20:$GS20)=0,0,MAX(N148-O84-O116,0))) -> 0 | P148: =IF(P$6=$C20,$D148,IF(SUM(Q20:$GS20)=0,0,MAX(O148-P84-P116,0))) -> 0 | Q148: =IF(Q$6=$C20,$D148,IF(SUM(R20:$GS20)=0,0,MAX(P148-Q84-Q116,0))) -> 0 | R148: =IF(R$6=$C20,$D148,IF(SUM(S20:$GS20)=0,0,MAX(Q148-R84-R116,0))) -> 0 | ... GR148: =IF(GR$6=$C20,$D148,IF(SUM(GS20:$GS20)=0,0,MAX(GQ148-GR84-GR116,0))) -> 0 | GS148: =IF(GS$6=$C20,$D148,IF(SUM($GS20:GT20)=0,0,MAX(GR148-GS84-GS116,0))) -> 0
... B163: =B35 -> CD 2017-CD3 | D163: =D35 -> 110692959 | K163: =IF(K$6=$C35,$D163,IF(SUM(L35:$GS35)=0,0,MAX(J163-K99-K131,0))) -> 110692959 | L163: =IF(L$6=$C35,$D163,IF(SUM(M35:$GS35)=0,0,MAX(K163-L99-L131,0))) -> 110692959 | M163: =IF(M$6=$C35,$D163,IF(SUM(N35:$GS35)=0,0,MAX(L163-M99-M131,0))) -> 110692959 | N163: =IF(N$6=$C35,$D163,IF(SUM(O35:$GS35)=0,0,MAX(M163-N99-N131,0))) -> 110692959 | O163: =IF(O$6=$C35,$D163,IF(SUM(P35:$GS35)=0,0,MAX(N163-O99-O131,0))) -> 110692959 | P163: =IF(P$6=$C35,$D163,IF(SUM(Q35:$GS35)=0,0,MAX(O163-P99-P131,0))) -> 110692959 | Q163: =IF(Q$6=$C35,$D163,IF(SUM(R35:$GS35)=0,0,MAX(P163-Q99-Q131,0))) -> 110692959 | R163: =IF(R$6=$C35,$D163,IF(SUM(S35:$GS35)=0,0,MAX(Q163-R99-R131,0))) -> 110692959 | ... GR163: =IF(GR$6=$C35,$D163,IF(SUM(GS35:$GS35)=0,0,MAX(GQ163-GR99-GR131,0))) -> 0 | GS163: =IF(GS$6=$C35,$D163,IF(SUM($GS35:GT35)=0,0,MAX(GR163-GS99-GS131,0))) -> 0
B165: Total | D165: =SUM(D136:D164) -> 2.1059857e+09 | K165: =SUM(K136:K164) -> 110692959 | L165: =SUM(L136:L164) -> 110692959 | M165: =SUM(M136:M164) -> 110692959 | N165: =SUM(N136:N164) -> 220610186 | O165: =SUM(O136:O164) -> 345582968 | P165: =SUM(P136:P164) -> 345582968 | Q165: =SUM(Q136:Q164) -> 516918754 | R165: =SUM(R136:R164) -> 516918754 | ... GS165: =SUM(GS136:GS164) -> 0
B167: Contributions | G167: =SUMIFS($K167:$GS167,$K$6:$GS$6,"<="&$G$2) -> -1.0078375e+09 | K167: =K69 -> -43347451 | L167: =L69 -> 0 | M167: =M69 -> 0 | N167: =N69 -> -45186561 | O167: =O69 -> -49225235 | P167: =P69 -> 0 | Q167: =Q69 -> -84968513 | R167: =R69 -> 0 | ... GS167: =GS69 -> 0 | GU167: =SUMIFS($K167:$GS167,$K$5:$GS$5,GU$6) -> -4.2527688e+08 | GV167: =SUMIFS($K167:$GS167,$K$5:$GS$5,GV$6) -> -3.8022976e+08 | GW167: =SUMIFS($K167:$GS167,$K$5:$GS$5,GW$6) -> -2.0233087e+08 | GX167: =SUMIFS($K167:$GS167,$K$5:$GS$5,GX$6) -> 0 | GY167: =SUMIFS($K167:$GS167,$K$5:$GS$5,GY$6) -> 0 | GZ167: =SUMIFS($K167:$GS167,$K$5:$GS$5,GZ$6) -> 0 | HA167: =SUMIFS($K167:$GS167,$K$5:$GS$5,HA$6) -> 0 | HB167: =SUMIFS($K167:$GS167,$K$5:$GS$5,HB$6) -> 0 | ... HJ167: =SUMIFS($K167:$GS167,$K$5:$GS$5,HJ$6) -> 0 | HK167: =SUM(GU167:HJ167) -> -1.0078375e+09
B169: Interest Collections | G169: =SUMIFS($K169:$GS169,$K$6:$GS$6,"<="&$G$2) -> 7.486876e+08 | K169: =K171-K170 -> 0 | L169: =L171-L170 -> 420938.93 | M169: =M171-M170 -> 434961.51 | N169: =N171-N170 -> 420924.57 | O169: =O171-O170 -> 452313.4 | P169: =P171-P170 -> 1308032.3 | Q169: =Q171-Q170 -> 1352307.2 | R169: =R171-R170 -> 1996791.5 | ... GS169: =GS171-GS170 -> 0 | GU169: =SUMIFS($K169:$GS169,$K$5:$GS$5,GU$6) -> 14464429 | GV169: =SUMIFS($K169:$GS169,$K$5:$GS$5,GV$6) -> 55477523 | GW169: =SUMIFS($K169:$GS169,$K$5:$GS$5,GW$6) -> 92133444 | GX169: =SUMIFS($K169:$GS169,$K$5:$GS$5,GX$6) -> 96447721 | GY169: =SUMIFS($K169:$GS169,$K$5:$GS$5,GY$6) -> 92127051 | GZ169: =SUMIFS($K169:$GS169,$K$5:$GS$5,GZ$6) -> 94729508 | HA169: =SUMIFS($K169:$GS169,$K$5:$GS$5,HA$6) -> 91916222 | HB169: =SUMIFS($K169:$GS169,$K$5:$GS$5,HB$6) -> 86688186 | ... HJ169: =SUMIFS($K169:$GS169,$K$5:$GS$5,HJ$6) -> 2732762.4 | HK169: =SUM(GU169:HJ169) -> 9.5444821e+08
B170: Principal Collections | G170: =SUMIFS($K170:$GS170,$K$6:$GS$6,"<="&$G$2) -> 0 | K170: =K101 -> 0 | L170: =L101 -> 0 | M170: =M101 -> 0 | N170: =N101 -> 0 | O170: =O101 -> 0 | P170: =P101 -> 0 | Q170: =Q101 -> 0 | R170: =R101 -> 0 | ... GS170: =GS101 -> 0 | GU170: =SUMIFS($K170:$GS170,$K$5:$GS$5,GU$6) -> 0 | GV170: =SUMIFS($K170:$GS170,$K$5:$GS$5,GV$6) -> 0 | GW170: =SUMIFS($K170:$GS170,$K$5:$GS$5,GW$6) -> 0 | GX170: =SUMIFS($K170:$GS170,$K$5:$GS$5,GX$6) -> 0 | GY170: =SUMIFS($K170:$GS170,$K$5:$GS$5,GY$6) -> 0 | GZ170: =SUMIFS($K170:$GS170,$K$5:$GS$5,GZ$6) -> 0 | HA170: =SUMIFS($K170:$GS170,$K$5:$GS$5,HA$6) -> 0 | HB170: =SUMIFS($K170:$GS170,$K$5:$GS$5,HB$6) -> 0 | ... HJ170: =SUMIFS($K170:$GS170,$K$5:$GS$5,HJ$6) -> 77415817 | HK170: =SUM(GU170:HJ170) -> 5.7529438e+08
B171: Gross Distributions | G171: =SUMIFS($K171:$GS171,$K$6:$GS$6,"<="&$G$2) -> 7.486876e+08 | H171: =G171/-G167 -> 0.74286538 | K171: =K173-K167 -> 0 | L171: =L173-L167 -> 420938.93 | M171: =M173-M167 -> 434961.51 | N171: =N173-N167 -> 420924.57 | O171: =O173-O167 -> 452313.4 | P171: =P173-P167 -> 1308032.3 | Q171: =Q173-Q167 -> 1352307.2 | R171: =R173-R167 -> 1996791.5 | ... GS171: =GS173-GS167 -> 0 | GU171: =SUMIFS($K171:$GS171,$K$5:$GS$5,GU$6) -> 14464429 | GV171: =SUMIFS($K171:$GS171,$K$5:$GS$5,GV$6) -> 55477523 | GW171: =SUMIFS($K171:$GS171,$K$5:$GS$5,GW$6) -> 92133444 | GX171: =SUMIFS($K171:$GS171,$K$5:$GS$5,GX$6) -> 96447721 | GY171: =SUMIFS($K171:$GS171,$K$5:$GS$5,GY$6) -> 92127051 | GZ171: =SUMIFS($K171:$GS171,$K$5:$GS$5,GZ$6) -> 94729508 | HA171: =SUMIFS($K171:$GS171,$K$5:$GS$5,HA$6) -> 91916222 | HB171: =SUMIFS($K171:$GS171,$K$5:$GS$5,HB$6) -> 86688186 | ... HJ171: =SUMIFS($K171:$GS171,$K$5:$GS$5,HJ$6) -> 80148580 | HK171: =SUM(GU171:HJ171) -> 1.5297426e+09
B173: Gross B-Piece Cash Flows | C173: =C37 -> 42794 | G173: =SUMIFS($K173:$GS173,$K$6:$GS$6,"<="&$G$2) -> -2.5914992e+08 | H173: =IFERROR(XIRR(OFFSET($J173,0,MATCH($C173,$K$6:$GS$6,0)):$GS173,OFFSET($J$6,0,MATCH($C173,$K$6:$GS$6,0)):$GS$6),"N/A") -> 0.057775828 | I173: =-HK171/G167 -> 1.5178464 | K173: =K37 -> -43347451 | L173: =L37 -> 420938.93 | M173: =M37 -> 434961.51 | N173: =N37 -> -44765636 | O173: =O37 -> -48772922 | P173: =P37 -> 1308032.3 | Q173: =Q37 -> -83616206 | R173: =R37 -> 1996791.5 | ... GS173: =GS37 -> 0 | GU173: =SUMIFS($K173:$GS173,$K$5:$GS$5,GU$6) -> -4.1081245e+08 | GV173: =SUMIFS($K173:$GS173,$K$5:$GS$5,GV$6) -> -3.2475224e+08 | GW173: =SUMIFS($K173:$GS173,$K$5:$GS$5,GW$6) -> -1.1019743e+08 | GX173: =SUMIFS($K173:$GS173,$K$5:$GS$5,GX$6) -> 96447721 | GY173: =SUMIFS($K173:$GS173,$K$5:$GS$5,GY$6) -> 92127051 | GZ173: =SUMIFS($K173:$GS173,$K$5:$GS$5,GZ$6) -> 94729508 | HA173: =SUMIFS($K173:$GS173,$K$5:$GS$5,HA$6) -> 91916222 | HB173: =SUMIFS($K173:$GS173,$K$5:$GS$5,HB$6) -> 86688186 | ... HJ173: =SUMIFS($K173:$GS173,$K$5:$GS$5,HJ$6) -> 80148580 | HK173: =SUM(GU173:HJ173) -> 5.2190507e+08
B175: Projected Fee Basis | F175: Purch Proceeds
A177: =A9 -> UBSCM 2017-C2 B-Piece Cashflows | B177: =B9 -> UBSCM 2017-C2 | F177: =F9 -> 46811027 | K177: =IF(K$6<$C9,0,K137/$D137*$F177) -> 0 | L177: =IF(L$6<$C9,0,L137/$D137*$F177) -> 0 | M177: =IF(M$6<$C9,0,M137/$D137*$F177) -> 0 | N177: =IF(N$6<$C9,0,N137/$D137*$F177) -> 0 | O177: =IF(O$6<$C9,0,O137/$D137*$F177) -> 0 | P177: =IF(P$6<$C9,0,P137/$D137*$F177) -> 0 | Q177: =IF(Q$6<$C9,0,Q137/$D137*$F177) -> 46811027 | R177: =IF(R$6<$C9,0,R137/$D137*$F177) -> 46811027 | ... GS177: =IF(GS$6<$C9,0,GS137/$D137*$F177) -> 0 | GU177: =AVERAGEIFS($K177:$GS177,$K$5:$GS$5,GU$6)+IF(GU$6=YEAR($C177),$F177,0) -> 21277739 | GV177: =AVERAGEIFS($K177:$GS177,$K$5:$GS$5,GV$6)+IF(GV$6=YEAR($C177),$F177,0) -> 46811027 | GW177: =AVERAGEIFS($K177:$GS177,$K$5:$GS$5,GW$6)+IF(GW$6=YEAR($C177),$F177,0) -> 46811027 | GX177: =AVERAGEIFS($K177:$GS177,$K$5:$GS$5,GX$6)+IF(GX$6=YEAR($C177),$F177,0) -> 46811027 | GY177: =AVERAGEIFS($K177:$GS177,$K$5:$GS$5,GY$6)+IF(GY$6=YEAR($C177),$F177,0) -> 46811027 | GZ177: =AVERAGEIFS($K177:$GS177,$K$5:$GS$5,GZ$6)+IF(GZ$6=YEAR($C177),$F177,0) -> 46742304 | HA177: =AVERAGEIFS($K177:$GS177,$K$5:$GS$5,HA$6)+IF(HA$6=YEAR($C177),$F177,0) -> 46501774 | HB177: =AVERAGEIFS($K177:$GS177,$K$5:$GS$5,HB$6)+IF(HB$6=YEAR($C177),$F177,0) -> 46810943 | ... HJ177: =AVERAGEIFS($K177:$GS177,$K$5:$GS$5,HJ$6)+IF(HJ$6=YEAR($C177),$F177,0) -> 0 | HK177: =SUM(GU177:HJ177) -> 5.4074633e+08
A178: =A10 -> CGCMT 2017-C4 B-Piece Cashflows | B178: =B10 -> CGCMT 2017-C4 | F178: =F10 -> 50142415 | K178: =IF(K$6<$C10,0,K138/$D138*$F178) -> 0 | L178: =IF(L$6<$C10,0,L138/$D138*$F178) -> 0 | M178: =IF(M$6<$C10,0,M138/$D138*$F178) -> 0 | N178: =IF(N$6<$C10,0,N138/$D138*$F178) -> 0 | O178: =IF(O$6<$C10,0,O138/$D138*$F178) -> 0 | P178: =IF(P$6<$C10,0,P138/$D138*$F178) -> 0 | Q178: =IF(Q$6<$C10,0,Q138/$D138*$F178) -> 0 | R178: =IF(R$6<$C10,0,R138/$D138*$F178) -> 0 | ... GS178: =IF(GS$6<$C10,0,GS138/$D138*$F178) -> 0 | GU178: =AVERAGEIFS($K178:$GS178,$K$5:$GS$5,GU$6)+IF(GU$6=YEAR($C178),$F178,0) -> 13675204 | GV178: =AVERAGEIFS($K178:$GS178,$K$5:$GS$5,GV$6)+IF(GV$6=YEAR($C178),$F178,0) -> 50142415 | GW178: =AVERAGEIFS($K178:$GS178,$K$5:$GS$5,GW$6)+IF(GW$6=YEAR($C178),$F178,0) -> 50142415 | GX178: =AVERAGEIFS($K178:$GS178,$K$5:$GS$5,GX$6)+IF(GX$6=YEAR($C178),$F178,0) -> 50142415 | GY178: =AVERAGEIFS($K178:$GS178,$K$5:$GS$5,GY$6)+IF(GY$6=YEAR($C178),$F178,0) -> 50142415 | GZ178: =AVERAGEIFS($K178:$GS178,$K$5:$GS$5,GZ$6)+IF(GZ$6=YEAR($C178),$F178,0) -> 50142415 | HA178: =AVERAGEIFS($K178:$GS178,$K$5:$GS$5,HA$6)+IF(HA$6=YEAR($C178),$F178,0) -> 50142415 | HB178: =AVERAGEIFS($K178:$GS178,$K$5:$GS$5,HB$6)+IF(HB$6=YEAR($C178),$F178,0) -> 50142415 | ... HJ178: =AVERAGEIFS($K178:$GS178,$K$5:$GS$5,HJ$6)+IF(HJ$6=YEAR($C178),$F178,0) -> 0 | HK178: =SUM(GU178:HJ178) -> 6.3319861e+08
A179: =A11 -> WFCM 2018-C47 B-Piece Cashflows | B179: =B11 -> WFCM 2018-C47 | F179: =F11 -> 48654543 | K179: =IF(K$6<$C11,0,K139/$D139*$F179) -> 0 | L179: =IF(L$6<$C11,0,L139/$D139*$F179) -> 0 | M179: =IF(M$6<$C11,0,M139/$D139*$F179) -> 0 | N179: =IF(N$6<$C11,0,N139/$D139*$F179) -> 0 | O179: =IF(O$6<$C11,0,O139/$D139*$F179) -> 0 | P179: =IF(P$6<$C11,0,P139/$D139*$F179) -> 0 | Q179: =IF(Q$6<$C11,0,Q139/$D139*$F179) -> 0 | R179: =IF(R$6<$C11,0,R139/$D139*$F179) -> 0 | ... GS179: =IF(GS$6<$C11,0,GS139/$D139*$F179) -> 0 | GU179: =AVERAGEIFS($K179:$GS179,$K$5:$GS$5,GU$6)+IF(GU$6=YEAR($C179),$F179,0) -> 0 | GV179: =AVERAGEIFS($K179:$GS179,$K$5:$GS$5,GV$6)+IF(GV$6=YEAR($C179),$F179,0) -> 12163636 | GW179: =AVERAGEIFS($K179:$GS179,$K$5:$GS$5,GW$6)+IF(GW$6=YEAR($C179),$F179,0) -> 48654543 | GX179: =AVERAGEIFS($K179:$GS179,$K$5:$GS$5,GX$6)+IF(GX$6=YEAR($C179),$F179,0) -> 48654543 | GY179: =AVERAGEIFS($K179:$GS179,$K$5:$GS$5,GY$6)+IF(GY$6=YEAR($C179),$F179,0) -> 48654543 | GZ179: =AVERAGEIFS($K179:$GS179,$K$5:$GS$5,GZ$6)+IF(GZ$6=YEAR($C179),$F179,0) -> 48654543 | HA179: =AVERAGEIFS($K179:$GS179,$K$5:$GS$5,HA$6)+IF(HA$6=YEAR($C179),$F179,0) -> 48654543 | HB179: =AVERAGEIFS($K179:$GS179,$K$5:$GS$5,HB$6)+IF(HB$6=YEAR($C179),$F179,0) -> 48654543 | ... HJ179: =AVERAGEIFS($K179:$GS179,$K$5:$GS$5,HJ$6)+IF(HJ$6=YEAR($C179),$F179,0) -> 0 | HK179: =SUM(GU179:HJ179) -> 5.4699028e+08
A180: =A12 -> BBCMS 2019-C3 B-Piece Cashflows | B180: =B12 -> BBCMS 2019-C3 | F180: =F12 -> 49580194 | K180: =IF(K$6<$C12,0,K140/$D140*$F180) -> 0 | L180: =IF(L$6<$C12,0,L140/$D140*$F180) -> 0 | M180: =IF(M$6<$C12,0,M140/$D140*$F180) -> 0 | N180: =IF(N$6<$C12,0,N140/$D140*$F180) -> 0 | O180: =IF(O$6<$C12,0,O140/$D140*$F180) -> 0 | P180: =IF(P$6<$C12,0,P140/$D140*$F180) -> 0 | Q180: =IF(Q$6<$C12,0,Q140/$D140*$F180) -> 0 | R180: =IF(R$6<$C12,0,R140/$D140*$F180) -> 0 | ... GS180: =IF(GS$6<$C12,0,GS140/$D140*$F180) -> 0 | GU180: =AVERAGEIFS($K180:$GS180,$K$5:$GS$5,GU$6)+IF(GU$6=YEAR($C180),$F180,0) -> 0 | GV180: =AVERAGEIFS($K180:$GS180,$K$5:$GS$5,GV$6)+IF(GV$6=YEAR($C180),$F180,0) -> 0 | GW180: =AVERAGEIFS($K180:$GS180,$K$5:$GS$5,GW$6)+IF(GW$6=YEAR($C180),$F180,0) -> 28921780 | GX180: =AVERAGEIFS($K180:$GS180,$K$5:$GS$5,GX$6)+IF(GX$6=YEAR($C180),$F180,0) -> 49580194 | GY180: =AVERAGEIFS($K180:$GS180,$K$5:$GS$5,GY$6)+IF(GY$6=YEAR($C180),$F180,0) -> 49580194 | GZ180: =AVERAGEIFS($K180:$GS180,$K$5:$GS$5,GZ$6)+IF(GZ$6=YEAR($C180),$F180,0) -> 49580194 | HA180: =AVERAGEIFS($K180:$GS180,$K$5:$GS$5,HA$6)+IF(HA$6=YEAR($C180),$F180,0) -> 49580194 | HB180: =AVERAGEIFS($K180:$GS180,$K$5:$GS$5,HB$6)+IF(HB$6=YEAR($C180),$F180,0) -> 49580194 | ... HJ180: =AVERAGEIFS($K180:$GS180,$K$5:$GS$5,HJ$6)+IF(HJ$6=YEAR($C180),$F180,0) -> 7073423.2 | HK180: =SUM(GU180:HJ180) -> 5.8795164e+08
A181: =A13 -> GSMS 2019-GC38 B-Piece Cashflow | B181: =B13 -> GSMS 2019-GC38 | F181: =F13 -> 39335516 | K181: =IF(K$6<$C13,0,K141/$D141*$F181) -> 0 | L181: =IF(L$6<$C13,0,L141/$D141*$F181) -> 0 | M181: =IF(M$6<$C13,0,M141/$D141*$F181) -> 0 | N181: =IF(N$6<$C13,0,N141/$D141*$F181) -> 0 | O181: =IF(O$6<$C13,0,O141/$D141*$F181) -> 0 | P181: =IF(P$6<$C13,0,P141/$D141*$F181) -> 0 | Q181: =IF(Q$6<$C13,0,Q141/$D141*$F181) -> 0 | R181: =IF(R$6<$C13,0,R141/$D141*$F181) -> 0 | ... GS181: =IF(GS$6<$C13,0,GS141/$D141*$F181) -> 0 | GU181: =AVERAGEIFS($K181:$GS181,$K$5:$GS$5,GU$6)+IF(GU$6=YEAR($C181),$F181,0) -> 0 | GV181: =AVERAGEIFS($K181:$GS181,$K$5:$GS$5,GV$6)+IF(GV$6=YEAR($C181),$F181,0) -> 0 | GW181: =AVERAGEIFS($K181:$GS181,$K$5:$GS$5,GW$6)+IF(GW$6=YEAR($C181),$F181,0) -> 36057556 | GX181: =AVERAGEIFS($K181:$GS181,$K$5:$GS$5,GX$6)+IF(GX$6=YEAR($C181),$F181,0) -> 39335516 | GY181: =AVERAGEIFS($K181:$GS181,$K$5:$GS$5,GY$6)+IF(GY$6=YEAR($C181),$F181,0) -> 39335516 | GZ181: =AVERAGEIFS($K181:$GS181,$K$5:$GS$5,GZ$6)+IF(GZ$6=YEAR($C181),$F181,0) -> 39335516 | HA181: =AVERAGEIFS($K181:$GS181,$K$5:$GS$5,HA$6)+IF(HA$6=YEAR($C181),$F181,0) -> 39335516 | HB181: =AVERAGEIFS($K181:$GS181,$K$5:$GS$5,HB$6)+IF(HB$6=YEAR($C181),$F181,0) -> 39335516 | ... HJ181: =AVERAGEIFS($K181:$GS181,$K$5:$GS$5,HJ$6)+IF(HJ$6=YEAR($C181),$F181,0) -> 1744906 | HK181: =SUM(GU181:HJ181) -> 4.9419875e+08
A182: =A14 -> GSMS 2017-GS8 B-Piece Cashflow | B182: =B14 -> GSMS 2017-GS8 | F182: =F14 -> 52373515 | K182: =IF(K$6<$C14,0,K142/$D142*$F182) -> 0 | L182: =IF(L$6<$C14,0,L142/$D142*$F182) -> 0 | M182: =IF(M$6<$C14,0,M142/$D142*$F182) -> 0 | N182: =IF(N$6<$C14,0,N142/$D142*$F182) -> 0 | O182: =IF(O$6<$C14,0,O142/$D142*$F182) -> 0 | P182: =IF(P$6<$C14,0,P142/$D142*$F182) -> 0 | Q182: =IF(Q$6<$C14,0,Q142/$D142*$F182) -> 0 | R182: =IF(R$6<$C14,0,R142/$D142*$F182) -> 0 | ... GS182: =IF(GS$6<$C14,0,GS142/$D142*$F182) -> 0 | GU182: =AVERAGEIFS($K182:$GS182,$K$5:$GS$5,GU$6)+IF(GU$6=YEAR($C182),$F182,0) -> 9522457.3 | GV182: =AVERAGEIFS($K182:$GS182,$K$5:$GS$5,GV$6)+IF(GV$6=YEAR($C182),$F182,0) -> 52373515 | GW182: =AVERAGEIFS($K182:$GS182,$K$5:$GS$5,GW$6)+IF(GW$6=YEAR($C182),$F182,0) -> 52373515 | GX182: =AVERAGEIFS($K182:$GS182,$K$5:$GS$5,GX$6)+IF(GX$6=YEAR($C182),$F182,0) -> 52373515 | GY182: =AVERAGEIFS($K182:$GS182,$K$5:$GS$5,GY$6)+IF(GY$6=YEAR($C182),$F182,0) -> 52373515 | GZ182: =AVERAGEIFS($K182:$GS182,$K$5:$GS$5,GZ$6)+IF(GZ$6=YEAR($C182),$F182,0) -> 52373515 | HA182: =AVERAGEIFS($K182:$GS182,$K$5:$GS$5,HA$6)+IF(HA$6=YEAR($C182),$F182,0) -> 52373515 | HB182: =AVERAGEIFS($K182:$GS182,$K$5:$GS$5,HB$6)+IF(HB$6=YEAR($C182),$F182,0) -> 52373515 | ... HJ182: =AVERAGEIFS($K182:$GS182,$K$5:$GS$5,HJ$6)+IF(HJ$6=YEAR($C182),$F182,0) -> 0 | HK182: =SUM(GU182:HJ182) -> 6.6566428e+08
A183: =A15 -> UBSCM 2018-C8 B-Piece Cashflows | B183: =B15 -> UBSCM 2018-C8 | F183: =F15 -> 53204082 | K183: =IF(K$6<$C15,0,K143/$D143*$F183) -> 0 | L183: =IF(L$6<$C15,0,L143/$D143*$F183) -> 0 | M183: =IF(M$6<$C15,0,M143/$D143*$F183) -> 0 | N183: =IF(N$6<$C15,0,N143/$D143*$F183) -> 0 | O183: =IF(O$6<$C15,0,O143/$D143*$F183) -> 0 | P183: =IF(P$6<$C15,0,P143/$D143*$F183) -> 0 | Q183: =IF(Q$6<$C15,0,Q143/$D143*$F183) -> 0 | R183: =IF(R$6<$C15,0,R143/$D143*$F183) -> 0 | ... GS183: =IF(GS$6<$C15,0,GS143/$D143*$F183) -> 0 | GU183: =AVERAGEIFS($K183:$GS183,$K$5:$GS$5,GU$6)+IF(GU$6=YEAR($C183),$F183,0) -> 0 | GV183: =AVERAGEIFS($K183:$GS183,$K$5:$GS$5,GV$6)+IF(GV$6=YEAR($C183),$F183,0) -> 48770408 | GW183: =AVERAGEIFS($K183:$GS183,$K$5:$GS$5,GW$6)+IF(GW$6=YEAR($C183),$F183,0) -> 53204082 | GX183: =AVERAGEIFS($K183:$GS183,$K$5:$GS$5,GX$6)+IF(GX$6=YEAR($C183),$F183,0) -> 53204082 | GY183: =AVERAGEIFS($K183:$GS183,$K$5:$GS$5,GY$6)+IF(GY$6=YEAR($C183),$F183,0) -> 53204082 | GZ183: =AVERAGEIFS($K183:$GS183,$K$5:$GS$5,GZ$6)+IF(GZ$6=YEAR($C183),$F183,0) -> 52821652 | HA183: =AVERAGEIFS($K183:$GS183,$K$5:$GS$5,HA$6)+IF(HA$6=YEAR($C183),$F183,0) -> 52823708 | HB183: =AVERAGEIFS($K183:$GS183,$K$5:$GS$5,HB$6)+IF(HB$6=YEAR($C183),$F183,0) -> 52825433 | ... HJ183: =AVERAGEIFS($K183:$GS183,$K$5:$GS$5,HJ$6)+IF(HJ$6=YEAR($C183),$F183,0) -> 0 | HK183: =SUM(GU183:HJ183) -> 5.4731209e+08
A184: =A16 -> UBSCM 2017-C3 B-Piece Cashflows | B184: =B16 -> UBSCM 2017-C3 | F184: =F16 -> 38157487 | K184: =IF(K$6<$C16,0,K144/$D144*$F184) -> 0 | L184: =IF(L$6<$C16,0,L144/$D144*$F184) -> 0 | M184: =IF(M$6<$C16,0,M144/$D144*$F184) -> 0 | N184: =IF(N$6<$C16,0,N144/$D144*$F184) -> 0 | O184: =IF(O$6<$C16,0,O144/$D144*$F184) -> 0 | P184: =IF(P$6<$C16,0,P144/$D144*$F184) -> 0 | Q184: =IF(Q$6<$C16,0,Q144/$D144*$F184) -> 38157487 | R184: =IF(R$6<$C16,0,R144/$D144*$F184) -> 38157487 | ... GS184: =IF(GS$6<$C16,0,GS144/$D144*$F184) -> 0 | GU184: =AVERAGEIFS($K184:$GS184,$K$5:$GS$5,GU$6)+IF(GU$6=YEAR($C184),$F184,0) -> 17344312 | GV184: =AVERAGEIFS($K184:$GS184,$K$5:$GS$5,GV$6)+IF(GV$6=YEAR($C184),$F184,0) -> 38157487 | GW184: =AVERAGEIFS($K184:$GS184,$K$5:$GS$5,GW$6)+IF(GW$6=YEAR($C184),$F184,0) -> 38157487 | GX184: =AVERAGEIFS($K184:$GS184,$K$5:$GS$5,GX$6)+IF(GX$6=YEAR($C184),$F184,0) -> 38157487 | GY184: =AVERAGEIFS($K184:$GS184,$K$5:$GS$5,GY$6)+IF(GY$6=YEAR($C184),$F184,0) -> 38157487 | GZ184: =AVERAGEIFS($K184:$GS184,$K$5:$GS$5,GZ$6)+IF(GZ$6=YEAR($C184),$F184,0) -> 38157487 | HA184: =AVERAGEIFS($K184:$GS184,$K$5:$GS$5,HA$6)+IF(HA$6=YEAR($C184),$F184,0) -> 38157487 | HB184: =AVERAGEIFS($K184:$GS184,$K$5:$GS$5,HB$6)+IF(HB$6=YEAR($C184),$F184,0) -> 38157487 | ... HJ184: =AVERAGEIFS($K184:$GS184,$K$5:$GS$5,HJ$6)+IF(HJ$6=YEAR($C184),$F184,0) -> 0 | HK184: =SUM(GU184:HJ184) -> 4.7116695e+08
A185: =A17 -> UBSCM 2017-C5 B-Piece Cashflows | B185: =B17 -> UBSCM 2017-C5 | F185: =F17 -> 38300901 | K185: =IF(K$6<$C17,0,K145/$D145*$F185) -> 0 | L185: =IF(L$6<$C17,0,L145/$D145*$F185) -> 0 | M185: =IF(M$6<$C17,0,M145/$D145*$F185) -> 0 | N185: =IF(N$6<$C17,0,N145/$D145*$F185) -> 0 | O185: =IF(O$6<$C17,0,O145/$D145*$F185) -> 0 | P185: =IF(P$6<$C17,0,P145/$D145*$F185) -> 0 | Q185: =IF(Q$6<$C17,0,Q145/$D145*$F185) -> 0 | R185: =IF(R$6<$C17,0,R145/$D145*$F185) -> 0 | ... GS185: =IF(GS$6<$C17,0,GS145/$D145*$F185) -> 0 | GU185: =AVERAGEIFS($K185:$GS185,$K$5:$GS$5,GU$6)+IF(GU$6=YEAR($C185),$F185,0) -> 6963800.2 | GV185: =AVERAGEIFS($K185:$GS185,$K$5:$GS$5,GV$6)+IF(GV$6=YEAR($C185),$F185,0) -> 38300901 | GW185: =AVERAGEIFS($K185:$GS185,$K$5:$GS$5,GW$6)+IF(GW$6=YEAR($C185),$F185,0) -> 38300901 | GX185: =AVERAGEIFS($K185:$GS185,$K$5:$GS$5,GX$6)+IF(GX$6=YEAR($C185),$F185,0) -> 38300901 | GY185: =AVERAGEIFS($K185:$GS185,$K$5:$GS$5,GY$6)+IF(GY$6=YEAR($C185),$F185,0) -> 38300901 | GZ185: =AVERAGEIFS($K185:$GS185,$K$5:$GS$5,GZ$6)+IF(GZ$6=YEAR($C185),$F185,0) -> 38300901 | HA185: =AVERAGEIFS($K185:$GS185,$K$5:$GS$5,HA$6)+IF(HA$6=YEAR($C185),$F185,0) -> 38300901 | HB185: =AVERAGEIFS($K185:$GS185,$K$5:$GS$5,HB$6)+IF(HB$6=YEAR($C185),$F185,0) -> 36254916 | ... HJ185: =AVERAGEIFS($K185:$GS185,$K$5:$GS$5,HJ$6)+IF(HJ$6=YEAR($C185),$F185,0) -> 0 | HK185: =SUM(GU185:HJ185) -> 4.2456839e+08
A186: =A18 -> MSC 2019-H6 B-Piece Cashflows | B186: =B18 -> MSC 2019-H6 | F186: =F18 -> 36246073 | K186: =IF(K$6<$C18,0,K146/$D146*$F186) -> 0 | L186: =IF(L$6<$C18,0,L146/$D146*$F186) -> 0 | M186: =IF(M$6<$C18,0,M146/$D146*$F186) -> 0 | N186: =IF(N$6<$C18,0,N146/$D146*$F186) -> 0 | O186: =IF(O$6<$C18,0,O146/$D146*$F186) -> 0 | P186: =IF(P$6<$C18,0,P146/$D146*$F186) -> 0 | Q186: =IF(Q$6<$C18,0,Q146/$D146*$F186) -> 0 | R186: =IF(R$6<$C18,0,R146/$D146*$F186) -> 0 | ... GS186: =IF(GS$6<$C18,0,GS146/$D146*$F186) -> 0 | GU186: =AVERAGEIFS($K186:$GS186,$K$5:$GS$5,GU$6)+IF(GU$6=YEAR($C186),$F186,0) -> 0 | GV186: =AVERAGEIFS($K186:$GS186,$K$5:$GS$5,GV$6)+IF(GV$6=YEAR($C186),$F186,0) -> 0 | GW186: =AVERAGEIFS($K186:$GS186,$K$5:$GS$5,GW$6)+IF(GW$6=YEAR($C186),$F186,0) -> 21143542 | GX186: =AVERAGEIFS($K186:$GS186,$K$5:$GS$5,GX$6)+IF(GX$6=YEAR($C186),$F186,0) -> 36246073 | GY186: =AVERAGEIFS($K186:$GS186,$K$5:$GS$5,GY$6)+IF(GY$6=YEAR($C186),$F186,0) -> 36246073 | GZ186: =AVERAGEIFS($K186:$GS186,$K$5:$GS$5,GZ$6)+IF(GZ$6=YEAR($C186),$F186,0) -> 36246073 | HA186: =AVERAGEIFS($K186:$GS186,$K$5:$GS$5,HA$6)+IF(HA$6=YEAR($C186),$F186,0) -> 36246073 | HB186: =AVERAGEIFS($K186:$GS186,$K$5:$GS$5,HB$6)+IF(HB$6=YEAR($C186),$F186,0) -> 34838916 | ... HJ186: =AVERAGEIFS($K186:$GS186,$K$5:$GS$5,HJ$6)+IF(HJ$6=YEAR($C186),$F186,0) -> 0 | HK186: =SUM(GU186:HJ186) -> 3.9639227e+08
A187: =A19 -> WFCM 2019-C49 B-Piece Cashflows | B187: =B19 -> WFCM 2019-C49 | F187: =F19 -> 40530203 | K187: =IF(K$6<$C19,0,K147/$D147*$F187) -> 0 | L187: =IF(L$6<$C19,0,L147/$D147*$F187) -> 0 | M187: =IF(M$6<$C19,0,M147/$D147*$F187) -> 0 | N187: =IF(N$6<$C19,0,N147/$D147*$F187) -> 0 | O187: =IF(O$6<$C19,0,O147/$D147*$F187) -> 0 | P187: =IF(P$6<$C19,0,P147/$D147*$F187) -> 0 | Q187: =IF(Q$6<$C19,0,Q147/$D147*$F187) -> 0 | R187: =IF(R$6<$C19,0,R147/$D147*$F187) -> 0 | ... GS187: =IF(GS$6<$C19,0,GS147/$D147*$F187) -> 0 | GU187: =AVERAGEIFS($K187:$GS187,$K$5:$GS$5,GU$6)+IF(GU$6=YEAR($C187),$F187,0) -> 0 | GV187: =AVERAGEIFS($K187:$GS187,$K$5:$GS$5,GV$6)+IF(GV$6=YEAR($C187),$F187,0) -> 0 | GW187: =AVERAGEIFS($K187:$GS187,$K$5:$GS$5,GW$6)+IF(GW$6=YEAR($C187),$F187,0) -> 33775169 | GX187: =AVERAGEIFS($K187:$GS187,$K$5:$GS$5,GX$6)+IF(GX$6=YEAR($C187),$F187,0) -> 40530203 | GY187: =AVERAGEIFS($K187:$GS187,$K$5:$GS$5,GY$6)+IF(GY$6=YEAR($C187),$F187,0) -> 40530203 | GZ187: =AVERAGEIFS($K187:$GS187,$K$5:$GS$5,GZ$6)+IF(GZ$6=YEAR($C187),$F187,0) -> 40530203 | HA187: =AVERAGEIFS($K187:$GS187,$K$5:$GS$5,HA$6)+IF(HA$6=YEAR($C187),$F187,0) -> 40530203 | HB187: =AVERAGEIFS($K187:$GS187,$K$5:$GS$5,HB$6)+IF(HB$6=YEAR($C187),$F187,0) -> 40530203 | ... HJ187: =AVERAGEIFS($K187:$GS187,$K$5:$GS$5,HJ$6)+IF(HJ$6=YEAR($C187),$F187,0) -> 0 | HK187: =SUM(GU187:HJ187) -> 4.5693571e+08
A188: =A20 -> UBSCM 2018-C13 B-Piece Cashflow | B188: =B20 -> UBSCM 2018-C13 | F188: =F20 -> 36689695 | K188: =IF(K$6<$C20,0,K148/$D148*$F188) -> 0 | L188: =IF(L$6<$C20,0,L148/$D148*$F188) -> 0 | M188: =IF(M$6<$C20,0,M148/$D148*$F188) -> 0 | N188: =IF(N$6<$C20,0,N148/$D148*$F188) -> 0 | O188: =IF(O$6<$C20,0,O148/$D148*$F188) -> 0 | P188: =IF(P$6<$C20,0,P148/$D148*$F188) -> 0 | Q188: =IF(Q$6<$C20,0,Q148/$D148*$F188) -> 0 | R188: =IF(R$6<$C20,0,R148/$D148*$F188) -> 0 | ... GS188: =IF(GS$6<$C20,0,GS148/$D148*$F188) -> 0 | GU188: =AVERAGEIFS($K188:$GS188,$K$5:$GS$5,GU$6)+IF(GU$6=YEAR($C188),$F188,0) -> 0 | GV188: =AVERAGEIFS($K188:$GS188,$K$5:$GS$5,GV$6)+IF(GV$6=YEAR($C188),$F188,0) -> 9172423.9 | GW188: =AVERAGEIFS($K188:$GS188,$K$5:$GS$5,GW$6)+IF(GW$6=YEAR($C188),$F188,0) -> 36689695 | GX188: =AVERAGEIFS($K188:$GS188,$K$5:$GS$5,GX$6)+IF(GX$6=YEAR($C188),$F188,0) -> 36689695 | GY188: =AVERAGEIFS($K188:$GS188,$K$5:$GS$5,GY$6)+IF(GY$6=YEAR($C188),$F188,0) -> 36689695 | GZ188: =AVERAGEIFS($K188:$GS188,$K$5:$GS$5,GZ$6)+IF(GZ$6=YEAR($C188),$F188,0) -> 36689695 | HA188: =AVERAGEIFS($K188:$GS188,$K$5:$GS$5,HA$6)+IF(HA$6=YEAR($C188),$F188,0) -> 36689695 | HB188: =AVERAGEIFS($K188:$GS188,$K$5:$GS$5,HB$6)+IF(HB$6=YEAR($C188),$F188,0) -> 36689695 | ... HJ188: =AVERAGEIFS($K188:$GS188,$K$5:$GS$5,HJ$6)+IF(HJ$6=YEAR($C188),$F188,0) -> 0 | HK188: =SUM(GU188:HJ188) -> 4.0657488e+08
