Workbook

Sheet Side by Side
B2: SIDE BY SIDE: SELLING LP CASH FLOWS, SSP VS KKR (100% LP BASIS)
B5: Date | C5: SSP Model Cash Flow | D5: KKR Model Cash Flow (Row 63) | E5: Difference (KKR less SSP) | F5: Cumulative Difference | H5: Returns | I5: SSP | J5: KKR | K5: Difference
B6: =Inputs!$C$9 -> 46387 | C6: =IF(B6=Inputs!$C$9,-Inputs!$C$17,0)+SUMIFS('Monthly Collections'!$H$6:$H$83,'Monthly Collections'!$I$6:$I$83,B6)+IF(B6=Inputs!$C$12,Inputs!$C$14*Inputs!$C$18,0) -> -1.5831649e+08 | D6: =SUMIFS('KKR CF'!$F$6:$F$400,'KKR CF'!$E$6:$E$400,B6) -> 0 | E6: =D6-C6 -> 1.5831649e+08 | F6: =SUM(E$6:E6) -> 1.5831649e+08 | H6: Gross IRR | I6: =XIRR(C6:C78,B6:B78) -> 0.16230903 | J6: =XIRR(D7:D78,B7:B78) -> 0.17907204 | K6: =J6-I6 -> 0.016763001
B7: =Inputs!$C$10 -> 46388 | C7: =IF(B7=Inputs!$C$9,-Inputs!$C$17,0)+SUMIFS('Monthly Collections'!$H$6:$H$83,'Monthly Collections'!$I$6:$I$83,B7)+IF(B7=Inputs!$C$12,Inputs!$C$14*Inputs!$C$18,0) -> 0 | D7: =SUMIFS('KKR CF'!$F$6:$F$400,'KKR CF'!$E$6:$E$400,B7) -> -1.5634323e+08 | E7: =D7-C7 -> -1.5634323e+08 | F7: =SUM(E$6:E7) -> 1973265 | H7: Gross MOIC | I7: =SUMIF(C6:C78,">0")/-SUMIF(C6:C78,"<0") -> 1.6609101 | J7: =SUMIF(D6:D78,">0")/-SUMIF(D6:D78,"<0") -> 1.7241447 | K7: =J7-I7 -> 0.063234542
B8: =EOMONTH(B7,0) -> 46418 | C8: =IF(B8=Inputs!$C$9,-Inputs!$C$17,0)+SUMIFS('Monthly Collections'!$H$6:$H$83,'Monthly Collections'!$I$6:$I$83,B8)+IF(B8=Inputs!$C$12,Inputs!$C$14*Inputs!$C$18,0) -> 0 | D8: =SUMIFS('KKR CF'!$F$6:$F$400,'KKR CF'!$E$6:$E$400,B8) -> 0 | E8: =D8-C8 -> 0 | F8: =SUM(E$6:E8) -> 1973265 | H8: Net profit ($) | I8: =SUM(C6:C78) -> 1.0463297e+08 | J8: =SUM(D6:D78) -> 1.1321511e+08 | K8: =J8-I8 -> 8582141.4
B9: =EOMONTH(B8,1) -> 46446 | C9: =IF(B9=Inputs!$C$9,-Inputs!$C$17,0)+SUMIFS('Monthly Collections'!$H$6:$H$83,'Monthly Collections'!$I$6:$I$83,B9)+IF(B9=Inputs!$C$12,Inputs!$C$14*Inputs!$C$18,0) -> 0 | D9: =SUMIFS('KKR CF'!$F$6:$F$400,'KKR CF'!$E$6:$E$400,B9) -> 0 | E9: =D9-C9 -> 0 | F9: =SUM(E$6:E9) -> 1973265 | H9: IRR difference (bps) | K9: =K6*10000 -> 167.63001
B10: =EOMONTH(B9,1) -> 46477 | C10: =IF(B10=Inputs!$C$9,-Inputs!$C$17,0)+SUMIFS('Monthly Collections'!$H$6:$H$83,'Monthly Collections'!$I$6:$I$83,B10)+IF(B10=Inputs!$C$12,Inputs!$C$14*Inputs!$C$18,0) -> 5892019.1 | D10: =SUMIFS('KKR CF'!$F$6:$F$400,'KKR CF'!$E$6:$E$400,B10) -> 6162754.2 | E10: =D10-C10 -> 270735.13 | F10: =SUM(E$6:E10) -> 2244000.2
B11: =EOMONTH(B10,1) -> 46507 | C11: =IF(B11=Inputs!$C$9,-Inputs!$C$17,0)+SUMIFS('Monthly Collections'!$H$6:$H$83,'Monthly Collections'!$I$6:$I$83,B11)+IF(B11=Inputs!$C$12,Inputs!$C$14*Inputs!$C$18,0) -> 0 | D11: =SUMIFS('KKR CF'!$F$6:$F$400,'KKR CF'!$E$6:$E$400,B11) -> 0 | E11: =D11-C11 -> 0 | F11: =SUM(E$6:E11) -> 2244000.2
B12: =EOMONTH(B11,1) -> 46538 | C12: =IF(B12=Inputs!$C$9,-Inputs!$C$17,0)+SUMIFS('Monthly Collections'!$H$6:$H$83,'Monthly Collections'!$I$6:$I$83,B12)+IF(B12=Inputs!$C$12,Inputs!$C$14*Inputs!$C$18,0) -> 0 | D12: =SUMIFS('KKR CF'!$F$6:$F$400,'KKR CF'!$E$6:$E$400,B12) -> 0 | E12: =D12-C12 -> 0 | F12: =SUM(E$6:E12) -> 2244000.2 | H12: Calendar Year | I12: SSP | J12: KKR | K12: Difference
B13: =EOMONTH(B12,1) -> 46568 | C13: =IF(B13=Inputs!$C$9,-Inputs!$C$17,0)+SUMIFS('Monthly Collections'!$H$6:$H$83,'Monthly Collections'!$I$6:$I$83,B13)+IF(B13=Inputs!$C$12,Inputs!$C$14*Inputs!$C$18,0) -> 5603429.9 | D13: =SUMIFS('KKR CF'!$F$6:$F$400,'KKR CF'!$E$6:$E$400,B13) -> 5556569.7 | E13: =D13-C13 -> -46860.183 | F13: =SUM(E$6:E13) -> 2197140 | H13: 2026 | I13: =SUMPRODUCT((YEAR($B$6:$B$78)=H13)*$C$6:$C$78) -> -1.5831649e+08 | J13: =SUMPRODUCT((YEAR($B$6:$B$78)=H13)*$D$6:$D$78) -> 0 | K13: =J13-I13 -> 1.5831649e+08
B14: =EOMONTH(B13,1) -> 46599 | C14: =IF(B14=Inputs!$C$9,-Inputs!$C$17,0)+SUMIFS('Monthly Collections'!$H$6:$H$83,'Monthly Collections'!$I$6:$I$83,B14)+IF(B14=Inputs!$C$12,Inputs!$C$14*Inputs!$C$18,0) -> 0 | D14: =SUMIFS('KKR CF'!$F$6:$F$400,'KKR CF'!$E$6:$E$400,B14) -> 0 | E14: =D14-C14 -> 0 | F14: =SUM(E$6:E14) -> 2197140 | H14: 2027 | I14: =SUMPRODUCT((YEAR($B$6:$B$78)=H14)*$C$6:$C$78) -> 21935072 | J14: =SUMPRODUCT((YEAR($B$6:$B$78)=H14)*$D$6:$D$78) -> -1.3430232e+08 | K14: =J14-I14 -> -1.5623739e+08
B15: =EOMONTH(B14,1) -> 46630 | C15: =IF(B15=Inputs!$C$9,-Inputs!$C$17,0)+SUMIFS('Monthly Collections'!$H$6:$H$83,'Monthly Collections'!$I$6:$I$83,B15)+IF(B15=Inputs!$C$12,Inputs!$C$14*Inputs!$C$18,0) -> 0 | D15: =SUMIFS('KKR CF'!$F$6:$F$400,'KKR CF'!$E$6:$E$400,B15) -> 0 | E15: =D15-C15 -> 0 | F15: =SUM(E$6:E15) -> 2197140 | H15: 2028 | I15: =SUMPRODUCT((YEAR($B$6:$B$78)=H15)*$C$6:$C$78) -> 16348017 | J15: =SUMPRODUCT((YEAR($B$6:$B$78)=H15)*$D$6:$D$78) -> 17070003 | K15: =J15-I15 -> 721986.18
B16: =EOMONTH(B15,1) -> 46660 | C16: =IF(B16=Inputs!$C$9,-Inputs!$C$17,0)+SUMIFS('Monthly Collections'!$H$6:$H$83,'Monthly Collections'!$I$6:$I$83,B16)+IF(B16=Inputs!$C$12,Inputs!$C$14*Inputs!$C$18,0) -> 5443763.7 | D16: =SUMIFS('KKR CF'!$F$6:$F$400,'KKR CF'!$E$6:$E$400,B16) -> 5389272.5 | E16: =D16-C16 -> -54491.227 | F16: =SUM(E$6:E16) -> 2142648.8 | H16: 2029 | I16: =SUMPRODUCT((YEAR($B$6:$B$78)=H16)*$C$6:$C$78) -> 62650645 | J16: =SUMPRODUCT((YEAR($B$6:$B$78)=H16)*$D$6:$D$78) -> 63524509 | K16: =J16-I16 -> 873863.31
B17: =EOMONTH(B16,1) -> 46691 | C17: =IF(B17=Inputs!$C$9,-Inputs!$C$17,0)+SUMIFS('Monthly Collections'!$H$6:$H$83,'Monthly Collections'!$I$6:$I$83,B17)+IF(B17=Inputs!$C$12,Inputs!$C$14*Inputs!$C$18,0) -> 0 | D17: =SUMIFS('KKR CF'!$F$6:$F$400,'KKR CF'!$E$6:$E$400,B17) -> 0 | E17: =D17-C17 -> 0 | F17: =SUM(E$6:E17) -> 2142648.8 | H17: 2030 | I17: =SUMPRODUCT((YEAR($B$6:$B$78)=H17)*$C$6:$C$78) -> 73801206 | J17: =SUMPRODUCT((YEAR($B$6:$B$78)=H17)*$D$6:$D$78) -> 77951959 | K17: =J17-I17 -> 4150752.5
B18: =EOMONTH(B17,1) -> 46721 | C18: =IF(B18=Inputs!$C$9,-Inputs!$C$17,0)+SUMIFS('Monthly Collections'!$H$6:$H$83,'Monthly Collections'!$I$6:$I$83,B18)+IF(B18=Inputs!$C$12,Inputs!$C$14*Inputs!$C$18,0) -> 0 | D18: =SUMIFS('KKR CF'!$F$6:$F$400,'KKR CF'!$E$6:$E$400,B18) -> 0 | E18: =D18-C18 -> 0 | F18: =SUM(E$6:E18) -> 2142648.8 | H18: 2031 | I18: =SUMPRODUCT((YEAR($B$6:$B$78)=H18)*$C$6:$C$78) -> 60845274 | J18: =SUMPRODUCT((YEAR($B$6:$B$78)=H18)*$D$6:$D$78) -> 60291818 | K18: =J18-I18 -> -553455.47
B19: =EOMONTH(B18,1) -> 46752 | C19: =IF(B19=Inputs!$C$9,-Inputs!$C$17,0)+SUMIFS('Monthly Collections'!$H$6:$H$83,'Monthly Collections'!$I$6:$I$83,B19)+IF(B19=Inputs!$C$12,Inputs!$C$14*Inputs!$C$18,0) -> 4995859.3 | D19: =SUMIFS('KKR CF'!$F$6:$F$400,'KKR CF'!$E$6:$E$400,B19) -> 4932309.6 | E19: =D19-C19 -> -63549.696 | F19: =SUM(E$6:E19) -> 2079099.1 | H19: 2032 | I19: =SUMPRODUCT((YEAR($B$6:$B$78)=H19)*$C$6:$C$78) -> 27369247 | J19: =SUMPRODUCT((YEAR($B$6:$B$78)=H19)*$D$6:$D$78) -> 28679143 | K19: =J19-I19 -> 1309895.9
B20: =EOMONTH(B19,1) -> 46783 | C20: =IF(B20=Inputs!$C$9,-Inputs!$C$17,0)+SUMIFS('Monthly Collections'!$H$6:$H$83,'Monthly Collections'!$I$6:$I$83,B20)+IF(B20=Inputs!$C$12,Inputs!$C$14*Inputs!$C$18,0) -> 0 | D20: =SUMIFS('KKR CF'!$F$6:$F$400,'KKR CF'!$E$6:$E$400,B20) -> 0 | E20: =D20-C20 -> 0 | F20: =SUM(E$6:E20) -> 2079099.1 | H20: Total | I20: =SUM(I13:I19) -> 1.0463297e+08 | J20: =SUM(J13:J19) -> 1.1321511e+08 | K20: =SUM(K13:K19) -> 8582141.4
B21: =EOMONTH(B20,1) -> 46812 | C21: =IF(B21=Inputs!$C$9,-Inputs!$C$17,0)+SUMIFS('Monthly Collections'!$H$6:$H$83,'Monthly Collections'!$I$6:$I$83,B21)+IF(B21=Inputs!$C$12,Inputs!$C$14*Inputs!$C$18,0) -> 0 | D21: =SUMIFS('KKR CF'!$F$6:$F$400,'KKR CF'!$E$6:$E$400,B21) -> 0 | E21: =D21-C21 -> 0 | F21: =SUM(E$6:E21) -> 2079099.1
B22: =EOMONTH(B21,1) -> 46843 | C22: =IF(B22=Inputs!$C$9,-Inputs!$C$17,0)+SUMIFS('Monthly Collections'!$H$6:$H$83,'Monthly Collections'!$I$6:$I$83,B22)+IF(B22=Inputs!$C$12,Inputs!$C$14*Inputs!$C$18,0) -> 4591148.9 | D22: =SUMIFS('KKR CF'!$F$6:$F$400,'KKR CF'!$E$6:$E$400,B22) -> 4708894.3 | E22: =D22-C22 -> 117745.41 | F22: =SUM(E$6:E22) -> 2196844.5
B23: =EOMONTH(B22,1) -> 46873 | C23: =IF(B23=Inputs!$C$9,-Inputs!$C$17,0)+SUMIFS('Monthly Collections'!$H$6:$H$83,'Monthly Collections'!$I$6:$I$83,B23)+IF(B23=Inputs!$C$12,Inputs!$C$14*Inputs!$C$18,0) -> 0 | D23: =SUMIFS('KKR CF'!$F$6:$F$400,'KKR CF'!$E$6:$E$400,B23) -> 0 | E23: =D23-C23 -> 0 | F23: =SUM(E$6:E23) -> 2196844.5 | H23: Set the toggles on Inputs (C13 and C14) to 2 and 1 to swap in KKR collections and add the cash release to the SSP stream. The IRR difference then shrinks to the timing convention residual. SSP stream: price paid on the closing date, selling LP share of fund collections paid on SSP quarter dates (each month paid in the first quarter date after it). KKR stream: Fwd Returns row 63, price at the transaction date, KKR timing and reserve. KKR figures are from the zero fee case at 50% price.
B24: =EOMONTH(B23,1) -> 46904 | C24: =IF(B24=Inputs!$C$9,-Inputs!$C$17,0)+SUMIFS('Monthly Collections'!$H$6:$H$83,'Monthly Collections'!$I$6:$I$83,B24)+IF(B24=Inputs!$C$12,Inputs!$C$14*Inputs!$C$18,0) -> 0 | D24: =SUMIFS('KKR CF'!$F$6:$F$400,'KKR CF'!$E$6:$E$400,B24) -> 0 | E24: =D24-C24 -> 0 | F24: =SUM(E$6:E24) -> 2196844.5
B25: =EOMONTH(B24,1) -> 46934 | C25: =IF(B25=Inputs!$C$9,-Inputs!$C$17,0)+SUMIFS('Monthly Collections'!$H$6:$H$83,'Monthly Collections'!$I$6:$I$83,B25)+IF(B25=Inputs!$C$12,Inputs!$C$14*Inputs!$C$18,0) -> 4266299.9 | D25: =SUMIFS('KKR CF'!$F$6:$F$400,'KKR CF'!$E$6:$E$400,B25) -> 4419021.8 | E25: =D25-C25 -> 152721.85 | F25: =SUM(E$6:E25) -> 2349566.3
B26: =EOMONTH(B25,1) -> 46965 | C26: =IF(B26=Inputs!$C$9,-Inputs!$C$17,0)+SUMIFS('Monthly Collections'!$H$6:$H$83,'Monthly Collections'!$I$6:$I$83,B26)+IF(B26=Inputs!$C$12,Inputs!$C$14*Inputs!$C$18,0) -> 0 | D26: =SUMIFS('KKR CF'!$F$6:$F$400,'KKR CF'!$E$6:$E$400,B26) -> 0 | E26: =D26-C26 -> 0 | F26: =SUM(E$6:E26) -> 2349566.3
B27: =EOMONTH(B26,1) -> 46996 | C27: =IF(B27=Inputs!$C$9,-Inputs!$C$17,0)+SUMIFS('Monthly Collections'!$H$6:$H$83,'Monthly Collections'!$I$6:$I$83,B27)+IF(B27=Inputs!$C$12,Inputs!$C$14*Inputs!$C$18,0) -> 0 | D27: =SUMIFS('KKR CF'!$F$6:$F$400,'KKR CF'!$E$6:$E$400,B27) -> 0 | E27: =D27-C27 -> 0 | F27: =SUM(E$6:E27) -> 2349566.3
B28: =EOMONTH(B27,1) -> 47026 | C28: =IF(B28=Inputs!$C$9,-Inputs!$C$17,0)+SUMIFS('Monthly Collections'!$H$6:$H$83,'Monthly Collections'!$I$6:$I$83,B28)+IF(B28=Inputs!$C$12,Inputs!$C$14*Inputs!$C$18,0) -> 4165651 | D28: =SUMIFS('KKR CF'!$F$6:$F$400,'KKR CF'!$E$6:$E$400,B28) -> 4763460.1 | E28: =D28-C28 -> 597809.15 | F28: =SUM(E$6:E28) -> 2947375.5
B29: =EOMONTH(B28,1) -> 47057 | C29: =IF(B29=Inputs!$C$9,-Inputs!$C$17,0)+SUMIFS('Monthly Collections'!$H$6:$H$83,'Monthly Collections'!$I$6:$I$83,B29)+IF(B29=Inputs!$C$12,Inputs!$C$14*Inputs!$C$18,0) -> 0 | D29: =SUMIFS('KKR CF'!$F$6:$F$400,'KKR CF'!$E$6:$E$400,B29) -> 0 | E29: =D29-C29 -> 0 | F29: =SUM(E$6:E29) -> 2947375.5
B30: =EOMONTH(B29,1) -> 47087 | C30: =IF(B30=Inputs!$C$9,-Inputs!$C$17,0)+SUMIFS('Monthly Collections'!$H$6:$H$83,'Monthly Collections'!$I$6:$I$83,B30)+IF(B30=Inputs!$C$12,Inputs!$C$14*Inputs!$C$18,0) -> 0 | D30: =SUMIFS('KKR CF'!$F$6:$F$400,'KKR CF'!$E$6:$E$400,B30) -> 0 | E30: =D30-C30 -> 0 | F30: =SUM(E$6:E30) -> 2947375.5
B31: =EOMONTH(B30,1) -> 47118 | C31: =IF(B31=Inputs!$C$9,-Inputs!$C$17,0)+SUMIFS('Monthly Collections'!$H$6:$H$83,'Monthly Collections'!$I$6:$I$83,B31)+IF(B31=Inputs!$C$12,Inputs!$C$14*Inputs!$C$18,0) -> 3324917.4 | D31: =SUMIFS('KKR CF'!$F$6:$F$400,'KKR CF'!$E$6:$E$400,B31) -> 3178627.1 | E31: =D31-C31 -> -146290.22 | F31: =SUM(E$6:E31) -> 2801085.2
B32: =EOMONTH(B31,1) -> 47149 | C32: =IF(B32=Inputs!$C$9,-Inputs!$C$17,0)+SUMIFS('Monthly Collections'!$H$6:$H$83,'Monthly Collections'!$I$6:$I$83,B32)+IF(B32=Inputs!$C$12,Inputs!$C$14*Inputs!$C$18,0) -> 0 | D32: =SUMIFS('KKR CF'!$F$6:$F$400,'KKR CF'!$E$6:$E$400,B32) -> 0 | E32: =D32-C32 -> 0 | F32: =SUM(E$6:E32) -> 2801085.2
B33: =EOMONTH(B32,1) -> 47177 | C33: =IF(B33=Inputs!$C$9,-Inputs!$C$17,0)+SUMIFS('Monthly Collections'!$H$6:$H$83,'Monthly Collections'!$I$6:$I$83,B33)+IF(B33=Inputs!$C$12,Inputs!$C$14*Inputs!$C$18,0) -> 0 | D33: =SUMIFS('KKR CF'!$F$6:$F$400,'KKR CF'!$E$6:$E$400,B33) -> 0 | E33: =D33-C33 -> 0 | F33: =SUM(E$6:E33) -> 2801085.2
B34: =EOMONTH(B33,1) -> 47208 | C34: =IF(B34=Inputs!$C$9,-Inputs!$C$17,0)+SUMIFS('Monthly Collections'!$H$6:$H$83,'Monthly Collections'!$I$6:$I$83,B34)+IF(B34=Inputs!$C$12,Inputs!$C$14*Inputs!$C$18,0) -> 2640360.8 | D34: =SUMIFS('KKR CF'!$F$6:$F$400,'KKR CF'!$E$6:$E$400,B34) -> 2758894.9 | E34: =D34-C34 -> 118534.04 | F34: =SUM(E$6:E34) -> 2919619.3
B35: =EOMONTH(B34,1) -> 47238 | C35: =IF(B35=Inputs!$C$9,-Inputs!$C$17,0)+SUMIFS('Monthly Collections'!$H$6:$H$83,'Monthly Collections'!$I$6:$I$83,B35)+IF(B35=Inputs!$C$12,Inputs!$C$14*Inputs!$C$18,0) -> 0 | D35: =SUMIFS('KKR CF'!$F$6:$F$400,'KKR CF'!$E$6:$E$400,B35) -> 0 | E35: =D35-C35 -> 0 | F35: =SUM(E$6:E35) -> 2919619.3
... B78: =EOMONTH(B77,1) -> 48548 | C78: =IF(B78=Inputs!$C$9,-Inputs!$C$17,0)+SUMIFS('Monthly Collections'!$H$6:$H$83,'Monthly Collections'!$I$6:$I$83,B78)+IF(B78=Inputs!$C$12,Inputs!$C$14*Inputs!$C$18,0) -> 0 | D78: =SUMIFS('KKR CF'!$F$6:$F$400,'KKR CF'!$E$6:$E$400,B78) -> 0 | E78: =D78-C78 -> 0 | F78: =SUM(E$6:E78) -> 8582141.4
B79: Total | C79: =SUM(C6:C78) -> 1.0463297e+08 | D79: =SUM(D6:D78) -> 1.1321511e+08 | E79: =SUM(E6:E78) -> 8582141.4

Sheet Inputs
B2: SIDE BY SIDE CASH FLOW COMPARISON: INPUTS
B5: Assumption | C5: Value | D5: Notes
B6: Selling LP share of fund | C6: 0.3539823 | D6: KKR Assumptions!D5 / SSP Inputs!D11 (both 35.4%)
B7: Investor NAV ($) | C7: 3.3738401e+08 | D7: Same in both: SSP Inputs!D8, KKR Fwd Returns!I42
B8: SSP purchase price (% of NAV) | C8: 0.5 | D8: Set to 50% to match KKR. KKR side is pasted at 50%
B9: SSP closing / first distribution date | C9: 46387 | D9: SSP Inputs!D33
B10: KKR transaction date | C10: 46388 | D10: KKR Fwd Returns!I4
B11: KKR cash on hand at cutoff ($, 100% of fund) | C11: 15332622 | D11: KKR Assumptions!D32
B12: Cash release date used in SSP stream | C12: 46477 | D12: Assumption: KKR pays it through quarterly timing, first release 3/31/2027
B13: Toggle: SSP collections source (1 = SSP Intex, 2 = KKR collections) | C13: 1 | D13: Set to 2 to swap in KKR fund level collections (SSP quarterly bucketing kept)
B14: Toggle: add cash release to SSP stream (0 = no, 1 = yes) | C14: 0 | D14: Set to 1 to add cash on hand x selling LP share on the release date
B15: Cutoff date | C15: 46203 | D15: Intex settlement / KKR cutoff month
B17: SSP purchase price ($, 100% LP basis) | C17: =C7*C8 -> 1.68692e+08
B18: Cash release at selling LP share ($) | C18: =C11*C6 -> 5427476.7

Sheet SSP CF
B2: SSP MODEL: PASTE CF DROPS BASE CASE (DATE, PRINCIPAL, INTEREST)
B4: Paste from SSP file, CF Drops slot 1 (columns B:D from row 11 down) into B6:D. Column E sums principal plus interest. Extend the E formulas if you paste more rows.
B5: Date | C5: Principal | D5: Interest | E5: Total Fund CF
B6: 46203 | C6: 0 | D6: 0 | E6: =C6+D6 -> 0
B7: 46234 | C7: 0 | D7: 5801235 | E7: =C7+D7 -> 5801235
B8: 46265 | C8: 0 | D8: 6016712.8 | E8: =C8+D8 -> 6016712.8
B9: 46295 | C9: 0 | D9: 6157489.4 | E9: =C9+D9 -> 6157489.4
B10: 46326 | C10: 0 | D10: 5574857.1 | E10: =C10+D10 -> 5574857.1
B11: 46356 | C11: 0 | D11: 5760532 | E11: =C11+D11 -> 5760532
B12: 46387 | C12: 0 | D12: 5574473.8 | E12: =C12+D12 -> 5574473.8
B13: 46418 | C13: 0 | D13: 5534797.2 | E13: =C13+D13 -> 5534797.2
B14: 46446 | C14: 0 | D14: 5535683.1 | E14: =C14+D14 -> 5535683.1
B15: 46477 | C15: 0 | D15: 5336678.6 | E15: =C15+D15 -> 5336678.6
B16: 46507 | C16: 0 | D16: 5333537.1 | E16: =C16+D16 -> 5333537.1
B17: 46538 | C17: 0 | D17: 5159473.9 | E17: =C17+D17 -> 5159473.9
... B77: 48365 | C77: 34854677 | D77: 265727.12 | E77: =C77+D77 -> 35120404

Sheet KKR CF
B2: KKR MODEL: PASTE GROSS COLLECTIONS AND INVESTOR CASH FLOWS
B4: Left table: KKR HTM Output row 171 (Gross Distributions, 100% of fund), dates from row 6, cutoff onward. Right table: KKR Fwd Returns row 63 (Gross B Piece Cash Flows to investor, includes purchase price) and row 60 (cash and receivables release), dates from row 11. Pulled here from the zero fee recalculation.
B5: Date | C5: Fund Gross Distributions | E5: Date | F5: Investor Gross CF (Row 63) | G5: Cash and Receivables Release (Row 60)
B6: 46234 | C6: 5801235 | E6: 46388 | F6: -1.5634323e+08 | G6: 0
B7: 46265 | C7: 6016712.8 | E7: 46418 | F7: 0 | G7: -1959220.2
B8: 46295 | C8: 6157489.4 | E8: 46446 | F8: 0 | G8: -1959533.8
B9: 46326 | C9: 5574857.1 | E9: 46477 | F9: 6162754.2 | G9: 4273664.5
B10: 46356 | C10: 5760532 | E10: 46507 | F10: 0 | G10: -1887977.7
B11: 46387 | C11: 5574473.8 | E11: 46538 | F11: 0 | G11: -1826362.4
B12: 46418 | C12: 5534797.2 | E12: 46568 | F12: 5556569.7 | G12: 3721419.8
B13: 46446 | C13: 5535683.1 | E13: 46599 | F13: 0 | G13: -1789431.1
B14: 46477 | C14: 5336678.6 | E14: 46630 | F14: 0 | G14: -1819182.7
B15: 46507 | C15: 5333537.1 | E15: 46660 | F15: 5389272.5 | G15: 3608613.8
B16: 46538 | C16: 5159473.9 | E16: 46691 | F16: 0 | G16: -1604074.3
B17: 46568 | C17: 5184298.6 | E17: 46721 | F17: 0 | G17: -1611126.3
... B83: 48579 | C83: 0 | E83: 48730 | F83: 0 | G83: 0
E84: 48760 | F84: 0 | G84: 0
E85: 48791 | F85: 0 | G85: 0
E86: 48822 | F86: 0 | G86: 0
E87: 48852 | F87: 0 | G87: 0
E88: 48883 | F88: 0 | G88: 0
E89: 48913 | F89: 0 | G89: 0
E90: 48944 | F90: 0 | G90: 0

Sheet Monthly Collections
B2: FUND LEVEL COLLECTIONS: SSP VS KKR (100% OF FUND)
B5: Month | C5: SSP Model (Intex) | D5: KKR Model (Gross Distributions) | E5: Difference (KKR less SSP) | F5: Cumulative Difference | G5: Collections Used in SSP Stream | H5: Selling LP Share | I5: SSP Payment Date
B6: =EOMONTH(Inputs!$C$15,1) -> 46234 | C6: =SUMIFS('SSP CF'!$E$6:$E$77,'SSP CF'!$B$6:$B$77,B6) -> 5801235 | D6: =SUMIFS('KKR CF'!$C$6:$C$400,'KKR CF'!$B$6:$B$400,B6) -> 5801235 | E6: =D6-C6 -> 0 | F6: =SUM(E$6:E6) -> 0 | G6: =IF(Inputs!$C$13=2,D6,C6) -> 5801235 | H6: =G6*Inputs!$C$6 -> 2053534.5 | I6: =IF(B6<Inputs!$C$9,Inputs!$C$9,EOMONTH(Inputs!$C$9,3*(INT(((YEAR(B6)-YEAR(Inputs!$C$9))*12+MONTH(B6)-MONTH(Inputs!$C$9))/3)+1))) -> 46387
B7: =EOMONTH(B6,1) -> 46265 | C7: =SUMIFS('SSP CF'!$E$6:$E$77,'SSP CF'!$B$6:$B$77,B7) -> 6016712.8 | D7: =SUMIFS('KKR CF'!$C$6:$C$400,'KKR CF'!$B$6:$B$400,B7) -> 6016712.8 | E7: =D7-C7 -> 0 | F7: =SUM(E$6:E7) -> 0 | G7: =IF(Inputs!$C$13=2,D7,C7) -> 6016712.8 | H7: =G7*Inputs!$C$6 -> 2129809.8 | I7: =IF(B7<Inputs!$C$9,Inputs!$C$9,EOMONTH(Inputs!$C$9,3*(INT(((YEAR(B7)-YEAR(Inputs!$C$9))*12+MONTH(B7)-MONTH(Inputs!$C$9))/3)+1))) -> 46387
B8: =EOMONTH(B7,1) -> 46295 | C8: =SUMIFS('SSP CF'!$E$6:$E$77,'SSP CF'!$B$6:$B$77,B8) -> 6157489.4 | D8: =SUMIFS('KKR CF'!$C$6:$C$400,'KKR CF'!$B$6:$B$400,B8) -> 6157489.4 | E8: =D8-C8 -> 0 | F8: =SUM(E$6:E8) -> 0 | G8: =IF(Inputs!$C$13=2,D8,C8) -> 6157489.4 | H8: =G8*Inputs!$C$6 -> 2179642.3 | I8: =IF(B8<Inputs!$C$9,Inputs!$C$9,EOMONTH(Inputs!$C$9,3*(INT(((YEAR(B8)-YEAR(Inputs!$C$9))*12+MONTH(B8)-MONTH(Inputs!$C$9))/3)+1))) -> 46387
B9: =EOMONTH(B8,1) -> 46326 | C9: =SUMIFS('SSP CF'!$E$6:$E$77,'SSP CF'!$B$6:$B$77,B9) -> 5574857.1 | D9: =SUMIFS('KKR CF'!$C$6:$C$400,'KKR CF'!$B$6:$B$400,B9) -> 5574857.1 | E9: =D9-C9 -> 0 | F9: =SUM(E$6:E9) -> 0 | G9: =IF(Inputs!$C$13=2,D9,C9) -> 5574857.1 | H9: =G9*Inputs!$C$6 -> 1973400.7 | I9: =IF(B9<Inputs!$C$9,Inputs!$C$9,EOMONTH(Inputs!$C$9,3*(INT(((YEAR(B9)-YEAR(Inputs!$C$9))*12+MONTH(B9)-MONTH(Inputs!$C$9))/3)+1))) -> 46387
B10: =EOMONTH(B9,1) -> 46356 | C10: =SUMIFS('SSP CF'!$E$6:$E$77,'SSP CF'!$B$6:$B$77,B10) -> 5760532 | D10: =SUMIFS('KKR CF'!$C$6:$C$400,'KKR CF'!$B$6:$B$400,B10) -> 5760532 | E10: =D10-C10 -> 0 | F10: =SUM(E$6:E10) -> 0 | G10: =IF(Inputs!$C$13=2,D10,C10) -> 5760532 | H10: =G10*Inputs!$C$6 -> 2039126.4 | I10: =IF(B10<Inputs!$C$9,Inputs!$C$9,EOMONTH(Inputs!$C$9,3*(INT(((YEAR(B10)-YEAR(Inputs!$C$9))*12+MONTH(B10)-MONTH(Inputs!$C$9))/3)+1))) -> 46387
B11: =EOMONTH(B10,1) -> 46387 | C11: =SUMIFS('SSP CF'!$E$6:$E$77,'SSP CF'!$B$6:$B$77,B11) -> 5574473.8 | D11: =SUMIFS('KKR CF'!$C$6:$C$400,'KKR CF'!$B$6:$B$400,B11) -> 5574473.8 | E11: =D11-C11 -> 0 | F11: =SUM(E$6:E11) -> 0 | G11: =IF(Inputs!$C$13=2,D11,C11) -> 5574473.8 | H11: =G11*Inputs!$C$6 -> 1973265 | I11: =IF(B11<Inputs!$C$9,Inputs!$C$9,EOMONTH(Inputs!$C$9,3*(INT(((YEAR(B11)-YEAR(Inputs!$C$9))*12+MONTH(B11)-MONTH(Inputs!$C$9))/3)+1))) -> 46477
B12: =EOMONTH(B11,1) -> 46418 | C12: =SUMIFS('SSP CF'!$E$6:$E$77,'SSP CF'!$B$6:$B$77,B12) -> 5534797.2 | D12: =SUMIFS('KKR CF'!$C$6:$C$400,'KKR CF'!$B$6:$B$400,B12) -> 5534797.2 | E12: =D12-C12 -> 0 | F12: =SUM(E$6:E12) -> 0 | G12: =IF(Inputs!$C$13=2,D12,C12) -> 5534797.2 | H12: =G12*Inputs!$C$6 -> 1959220.2 | I12: =IF(B12<Inputs!$C$9,Inputs!$C$9,EOMONTH(Inputs!$C$9,3*(INT(((YEAR(B12)-YEAR(Inputs!$C$9))*12+MONTH(B12)-MONTH(Inputs!$C$9))/3)+1))) -> 46477
B13: =EOMONTH(B12,1) -> 46446 | C13: =SUMIFS('SSP CF'!$E$6:$E$77,'SSP CF'!$B$6:$B$77,B13) -> 5535683.1 | D13: =SUMIFS('KKR CF'!$C$6:$C$400,'KKR CF'!$B$6:$B$400,B13) -> 5535683.1 | E13: =D13-C13 -> 0 | F13: =SUM(E$6:E13) -> 0 | G13: =IF(Inputs!$C$13=2,D13,C13) -> 5535683.1 | H13: =G13*Inputs!$C$6 -> 1959533.8 | I13: =IF(B13<Inputs!$C$9,Inputs!$C$9,EOMONTH(Inputs!$C$9,3*(INT(((YEAR(B13)-YEAR(Inputs!$C$9))*12+MONTH(B13)-MONTH(Inputs!$C$9))/3)+1))) -> 46477
B14: =EOMONTH(B13,1) -> 46477 | C14: =SUMIFS('SSP CF'!$E$6:$E$77,'SSP CF'!$B$6:$B$77,B14) -> 5336678.6 | D14: =SUMIFS('KKR CF'!$C$6:$C$400,'KKR CF'!$B$6:$B$400,B14) -> 5336678.6 | E14: =D14-C14 -> 0 | F14: =SUM(E$6:E14) -> 0 | G14: =IF(Inputs!$C$13=2,D14,C14) -> 5336678.6 | H14: =G14*Inputs!$C$6 -> 1889089.8 | I14: =IF(B14<Inputs!$C$9,Inputs!$C$9,EOMONTH(Inputs!$C$9,3*(INT(((YEAR(B14)-YEAR(Inputs!$C$9))*12+MONTH(B14)-MONTH(Inputs!$C$9))/3)+1))) -> 46568
B15: =EOMONTH(B14,1) -> 46507 | C15: =SUMIFS('SSP CF'!$E$6:$E$77,'SSP CF'!$B$6:$B$77,B15) -> 5333537.1 | D15: =SUMIFS('KKR CF'!$C$6:$C$400,'KKR CF'!$B$6:$B$400,B15) -> 5333537.1 | E15: =D15-C15 -> 0 | F15: =SUM(E$6:E15) -> 0 | G15: =IF(Inputs!$C$13=2,D15,C15) -> 5333537.1 | H15: =G15*Inputs!$C$6 -> 1887977.7 | I15: =IF(B15<Inputs!$C$9,Inputs!$C$9,EOMONTH(Inputs!$C$9,3*(INT(((YEAR(B15)-YEAR(Inputs!$C$9))*12+MONTH(B15)-MONTH(Inputs!$C$9))/3)+1))) -> 46568
B16: =EOMONTH(B15,1) -> 46538 | C16: =SUMIFS('SSP CF'!$E$6:$E$77,'SSP CF'!$B$6:$B$77,B16) -> 5159473.9 | D16: =SUMIFS('KKR CF'!$C$6:$C$400,'KKR CF'!$B$6:$B$400,B16) -> 5159473.9 | E16: =D16-C16 -> 0 | F16: =SUM(E$6:E16) -> 0 | G16: =IF(Inputs!$C$13=2,D16,C16) -> 5159473.9 | H16: =G16*Inputs!$C$6 -> 1826362.4 | I16: =IF(B16<Inputs!$C$9,Inputs!$C$9,EOMONTH(Inputs!$C$9,3*(INT(((YEAR(B16)-YEAR(Inputs!$C$9))*12+MONTH(B16)-MONTH(Inputs!$C$9))/3)+1))) -> 46568
B17: =EOMONTH(B16,1) -> 46568 | C17: =SUMIFS('SSP CF'!$E$6:$E$77,'SSP CF'!$B$6:$B$77,B17) -> 5184298.6 | D17: =SUMIFS('KKR CF'!$C$6:$C$400,'KKR CF'!$B$6:$B$400,B17) -> 5184298.6 | E17: =D17-C17 -> 0 | F17: =SUM(E$6:E17) -> 0 | G17: =IF(Inputs!$C$13=2,D17,C17) -> 5184298.6 | H17: =G17*Inputs!$C$6 -> 1835149.9 | I17: =IF(B17<Inputs!$C$9,Inputs!$C$9,EOMONTH(Inputs!$C$9,3*(INT(((YEAR(B17)-YEAR(Inputs!$C$9))*12+MONTH(B17)-MONTH(Inputs!$C$9))/3)+1))) -> 46660
B18: =EOMONTH(B17,1) -> 46599 | C18: =SUMIFS('SSP CF'!$E$6:$E$77,'SSP CF'!$B$6:$B$77,B18) -> 5055142.9 | D18: =SUMIFS('KKR CF'!$C$6:$C$400,'KKR CF'!$B$6:$B$400,B18) -> 5055142.9 | E18: =D18-C18 -> 0 | F18: =SUM(E$6:E18) -> 0 | G18: =IF(Inputs!$C$13=2,D18,C18) -> 5055142.9 | H18: =G18*Inputs!$C$6 -> 1789431.1 | I18: =IF(B18<Inputs!$C$9,Inputs!$C$9,EOMONTH(Inputs!$C$9,3*(INT(((YEAR(B18)-YEAR(Inputs!$C$9))*12+MONTH(B18)-MONTH(Inputs!$C$9))/3)+1))) -> 46660
... B83: =EOMONTH(B82,1) -> 48579 | C83: =SUMIFS('SSP CF'!$E$6:$E$77,'SSP CF'!$B$6:$B$77,B83) -> 0 | D83: =SUMIFS('KKR CF'!$C$6:$C$400,'KKR CF'!$B$6:$B$400,B83) -> 0 | E83: =D83-C83 -> 0 | F83: =SUM(E$6:E83) -> 8911927.8 | G83: =IF(Inputs!$C$13=2,D83,C83) -> 0 | H83: =G83*Inputs!$C$6 -> 0 | I83: =IF(B83<Inputs!$C$9,Inputs!$C$9,EOMONTH(Inputs!$C$9,3*(INT(((YEAR(B83)-YEAR(Inputs!$C$9))*12+MONTH(B83)-MONTH(Inputs!$C$9))/3)+1))) -> 48669
B84: Total | C84: =SUM(C6:C83) -> 7.7214306e+08 | D84: =SUM(D6:D83) -> 7.8105499e+08 | E84: =SUM(E6:E83) -> 8911927.8 | G84: =SUM(G6:G83) -> 7.7214306e+08 | H84: =SUM(H6:H83) -> 2.7332498e+08
