Workbook

Sheet Instructions
B2: TEMPLATE INSTRUCTIONS
B4: STEP | C4: WHAT TO DO
B5: 1. Tape | C5: Paste the lender data tape into Tape!B7:ME36 (one asset per row, up to 30 assets). Keep the column order of the header rows 2 to 5.
C6: Set the nine period labels once in Tape!T5:AB5 (years must be numbers, e.g. 2025). Every other period block, the asset tabs and the Rollup pick them up automatically.
C7: Row labels in Tape row 2 must match the line item labels in column C of the asset tabs. Do not rename them.
B8: 2. Cap Stack | C8: Enter the class, rating, size and spread (bps) for each tranche in 'Cap Stack Control'!F15:S22, the index rate in I28, and the IG / Non-IG tag in K28:K35.
C9: Enter deal name (D4), estimated appraised value (D9) and PIP reserve (D12). SSP hold amounts go in column U.
B10: 3. UW Drivers | C10: Asset names and history populate from the Tape. Set Sixth Street occupancy in P (defaults to TTM), cap rate in AA, as-is capex / key in AC, franchise fee in AH, and any override NOI margin in X. Set V to No to use the in-place NOI.
B11: 4. Capex | C11: Optional: paste historical capex by year in Capex!E6:N35. Start year is set in Capex!E5; Rollup!AB1 sets which year is matched to the TTM column.
B12: 5. S&U | C12: Mortgage loan links to the cap stack total. Enter the uses and sponsor equity; M10 checks that sources equal uses.
B13: Asset tabs | C13: Tabs 1 to 30 sit between START and END and pull their asset from the Tape by row order. Unused tabs show dashes and add nothing to the Rollup; they can be deleted. To add assets beyond 30, copy tab 1, rename it with the next number, place it before END, and change the row number inside the formula in C3.
B14: Colour key | C14: Blue font = input. Black font = formula. Blank slots show "-" because division formulas are wrapped in IFERROR.

Sheet Cap Stack Control
C3: Deal / Property Info
C4: Deal Name | D4: [Deal Name]
C5: Keys | D5: =Rollup!$AN$4 -> 0
C6: TTM NOI | D6: =Rollup!$AB$53 -> 0
C7: SSP IP NOI | D7: ='SSP UW Summary'!$O$36 -> 0
C8: SSP Stresed NOI | D8: =SUM('UW Drivers'!$W$9:$W$38) -> 0
C9: Est. Appraised Value
C10: SSP Stressed Value | D10: ='UW Drivers'!AE40+D12 -> 0
C11: SSP IP Value | D11: ='UW Drivers'!AD40+D12 -> 0
C12: PIP Reserve | F12: =$D$4&" - Capital Stack" -> [Deal Name] - Capital Stack
S13: Pricing | U13: SSP Order
F14: Class | G14: Rating (M / KBRA) | H14: Size | I14: % of Deal | J14: Cum. | K14: % CE | L14: $ / Key | M14: =Tape!$Z$5&" DY" -> TTM DY | N14: SSP In-Place DY | O14: SSP Stressed DY | P14: Est. Appr.LTV | Q14: SSP In-Place LTV | R14: SSP Stressed LTV | S14: DM | T14: Cum. DM | U14: SSP Hold | V14: % of Class | W14: Blended DM
C15: IG Bifurcation | F15: A | I15: =IFERROR(H15/$H$23,0) -> 0 | J15: =SUM(H$15:H15) -> 0 | K15: =IFERROR(SUM(H16:H$22)/$H$23,0) -> 0 | L15: =IFERROR(J15/$D$5,0) -> 0 | M15: =IFERROR($D$6/J15,0) -> 0 | N15: =IFERROR($D$7/J15,0) -> 0 | O15: =IFERROR($D$8/J15,0) -> 0 | P15: =IFERROR(J15/$D$9,0) -> 0 | Q15: =IFERROR(J15/$D$11,0) -> 0 | R15: =IFERROR(J15/$D$10,0) -> 0 | T15: =IFERROR(SUMPRODUCT(S$15:S15,H$15:H15)/J15,0) -> 0 | V15: =IFERROR(U15/$H15,0) -> 0 | W15: =IF(U15=0,"-",IFERROR(SUMPRODUCT($S$15:$S15,U$15:U15)/SUM(U$15:U15),"-")) -> -
C16: Portion | D16: Size | F16: B | I16: =IFERROR(H16/$H$23,0) -> 0 | J16: =SUM(H$15:H16) -> 0 | K16: =IFERROR(SUM(H17:H$22)/$H$23,0) -> 0 | L16: =IFERROR(J16/$D$5,0) -> 0 | M16: =IFERROR($D$6/J16,0) -> 0 | N16: =IFERROR($D$7/J16,0) -> 0 | O16: =IFERROR($D$8/J16,0) -> 0 | P16: =IFERROR(J16/$D$9,0) -> 0 | Q16: =IFERROR(J16/$D$11,0) -> 0 | R16: =IFERROR(J16/$D$10,0) -> 0 | T16: =IFERROR(SUMPRODUCT(S$15:S16,H$15:H16)/J16,0) -> 0 | V16: =IFERROR(U16/$H16,0) -> 0 | W16: =IF(U16=0,"-",IFERROR(SUMPRODUCT($S$15:$S16,U$15:U16)/SUM(U$15:U16),"-")) -> -
C17: IG | D17: =SUMIFS($G$28:$G$35,$K$28:$K$35,C17) -> 0 | F17: C | I17: =IFERROR(H17/$H$23,0) -> 0 | J17: =SUM(H$15:H17) -> 0 | K17: =IFERROR(SUM(H18:H$22)/$H$23,0) -> 0 | L17: =IFERROR(J17/$D$5,0) -> 0 | M17: =IFERROR($D$6/J17,0) -> 0 | N17: =IFERROR($D$7/J17,0) -> 0 | O17: =IFERROR($D$8/J17,0) -> 0 | P17: =IFERROR(J17/$D$9,0) -> 0 | Q17: =IFERROR(J17/$D$11,0) -> 0 | R17: =IFERROR(J17/$D$10,0) -> 0 | T17: =IFERROR(SUMPRODUCT(S$15:S17,H$15:H17)/J17,0) -> 0 | V17: =IFERROR(U17/$H17,0) -> 0 | W17: =IF(U17=0,"-",IFERROR(SUMPRODUCT($S$15:$S17,U$15:U17)/SUM(U$15:U17),"-")) -> -
C18: Non-IG | D18: =SUMIFS($G$28:$G$35,$K$28:$K$35,C18) -> 0 | F18: D | I18: =IFERROR(H18/$H$23,0) -> 0 | J18: =SUM(H$15:H18) -> 0 | K18: =IFERROR(SUM(H19:H$22)/$H$23,0) -> 0 | L18: =IFERROR(J18/$D$5,0) -> 0 | M18: =IFERROR($D$6/J18,0) -> 0 | N18: =IFERROR($D$7/J18,0) -> 0 | O18: =IFERROR($D$8/J18,0) -> 0 | P18: =IFERROR(J18/$D$9,0) -> 0 | Q18: =IFERROR(J18/$D$11,0) -> 0 | R18: =IFERROR(J18/$D$10,0) -> 0 | T18: =IFERROR(SUMPRODUCT(S$15:S18,H$15:H18)/J18,0) -> 0 | V18: =IFERROR(U18/$H18,0) -> 0 | W18: =IF(U18=0,"-",IFERROR(SUMPRODUCT($S$15:$S18,U$15:U18)/SUM(U$15:U18),"-")) -> -
C19: Total | D19: =SUM(D17:D18) -> 0 | F19: E | I19: =IFERROR(H19/$H$23,0) -> 0 | J19: =SUM(H$15:H19) -> 0 | K19: =IFERROR(SUM(H20:H$22)/$H$23,0) -> 0 | L19: =IFERROR(J19/$D$5,0) -> 0 | M19: =IFERROR($D$6/J19,0) -> 0 | N19: =IFERROR($D$7/J19,0) -> 0 | O19: =IFERROR($D$8/J19,0) -> 0 | P19: =IFERROR(J19/$D$9,0) -> 0 | Q19: =IFERROR(J19/$D$11,0) -> 0 | R19: =IFERROR(J19/$D$10,0) -> 0 | T19: =IFERROR(SUMPRODUCT(S$15:S19,H$15:H19)/J19,0) -> 0 | V19: =IFERROR(U19/$H19,0) -> 0 | W19: =IF(U19=0,"-",IFERROR(SUMPRODUCT($S$15:$S19,U$15:U19)/SUM(U$15:U19),"-")) -> -
F20: F | I20: =IFERROR(H20/$H$23,0) -> 0 | J20: =SUM(H$15:H20) -> 0 | K20: =IFERROR(SUM(H21:H$22)/$H$23,0) -> 0 | L20: =IFERROR(J20/$D$5,0) -> 0 | M20: =IFERROR($D$6/J20,0) -> 0 | N20: =IFERROR($D$7/J20,0) -> 0 | O20: =IFERROR($D$8/J20,0) -> 0 | P20: =IFERROR(J20/$D$9,0) -> 0 | Q20: =IFERROR(J20/$D$11,0) -> 0 | R20: =IFERROR(J20/$D$10,0) -> 0 | T20: =IFERROR(SUMPRODUCT(S$15:S20,H$15:H20)/J20,0) -> 0 | V20: =IFERROR(U20/$H20,0) -> 0 | W20: =IF(U20=0,"-",IFERROR(SUMPRODUCT($S$15:$S20,U$15:U20)/SUM(U$15:U20),"-")) -> -
F21: G | I21: =IFERROR(H21/$H$23,0) -> 0 | J21: =SUM(H$15:H21) -> 0 | K21: =IFERROR(SUM(H22:H$22)/$H$23,0) -> 0 | L21: =IFERROR(J21/$D$5,0) -> 0 | M21: =IFERROR($D$6/J21,0) -> 0 | N21: =IFERROR($D$7/J21,0) -> 0 | O21: =IFERROR($D$8/J21,0) -> 0 | P21: =IFERROR(J21/$D$9,0) -> 0 | Q21: =IFERROR(J21/$D$11,0) -> 0 | R21: =IFERROR(J21/$D$10,0) -> 0 | T21: =IFERROR(SUMPRODUCT(S$15:S21,H$15:H21)/J21,0) -> 0 | V21: =IFERROR(U21/$H21,0) -> 0 | W21: =IF(U21=0,"-",IFERROR(SUMPRODUCT($S$15:$S21,U$15:U21)/SUM(U$15:U21),"-")) -> -
F22: HRR | I22: =IFERROR(H22/$H$23,0) -> 0 | J22: =SUM(H$15:H22) -> 0 | K22: - | L22: =IFERROR(J22/$D$5,0) -> 0 | M22: =IFERROR($D$6/J22,0) -> 0 | N22: =IFERROR($D$7/J22,0) -> 0 | O22: =IFERROR($D$8/J22,0) -> 0 | P22: =IFERROR(J22/$D$9,0) -> 0 | Q22: =IFERROR(J22/$D$11,0) -> 0 | R22: =IFERROR(J22/$D$10,0) -> 0 | T22: =IFERROR(SUMPRODUCT(S$15:S22,H$15:H22)/J22,0) -> 0 | V22: =IFERROR(U22/$H22,0) -> 0 | W22: =IF(U22=0,"-",IFERROR(SUMPRODUCT($S$15:$S22,U$15:U22)/SUM(U$15:U22),"-")) -> -
F23: Total SASB | H23: =SUM(H15:H22) -> 0 | I23: =IFERROR(H23/$H$23,0) -> 0 | J23: =J22 -> 0 | K23: - | L23: =IFERROR(J23/$D$5,0) -> 0 | M23: =IFERROR($D$6/J23,0) -> 0 | N23: =IFERROR($D$7/J23,0) -> 0 | O23: =IFERROR($D$8/J23,0) -> 0 | P23: =IFERROR(J23/$D$9,0) -> 0 | Q23: =IFERROR(J23/$D$11,0) -> 0 | R23: =IFERROR(J23/$D$10,0) -> 0 | S23: =IFERROR(SUMPRODUCT(S15:S22,$H$15:$H$22)/SUM(H15:H22),0) -> 0 | T23: =T22 -> 0 | U23: =SUM(U15:U22) -> 0 | V23: =IFERROR(U23/$H23,0) -> 0 | W23: =IF(U23=0,"-",IFERROR(SUMPRODUCT($S$15:$S$22,U$15:U$22)/U23,"-")) -> -
F26: Debt Service Calculations
F27: Class | G27: Size | H27: Spread | I27: Index | J27: Debt Service | K27: IG Tag
F28: =F15 -> A | G28: =H15 -> 0 | H28: =IFERROR(S15/10000,0) -> 0 | J28: =IFERROR(G28*(H28+I28)*365/360,0) -> 0 | K28: IG
F29: =F16 -> B | G29: =H16 -> 0 | H29: =IFERROR(S16/10000,0) -> 0 | I29: =$I$28 -> 0 | J29: =IFERROR(G29*(H29+I29)*365/360,0) -> 0 | K29: IG
F30: =F17 -> C | G30: =H17 -> 0 | H30: =IFERROR(S17/10000,0) -> 0 | I30: =$I$28 -> 0 | J30: =IFERROR(G30*(H30+I30)*365/360,0) -> 0 | K30: IG
F31: =F18 -> D | G31: =H18 -> 0 | H31: =IFERROR(S18/10000,0) -> 0 | I31: =$I$28 -> 0 | J31: =IFERROR(G31*(H31+I31)*365/360,0) -> 0 | K31: IG
F32: =F19 -> E | G32: =H19 -> 0 | H32: =IFERROR(S19/10000,0) -> 0 | I32: =$I$28 -> 0 | J32: =IFERROR(G32*(H32+I32)*365/360,0) -> 0 | K32: Non-IG
F33: =F20 -> F | G33: =H20 -> 0 | H33: =IFERROR(S20/10000,0) -> 0 | I33: =$I$28 -> 0 | J33: =IFERROR(G33*(H33+I33)*365/360,0) -> 0 | K33: Non-IG
F34: =F21 -> G | G34: =H21 -> 0 | H34: =IFERROR(S21/10000,0) -> 0 | I34: =$I$28 -> 0 | J34: =IFERROR(G34*(H34+I34)*365/360,0) -> 0 | K34: Non-IG
F35: =F22 -> HRR | G35: =H22 -> 0 | H35: =IFERROR(S22/10000,0) -> 0 | I35: =$I$28 -> 0 | J35: =IFERROR(G35*(H35+I35)*365/360,0) -> 0 | K35: Non-IG

Sheet S&U
C1: Keys | D1: ='Cap Stack Control'!$D$5 -> 0
C3: Project Capitalization
C4: Sources | D4: $ | E4: $ / Key | F4: % | H4: Uses | I4: $ | J4: $ / Key | K4: %
C5: Mortgage Loan | D5: ='Cap Stack Control'!$H$23 -> 0 | E5: =IFERROR(SUM(D$5:D5)/$D$1,0) -> 0 | F5: =IFERROR(SUM(D$5:D5)/$D$10,0) -> 0 | H5: Refinance Existing Debt | J5: =IFERROR(I5/$D$1,0) -> 0 | K5: =IFERROR(I5/$I$10,0) -> 0
C6: Sponsor Equity | E6: =IFERROR(SUM(D$5:D6)/$D$1,0) -> 0 | F6: =IFERROR(SUM(D$5:D6)/$D$10,0) -> 0 | H6: Upfront PIP Reserve | J6: =IFERROR(I6/$D$1,0) -> 0 | K6: =IFERROR(I6/$I$10,0) -> 0
H7: Estimated Closing Costs | J7: =IFERROR(I7/$D$1,0) -> 0 | K7: =IFERROR(I7/$I$10,0) -> 0
H8: Return of Equity to Sponsor | J8: =IFERROR(I8/$D$1,0) -> 0 | K8: =IFERROR(I8/$I$10,0) -> 0
C10: Total Sources | D10: =SUM(D5:D8) -> 0 | E10: =IFERROR(D10/D1,0) -> 0 | F10: =IFERROR(D10/D10,0) -> 0 | H10: Total Uses | I10: =SUM(I5:I8) -> 0 | J10: =IFERROR(I10/$D$1,0) -> 0 | K10: =IFERROR(I10/$I$10,0) -> 0 | M10: =I10=D10 -> TRUE

Sheet UW Drivers
F1: AN6 | G1: X9 | H1: X10 | I1: X11 | J1: AB9 | K1: AB10 | L1: AB11 | M1: AF9 | N1: AF10 | O1: AF11 | S1: AN19 | T1: AN55 | U1: AO55 | W1: AN55
D3: Franchise Fee Floor | E3: 0.06
D4: CapEx Hit / Key | E4: 15000
D5: Normalized NOI Margin | E5: 0.25
G7: =Tape!$Y$5 -> 2025 | J7: =Tape!$Z$5 -> TTM | M7: =Tape!$AA$5 -> Reforecast | P7: Sixth Street UW
C8: No. | D8: Asset | E8: Year Built | F8: Keys | G8: Occ | H8: ADR | I8: RevPAR | J8: Occ | K8: ADR | L8: RevPAR | M8: Occ | N8: ADR | O8: RevPAR | P8: Occ | Q8: ADR | R8: RevPAR | S8: Total Revenue | T8: In-Place NOI | U8: Natural NOI Margin | V8: Normalize NOI Margin | W8: Stressed NOI | X8: Override NOI Margin | Y8: UW NOI Margin | Z8: Check | AA8: Cap Rate | AB8: Gross Value (Inc. Capex) | AC8: As-Is Capex ($ / Key) | AD8: Base Case Property Value | AE8: Stressed Value | AF8: $ / Key | AH8: Franchise Fee | AJ8: NOI per Key | AK8: Valuation Commentary
C9: 1 | D9: =IF(INDEX(Tape!$C$7:$C$36,$C9)="","",INDEX(Tape!$C$7:$C$36,$C9)) | E9: =IFERROR(INDEX(Tape!$O$7:$O$36,MATCH('UW Drivers'!$D9,Tape!$C$7:$C$36,0)),0) -> 0 | F9: =IFERROR(INDIRECT("'" & $C9 & "'!" & F$1),0) -> 0 | G9: =IFERROR(INDIRECT("'" & $C9 & "'!" & G$1),0) -> 0 | H9: =IFERROR(INDIRECT("'" & $C9 & "'!" & H$1),0) -> 0 | I9: =IFERROR(INDIRECT("'" & $C9 & "'!" & I$1),0) -> 0 | J9: =IFERROR(INDIRECT("'" & $C9 & "'!" & J$1),0) -> 0 | K9: =IFERROR(INDIRECT("'" & $C9 & "'!" & K$1),0) -> 0 | L9: =IFERROR(INDIRECT("'" & $C9 & "'!" & L$1),0) -> 0 | M9: =IFERROR(INDIRECT("'" & $C9 & "'!" & M$1),0) -> 0 | ... O9: =IFERROR(INDIRECT("'" & $C9 & "'!" & O$1),0) -> 0 | P9: =J9 -> 0 | Q9: =K9 -> 0 | R9: =P9*Q9 -> 0 | S9: =IFERROR(INDIRECT("'" & $C9 & "'!" & S$1),0) -> 0 | T9: =IFERROR(INDIRECT("'" & $C9 & "'!" & T$1),0) -> 0 | U9: =IFERROR(INDIRECT("'" & $C9 & "'!" & U$1),0) -> 0 | V9: Yes | W9: =IFERROR(IF(V9="No",INDIRECT("'"&$C9&"'!"&W$1),S9*Y9),0) -> 0 | Y9: =IF(X9>0,X9,U9) -> 0 | Z9: =IFERROR(W9/S9,0) -> 0 | AB9: =IFERROR(ROUND(T9/AA9,-5),0) -> 0 | AD9: =AB9-(AC9*F9) -> 0 | AE9: =IFERROR(ROUND(W9/AA9,-5)-(AC9*F9),0) -> 0 | AF9: =IFERROR(AE9/F9,0) -> 0 | AI9: =AC9*F9 -> 0 | AJ9: =IFERROR(+W9/$F9,0) -> 0
C10: =C9+1 -> 2 | D10: =IF(INDEX(Tape!$C$7:$C$36,$C10)="","",INDEX(Tape!$C$7:$C$36,$C10)) | E10: =IFERROR(INDEX(Tape!$O$7:$O$36,MATCH('UW Drivers'!$D10,Tape!$C$7:$C$36,0)),0) -> 0 | F10: =IFERROR(INDIRECT("'" & $C10 & "'!" & F$1),0) -> 0 | G10: =IFERROR(INDIRECT("'" & $C10 & "'!" & G$1),0) -> 0 | H10: =IFERROR(INDIRECT("'" & $C10 & "'!" & H$1),0) -> 0 | I10: =IFERROR(INDIRECT("'" & $C10 & "'!" & I$1),0) -> 0 | J10: =IFERROR(INDIRECT("'" & $C10 & "'!" & J$1),0) -> 0 | K10: =IFERROR(INDIRECT("'" & $C10 & "'!" & K$1),0) -> 0 | L10: =IFERROR(INDIRECT("'" & $C10 & "'!" & L$1),0) -> 0 | M10: =IFERROR(INDIRECT("'" & $C10 & "'!" & M$1),0) -> 0 | ... O10: =IFERROR(INDIRECT("'" & $C10 & "'!" & O$1),0) -> 0 | P10: =J10 -> 0 | Q10: =K10 -> 0 | R10: =P10*Q10 -> 0 | S10: =IFERROR(INDIRECT("'" & $C10 & "'!" & S$1),0) -> 0 | T10: =IFERROR(INDIRECT("'" & $C10 & "'!" & T$1),0) -> 0 | U10: =IFERROR(INDIRECT("'" & $C10 & "'!" & U$1),0) -> 0 | V10: Yes | W10: =IFERROR(IF(V10="No",INDIRECT("'"&$C10&"'!"&W$1),S10*Y10),0) -> 0 | Y10: =IF(X10>0,X10,U10) -> 0 | Z10: =IFERROR(W10/S10,0) -> 0 | AB10: =IFERROR(ROUND(T10/AA10,-5),0) -> 0 | AD10: =AB10-(AC10*F10) -> 0 | AE10: =IFERROR(ROUND(W10/AA10,-5)-(AC10*F10),0) -> 0 | AF10: =IFERROR(AE10/F10,0) -> 0 | AI10: =AC10*F10 -> 0 | AJ10: =IFERROR(+W10/$F10,0) -> 0
C11: =C10+1 -> 3 | D11: =IF(INDEX(Tape!$C$7:$C$36,$C11)="","",INDEX(Tape!$C$7:$C$36,$C11)) | E11: =IFERROR(INDEX(Tape!$O$7:$O$36,MATCH('UW Drivers'!$D11,Tape!$C$7:$C$36,0)),0) -> 0 | F11: =IFERROR(INDIRECT("'" & $C11 & "'!" & F$1),0) -> 0 | G11: =IFERROR(INDIRECT("'" & $C11 & "'!" & G$1),0) -> 0 | H11: =IFERROR(INDIRECT("'" & $C11 & "'!" & H$1),0) -> 0 | I11: =IFERROR(INDIRECT("'" & $C11 & "'!" & I$1),0) -> 0 | J11: =IFERROR(INDIRECT("'" & $C11 & "'!" & J$1),0) -> 0 | K11: =IFERROR(INDIRECT("'" & $C11 & "'!" & K$1),0) -> 0 | L11: =IFERROR(INDIRECT("'" & $C11 & "'!" & L$1),0) -> 0 | M11: =IFERROR(INDIRECT("'" & $C11 & "'!" & M$1),0) -> 0 | ... O11: =IFERROR(INDIRECT("'" & $C11 & "'!" & O$1),0) -> 0 | P11: =J11 -> 0 | Q11: =K11 -> 0 | R11: =P11*Q11 -> 0 | S11: =IFERROR(INDIRECT("'" & $C11 & "'!" & S$1),0) -> 0 | T11: =IFERROR(INDIRECT("'" & $C11 & "'!" & T$1),0) -> 0 | U11: =IFERROR(INDIRECT("'" & $C11 & "'!" & U$1),0) -> 0 | V11: Yes | W11: =IFERROR(IF(V11="No",INDIRECT("'"&$C11&"'!"&W$1),S11*Y11),0) -> 0 | Y11: =IF(X11>0,X11,U11) -> 0 | Z11: =IFERROR(W11/S11,0) -> 0 | AB11: =IFERROR(ROUND(T11/AA11,-5),0) -> 0 | AD11: =AB11-(AC11*F11) -> 0 | AE11: =IFERROR(ROUND(W11/AA11,-5)-(AC11*F11),0) -> 0 | AF11: =IFERROR(AE11/F11,0) -> 0 | AI11: =AC11*F11 -> 0 | AJ11: =IFERROR(+W11/$F11,0) -> 0
C12: =C11+1 -> 4 | D12: =IF(INDEX(Tape!$C$7:$C$36,$C12)="","",INDEX(Tape!$C$7:$C$36,$C12)) | E12: =IFERROR(INDEX(Tape!$O$7:$O$36,MATCH('UW Drivers'!$D12,Tape!$C$7:$C$36,0)),0) -> 0 | F12: =IFERROR(INDIRECT("'" & $C12 & "'!" & F$1),0) -> 0 | G12: =IFERROR(INDIRECT("'" & $C12 & "'!" & G$1),0) -> 0 | H12: =IFERROR(INDIRECT("'" & $C12 & "'!" & H$1),0) -> 0 | I12: =IFERROR(INDIRECT("'" & $C12 & "'!" & I$1),0) -> 0 | J12: =IFERROR(INDIRECT("'" & $C12 & "'!" & J$1),0) -> 0 | K12: =IFERROR(INDIRECT("'" & $C12 & "'!" & K$1),0) -> 0 | L12: =IFERROR(INDIRECT("'" & $C12 & "'!" & L$1),0) -> 0 | M12: =IFERROR(INDIRECT("'" & $C12 & "'!" & M$1),0) -> 0 | ... O12: =IFERROR(INDIRECT("'" & $C12 & "'!" & O$1),0) -> 0 | P12: =J12 -> 0 | Q12: =K12 -> 0 | R12: =P12*Q12 -> 0 | S12: =IFERROR(INDIRECT("'" & $C12 & "'!" & S$1),0) -> 0 | T12: =IFERROR(INDIRECT("'" & $C12 & "'!" & T$1),0) -> 0 | U12: =IFERROR(INDIRECT("'" & $C12 & "'!" & U$1),0) -> 0 | V12: Yes | W12: =IFERROR(IF(V12="No",INDIRECT("'"&$C12&"'!"&W$1),S12*Y12),0) -> 0 | Y12: =IF(X12>0,X12,U12) -> 0 | Z12: =IFERROR(W12/S12,0) -> 0 | AB12: =IFERROR(ROUND(T12/AA12,-5),0) -> 0 | AD12: =AB12-(AC12*F12) -> 0 | AE12: =IFERROR(ROUND(W12/AA12,-5)-(AC12*F12),0) -> 0 | AF12: =IFERROR(AE12/F12,0) -> 0 | AI12: =AC12*F12 -> 0 | AJ12: =IFERROR(+W12/$F12,0) -> 0
C13: =C12+1 -> 5 | D13: =IF(INDEX(Tape!$C$7:$C$36,$C13)="","",INDEX(Tape!$C$7:$C$36,$C13)) | E13: =IFERROR(INDEX(Tape!$O$7:$O$36,MATCH('UW Drivers'!$D13,Tape!$C$7:$C$36,0)),0) -> 0 | F13: =IFERROR(INDIRECT("'" & $C13 & "'!" & F$1),0) -> 0 | G13: =IFERROR(INDIRECT("'" & $C13 & "'!" & G$1),0) -> 0 | H13: =IFERROR(INDIRECT("'" & $C13 & "'!" & H$1),0) -> 0 | I13: =IFERROR(INDIRECT("'" & $C13 & "'!" & I$1),0) -> 0 | J13: =IFERROR(INDIRECT("'" & $C13 & "'!" & J$1),0) -> 0 | K13: =IFERROR(INDIRECT("'" & $C13 & "'!" & K$1),0) -> 0 | L13: =IFERROR(INDIRECT("'" & $C13 & "'!" & L$1),0) -> 0 | M13: =IFERROR(INDIRECT("'" & $C13 & "'!" & M$1),0) -> 0 | ... O13: =IFERROR(INDIRECT("'" & $C13 & "'!" & O$1),0) -> 0 | P13: =J13 -> 0 | Q13: =K13 -> 0 | R13: =P13*Q13 -> 0 | S13: =IFERROR(INDIRECT("'" & $C13 & "'!" & S$1),0) -> 0 | T13: =IFERROR(INDIRECT("'" & $C13 & "'!" & T$1),0) -> 0 | U13: =IFERROR(INDIRECT("'" & $C13 & "'!" & U$1),0) -> 0 | V13: Yes | W13: =IFERROR(IF(V13="No",INDIRECT("'"&$C13&"'!"&W$1),S13*Y13),0) -> 0 | Y13: =IF(X13>0,X13,U13) -> 0 | Z13: =IFERROR(W13/S13,0) -> 0 | AB13: =IFERROR(ROUND(T13/AA13,-5),0) -> 0 | AD13: =AB13-(AC13*F13) -> 0 | AE13: =IFERROR(ROUND(W13/AA13,-5)-(AC13*F13),0) -> 0 | AF13: =IFERROR(AE13/F13,0) -> 0 | AI13: =AC13*F13 -> 0 | AJ13: =IFERROR(+W13/$F13,0) -> 0
C14: =C13+1 -> 6 | D14: =IF(INDEX(Tape!$C$7:$C$36,$C14)="","",INDEX(Tape!$C$7:$C$36,$C14)) | E14: =IFERROR(INDEX(Tape!$O$7:$O$36,MATCH('UW Drivers'!$D14,Tape!$C$7:$C$36,0)),0) -> 0 | F14: =IFERROR(INDIRECT("'" & $C14 & "'!" & F$1),0) -> 0 | G14: =IFERROR(INDIRECT("'" & $C14 & "'!" & G$1),0) -> 0 | H14: =IFERROR(INDIRECT("'" & $C14 & "'!" & H$1),0) -> 0 | I14: =IFERROR(INDIRECT("'" & $C14 & "'!" & I$1),0) -> 0 | J14: =IFERROR(INDIRECT("'" & $C14 & "'!" & J$1),0) -> 0 | K14: =IFERROR(INDIRECT("'" & $C14 & "'!" & K$1),0) -> 0 | L14: =IFERROR(INDIRECT("'" & $C14 & "'!" & L$1),0) -> 0 | M14: =IFERROR(INDIRECT("'" & $C14 & "'!" & M$1),0) -> 0 | ... O14: =IFERROR(INDIRECT("'" & $C14 & "'!" & O$1),0) -> 0 | P14: =J14 -> 0 | Q14: =K14 -> 0 | R14: =P14*Q14 -> 0 | S14: =IFERROR(INDIRECT("'" & $C14 & "'!" & S$1),0) -> 0 | T14: =IFERROR(INDIRECT("'" & $C14 & "'!" & T$1),0) -> 0 | U14: =IFERROR(INDIRECT("'" & $C14 & "'!" & U$1),0) -> 0 | V14: Yes | W14: =IFERROR(IF(V14="No",INDIRECT("'"&$C14&"'!"&W$1),S14*Y14),0) -> 0 | Y14: =IF(X14>0,X14,U14) -> 0 | Z14: =IFERROR(W14/S14,0) -> 0 | AB14: =IFERROR(ROUND(T14/AA14,-5),0) -> 0 | AD14: =AB14-(AC14*F14) -> 0 | AE14: =IFERROR(ROUND(W14/AA14,-5)-(AC14*F14),0) -> 0 | AF14: =IFERROR(AE14/F14,0) -> 0 | AI14: =AC14*F14 -> 0 | AJ14: =IFERROR(+W14/$F14,0) -> 0
C15: =C14+1 -> 7 | D15: =IF(INDEX(Tape!$C$7:$C$36,$C15)="","",INDEX(Tape!$C$7:$C$36,$C15)) | E15: =IFERROR(INDEX(Tape!$O$7:$O$36,MATCH('UW Drivers'!$D15,Tape!$C$7:$C$36,0)),0) -> 0 | F15: =IFERROR(INDIRECT("'" & $C15 & "'!" & F$1),0) -> 0 | G15: =IFERROR(INDIRECT("'" & $C15 & "'!" & G$1),0) -> 0 | H15: =IFERROR(INDIRECT("'" & $C15 & "'!" & H$1),0) -> 0 | I15: =IFERROR(INDIRECT("'" & $C15 & "'!" & I$1),0) -> 0 | J15: =IFERROR(INDIRECT("'" & $C15 & "'!" & J$1),0) -> 0 | K15: =IFERROR(INDIRECT("'" & $C15 & "'!" & K$1),0) -> 0 | L15: =IFERROR(INDIRECT("'" & $C15 & "'!" & L$1),0) -> 0 | M15: =IFERROR(INDIRECT("'" & $C15 & "'!" & M$1),0) -> 0 | ... O15: =IFERROR(INDIRECT("'" & $C15 & "'!" & O$1),0) -> 0 | P15: =J15 -> 0 | Q15: =K15 -> 0 | R15: =P15*Q15 -> 0 | S15: =IFERROR(INDIRECT("'" & $C15 & "'!" & S$1),0) -> 0 | T15: =IFERROR(INDIRECT("'" & $C15 & "'!" & T$1),0) -> 0 | U15: =IFERROR(INDIRECT("'" & $C15 & "'!" & U$1),0) -> 0 | V15: Yes | W15: =IFERROR(IF(V15="No",INDIRECT("'"&$C15&"'!"&W$1),S15*Y15),0) -> 0 | Y15: =IF(X15>0,X15,U15) -> 0 | Z15: =IFERROR(W15/S15,0) -> 0 | AB15: =IFERROR(ROUND(T15/AA15,-5),0) -> 0 | AD15: =AB15-(AC15*F15) -> 0 | AE15: =IFERROR(ROUND(W15/AA15,-5)-(AC15*F15),0) -> 0 | AF15: =IFERROR(AE15/F15,0) -> 0 | AI15: =AC15*F15 -> 0 | AJ15: =IFERROR(+W15/$F15,0) -> 0
C16: =C15+1 -> 8 | D16: =IF(INDEX(Tape!$C$7:$C$36,$C16)="","",INDEX(Tape!$C$7:$C$36,$C16)) | E16: =IFERROR(INDEX(Tape!$O$7:$O$36,MATCH('UW Drivers'!$D16,Tape!$C$7:$C$36,0)),0) -> 0 | F16: =IFERROR(INDIRECT("'" & $C16 & "'!" & F$1),0) -> 0 | G16: =IFERROR(INDIRECT("'" & $C16 & "'!" & G$1),0) -> 0 | H16: =IFERROR(INDIRECT("'" & $C16 & "'!" & H$1),0) -> 0 | I16: =IFERROR(INDIRECT("'" & $C16 & "'!" & I$1),0) -> 0 | J16: =IFERROR(INDIRECT("'" & $C16 & "'!" & J$1),0) -> 0 | K16: =IFERROR(INDIRECT("'" & $C16 & "'!" & K$1),0) -> 0 | L16: =IFERROR(INDIRECT("'" & $C16 & "'!" & L$1),0) -> 0 | M16: =IFERROR(INDIRECT("'" & $C16 & "'!" & M$1),0) -> 0 | ... O16: =IFERROR(INDIRECT("'" & $C16 & "'!" & O$1),0) -> 0 | P16: =J16 -> 0 | Q16: =K16 -> 0 | R16: =P16*Q16 -> 0 | S16: =IFERROR(INDIRECT("'" & $C16 & "'!" & S$1),0) -> 0 | T16: =IFERROR(INDIRECT("'" & $C16 & "'!" & T$1),0) -> 0 | U16: =IFERROR(INDIRECT("'" & $C16 & "'!" & U$1),0) -> 0 | V16: Yes | W16: =IFERROR(IF(V16="No",INDIRECT("'"&$C16&"'!"&W$1),S16*Y16),0) -> 0 | Y16: =IF(X16>0,X16,U16) -> 0 | Z16: =IFERROR(W16/S16,0) -> 0 | AB16: =IFERROR(ROUND(T16/AA16,-5),0) -> 0 | AD16: =AB16-(AC16*F16) -> 0 | AE16: =IFERROR(ROUND(W16/AA16,-5)-(AC16*F16),0) -> 0 | AF16: =IFERROR(AE16/F16,0) -> 0 | AI16: =AC16*F16 -> 0 | AJ16: =IFERROR(+W16/$F16,0) -> 0
C17: =C16+1 -> 9 | D17: =IF(INDEX(Tape!$C$7:$C$36,$C17)="","",INDEX(Tape!$C$7:$C$36,$C17)) | E17: =IFERROR(INDEX(Tape!$O$7:$O$36,MATCH('UW Drivers'!$D17,Tape!$C$7:$C$36,0)),0) -> 0 | F17: =IFERROR(INDIRECT("'" & $C17 & "'!" & F$1),0) -> 0 | G17: =IFERROR(INDIRECT("'" & $C17 & "'!" & G$1),0) -> 0 | H17: =IFERROR(INDIRECT("'" & $C17 & "'!" & H$1),0) -> 0 | I17: =IFERROR(INDIRECT("'" & $C17 & "'!" & I$1),0) -> 0 | J17: =IFERROR(INDIRECT("'" & $C17 & "'!" & J$1),0) -> 0 | K17: =IFERROR(INDIRECT("'" & $C17 & "'!" & K$1),0) -> 0 | L17: =IFERROR(INDIRECT("'" & $C17 & "'!" & L$1),0) -> 0 | M17: =IFERROR(INDIRECT("'" & $C17 & "'!" & M$1),0) -> 0 | ... O17: =IFERROR(INDIRECT("'" & $C17 & "'!" & O$1),0) -> 0 | P17: =J17 -> 0 | Q17: =K17 -> 0 | R17: =P17*Q17 -> 0 | S17: =IFERROR(INDIRECT("'" & $C17 & "'!" & S$1),0) -> 0 | T17: =IFERROR(INDIRECT("'" & $C17 & "'!" & T$1),0) -> 0 | U17: =IFERROR(INDIRECT("'" & $C17 & "'!" & U$1),0) -> 0 | V17: Yes | W17: =IFERROR(IF(V17="No",INDIRECT("'"&$C17&"'!"&W$1),S17*Y17),0) -> 0 | Y17: =IF(X17>0,X17,U17) -> 0 | Z17: =IFERROR(W17/S17,0) -> 0 | AB17: =IFERROR(ROUND(T17/AA17,-5),0) -> 0 | AD17: =AB17-(AC17*F17) -> 0 | AE17: =IFERROR(ROUND(W17/AA17,-5)-(AC17*F17),0) -> 0 | AF17: =IFERROR(AE17/F17,0) -> 0 | AI17: =AC17*F17 -> 0 | AJ17: =IFERROR(+W17/$F17,0) -> 0
C18: =C17+1 -> 10 | D18: =IF(INDEX(Tape!$C$7:$C$36,$C18)="","",INDEX(Tape!$C$7:$C$36,$C18)) | E18: =IFERROR(INDEX(Tape!$O$7:$O$36,MATCH('UW Drivers'!$D18,Tape!$C$7:$C$36,0)),0) -> 0 | F18: =IFERROR(INDIRECT("'" & $C18 & "'!" & F$1),0) -> 0 | G18: =IFERROR(INDIRECT("'" & $C18 & "'!" & G$1),0) -> 0 | H18: =IFERROR(INDIRECT("'" & $C18 & "'!" & H$1),0) -> 0 | I18: =IFERROR(INDIRECT("'" & $C18 & "'!" & I$1),0) -> 0 | J18: =IFERROR(INDIRECT("'" & $C18 & "'!" & J$1),0) -> 0 | K18: =IFERROR(INDIRECT("'" & $C18 & "'!" & K$1),0) -> 0 | L18: =IFERROR(INDIRECT("'" & $C18 & "'!" & L$1),0) -> 0 | M18: =IFERROR(INDIRECT("'" & $C18 & "'!" & M$1),0) -> 0 | ... O18: =IFERROR(INDIRECT("'" & $C18 & "'!" & O$1),0) -> 0 | P18: =J18 -> 0 | Q18: =K18 -> 0 | R18: =P18*Q18 -> 0 | S18: =IFERROR(INDIRECT("'" & $C18 & "'!" & S$1),0) -> 0 | T18: =IFERROR(INDIRECT("'" & $C18 & "'!" & T$1),0) -> 0 | U18: =IFERROR(INDIRECT("'" & $C18 & "'!" & U$1),0) -> 0 | V18: Yes | W18: =IFERROR(IF(V18="No",INDIRECT("'"&$C18&"'!"&W$1),S18*Y18),0) -> 0 | Y18: =IF(X18>0,X18,U18) -> 0 | Z18: =IFERROR(W18/S18,0) -> 0 | AB18: =IFERROR(ROUND(T18/AA18,-5),0) -> 0 | AD18: =AB18-(AC18*F18) -> 0 | AE18: =IFERROR(ROUND(W18/AA18,-5)-(AC18*F18),0) -> 0 | AF18: =IFERROR(AE18/F18,0) -> 0 | AI18: =AC18*F18 -> 0 | AJ18: =IFERROR(+W18/$F18,0) -> 0
C19: =C18+1 -> 11 | D19: =IF(INDEX(Tape!$C$7:$C$36,$C19)="","",INDEX(Tape!$C$7:$C$36,$C19)) | E19: =IFERROR(INDEX(Tape!$O$7:$O$36,MATCH('UW Drivers'!$D19,Tape!$C$7:$C$36,0)),0) -> 0 | F19: =IFERROR(INDIRECT("'" & $C19 & "'!" & F$1),0) -> 0 | G19: =IFERROR(INDIRECT("'" & $C19 & "'!" & G$1),0) -> 0 | H19: =IFERROR(INDIRECT("'" & $C19 & "'!" & H$1),0) -> 0 | I19: =IFERROR(INDIRECT("'" & $C19 & "'!" & I$1),0) -> 0 | J19: =IFERROR(INDIRECT("'" & $C19 & "'!" & J$1),0) -> 0 | K19: =IFERROR(INDIRECT("'" & $C19 & "'!" & K$1),0) -> 0 | L19: =IFERROR(INDIRECT("'" & $C19 & "'!" & L$1),0) -> 0 | M19: =IFERROR(INDIRECT("'" & $C19 & "'!" & M$1),0) -> 0 | ... O19: =IFERROR(INDIRECT("'" & $C19 & "'!" & O$1),0) -> 0 | P19: =J19 -> 0 | Q19: =K19 -> 0 | R19: =P19*Q19 -> 0 | S19: =IFERROR(INDIRECT("'" & $C19 & "'!" & S$1),0) -> 0 | T19: =IFERROR(INDIRECT("'" & $C19 & "'!" & T$1),0) -> 0 | U19: =IFERROR(INDIRECT("'" & $C19 & "'!" & U$1),0) -> 0 | V19: Yes | W19: =IFERROR(IF(V19="No",INDIRECT("'"&$C19&"'!"&W$1),S19*Y19),0) -> 0 | Y19: =IF(X19>0,X19,U19) -> 0 | Z19: =IFERROR(W19/S19,0) -> 0 | AB19: =IFERROR(ROUND(T19/AA19,-5),0) -> 0 | AD19: =AB19-(AC19*F19) -> 0 | AE19: =IFERROR(ROUND(W19/AA19,-5)-(AC19*F19),0) -> 0 | AF19: =IFERROR(AE19/F19,0) -> 0 | AI19: =AC19*F19 -> 0 | AJ19: =IFERROR(+W19/$F19,0) -> 0
C20: =C19+1 -> 12 | D20: =IF(INDEX(Tape!$C$7:$C$36,$C20)="","",INDEX(Tape!$C$7:$C$36,$C20)) | E20: =IFERROR(INDEX(Tape!$O$7:$O$36,MATCH('UW Drivers'!$D20,Tape!$C$7:$C$36,0)),0) -> 0 | F20: =IFERROR(INDIRECT("'" & $C20 & "'!" & F$1),0) -> 0 | G20: =IFERROR(INDIRECT("'" & $C20 & "'!" & G$1),0) -> 0 | H20: =IFERROR(INDIRECT("'" & $C20 & "'!" & H$1),0) -> 0 | I20: =IFERROR(INDIRECT("'" & $C20 & "'!" & I$1),0) -> 0 | J20: =IFERROR(INDIRECT("'" & $C20 & "'!" & J$1),0) -> 0 | K20: =IFERROR(INDIRECT("'" & $C20 & "'!" & K$1),0) -> 0 | L20: =IFERROR(INDIRECT("'" & $C20 & "'!" & L$1),0) -> 0 | M20: =IFERROR(INDIRECT("'" & $C20 & "'!" & M$1),0) -> 0 | ... O20: =IFERROR(INDIRECT("'" & $C20 & "'!" & O$1),0) -> 0 | P20: =J20 -> 0 | Q20: =K20 -> 0 | R20: =P20*Q20 -> 0 | S20: =IFERROR(INDIRECT("'" & $C20 & "'!" & S$1),0) -> 0 | T20: =IFERROR(INDIRECT("'" & $C20 & "'!" & T$1),0) -> 0 | U20: =IFERROR(INDIRECT("'" & $C20 & "'!" & U$1),0) -> 0 | V20: Yes | W20: =IFERROR(IF(V20="No",INDIRECT("'"&$C20&"'!"&W$1),S20*Y20),0) -> 0 | Y20: =IF(X20>0,X20,U20) -> 0 | Z20: =IFERROR(W20/S20,0) -> 0 | AB20: =IFERROR(ROUND(T20/AA20,-5),0) -> 0 | AD20: =AB20-(AC20*F20) -> 0 | AE20: =IFERROR(ROUND(W20/AA20,-5)-(AC20*F20),0) -> 0 | AF20: =IFERROR(AE20/F20,0) -> 0 | AI20: =AC20*F20 -> 0 | AJ20: =IFERROR(+W20/$F20,0) -> 0
C21: =C20+1 -> 13 | D21: =IF(INDEX(Tape!$C$7:$C$36,$C21)="","",INDEX(Tape!$C$7:$C$36,$C21)) | E21: =IFERROR(INDEX(Tape!$O$7:$O$36,MATCH('UW Drivers'!$D21,Tape!$C$7:$C$36,0)),0) -> 0 | F21: =IFERROR(INDIRECT("'" & $C21 & "'!" & F$1),0) -> 0 | G21: =IFERROR(INDIRECT("'" & $C21 & "'!" & G$1),0) -> 0 | H21: =IFERROR(INDIRECT("'" & $C21 & "'!" & H$1),0) -> 0 | I21: =IFERROR(INDIRECT("'" & $C21 & "'!" & I$1),0) -> 0 | J21: =IFERROR(INDIRECT("'" & $C21 & "'!" & J$1),0) -> 0 | K21: =IFERROR(INDIRECT("'" & $C21 & "'!" & K$1),0) -> 0 | L21: =IFERROR(INDIRECT("'" & $C21 & "'!" & L$1),0) -> 0 | M21: =IFERROR(INDIRECT("'" & $C21 & "'!" & M$1),0) -> 0 | ... O21: =IFERROR(INDIRECT("'" & $C21 & "'!" & O$1),0) -> 0 | P21: =J21 -> 0 | Q21: =K21 -> 0 | R21: =P21*Q21 -> 0 | S21: =IFERROR(INDIRECT("'" & $C21 & "'!" & S$1),0) -> 0 | T21: =IFERROR(INDIRECT("'" & $C21 & "'!" & T$1),0) -> 0 | U21: =IFERROR(INDIRECT("'" & $C21 & "'!" & U$1),0) -> 0 | V21: Yes | W21: =IFERROR(IF(V21="No",INDIRECT("'"&$C21&"'!"&W$1),S21*Y21),0) -> 0 | Y21: =IF(X21>0,X21,U21) -> 0 | Z21: =IFERROR(W21/S21,0) -> 0 | AB21: =IFERROR(ROUND(T21/AA21,-5),0) -> 0 | AD21: =AB21-(AC21*F21) -> 0 | AE21: =IFERROR(ROUND(W21/AA21,-5)-(AC21*F21),0) -> 0 | AF21: =IFERROR(AE21/F21,0) -> 0 | AI21: =AC21*F21 -> 0 | AJ21: =IFERROR(+W21/$F21,0) -> 0
... C38: =C37+1 -> 30 | D38: =IF(INDEX(Tape!$C$7:$C$36,$C38)="","",INDEX(Tape!$C$7:$C$36,$C38)) | E38: =IFERROR(INDEX(Tape!$O$7:$O$36,MATCH('UW Drivers'!$D38,Tape!$C$7:$C$36,0)),0) -> 0 | F38: =IFERROR(INDIRECT("'" & $C38 & "'!" & F$1),0) -> 0 | G38: =IFERROR(INDIRECT("'" & $C38 & "'!" & G$1),0) -> 0 | H38: =IFERROR(INDIRECT("'" & $C38 & "'!" & H$1),0) -> 0 | I38: =IFERROR(INDIRECT("'" & $C38 & "'!" & I$1),0) -> 0 | J38: =IFERROR(INDIRECT("'" & $C38 & "'!" & J$1),0) -> 0 | K38: =IFERROR(INDIRECT("'" & $C38 & "'!" & K$1),0) -> 0 | L38: =IFERROR(INDIRECT("'" & $C38 & "'!" & L$1),0) -> 0 | M38: =IFERROR(INDIRECT("'" & $C38 & "'!" & M$1),0) -> 0 | ... O38: =IFERROR(INDIRECT("'" & $C38 & "'!" & O$1),0) -> 0 | P38: =J38 -> 0 | Q38: =K38 -> 0 | R38: =P38*Q38 -> 0 | S38: =IFERROR(INDIRECT("'" & $C38 & "'!" & S$1),0) -> 0 | T38: =IFERROR(INDIRECT("'" & $C38 & "'!" & T$1),0) -> 0 | U38: =IFERROR(INDIRECT("'" & $C38 & "'!" & U$1),0) -> 0 | V38: Yes | W38: =IFERROR(IF(V38="No",INDIRECT("'"&$C38&"'!"&W$1),S38*Y38),0) -> 0 | Y38: =IF(X38>0,X38,U38) -> 0 | Z38: =IFERROR(W38/S38,0) -> 0 | AB38: =IFERROR(ROUND(T38/AA38,-5),0) -> 0 | AD38: =AB38-(AC38*F38) -> 0 | AE38: =IFERROR(ROUND(W38/AA38,-5)-(AC38*F38),0) -> 0 | AF38: =IFERROR(AE38/F38,0) -> 0 | AI38: =AC38*F38 -> 0 | AJ38: =IFERROR(+W38/$F38,0) -> 0
F40: =SUM(F9:F38) -> 0 | J40: =IFERROR(SUMPRODUCT(J9:J38,$F$9:$F$38)/SUM($F$9:$F$38),0) -> 0 | K40: =IFERROR(SUMPRODUCT(K9:K38,$F$9:$F$38)/SUM($F$9:$F$38),0) -> 0 | L40: =IFERROR(SUMPRODUCT(L9:L38,$F$9:$F$38)/SUM($F$9:$F$38),0) -> 0 | T40: =SUM(T9:T38) -> 0 | U40: =SUMPRODUCT(U9:U38,S9:S38) -> 0 | W40: =SUM(W9:W38) -> 0 | X40: Max | Y40: Max | Z40: Max | AA40: =MIN(AA9:AA38) -> 0 | AB40: =SUM(AB9:AB38) -> 0 | AD40: =SUM(AD9:AD38) -> 0 | AE40: =SUM(AE9:AE38) -> 0 | AI40: =SUM(AI9:AI38) -> 0
U41: =U40-W40 -> 0 | W41: =IFERROR('UW Drivers'!W40/'Cap Stack Control'!$D$17,0) -> 0 | X41: Min | Y41: Min | Z41: Min | AA41: =MAX(AA9:AA38) -> 0 | AB41: =IFERROR('Cap Stack Control'!$D$17/'UW Drivers'!AB40,0) -> 0 | AD41: =AD40+'Cap Stack Control'!$D$12 -> 0 | AE41: =IFERROR('Cap Stack Control'!$D$17/'UW Drivers'!AE40,0) -> 0
X42: WAVG | Y42: WAVG | Z42: WAVG | AA42: =IFERROR(SUMPRODUCT(AA9:AA38,AB9:AB38)/AB40,0) -> 0 | AD42: =IFERROR('Cap Stack Control'!$D$17/'UW Drivers'!AD41,0) -> 0
AE43: =AE40+'Cap Stack Control'!$D$12 -> 0
AE44: =IFERROR('Cap Stack Control'!$D$17/AE43,0) -> 0

Sheet Rollup
D1: =D3 -> 2019 | H1: =H3 -> 2021 | L1: =L3 -> 2022 | P1: =P3 -> 2023 | T1: =T3 -> 2024 | X1: =X3 -> 2025 | AB1: 2025 | AF1: 2026
D3: =Tape!$T$5 -> 2019 | H3: =Tape!$U$5 -> 2021 | L3: =Tape!$V$5 -> 2022 | P3: =Tape!$W$5 -> 2023 | T3: =Tape!$X$5 -> 2024 | X3: =Tape!$Y$5 -> 2025 | AB3: =Tape!$Z$5 -> TTM | AF3: =Tape!$AA$5 -> Reforecast | AJ3: =Tape!$AB$5 -> Lender UW | AN3: Sixth Street In-Place UW
C4: Keys | D4: =SUM(START:END!D6:D6) -> 0 | H4: =SUM(START:END!H6:H6) -> 0 | L4: =SUM(START:END!L6:L6) -> 0 | P4: =SUM(START:END!P6:P6) -> 0 | T4: =SUM(START:END!T6:T6) -> 0 | X4: =SUM(START:END!X6:X6) -> 0 | AB4: =SUM(START:END!AB6:AB6) -> 0 | AF4: =SUM(START:END!AF6:AF6) -> 0 | AJ4: =SUM(START:END!AJ6:AJ6) -> 0 | AN4: =SUM(START:END!AN6:AN6) -> 0
C5: Rooms Available | D5: =SUM(START:END!D7:D7) -> 0 | H5: =SUM(START:END!H7:H7) -> 0 | L5: =SUM(START:END!L7:L7) -> 0 | P5: =SUM(START:END!P7:P7) -> 0 | T5: =SUM(START:END!T7:T7) -> 0 | X5: =SUM(START:END!X7:X7) -> 0 | AB5: =SUM(START:END!AB7:AB7) -> 0 | AF5: =SUM(START:END!AF7:AF7) -> 0 | AJ5: =SUM(START:END!AJ7:AJ7) -> 0 | AN5: =SUM(START:END!AN7:AN7) -> 0
C6: Rooms Sold | D6: =SUM(START:END!D8:D8) -> 0 | H6: =SUM(START:END!H8:H8) -> 0 | L6: =SUM(START:END!L8:L8) -> 0 | P6: =SUM(START:END!P8:P8) -> 0 | T6: =SUM(START:END!T8:T8) -> 0 | X6: =SUM(START:END!X8:X8) -> 0 | AB6: =SUM(START:END!AB8:AB8) -> 0 | AF6: =SUM(START:END!AF8:AF8) -> 0 | AJ6: =SUM(START:END!AJ8:AJ8) -> 0 | AN6: =SUM(START:END!AN8:AN8) -> 0
C7: Occupancy | D7: =IFERROR(D6/D5,0) -> 0 | H7: =IFERROR(H6/H5,0) -> 0 | L7: =IFERROR(L6/L5,0) -> 0 | P7: =IFERROR(P6/P5,0) -> 0 | T7: =IFERROR(T6/T5,0) -> 0 | X7: =IFERROR(X6/X5,0) -> 0 | AB7: =IFERROR(AB6/AB5,0) -> 0 | AF7: =IFERROR(AF6/AF5,0) -> 0 | AJ7: =IFERROR(AJ6/AJ5,0) -> 0 | AN7: =IFERROR(AN6/AN5,0) -> 0
C8: ADR | D8: =IFERROR(D12/D6,0) -> 0 | H8: =IFERROR(H12/H6,0) -> 0 | L8: =IFERROR(L12/L6,0) -> 0 | P8: =IFERROR(P12/P6,0) -> 0 | T8: =IFERROR(T12/T6,0) -> 0 | X8: =IFERROR(X12/X6,0) -> 0 | AB8: =IFERROR(AB12/AB6,0) -> 0 | AF8: =IFERROR(AF12/AF6,0) -> 0 | AJ8: =IFERROR(AJ12/AJ6,0) -> 0 | AN8: =IFERROR(AN12/AN6,0) -> 0
C9: RevPAR | D9: =D7*D8 -> 0 | H9: =H7*H8 -> 0 | L9: =L7*L8 -> 0 | P9: =P7*P8 -> 0 | T9: =T7*T8 -> 0 | X9: =X7*X8 -> 0 | AB9: =AB7*AB8 -> 0 | AF9: =AF7*AF8 -> 0 | AJ9: =AJ7*AJ8 -> 0 | AN9: =AN7*AN8 -> 0
C11: REVENUES | D11: $ | E11: % Total Rev. | F11: POR | G11: PAR | H11: $ | I11: % Total Rev. | J11: POR | K11: PAR | L11: $ | M11: % Total Rev. | N11: POR | O11: PAR | P11: $ | Q11: % Total Rev. | R11: POR | S11: PAR | T11: $ | U11: % Total Rev. | V11: POR | W11: PAR | X11: $ | Y11: % Total Rev. | Z11: POR | AA11: PAR | AB11: $ | AC11: % Total Rev. | AD11: POR | AE11: PAR | AF11: $ | AG11: % Total Rev. | AH11: POR | AI11: PAR | AJ11: $ | AK11: % Total Rev. | AL11: POR | AM11: PAR | AN11: $ | AO11: % Total Rev. | AP11: POR | AQ11: PAR
C12: Rooms Revenue | D12: =SUM(START:END!D14:D14) -> 0 | E12: =IFERROR(D12/D$17,0) -> 0 | F12: =IFERROR(D12/D$6,0) -> 0 | G12: =IFERROR(D12/D$5,0) -> 0 | H12: =SUM(START:END!H14:H14) -> 0 | I12: =IFERROR(H12/H$17,0) -> 0 | J12: =IFERROR(H12/H$6,0) -> 0 | K12: =IFERROR(H12/H$5,0) -> 0 | L12: =SUM(START:END!L14:L14) -> 0 | M12: =IFERROR(L12/L$17,0) -> 0 | N12: =IFERROR(L12/L$6,0) -> 0 | O12: =IFERROR(L12/L$5,0) -> 0 | P12: =SUM(START:END!P14:P14) -> 0 | Q12: =IFERROR(P12/P$17,0) -> 0 | R12: =IFERROR(P12/P$6,0) -> 0 | S12: =IFERROR(P12/P$5,0) -> 0 | T12: =SUM(START:END!T14:T14) -> 0 | U12: =IFERROR(T12/T$17,0) -> 0 | V12: =IFERROR(T12/T$6,0) -> 0 | W12: =IFERROR(T12/T$5,0) -> 0 | X12: =SUM(START:END!X14:X14) -> 0 | Y12: =IFERROR(X12/X$17,0) -> 0 | Z12: =IFERROR(X12/X$6,0) -> 0 | AA12: =IFERROR(X12/X$5,0) -> 0 | AB12: =SUM(START:END!AB14:AB14) -> 0 | AC12: =IFERROR(AB12/AB$17,0) -> 0 | AD12: =IFERROR(AB12/AB$6,0) -> 0 | AE12: =IFERROR(AB12/AB$5,0) -> 0 | AF12: =SUM(START:END!AF14:AF14) -> 0 | AG12: =IFERROR(AF12/AF$17,0) -> 0 | AH12: =IFERROR(AF12/AF$6,0) -> 0 | AI12: =IFERROR(AF12/AF$5,0) -> 0 | AJ12: =SUM(START:END!AJ14:AJ14) -> 0 | AK12: =IFERROR(AJ12/AJ$17,0) -> 0 | AL12: =IFERROR(AJ12/AJ$6,0) -> 0 | AM12: =IFERROR(AJ12/AJ$5,0) -> 0 | AN12: =SUM(START:END!AN14:AN14) -> 0 | AO12: =IFERROR(AN12/AN$17,0) -> 0 | AP12: =IFERROR(AN12/AN$6,0) -> 0 | AQ12: =IFERROR(AN12/AN$5,0) -> 0
C13: Food & Beverage Revenue | D13: =SUM(START:END!D15:D15) -> 0 | E13: =IFERROR(D13/D$17,0) -> 0 | F13: =IFERROR(D13/D$6,0) -> 0 | G13: =IFERROR(D13/D$5,0) -> 0 | H13: =SUM(START:END!H15:H15) -> 0 | I13: =IFERROR(H13/H$17,0) -> 0 | J13: =IFERROR(H13/H$6,0) -> 0 | K13: =IFERROR(H13/H$5,0) -> 0 | L13: =SUM(START:END!L15:L15) -> 0 | M13: =IFERROR(L13/L$17,0) -> 0 | N13: =IFERROR(L13/L$6,0) -> 0 | O13: =IFERROR(L13/L$5,0) -> 0 | P13: =SUM(START:END!P15:P15) -> 0 | Q13: =IFERROR(P13/P$17,0) -> 0 | R13: =IFERROR(P13/P$6,0) -> 0 | S13: =IFERROR(P13/P$5,0) -> 0 | T13: =SUM(START:END!T15:T15) -> 0 | U13: =IFERROR(T13/T$17,0) -> 0 | V13: =IFERROR(T13/T$6,0) -> 0 | W13: =IFERROR(T13/T$5,0) -> 0 | X13: =SUM(START:END!X15:X15) -> 0 | Y13: =IFERROR(X13/X$17,0) -> 0 | Z13: =IFERROR(X13/X$6,0) -> 0 | AA13: =IFERROR(X13/X$5,0) -> 0 | AB13: =SUM(START:END!AB15:AB15) -> 0 | AC13: =IFERROR(AB13/AB$17,0) -> 0 | AD13: =IFERROR(AB13/AB$6,0) -> 0 | AE13: =IFERROR(AB13/AB$5,0) -> 0 | AF13: =SUM(START:END!AF15:AF15) -> 0 | AG13: =IFERROR(AF13/AF$17,0) -> 0 | AH13: =IFERROR(AF13/AF$6,0) -> 0 | AI13: =IFERROR(AF13/AF$5,0) -> 0 | AJ13: =SUM(START:END!AJ15:AJ15) -> 0 | AK13: =IFERROR(AJ13/AJ$17,0) -> 0 | AL13: =IFERROR(AJ13/AJ$6,0) -> 0 | AM13: =IFERROR(AJ13/AJ$5,0) -> 0 | AN13: =SUM(START:END!AN15:AN15) -> 0 | AO13: =IFERROR(AN13/AN$17,0) -> 0 | AP13: =IFERROR(AN13/AN$6,0) -> 0 | AQ13: =IFERROR(AN13/AN$5,0) -> 0
C14: Other Departmental Revenue | D14: =SUM(START:END!D16:D16) -> 0 | E14: =IFERROR(D14/D$17,0) -> 0 | F14: =IFERROR(D14/D$6,0) -> 0 | G14: =IFERROR(D14/D$5,0) -> 0 | H14: =SUM(START:END!H16:H16) -> 0 | I14: =IFERROR(H14/H$17,0) -> 0 | J14: =IFERROR(H14/H$6,0) -> 0 | K14: =IFERROR(H14/H$5,0) -> 0 | L14: =SUM(START:END!L16:L16) -> 0 | M14: =IFERROR(L14/L$17,0) -> 0 | N14: =IFERROR(L14/L$6,0) -> 0 | O14: =IFERROR(L14/L$5,0) -> 0 | P14: =SUM(START:END!P16:P16) -> 0 | Q14: =IFERROR(P14/P$17,0) -> 0 | R14: =IFERROR(P14/P$6,0) -> 0 | S14: =IFERROR(P14/P$5,0) -> 0 | T14: =SUM(START:END!T16:T16) -> 0 | U14: =IFERROR(T14/T$17,0) -> 0 | V14: =IFERROR(T14/T$6,0) -> 0 | W14: =IFERROR(T14/T$5,0) -> 0 | X14: =SUM(START:END!X16:X16) -> 0 | Y14: =IFERROR(X14/X$17,0) -> 0 | Z14: =IFERROR(X14/X$6,0) -> 0 | AA14: =IFERROR(X14/X$5,0) -> 0 | AB14: =SUM(START:END!AB16:AB16) -> 0 | AC14: =IFERROR(AB14/AB$17,0) -> 0 | AD14: =IFERROR(AB14/AB$6,0) -> 0 | AE14: =IFERROR(AB14/AB$5,0) -> 0 | AF14: =SUM(START:END!AF16:AF16) -> 0 | AG14: =IFERROR(AF14/AF$17,0) -> 0 | AH14: =IFERROR(AF14/AF$6,0) -> 0 | AI14: =IFERROR(AF14/AF$5,0) -> 0 | AJ14: =SUM(START:END!AJ16:AJ16) -> 0 | AK14: =IFERROR(AJ14/AJ$17,0) -> 0 | AL14: =IFERROR(AJ14/AJ$6,0) -> 0 | AM14: =IFERROR(AJ14/AJ$5,0) -> 0 | AN14: =SUM(START:END!AN16:AN16) -> 0 | AO14: =IFERROR(AN14/AN$17,0) -> 0 | AP14: =IFERROR(AN14/AN$6,0) -> 0 | AQ14: =IFERROR(AN14/AN$5,0) -> 0
C15: Parking Revenue | D15: =SUM(START:END!D17:D17) -> 0 | E15: =IFERROR(D15/D$17,0) -> 0 | F15: =IFERROR(D15/D$6,0) -> 0 | G15: =IFERROR(D15/D$5,0) -> 0 | H15: =SUM(START:END!H17:H17) -> 0 | I15: =IFERROR(H15/H$17,0) -> 0 | J15: =IFERROR(H15/H$6,0) -> 0 | K15: =IFERROR(H15/H$5,0) -> 0 | L15: =SUM(START:END!L17:L17) -> 0 | M15: =IFERROR(L15/L$17,0) -> 0 | N15: =IFERROR(L15/L$6,0) -> 0 | O15: =IFERROR(L15/L$5,0) -> 0 | P15: =SUM(START:END!P17:P17) -> 0 | Q15: =IFERROR(P15/P$17,0) -> 0 | R15: =IFERROR(P15/P$6,0) -> 0 | S15: =IFERROR(P15/P$5,0) -> 0 | T15: =SUM(START:END!T17:T17) -> 0 | U15: =IFERROR(T15/T$17,0) -> 0 | V15: =IFERROR(T15/T$6,0) -> 0 | W15: =IFERROR(T15/T$5,0) -> 0 | X15: =SUM(START:END!X17:X17) -> 0 | Y15: =IFERROR(X15/X$17,0) -> 0 | Z15: =IFERROR(X15/X$6,0) -> 0 | AA15: =IFERROR(X15/X$5,0) -> 0 | AB15: =SUM(START:END!AB17:AB17) -> 0 | AC15: =IFERROR(AB15/AB$17,0) -> 0 | AD15: =IFERROR(AB15/AB$6,0) -> 0 | AE15: =IFERROR(AB15/AB$5,0) -> 0 | AF15: =SUM(START:END!AF17:AF17) -> 0 | AG15: =IFERROR(AF15/AF$17,0) -> 0 | AH15: =IFERROR(AF15/AF$6,0) -> 0 | AI15: =IFERROR(AF15/AF$5,0) -> 0 | AJ15: =SUM(START:END!AJ17:AJ17) -> 0 | AK15: =IFERROR(AJ15/AJ$17,0) -> 0 | AL15: =IFERROR(AJ15/AJ$6,0) -> 0 | AM15: =IFERROR(AJ15/AJ$5,0) -> 0 | AN15: =SUM(START:END!AN17:AN17) -> 0 | AO15: =IFERROR(AN15/AN$17,0) -> 0 | AP15: =IFERROR(AN15/AN$6,0) -> 0 | AQ15: =IFERROR(AN15/AN$5,0) -> 0
C16: Miscellaneous | D16: =SUM(START:END!D18:D18) -> 0 | E16: =IFERROR(D16/D$17,0) -> 0 | F16: =IFERROR(D16/D$6,0) -> 0 | G16: =IFERROR(D16/D$5,0) -> 0 | H16: =SUM(START:END!H18:H18) -> 0 | I16: =IFERROR(H16/H$17,0) -> 0 | J16: =IFERROR(H16/H$6,0) -> 0 | K16: =IFERROR(H16/H$5,0) -> 0 | L16: =SUM(START:END!L18:L18) -> 0 | M16: =IFERROR(L16/L$17,0) -> 0 | N16: =IFERROR(L16/L$6,0) -> 0 | O16: =IFERROR(L16/L$5,0) -> 0 | P16: =SUM(START:END!P18:P18) -> 0 | Q16: =IFERROR(P16/P$17,0) -> 0 | R16: =IFERROR(P16/P$6,0) -> 0 | S16: =IFERROR(P16/P$5,0) -> 0 | T16: =SUM(START:END!T18:T18) -> 0 | U16: =IFERROR(T16/T$17,0) -> 0 | V16: =IFERROR(T16/T$6,0) -> 0 | W16: =IFERROR(T16/T$5,0) -> 0 | X16: =SUM(START:END!X18:X18) -> 0 | Y16: =IFERROR(X16/X$17,0) -> 0 | Z16: =IFERROR(X16/X$6,0) -> 0 | AA16: =IFERROR(X16/X$5,0) -> 0 | AB16: =SUM(START:END!AB18:AB18) -> 0 | AC16: =IFERROR(AB16/AB$17,0) -> 0 | AD16: =IFERROR(AB16/AB$6,0) -> 0 | AE16: =IFERROR(AB16/AB$5,0) -> 0 | AF16: =SUM(START:END!AF18:AF18) -> 0 | AG16: =IFERROR(AF16/AF$17,0) -> 0 | AH16: =IFERROR(AF16/AF$6,0) -> 0 | AI16: =IFERROR(AF16/AF$5,0) -> 0 | AJ16: =SUM(START:END!AJ18:AJ18) -> 0 | AK16: =IFERROR(AJ16/AJ$17,0) -> 0 | AL16: =IFERROR(AJ16/AJ$6,0) -> 0 | AM16: =IFERROR(AJ16/AJ$5,0) -> 0 | AN16: =SUM(START:END!AN18:AN18) -> 0 | AO16: =IFERROR(AN16/AN$17,0) -> 0 | AP16: =IFERROR(AN16/AN$6,0) -> 0 | AQ16: =IFERROR(AN16/AN$5,0) -> 0
C17: TOTAL REVENUES | D17: =SUM(D12:D16) -> 0 | E17: =IFERROR(D17/D$17,0) -> 0 | F17: =IFERROR(D17/D$6,0) -> 0 | G17: =IFERROR(D17/D$5,0) -> 0 | H17: =SUM(H12:H16) -> 0 | I17: =IFERROR(H17/H$17,0) -> 0 | J17: =IFERROR(H17/H$6,0) -> 0 | K17: =IFERROR(H17/H$5,0) -> 0 | L17: =SUM(L12:L16) -> 0 | M17: =IFERROR(L17/L$17,0) -> 0 | N17: =IFERROR(L17/L$6,0) -> 0 | O17: =IFERROR(L17/L$5,0) -> 0 | P17: =SUM(P12:P16) -> 0 | Q17: =IFERROR(P17/P$17,0) -> 0 | R17: =IFERROR(P17/P$6,0) -> 0 | S17: =IFERROR(P17/P$5,0) -> 0 | T17: =SUM(T12:T16) -> 0 | U17: =IFERROR(T17/T$17,0) -> 0 | V17: =IFERROR(T17/T$6,0) -> 0 | W17: =IFERROR(T17/T$5,0) -> 0 | X17: =SUM(X12:X16) -> 0 | Y17: =IFERROR(X17/X$17,0) -> 0 | Z17: =IFERROR(X17/X$6,0) -> 0 | AA17: =IFERROR(X17/X$5,0) -> 0 | AB17: =SUM(AB12:AB16) -> 0 | AC17: =IFERROR(AB17/AB$17,0) -> 0 | AD17: =IFERROR(AB17/AB$6,0) -> 0 | AE17: =IFERROR(AB17/AB$5,0) -> 0 | AF17: =SUM(AF12:AF16) -> 0 | AG17: =IFERROR(AF17/AF$17,0) -> 0 | AH17: =IFERROR(AF17/AF$6,0) -> 0 | AI17: =IFERROR(AF17/AF$5,0) -> 0 | AJ17: =SUM(AJ12:AJ16) -> 0 | AK17: =IFERROR(AJ17/AJ$17,0) -> 0 | AL17: =IFERROR(AJ17/AJ$6,0) -> 0 | AM17: =IFERROR(AJ17/AJ$5,0) -> 0 | AN17: =SUM(AN12:AN16) -> 0 | AO17: =IFERROR(AN17/AN$17,0) -> 0 | AP17: =IFERROR(AN17/AN$6,0) -> 0 | AQ17: =IFERROR(AN17/AN$5,0) -> 0
C19: DEPARTMENTAL EXPENSES
C20: Rooms Expense | D20: =SUM(START:END!D22:D22) -> 0 | E20: =IFERROR(D20/D12,0) -> 0 | F20: =IFERROR(D20/D$6,0) -> 0 | G20: =IFERROR(D20/D$5,0) -> 0 | H20: =SUM(START:END!H22:H22) -> 0 | I20: =IFERROR(H20/H12,0) -> 0 | J20: =IFERROR(H20/H$6,0) -> 0 | K20: =IFERROR(H20/H$5,0) -> 0 | L20: =SUM(START:END!L22:L22) -> 0 | M20: =IFERROR(L20/L12,0) -> 0 | N20: =IFERROR(L20/L$6,0) -> 0 | O20: =IFERROR(L20/L$5,0) -> 0 | P20: =SUM(START:END!P22:P22) -> 0 | Q20: =IFERROR(P20/P12,0) -> 0 | R20: =IFERROR(P20/P$6,0) -> 0 | S20: =IFERROR(P20/P$5,0) -> 0 | T20: =SUM(START:END!T22:T22) -> 0 | U20: =IFERROR(T20/T12,0) -> 0 | V20: =IFERROR(T20/T$6,0) -> 0 | W20: =IFERROR(T20/T$5,0) -> 0 | X20: =SUM(START:END!X22:X22) -> 0 | Y20: =IFERROR(X20/X12,0) -> 0 | Z20: =IFERROR(X20/X$6,0) -> 0 | AA20: =IFERROR(X20/X$5,0) -> 0 | AB20: =SUM(START:END!AB22:AB22) -> 0 | AC20: =IFERROR(AB20/AB12,0) -> 0 | AD20: =IFERROR(AB20/AB$6,0) -> 0 | AE20: =IFERROR(AB20/AB$5,0) -> 0 | AF20: =SUM(START:END!AF22:AF22) -> 0 | AG20: =IFERROR(AF20/AF12,0) -> 0 | AH20: =IFERROR(AF20/AF$6,0) -> 0 | AI20: =IFERROR(AF20/AF$5,0) -> 0 | AJ20: =SUM(START:END!AJ22:AJ22) -> 0 | AK20: =IFERROR(AJ20/AJ12,0) -> 0 | AL20: =IFERROR(AJ20/AJ$6,0) -> 0 | AM20: =IFERROR(AJ20/AJ$5,0) -> 0 | AN20: =SUM(START:END!AN22:AN22) -> 0 | AO20: =IFERROR(AN20/AN12,0) -> 0 | AP20: =IFERROR(AN20/AN$6,0) -> 0 | AQ20: =IFERROR(AN20/AN$5,0) -> 0
C21: Food & Beverage Expense | D21: =SUM(START:END!D23:D23) -> 0 | E21: =IFERROR(D21/D13,0) -> 0 | F21: =IFERROR(D21/D$6,0) -> 0 | G21: =IFERROR(D21/D$5,0) -> 0 | H21: =SUM(START:END!H23:H23) -> 0 | I21: =IFERROR(H21/H13,0) -> 0 | J21: =IFERROR(H21/H$6,0) -> 0 | K21: =IFERROR(H21/H$5,0) -> 0 | L21: =SUM(START:END!L23:L23) -> 0 | M21: =IFERROR(L21/L13,0) -> 0 | N21: =IFERROR(L21/L$6,0) -> 0 | O21: =IFERROR(L21/L$5,0) -> 0 | P21: =SUM(START:END!P23:P23) -> 0 | Q21: =IFERROR(P21/P13,0) -> 0 | R21: =IFERROR(P21/P$6,0) -> 0 | S21: =IFERROR(P21/P$5,0) -> 0 | T21: =SUM(START:END!T23:T23) -> 0 | U21: =IFERROR(T21/T13,0) -> 0 | V21: =IFERROR(T21/T$6,0) -> 0 | W21: =IFERROR(T21/T$5,0) -> 0 | X21: =SUM(START:END!X23:X23) -> 0 | Y21: =IFERROR(X21/X13,0) -> 0 | Z21: =IFERROR(X21/X$6,0) -> 0 | AA21: =IFERROR(X21/X$5,0) -> 0 | AB21: =SUM(START:END!AB23:AB23) -> 0 | AC21: =IFERROR(AB21/AB13,0) -> 0 | AD21: =IFERROR(AB21/AB$6,0) -> 0 | AE21: =IFERROR(AB21/AB$5,0) -> 0 | AF21: =SUM(START:END!AF23:AF23) -> 0 | AG21: =IFERROR(AF21/AF13,0) -> 0 | AH21: =IFERROR(AF21/AF$6,0) -> 0 | AI21: =IFERROR(AF21/AF$5,0) -> 0 | AJ21: =SUM(START:END!AJ23:AJ23) -> 0 | AK21: =IFERROR(AJ21/AJ13,0) -> 0 | AL21: =IFERROR(AJ21/AJ$6,0) -> 0 | AM21: =IFERROR(AJ21/AJ$5,0) -> 0 | AN21: =SUM(START:END!AN23:AN23) -> 0 | AO21: =IFERROR(AN21/AN13,0) -> 0 | AP21: =IFERROR(AN21/AN$6,0) -> 0 | AQ21: =IFERROR(AN21/AN$5,0) -> 0
C22: Other Departmental Expense | D22: =SUM(START:END!D24:D24) -> 0 | E22: =IFERROR(D22/D14,0) -> 0 | F22: =IFERROR(D22/D$6,0) -> 0 | G22: =IFERROR(D22/D$5,0) -> 0 | H22: =SUM(START:END!H24:H24) -> 0 | I22: =IFERROR(H22/H14,0) -> 0 | J22: =IFERROR(H22/H$6,0) -> 0 | K22: =IFERROR(H22/H$5,0) -> 0 | L22: =SUM(START:END!L24:L24) -> 0 | M22: =IFERROR(L22/L14,0) -> 0 | N22: =IFERROR(L22/L$6,0) -> 0 | O22: =IFERROR(L22/L$5,0) -> 0 | P22: =SUM(START:END!P24:P24) -> 0 | Q22: =IFERROR(P22/P14,0) -> 0 | R22: =IFERROR(P22/P$6,0) -> 0 | S22: =IFERROR(P22/P$5,0) -> 0 | T22: =SUM(START:END!T24:T24) -> 0 | U22: =IFERROR(T22/T14,0) -> 0 | V22: =IFERROR(T22/T$6,0) -> 0 | W22: =IFERROR(T22/T$5,0) -> 0 | X22: =SUM(START:END!X24:X24) -> 0 | Y22: =IFERROR(X22/X14,0) -> 0 | Z22: =IFERROR(X22/X$6,0) -> 0 | AA22: =IFERROR(X22/X$5,0) -> 0 | AB22: =SUM(START:END!AB24:AB24) -> 0 | AC22: =IFERROR(AB22/AB14,0) -> 0 | AD22: =IFERROR(AB22/AB$6,0) -> 0 | AE22: =IFERROR(AB22/AB$5,0) -> 0 | AF22: =SUM(START:END!AF24:AF24) -> 0 | AG22: =IFERROR(AF22/AF14,0) -> 0 | AH22: =IFERROR(AF22/AF$6,0) -> 0 | AI22: =IFERROR(AF22/AF$5,0) -> 0 | AJ22: =SUM(START:END!AJ24:AJ24) -> 0 | AK22: =IFERROR(AJ22/AJ14,0) -> 0 | AL22: =IFERROR(AJ22/AJ$6,0) -> 0 | AM22: =IFERROR(AJ22/AJ$5,0) -> 0 | AN22: =SUM(START:END!AN24:AN24) -> 0 | AO22: =IFERROR(AN22/AN14,0) -> 0 | AP22: =IFERROR(AN22/AN$6,0) -> 0 | AQ22: =IFERROR(AN22/AN$5,0) -> 0
C23: TOTAL DEPARTMENTAL EXPENSES | D23: =SUM(D20:D22) -> 0 | E23: =IFERROR(D23/D$17,0) -> 0 | F23: =IFERROR(D23/D$6,0) -> 0 | G23: =IFERROR(D23/D$5,0) -> 0 | H23: =SUM(H20:H22) -> 0 | I23: =IFERROR(H23/H$17,0) -> 0 | J23: =IFERROR(H23/H$6,0) -> 0 | K23: =IFERROR(H23/H$5,0) -> 0 | L23: =SUM(L20:L22) -> 0 | M23: =IFERROR(L23/L$17,0) -> 0 | N23: =IFERROR(L23/L$6,0) -> 0 | O23: =IFERROR(L23/L$5,0) -> 0 | P23: =SUM(P20:P22) -> 0 | Q23: =IFERROR(P23/P$17,0) -> 0 | R23: =IFERROR(P23/P$6,0) -> 0 | S23: =IFERROR(P23/P$5,0) -> 0 | T23: =SUM(T20:T22) -> 0 | U23: =IFERROR(T23/T$17,0) -> 0 | V23: =IFERROR(T23/T$6,0) -> 0 | W23: =IFERROR(T23/T$5,0) -> 0 | X23: =SUM(X20:X22) -> 0 | Y23: =IFERROR(X23/X$17,0) -> 0 | Z23: =IFERROR(X23/X$6,0) -> 0 | AA23: =IFERROR(X23/X$5,0) -> 0 | AB23: =SUM(AB20:AB22) -> 0 | AC23: =IFERROR(AB23/AB$17,0) -> 0 | AD23: =IFERROR(AB23/AB$6,0) -> 0 | AE23: =IFERROR(AB23/AB$5,0) -> 0 | AF23: =SUM(AF20:AF22) -> 0 | AG23: =IFERROR(AF23/AF$17,0) -> 0 | AH23: =IFERROR(AF23/AF$6,0) -> 0 | AI23: =IFERROR(AF23/AF$5,0) -> 0 | AJ23: =SUM(AJ20:AJ22) -> 0 | AK23: =IFERROR(AJ23/AJ$17,0) -> 0 | AL23: =IFERROR(AJ23/AJ$6,0) -> 0 | AM23: =IFERROR(AJ23/AJ$5,0) -> 0 | AN23: =SUM(AN20:AN22) -> 0 | AO23: =IFERROR(AN23/AN$17,0) -> 0 | AP23: =IFERROR(AN23/AN$6,0) -> 0 | AQ23: =IFERROR(AN23/AN$5,0) -> 0
C25: GROSS OPERATING INCOME | D25: =D17-D23 -> 0 | E25: =IFERROR(D25/D$17,0) -> 0 | F25: =IFERROR(D25/D$6,0) -> 0 | G25: =IFERROR(D25/D$5,0) -> 0 | H25: =H17-H23 -> 0 | I25: =IFERROR(H25/H$17,0) -> 0 | J25: =IFERROR(H25/H$6,0) -> 0 | K25: =IFERROR(H25/H$5,0) -> 0 | L25: =L17-L23 -> 0 | M25: =IFERROR(L25/L$17,0) -> 0 | N25: =IFERROR(L25/L$6,0) -> 0 | O25: =IFERROR(L25/L$5,0) -> 0 | P25: =P17-P23 -> 0 | Q25: =IFERROR(P25/P$17,0) -> 0 | R25: =IFERROR(P25/P$6,0) -> 0 | S25: =IFERROR(P25/P$5,0) -> 0 | T25: =T17-T23 -> 0 | U25: =IFERROR(T25/T$17,0) -> 0 | V25: =IFERROR(T25/T$6,0) -> 0 | W25: =IFERROR(T25/T$5,0) -> 0 | X25: =X17-X23 -> 0 | Y25: =IFERROR(X25/X$17,0) -> 0 | Z25: =IFERROR(X25/X$6,0) -> 0 | AA25: =IFERROR(X25/X$5,0) -> 0 | AB25: =AB17-AB23 -> 0 | AC25: =IFERROR(AB25/AB$17,0) -> 0 | AD25: =IFERROR(AB25/AB$6,0) -> 0 | AE25: =IFERROR(AB25/AB$5,0) -> 0 | AF25: =AF17-AF23 -> 0 | AG25: =IFERROR(AF25/AF$17,0) -> 0 | AH25: =IFERROR(AF25/AF$6,0) -> 0 | AI25: =IFERROR(AF25/AF$5,0) -> 0 | AJ25: =AJ17-AJ23 -> 0 | AK25: =IFERROR(AJ25/AJ$17,0) -> 0 | AL25: =IFERROR(AJ25/AJ$6,0) -> 0 | AM25: =IFERROR(AJ25/AJ$5,0) -> 0 | AN25: =AN17-AN23 -> 0 | AO25: =IFERROR(AN25/AN$17,0) -> 0 | AP25: =IFERROR(AN25/AN$6,0) -> 0 | AQ25: =IFERROR(AN25/AN$5,0) -> 0
C27: UNDISTRIBUTED EXPENSES
C28: General and Administrative | D28: =SUM(START:END!D30:D30) -> 0 | E28: =IFERROR(D28/D$17,0) -> 0 | F28: =IFERROR(D28/D$6,0) -> 0 | G28: =IFERROR(D28/D$5,0) -> 0 | H28: =SUM(START:END!H30:H30) -> 0 | I28: =IFERROR(H28/H$17,0) -> 0 | J28: =IFERROR(H28/H$6,0) -> 0 | K28: =IFERROR(H28/H$5,0) -> 0 | L28: =SUM(START:END!L30:L30) -> 0 | M28: =IFERROR(L28/L$17,0) -> 0 | N28: =IFERROR(L28/L$6,0) -> 0 | O28: =IFERROR(L28/L$5,0) -> 0 | P28: =SUM(START:END!P30:P30) -> 0 | Q28: =IFERROR(P28/P$17,0) -> 0 | R28: =IFERROR(P28/P$6,0) -> 0 | S28: =IFERROR(P28/P$5,0) -> 0 | T28: =SUM(START:END!T30:T30) -> 0 | U28: =IFERROR(T28/T$17,0) -> 0 | V28: =IFERROR(T28/T$6,0) -> 0 | W28: =IFERROR(T28/T$5,0) -> 0 | X28: =SUM(START:END!X30:X30) -> 0 | Y28: =IFERROR(X28/X$17,0) -> 0 | Z28: =IFERROR(X28/X$6,0) -> 0 | AA28: =IFERROR(X28/X$5,0) -> 0 | AB28: =SUM(START:END!AB30:AB30) -> 0 | AC28: =IFERROR(AB28/AB$17,0) -> 0 | AD28: =IFERROR(AB28/AB$6,0) -> 0 | AE28: =IFERROR(AB28/AB$5,0) -> 0 | AF28: =SUM(START:END!AF30:AF30) -> 0 | AG28: =IFERROR(AF28/AF$17,0) -> 0 | AH28: =IFERROR(AF28/AF$6,0) -> 0 | AI28: =IFERROR(AF28/AF$5,0) -> 0 | AJ28: =SUM(START:END!AJ30:AJ30) -> 0 | AK28: =IFERROR(AJ28/AJ$17,0) -> 0 | AL28: =IFERROR(AJ28/AJ$6,0) -> 0 | AM28: =IFERROR(AJ28/AJ$5,0) -> 0 | AN28: =SUM(START:END!AN30:AN30) -> 0 | AO28: =IFERROR(AN28/AN$17,0) -> 0 | AP28: =IFERROR(AN28/AN$6,0) -> 0 | AQ28: =IFERROR(AN28/AN$5,0) -> 0
C29: Credit Card Commissions | D29: =SUM(START:END!D31:D31) -> 0 | E29: =IFERROR(D29/D$17,0) -> 0 | F29: =IFERROR(D29/D$6,0) -> 0 | G29: =IFERROR(D29/D$5,0) -> 0 | H29: =SUM(START:END!H31:H31) -> 0 | I29: =IFERROR(H29/H$17,0) -> 0 | J29: =IFERROR(H29/H$6,0) -> 0 | K29: =IFERROR(H29/H$5,0) -> 0 | L29: =SUM(START:END!L31:L31) -> 0 | M29: =IFERROR(L29/L$17,0) -> 0 | N29: =IFERROR(L29/L$6,0) -> 0 | O29: =IFERROR(L29/L$5,0) -> 0 | P29: =SUM(START:END!P31:P31) -> 0 | Q29: =IFERROR(P29/P$17,0) -> 0 | R29: =IFERROR(P29/P$6,0) -> 0 | S29: =IFERROR(P29/P$5,0) -> 0 | T29: =SUM(START:END!T31:T31) -> 0 | U29: =IFERROR(T29/T$17,0) -> 0 | V29: =IFERROR(T29/T$6,0) -> 0 | W29: =IFERROR(T29/T$5,0) -> 0 | X29: =SUM(START:END!X31:X31) -> 0 | Y29: =IFERROR(X29/X$17,0) -> 0 | Z29: =IFERROR(X29/X$6,0) -> 0 | AA29: =IFERROR(X29/X$5,0) -> 0 | AB29: =SUM(START:END!AB31:AB31) -> 0 | AC29: =IFERROR(AB29/AB$17,0) -> 0 | AD29: =IFERROR(AB29/AB$6,0) -> 0 | AE29: =IFERROR(AB29/AB$5,0) -> 0 | AF29: =SUM(START:END!AF31:AF31) -> 0 | AG29: =IFERROR(AF29/AF$17,0) -> 0 | AH29: =IFERROR(AF29/AF$6,0) -> 0 | AI29: =IFERROR(AF29/AF$5,0) -> 0 | AJ29: =SUM(START:END!AJ31:AJ31) -> 0 | AK29: =IFERROR(AJ29/AJ$17,0) -> 0 | AL29: =IFERROR(AJ29/AJ$6,0) -> 0 | AM29: =IFERROR(AJ29/AJ$5,0) -> 0 | AN29: =SUM(START:END!AN31:AN31) -> 0 | AO29: =IFERROR(AN29/AN$17,0) -> 0 | AP29: =IFERROR(AN29/AN$6,0) -> 0 | AQ29: =IFERROR(AN29/AN$5,0) -> 0
C30: Information & Telecommunication | D30: =SUM(START:END!D32:D32) -> 0 | E30: =IFERROR(D30/D$17,0) -> 0 | F30: =IFERROR(D30/D$6,0) -> 0 | G30: =IFERROR(D30/D$5,0) -> 0 | H30: =SUM(START:END!H32:H32) -> 0 | I30: =IFERROR(H30/H$17,0) -> 0 | J30: =IFERROR(H30/H$6,0) -> 0 | K30: =IFERROR(H30/H$5,0) -> 0 | L30: =SUM(START:END!L32:L32) -> 0 | M30: =IFERROR(L30/L$17,0) -> 0 | N30: =IFERROR(L30/L$6,0) -> 0 | O30: =IFERROR(L30/L$5,0) -> 0 | P30: =SUM(START:END!P32:P32) -> 0 | Q30: =IFERROR(P30/P$17,0) -> 0 | R30: =IFERROR(P30/P$6,0) -> 0 | S30: =IFERROR(P30/P$5,0) -> 0 | T30: =SUM(START:END!T32:T32) -> 0 | U30: =IFERROR(T30/T$17,0) -> 0 | V30: =IFERROR(T30/T$6,0) -> 0 | W30: =IFERROR(T30/T$5,0) -> 0 | X30: =SUM(START:END!X32:X32) -> 0 | Y30: =IFERROR(X30/X$17,0) -> 0 | Z30: =IFERROR(X30/X$6,0) -> 0 | AA30: =IFERROR(X30/X$5,0) -> 0 | AB30: =SUM(START:END!AB32:AB32) -> 0 | AC30: =IFERROR(AB30/AB$17,0) -> 0 | AD30: =IFERROR(AB30/AB$6,0) -> 0 | AE30: =IFERROR(AB30/AB$5,0) -> 0 | AF30: =SUM(START:END!AF32:AF32) -> 0 | AG30: =IFERROR(AF30/AF$17,0) -> 0 | AH30: =IFERROR(AF30/AF$6,0) -> 0 | AI30: =IFERROR(AF30/AF$5,0) -> 0 | AJ30: =SUM(START:END!AJ32:AJ32) -> 0 | AK30: =IFERROR(AJ30/AJ$17,0) -> 0 | AL30: =IFERROR(AJ30/AJ$6,0) -> 0 | AM30: =IFERROR(AJ30/AJ$5,0) -> 0 | AN30: =SUM(START:END!AN32:AN32) -> 0 | AO30: =IFERROR(AN30/AN$17,0) -> 0 | AP30: =IFERROR(AN30/AN$6,0) -> 0 | AQ30: =IFERROR(AN30/AN$5,0) -> 0
C31: Sales & Marketing | D31: =SUM(START:END!D33:D33) -> 0 | E31: =IFERROR(D31/D$17,0) -> 0 | F31: =IFERROR(D31/D$6,0) -> 0 | G31: =IFERROR(D31/D$5,0) -> 0 | H31: =SUM(START:END!H33:H33) -> 0 | I31: =IFERROR(H31/H$17,0) -> 0 | J31: =IFERROR(H31/H$6,0) -> 0 | K31: =IFERROR(H31/H$5,0) -> 0 | L31: =SUM(START:END!L33:L33) -> 0 | M31: =IFERROR(L31/L$17,0) -> 0 | N31: =IFERROR(L31/L$6,0) -> 0 | O31: =IFERROR(L31/L$5,0) -> 0 | P31: =SUM(START:END!P33:P33) -> 0 | Q31: =IFERROR(P31/P$17,0) -> 0 | R31: =IFERROR(P31/P$6,0) -> 0 | S31: =IFERROR(P31/P$5,0) -> 0 | T31: =SUM(START:END!T33:T33) -> 0 | U31: =IFERROR(T31/T$17,0) -> 0 | V31: =IFERROR(T31/T$6,0) -> 0 | W31: =IFERROR(T31/T$5,0) -> 0 | X31: =SUM(START:END!X33:X33) -> 0 | Y31: =IFERROR(X31/X$17,0) -> 0 | Z31: =IFERROR(X31/X$6,0) -> 0 | AA31: =IFERROR(X31/X$5,0) -> 0 | AB31: =SUM(START:END!AB33:AB33) -> 0 | AC31: =IFERROR(AB31/AB$17,0) -> 0 | AD31: =IFERROR(AB31/AB$6,0) -> 0 | AE31: =IFERROR(AB31/AB$5,0) -> 0 | AF31: =SUM(START:END!AF33:AF33) -> 0 | AG31: =IFERROR(AF31/AF$17,0) -> 0 | AH31: =IFERROR(AF31/AF$6,0) -> 0 | AI31: =IFERROR(AF31/AF$5,0) -> 0 | AJ31: =SUM(START:END!AJ33:AJ33) -> 0 | AK31: =IFERROR(AJ31/AJ$17,0) -> 0 | AL31: =IFERROR(AJ31/AJ$6,0) -> 0 | AM31: =IFERROR(AJ31/AJ$5,0) -> 0 | AN31: =SUM(START:END!AN33:AN33) -> 0 | AO31: =IFERROR(AN31/AN$17,0) -> 0 | AP31: =IFERROR(AN31/AN$6,0) -> 0 | AQ31: =IFERROR(AN31/AN$5,0) -> 0
C32: Franchise Fees | D32: =SUM(START:END!D34:D34) -> 0 | E32: =IFERROR(D32/D$17,0) -> 0 | F32: =IFERROR(D32/D$6,0) -> 0 | G32: =IFERROR(D32/D$5,0) -> 0 | H32: =SUM(START:END!H34:H34) -> 0 | I32: =IFERROR(H32/H$17,0) -> 0 | J32: =IFERROR(H32/H$6,0) -> 0 | K32: =IFERROR(H32/H$5,0) -> 0 | L32: =SUM(START:END!L34:L34) -> 0 | M32: =IFERROR(L32/L$17,0) -> 0 | N32: =IFERROR(L32/L$6,0) -> 0 | O32: =IFERROR(L32/L$5,0) -> 0 | P32: =SUM(START:END!P34:P34) -> 0 | Q32: =IFERROR(P32/P$17,0) -> 0 | R32: =IFERROR(P32/P$6,0) -> 0 | S32: =IFERROR(P32/P$5,0) -> 0 | T32: =SUM(START:END!T34:T34) -> 0 | U32: =IFERROR(T32/T$17,0) -> 0 | V32: =IFERROR(T32/T$6,0) -> 0 | W32: =IFERROR(T32/T$5,0) -> 0 | X32: =SUM(START:END!X34:X34) -> 0 | Y32: =IFERROR(X32/X$17,0) -> 0 | Z32: =IFERROR(X32/X$6,0) -> 0 | AA32: =IFERROR(X32/X$5,0) -> 0 | AB32: =SUM(START:END!AB34:AB34) -> 0 | AC32: =IFERROR(AB32/AB$17,0) -> 0 | AD32: =IFERROR(AB32/AB$6,0) -> 0 | AE32: =IFERROR(AB32/AB$5,0) -> 0 | AF32: =SUM(START:END!AF34:AF34) -> 0 | AG32: =IFERROR(AF32/AF$17,0) -> 0 | AH32: =IFERROR(AF32/AF$6,0) -> 0 | AI32: =IFERROR(AF32/AF$5,0) -> 0 | AJ32: =SUM(START:END!AJ34:AJ34) -> 0 | AK32: =IFERROR(AJ32/AJ$17,0) -> 0 | AL32: =IFERROR(AJ32/AJ$6,0) -> 0 | AM32: =IFERROR(AJ32/AJ$5,0) -> 0 | AN32: =SUM(START:END!AN34:AN34) -> 0 | AO32: =IFERROR(AN32/AN$17,0) -> 0 | AP32: =IFERROR(AN32/AN$6,0) -> 0 | AQ32: =IFERROR(AN32/AN$5,0) -> 0
C33: Property Ops./R&M | D33: =SUM(START:END!D35:D35) -> 0 | E33: =IFERROR(D33/D$17,0) -> 0 | F33: =IFERROR(D33/D$6,0) -> 0 | G33: =IFERROR(D33/D$5,0) -> 0 | H33: =SUM(START:END!H35:H35) -> 0 | I33: =IFERROR(H33/H$17,0) -> 0 | J33: =IFERROR(H33/H$6,0) -> 0 | K33: =IFERROR(H33/H$5,0) -> 0 | L33: =SUM(START:END!L35:L35) -> 0 | M33: =IFERROR(L33/L$17,0) -> 0 | N33: =IFERROR(L33/L$6,0) -> 0 | O33: =IFERROR(L33/L$5,0) -> 0 | P33: =SUM(START:END!P35:P35) -> 0 | Q33: =IFERROR(P33/P$17,0) -> 0 | R33: =IFERROR(P33/P$6,0) -> 0 | S33: =IFERROR(P33/P$5,0) -> 0 | T33: =SUM(START:END!T35:T35) -> 0 | U33: =IFERROR(T33/T$17,0) -> 0 | V33: =IFERROR(T33/T$6,0) -> 0 | W33: =IFERROR(T33/T$5,0) -> 0 | X33: =SUM(START:END!X35:X35) -> 0 | Y33: =IFERROR(X33/X$17,0) -> 0 | Z33: =IFERROR(X33/X$6,0) -> 0 | AA33: =IFERROR(X33/X$5,0) -> 0 | AB33: =SUM(START:END!AB35:AB35) -> 0 | AC33: =IFERROR(AB33/AB$17,0) -> 0 | AD33: =IFERROR(AB33/AB$6,0) -> 0 | AE33: =IFERROR(AB33/AB$5,0) -> 0 | AF33: =SUM(START:END!AF35:AF35) -> 0 | AG33: =IFERROR(AF33/AF$17,0) -> 0 | AH33: =IFERROR(AF33/AF$6,0) -> 0 | AI33: =IFERROR(AF33/AF$5,0) -> 0 | AJ33: =SUM(START:END!AJ35:AJ35) -> 0 | AK33: =IFERROR(AJ33/AJ$17,0) -> 0 | AL33: =IFERROR(AJ33/AJ$6,0) -> 0 | AM33: =IFERROR(AJ33/AJ$5,0) -> 0 | AN33: =SUM(START:END!AN35:AN35) -> 0 | AO33: =IFERROR(AN33/AN$17,0) -> 0 | AP33: =IFERROR(AN33/AN$6,0) -> 0 | AQ33: =IFERROR(AN33/AN$5,0) -> 0
C34: Utilities | D34: =SUM(START:END!D36:D36) -> 0 | E34: =IFERROR(D34/D$17,0) -> 0 | F34: =IFERROR(D34/D$6,0) -> 0 | G34: =IFERROR(D34/D$5,0) -> 0 | H34: =SUM(START:END!H36:H36) -> 0 | I34: =IFERROR(H34/H$17,0) -> 0 | J34: =IFERROR(H34/H$6,0) -> 0 | K34: =IFERROR(H34/H$5,0) -> 0 | L34: =SUM(START:END!L36:L36) -> 0 | M34: =IFERROR(L34/L$17,0) -> 0 | N34: =IFERROR(L34/L$6,0) -> 0 | O34: =IFERROR(L34/L$5,0) -> 0 | P34: =SUM(START:END!P36:P36) -> 0 | Q34: =IFERROR(P34/P$17,0) -> 0 | R34: =IFERROR(P34/P$6,0) -> 0 | S34: =IFERROR(P34/P$5,0) -> 0 | T34: =SUM(START:END!T36:T36) -> 0 | U34: =IFERROR(T34/T$17,0) -> 0 | V34: =IFERROR(T34/T$6,0) -> 0 | W34: =IFERROR(T34/T$5,0) -> 0 | X34: =SUM(START:END!X36:X36) -> 0 | Y34: =IFERROR(X34/X$17,0) -> 0 | Z34: =IFERROR(X34/X$6,0) -> 0 | AA34: =IFERROR(X34/X$5,0) -> 0 | AB34: =SUM(START:END!AB36:AB36) -> 0 | AC34: =IFERROR(AB34/AB$17,0) -> 0 | AD34: =IFERROR(AB34/AB$6,0) -> 0 | AE34: =IFERROR(AB34/AB$5,0) -> 0 | AF34: =SUM(START:END!AF36:AF36) -> 0 | AG34: =IFERROR(AF34/AF$17,0) -> 0 | AH34: =IFERROR(AF34/AF$6,0) -> 0 | AI34: =IFERROR(AF34/AF$5,0) -> 0 | AJ34: =SUM(START:END!AJ36:AJ36) -> 0 | AK34: =IFERROR(AJ34/AJ$17,0) -> 0 | AL34: =IFERROR(AJ34/AJ$6,0) -> 0 | AM34: =IFERROR(AJ34/AJ$5,0) -> 0 | AN34: =SUM(START:END!AN36:AN36) -> 0 | AO34: =IFERROR(AN34/AN$17,0) -> 0 | AP34: =IFERROR(AN34/AN$6,0) -> 0 | AQ34: =IFERROR(AN34/AN$5,0) -> 0
C35: TOTAL UNDISTRIBUTED EXPENSES | D35: =SUM(D28:D34) -> 0 | E35: =IFERROR(D35/D$17,0) -> 0 | F35: =IFERROR(D35/D$6,0) -> 0 | G35: =IFERROR(D35/D$5,0) -> 0 | H35: =SUM(H28:H34) -> 0 | I35: =IFERROR(H35/H$17,0) -> 0 | J35: =IFERROR(H35/H$6,0) -> 0 | K35: =IFERROR(H35/H$5,0) -> 0 | L35: =SUM(L28:L34) -> 0 | M35: =IFERROR(L35/L$17,0) -> 0 | N35: =IFERROR(L35/L$6,0) -> 0 | O35: =IFERROR(L35/L$5,0) -> 0 | P35: =SUM(P28:P34) -> 0 | Q35: =IFERROR(P35/P$17,0) -> 0 | R35: =IFERROR(P35/P$6,0) -> 0 | S35: =IFERROR(P35/P$5,0) -> 0 | T35: =SUM(T28:T34) -> 0 | U35: =IFERROR(T35/T$17,0) -> 0 | V35: =IFERROR(T35/T$6,0) -> 0 | W35: =IFERROR(T35/T$5,0) -> 0 | X35: =SUM(X28:X34) -> 0 | Y35: =IFERROR(X35/X$17,0) -> 0 | Z35: =IFERROR(X35/X$6,0) -> 0 | AA35: =IFERROR(X35/X$5,0) -> 0 | AB35: =SUM(AB28:AB34) -> 0 | AC35: =IFERROR(AB35/AB$17,0) -> 0 | AD35: =IFERROR(AB35/AB$6,0) -> 0 | AE35: =IFERROR(AB35/AB$5,0) -> 0 | AF35: =SUM(AF28:AF34) -> 0 | AG35: =IFERROR(AF35/AF$17,0) -> 0 | AH35: =IFERROR(AF35/AF$6,0) -> 0 | AI35: =IFERROR(AF35/AF$5,0) -> 0 | AJ35: =SUM(AJ28:AJ34) -> 0 | AK35: =IFERROR(AJ35/AJ$17,0) -> 0 | AL35: =IFERROR(AJ35/AJ$6,0) -> 0 | AM35: =IFERROR(AJ35/AJ$5,0) -> 0 | AN35: =SUM(AN28:AN34) -> 0 | AO35: =IFERROR(AN35/AN$17,0) -> 0 | AP35: =IFERROR(AN35/AN$6,0) -> 0 | AQ35: =IFERROR(AN35/AN$5,0) -> 0
C37: GROSS OPERATING PROFIT | D37: =D25-D35 -> 0 | E37: =IFERROR(D37/D$17,0) -> 0 | F37: =IFERROR(D37/D$6,0) -> 0 | G37: =IFERROR(D37/D$5,0) -> 0 | H37: =H25-H35 -> 0 | I37: =IFERROR(H37/H$17,0) -> 0 | J37: =IFERROR(H37/H$6,0) -> 0 | K37: =IFERROR(H37/H$5,0) -> 0 | L37: =L25-L35 -> 0 | M37: =IFERROR(L37/L$17,0) -> 0 | N37: =IFERROR(L37/L$6,0) -> 0 | O37: =IFERROR(L37/L$5,0) -> 0 | P37: =P25-P35 -> 0 | Q37: =IFERROR(P37/P$17,0) -> 0 | R37: =IFERROR(P37/P$6,0) -> 0 | S37: =IFERROR(P37/P$5,0) -> 0 | T37: =T25-T35 -> 0 | U37: =IFERROR(T37/T$17,0) -> 0 | V37: =IFERROR(T37/T$6,0) -> 0 | W37: =IFERROR(T37/T$5,0) -> 0 | X37: =X25-X35 -> 0 | Y37: =IFERROR(X37/X$17,0) -> 0 | Z37: =IFERROR(X37/X$6,0) -> 0 | AA37: =IFERROR(X37/X$5,0) -> 0 | AB37: =AB25-AB35 -> 0 | AC37: =IFERROR(AB37/AB$17,0) -> 0 | AD37: =IFERROR(AB37/AB$6,0) -> 0 | AE37: =IFERROR(AB37/AB$5,0) -> 0 | AF37: =AF25-AF35 -> 0 | AG37: =IFERROR(AF37/AF$17,0) -> 0 | AH37: =IFERROR(AF37/AF$6,0) -> 0 | AI37: =IFERROR(AF37/AF$5,0) -> 0 | AJ37: =AJ25-AJ35 -> 0 | AK37: =IFERROR(AJ37/AJ$17,0) -> 0 | AL37: =IFERROR(AJ37/AJ$6,0) -> 0 | AM37: =IFERROR(AJ37/AJ$5,0) -> 0 | AN37: =AN25-AN35 -> 0 | AO37: =IFERROR(AN37/AN$17,0) -> 0 | AP37: =IFERROR(AN37/AN$6,0) -> 0 | AQ37: =IFERROR(AN37/AN$5,0) -> 0
C39: Management Fees
C40: Management Fee | D40: =SUM(START:END!D42:D42) -> 0 | E40: =IFERROR(D40/D$17,0) -> 0 | F40: =IFERROR(D40/D$6,0) -> 0 | G40: =IFERROR(D40/D$5,0) -> 0 | H40: =SUM(START:END!H42:H42) -> 0 | I40: =IFERROR(H40/H$17,0) -> 0 | J40: =IFERROR(H40/H$6,0) -> 0 | K40: =IFERROR(H40/H$5,0) -> 0 | L40: =SUM(START:END!L42:L42) -> 0 | M40: =IFERROR(L40/L$17,0) -> 0 | N40: =IFERROR(L40/L$6,0) -> 0 | O40: =IFERROR(L40/L$5,0) -> 0 | P40: =SUM(START:END!P42:P42) -> 0 | Q40: =IFERROR(P40/P$17,0) -> 0 | R40: =IFERROR(P40/P$6,0) -> 0 | S40: =IFERROR(P40/P$5,0) -> 0 | T40: =SUM(START:END!T42:T42) -> 0 | U40: =IFERROR(T40/T$17,0) -> 0 | V40: =IFERROR(T40/T$6,0) -> 0 | W40: =IFERROR(T40/T$5,0) -> 0 | X40: =SUM(START:END!X42:X42) -> 0 | Y40: =IFERROR(X40/X$17,0) -> 0 | Z40: =IFERROR(X40/X$6,0) -> 0 | AA40: =IFERROR(X40/X$5,0) -> 0 | AB40: =SUM(START:END!AB42:AB42) -> 0 | AC40: =IFERROR(AB40/AB$17,0) -> 0 | AD40: =IFERROR(AB40/AB$6,0) -> 0 | AE40: =IFERROR(AB40/AB$5,0) -> 0 | AF40: =SUM(START:END!AF42:AF42) -> 0 | AG40: =IFERROR(AF40/AF$17,0) -> 0 | AH40: =IFERROR(AF40/AF$6,0) -> 0 | AI40: =IFERROR(AF40/AF$5,0) -> 0 | AJ40: =SUM(START:END!AJ42:AJ42) -> 0 | AK40: =IFERROR(AJ40/AJ$17,0) -> 0 | AL40: =IFERROR(AJ40/AJ$6,0) -> 0 | AM40: =IFERROR(AJ40/AJ$5,0) -> 0 | AN40: =SUM(START:END!AN42:AN42) -> 0 | AO40: =IFERROR(AN40/AN$17,0) -> 0 | AP40: =IFERROR(AN40/AN$6,0) -> 0 | AQ40: =IFERROR(AN40/AN$5,0) -> 0
C41: Incentive Management Fee | D41: =SUM(START:END!D43:D43) -> 0 | E41: =IFERROR(D41/D$17,0) -> 0 | F41: =IFERROR(D41/D$6,0) -> 0 | G41: =IFERROR(D41/D$5,0) -> 0 | H41: =SUM(START:END!H43:H43) -> 0 | I41: =IFERROR(H41/H$17,0) -> 0 | J41: =IFERROR(H41/H$6,0) -> 0 | K41: =IFERROR(H41/H$5,0) -> 0 | L41: =SUM(START:END!L43:L43) -> 0 | M41: =IFERROR(L41/L$17,0) -> 0 | N41: =IFERROR(L41/L$6,0) -> 0 | O41: =IFERROR(L41/L$5,0) -> 0 | P41: =SUM(START:END!P43:P43) -> 0 | Q41: =IFERROR(P41/P$17,0) -> 0 | R41: =IFERROR(P41/P$6,0) -> 0 | S41: =IFERROR(P41/P$5,0) -> 0 | T41: =SUM(START:END!T43:T43) -> 0 | U41: =IFERROR(T41/T$17,0) -> 0 | V41: =IFERROR(T41/T$6,0) -> 0 | W41: =IFERROR(T41/T$5,0) -> 0 | X41: =SUM(START:END!X43:X43) -> 0 | Y41: =IFERROR(X41/X$17,0) -> 0 | Z41: =IFERROR(X41/X$6,0) -> 0 | AA41: =IFERROR(X41/X$5,0) -> 0 | AB41: =SUM(START:END!AB43:AB43) -> 0 | AC41: =IFERROR(AB41/AB$17,0) -> 0 | AD41: =IFERROR(AB41/AB$6,0) -> 0 | AE41: =IFERROR(AB41/AB$5,0) -> 0 | AF41: =SUM(START:END!AF43:AF43) -> 0 | AG41: =IFERROR(AF41/AF$17,0) -> 0 | AH41: =IFERROR(AF41/AF$6,0) -> 0 | AI41: =IFERROR(AF41/AF$5,0) -> 0 | AJ41: =SUM(START:END!AJ43:AJ43) -> 0 | AK41: =IFERROR(AJ41/AJ$17,0) -> 0 | AL41: =IFERROR(AJ41/AJ$6,0) -> 0 | AM41: =IFERROR(AJ41/AJ$5,0) -> 0 | AN41: =SUM(START:END!AN43:AN43) -> 0 | AO41: =IFERROR(AN41/AN$17,0) -> 0 | AP41: =IFERROR(AN41/AN$6,0) -> 0 | AQ41: =IFERROR(AN41/AN$5,0) -> 0
C42: Management Fee | D42: =SUM(D40:D41) -> 0 | E42: =IFERROR(D42/D$17,0) -> 0 | F42: =IFERROR(D42/D$6,0) -> 0 | G42: =IFERROR(D42/D$5,0) -> 0 | H42: =SUM(H40:H41) -> 0 | I42: =IFERROR(H42/H$17,0) -> 0 | J42: =IFERROR(H42/H$6,0) -> 0 | K42: =IFERROR(H42/H$5,0) -> 0 | L42: =SUM(L40:L41) -> 0 | M42: =IFERROR(L42/L$17,0) -> 0 | N42: =IFERROR(L42/L$6,0) -> 0 | O42: =IFERROR(L42/L$5,0) -> 0 | P42: =SUM(P40:P41) -> 0 | Q42: =IFERROR(P42/P$17,0) -> 0 | R42: =IFERROR(P42/P$6,0) -> 0 | S42: =IFERROR(P42/P$5,0) -> 0 | T42: =SUM(T40:T41) -> 0 | U42: =IFERROR(T42/T$17,0) -> 0 | V42: =IFERROR(T42/T$6,0) -> 0 | W42: =IFERROR(T42/T$5,0) -> 0 | X42: =SUM(X40:X41) -> 0 | Y42: =IFERROR(X42/X$17,0) -> 0 | Z42: =IFERROR(X42/X$6,0) -> 0 | AA42: =IFERROR(X42/X$5,0) -> 0 | AB42: =SUM(AB40:AB41) -> 0 | AC42: =IFERROR(AB42/AB$17,0) -> 0 | AD42: =IFERROR(AB42/AB$6,0) -> 0 | AE42: =IFERROR(AB42/AB$5,0) -> 0 | AF42: =SUM(AF40:AF41) -> 0 | AG42: =IFERROR(AF42/AF$17,0) -> 0 | AH42: =IFERROR(AF42/AF$6,0) -> 0 | AI42: =IFERROR(AF42/AF$5,0) -> 0 | AJ42: =SUM(AJ40:AJ41) -> 0 | AK42: =IFERROR(AJ42/AJ$17,0) -> 0 | AL42: =IFERROR(AJ42/AJ$6,0) -> 0 | AM42: =IFERROR(AJ42/AJ$5,0) -> 0 | AN42: =SUM(AN40:AN41) -> 0 | AO42: =IFERROR(AN42/AN$17,0) -> 0 | AP42: =IFERROR(AN42/AN$6,0) -> 0 | AQ42: =IFERROR(AN42/AN$5,0) -> 0
C44: Fixed Expenses
C45: Other Fixed Expense | D45: =SUM(START:END!D47:D47) -> 0 | E45: =IFERROR(D45/D$17,0) -> 0 | F45: =IFERROR(D45/D$6,0) -> 0 | G45: =IFERROR(D45/D$5,0) -> 0 | H45: =SUM(START:END!H47:H47) -> 0 | I45: =IFERROR(H45/H$17,0) -> 0 | J45: =IFERROR(H45/H$6,0) -> 0 | K45: =IFERROR(H45/H$5,0) -> 0 | L45: =SUM(START:END!L47:L47) -> 0 | M45: =IFERROR(L45/L$17,0) -> 0 | N45: =IFERROR(L45/L$6,0) -> 0 | O45: =IFERROR(L45/L$5,0) -> 0 | P45: =SUM(START:END!P47:P47) -> 0 | Q45: =IFERROR(P45/P$17,0) -> 0 | R45: =IFERROR(P45/P$6,0) -> 0 | S45: =IFERROR(P45/P$5,0) -> 0 | T45: =SUM(START:END!T47:T47) -> 0 | U45: =IFERROR(T45/T$17,0) -> 0 | V45: =IFERROR(T45/T$6,0) -> 0 | W45: =IFERROR(T45/T$5,0) -> 0 | X45: =SUM(START:END!X47:X47) -> 0 | Y45: =IFERROR(X45/X$17,0) -> 0 | Z45: =IFERROR(X45/X$6,0) -> 0 | AA45: =IFERROR(X45/X$5,0) -> 0 | AB45: =SUM(START:END!AB47:AB47) -> 0 | AC45: =IFERROR(AB45/AB$17,0) -> 0 | AD45: =IFERROR(AB45/AB$6,0) -> 0 | AE45: =IFERROR(AB45/AB$5,0) -> 0 | AF45: =SUM(START:END!AF47:AF47) -> 0 | AG45: =IFERROR(AF45/AF$17,0) -> 0 | AH45: =IFERROR(AF45/AF$6,0) -> 0 | AI45: =IFERROR(AF45/AF$5,0) -> 0 | AJ45: =SUM(START:END!AJ47:AJ47) -> 0 | AK45: =IFERROR(AJ45/AJ$17,0) -> 0 | AL45: =IFERROR(AJ45/AJ$6,0) -> 0 | AM45: =IFERROR(AJ45/AJ$5,0) -> 0 | AN45: =SUM(START:END!AN47:AN47) -> 0 | AO45: =IFERROR(AN45/AN$17,0) -> 0 | AP45: =IFERROR(AN45/AN$6,0) -> 0 | AQ45: =IFERROR(AN45/AN$5,0) -> 0
C46: Rents | D46: =SUM(START:END!D48:D48) -> 0 | E46: =IFERROR(D46/D$17,0) -> 0 | F46: =IFERROR(D46/D$6,0) -> 0 | G46: =IFERROR(D46/D$5,0) -> 0 | H46: =SUM(START:END!H48:H48) -> 0 | I46: =IFERROR(H46/H$17,0) -> 0 | J46: =IFERROR(H46/H$6,0) -> 0 | K46: =IFERROR(H46/H$5,0) -> 0 | L46: =SUM(START:END!L48:L48) -> 0 | M46: =IFERROR(L46/L$17,0) -> 0 | N46: =IFERROR(L46/L$6,0) -> 0 | O46: =IFERROR(L46/L$5,0) -> 0 | P46: =SUM(START:END!P48:P48) -> 0 | Q46: =IFERROR(P46/P$17,0) -> 0 | R46: =IFERROR(P46/P$6,0) -> 0 | S46: =IFERROR(P46/P$5,0) -> 0 | T46: =SUM(START:END!T48:T48) -> 0 | U46: =IFERROR(T46/T$17,0) -> 0 | V46: =IFERROR(T46/T$6,0) -> 0 | W46: =IFERROR(T46/T$5,0) -> 0 | X46: =SUM(START:END!X48:X48) -> 0 | Y46: =IFERROR(X46/X$17,0) -> 0 | Z46: =IFERROR(X46/X$6,0) -> 0 | AA46: =IFERROR(X46/X$5,0) -> 0 | AB46: =SUM(START:END!AB48:AB48) -> 0 | AC46: =IFERROR(AB46/AB$17,0) -> 0 | AD46: =IFERROR(AB46/AB$6,0) -> 0 | AE46: =IFERROR(AB46/AB$5,0) -> 0 | AF46: =SUM(START:END!AF48:AF48) -> 0 | AG46: =IFERROR(AF46/AF$17,0) -> 0 | AH46: =IFERROR(AF46/AF$6,0) -> 0 | AI46: =IFERROR(AF46/AF$5,0) -> 0 | AJ46: =SUM(START:END!AJ48:AJ48) -> 0 | AK46: =IFERROR(AJ46/AJ$17,0) -> 0 | AL46: =IFERROR(AJ46/AJ$6,0) -> 0 | AM46: =IFERROR(AJ46/AJ$5,0) -> 0 | AN46: =SUM(START:END!AN48:AN48) -> 0 | AO46: =IFERROR(AN46/AN$17,0) -> 0 | AP46: =IFERROR(AN46/AN$6,0) -> 0 | AQ46: =IFERROR(AN46/AN$5,0) -> 0
C47: Property Taxes | D47: =SUM(START:END!D49:D49) -> 0 | E47: =IFERROR(D47/D$17,0) -> 0 | F47: =IFERROR(D47/D$6,0) -> 0 | G47: =IFERROR(D47/D$5,0) -> 0 | H47: =SUM(START:END!H49:H49) -> 0 | I47: =IFERROR(H47/H$17,0) -> 0 | J47: =IFERROR(H47/H$6,0) -> 0 | K47: =IFERROR(H47/H$5,0) -> 0 | L47: =SUM(START:END!L49:L49) -> 0 | M47: =IFERROR(L47/L$17,0) -> 0 | N47: =IFERROR(L47/L$6,0) -> 0 | O47: =IFERROR(L47/L$5,0) -> 0 | P47: =SUM(START:END!P49:P49) -> 0 | Q47: =IFERROR(P47/P$17,0) -> 0 | R47: =IFERROR(P47/P$6,0) -> 0 | S47: =IFERROR(P47/P$5,0) -> 0 | T47: =SUM(START:END!T49:T49) -> 0 | U47: =IFERROR(T47/T$17,0) -> 0 | V47: =IFERROR(T47/T$6,0) -> 0 | W47: =IFERROR(T47/T$5,0) -> 0 | X47: =SUM(START:END!X49:X49) -> 0 | Y47: =IFERROR(X47/X$17,0) -> 0 | Z47: =IFERROR(X47/X$6,0) -> 0 | AA47: =IFERROR(X47/X$5,0) -> 0 | AB47: =SUM(START:END!AB49:AB49) -> 0 | AC47: =IFERROR(AB47/AB$17,0) -> 0 | AD47: =IFERROR(AB47/AB$6,0) -> 0 | AE47: =IFERROR(AB47/AB$5,0) -> 0 | AF47: =SUM(START:END!AF49:AF49) -> 0 | AG47: =IFERROR(AF47/AF$17,0) -> 0 | AH47: =IFERROR(AF47/AF$6,0) -> 0 | AI47: =IFERROR(AF47/AF$5,0) -> 0 | AJ47: =SUM(START:END!AJ49:AJ49) -> 0 | AK47: =IFERROR(AJ47/AJ$17,0) -> 0 | AL47: =IFERROR(AJ47/AJ$6,0) -> 0 | AM47: =IFERROR(AJ47/AJ$5,0) -> 0 | AN47: =SUM(START:END!AN49:AN49) -> 0 | AO47: =IFERROR(AN47/AN$17,0) -> 0 | AP47: =IFERROR(AN47/AN$6,0) -> 0 | AQ47: =IFERROR(AN47/AN$5,0) -> 0
C48: Property Insurance | D48: =SUM(START:END!D50:D50) -> 0 | E48: =IFERROR(D48/D$17,0) -> 0 | F48: =IFERROR(D48/D$6,0) -> 0 | G48: =IFERROR(D48/D$5,0) -> 0 | H48: =SUM(START:END!H50:H50) -> 0 | I48: =IFERROR(H48/H$17,0) -> 0 | J48: =IFERROR(H48/H$6,0) -> 0 | K48: =IFERROR(H48/H$5,0) -> 0 | L48: =SUM(START:END!L50:L50) -> 0 | M48: =IFERROR(L48/L$17,0) -> 0 | N48: =IFERROR(L48/L$6,0) -> 0 | O48: =IFERROR(L48/L$5,0) -> 0 | P48: =SUM(START:END!P50:P50) -> 0 | Q48: =IFERROR(P48/P$17,0) -> 0 | R48: =IFERROR(P48/P$6,0) -> 0 | S48: =IFERROR(P48/P$5,0) -> 0 | T48: =SUM(START:END!T50:T50) -> 0 | U48: =IFERROR(T48/T$17,0) -> 0 | V48: =IFERROR(T48/T$6,0) -> 0 | W48: =IFERROR(T48/T$5,0) -> 0 | X48: =SUM(START:END!X50:X50) -> 0 | Y48: =IFERROR(X48/X$17,0) -> 0 | Z48: =IFERROR(X48/X$6,0) -> 0 | AA48: =IFERROR(X48/X$5,0) -> 0 | AB48: =SUM(START:END!AB50:AB50) -> 0 | AC48: =IFERROR(AB48/AB$17,0) -> 0 | AD48: =IFERROR(AB48/AB$6,0) -> 0 | AE48: =IFERROR(AB48/AB$5,0) -> 0 | AF48: =SUM(START:END!AF50:AF50) -> 0 | AG48: =IFERROR(AF48/AF$17,0) -> 0 | AH48: =IFERROR(AF48/AF$6,0) -> 0 | AI48: =IFERROR(AF48/AF$5,0) -> 0 | AJ48: =SUM(START:END!AJ50:AJ50) -> 0 | AK48: =IFERROR(AJ48/AJ$17,0) -> 0 | AL48: =IFERROR(AJ48/AJ$6,0) -> 0 | AM48: =IFERROR(AJ48/AJ$5,0) -> 0 | AN48: =SUM(START:END!AN50:AN50) -> 0 | AO48: =IFERROR(AN48/AN$17,0) -> 0 | AP48: =IFERROR(AN48/AN$6,0) -> 0 | AQ48: =IFERROR(AN48/AN$5,0) -> 0
C49: TOTAL FIXED EXPENSES | D49: =SUM(D45:D48) -> 0 | E49: =IFERROR(D49/D$17,0) -> 0 | F49: =IFERROR(D49/D$6,0) -> 0 | G49: =IFERROR(D49/D$5,0) -> 0 | H49: =SUM(H45:H48) -> 0 | I49: =IFERROR(H49/H$17,0) -> 0 | J49: =IFERROR(H49/H$6,0) -> 0 | K49: =IFERROR(H49/H$5,0) -> 0 | L49: =SUM(L45:L48) -> 0 | M49: =IFERROR(L49/L$17,0) -> 0 | N49: =IFERROR(L49/L$6,0) -> 0 | O49: =IFERROR(L49/L$5,0) -> 0 | P49: =SUM(P45:P48) -> 0 | Q49: =IFERROR(P49/P$17,0) -> 0 | R49: =IFERROR(P49/P$6,0) -> 0 | S49: =IFERROR(P49/P$5,0) -> 0 | T49: =SUM(T45:T48) -> 0 | U49: =IFERROR(T49/T$17,0) -> 0 | V49: =IFERROR(T49/T$6,0) -> 0 | W49: =IFERROR(T49/T$5,0) -> 0 | X49: =SUM(X45:X48) -> 0 | Y49: =IFERROR(X49/X$17,0) -> 0 | Z49: =IFERROR(X49/X$6,0) -> 0 | AA49: =IFERROR(X49/X$5,0) -> 0 | AB49: =SUM(AB45:AB48) -> 0 | AC49: =IFERROR(AB49/AB$17,0) -> 0 | AD49: =IFERROR(AB49/AB$6,0) -> 0 | AE49: =IFERROR(AB49/AB$5,0) -> 0 | AF49: =SUM(AF45:AF48) -> 0 | AG49: =IFERROR(AF49/AF$17,0) -> 0 | AH49: =IFERROR(AF49/AF$6,0) -> 0 | AI49: =IFERROR(AF49/AF$5,0) -> 0 | AJ49: =SUM(AJ45:AJ48) -> 0 | AK49: =IFERROR(AJ49/AJ$17,0) -> 0 | AL49: =IFERROR(AJ49/AJ$6,0) -> 0 | AM49: =IFERROR(AJ49/AJ$5,0) -> 0 | AN49: =SUM(AN45:AN48) -> 0 | AO49: =IFERROR(AN49/AN$17,0) -> 0 | AP49: =IFERROR(AN49/AN$6,0) -> 0 | AQ49: =IFERROR(AN49/AN$5,0) -> 0
C51: EBITDA | D51: =D37-D42-D49 -> 0 | E51: =IFERROR(D51/D$17,0) -> 0 | F51: =IFERROR(D51/D$6,0) -> 0 | G51: =IFERROR(D51/D$5,0) -> 0 | H51: =H37-H42-H49 -> 0 | I51: =IFERROR(H51/H$17,0) -> 0 | J51: =IFERROR(H51/H$6,0) -> 0 | K51: =IFERROR(H51/H$5,0) -> 0 | L51: =L37-L42-L49 -> 0 | M51: =IFERROR(L51/L$17,0) -> 0 | N51: =IFERROR(L51/L$6,0) -> 0 | O51: =IFERROR(L51/L$5,0) -> 0 | P51: =P37-P42-P49 -> 0 | Q51: =IFERROR(P51/P$17,0) -> 0 | R51: =IFERROR(P51/P$6,0) -> 0 | S51: =IFERROR(P51/P$5,0) -> 0 | T51: =T37-T42-T49 -> 0 | U51: =IFERROR(T51/T$17,0) -> 0 | V51: =IFERROR(T51/T$6,0) -> 0 | W51: =IFERROR(T51/T$5,0) -> 0 | X51: =X37-X42-X49 -> 0 | Y51: =IFERROR(X51/X$17,0) -> 0 | Z51: =IFERROR(X51/X$6,0) -> 0 | AA51: =IFERROR(X51/X$5,0) -> 0 | AB51: =AB37-AB42-AB49 -> 0 | AC51: =IFERROR(AB51/AB$17,0) -> 0 | AD51: =IFERROR(AB51/AB$6,0) -> 0 | AE51: =IFERROR(AB51/AB$5,0) -> 0 | AF51: =AF37-AF42-AF49 -> 0 | AG51: =IFERROR(AF51/AF$17,0) -> 0 | AH51: =IFERROR(AF51/AF$6,0) -> 0 | AI51: =IFERROR(AF51/AF$5,0) -> 0 | AJ51: =AJ37-AJ42-AJ49 -> 0 | AK51: =IFERROR(AJ51/AJ$17,0) -> 0 | AL51: =IFERROR(AJ51/AJ$6,0) -> 0 | AM51: =IFERROR(AJ51/AJ$5,0) -> 0 | AN51: =AN37-AN42-AN49 -> 0 | AO51: =IFERROR(AN51/AN$17,0) -> 0 | AP51: =IFERROR(AN51/AN$6,0) -> 0 | AQ51: =IFERROR(AN51/AN$5,0) -> 0
C52: FF&E Reserves | D52: =SUM(START:END!D54:D54) -> 0 | E52: =IFERROR(D52/D$17,0) -> 0 | F52: =IFERROR(D52/D$6,0) -> 0 | G52: =IFERROR(D52/D$5,0) -> 0 | H52: =SUM(START:END!H54:H54) -> 0 | I52: =IFERROR(H52/H$17,0) -> 0 | J52: =IFERROR(H52/H$6,0) -> 0 | K52: =IFERROR(H52/H$5,0) -> 0 | L52: =SUM(START:END!L54:L54) -> 0 | M52: =IFERROR(L52/L$17,0) -> 0 | N52: =IFERROR(L52/L$6,0) -> 0 | O52: =IFERROR(L52/L$5,0) -> 0 | P52: =SUM(START:END!P54:P54) -> 0 | Q52: =IFERROR(P52/P$17,0) -> 0 | R52: =IFERROR(P52/P$6,0) -> 0 | S52: =IFERROR(P52/P$5,0) -> 0 | T52: =SUM(START:END!T54:T54) -> 0 | U52: =IFERROR(T52/T$17,0) -> 0 | V52: =IFERROR(T52/T$6,0) -> 0 | W52: =IFERROR(T52/T$5,0) -> 0 | X52: =SUM(START:END!X54:X54) -> 0 | Y52: =IFERROR(X52/X$17,0) -> 0 | Z52: =IFERROR(X52/X$6,0) -> 0 | AA52: =IFERROR(X52/X$5,0) -> 0 | AB52: =SUM(START:END!AB54:AB54) -> 0 | AC52: =IFERROR(AB52/AB$17,0) -> 0 | AD52: =IFERROR(AB52/AB$6,0) -> 0 | AE52: =IFERROR(AB52/AB$5,0) -> 0 | AF52: =SUM(START:END!AF54:AF54) -> 0 | AG52: =IFERROR(AF52/AF$17,0) -> 0 | AH52: =IFERROR(AF52/AF$6,0) -> 0 | AI52: =IFERROR(AF52/AF$5,0) -> 0 | AJ52: =SUM(START:END!AJ54:AJ54) -> 0 | AK52: =IFERROR(AJ52/AJ$17,0) -> 0 | AL52: =IFERROR(AJ52/AJ$6,0) -> 0 | AM52: =IFERROR(AJ52/AJ$5,0) -> 0 | AN52: =SUM(START:END!AN54:AN54) -> 0 | AO52: =IFERROR(AN52/AN$17,0) -> 0 | AP52: =IFERROR(AN52/AN$6,0) -> 0 | AQ52: =IFERROR(AN52/AN$5,0) -> 0
C53: NOI | D53: =D51-D52 -> 0 | E53: =IFERROR(D53/D$17,0) -> 0 | F53: =IFERROR(D53/D$6,0) -> 0 | G53: =IFERROR(D53/D$5,0) -> 0 | H53: =H51-H52 -> 0 | I53: =IFERROR(H53/H$17,0) -> 0 | J53: =IFERROR(H53/H$6,0) -> 0 | K53: =IFERROR(H53/H$5,0) -> 0 | L53: =L51-L52 -> 0 | M53: =IFERROR(L53/L$17,0) -> 0 | N53: =IFERROR(L53/L$6,0) -> 0 | O53: =IFERROR(L53/L$5,0) -> 0 | P53: =P51-P52 -> 0 | Q53: =IFERROR(P53/P$17,0) -> 0 | R53: =IFERROR(P53/P$6,0) -> 0 | S53: =IFERROR(P53/P$5,0) -> 0 | T53: =T51-T52 -> 0 | U53: =IFERROR(T53/T$17,0) -> 0 | V53: =IFERROR(T53/T$6,0) -> 0 | W53: =IFERROR(T53/T$5,0) -> 0 | X53: =X51-X52 -> 0 | Y53: =IFERROR(X53/X$17,0) -> 0 | Z53: =IFERROR(X53/X$6,0) -> 0 | AA53: =IFERROR(X53/X$5,0) -> 0 | AB53: =AB51-AB52 -> 0 | AC53: =IFERROR(AB53/AB$17,0) -> 0 | AD53: =IFERROR(AB53/AB$6,0) -> 0 | AE53: =IFERROR(AB53/AB$5,0) -> 0 | AF53: =AF51-AF52 -> 0 | AG53: =IFERROR(AF53/AF$17,0) -> 0 | AH53: =IFERROR(AF53/AF$6,0) -> 0 | AI53: =IFERROR(AF53/AF$5,0) -> 0 | AJ53: =AJ51-AJ52 -> 0 | AK53: =IFERROR(AJ53/AJ$17,0) -> 0 | AL53: =IFERROR(AJ53/AJ$6,0) -> 0 | AM53: =IFERROR(AJ53/AJ$5,0) -> 0 | AN53: =AN51-AN52 -> 0 | AO53: =IFERROR(AN53/AN$17,0) -> 0 | AP53: =IFERROR(AN53/AN$6,0) -> 0 | AQ53: =IFERROR(AN53/AN$5,0) -> 0
C54: Capital Expenditures | D54: =SUMIFS(Capex!$E$36:$N$36,Capex!$E$5:$N$5,Rollup!D1) -> 0 | H54: =MAX(SUMIFS(Capex!$E$36:$N$36,Capex!$E$5:$N$5,Rollup!H1)-H52,0) -> 0 | L54: =MAX(SUMIFS(Capex!$E$36:$N$36,Capex!$E$5:$N$5,Rollup!L1)-L52,0) -> 0 | P54: =MAX(SUMIFS(Capex!$E$36:$N$36,Capex!$E$5:$N$5,Rollup!P1)-P52,0) -> 0 | T54: =MAX(SUMIFS(Capex!$E$36:$N$36,Capex!$E$5:$N$5,Rollup!T1)-T52,0) -> 0 | X54: =MAX(SUMIFS(Capex!$E$36:$N$36,Capex!$E$5:$N$5,Rollup!X1)-X52,0) -> 0 | AB54: =MAX(SUMIFS(Capex!$E$36:$N$36,Capex!$E$5:$N$5,Rollup!AB1)-AB52,0) -> 0 | AF54: =MAX(SUMIFS(Capex!$E$36:$N$36,Capex!$E$5:$N$5,Rollup!AF1)-AF52,0) -> 0 | AJ54: =SUMIFS(Capex!$E$36:$N$36,Capex!$E$5:$N$5,Rollup!AJ1) -> 0 | AN54: =AF54 -> 0
C55: NOI | D55: =D53-D54 -> 0 | E55: =IFERROR(D55/D$17,0) -> 0 | F55: =IFERROR(D55/D$6,0) -> 0 | G55: =IFERROR(D55/D$5,0) -> 0 | H55: =H53-H54 -> 0 | I55: =IFERROR(H55/H$17,0) -> 0 | J55: =IFERROR(H55/H$6,0) -> 0 | K55: =IFERROR(H55/H$5,0) -> 0 | L55: =L53-L54 -> 0 | M55: =IFERROR(L55/L$17,0) -> 0 | N55: =IFERROR(L55/L$6,0) -> 0 | O55: =IFERROR(L55/L$5,0) -> 0 | P55: =P53-P54 -> 0 | Q55: =IFERROR(P55/P$17,0) -> 0 | R55: =IFERROR(P55/P$6,0) -> 0 | S55: =IFERROR(P55/P$5,0) -> 0 | T55: =T53-T54 -> 0 | U55: =IFERROR(T55/T$17,0) -> 0 | V55: =IFERROR(T55/T$6,0) -> 0 | W55: =IFERROR(T55/T$5,0) -> 0 | X55: =X53-X54 -> 0 | Y55: =IFERROR(X55/X$17,0) -> 0 | Z55: =IFERROR(X55/X$6,0) -> 0 | AA55: =IFERROR(X55/X$5,0) -> 0 | AB55: =AB53-AB54 -> 0 | AC55: =IFERROR(AB55/AB$17,0) -> 0 | AD55: =IFERROR(AB55/AB$6,0) -> 0 | AE55: =IFERROR(AB55/AB$5,0) -> 0 | AF55: =AF53-AF54 -> 0 | AG55: =IFERROR(AF55/AF$17,0) -> 0 | AH55: =IFERROR(AF55/AF$6,0) -> 0 | AI55: =IFERROR(AF55/AF$5,0) -> 0 | AJ55: =AJ53-AJ54 -> 0 | AK55: =IFERROR(AJ55/AJ$17,0) -> 0 | AL55: =IFERROR(AJ55/AJ$6,0) -> 0 | AM55: =IFERROR(AJ55/AJ$5,0) -> 0 | AN55: =AN53-AN54 -> 0 | AO55: =IFERROR(AN55/AN$17,0) -> 0 | AP55: =IFERROR(AN55/AN$6,0) -> 0 | AQ55: =IFERROR(AN55/AN$5,0) -> 0
A56: IG | C56: Debt Service Through IG Classes | D56: =SUMIFS('Cap Stack Control'!$J$28:$J$35,'Cap Stack Control'!$K$28:$K$35,Rollup!$A56) -> 0 | H56: =SUMIFS('Cap Stack Control'!$J$28:$J$35,'Cap Stack Control'!$K$28:$K$35,Rollup!$A56) -> 0 | L56: =SUMIFS('Cap Stack Control'!$J$28:$J$35,'Cap Stack Control'!$K$28:$K$35,Rollup!$A56) -> 0 | P56: =SUMIFS('Cap Stack Control'!$J$28:$J$35,'Cap Stack Control'!$K$28:$K$35,Rollup!$A56) -> 0 | T56: =SUMIFS('Cap Stack Control'!$J$28:$J$35,'Cap Stack Control'!$K$28:$K$35,Rollup!$A56) -> 0 | X56: =SUMIFS('Cap Stack Control'!$J$28:$J$35,'Cap Stack Control'!$K$28:$K$35,Rollup!$A56) -> 0 | AB56: =SUMIFS('Cap Stack Control'!$J$28:$J$35,'Cap Stack Control'!$K$28:$K$35,Rollup!$A56) -> 0 | AF56: =SUMIFS('Cap Stack Control'!$J$28:$J$35,'Cap Stack Control'!$K$28:$K$35,Rollup!$A56) -> 0 | AJ56: =SUMIFS('Cap Stack Control'!$J$28:$J$35,'Cap Stack Control'!$K$28:$K$35,Rollup!$A56) -> 0 | AN56: =SUMIFS('Cap Stack Control'!$J$28:$J$35,'Cap Stack Control'!$K$28:$K$35,Rollup!$A56) -> 0
C57: Cash Flow after IG Debt Service | D57: =D55-D56 -> 0 | E57: =IFERROR(D57/D$17,0) -> 0 | F57: =IFERROR(D57/D$6,0) -> 0 | G57: =IFERROR(D57/D$5,0) -> 0 | H57: =H55-H56 -> 0 | I57: =IFERROR(H57/H$17,0) -> 0 | J57: =IFERROR(H57/H$6,0) -> 0 | K57: =IFERROR(H57/H$5,0) -> 0 | L57: =L55-L56 -> 0 | M57: =IFERROR(L57/L$17,0) -> 0 | N57: =IFERROR(L57/L$6,0) -> 0 | O57: =IFERROR(L57/L$5,0) -> 0 | P57: =P55-P56 -> 0 | Q57: =IFERROR(P57/P$17,0) -> 0 | R57: =IFERROR(P57/P$6,0) -> 0 | S57: =IFERROR(P57/P$5,0) -> 0 | T57: =T55-T56 -> 0 | U57: =IFERROR(T57/T$17,0) -> 0 | V57: =IFERROR(T57/T$6,0) -> 0 | W57: =IFERROR(T57/T$5,0) -> 0 | X57: =X55-X56 -> 0 | Y57: =IFERROR(X57/X$17,0) -> 0 | Z57: =IFERROR(X57/X$6,0) -> 0 | AA57: =IFERROR(X57/X$5,0) -> 0 | AB57: =AB55-AB56 -> 0 | AC57: =IFERROR(AB57/AB$17,0) -> 0 | AD57: =IFERROR(AB57/AB$6,0) -> 0 | AE57: =IFERROR(AB57/AB$5,0) -> 0 | AF57: =AF55-AF56 -> 0 | AG57: =IFERROR(AF57/AF$17,0) -> 0 | AH57: =IFERROR(AF57/AF$6,0) -> 0 | AI57: =IFERROR(AF57/AF$5,0) -> 0 | AJ57: =AJ55-AJ56 -> 0 | AK57: =IFERROR(AJ57/AJ$17,0) -> 0 | AL57: =IFERROR(AJ57/AJ$6,0) -> 0 | AM57: =IFERROR(AJ57/AJ$5,0) -> 0 | AN57: =AN55-AN56 -> 0 | AO57: =IFERROR(AN57/AN$17,0) -> 0 | AP57: =IFERROR(AN57/AN$6,0) -> 0 | AQ57: =IFERROR(AN57/AN$5,0) -> 0
A58: Non-IG | C58: Debt Service Through Bottom of Stack | D58: =SUMIFS('Cap Stack Control'!$J$28:$J$35,'Cap Stack Control'!$K$28:$K$35,Rollup!$A58) -> 0 | H58: =SUMIFS('Cap Stack Control'!$J$28:$J$35,'Cap Stack Control'!$K$28:$K$35,Rollup!$A58) -> 0 | L58: =SUMIFS('Cap Stack Control'!$J$28:$J$35,'Cap Stack Control'!$K$28:$K$35,Rollup!$A58) -> 0 | P58: =SUMIFS('Cap Stack Control'!$J$28:$J$35,'Cap Stack Control'!$K$28:$K$35,Rollup!$A58) -> 0 | T58: =SUMIFS('Cap Stack Control'!$J$28:$J$35,'Cap Stack Control'!$K$28:$K$35,Rollup!$A58) -> 0 | X58: =SUMIFS('Cap Stack Control'!$J$28:$J$35,'Cap Stack Control'!$K$28:$K$35,Rollup!$A58) -> 0 | AB58: =SUMIFS('Cap Stack Control'!$J$28:$J$35,'Cap Stack Control'!$K$28:$K$35,Rollup!$A58) -> 0 | AF58: =SUMIFS('Cap Stack Control'!$J$28:$J$35,'Cap Stack Control'!$K$28:$K$35,Rollup!$A58) -> 0 | AJ58: =SUMIFS('Cap Stack Control'!$J$28:$J$35,'Cap Stack Control'!$K$28:$K$35,Rollup!$A58) -> 0 | AN58: =SUMIFS('Cap Stack Control'!$J$28:$J$35,'Cap Stack Control'!$K$28:$K$35,Rollup!$A58) -> 0
C59: Cash Flow after All Debt Service | D59: =D57-D58 -> 0 | E59: =IFERROR(D59/D$17,0) -> 0 | F59: =IFERROR(D59/D$6,0) -> 0 | G59: =IFERROR(D59/D$5,0) -> 0 | H59: =H57-H58 -> 0 | I59: =IFERROR(H59/H$17,0) -> 0 | J59: =IFERROR(H59/H$6,0) -> 0 | K59: =IFERROR(H59/H$5,0) -> 0 | L59: =L57-L58 -> 0 | M59: =IFERROR(L59/L$17,0) -> 0 | N59: =IFERROR(L59/L$6,0) -> 0 | O59: =IFERROR(L59/L$5,0) -> 0 | P59: =P57-P58 -> 0 | Q59: =IFERROR(P59/P$17,0) -> 0 | R59: =IFERROR(P59/P$6,0) -> 0 | S59: =IFERROR(P59/P$5,0) -> 0 | T59: =T57-T58 -> 0 | U59: =IFERROR(T59/T$17,0) -> 0 | V59: =IFERROR(T59/T$6,0) -> 0 | W59: =IFERROR(T59/T$5,0) -> 0 | X59: =X57-X58 -> 0 | Y59: =IFERROR(X59/X$17,0) -> 0 | Z59: =IFERROR(X59/X$6,0) -> 0 | AA59: =IFERROR(X59/X$5,0) -> 0 | AB59: =AB57-AB58 -> 0 | AC59: =IFERROR(AB59/AB$17,0) -> 0 | AD59: =IFERROR(AB59/AB$6,0) -> 0 | AE59: =IFERROR(AB59/AB$5,0) -> 0 | AF59: =AF57-AF58 -> 0 | AG59: =IFERROR(AF59/AF$17,0) -> 0 | AH59: =IFERROR(AF59/AF$6,0) -> 0 | AI59: =IFERROR(AF59/AF$5,0) -> 0 | AJ59: =AJ57-AJ58 -> 0 | AK59: =IFERROR(AJ59/AJ$17,0) -> 0 | AL59: =IFERROR(AJ59/AJ$6,0) -> 0 | AM59: =IFERROR(AJ59/AJ$5,0) -> 0 | AN59: =AN57-AN58 -> 0 | AO59: =IFERROR(AN59/AN$17,0) -> 0 | AP59: =IFERROR(AN59/AN$6,0) -> 0 | AQ59: =IFERROR(AN59/AN$5,0) -> 0
C60: Cap Rate (Applied to NOI) | D60: - | H60: - | L60: - | P60: - | T60: - | X60: - | AB60: =IFERROR(AB55/AB61,0) -> 0 | AF60: =IFERROR(AF55/AF61,0) -> 0 | AJ60: - | AN60: =IFERROR(AN53/AN61,0) -> 0
C61: Gross Property Value | D61: - | F61: - | H61: - | J61: - | L61: - | N61: - | P61: - | R61: - | T61: - | V61: - | X61: - | Z61: - | AB61: ='Cap Stack Control'!$D$9 -> 0 | AD61: =IFERROR(AB61/$AF$4,0) -> 0 | AF61: ='Cap Stack Control'!$D$9 -> 0 | AH61: =IFERROR(AF61/$AF$4,0) -> 0 | AJ61: - | AL61: - | AN61: ='UW Drivers'!$AB$40 -> 0 | AP61: =IFERROR(AN61/AN4,0) -> 0
C62: CapEx | D62: - | H62: - | L62: - | P62: - | T62: - | X62: - | AB62: 0 | AF62: 0 | AN62: ='UW Drivers'!AI40 -> 0
C63: Net Property Value | D63: - | F63: - | H63: - | J63: - | L63: - | N63: - | P63: - | R63: - | T63: - | V63: - | X63: - | Z63: - | AB63: =AB61-AB62 -> 0 | AD63: =IFERROR(AB63/$AF$4,0) -> 0 | AF63: =AF61-AF62 -> 0 | AH63: =IFERROR(AF63/$AF$4,0) -> 0 | AN63: =AN61-AN62 -> 0 | AP63: =IFERROR(AN63/$AF$4,0) -> 0
C64: IG Bonds DY / DSCR | D64: =IFERROR(TEXT(D53/'Cap Stack Control'!$D$17,"0.0%")&" / "&TEXT(D53/D56,"0.00x"),0) -> 0 | H64: =IFERROR(TEXT(H53/'Cap Stack Control'!$D$17,"0.0%")&" / "&TEXT(H53/H56,"0.00x"),0) -> 0 | L64: =IFERROR(TEXT(L53/'Cap Stack Control'!$D$17,"0.0%")&" / "&TEXT(L53/L56,"0.00x"),0) -> 0 | P64: =IFERROR(TEXT(P53/'Cap Stack Control'!$D$17,"0.0%")&" / "&TEXT(P53/P56,"0.00x"),0) -> 0 | T64: =IFERROR(TEXT(T53/'Cap Stack Control'!$D$17,"0.0%")&" / "&TEXT(T53/T56,"0.00x"),0) -> 0 | X64: =IFERROR(TEXT(X53/'Cap Stack Control'!$D$17,"0.0%")&" / "&TEXT(X53/X56,"0.00x"),0) -> 0 | AB64: =IFERROR(TEXT(AB53/'Cap Stack Control'!$D$17,"0.0%")&" / "&TEXT(AB53/AB56,"0.00x"),0) -> 0 | AF64: =IFERROR(TEXT(AF53/'Cap Stack Control'!$D$17,"0.0%")&" / "&TEXT(AF53/AF56,"0.00x"),0) -> 0 | AJ64: =IFERROR(TEXT(AJ53/'Cap Stack Control'!$D$17,"0.0%")&" / "&TEXT(AJ53/AJ56,"0.00x"),0) -> 0 | AN64: =IFERROR(TEXT(AN53/'Cap Stack Control'!$D$17,"0.0%")&" / "&TEXT(AN53/AN56,"0.00x"),0) -> 0
C65: Last Dollar Debt DY / DSCR | D65: =IFERROR(TEXT(D53/'Cap Stack Control'!$H$23,"0.0%")&" / "&TEXT(D53/(D56+D58),"0.00x"),0) -> 0 | H65: =IFERROR(TEXT(H53/'Cap Stack Control'!$H$23,"0.0%")&" / "&TEXT(H53/(H56+H58),"0.00x"),0) -> 0 | L65: =IFERROR(TEXT(L53/'Cap Stack Control'!$H$23,"0.0%")&" / "&TEXT(L53/(L56+L58),"0.00x"),0) -> 0 | P65: =IFERROR(TEXT(P53/'Cap Stack Control'!$H$23,"0.0%")&" / "&TEXT(P53/(P56+P58),"0.00x"),0) -> 0 | T65: =IFERROR(TEXT(T53/'Cap Stack Control'!$H$23,"0.0%")&" / "&TEXT(T53/(T56+T58),"0.00x"),0) -> 0 | X65: =IFERROR(TEXT(X53/'Cap Stack Control'!$H$23,"0.0%")&" / "&TEXT(X53/(X56+X58),"0.00x"),0) -> 0 | AB65: =IFERROR(TEXT(AB53/'Cap Stack Control'!$H$23,"0.0%")&" / "&TEXT(AB53/(AB56+AB58),"0.00x"),0) -> 0 | AF65: =IFERROR(TEXT(AF53/'Cap Stack Control'!$H$23,"0.0%")&" / "&TEXT(AF53/(AF56+AF58),"0.00x"),0) -> 0 | AJ65: =IFERROR(TEXT(AJ53/'Cap Stack Control'!$H$23,"0.0%")&" / "&TEXT(AJ53/(AJ56+AJ58),"0.00x"),0) -> 0 | AN65: =IFERROR(TEXT(AN53/'Cap Stack Control'!$H$23,"0.0%")&" / "&TEXT(AN53/(AN56+AN58),"0.00x"),0) -> 0
C66: IG Bonds LTV | D66: - | H66: - | L66: - | P66: - | T66: - | X66: - | AB66: - | AF66: =IFERROR('Cap Stack Control'!$D$17/AF61,0) -> 0 | AJ66: =IFERROR('Cap Stack Control'!$D$17/AJ61,0) -> 0 | AN66: =IFERROR('Cap Stack Control'!$D$17/'Cap Stack Control'!$D$11,0) -> 0
C67: Last Dollar Mortgage LTV | D67: - | H67: - | L67: - | P67: - | T67: - | X67: - | AB67: - | AF67: =IFERROR('Cap Stack Control'!$J$23/AF61,0) -> 0 | AJ67: =IFERROR('Cap Stack Control'!$J$23/AJ61,0) -> 0 | AN67: ='Cap Stack Control'!Q23 -> 0
C68: =IFERROR("*Reforecast LTV reflects the estimated appraised value of "&TEXT('Cap Stack Control'!$D$9/1000000,"$#,##0")&"M",0) -> *Reforecast LTV reflects the estimated appraised value of $0M
C69: =IFERROR("*IG Bonds & Last Dollar LTV / DY reflect Sixth Street's in-place UW values after giving credit to the "&TEXT('Cap Stack Control'!$D$12/1000000,"$#,##0")&"M PIP Reserve",0) -> *IG Bonds & Last Dollar LTV / DY reflect Sixth Street's in-place UW values after giving credit to the $0M PIP Reserve
C73: Net Cash Flow | D73: =SUMIFS(Tape!$LW$6:$ME$6,Tape!$LW$5:$ME$5,D3) -> 0 | H73: =SUMIFS(Tape!$LW$6:$ME$6,Tape!$LW$5:$ME$5,H3) -> 0 | L73: =SUMIFS(Tape!$LW$6:$ME$6,Tape!$LW$5:$ME$5,L3) -> 0 | P73: =SUMIFS(Tape!$LW$6:$ME$6,Tape!$LW$5:$ME$5,P3) -> 0 | T73: =SUMIFS(Tape!$LW$6:$ME$6,Tape!$LW$5:$ME$5,T3) -> 0 | X73: =SUMIFS(Tape!$LW$6:$ME$6,Tape!$LW$5:$ME$5,X3) -> 0 | AB73: =SUMIFS(Tape!$LW$6:$ME$6,Tape!$LW$5:$ME$5,AB3) -> 0 | AF73: =SUMIFS(Tape!$LW$6:$ME$6,Tape!$LW$5:$ME$5,AF3) -> 0 | AJ73: =SUMIFS(Tape!$LW$6:$ME$6,Tape!$LW$5:$ME$5,AJ3) -> 0
C74: ADD BACK: DISPLACEMENT | D74: =SUMIFS(Tape!$LN$6:$LV$6,Tape!$LN$5:$LV$5,D3) -> 0 | H74: =SUMIFS(Tape!$LN$6:$LV$6,Tape!$LN$5:$LV$5,H3) -> 0 | L74: =SUMIFS(Tape!$LN$6:$LV$6,Tape!$LN$5:$LV$5,L3) -> 0 | P74: =SUMIFS(Tape!$LN$6:$LV$6,Tape!$LN$5:$LV$5,P3) -> 0 | T74: =SUMIFS(Tape!$LN$6:$LV$6,Tape!$LN$5:$LV$5,T3) -> 0 | X74: =SUMIFS(Tape!$LN$6:$LV$6,Tape!$LN$5:$LV$5,X3) -> 0 | AB74: =SUMIFS(Tape!$LN$6:$LV$6,Tape!$LN$5:$LV$5,AB3) -> 0 | AF74: =SUMIFS(Tape!$LN$6:$LV$6,Tape!$LN$5:$LV$5,AF3) -> 0 | AJ74: =SUMIFS(Tape!$LN$6:$LV$6,Tape!$LN$5:$LV$5,AJ3) -> 0
C75: CHECK | D75: =SUM(D73:D74)=D53 -> TRUE | H75: =SUM(H73,-H74)=H53 -> TRUE | L75: =SUM(L73,-L74)-L53 -> 0 | P75: =SUM(P73:P74)=P53 -> TRUE | T75: =SUM(T73,-T74)=T53 -> TRUE | X75: =SUM(X73,-X74)=X53 -> TRUE | AB75: =SUM(AB73,-AB74)=AB53 -> TRUE | AF75: =SUM(AF73,-AF74)-AF53 -> 0 | AJ75: =SUM(AJ73,-AJ74)=AJ53 -> TRUE

Sheet SSP UW Summary
H1: AB11 | I1: AB55 | J1: AN9 | K1: AN10 | L1: AN11 | M1: AN56 | O1: AN55 | P1: AO55 | Q1: AN57 | AA1: AD3
D3: ='Cap Stack Control'!$D$4&" - Sixth Street UW Summary" -> [Deal Name] - Sixth Street UW Summary
H4: =Tape!$Z$5 -> TTM | J4: Sixth Street Underwriting
D5: Asset | E5: City, State | F5: Service Type | G5: Keys | H5: RevPAR | I5: NOI | J5: Occupancy | K5: ADR | L5: RevPAR | M5: Cap Rate | N5: CapEx Deduct / Key | O5: In-Place NOI | P5: In-Place NOI Margin | Q5: In-Place Value | R5: In-Place Value / Unit | S5: % of Total | T5: Stressed NOI | U5: Stressed NOI Margin | V5: Stressed Value | W5: Stressed Value / Key | X5: % of Total | AA5: YoY RevPAR
B6: =IFERROR(INDEX('UW Drivers'!$C$9:$C$38,MATCH('SSP UW Summary'!$D6,'UW Drivers'!$D$9:$D$38,0)),0) -> 1 | D6: ='UW Drivers'!D9 | E6: =IFERROR(INDEX($G$42:$G$71,MATCH(D6,$D$42:$D$71,0)),"") | F6: =IFERROR(INDEX($H$42:$H$71,MATCH(D6,$D$42:$D$71,0)),"") | G6: =SUMIFS(Tape!$M$7:$M$36,Tape!$C$7:$C$36,'SSP UW Summary'!D6) -> 0 | H6: =IFERROR(INDIRECT("'" & $B6 & "'!" & H$1),0) -> 0 | I6: =IFERROR(INDIRECT("'" & $B6 & "'!" & I$1),0) -> 0 | J6: =IFERROR(INDIRECT("'" & $B6 & "'!" & J$1),0) -> 0 | K6: =IFERROR(INDIRECT("'" & $B6 & "'!" & K$1),0) -> 0 | L6: =IFERROR(INDIRECT("'" & $B6 & "'!" & L$1),0) -> 0 | M6: =IFERROR(INDIRECT("'" & $B6 & "'!" & M$1),0) -> 0 | N6: =SUMIFS('UW Drivers'!$AC$9:$AC$38,'UW Drivers'!$D$9:$D$38, 'SSP UW Summary'!$D6) -> 0 | O6: =IFERROR(INDIRECT("'" & $B6 & "'!" & O$1),0) -> 0 | P6: =IFERROR(INDIRECT("'" & $B6 & "'!" & P$1),0) -> 0 | Q6: =SUMIFS('UW Drivers'!$AD$9:$AD$38,'UW Drivers'!$D$9:$D$38, 'SSP UW Summary'!D6) -> 0 | R6: =IFERROR(Q6/G6,0) -> 0 | S6: =IFERROR(O6/$O$36,0) -> 0 | T6: =SUMIFS('UW Drivers'!$W$9:$W$38,'UW Drivers'!$D$9:$D$38,'SSP UW Summary'!D6) -> 0 | U6: =SUMIFS('UW Drivers'!$Y$9:$Y$38,'UW Drivers'!$D$9:$D$38,'SSP UW Summary'!D6) -> 0 | V6: =SUMIFS('UW Drivers'!$AE$9:$AE$38,'UW Drivers'!$D$9:$D$38,D6) -> 0 | W6: =IFERROR(V6/G6,0) -> 0 | X6: =IFERROR(T6/$T$36,0) -> 0 | AA6: =IFERROR(INDIRECT("'" & $B6 & "'!" & AA$1),0) -> 0
B7: =IFERROR(INDEX('UW Drivers'!$C$9:$C$38,MATCH('SSP UW Summary'!$D7,'UW Drivers'!$D$9:$D$38,0)),0) -> 1 | D7: ='UW Drivers'!D10 | E7: =IFERROR(INDEX($G$42:$G$71,MATCH(D7,$D$42:$D$71,0)),"") | F7: =IFERROR(INDEX($H$42:$H$71,MATCH(D7,$D$42:$D$71,0)),"") | G7: =SUMIFS(Tape!$M$7:$M$36,Tape!$C$7:$C$36,'SSP UW Summary'!D7) -> 0 | H7: =IFERROR(INDIRECT("'" & $B7 & "'!" & H$1),0) -> 0 | I7: =IFERROR(INDIRECT("'" & $B7 & "'!" & I$1),0) -> 0 | J7: =IFERROR(INDIRECT("'" & $B7 & "'!" & J$1),0) -> 0 | K7: =IFERROR(INDIRECT("'" & $B7 & "'!" & K$1),0) -> 0 | L7: =IFERROR(INDIRECT("'" & $B7 & "'!" & L$1),0) -> 0 | M7: =IFERROR(INDIRECT("'" & $B7 & "'!" & M$1),0) -> 0 | N7: =SUMIFS('UW Drivers'!$AC$9:$AC$38,'UW Drivers'!$D$9:$D$38, 'SSP UW Summary'!$D7) -> 0 | O7: =IFERROR(INDIRECT("'" & $B7 & "'!" & O$1),0) -> 0 | P7: =IFERROR(INDIRECT("'" & $B7 & "'!" & P$1),0) -> 0 | Q7: =SUMIFS('UW Drivers'!$AD$9:$AD$38,'UW Drivers'!$D$9:$D$38, 'SSP UW Summary'!D7) -> 0 | R7: =IFERROR(Q7/G7,0) -> 0 | S7: =IFERROR(O7/$O$36,0) -> 0 | T7: =SUMIFS('UW Drivers'!$W$9:$W$38,'UW Drivers'!$D$9:$D$38,'SSP UW Summary'!D7) -> 0 | U7: =SUMIFS('UW Drivers'!$Y$9:$Y$38,'UW Drivers'!$D$9:$D$38,'SSP UW Summary'!D7) -> 0 | V7: =SUMIFS('UW Drivers'!$AE$9:$AE$38,'UW Drivers'!$D$9:$D$38,D7) -> 0 | W7: =IFERROR(V7/G7,0) -> 0 | X7: =IFERROR(T7/$T$36,0) -> 0 | AA7: =IFERROR(INDIRECT("'" & $B7 & "'!" & AA$1),0) -> 0
B8: =IFERROR(INDEX('UW Drivers'!$C$9:$C$38,MATCH('SSP UW Summary'!$D8,'UW Drivers'!$D$9:$D$38,0)),0) -> 1 | D8: ='UW Drivers'!D11 | E8: =IFERROR(INDEX($G$42:$G$71,MATCH(D8,$D$42:$D$71,0)),"") | F8: =IFERROR(INDEX($H$42:$H$71,MATCH(D8,$D$42:$D$71,0)),"") | G8: =SUMIFS(Tape!$M$7:$M$36,Tape!$C$7:$C$36,'SSP UW Summary'!D8) -> 0 | H8: =IFERROR(INDIRECT("'" & $B8 & "'!" & H$1),0) -> 0 | I8: =IFERROR(INDIRECT("'" & $B8 & "'!" & I$1),0) -> 0 | J8: =IFERROR(INDIRECT("'" & $B8 & "'!" & J$1),0) -> 0 | K8: =IFERROR(INDIRECT("'" & $B8 & "'!" & K$1),0) -> 0 | L8: =IFERROR(INDIRECT("'" & $B8 & "'!" & L$1),0) -> 0 | M8: =IFERROR(INDIRECT("'" & $B8 & "'!" & M$1),0) -> 0 | N8: =SUMIFS('UW Drivers'!$AC$9:$AC$38,'UW Drivers'!$D$9:$D$38, 'SSP UW Summary'!$D8) -> 0 | O8: =IFERROR(INDIRECT("'" & $B8 & "'!" & O$1),0) -> 0 | P8: =IFERROR(INDIRECT("'" & $B8 & "'!" & P$1),0) -> 0 | Q8: =SUMIFS('UW Drivers'!$AD$9:$AD$38,'UW Drivers'!$D$9:$D$38, 'SSP UW Summary'!D8) -> 0 | R8: =IFERROR(Q8/G8,0) -> 0 | S8: =IFERROR(O8/$O$36,0) -> 0 | T8: =SUMIFS('UW Drivers'!$W$9:$W$38,'UW Drivers'!$D$9:$D$38,'SSP UW Summary'!D8) -> 0 | U8: =SUMIFS('UW Drivers'!$Y$9:$Y$38,'UW Drivers'!$D$9:$D$38,'SSP UW Summary'!D8) -> 0 | V8: =SUMIFS('UW Drivers'!$AE$9:$AE$38,'UW Drivers'!$D$9:$D$38,D8) -> 0 | W8: =IFERROR(V8/G8,0) -> 0 | X8: =IFERROR(T8/$T$36,0) -> 0 | AA8: =IFERROR(INDIRECT("'" & $B8 & "'!" & AA$1),0) -> 0
B9: =IFERROR(INDEX('UW Drivers'!$C$9:$C$38,MATCH('SSP UW Summary'!$D9,'UW Drivers'!$D$9:$D$38,0)),0) -> 1 | D9: ='UW Drivers'!D12 | E9: =IFERROR(INDEX($G$42:$G$71,MATCH(D9,$D$42:$D$71,0)),"") | F9: =IFERROR(INDEX($H$42:$H$71,MATCH(D9,$D$42:$D$71,0)),"") | G9: =SUMIFS(Tape!$M$7:$M$36,Tape!$C$7:$C$36,'SSP UW Summary'!D9) -> 0 | H9: =IFERROR(INDIRECT("'" & $B9 & "'!" & H$1),0) -> 0 | I9: =IFERROR(INDIRECT("'" & $B9 & "'!" & I$1),0) -> 0 | J9: =IFERROR(INDIRECT("'" & $B9 & "'!" & J$1),0) -> 0 | K9: =IFERROR(INDIRECT("'" & $B9 & "'!" & K$1),0) -> 0 | L9: =IFERROR(INDIRECT("'" & $B9 & "'!" & L$1),0) -> 0 | M9: =IFERROR(INDIRECT("'" & $B9 & "'!" & M$1),0) -> 0 | N9: =SUMIFS('UW Drivers'!$AC$9:$AC$38,'UW Drivers'!$D$9:$D$38, 'SSP UW Summary'!$D9) -> 0 | O9: =IFERROR(INDIRECT("'" & $B9 & "'!" & O$1),0) -> 0 | P9: =IFERROR(INDIRECT("'" & $B9 & "'!" & P$1),0) -> 0 | Q9: =SUMIFS('UW Drivers'!$AD$9:$AD$38,'UW Drivers'!$D$9:$D$38, 'SSP UW Summary'!D9) -> 0 | R9: =IFERROR(Q9/G9,0) -> 0 | S9: =IFERROR(O9/$O$36,0) -> 0 | T9: =SUMIFS('UW Drivers'!$W$9:$W$38,'UW Drivers'!$D$9:$D$38,'SSP UW Summary'!D9) -> 0 | U9: =SUMIFS('UW Drivers'!$Y$9:$Y$38,'UW Drivers'!$D$9:$D$38,'SSP UW Summary'!D9) -> 0 | V9: =SUMIFS('UW Drivers'!$AE$9:$AE$38,'UW Drivers'!$D$9:$D$38,D9) -> 0 | W9: =IFERROR(V9/G9,0) -> 0 | X9: =IFERROR(T9/$T$36,0) -> 0 | AA9: =IFERROR(INDIRECT("'" & $B9 & "'!" & AA$1),0) -> 0
B10: =IFERROR(INDEX('UW Drivers'!$C$9:$C$38,MATCH('SSP UW Summary'!$D10,'UW Drivers'!$D$9:$D$38,0)),0) -> 1 | D10: ='UW Drivers'!D13 | E10: =IFERROR(INDEX($G$42:$G$71,MATCH(D10,$D$42:$D$71,0)),"") | F10: =IFERROR(INDEX($H$42:$H$71,MATCH(D10,$D$42:$D$71,0)),"") | G10: =SUMIFS(Tape!$M$7:$M$36,Tape!$C$7:$C$36,'SSP UW Summary'!D10) -> 0 | H10: =IFERROR(INDIRECT("'" & $B10 & "'!" & H$1),0) -> 0 | I10: =IFERROR(INDIRECT("'" & $B10 & "'!" & I$1),0) -> 0 | J10: =IFERROR(INDIRECT("'" & $B10 & "'!" & J$1),0) -> 0 | K10: =IFERROR(INDIRECT("'" & $B10 & "'!" & K$1),0) -> 0 | L10: =IFERROR(INDIRECT("'" & $B10 & "'!" & L$1),0) -> 0 | M10: =IFERROR(INDIRECT("'" & $B10 & "'!" & M$1),0) -> 0 | N10: =SUMIFS('UW Drivers'!$AC$9:$AC$38,'UW Drivers'!$D$9:$D$38, 'SSP UW Summary'!$D10) -> 0 | O10: =IFERROR(INDIRECT("'" & $B10 & "'!" & O$1),0) -> 0 | P10: =IFERROR(INDIRECT("'" & $B10 & "'!" & P$1),0) -> 0 | Q10: =SUMIFS('UW Drivers'!$AD$9:$AD$38,'UW Drivers'!$D$9:$D$38, 'SSP UW Summary'!D10) -> 0 | R10: =IFERROR(Q10/G10,0) -> 0 | S10: =IFERROR(O10/$O$36,0) -> 0 | T10: =SUMIFS('UW Drivers'!$W$9:$W$38,'UW Drivers'!$D$9:$D$38,'SSP UW Summary'!D10) -> 0 | U10: =SUMIFS('UW Drivers'!$Y$9:$Y$38,'UW Drivers'!$D$9:$D$38,'SSP UW Summary'!D10) -> 0 | V10: =SUMIFS('UW Drivers'!$AE$9:$AE$38,'UW Drivers'!$D$9:$D$38,D10) -> 0 | W10: =IFERROR(V10/G10,0) -> 0 | X10: =IFERROR(T10/$T$36,0) -> 0 | AA10: =IFERROR(INDIRECT("'" & $B10 & "'!" & AA$1),0) -> 0
B11: =IFERROR(INDEX('UW Drivers'!$C$9:$C$38,MATCH('SSP UW Summary'!$D11,'UW Drivers'!$D$9:$D$38,0)),0) -> 1 | D11: ='UW Drivers'!D14 | E11: =IFERROR(INDEX($G$42:$G$71,MATCH(D11,$D$42:$D$71,0)),"") | F11: =IFERROR(INDEX($H$42:$H$71,MATCH(D11,$D$42:$D$71,0)),"") | G11: =SUMIFS(Tape!$M$7:$M$36,Tape!$C$7:$C$36,'SSP UW Summary'!D11) -> 0 | H11: =IFERROR(INDIRECT("'" & $B11 & "'!" & H$1),0) -> 0 | I11: =IFERROR(INDIRECT("'" & $B11 & "'!" & I$1),0) -> 0 | J11: =IFERROR(INDIRECT("'" & $B11 & "'!" & J$1),0) -> 0 | K11: =IFERROR(INDIRECT("'" & $B11 & "'!" & K$1),0) -> 0 | L11: =IFERROR(INDIRECT("'" & $B11 & "'!" & L$1),0) -> 0 | M11: =IFERROR(INDIRECT("'" & $B11 & "'!" & M$1),0) -> 0 | N11: =SUMIFS('UW Drivers'!$AC$9:$AC$38,'UW Drivers'!$D$9:$D$38, 'SSP UW Summary'!$D11) -> 0 | O11: =IFERROR(INDIRECT("'" & $B11 & "'!" & O$1),0) -> 0 | P11: =IFERROR(INDIRECT("'" & $B11 & "'!" & P$1),0) -> 0 | Q11: =SUMIFS('UW Drivers'!$AD$9:$AD$38,'UW Drivers'!$D$9:$D$38, 'SSP UW Summary'!D11) -> 0 | R11: =IFERROR(Q11/G11,0) -> 0 | S11: =IFERROR(O11/$O$36,0) -> 0 | T11: =SUMIFS('UW Drivers'!$W$9:$W$38,'UW Drivers'!$D$9:$D$38,'SSP UW Summary'!D11) -> 0 | U11: =SUMIFS('UW Drivers'!$Y$9:$Y$38,'UW Drivers'!$D$9:$D$38,'SSP UW Summary'!D11) -> 0 | V11: =SUMIFS('UW Drivers'!$AE$9:$AE$38,'UW Drivers'!$D$9:$D$38,D11) -> 0 | W11: =IFERROR(V11/G11,0) -> 0 | X11: =IFERROR(T11/$T$36,0) -> 0 | AA11: =IFERROR(INDIRECT("'" & $B11 & "'!" & AA$1),0) -> 0
B12: =IFERROR(INDEX('UW Drivers'!$C$9:$C$38,MATCH('SSP UW Summary'!$D12,'UW Drivers'!$D$9:$D$38,0)),0) -> 1 | D12: ='UW Drivers'!D15 | E12: =IFERROR(INDEX($G$42:$G$71,MATCH(D12,$D$42:$D$71,0)),"") | F12: =IFERROR(INDEX($H$42:$H$71,MATCH(D12,$D$42:$D$71,0)),"") | G12: =SUMIFS(Tape!$M$7:$M$36,Tape!$C$7:$C$36,'SSP UW Summary'!D12) -> 0 | H12: =IFERROR(INDIRECT("'" & $B12 & "'!" & H$1),0) -> 0 | I12: =IFERROR(INDIRECT("'" & $B12 & "'!" & I$1),0) -> 0 | J12: =IFERROR(INDIRECT("'" & $B12 & "'!" & J$1),0) -> 0 | K12: =IFERROR(INDIRECT("'" & $B12 & "'!" & K$1),0) -> 0 | L12: =IFERROR(INDIRECT("'" & $B12 & "'!" & L$1),0) -> 0 | M12: =IFERROR(INDIRECT("'" & $B12 & "'!" & M$1),0) -> 0 | N12: =SUMIFS('UW Drivers'!$AC$9:$AC$38,'UW Drivers'!$D$9:$D$38, 'SSP UW Summary'!$D12) -> 0 | O12: =IFERROR(INDIRECT("'" & $B12 & "'!" & O$1),0) -> 0 | P12: =IFERROR(INDIRECT("'" & $B12 & "'!" & P$1),0) -> 0 | Q12: =SUMIFS('UW Drivers'!$AD$9:$AD$38,'UW Drivers'!$D$9:$D$38, 'SSP UW Summary'!D12) -> 0 | R12: =IFERROR(Q12/G12,0) -> 0 | S12: =IFERROR(O12/$O$36,0) -> 0 | T12: =SUMIFS('UW Drivers'!$W$9:$W$38,'UW Drivers'!$D$9:$D$38,'SSP UW Summary'!D12) -> 0 | U12: =SUMIFS('UW Drivers'!$Y$9:$Y$38,'UW Drivers'!$D$9:$D$38,'SSP UW Summary'!D12) -> 0 | V12: =SUMIFS('UW Drivers'!$AE$9:$AE$38,'UW Drivers'!$D$9:$D$38,D12) -> 0 | W12: =IFERROR(V12/G12,0) -> 0 | X12: =IFERROR(T12/$T$36,0) -> 0 | AA12: =IFERROR(INDIRECT("'" & $B12 & "'!" & AA$1),0) -> 0
B13: =IFERROR(INDEX('UW Drivers'!$C$9:$C$38,MATCH('SSP UW Summary'!$D13,'UW Drivers'!$D$9:$D$38,0)),0) -> 1 | D13: ='UW Drivers'!D16 | E13: =IFERROR(INDEX($G$42:$G$71,MATCH(D13,$D$42:$D$71,0)),"") | F13: =IFERROR(INDEX($H$42:$H$71,MATCH(D13,$D$42:$D$71,0)),"") | G13: =SUMIFS(Tape!$M$7:$M$36,Tape!$C$7:$C$36,'SSP UW Summary'!D13) -> 0 | H13: =IFERROR(INDIRECT("'" & $B13 & "'!" & H$1),0) -> 0 | I13: =IFERROR(INDIRECT("'" & $B13 & "'!" & I$1),0) -> 0 | J13: =IFERROR(INDIRECT("'" & $B13 & "'!" & J$1),0) -> 0 | K13: =IFERROR(INDIRECT("'" & $B13 & "'!" & K$1),0) -> 0 | L13: =IFERROR(INDIRECT("'" & $B13 & "'!" & L$1),0) -> 0 | M13: =IFERROR(INDIRECT("'" & $B13 & "'!" & M$1),0) -> 0 | N13: =SUMIFS('UW Drivers'!$AC$9:$AC$38,'UW Drivers'!$D$9:$D$38, 'SSP UW Summary'!$D13) -> 0 | O13: =IFERROR(INDIRECT("'" & $B13 & "'!" & O$1),0) -> 0 | P13: =IFERROR(INDIRECT("'" & $B13 & "'!" & P$1),0) -> 0 | Q13: =SUMIFS('UW Drivers'!$AD$9:$AD$38,'UW Drivers'!$D$9:$D$38, 'SSP UW Summary'!D13) -> 0 | R13: =IFERROR(Q13/G13,0) -> 0 | S13: =IFERROR(O13/$O$36,0) -> 0 | T13: =SUMIFS('UW Drivers'!$W$9:$W$38,'UW Drivers'!$D$9:$D$38,'SSP UW Summary'!D13) -> 0 | U13: =SUMIFS('UW Drivers'!$Y$9:$Y$38,'UW Drivers'!$D$9:$D$38,'SSP UW Summary'!D13) -> 0 | V13: =SUMIFS('UW Drivers'!$AE$9:$AE$38,'UW Drivers'!$D$9:$D$38,D13) -> 0 | W13: =IFERROR(V13/G13,0) -> 0 | X13: =IFERROR(T13/$T$36,0) -> 0 | AA13: =IFERROR(INDIRECT("'" & $B13 & "'!" & AA$1),0) -> 0
B14: =IFERROR(INDEX('UW Drivers'!$C$9:$C$38,MATCH('SSP UW Summary'!$D14,'UW Drivers'!$D$9:$D$38,0)),0) -> 1 | D14: ='UW Drivers'!D17 | E14: =IFERROR(INDEX($G$42:$G$71,MATCH(D14,$D$42:$D$71,0)),"") | F14: =IFERROR(INDEX($H$42:$H$71,MATCH(D14,$D$42:$D$71,0)),"") | G14: =SUMIFS(Tape!$M$7:$M$36,Tape!$C$7:$C$36,'SSP UW Summary'!D14) -> 0 | H14: =IFERROR(INDIRECT("'" & $B14 & "'!" & H$1),0) -> 0 | I14: =IFERROR(INDIRECT("'" & $B14 & "'!" & I$1),0) -> 0 | J14: =IFERROR(INDIRECT("'" & $B14 & "'!" & J$1),0) -> 0 | K14: =IFERROR(INDIRECT("'" & $B14 & "'!" & K$1),0) -> 0 | L14: =IFERROR(INDIRECT("'" & $B14 & "'!" & L$1),0) -> 0 | M14: =IFERROR(INDIRECT("'" & $B14 & "'!" & M$1),0) -> 0 | N14: =SUMIFS('UW Drivers'!$AC$9:$AC$38,'UW Drivers'!$D$9:$D$38, 'SSP UW Summary'!$D14) -> 0 | O14: =IFERROR(INDIRECT("'" & $B14 & "'!" & O$1),0) -> 0 | P14: =IFERROR(INDIRECT("'" & $B14 & "'!" & P$1),0) -> 0 | Q14: =SUMIFS('UW Drivers'!$AD$9:$AD$38,'UW Drivers'!$D$9:$D$38, 'SSP UW Summary'!D14) -> 0 | R14: =IFERROR(Q14/G14,0) -> 0 | S14: =IFERROR(O14/$O$36,0) -> 0 | T14: =SUMIFS('UW Drivers'!$W$9:$W$38,'UW Drivers'!$D$9:$D$38,'SSP UW Summary'!D14) -> 0 | U14: =SUMIFS('UW Drivers'!$Y$9:$Y$38,'UW Drivers'!$D$9:$D$38,'SSP UW Summary'!D14) -> 0 | V14: =SUMIFS('UW Drivers'!$AE$9:$AE$38,'UW Drivers'!$D$9:$D$38,D14) -> 0 | W14: =IFERROR(V14/G14,0) -> 0 | X14: =IFERROR(T14/$T$36,0) -> 0 | AA14: =IFERROR(INDIRECT("'" & $B14 & "'!" & AA$1),0) -> 0
B15: =IFERROR(INDEX('UW Drivers'!$C$9:$C$38,MATCH('SSP UW Summary'!$D15,'UW Drivers'!$D$9:$D$38,0)),0) -> 1 | D15: ='UW Drivers'!D18 | E15: =IFERROR(INDEX($G$42:$G$71,MATCH(D15,$D$42:$D$71,0)),"") | F15: =IFERROR(INDEX($H$42:$H$71,MATCH(D15,$D$42:$D$71,0)),"") | G15: =SUMIFS(Tape!$M$7:$M$36,Tape!$C$7:$C$36,'SSP UW Summary'!D15) -> 0 | H15: =IFERROR(INDIRECT("'" & $B15 & "'!" & H$1),0) -> 0 | I15: =IFERROR(INDIRECT("'" & $B15 & "'!" & I$1),0) -> 0 | J15: =IFERROR(INDIRECT("'" & $B15 & "'!" & J$1),0) -> 0 | K15: =IFERROR(INDIRECT("'" & $B15 & "'!" & K$1),0) -> 0 | L15: =IFERROR(INDIRECT("'" & $B15 & "'!" & L$1),0) -> 0 | M15: =IFERROR(INDIRECT("'" & $B15 & "'!" & M$1),0) -> 0 | N15: =SUMIFS('UW Drivers'!$AC$9:$AC$38,'UW Drivers'!$D$9:$D$38, 'SSP UW Summary'!$D15) -> 0 | O15: =IFERROR(INDIRECT("'" & $B15 & "'!" & O$1),0) -> 0 | P15: =IFERROR(INDIRECT("'" & $B15 & "'!" & P$1),0) -> 0 | Q15: =SUMIFS('UW Drivers'!$AD$9:$AD$38,'UW Drivers'!$D$9:$D$38, 'SSP UW Summary'!D15) -> 0 | R15: =IFERROR(Q15/G15,0) -> 0 | S15: =IFERROR(O15/$O$36,0) -> 0 | T15: =SUMIFS('UW Drivers'!$W$9:$W$38,'UW Drivers'!$D$9:$D$38,'SSP UW Summary'!D15) -> 0 | U15: =SUMIFS('UW Drivers'!$Y$9:$Y$38,'UW Drivers'!$D$9:$D$38,'SSP UW Summary'!D15) -> 0 | V15: =SUMIFS('UW Drivers'!$AE$9:$AE$38,'UW Drivers'!$D$9:$D$38,D15) -> 0 | W15: =IFERROR(V15/G15,0) -> 0 | X15: =IFERROR(T15/$T$36,0) -> 0 | AA15: =IFERROR(INDIRECT("'" & $B15 & "'!" & AA$1),0) -> 0
B16: =IFERROR(INDEX('UW Drivers'!$C$9:$C$38,MATCH('SSP UW Summary'!$D16,'UW Drivers'!$D$9:$D$38,0)),0) -> 1 | D16: ='UW Drivers'!D19 | E16: =IFERROR(INDEX($G$42:$G$71,MATCH(D16,$D$42:$D$71,0)),"") | F16: =IFERROR(INDEX($H$42:$H$71,MATCH(D16,$D$42:$D$71,0)),"") | G16: =SUMIFS(Tape!$M$7:$M$36,Tape!$C$7:$C$36,'SSP UW Summary'!D16) -> 0 | H16: =IFERROR(INDIRECT("'" & $B16 & "'!" & H$1),0) -> 0 | I16: =IFERROR(INDIRECT("'" & $B16 & "'!" & I$1),0) -> 0 | J16: =IFERROR(INDIRECT("'" & $B16 & "'!" & J$1),0) -> 0 | K16: =IFERROR(INDIRECT("'" & $B16 & "'!" & K$1),0) -> 0 | L16: =IFERROR(INDIRECT("'" & $B16 & "'!" & L$1),0) -> 0 | M16: =IFERROR(INDIRECT("'" & $B16 & "'!" & M$1),0) -> 0 | N16: =SUMIFS('UW Drivers'!$AC$9:$AC$38,'UW Drivers'!$D$9:$D$38, 'SSP UW Summary'!$D16) -> 0 | O16: =IFERROR(INDIRECT("'" & $B16 & "'!" & O$1),0) -> 0 | P16: =IFERROR(INDIRECT("'" & $B16 & "'!" & P$1),0) -> 0 | Q16: =SUMIFS('UW Drivers'!$AD$9:$AD$38,'UW Drivers'!$D$9:$D$38, 'SSP UW Summary'!D16) -> 0 | R16: =IFERROR(Q16/G16,0) -> 0 | S16: =IFERROR(O16/$O$36,0) -> 0 | T16: =SUMIFS('UW Drivers'!$W$9:$W$38,'UW Drivers'!$D$9:$D$38,'SSP UW Summary'!D16) -> 0 | U16: =SUMIFS('UW Drivers'!$Y$9:$Y$38,'UW Drivers'!$D$9:$D$38,'SSP UW Summary'!D16) -> 0 | V16: =SUMIFS('UW Drivers'!$AE$9:$AE$38,'UW Drivers'!$D$9:$D$38,D16) -> 0 | W16: =IFERROR(V16/G16,0) -> 0 | X16: =IFERROR(T16/$T$36,0) -> 0 | AA16: =IFERROR(INDIRECT("'" & $B16 & "'!" & AA$1),0) -> 0
B17: =IFERROR(INDEX('UW Drivers'!$C$9:$C$38,MATCH('SSP UW Summary'!$D17,'UW Drivers'!$D$9:$D$38,0)),0) -> 1 | D17: ='UW Drivers'!D20 | E17: =IFERROR(INDEX($G$42:$G$71,MATCH(D17,$D$42:$D$71,0)),"") | F17: =IFERROR(INDEX($H$42:$H$71,MATCH(D17,$D$42:$D$71,0)),"") | G17: =SUMIFS(Tape!$M$7:$M$36,Tape!$C$7:$C$36,'SSP UW Summary'!D17) -> 0 | H17: =IFERROR(INDIRECT("'" & $B17 & "'!" & H$1),0) -> 0 | I17: =IFERROR(INDIRECT("'" & $B17 & "'!" & I$1),0) -> 0 | J17: =IFERROR(INDIRECT("'" & $B17 & "'!" & J$1),0) -> 0 | K17: =IFERROR(INDIRECT("'" & $B17 & "'!" & K$1),0) -> 0 | L17: =IFERROR(INDIRECT("'" & $B17 & "'!" & L$1),0) -> 0 | M17: =IFERROR(INDIRECT("'" & $B17 & "'!" & M$1),0) -> 0 | N17: =SUMIFS('UW Drivers'!$AC$9:$AC$38,'UW Drivers'!$D$9:$D$38, 'SSP UW Summary'!$D17) -> 0 | O17: =IFERROR(INDIRECT("'" & $B17 & "'!" & O$1),0) -> 0 | P17: =IFERROR(INDIRECT("'" & $B17 & "'!" & P$1),0) -> 0 | Q17: =SUMIFS('UW Drivers'!$AD$9:$AD$38,'UW Drivers'!$D$9:$D$38, 'SSP UW Summary'!D17) -> 0 | R17: =IFERROR(Q17/G17,0) -> 0 | S17: =IFERROR(O17/$O$36,0) -> 0 | T17: =SUMIFS('UW Drivers'!$W$9:$W$38,'UW Drivers'!$D$9:$D$38,'SSP UW Summary'!D17) -> 0 | U17: =SUMIFS('UW Drivers'!$Y$9:$Y$38,'UW Drivers'!$D$9:$D$38,'SSP UW Summary'!D17) -> 0 | V17: =SUMIFS('UW Drivers'!$AE$9:$AE$38,'UW Drivers'!$D$9:$D$38,D17) -> 0 | W17: =IFERROR(V17/G17,0) -> 0 | X17: =IFERROR(T17/$T$36,0) -> 0 | AA17: =IFERROR(INDIRECT("'" & $B17 & "'!" & AA$1),0) -> 0
... B35: =IFERROR(INDEX('UW Drivers'!$C$9:$C$38,MATCH('SSP UW Summary'!$D35,'UW Drivers'!$D$9:$D$38,0)),0) -> 1 | D35: ='UW Drivers'!D38 | E35: =IFERROR(INDEX($G$42:$G$71,MATCH(D35,$D$42:$D$71,0)),"") | F35: =IFERROR(INDEX($H$42:$H$71,MATCH(D35,$D$42:$D$71,0)),"") | G35: =SUMIFS(Tape!$M$7:$M$36,Tape!$C$7:$C$36,'SSP UW Summary'!D35) -> 0 | H35: =IFERROR(INDIRECT("'" & $B35 & "'!" & H$1),0) -> 0 | I35: =IFERROR(INDIRECT("'" & $B35 & "'!" & I$1),0) -> 0 | J35: =IFERROR(INDIRECT("'" & $B35 & "'!" & J$1),0) -> 0 | K35: =IFERROR(INDIRECT("'" & $B35 & "'!" & K$1),0) -> 0 | L35: =IFERROR(INDIRECT("'" & $B35 & "'!" & L$1),0) -> 0 | M35: =IFERROR(INDIRECT("'" & $B35 & "'!" & M$1),0) -> 0 | N35: =SUMIFS('UW Drivers'!$AC$9:$AC$38,'UW Drivers'!$D$9:$D$38, 'SSP UW Summary'!$D35) -> 0 | O35: =IFERROR(INDIRECT("'" & $B35 & "'!" & O$1),0) -> 0 | P35: =IFERROR(INDIRECT("'" & $B35 & "'!" & P$1),0) -> 0 | Q35: =SUMIFS('UW Drivers'!$AD$9:$AD$38,'UW Drivers'!$D$9:$D$38, 'SSP UW Summary'!D35) -> 0 | R35: =IFERROR(Q35/G35,0) -> 0 | S35: =IFERROR(O35/$O$36,0) -> 0 | T35: =SUMIFS('UW Drivers'!$W$9:$W$38,'UW Drivers'!$D$9:$D$38,'SSP UW Summary'!D35) -> 0 | U35: =SUMIFS('UW Drivers'!$Y$9:$Y$38,'UW Drivers'!$D$9:$D$38,'SSP UW Summary'!D35) -> 0 | V35: =SUMIFS('UW Drivers'!$AE$9:$AE$38,'UW Drivers'!$D$9:$D$38,D35) -> 0 | W35: =IFERROR(V35/G35,0) -> 0 | X35: =IFERROR(T35/$T$36,0) -> 0 | AA35: =IFERROR(INDIRECT("'" & $B35 & "'!" & AA$1),0) -> 0
D36: Total / Wtd. Avg. | G36: =SUM(G6:G35) -> 0 | H36: =Rollup!AB9 -> 0 | I36: =SUM(I6:I35) -> 0 | J36: =Rollup!$AN$7 -> 0 | K36: =Rollup!$AN$8 -> 0 | L36: =Rollup!$AN$9 -> 0 | M36: ='UW Drivers'!AA42 -> 0 | N36: =IFERROR(SUMPRODUCT(N6:N35,$G$6:$G$35)/$G$36,0) -> 0 | O36: =SUM(O6:O35) -> 0 | P36: =IFERROR(SUMPRODUCT(P6:P35,$O$6:$O$35)/O36,0) -> 0 | Q36: =SUM(Q6:Q35) -> 0 | R36: =IFERROR(Q36/G36,0) -> 0 | S36: =IFERROR(O36/$O$36,0) -> 0 | T36: =SUM(T6:T35) -> 0 | U36: =IFERROR(SUMPRODUCT(U6:U35,$O$6:$O$35)/T36,0) -> 0 | V36: =SUM(V6:V35) -> 0 | W36: =IFERROR(V36/G36,0) -> 0 | X36: =IFERROR(T36/$T$36,0) -> 0
D37: SSP Underwritten IG Detach | Q37: =Q36+'Cap Stack Control'!$D$12 -> 0 | V37: =V36+'Cap Stack Control'!$D$12 -> 0
A38: IG | B38: ='Cap Stack Control'!$D$17 -> 0 | D38: Debt Yield (In-Place / Adj.) | E38: =IFERROR(TEXT($O$36/B38,"0.0%")&" / "&TEXT($T$36/B38,"0.0%"),0) -> 0
D39: LTV (In-Place / Adj.) | E39: =IFERROR(TEXT(B38/Q36,"0.0%")&" / "&TEXT(B38/V36,"0.0%"),0) -> 0
D40: Net LTV (In-Place / Adj.) | E40: =IFERROR(TEXT(B38/Q37,"0.0%")&" / "&TEXT(B38/V37,"0.0%"),0) -> 0
D42: =Tape!C7 -> 0 | E42: =Tape!E7 -> 0 | F42: =Tape!F7 -> 0 | G42: =CONCATENATE(E42,", ",F42) -> 0, 0 | H42: =Tape!L7 -> 0
D43: =Tape!C8 -> 0 | E43: =Tape!E8 -> 0 | F43: =Tape!F8 -> 0 | G43: =CONCATENATE(E43,", ",F43) -> 0, 0 | H43: =Tape!L8 -> 0
D44: =Tape!C9 -> 0 | E44: =Tape!E9 -> 0 | F44: =Tape!F9 -> 0 | G44: =CONCATENATE(E44,", ",F44) -> 0, 0 | H44: =Tape!L9 -> 0
D45: =Tape!C10 -> 0 | E45: =Tape!E10 -> 0 | F45: =Tape!F10 -> 0 | G45: =CONCATENATE(E45,", ",F45) -> 0, 0 | H45: =Tape!L10 -> 0
D46: =Tape!C11 -> 0 | E46: =Tape!E11 -> 0 | F46: =Tape!F11 -> 0 | G46: =CONCATENATE(E46,", ",F46) -> 0, 0 | H46: =Tape!L11 -> 0
D47: =Tape!C12 -> 0 | E47: =Tape!E12 -> 0 | F47: =Tape!F12 -> 0 | G47: =CONCATENATE(E47,", ",F47) -> 0, 0 | H47: =Tape!L12 -> 0
D48: =Tape!C13 -> 0 | E48: =Tape!E13 -> 0 | F48: =Tape!F13 -> 0 | G48: =CONCATENATE(E48,", ",F48) -> 0, 0 | H48: =Tape!L13 -> 0
D49: =Tape!C14 -> 0 | E49: =Tape!E14 -> 0 | F49: =Tape!F14 -> 0 | G49: =CONCATENATE(E49,", ",F49) -> 0, 0 | H49: =Tape!L14 -> 0
D50: =Tape!C15 -> 0 | E50: =Tape!E15 -> 0 | F50: =Tape!F15 -> 0 | G50: =CONCATENATE(E50,", ",F50) -> 0, 0 | H50: =Tape!L15 -> 0
D51: =Tape!C16 -> 0 | E51: =Tape!E16 -> 0 | F51: =Tape!F16 -> 0 | G51: =CONCATENATE(E51,", ",F51) -> 0, 0 | H51: =Tape!L16 -> 0
D52: =Tape!C17 -> 0 | E52: =Tape!E17 -> 0 | F52: =Tape!F17 -> 0 | G52: =CONCATENATE(E52,", ",F52) -> 0, 0 | H52: =Tape!L17 -> 0
D53: =Tape!C18 -> 0 | E53: =Tape!E18 -> 0 | F53: =Tape!F18 -> 0 | G53: =CONCATENATE(E53,", ",F53) -> 0, 0 | H53: =Tape!L18 -> 0
... D71: =Tape!C36 -> 0 | E71: =Tape!E36 -> 0 | F71: =Tape!F36 -> 0 | G71: =CONCATENATE(E71,", ",F71) -> 0, 0 | H71: =Tape!L36 -> 0

Sheet START

Sheet 1
AB2: 2yr RevPAR Growth | AD2: =IFERROR((X11/P11)-1,0) -> 0
C3: =IF(INDEX(Tape!$C$7:$C$36,1)="","",INDEX(Tape!$C$7:$C$36,1)) | AB3: YOY RevPAR Growth | AD3: =IFERROR((X11/T11)-1,0) -> 0
D5: =Tape!$T$5 -> 2019 | H5: =Tape!$U$5 -> 2021 | L5: =Tape!$V$5 -> 2022 | P5: =Tape!$W$5 -> 2023 | T5: =Tape!$X$5 -> 2024 | X5: =Tape!$Y$5 -> 2025 | AB5: =Tape!$Z$5 -> TTM | AF5: =Tape!$AA$5 -> Reforecast | AJ5: =Tape!$AB$5 -> Lender UW | AN5: Sixth Street UW
C6: Keys | D6: =SUMIFS(Tape!$M$7:$M$36,Tape!$C$7:$C$36,$C$3) -> 0 | H6: =SUMIFS(Tape!$M$7:$M$36,Tape!$C$7:$C$36,$C$3) -> 0 | L6: =SUMIFS(Tape!$M$7:$M$36,Tape!$C$7:$C$36,$C$3) -> 0 | P6: =SUMIFS(Tape!$M$7:$M$36,Tape!$C$7:$C$36,$C$3) -> 0 | T6: =SUMIFS(Tape!$M$7:$M$36,Tape!$C$7:$C$36,$C$3) -> 0 | X6: =SUMIFS(Tape!$M$7:$M$36,Tape!$C$7:$C$36,$C$3) -> 0 | AB6: =SUMIFS(Tape!$M$7:$M$36,Tape!$C$7:$C$36,$C$3) -> 0 | AF6: =SUMIFS(Tape!$M$7:$M$36,Tape!$C$7:$C$36,$C$3) -> 0 | AJ6: =SUMIFS(Tape!$M$7:$M$36,Tape!$C$7:$C$36,$C$3) -> 0 | AN6: =AJ6 -> 0
C7: ROOMS AVAILABLE | D7: =IFERROR(INDEX(Tape!$T$7:$ME$36,MATCH($C$3,Tape!$C$7:$C$36,0),MATCH($C7&"+"&D$5,Tape!$T$1:$ME$1,0)),0) -> 0 | H7: =IFERROR(INDEX(Tape!$T$7:$ME$36,MATCH($C$3,Tape!$C$7:$C$36,0),MATCH($C7&"+"&H$5,Tape!$T$1:$ME$1,0)),0) -> 0 | L7: =IFERROR(INDEX(Tape!$T$7:$ME$36,MATCH($C$3,Tape!$C$7:$C$36,0),MATCH($C7&"+"&L$5,Tape!$T$1:$ME$1,0)),0) -> 0 | P7: =IFERROR(INDEX(Tape!$T$7:$ME$36,MATCH($C$3,Tape!$C$7:$C$36,0),MATCH($C7&"+"&P$5,Tape!$T$1:$ME$1,0)),0) -> 0 | T7: =IFERROR(INDEX(Tape!$T$7:$ME$36,MATCH($C$3,Tape!$C$7:$C$36,0),MATCH($C7&"+"&T$5,Tape!$T$1:$ME$1,0)),0) -> 0 | X7: =IFERROR(INDEX(Tape!$T$7:$ME$36,MATCH($C$3,Tape!$C$7:$C$36,0),MATCH($C7&"+"&X$5,Tape!$T$1:$ME$1,0)),0) -> 0 | AB7: =IFERROR(INDEX(Tape!$T$7:$ME$36,MATCH($C$3,Tape!$C$7:$C$36,0),MATCH($C7&"+"&AB$5,Tape!$T$1:$ME$1,0)),0) -> 0 | AF7: =IFERROR(INDEX(Tape!$T$7:$ME$36,MATCH($C$3,Tape!$C$7:$C$36,0),MATCH($C7&"+"&AF$5,Tape!$T$1:$ME$1,0)),0) -> 0 | AJ7: =IFERROR(INDEX(Tape!$T$7:$ME$36,MATCH($C$3,Tape!$C$7:$C$36,0),MATCH($C7&"+"&AJ$5,Tape!$T$1:$ME$1,0)),0) -> 0 | AN7: =AN6*365 -> 0
C8: ROOMS SOLD | D8: =IFERROR(INDEX(Tape!$T$7:$ME$36,MATCH($C$3,Tape!$C$7:$C$36,0),MATCH($C8&"+"&D$5,Tape!$T$1:$ME$1,0)),0) -> 0 | H8: =IFERROR(INDEX(Tape!$T$7:$ME$36,MATCH($C$3,Tape!$C$7:$C$36,0),MATCH($C8&"+"&H$5,Tape!$T$1:$ME$1,0)),0) -> 0 | L8: =IFERROR(INDEX(Tape!$T$7:$ME$36,MATCH($C$3,Tape!$C$7:$C$36,0),MATCH($C8&"+"&L$5,Tape!$T$1:$ME$1,0)),0) -> 0 | P8: =IFERROR(INDEX(Tape!$T$7:$ME$36,MATCH($C$3,Tape!$C$7:$C$36,0),MATCH($C8&"+"&P$5,Tape!$T$1:$ME$1,0)),0) -> 0 | T8: =IFERROR(INDEX(Tape!$T$7:$ME$36,MATCH($C$3,Tape!$C$7:$C$36,0),MATCH($C8&"+"&T$5,Tape!$T$1:$ME$1,0)),0) -> 0 | X8: =IFERROR(INDEX(Tape!$T$7:$ME$36,MATCH($C$3,Tape!$C$7:$C$36,0),MATCH($C8&"+"&X$5,Tape!$T$1:$ME$1,0)),0) -> 0 | AB8: =IFERROR(INDEX(Tape!$T$7:$ME$36,MATCH($C$3,Tape!$C$7:$C$36,0),MATCH($C8&"+"&AB$5,Tape!$T$1:$ME$1,0)),0) -> 0 | AF8: =IFERROR(INDEX(Tape!$T$7:$ME$36,MATCH($C$3,Tape!$C$7:$C$36,0),MATCH($C8&"+"&AF$5,Tape!$T$1:$ME$1,0)),0) -> 0 | AJ8: =IFERROR(INDEX(Tape!$T$7:$ME$36,MATCH($C$3,Tape!$C$7:$C$36,0),MATCH($C8&"+"&AJ$5,Tape!$T$1:$ME$1,0)),0) -> 0 | AN8: =AN9*AN7 -> 0
C9: OCCUPANCY | D9: =IFERROR(INDEX(Tape!$T$7:$ME$36,MATCH($C$3,Tape!$C$7:$C$36,0),MATCH($C9&"+"&D$5,Tape!$T$1:$ME$1,0)),0) -> 0 | H9: =IFERROR(INDEX(Tape!$T$7:$ME$36,MATCH($C$3,Tape!$C$7:$C$36,0),MATCH($C9&"+"&H$5,Tape!$T$1:$ME$1,0)),0) -> 0 | L9: =IFERROR(INDEX(Tape!$T$7:$ME$36,MATCH($C$3,Tape!$C$7:$C$36,0),MATCH($C9&"+"&L$5,Tape!$T$1:$ME$1,0)),0) -> 0 | P9: =IFERROR(INDEX(Tape!$T$7:$ME$36,MATCH($C$3,Tape!$C$7:$C$36,0),MATCH($C9&"+"&P$5,Tape!$T$1:$ME$1,0)),0) -> 0 | T9: =IFERROR(INDEX(Tape!$T$7:$ME$36,MATCH($C$3,Tape!$C$7:$C$36,0),MATCH($C9&"+"&T$5,Tape!$T$1:$ME$1,0)),0) -> 0 | X9: =IFERROR(INDEX(Tape!$T$7:$ME$36,MATCH($C$3,Tape!$C$7:$C$36,0),MATCH($C9&"+"&X$5,Tape!$T$1:$ME$1,0)),0) -> 0 | AB9: =IFERROR(INDEX(Tape!$T$7:$ME$36,MATCH($C$3,Tape!$C$7:$C$36,0),MATCH($C9&"+"&AB$5,Tape!$T$1:$ME$1,0)),0) -> 0 | AF9: =IFERROR(INDEX(Tape!$T$7:$ME$36,MATCH($C$3,Tape!$C$7:$C$36,0),MATCH($C9&"+"&AF$5,Tape!$T$1:$ME$1,0)),0) -> 0 | AJ9: =IFERROR(INDEX(Tape!$T$7:$ME$36,MATCH($C$3,Tape!$C$7:$C$36,0),MATCH($C9&"+"&AJ$5,Tape!$T$1:$ME$1,0)),0) -> 0 | AN9: =SUMIFS('UW Drivers'!$P$9:$P$38,'UW Drivers'!$D$9:$D$38,$C$3) -> 0
C10: ADR | D10: =IFERROR(INDEX(Tape!$T$7:$ME$36,MATCH($C$3,Tape!$C$7:$C$36,0),MATCH($C10&"+"&D$5,Tape!$T$1:$ME$1,0)),0) -> 0 | H10: =IFERROR(INDEX(Tape!$T$7:$ME$36,MATCH($C$3,Tape!$C$7:$C$36,0),MATCH($C10&"+"&H$5,Tape!$T$1:$ME$1,0)),0) -> 0 | L10: =IFERROR(INDEX(Tape!$T$7:$ME$36,MATCH($C$3,Tape!$C$7:$C$36,0),MATCH($C10&"+"&L$5,Tape!$T$1:$ME$1,0)),0) -> 0 | P10: =IFERROR(INDEX(Tape!$T$7:$ME$36,MATCH($C$3,Tape!$C$7:$C$36,0),MATCH($C10&"+"&P$5,Tape!$T$1:$ME$1,0)),0) -> 0 | T10: =IFERROR(INDEX(Tape!$T$7:$ME$36,MATCH($C$3,Tape!$C$7:$C$36,0),MATCH($C10&"+"&T$5,Tape!$T$1:$ME$1,0)),0) -> 0 | X10: =IFERROR(INDEX(Tape!$T$7:$ME$36,MATCH($C$3,Tape!$C$7:$C$36,0),MATCH($C10&"+"&X$5,Tape!$T$1:$ME$1,0)),0) -> 0 | AB10: =IFERROR(INDEX(Tape!$T$7:$ME$36,MATCH($C$3,Tape!$C$7:$C$36,0),MATCH($C10&"+"&AB$5,Tape!$T$1:$ME$1,0)),0) -> 0 | AF10: =IFERROR(INDEX(Tape!$T$7:$ME$36,MATCH($C$3,Tape!$C$7:$C$36,0),MATCH($C10&"+"&AF$5,Tape!$T$1:$ME$1,0)),0) -> 0 | AJ10: =IFERROR(INDEX(Tape!$T$7:$ME$36,MATCH($C$3,Tape!$C$7:$C$36,0),MATCH($C10&"+"&AJ$5,Tape!$T$1:$ME$1,0)),0) -> 0 | AN10: =SUMIFS('UW Drivers'!$Q$9:$Q$38,'UW Drivers'!$D$9:$D$38,$C$3) -> 0
C11: REVPAR | D11: =IFERROR(INDEX(Tape!$T$7:$ME$36,MATCH($C$3,Tape!$C$7:$C$36,0),MATCH($C11&"+"&D$5,Tape!$T$1:$ME$1,0)),0) -> 0 | H11: =IFERROR(INDEX(Tape!$T$7:$ME$36,MATCH($C$3,Tape!$C$7:$C$36,0),MATCH($C11&"+"&H$5,Tape!$T$1:$ME$1,0)),0) -> 0 | L11: =IFERROR(INDEX(Tape!$T$7:$ME$36,MATCH($C$3,Tape!$C$7:$C$36,0),MATCH($C11&"+"&L$5,Tape!$T$1:$ME$1,0)),0) -> 0 | P11: =IFERROR(INDEX(Tape!$T$7:$ME$36,MATCH($C$3,Tape!$C$7:$C$36,0),MATCH($C11&"+"&P$5,Tape!$T$1:$ME$1,0)),0) -> 0 | T11: =IFERROR(INDEX(Tape!$T$7:$ME$36,MATCH($C$3,Tape!$C$7:$C$36,0),MATCH($C11&"+"&T$5,Tape!$T$1:$ME$1,0)),0) -> 0 | X11: =IFERROR(INDEX(Tape!$T$7:$ME$36,MATCH($C$3,Tape!$C$7:$C$36,0),MATCH($C11&"+"&X$5,Tape!$T$1:$ME$1,0)),0) -> 0 | AB11: =IFERROR(INDEX(Tape!$T$7:$ME$36,MATCH($C$3,Tape!$C$7:$C$36,0),MATCH($C11&"+"&AB$5,Tape!$T$1:$ME$1,0)),0) -> 0 | AF11: =IFERROR(INDEX(Tape!$T$7:$ME$36,MATCH($C$3,Tape!$C$7:$C$36,0),MATCH($C11&"+"&AF$5,Tape!$T$1:$ME$1,0)),0) -> 0 | AJ11: =IFERROR(INDEX(Tape!$T$7:$ME$36,MATCH($C$3,Tape!$C$7:$C$36,0),MATCH($C11&"+"&AJ$5,Tape!$T$1:$ME$1,0)),0) -> 0 | AN11: =AN9*AN10 -> 0
C13: REVENUES | D13: $ | E13: % Total Rev. | F13: POR | G13: PAR | H13: $ | I13: % Total Rev. | J13: POR | K13: PAR | L13: $ | M13: % Total Rev. | N13: POR | O13: PAR | P13: $ | Q13: % Total Rev. | R13: POR | S13: PAR | T13: $ | U13: % Total Rev. | V13: POR | W13: PAR | X13: $ | Y13: % Total Rev. | Z13: POR | AA13: PAR | AB13: $ | AC13: % Total Rev. | AD13: POR | AE13: PAR | AF13: $ | AG13: % Total Rev. | AH13: POR | AI13: PAR | AJ13: $ | AK13: % Total Rev. | AL13: POR | AM13: PAR | AN13: $ | AO13: % Total Rev. | AP13: POR | AQ13: PAR
C14: Rooms Revenue | D14: =IFERROR(INDEX(Tape!$T$7:$ME$36,MATCH($C$3,Tape!$C$7:$C$36,0),MATCH($C14&"+"&D$5,Tape!$T$1:$ME$1,0)),0) -> 0 | E14: =IFERROR(D14/D$19,0) -> 0 | F14: =IFERROR(D14/D$8,0) -> 0 | G14: =IFERROR(D14/D$7,0) -> 0 | H14: =IFERROR(INDEX(Tape!$T$7:$ME$36,MATCH($C$3,Tape!$C$7:$C$36,0),MATCH($C14&"+"&H$5,Tape!$T$1:$ME$1,0)),0) -> 0 | I14: =IFERROR(H14/H$19,0) -> 0 | J14: =IFERROR(H14/H$8,0) -> 0 | K14: =IFERROR(H14/H$7,0) -> 0 | L14: =IFERROR(INDEX(Tape!$T$7:$ME$36,MATCH($C$3,Tape!$C$7:$C$36,0),MATCH($C14&"+"&L$5,Tape!$T$1:$ME$1,0)),0) -> 0 | M14: =IFERROR(L14/L$19,0) -> 0 | N14: =IFERROR(L14/L$8,0) -> 0 | O14: =IFERROR(L14/L$7,0) -> 0 | P14: =IFERROR(INDEX(Tape!$T$7:$ME$36,MATCH($C$3,Tape!$C$7:$C$36,0),MATCH($C14&"+"&P$5,Tape!$T$1:$ME$1,0)),0) -> 0 | Q14: =IFERROR(P14/P$19,0) -> 0 | R14: =IFERROR(P14/P$8,0) -> 0 | S14: =IFERROR(P14/P$7,0) -> 0 | T14: =IFERROR(INDEX(Tape!$T$7:$ME$36,MATCH($C$3,Tape!$C$7:$C$36,0),MATCH($C14&"+"&T$5,Tape!$T$1:$ME$1,0)),0) -> 0 | U14: =IFERROR(T14/T$19,0) -> 0 | V14: =IFERROR(T14/T$8,0) -> 0 | W14: =IFERROR(T14/T$7,0) -> 0 | X14: =IFERROR(INDEX(Tape!$T$7:$ME$36,MATCH($C$3,Tape!$C$7:$C$36,0),MATCH($C14&"+"&X$5,Tape!$T$1:$ME$1,0)),0) -> 0 | Y14: =IFERROR(X14/X$19,0) -> 0 | Z14: =IFERROR(X14/X$8,0) -> 0 | AA14: =IFERROR(X14/X$7,0) -> 0 | AB14: =IFERROR(INDEX(Tape!$T$7:$ME$36,MATCH($C$3,Tape!$C$7:$C$36,0),MATCH($C14&"+"&AB$5,Tape!$T$1:$ME$1,0)),0) -> 0 | AC14: =IFERROR(AB14/AB$19,0) -> 0 | AD14: =IFERROR(AB14/AB$8,0) -> 0 | AE14: =IFERROR(AB14/AB$7,0) -> 0 | AF14: =IFERROR(INDEX(Tape!$T$7:$ME$36,MATCH($C$3,Tape!$C$7:$C$36,0),MATCH($C14&"+"&AF$5,Tape!$T$1:$ME$1,0)),0) -> 0 | AG14: =IFERROR(AF14/AF$19,0) -> 0 | AH14: =IFERROR(AF14/AF$8,0) -> 0 | AI14: =IFERROR(AF14/AF$7,0) -> 0 | AJ14: =IFERROR(INDEX(Tape!$T$7:$ME$36,MATCH($C$3,Tape!$C$7:$C$36,0),MATCH($C14&"+"&AJ$5,Tape!$T$1:$ME$1,0)),0) -> 0 | AK14: =IFERROR(AJ14/AJ$19,0) -> 0 | AL14: =IFERROR(AJ14/AJ$8,0) -> 0 | AM14: =IFERROR(AJ14/AJ$7,0) -> 0 | AN14: =AN8*AN10 -> 0 | AO14: =IFERROR(AN14/AN$19,0) -> 0 | AP14: =IFERROR(AN14/AN$8,0) -> 0 | AQ14: =IFERROR(AN14/AN$7,0) -> 0
C15: Food & Beverage Revenue | D15: =IFERROR(INDEX(Tape!$T$7:$ME$36,MATCH($C$3,Tape!$C$7:$C$36,0),MATCH($C15&"+"&D$5,Tape!$T$1:$ME$1,0)),0) -> 0 | E15: =IFERROR(D15/D$19,0) -> 0 | F15: =IFERROR(D15/D$8,0) -> 0 | G15: =IFERROR(D15/D$7,0) -> 0 | H15: =IFERROR(INDEX(Tape!$T$7:$ME$36,MATCH($C$3,Tape!$C$7:$C$36,0),MATCH($C15&"+"&H$5,Tape!$T$1:$ME$1,0)),0) -> 0 | I15: =IFERROR(H15/H$19,0) -> 0 | J15: =IFERROR(H15/H$8,0) -> 0 | K15: =IFERROR(H15/H$7,0) -> 0 | L15: =IFERROR(INDEX(Tape!$T$7:$ME$36,MATCH($C$3,Tape!$C$7:$C$36,0),MATCH($C15&"+"&L$5,Tape!$T$1:$ME$1,0)),0) -> 0 | M15: =IFERROR(L15/L$19,0) -> 0 | N15: =IFERROR(L15/L$8,0) -> 0 | O15: =IFERROR(L15/L$7,0) -> 0 | P15: =IFERROR(INDEX(Tape!$T$7:$ME$36,MATCH($C$3,Tape!$C$7:$C$36,0),MATCH($C15&"+"&P$5,Tape!$T$1:$ME$1,0)),0) -> 0 | Q15: =IFERROR(P15/P$19,0) -> 0 | R15: =IFERROR(P15/P$8,0) -> 0 | S15: =IFERROR(P15/P$7,0) -> 0 | T15: =IFERROR(INDEX(Tape!$T$7:$ME$36,MATCH($C$3,Tape!$C$7:$C$36,0),MATCH($C15&"+"&T$5,Tape!$T$1:$ME$1,0)),0) -> 0 | U15: =IFERROR(T15/T$19,0) -> 0 | V15: =IFERROR(T15/T$8,0) -> 0 | W15: =IFERROR(T15/T$7,0) -> 0 | X15: =IFERROR(INDEX(Tape!$T$7:$ME$36,MATCH($C$3,Tape!$C$7:$C$36,0),MATCH($C15&"+"&X$5,Tape!$T$1:$ME$1,0)),0) -> 0 | Y15: =IFERROR(X15/X$19,0) -> 0 | Z15: =IFERROR(X15/X$8,0) -> 0 | AA15: =IFERROR(X15/X$7,0) -> 0 | AB15: =IFERROR(INDEX(Tape!$T$7:$ME$36,MATCH($C$3,Tape!$C$7:$C$36,0),MATCH($C15&"+"&AB$5,Tape!$T$1:$ME$1,0)),0) -> 0 | AC15: =IFERROR(AB15/AB$19,0) -> 0 | AD15: =IFERROR(AB15/AB$8,0) -> 0 | AE15: =IFERROR(AB15/AB$7,0) -> 0 | AF15: =IFERROR(INDEX(Tape!$T$7:$ME$36,MATCH($C$3,Tape!$C$7:$C$36,0),MATCH($C15&"+"&AF$5,Tape!$T$1:$ME$1,0)),0) -> 0 | AG15: =IFERROR(AF15/AF$19,0) -> 0 | AH15: =IFERROR(AF15/AF$8,0) -> 0 | AI15: =IFERROR(AF15/AF$7,0) -> 0 | AJ15: =IFERROR(INDEX(Tape!$T$7:$ME$36,MATCH($C$3,Tape!$C$7:$C$36,0),MATCH($C15&"+"&AJ$5,Tape!$T$1:$ME$1,0)),0) -> 0 | AK15: =IFERROR(AJ15/AJ$19,0) -> 0 | AL15: =IFERROR(AJ15/AJ$8,0) -> 0 | AM15: =IFERROR(AJ15/AJ$7,0) -> 0 | AN15: =AP15*AN$8 -> 0 | AO15: =IFERROR(AN15/AN$19,0) -> 0 | AP15: =AD15 -> 0 | AQ15: =IFERROR(AN15/AN$7,0) -> 0
C16: Other Departmental Revenue | D16: =IFERROR(INDEX(Tape!$T$7:$ME$36,MATCH($C$3,Tape!$C$7:$C$36,0),MATCH($C16&"+"&D$5,Tape!$T$1:$ME$1,0)),0) -> 0 | E16: =IFERROR(D16/D$19,0) -> 0 | F16: =IFERROR(D16/D$8,0) -> 0 | G16: =IFERROR(D16/D$7,0) -> 0 | H16: =IFERROR(INDEX(Tape!$T$7:$ME$36,MATCH($C$3,Tape!$C$7:$C$36,0),MATCH($C16&"+"&H$5,Tape!$T$1:$ME$1,0)),0) -> 0 | I16: =IFERROR(H16/H$19,0) -> 0 | J16: =IFERROR(H16/H$8,0) -> 0 | K16: =IFERROR(H16/H$7,0) -> 0 | L16: =IFERROR(INDEX(Tape!$T$7:$ME$36,MATCH($C$3,Tape!$C$7:$C$36,0),MATCH($C16&"+"&L$5,Tape!$T$1:$ME$1,0)),0) -> 0 | M16: =IFERROR(L16/L$19,0) -> 0 | N16: =IFERROR(L16/L$8,0) -> 0 | O16: =IFERROR(L16/L$7,0) -> 0 | P16: =IFERROR(INDEX(Tape!$T$7:$ME$36,MATCH($C$3,Tape!$C$7:$C$36,0),MATCH($C16&"+"&P$5,Tape!$T$1:$ME$1,0)),0) -> 0 | Q16: =IFERROR(P16/P$19,0) -> 0 | R16: =IFERROR(P16/P$8,0) -> 0 | S16: =IFERROR(P16/P$7,0) -> 0 | T16: =IFERROR(INDEX(Tape!$T$7:$ME$36,MATCH($C$3,Tape!$C$7:$C$36,0),MATCH($C16&"+"&T$5,Tape!$T$1:$ME$1,0)),0) -> 0 | U16: =IFERROR(T16/T$19,0) -> 0 | V16: =IFERROR(T16/T$8,0) -> 0 | W16: =IFERROR(T16/T$7,0) -> 0 | X16: =IFERROR(INDEX(Tape!$T$7:$ME$36,MATCH($C$3,Tape!$C$7:$C$36,0),MATCH($C16&"+"&X$5,Tape!$T$1:$ME$1,0)),0) -> 0 | Y16: =IFERROR(X16/X$19,0) -> 0 | Z16: =IFERROR(X16/X$8,0) -> 0 | AA16: =IFERROR(X16/X$7,0) -> 0 | AB16: =IFERROR(INDEX(Tape!$T$7:$ME$36,MATCH($C$3,Tape!$C$7:$C$36,0),MATCH($C16&"+"&AB$5,Tape!$T$1:$ME$1,0)),0) -> 0 | AC16: =IFERROR(AB16/AB$19,0) -> 0 | AD16: =IFERROR(AB16/AB$8,0) -> 0 | AE16: =IFERROR(AB16/AB$7,0) -> 0 | AF16: =IFERROR(INDEX(Tape!$T$7:$ME$36,MATCH($C$3,Tape!$C$7:$C$36,0),MATCH($C16&"+"&AF$5,Tape!$T$1:$ME$1,0)),0) -> 0 | AG16: =IFERROR(AF16/AF$19,0) -> 0 | AH16: =IFERROR(AF16/AF$8,0) -> 0 | AI16: =IFERROR(AF16/AF$7,0) -> 0 | AJ16: =IFERROR(INDEX(Tape!$T$7:$ME$36,MATCH($C$3,Tape!$C$7:$C$36,0),MATCH($C16&"+"&AJ$5,Tape!$T$1:$ME$1,0)),0) -> 0 | AK16: =IFERROR(AJ16/AJ$19,0) -> 0 | AL16: =IFERROR(AJ16/AJ$8,0) -> 0 | AM16: =IFERROR(AJ16/AJ$7,0) -> 0 | AN16: =AP16*AN$8 -> 0 | AO16: =IFERROR(AN16/AN$19,0) -> 0 | AP16: =AD16 -> 0 | AQ16: =IFERROR(AN16/AN$7,0) -> 0
C17: Parking Revenue | D17: =IFERROR(INDEX(Tape!$T$7:$ME$36,MATCH($C$3,Tape!$C$7:$C$36,0),MATCH($C17&"+"&D$5,Tape!$T$1:$ME$1,0)),0) -> 0 | E17: =IFERROR(D17/D$19,0) -> 0 | F17: =IFERROR(D17/D$8,0) -> 0 | G17: =IFERROR(D17/D$7,0) -> 0 | H17: =IFERROR(INDEX(Tape!$T$7:$ME$36,MATCH($C$3,Tape!$C$7:$C$36,0),MATCH($C17&"+"&H$5,Tape!$T$1:$ME$1,0)),0) -> 0 | I17: =IFERROR(H17/H$19,0) -> 0 | J17: =IFERROR(H17/H$8,0) -> 0 | K17: =IFERROR(H17/H$7,0) -> 0 | L17: =IFERROR(INDEX(Tape!$T$7:$ME$36,MATCH($C$3,Tape!$C$7:$C$36,0),MATCH($C17&"+"&L$5,Tape!$T$1:$ME$1,0)),0) -> 0 | M17: =IFERROR(L17/L$19,0) -> 0 | N17: =IFERROR(L17/L$8,0) -> 0 | O17: =IFERROR(L17/L$7,0) -> 0 | P17: =IFERROR(INDEX(Tape!$T$7:$ME$36,MATCH($C$3,Tape!$C$7:$C$36,0),MATCH($C17&"+"&P$5,Tape!$T$1:$ME$1,0)),0) -> 0 | Q17: =IFERROR(P17/P$19,0) -> 0 | R17: =IFERROR(P17/P$8,0) -> 0 | S17: =IFERROR(P17/P$7,0) -> 0 | T17: =IFERROR(INDEX(Tape!$T$7:$ME$36,MATCH($C$3,Tape!$C$7:$C$36,0),MATCH($C17&"+"&T$5,Tape!$T$1:$ME$1,0)),0) -> 0 | U17: =IFERROR(T17/T$19,0) -> 0 | V17: =IFERROR(T17/T$8,0) -> 0 | W17: =IFERROR(T17/T$7,0) -> 0 | X17: =IFERROR(INDEX(Tape!$T$7:$ME$36,MATCH($C$3,Tape!$C$7:$C$36,0),MATCH($C17&"+"&X$5,Tape!$T$1:$ME$1,0)),0) -> 0 | Y17: =IFERROR(X17/X$19,0) -> 0 | Z17: =IFERROR(X17/X$8,0) -> 0 | AA17: =IFERROR(X17/X$7,0) -> 0 | AB17: =IFERROR(INDEX(Tape!$T$7:$ME$36,MATCH($C$3,Tape!$C$7:$C$36,0),MATCH($C17&"+"&AB$5,Tape!$T$1:$ME$1,0)),0) -> 0 | AC17: =IFERROR(AB17/AB$19,0) -> 0 | AD17: =IFERROR(AB17/AB$8,0) -> 0 | AE17: =IFERROR(AB17/AB$7,0) -> 0 | AF17: =IFERROR(INDEX(Tape!$T$7:$ME$36,MATCH($C$3,Tape!$C$7:$C$36,0),MATCH($C17&"+"&AF$5,Tape!$T$1:$ME$1,0)),0) -> 0 | AG17: =IFERROR(AF17/AF$19,0) -> 0 | AH17: =IFERROR(AF17/AF$8,0) -> 0 | AI17: =IFERROR(AF17/AF$7,0) -> 0 | AJ17: =IFERROR(INDEX(Tape!$T$7:$ME$36,MATCH($C$3,Tape!$C$7:$C$36,0),MATCH($C17&"+"&AJ$5,Tape!$T$1:$ME$1,0)),0) -> 0 | AK17: =IFERROR(AJ17/AJ$19,0) -> 0 | AL17: =IFERROR(AJ17/AJ$8,0) -> 0 | AM17: =IFERROR(AJ17/AJ$7,0) -> 0 | AN17: =AP17*AN$8 -> 0 | AO17: =IFERROR(AN17/AN$19,0) -> 0 | AP17: =AD17 -> 0 | AQ17: =IFERROR(AN17/AN$7,0) -> 0
C18: Miscellaneous | D18: =IFERROR(INDEX(Tape!$T$7:$ME$36,MATCH($C$3,Tape!$C$7:$C$36,0),MATCH($C18&"+"&D$5,Tape!$T$1:$ME$1,0)),0) -> 0 | E18: =IFERROR(D18/D$19,0) -> 0 | F18: =IFERROR(D18/D$8,0) -> 0 | G18: =IFERROR(D18/D$7,0) -> 0 | H18: =IFERROR(INDEX(Tape!$T$7:$ME$36,MATCH($C$3,Tape!$C$7:$C$36,0),MATCH($C18&"+"&H$5,Tape!$T$1:$ME$1,0)),0) -> 0 | I18: =IFERROR(H18/H$19,0) -> 0 | J18: =IFERROR(H18/H$8,0) -> 0 | K18: =IFERROR(H18/H$7,0) -> 0 | L18: =IFERROR(INDEX(Tape!$T$7:$ME$36,MATCH($C$3,Tape!$C$7:$C$36,0),MATCH($C18&"+"&L$5,Tape!$T$1:$ME$1,0)),0) -> 0 | M18: =IFERROR(L18/L$19,0) -> 0 | N18: =IFERROR(L18/L$8,0) -> 0 | O18: =IFERROR(L18/L$7,0) -> 0 | P18: =IFERROR(INDEX(Tape!$T$7:$ME$36,MATCH($C$3,Tape!$C$7:$C$36,0),MATCH($C18&"+"&P$5,Tape!$T$1:$ME$1,0)),0) -> 0 | Q18: =IFERROR(P18/P$19,0) -> 0 | R18: =IFERROR(P18/P$8,0) -> 0 | S18: =IFERROR(P18/P$7,0) -> 0 | T18: =IFERROR(INDEX(Tape!$T$7:$ME$36,MATCH($C$3,Tape!$C$7:$C$36,0),MATCH($C18&"+"&T$5,Tape!$T$1:$ME$1,0)),0) -> 0 | U18: =IFERROR(T18/T$19,0) -> 0 | V18: =IFERROR(T18/T$8,0) -> 0 | W18: =IFERROR(T18/T$7,0) -> 0 | X18: =IFERROR(INDEX(Tape!$T$7:$ME$36,MATCH($C$3,Tape!$C$7:$C$36,0),MATCH($C18&"+"&X$5,Tape!$T$1:$ME$1,0)),0) -> 0 | Y18: =IFERROR(X18/X$19,0) -> 0 | Z18: =IFERROR(X18/X$8,0) -> 0 | AA18: =IFERROR(X18/X$7,0) -> 0 | AB18: =IFERROR(INDEX(Tape!$T$7:$ME$36,MATCH($C$3,Tape!$C$7:$C$36,0),MATCH($C18&"+"&AB$5,Tape!$T$1:$ME$1,0)),0) -> 0 | AC18: =IFERROR(AB18/AB$19,0) -> 0 | AD18: =IFERROR(AB18/AB$8,0) -> 0 | AE18: =IFERROR(AB18/AB$7,0) -> 0 | AF18: =IFERROR(INDEX(Tape!$T$7:$ME$36,MATCH($C$3,Tape!$C$7:$C$36,0),MATCH($C18&"+"&AF$5,Tape!$T$1:$ME$1,0)),0) -> 0 | AG18: =IFERROR(AF18/AF$19,0) -> 0 | AH18: =IFERROR(AF18/AF$8,0) -> 0 | AI18: =IFERROR(AF18/AF$7,0) -> 0 | AJ18: =IFERROR(INDEX(Tape!$T$7:$ME$36,MATCH($C$3,Tape!$C$7:$C$36,0),MATCH($C18&"+"&AJ$5,Tape!$T$1:$ME$1,0)),0) -> 0 | AK18: =IFERROR(AJ18/AJ$19,0) -> 0 | AL18: =IFERROR(AJ18/AJ$8,0) -> 0 | AM18: =IFERROR(AJ18/AJ$7,0) -> 0 | AN18: =AP18*AN$8 -> 0 | AO18: =IFERROR(AN18/AN$19,0) -> 0 | AP18: =AD18 -> 0 | AQ18: =IFERROR(AN18/AN$7,0) -> 0
C19: TOTAL REVENUES | D19: =SUM(D14:D18) -> 0 | E19: =IFERROR(D19/D$19,0) -> 0 | F19: =IFERROR(D19/D$8,0) -> 0 | G19: =IFERROR(D19/D$7,0) -> 0 | H19: =SUM(H14:H18) -> 0 | I19: =IFERROR(H19/H$19,0) -> 0 | J19: =IFERROR(H19/H$8,0) -> 0 | K19: =IFERROR(H19/H$7,0) -> 0 | L19: =SUM(L14:L18) -> 0 | M19: =IFERROR(L19/L$19,0) -> 0 | N19: =IFERROR(L19/L$8,0) -> 0 | O19: =IFERROR(L19/L$7,0) -> 0 | P19: =SUM(P14:P18) -> 0 | Q19: =IFERROR(P19/P$19,0) -> 0 | R19: =IFERROR(P19/P$8,0) -> 0 | S19: =IFERROR(P19/P$7,0) -> 0 | T19: =SUM(T14:T18) -> 0 | U19: =IFERROR(T19/T$19,0) -> 0 | V19: =IFERROR(T19/T$8,0) -> 0 | W19: =IFERROR(T19/T$7,0) -> 0 | X19: =SUM(X14:X18) -> 0 | Y19: =IFERROR(X19/X$19,0) -> 0 | Z19: =IFERROR(X19/X$8,0) -> 0 | AA19: =IFERROR(X19/X$7,0) -> 0 | AB19: =SUM(AB14:AB18) -> 0 | AC19: =IFERROR(AB19/AB$19,0) -> 0 | AD19: =IFERROR(AB19/AB$8,0) -> 0 | AE19: =IFERROR(AB19/AB$7,0) -> 0 | AF19: =SUM(AF14:AF18) -> 0 | AG19: =IFERROR(AF19/AF$19,0) -> 0 | AH19: =IFERROR(AF19/AF$8,0) -> 0 | AI19: =IFERROR(AF19/AF$7,0) -> 0 | AJ19: =SUM(AJ14:AJ18) -> 0 | AK19: =IFERROR(AJ19/AJ$19,0) -> 0 | AL19: =IFERROR(AJ19/AJ$8,0) -> 0 | AM19: =IFERROR(AJ19/AJ$7,0) -> 0 | AN19: =SUM(AN14:AN18) -> 0 | AO19: =IFERROR(AN19/AN$19,0) -> 0 | AP19: =IFERROR(AN19/AN$8,0) -> 0 | AQ19: =IFERROR(AN19/AN$7,0) -> 0
C21: DEPARTMENTAL EXPENSES
C22: Rooms Expense | D22: =IFERROR(INDEX(Tape!$T$7:$ME$36,MATCH($C$3,Tape!$C$7:$C$36,0),MATCH($C22&"+"&D$5,Tape!$T$1:$ME$1,0)),0) -> 0 | E22: =IFERROR(D22/D14,0) -> 0 | F22: =IFERROR(D22/D$8,0) -> 0 | G22: =IFERROR(D22/D$7,0) -> 0 | H22: =IFERROR(INDEX(Tape!$T$7:$ME$36,MATCH($C$3,Tape!$C$7:$C$36,0),MATCH($C22&"+"&H$5,Tape!$T$1:$ME$1,0)),0) -> 0 | I22: =IFERROR(H22/H14,0) -> 0 | J22: =IFERROR(H22/H$8,0) -> 0 | K22: =IFERROR(H22/H$7,0) -> 0 | L22: =IFERROR(INDEX(Tape!$T$7:$ME$36,MATCH($C$3,Tape!$C$7:$C$36,0),MATCH($C22&"+"&L$5,Tape!$T$1:$ME$1,0)),0) -> 0 | M22: =IFERROR(L22/L14,0) -> 0 | N22: =IFERROR(L22/L$8,0) -> 0 | O22: =IFERROR(L22/L$7,0) -> 0 | P22: =IFERROR(INDEX(Tape!$T$7:$ME$36,MATCH($C$3,Tape!$C$7:$C$36,0),MATCH($C22&"+"&P$5,Tape!$T$1:$ME$1,0)),0) -> 0 | Q22: =IFERROR(P22/P14,0) -> 0 | R22: =IFERROR(P22/P$8,0) -> 0 | S22: =IFERROR(P22/P$7,0) -> 0 | T22: =IFERROR(INDEX(Tape!$T$7:$ME$36,MATCH($C$3,Tape!$C$7:$C$36,0),MATCH($C22&"+"&T$5,Tape!$T$1:$ME$1,0)),0) -> 0 | U22: =IFERROR(T22/T14,0) -> 0 | V22: =IFERROR(T22/T$8,0) -> 0 | W22: =IFERROR(T22/T$7,0) -> 0 | X22: =IFERROR(INDEX(Tape!$T$7:$ME$36,MATCH($C$3,Tape!$C$7:$C$36,0),MATCH($C22&"+"&X$5,Tape!$T$1:$ME$1,0)),0) -> 0 | Y22: =IFERROR(X22/X14,0) -> 0 | Z22: =IFERROR(X22/X$8,0) -> 0 | AA22: =IFERROR(X22/X$7,0) -> 0 | AB22: =IFERROR(INDEX(Tape!$T$7:$ME$36,MATCH($C$3,Tape!$C$7:$C$36,0),MATCH($C22&"+"&AB$5,Tape!$T$1:$ME$1,0)),0) -> 0 | AC22: =IFERROR(AB22/AB14,0) -> 0 | AD22: =IFERROR(AB22/AB$8,0) -> 0 | AE22: =IFERROR(AB22/AB$7,0) -> 0 | AF22: =IFERROR(INDEX(Tape!$T$7:$ME$36,MATCH($C$3,Tape!$C$7:$C$36,0),MATCH($C22&"+"&AF$5,Tape!$T$1:$ME$1,0)),0) -> 0 | AG22: =IFERROR(AF22/AF14,0) -> 0 | AH22: =IFERROR(AF22/AF$8,0) -> 0 | AI22: =IFERROR(AF22/AF$7,0) -> 0 | AJ22: =IFERROR(INDEX(Tape!$T$7:$ME$36,MATCH($C$3,Tape!$C$7:$C$36,0),MATCH($C22&"+"&AJ$5,Tape!$T$1:$ME$1,0)),0) -> 0 | AK22: =IFERROR(AJ22/AJ14,0) -> 0 | AL22: =IFERROR(AJ22/AJ$8,0) -> 0 | AM22: =IFERROR(AJ22/AJ$7,0) -> 0 | AN22: =AO22*AN14 -> 0 | AO22: =AC22 -> 0 | AP22: =IFERROR(AN22/AN$8,0) -> 0 | AQ22: =IFERROR(AN22/AN$7,0) -> 0
C23: Food & Beverage Expense | D23: =IFERROR(INDEX(Tape!$T$7:$ME$36,MATCH($C$3,Tape!$C$7:$C$36,0),MATCH($C23&"+"&D$5,Tape!$T$1:$ME$1,0)),0) -> 0 | E23: =IFERROR(D23/D15,"-") -> - | F23: =IFERROR(D23/D$8,0) -> 0 | G23: =IFERROR(D23/D$7,0) -> 0 | H23: =IFERROR(INDEX(Tape!$T$7:$ME$36,MATCH($C$3,Tape!$C$7:$C$36,0),MATCH($C23&"+"&H$5,Tape!$T$1:$ME$1,0)),0) -> 0 | I23: =IFERROR(H23/H15,"-") -> - | J23: =IFERROR(H23/H$8,0) -> 0 | K23: =IFERROR(H23/H$7,0) -> 0 | L23: =IFERROR(INDEX(Tape!$T$7:$ME$36,MATCH($C$3,Tape!$C$7:$C$36,0),MATCH($C23&"+"&L$5,Tape!$T$1:$ME$1,0)),0) -> 0 | M23: =IFERROR(L23/L15,"-") -> - | N23: =IFERROR(L23/L$8,0) -> 0 | O23: =IFERROR(L23/L$7,0) -> 0 | P23: =IFERROR(INDEX(Tape!$T$7:$ME$36,MATCH($C$3,Tape!$C$7:$C$36,0),MATCH($C23&"+"&P$5,Tape!$T$1:$ME$1,0)),0) -> 0 | Q23: =IFERROR(P23/P15,"-") -> - | R23: =IFERROR(P23/P$8,0) -> 0 | S23: =IFERROR(P23/P$7,0) -> 0 | T23: =IFERROR(INDEX(Tape!$T$7:$ME$36,MATCH($C$3,Tape!$C$7:$C$36,0),MATCH($C23&"+"&T$5,Tape!$T$1:$ME$1,0)),0) -> 0 | U23: =IFERROR(T23/T15,"-") -> - | V23: =IFERROR(T23/T$8,0) -> 0 | W23: =IFERROR(T23/T$7,0) -> 0 | X23: =IFERROR(INDEX(Tape!$T$7:$ME$36,MATCH($C$3,Tape!$C$7:$C$36,0),MATCH($C23&"+"&X$5,Tape!$T$1:$ME$1,0)),0) -> 0 | Y23: =IFERROR(X23/X15,"-") -> - | Z23: =IFERROR(X23/X$8,0) -> 0 | AA23: =IFERROR(X23/X$7,0) -> 0 | AB23: =IFERROR(INDEX(Tape!$T$7:$ME$36,MATCH($C$3,Tape!$C$7:$C$36,0),MATCH($C23&"+"&AB$5,Tape!$T$1:$ME$1,0)),0) -> 0 | AC23: =IFERROR(AB23/AB15,"-") -> - | AD23: =IFERROR(AB23/AB$8,0) -> 0 | AE23: =IFERROR(AB23/AB$7,0) -> 0 | AF23: =IFERROR(INDEX(Tape!$T$7:$ME$36,MATCH($C$3,Tape!$C$7:$C$36,0),MATCH($C23&"+"&AF$5,Tape!$T$1:$ME$1,0)),0) -> 0 | AG23: =IFERROR(AF23/AF15,"-") -> - | AH23: =IFERROR(AF23/AF$8,0) -> 0 | AI23: =IFERROR(AF23/AF$7,0) -> 0 | AJ23: =IFERROR(INDEX(Tape!$T$7:$ME$36,MATCH($C$3,Tape!$C$7:$C$36,0),MATCH($C23&"+"&AJ$5,Tape!$T$1:$ME$1,0)),0) -> 0 | AK23: =IFERROR(AJ23/AJ15,"-") -> - | AL23: =IFERROR(AJ23/AJ$8,0) -> 0 | AM23: =IFERROR(AJ23/AJ$7,0) -> 0 | AN23: =IFERROR(AO23*AN15,"-") -> - | AO23: =IFERROR(AC23,"-") -> - | AP23: =IFERROR(AN23/AN$8,"-") -> - | AQ23: =IFERROR(AN23/AN$7,"-") -> -
C24: Other Departmental Expense | D24: =IFERROR(INDEX(Tape!$T$7:$ME$36,MATCH($C$3,Tape!$C$7:$C$36,0),MATCH($C24&"+"&D$5,Tape!$T$1:$ME$1,0)),0) -> 0 | E24: =IFERROR(D24/D16,0) -> 0 | F24: =IFERROR(D24/D$8,0) -> 0 | G24: =IFERROR(D24/D$7,0) -> 0 | H24: =IFERROR(INDEX(Tape!$T$7:$ME$36,MATCH($C$3,Tape!$C$7:$C$36,0),MATCH($C24&"+"&H$5,Tape!$T$1:$ME$1,0)),0) -> 0 | I24: =IFERROR(H24/H16,0) -> 0 | J24: =IFERROR(H24/H$8,0) -> 0 | K24: =IFERROR(H24/H$7,0) -> 0 | L24: =IFERROR(INDEX(Tape!$T$7:$ME$36,MATCH($C$3,Tape!$C$7:$C$36,0),MATCH($C24&"+"&L$5,Tape!$T$1:$ME$1,0)),0) -> 0 | M24: =IFERROR(L24/L16,0) -> 0 | N24: =IFERROR(L24/L$8,0) -> 0 | O24: =IFERROR(L24/L$7,0) -> 0 | P24: =IFERROR(INDEX(Tape!$T$7:$ME$36,MATCH($C$3,Tape!$C$7:$C$36,0),MATCH($C24&"+"&P$5,Tape!$T$1:$ME$1,0)),0) -> 0 | Q24: =IFERROR(P24/P16,0) -> 0 | R24: =IFERROR(P24/P$8,0) -> 0 | S24: =IFERROR(P24/P$7,0) -> 0 | T24: =IFERROR(INDEX(Tape!$T$7:$ME$36,MATCH($C$3,Tape!$C$7:$C$36,0),MATCH($C24&"+"&T$5,Tape!$T$1:$ME$1,0)),0) -> 0 | U24: =IFERROR(T24/T16,0) -> 0 | V24: =IFERROR(T24/T$8,0) -> 0 | W24: =IFERROR(T24/T$7,0) -> 0 | X24: =IFERROR(INDEX(Tape!$T$7:$ME$36,MATCH($C$3,Tape!$C$7:$C$36,0),MATCH($C24&"+"&X$5,Tape!$T$1:$ME$1,0)),0) -> 0 | Y24: =IFERROR(X24/X16,0) -> 0 | Z24: =IFERROR(X24/X$8,0) -> 0 | AA24: =IFERROR(X24/X$7,0) -> 0 | AB24: =IFERROR(INDEX(Tape!$T$7:$ME$36,MATCH($C$3,Tape!$C$7:$C$36,0),MATCH($C24&"+"&AB$5,Tape!$T$1:$ME$1,0)),0) -> 0 | AC24: =IFERROR(AB24/AB16,0) -> 0 | AD24: =IFERROR(AB24/AB$8,0) -> 0 | AE24: =IFERROR(AB24/AB$7,0) -> 0 | AF24: =IFERROR(INDEX(Tape!$T$7:$ME$36,MATCH($C$3,Tape!$C$7:$C$36,0),MATCH($C24&"+"&AF$5,Tape!$T$1:$ME$1,0)),0) -> 0 | AG24: =IFERROR(AF24/AF16,0) -> 0 | AH24: =IFERROR(AF24/AF$8,0) -> 0 | AI24: =IFERROR(AF24/AF$7,0) -> 0 | AJ24: =IFERROR(INDEX(Tape!$T$7:$ME$36,MATCH($C$3,Tape!$C$7:$C$36,0),MATCH($C24&"+"&AJ$5,Tape!$T$1:$ME$1,0)),0) -> 0 | AK24: =IFERROR(AJ24/AJ16,0) -> 0 | AL24: =IFERROR(AJ24/AJ$8,0) -> 0 | AM24: =IFERROR(AJ24/AJ$7,0) -> 0 | AN24: =AO24*AN16 -> 0 | AO24: =AC24 -> 0 | AP24: =IFERROR(AN24/AN$8,0) -> 0 | AQ24: =IFERROR(AN24/AN$7,0) -> 0
C25: TOTAL DEPARTMENTAL EXPENSES | D25: =SUM(D22:D24) -> 0 | E25: =IFERROR(D25/D$19,0) -> 0 | F25: =IFERROR(D25/D$8,0) -> 0 | G25: =IFERROR(D25/D$7,0) -> 0 | H25: =SUM(H22:H24) -> 0 | I25: =IFERROR(H25/H$19,0) -> 0 | J25: =IFERROR(H25/H$8,0) -> 0 | K25: =IFERROR(H25/H$7,0) -> 0 | L25: =SUM(L22:L24) -> 0 | M25: =IFERROR(L25/L$19,0) -> 0 | N25: =IFERROR(L25/L$8,0) -> 0 | O25: =IFERROR(L25/L$7,0) -> 0 | P25: =SUM(P22:P24) -> 0 | Q25: =IFERROR(P25/P$19,0) -> 0 | R25: =IFERROR(P25/P$8,0) -> 0 | S25: =IFERROR(P25/P$7,0) -> 0 | T25: =SUM(T22:T24) -> 0 | U25: =IFERROR(T25/T$19,0) -> 0 | V25: =IFERROR(T25/T$8,0) -> 0 | W25: =IFERROR(T25/T$7,0) -> 0 | X25: =SUM(X22:X24) -> 0 | Y25: =IFERROR(X25/X$19,0) -> 0 | Z25: =IFERROR(X25/X$8,0) -> 0 | AA25: =IFERROR(X25/X$7,0) -> 0 | AB25: =SUM(AB22:AB24) -> 0 | AC25: =IFERROR(AB25/AB$19,0) -> 0 | AD25: =IFERROR(AB25/AB$8,0) -> 0 | AE25: =IFERROR(AB25/AB$7,0) -> 0 | AF25: =SUM(AF22:AF24) -> 0 | AG25: =IFERROR(AF25/AF$19,0) -> 0 | AH25: =IFERROR(AF25/AF$8,0) -> 0 | AI25: =IFERROR(AF25/AF$7,0) -> 0 | AJ25: =SUM(AJ22:AJ24) -> 0 | AK25: =IFERROR(AJ25/AJ$19,0) -> 0 | AL25: =IFERROR(AJ25/AJ$8,0) -> 0 | AM25: =IFERROR(AJ25/AJ$7,0) -> 0 | AN25: =SUM(AN22:AN24) -> 0 | AO25: =IFERROR(AN25/AN$19,0) -> 0 | AP25: =IFERROR(AN25/AN$8,0) -> 0 | AQ25: =IFERROR(AN25/AN$7,0) -> 0
C27: GROSS OPERATING INCOME | D27: =D19-D25 -> 0 | E27: =IFERROR(D27/D$19,0) -> 0 | F27: =IFERROR(D27/D$8,0) -> 0 | G27: =IFERROR(D27/D$7,0) -> 0 | H27: =H19-H25 -> 0 | I27: =IFERROR(H27/H$19,0) -> 0 | J27: =IFERROR(H27/H$8,0) -> 0 | K27: =IFERROR(H27/H$7,0) -> 0 | L27: =L19-L25 -> 0 | M27: =IFERROR(L27/L$19,0) -> 0 | N27: =IFERROR(L27/L$8,0) -> 0 | O27: =IFERROR(L27/L$7,0) -> 0 | P27: =P19-P25 -> 0 | Q27: =IFERROR(P27/P$19,0) -> 0 | R27: =IFERROR(P27/P$8,0) -> 0 | S27: =IFERROR(P27/P$7,0) -> 0 | T27: =T19-T25 -> 0 | U27: =IFERROR(T27/T$19,0) -> 0 | V27: =IFERROR(T27/T$8,0) -> 0 | W27: =IFERROR(T27/T$7,0) -> 0 | X27: =X19-X25 -> 0 | Y27: =IFERROR(X27/X$19,0) -> 0 | Z27: =IFERROR(X27/X$8,0) -> 0 | AA27: =IFERROR(X27/X$7,0) -> 0 | AB27: =AB19-AB25 -> 0 | AC27: =IFERROR(AB27/AB$19,0) -> 0 | AD27: =IFERROR(AB27/AB$8,0) -> 0 | AE27: =IFERROR(AB27/AB$7,0) -> 0 | AF27: =AF19-AF25 -> 0 | AG27: =IFERROR(AF27/AF$19,0) -> 0 | AH27: =IFERROR(AF27/AF$8,0) -> 0 | AI27: =IFERROR(AF27/AF$7,0) -> 0 | AJ27: =AJ19-AJ25 -> 0 | AK27: =IFERROR(AJ27/AJ$19,0) -> 0 | AL27: =IFERROR(AJ27/AJ$8,0) -> 0 | AM27: =IFERROR(AJ27/AJ$7,0) -> 0 | AN27: =AN19-AN25 -> 0 | AO27: =IFERROR(AN27/AN$19,0) -> 0 | AP27: =IFERROR(AN27/AN$8,0) -> 0 | AQ27: =IFERROR(AN27/AN$7,0) -> 0
C29: UNDISTRIBUTED EXPENSES
C30: General and Administrative | D30: =IFERROR(INDEX(Tape!$T$7:$ME$36,MATCH($C$3,Tape!$C$7:$C$36,0),MATCH($C30&"+"&D$5,Tape!$T$1:$ME$1,0)),0) -> 0 | E30: =IFERROR(D30/D$19,0) -> 0 | F30: =IFERROR(D30/D$8,0) -> 0 | G30: =IFERROR(D30/D$7,0) -> 0 | H30: =IFERROR(INDEX(Tape!$T$7:$ME$36,MATCH($C$3,Tape!$C$7:$C$36,0),MATCH($C30&"+"&H$5,Tape!$T$1:$ME$1,0)),0) -> 0 | I30: =IFERROR(H30/H$19,0) -> 0 | J30: =IFERROR(H30/H$8,0) -> 0 | K30: =IFERROR(H30/H$7,0) -> 0 | L30: =IFERROR(INDEX(Tape!$T$7:$ME$36,MATCH($C$3,Tape!$C$7:$C$36,0),MATCH($C30&"+"&L$5,Tape!$T$1:$ME$1,0)),0) -> 0 | M30: =IFERROR(L30/L$19,0) -> 0 | N30: =IFERROR(L30/L$8,0) -> 0 | O30: =IFERROR(L30/L$7,0) -> 0 | P30: =IFERROR(INDEX(Tape!$T$7:$ME$36,MATCH($C$3,Tape!$C$7:$C$36,0),MATCH($C30&"+"&P$5,Tape!$T$1:$ME$1,0)),0) -> 0 | Q30: =IFERROR(P30/P$19,0) -> 0 | R30: =IFERROR(P30/P$8,0) -> 0 | S30: =IFERROR(P30/P$7,0) -> 0 | T30: =IFERROR(INDEX(Tape!$T$7:$ME$36,MATCH($C$3,Tape!$C$7:$C$36,0),MATCH($C30&"+"&T$5,Tape!$T$1:$ME$1,0)),0) -> 0 | U30: =IFERROR(T30/T$19,0) -> 0 | V30: =IFERROR(T30/T$8,0) -> 0 | W30: =IFERROR(T30/T$7,0) -> 0 | X30: =IFERROR(INDEX(Tape!$T$7:$ME$36,MATCH($C$3,Tape!$C$7:$C$36,0),MATCH($C30&"+"&X$5,Tape!$T$1:$ME$1,0)),0) -> 0 | Y30: =IFERROR(X30/X$19,0) -> 0 | Z30: =IFERROR(X30/X$8,0) -> 0 | AA30: =IFERROR(X30/X$7,0) -> 0 | AB30: =IFERROR(INDEX(Tape!$T$7:$ME$36,MATCH($C$3,Tape!$C$7:$C$36,0),MATCH($C30&"+"&AB$5,Tape!$T$1:$ME$1,0)),0) -> 0 | AC30: =IFERROR(AB30/AB$19,0) -> 0 | AD30: =IFERROR(AB30/AB$8,0) -> 0 | AE30: =IFERROR(AB30/AB$7,0) -> 0 | AF30: =IFERROR(INDEX(Tape!$T$7:$ME$36,MATCH($C$3,Tape!$C$7:$C$36,0),MATCH($C30&"+"&AF$5,Tape!$T$1:$ME$1,0)),0) -> 0 | AG30: =IFERROR(AF30/AF$19,0) -> 0 | AH30: =IFERROR(AF30/AF$8,0) -> 0 | AI30: =IFERROR(AF30/AF$7,0) -> 0 | AJ30: =IFERROR(INDEX(Tape!$T$7:$ME$36,MATCH($C$3,Tape!$C$7:$C$36,0),MATCH($C30&"+"&AJ$5,Tape!$T$1:$ME$1,0)),0) -> 0 | AK30: =IFERROR(AJ30/AJ$19,0) -> 0 | AL30: =IFERROR(AJ30/AJ$8,0) -> 0 | AM30: =IFERROR(AJ30/AJ$7,0) -> 0 | AN30: =AQ30*AN$7 -> 0 | AO30: =IFERROR(AN30/AN$19,0) -> 0 | AP30: =IFERROR(AN30/AN$8,0) -> 0 | AQ30: =AE30 -> 0
C31: Credit Card Commissions | D31: =IFERROR(INDEX(Tape!$T$7:$ME$36,MATCH($C$3,Tape!$C$7:$C$36,0),MATCH($C31&"+"&D$5,Tape!$T$1:$ME$1,0)),0) -> 0 | E31: =IFERROR(D31/D$19,0) -> 0 | F31: =IFERROR(D31/D$8,0) -> 0 | G31: =IFERROR(D31/D$7,0) -> 0 | H31: =IFERROR(INDEX(Tape!$T$7:$ME$36,MATCH($C$3,Tape!$C$7:$C$36,0),MATCH($C31&"+"&H$5,Tape!$T$1:$ME$1,0)),0) -> 0 | I31: =IFERROR(H31/H$19,0) -> 0 | J31: =IFERROR(H31/H$8,0) -> 0 | K31: =IFERROR(H31/H$7,0) -> 0 | L31: =IFERROR(INDEX(Tape!$T$7:$ME$36,MATCH($C$3,Tape!$C$7:$C$36,0),MATCH($C31&"+"&L$5,Tape!$T$1:$ME$1,0)),0) -> 0 | M31: =IFERROR(L31/L$19,0) -> 0 | N31: =IFERROR(L31/L$8,0) -> 0 | O31: =IFERROR(L31/L$7,0) -> 0 | P31: =IFERROR(INDEX(Tape!$T$7:$ME$36,MATCH($C$3,Tape!$C$7:$C$36,0),MATCH($C31&"+"&P$5,Tape!$T$1:$ME$1,0)),0) -> 0 | Q31: =IFERROR(P31/P$19,0) -> 0 | R31: =IFERROR(P31/P$8,0) -> 0 | S31: =IFERROR(P31/P$7,0) -> 0 | T31: =IFERROR(INDEX(Tape!$T$7:$ME$36,MATCH($C$3,Tape!$C$7:$C$36,0),MATCH($C31&"+"&T$5,Tape!$T$1:$ME$1,0)),0) -> 0 | U31: =IFERROR(T31/T$19,0) -> 0 | V31: =IFERROR(T31/T$8,0) -> 0 | W31: =IFERROR(T31/T$7,0) -> 0 | X31: =IFERROR(INDEX(Tape!$T$7:$ME$36,MATCH($C$3,Tape!$C$7:$C$36,0),MATCH($C31&"+"&X$5,Tape!$T$1:$ME$1,0)),0) -> 0 | Y31: =IFERROR(X31/X$19,0) -> 0 | Z31: =IFERROR(X31/X$8,0) -> 0 | AA31: =IFERROR(X31/X$7,0) -> 0 | AB31: =IFERROR(INDEX(Tape!$T$7:$ME$36,MATCH($C$3,Tape!$C$7:$C$36,0),MATCH($C31&"+"&AB$5,Tape!$T$1:$ME$1,0)),0) -> 0 | AC31: =IFERROR(AB31/AB$19,0) -> 0 | AD31: =IFERROR(AB31/AB$8,0) -> 0 | AE31: =IFERROR(AB31/AB$7,0) -> 0 | AF31: =IFERROR(INDEX(Tape!$T$7:$ME$36,MATCH($C$3,Tape!$C$7:$C$36,0),MATCH($C31&"+"&AF$5,Tape!$T$1:$ME$1,0)),0) -> 0 | AG31: =IFERROR(AF31/AF$19,0) -> 0 | AH31: =IFERROR(AF31/AF$8,0) -> 0 | AI31: =IFERROR(AF31/AF$7,0) -> 0 | AJ31: =IFERROR(INDEX(Tape!$T$7:$ME$36,MATCH($C$3,Tape!$C$7:$C$36,0),MATCH($C31&"+"&AJ$5,Tape!$T$1:$ME$1,0)),0) -> 0 | AK31: =IFERROR(AJ31/AJ$19,0) -> 0 | AL31: =IFERROR(AJ31/AJ$8,0) -> 0 | AM31: =IFERROR(AJ31/AJ$7,0) -> 0 | AN31: =AP31*AN$8 -> 0 | AO31: =IFERROR(AN31/AN$19,0) -> 0 | AP31: =AD31 -> 0 | AQ31: =IFERROR(AN31/AN$7,0) -> 0
C32: Information & Telecommunication | D32: =IFERROR(INDEX(Tape!$T$7:$ME$36,MATCH($C$3,Tape!$C$7:$C$36,0),MATCH($C32&"+"&D$5,Tape!$T$1:$ME$1,0)),0) -> 0 | E32: =IFERROR(D32/D$19,0) -> 0 | F32: =IFERROR(D32/D$8,0) -> 0 | G32: =IFERROR(D32/D$7,0) -> 0 | H32: =IFERROR(INDEX(Tape!$T$7:$ME$36,MATCH($C$3,Tape!$C$7:$C$36,0),MATCH($C32&"+"&H$5,Tape!$T$1:$ME$1,0)),0) -> 0 | I32: =IFERROR(H32/H$19,0) -> 0 | J32: =IFERROR(H32/H$8,0) -> 0 | K32: =IFERROR(H32/H$7,0) -> 0 | L32: =IFERROR(INDEX(Tape!$T$7:$ME$36,MATCH($C$3,Tape!$C$7:$C$36,0),MATCH($C32&"+"&L$5,Tape!$T$1:$ME$1,0)),0) -> 0 | M32: =IFERROR(L32/L$19,0) -> 0 | N32: =IFERROR(L32/L$8,0) -> 0 | O32: =IFERROR(L32/L$7,0) -> 0 | P32: =IFERROR(INDEX(Tape!$T$7:$ME$36,MATCH($C$3,Tape!$C$7:$C$36,0),MATCH($C32&"+"&P$5,Tape!$T$1:$ME$1,0)),0) -> 0 | Q32: =IFERROR(P32/P$19,0) -> 0 | R32: =IFERROR(P32/P$8,0) -> 0 | S32: =IFERROR(P32/P$7,0) -> 0 | T32: =IFERROR(INDEX(Tape!$T$7:$ME$36,MATCH($C$3,Tape!$C$7:$C$36,0),MATCH($C32&"+"&T$5,Tape!$T$1:$ME$1,0)),0) -> 0 | U32: =IFERROR(T32/T$19,0) -> 0 | V32: =IFERROR(T32/T$8,0) -> 0 | W32: =IFERROR(T32/T$7,0) -> 0 | X32: =IFERROR(INDEX(Tape!$T$7:$ME$36,MATCH($C$3,Tape!$C$7:$C$36,0),MATCH($C32&"+"&X$5,Tape!$T$1:$ME$1,0)),0) -> 0 | Y32: =IFERROR(X32/X$19,0) -> 0 | Z32: =IFERROR(X32/X$8,0) -> 0 | AA32: =IFERROR(X32/X$7,0) -> 0 | AB32: =IFERROR(INDEX(Tape!$T$7:$ME$36,MATCH($C$3,Tape!$C$7:$C$36,0),MATCH($C32&"+"&AB$5,Tape!$T$1:$ME$1,0)),0) -> 0 | AC32: =IFERROR(AB32/AB$19,0) -> 0 | AD32: =IFERROR(AB32/AB$8,0) -> 0 | AE32: =IFERROR(AB32/AB$7,0) -> 0 | AF32: =IFERROR(INDEX(Tape!$T$7:$ME$36,MATCH($C$3,Tape!$C$7:$C$36,0),MATCH($C32&"+"&AF$5,Tape!$T$1:$ME$1,0)),0) -> 0 | AG32: =IFERROR(AF32/AF$19,0) -> 0 | AH32: =IFERROR(AF32/AF$8,0) -> 0 | AI32: =IFERROR(AF32/AF$7,0) -> 0 | AJ32: =IFERROR(INDEX(Tape!$T$7:$ME$36,MATCH($C$3,Tape!$C$7:$C$36,0),MATCH($C32&"+"&AJ$5,Tape!$T$1:$ME$1,0)),0) -> 0 | AK32: =IFERROR(AJ32/AJ$19,0) -> 0 | AL32: =IFERROR(AJ32/AJ$8,0) -> 0 | AM32: =IFERROR(AJ32/AJ$7,0) -> 0 | AN32: =AQ32*AN$7 -> 0 | AO32: =IFERROR(AN32/AN$19,0) -> 0 | AP32: =IFERROR(AN32/AN$8,0) -> 0 | AQ32: =AE32 -> 0
C33: Sales & Marketing | D33: =IFERROR(INDEX(Tape!$T$7:$ME$36,MATCH($C$3,Tape!$C$7:$C$36,0),MATCH($C33&"+"&D$5,Tape!$T$1:$ME$1,0)),0) -> 0 | E33: =IFERROR(D33/D$19,0) -> 0 | F33: =IFERROR(D33/D$8,0) -> 0 | G33: =IFERROR(D33/D$7,0) -> 0 | H33: =IFERROR(INDEX(Tape!$T$7:$ME$36,MATCH($C$3,Tape!$C$7:$C$36,0),MATCH($C33&"+"&H$5,Tape!$T$1:$ME$1,0)),0) -> 0 | I33: =IFERROR(H33/H$19,0) -> 0 | J33: =IFERROR(H33/H$8,0) -> 0 | K33: =IFERROR(H33/H$7,0) -> 0 | L33: =IFERROR(INDEX(Tape!$T$7:$ME$36,MATCH($C$3,Tape!$C$7:$C$36,0),MATCH($C33&"+"&L$5,Tape!$T$1:$ME$1,0)),0) -> 0 | M33: =IFERROR(L33/L$19,0) -> 0 | N33: =IFERROR(L33/L$8,0) -> 0 | O33: =IFERROR(L33/L$7,0) -> 0 | P33: =IFERROR(INDEX(Tape!$T$7:$ME$36,MATCH($C$3,Tape!$C$7:$C$36,0),MATCH($C33&"+"&P$5,Tape!$T$1:$ME$1,0)),0) -> 0 | Q33: =IFERROR(P33/P$19,0) -> 0 | R33: =IFERROR(P33/P$8,0) -> 0 | S33: =IFERROR(P33/P$7,0) -> 0 | T33: =IFERROR(INDEX(Tape!$T$7:$ME$36,MATCH($C$3,Tape!$C$7:$C$36,0),MATCH($C33&"+"&T$5,Tape!$T$1:$ME$1,0)),0) -> 0 | U33: =IFERROR(T33/T$19,0) -> 0 | V33: =IFERROR(T33/T$8,0) -> 0 | W33: =IFERROR(T33/T$7,0) -> 0 | X33: =IFERROR(INDEX(Tape!$T$7:$ME$36,MATCH($C$3,Tape!$C$7:$C$36,0),MATCH($C33&"+"&X$5,Tape!$T$1:$ME$1,0)),0) -> 0 | Y33: =IFERROR(X33/X$19,0) -> 0 | Z33: =IFERROR(X33/X$8,0) -> 0 | AA33: =IFERROR(X33/X$7,0) -> 0 | AB33: =IFERROR(INDEX(Tape!$T$7:$ME$36,MATCH($C$3,Tape!$C$7:$C$36,0),MATCH($C33&"+"&AB$5,Tape!$T$1:$ME$1,0)),0) -> 0 | AC33: =IFERROR(AB33/AB$19,0) -> 0 | AD33: =IFERROR(AB33/AB$8,0) -> 0 | AE33: =IFERROR(AB33/AB$7,0) -> 0 | AF33: =IFERROR(INDEX(Tape!$T$7:$ME$36,MATCH($C$3,Tape!$C$7:$C$36,0),MATCH($C33&"+"&AF$5,Tape!$T$1:$ME$1,0)),0) -> 0 | AG33: =IFERROR(AF33/AF$19,0) -> 0 | AH33: =IFERROR(AF33/AF$8,0) -> 0 | AI33: =IFERROR(AF33/AF$7,0) -> 0 | AJ33: =IFERROR(INDEX(Tape!$T$7:$ME$36,MATCH($C$3,Tape!$C$7:$C$36,0),MATCH($C33&"+"&AJ$5,Tape!$T$1:$ME$1,0)),0) -> 0 | AK33: =IFERROR(AJ33/AJ$19,0) -> 0 | AL33: =IFERROR(AJ33/AJ$8,0) -> 0 | AM33: =IFERROR(AJ33/AJ$7,0) -> 0 | AN33: =AQ33*AN$7 -> 0 | AO33: =IFERROR(AN33/AN$19,0) -> 0 | AP33: =IFERROR(AN33/AN$8,0) -> 0 | AQ33: =AE33 -> 0
C34: Franchise Fees | D34: =IFERROR(INDEX(Tape!$T$7:$ME$36,MATCH($C$3,Tape!$C$7:$C$36,0),MATCH($C34&"+"&D$5,Tape!$T$1:$ME$1,0)),0) -> 0 | E34: =IFERROR(D34/D$19,0) -> 0 | F34: =IFERROR(D34/D$8,0) -> 0 | G34: =IFERROR(D34/D$7,0) -> 0 | H34: =IFERROR(INDEX(Tape!$T$7:$ME$36,MATCH($C$3,Tape!$C$7:$C$36,0),MATCH($C34&"+"&H$5,Tape!$T$1:$ME$1,0)),0) -> 0 | I34: =IFERROR(H34/H$19,0) -> 0 | J34: =IFERROR(H34/H$8,0) -> 0 | K34: =IFERROR(H34/H$7,0) -> 0 | L34: =IFERROR(INDEX(Tape!$T$7:$ME$36,MATCH($C$3,Tape!$C$7:$C$36,0),MATCH($C34&"+"&L$5,Tape!$T$1:$ME$1,0)),0) -> 0 | M34: =IFERROR(L34/L$19,0) -> 0 | N34: =IFERROR(L34/L$8,0) -> 0 | O34: =IFERROR(L34/L$7,0) -> 0 | P34: =IFERROR(INDEX(Tape!$T$7:$ME$36,MATCH($C$3,Tape!$C$7:$C$36,0),MATCH($C34&"+"&P$5,Tape!$T$1:$ME$1,0)),0) -> 0 | Q34: =IFERROR(P34/P$19,0) -> 0 | R34: =IFERROR(P34/P$8,0) -> 0 | S34: =IFERROR(P34/P$7,0) -> 0 | T34: =IFERROR(INDEX(Tape!$T$7:$ME$36,MATCH($C$3,Tape!$C$7:$C$36,0),MATCH($C34&"+"&T$5,Tape!$T$1:$ME$1,0)),0) -> 0 | U34: =IFERROR(T34/T$19,0) -> 0 | V34: =IFERROR(T34/T$8,0) -> 0 | W34: =IFERROR(T34/T$7,0) -> 0 | X34: =IFERROR(INDEX(Tape!$T$7:$ME$36,MATCH($C$3,Tape!$C$7:$C$36,0),MATCH($C34&"+"&X$5,Tape!$T$1:$ME$1,0)),0) -> 0 | Y34: =IFERROR(X34/X$19,0) -> 0 | Z34: =IFERROR(X34/X$8,0) -> 0 | AA34: =IFERROR(X34/X$7,0) -> 0 | AB34: =IFERROR(INDEX(Tape!$T$7:$ME$36,MATCH($C$3,Tape!$C$7:$C$36,0),MATCH($C34&"+"&AB$5,Tape!$T$1:$ME$1,0)),0) -> 0 | AC34: =IFERROR(AB34/AB$19,0) -> 0 | AD34: =IFERROR(AB34/AB$8,0) -> 0 | AE34: =IFERROR(AB34/AB$7,0) -> 0 | AF34: =IFERROR(INDEX(Tape!$T$7:$ME$36,MATCH($C$3,Tape!$C$7:$C$36,0),MATCH($C34&"+"&AF$5,Tape!$T$1:$ME$1,0)),0) -> 0 | AG34: =IFERROR(AF34/AF$19,0) -> 0 | AH34: =IFERROR(AF34/AF$8,0) -> 0 | AI34: =IFERROR(AF34/AF$7,0) -> 0 | AJ34: =IFERROR(INDEX(Tape!$T$7:$ME$36,MATCH($C$3,Tape!$C$7:$C$36,0),MATCH($C34&"+"&AJ$5,Tape!$T$1:$ME$1,0)),0) -> 0 | AK34: =IFERROR(AJ34/AJ$19,0) -> 0 | AL34: =IFERROR(AJ34/AJ$8,0) -> 0 | AM34: =IFERROR(AJ34/AJ$7,0) -> 0 | AN34: =AO34*AN19 -> 0 | AO34: =IFERROR(MAX(AC34, VLOOKUP($C$3, 'UW Drivers'!$D$9:$AH$38, 31,FALSE())),0) -> 0 | AP34: =IFERROR(AN34/AN$8,0) -> 0 | AQ34: =IFERROR(AN34/AN$7,0) -> 0
C35: Property Ops./R&M | D35: =IFERROR(INDEX(Tape!$T$7:$ME$36,MATCH($C$3,Tape!$C$7:$C$36,0),MATCH($C35&"+"&D$5,Tape!$T$1:$ME$1,0)),0) -> 0 | E35: =IFERROR(D35/D$19,0) -> 0 | F35: =IFERROR(D35/D$8,0) -> 0 | G35: =IFERROR(D35/D$7,0) -> 0 | H35: =IFERROR(INDEX(Tape!$T$7:$ME$36,MATCH($C$3,Tape!$C$7:$C$36,0),MATCH($C35&"+"&H$5,Tape!$T$1:$ME$1,0)),0) -> 0 | I35: =IFERROR(H35/H$19,0) -> 0 | J35: =IFERROR(H35/H$8,0) -> 0 | K35: =IFERROR(H35/H$7,0) -> 0 | L35: =IFERROR(INDEX(Tape!$T$7:$ME$36,MATCH($C$3,Tape!$C$7:$C$36,0),MATCH($C35&"+"&L$5,Tape!$T$1:$ME$1,0)),0) -> 0 | M35: =IFERROR(L35/L$19,0) -> 0 | N35: =IFERROR(L35/L$8,0) -> 0 | O35: =IFERROR(L35/L$7,0) -> 0 | P35: =IFERROR(INDEX(Tape!$T$7:$ME$36,MATCH($C$3,Tape!$C$7:$C$36,0),MATCH($C35&"+"&P$5,Tape!$T$1:$ME$1,0)),0) -> 0 | Q35: =IFERROR(P35/P$19,0) -> 0 | R35: =IFERROR(P35/P$8,0) -> 0 | S35: =IFERROR(P35/P$7,0) -> 0 | T35: =IFERROR(INDEX(Tape!$T$7:$ME$36,MATCH($C$3,Tape!$C$7:$C$36,0),MATCH($C35&"+"&T$5,Tape!$T$1:$ME$1,0)),0) -> 0 | U35: =IFERROR(T35/T$19,0) -> 0 | V35: =IFERROR(T35/T$8,0) -> 0 | W35: =IFERROR(T35/T$7,0) -> 0 | X35: =IFERROR(INDEX(Tape!$T$7:$ME$36,MATCH($C$3,Tape!$C$7:$C$36,0),MATCH($C35&"+"&X$5,Tape!$T$1:$ME$1,0)),0) -> 0 | Y35: =IFERROR(X35/X$19,0) -> 0 | Z35: =IFERROR(X35/X$8,0) -> 0 | AA35: =IFERROR(X35/X$7,0) -> 0 | AB35: =IFERROR(INDEX(Tape!$T$7:$ME$36,MATCH($C$3,Tape!$C$7:$C$36,0),MATCH($C35&"+"&AB$5,Tape!$T$1:$ME$1,0)),0) -> 0 | AC35: =IFERROR(AB35/AB$19,0) -> 0 | AD35: =IFERROR(AB35/AB$8,0) -> 0 | AE35: =IFERROR(AB35/AB$7,0) -> 0 | AF35: =IFERROR(INDEX(Tape!$T$7:$ME$36,MATCH($C$3,Tape!$C$7:$C$36,0),MATCH($C35&"+"&AF$5,Tape!$T$1:$ME$1,0)),0) -> 0 | AG35: =IFERROR(AF35/AF$19,0) -> 0 | AH35: =IFERROR(AF35/AF$8,0) -> 0 | AI35: =IFERROR(AF35/AF$7,0) -> 0 | AJ35: =IFERROR(INDEX(Tape!$T$7:$ME$36,MATCH($C$3,Tape!$C$7:$C$36,0),MATCH($C35&"+"&AJ$5,Tape!$T$1:$ME$1,0)),0) -> 0 | AK35: =IFERROR(AJ35/AJ$19,0) -> 0 | AL35: =IFERROR(AJ35/AJ$8,0) -> 0 | AM35: =IFERROR(AJ35/AJ$7,0) -> 0 | AN35: =AP35*AN$8 -> 0 | AO35: =IFERROR(AN35/AN$19,0) -> 0 | AP35: =AD35 -> 0 | AQ35: =IFERROR(AN35/AN$7,0) -> 0
C36: Utilities | D36: =IFERROR(INDEX(Tape!$T$7:$ME$36,MATCH($C$3,Tape!$C$7:$C$36,0),MATCH($C36&"+"&D$5,Tape!$T$1:$ME$1,0)),0) -> 0 | E36: =IFERROR(D36/D$19,0) -> 0 | F36: =IFERROR(D36/D$8,0) -> 0 | G36: =IFERROR(D36/D$7,0) -> 0 | H36: =IFERROR(INDEX(Tape!$T$7:$ME$36,MATCH($C$3,Tape!$C$7:$C$36,0),MATCH($C36&"+"&H$5,Tape!$T$1:$ME$1,0)),0) -> 0 | I36: =IFERROR(H36/H$19,0) -> 0 | J36: =IFERROR(H36/H$8,0) -> 0 | K36: =IFERROR(H36/H$7,0) -> 0 | L36: =IFERROR(INDEX(Tape!$T$7:$ME$36,MATCH($C$3,Tape!$C$7:$C$36,0),MATCH($C36&"+"&L$5,Tape!$T$1:$ME$1,0)),0) -> 0 | M36: =IFERROR(L36/L$19,0) -> 0 | N36: =IFERROR(L36/L$8,0) -> 0 | O36: =IFERROR(L36/L$7,0) -> 0 | P36: =IFERROR(INDEX(Tape!$T$7:$ME$36,MATCH($C$3,Tape!$C$7:$C$36,0),MATCH($C36&"+"&P$5,Tape!$T$1:$ME$1,0)),0) -> 0 | Q36: =IFERROR(P36/P$19,0) -> 0 | R36: =IFERROR(P36/P$8,0) -> 0 | S36: =IFERROR(P36/P$7,0) -> 0 | T36: =IFERROR(INDEX(Tape!$T$7:$ME$36,MATCH($C$3,Tape!$C$7:$C$36,0),MATCH($C36&"+"&T$5,Tape!$T$1:$ME$1,0)),0) -> 0 | U36: =IFERROR(T36/T$19,0) -> 0 | V36: =IFERROR(T36/T$8,0) -> 0 | W36: =IFERROR(T36/T$7,0) -> 0 | X36: =IFERROR(INDEX(Tape!$T$7:$ME$36,MATCH($C$3,Tape!$C$7:$C$36,0),MATCH($C36&"+"&X$5,Tape!$T$1:$ME$1,0)),0) -> 0 | Y36: =IFERROR(X36/X$19,0) -> 0 | Z36: =IFERROR(X36/X$8,0) -> 0 | AA36: =IFERROR(X36/X$7,0) -> 0 | AB36: =IFERROR(INDEX(Tape!$T$7:$ME$36,MATCH($C$3,Tape!$C$7:$C$36,0),MATCH($C36&"+"&AB$5,Tape!$T$1:$ME$1,0)),0) -> 0 | AC36: =IFERROR(AB36/AB$19,0) -> 0 | AD36: =IFERROR(AB36/AB$8,0) -> 0 | AE36: =IFERROR(AB36/AB$7,0) -> 0 | AF36: =IFERROR(INDEX(Tape!$T$7:$ME$36,MATCH($C$3,Tape!$C$7:$C$36,0),MATCH($C36&"+"&AF$5,Tape!$T$1:$ME$1,0)),0) -> 0 | AG36: =IFERROR(AF36/AF$19,0) -> 0 | AH36: =IFERROR(AF36/AF$8,0) -> 0 | AI36: =IFERROR(AF36/AF$7,0) -> 0 | AJ36: =IFERROR(INDEX(Tape!$T$7:$ME$36,MATCH($C$3,Tape!$C$7:$C$36,0),MATCH($C36&"+"&AJ$5,Tape!$T$1:$ME$1,0)),0) -> 0 | AK36: =IFERROR(AJ36/AJ$19,0) -> 0 | AL36: =IFERROR(AJ36/AJ$8,0) -> 0 | AM36: =IFERROR(AJ36/AJ$7,0) -> 0 | AN36: =AP36*AN$8 -> 0 | AO36: =IFERROR(AN36/AN$19,0) -> 0 | AP36: =AD36 -> 0 | AQ36: =IFERROR(AN36/AN$7,0) -> 0
C37: TOTAL UNDISTRIBUTED EXPENSES | D37: =SUM(D30:D36) -> 0 | E37: =IFERROR(D37/D$19,0) -> 0 | F37: =IFERROR(D37/D$8,0) -> 0 | G37: =IFERROR(D37/D$7,0) -> 0 | H37: =SUM(H30:H36) -> 0 | I37: =IFERROR(H37/H$19,0) -> 0 | J37: =IFERROR(H37/H$8,0) -> 0 | K37: =IFERROR(H37/H$7,0) -> 0 | L37: =SUM(L30:L36) -> 0 | M37: =IFERROR(L37/L$19,0) -> 0 | N37: =IFERROR(L37/L$8,0) -> 0 | O37: =IFERROR(L37/L$7,0) -> 0 | P37: =SUM(P30:P36) -> 0 | Q37: =IFERROR(P37/P$19,0) -> 0 | R37: =IFERROR(P37/P$8,0) -> 0 | S37: =IFERROR(P37/P$7,0) -> 0 | T37: =SUM(T30:T36) -> 0 | U37: =IFERROR(T37/T$19,0) -> 0 | V37: =IFERROR(T37/T$8,0) -> 0 | W37: =IFERROR(T37/T$7,0) -> 0 | X37: =SUM(X30:X36) -> 0 | Y37: =IFERROR(X37/X$19,0) -> 0 | Z37: =IFERROR(X37/X$8,0) -> 0 | AA37: =IFERROR(X37/X$7,0) -> 0 | AB37: =SUM(AB30:AB36) -> 0 | AC37: =IFERROR(AB37/AB$19,0) -> 0 | AD37: =IFERROR(AB37/AB$8,0) -> 0 | AE37: =IFERROR(AB37/AB$7,0) -> 0 | AF37: =SUM(AF30:AF36) -> 0 | AG37: =IFERROR(AF37/AF$19,0) -> 0 | AH37: =IFERROR(AF37/AF$8,0) -> 0 | AI37: =IFERROR(AF37/AF$7,0) -> 0 | AJ37: =SUM(AJ30:AJ36) -> 0 | AK37: =IFERROR(AJ37/AJ$19,0) -> 0 | AL37: =IFERROR(AJ37/AJ$8,0) -> 0 | AM37: =IFERROR(AJ37/AJ$7,0) -> 0 | AN37: =SUM(AN30:AN36) -> 0 | AO37: =IFERROR(AN37/AN$19,0) -> 0 | AP37: =IFERROR(AN37/AN$8,0) -> 0 | AQ37: =IFERROR(AN37/AN$7,0) -> 0
C39: GROSS OPERATING PROFIT | D39: =D27-D37 -> 0 | E39: =IFERROR(D39/D$19,0) -> 0 | F39: =IFERROR(D39/D$8,0) -> 0 | G39: =IFERROR(D39/D$7,0) -> 0 | H39: =H27-H37 -> 0 | I39: =IFERROR(H39/H$19,0) -> 0 | J39: =IFERROR(H39/H$8,0) -> 0 | K39: =IFERROR(H39/H$7,0) -> 0 | L39: =L27-L37 -> 0 | M39: =IFERROR(L39/L$19,0) -> 0 | N39: =IFERROR(L39/L$8,0) -> 0 | O39: =IFERROR(L39/L$7,0) -> 0 | P39: =P27-P37 -> 0 | Q39: =IFERROR(P39/P$19,0) -> 0 | R39: =IFERROR(P39/P$8,0) -> 0 | S39: =IFERROR(P39/P$7,0) -> 0 | T39: =T27-T37 -> 0 | U39: =IFERROR(T39/T$19,0) -> 0 | V39: =IFERROR(T39/T$8,0) -> 0 | W39: =IFERROR(T39/T$7,0) -> 0 | X39: =X27-X37 -> 0 | Y39: =IFERROR(X39/X$19,0) -> 0 | Z39: =IFERROR(X39/X$8,0) -> 0 | AA39: =IFERROR(X39/X$7,0) -> 0 | AB39: =AB27-AB37 -> 0 | AC39: =IFERROR(AB39/AB$19,0) -> 0 | AD39: =IFERROR(AB39/AB$8,0) -> 0 | AE39: =IFERROR(AB39/AB$7,0) -> 0 | AF39: =AF27-AF37 -> 0 | AG39: =IFERROR(AF39/AF$19,0) -> 0 | AH39: =IFERROR(AF39/AF$8,0) -> 0 | AI39: =IFERROR(AF39/AF$7,0) -> 0 | AJ39: =AJ27-AJ37 -> 0 | AK39: =IFERROR(AJ39/AJ$19,0) -> 0 | AL39: =IFERROR(AJ39/AJ$8,0) -> 0 | AM39: =IFERROR(AJ39/AJ$7,0) -> 0 | AN39: =AN27-AN37 -> 0 | AO39: =IFERROR(AN39/AN$19,0) -> 0 | AP39: =IFERROR(AN39/AN$8,0) -> 0 | AQ39: =IFERROR(AN39/AN$7,0) -> 0
C41: Management Fees
C42: Management Fee | D42: =IFERROR(INDEX(Tape!$T$7:$ME$36,MATCH($C$3,Tape!$C$7:$C$36,0),MATCH($C42&"+"&D$5,Tape!$T$1:$ME$1,0)),0) -> 0 | E42: =IFERROR(D42/D$19,0) -> 0 | F42: =IFERROR(D42/D$8,0) -> 0 | G42: =IFERROR(D42/D$7,0) -> 0 | H42: =IFERROR(INDEX(Tape!$T$7:$ME$36,MATCH($C$3,Tape!$C$7:$C$36,0),MATCH($C42&"+"&H$5,Tape!$T$1:$ME$1,0)),0) -> 0 | I42: =IFERROR(H42/H$19,0) -> 0 | J42: =IFERROR(H42/H$8,0) -> 0 | K42: =IFERROR(H42/H$7,0) -> 0 | L42: =IFERROR(INDEX(Tape!$T$7:$ME$36,MATCH($C$3,Tape!$C$7:$C$36,0),MATCH($C42&"+"&L$5,Tape!$T$1:$ME$1,0)),0) -> 0 | M42: =IFERROR(L42/L$19,0) -> 0 | N42: =IFERROR(L42/L$8,0) -> 0 | O42: =IFERROR(L42/L$7,0) -> 0 | P42: =IFERROR(INDEX(Tape!$T$7:$ME$36,MATCH($C$3,Tape!$C$7:$C$36,0),MATCH($C42&"+"&P$5,Tape!$T$1:$ME$1,0)),0) -> 0 | Q42: =IFERROR(P42/P$19,0) -> 0 | R42: =IFERROR(P42/P$8,0) -> 0 | S42: =IFERROR(P42/P$7,0) -> 0 | T42: =IFERROR(INDEX(Tape!$T$7:$ME$36,MATCH($C$3,Tape!$C$7:$C$36,0),MATCH($C42&"+"&T$5,Tape!$T$1:$ME$1,0)),0) -> 0 | U42: =IFERROR(T42/T$19,0) -> 0 | V42: =IFERROR(T42/T$8,0) -> 0 | W42: =IFERROR(T42/T$7,0) -> 0 | X42: =IFERROR(INDEX(Tape!$T$7:$ME$36,MATCH($C$3,Tape!$C$7:$C$36,0),MATCH($C42&"+"&X$5,Tape!$T$1:$ME$1,0)),0) -> 0 | Y42: =IFERROR(X42/X$19,0) -> 0 | Z42: =IFERROR(X42/X$8,0) -> 0 | AA42: =IFERROR(X42/X$7,0) -> 0 | AB42: =IFERROR(INDEX(Tape!$T$7:$ME$36,MATCH($C$3,Tape!$C$7:$C$36,0),MATCH($C42&"+"&AB$5,Tape!$T$1:$ME$1,0)),0) -> 0 | AC42: =IFERROR(AB42/AB$19,0) -> 0 | AD42: =IFERROR(AB42/AB$8,0) -> 0 | AE42: =IFERROR(AB42/AB$7,0) -> 0 | AF42: =IFERROR(INDEX(Tape!$T$7:$ME$36,MATCH($C$3,Tape!$C$7:$C$36,0),MATCH($C42&"+"&AF$5,Tape!$T$1:$ME$1,0)),0) -> 0 | AG42: =IFERROR(AF42/AF$19,0) -> 0 | AH42: =IFERROR(AF42/AF$8,0) -> 0 | AI42: =IFERROR(AF42/AF$7,0) -> 0 | AJ42: =IFERROR(INDEX(Tape!$T$7:$ME$36,MATCH($C$3,Tape!$C$7:$C$36,0),MATCH($C42&"+"&AJ$5,Tape!$T$1:$ME$1,0)),0) -> 0 | AK42: =IFERROR(AJ42/AJ$19,0) -> 0 | AL42: =IFERROR(AJ42/AJ$8,0) -> 0 | AM42: =IFERROR(AJ42/AJ$7,0) -> 0 | AN42: =AO42*AN19 -> 0 | AO42: 0.03 | AP42: =IFERROR(AN42/AN$8,0) -> 0 | AQ42: =IFERROR(AN42/AN$7,0) -> 0
C43: Incentive Management Fee | D43: =IFERROR(INDEX(Tape!$T$7:$ME$36,MATCH($C$3,Tape!$C$7:$C$36,0),MATCH($C43&"+"&D$5,Tape!$T$1:$ME$1,0)),0) -> 0 | E43: =IFERROR(D43/D$19,0) -> 0 | F43: =IFERROR(D43/D$8,0) -> 0 | G43: =IFERROR(D43/D$7,0) -> 0 | H43: =IFERROR(INDEX(Tape!$T$7:$ME$36,MATCH($C$3,Tape!$C$7:$C$36,0),MATCH($C43&"+"&H$5,Tape!$T$1:$ME$1,0)),0) -> 0 | I43: =IFERROR(H43/H$19,0) -> 0 | J43: =IFERROR(H43/H$8,0) -> 0 | K43: =IFERROR(H43/H$7,0) -> 0 | L43: =IFERROR(INDEX(Tape!$T$7:$ME$36,MATCH($C$3,Tape!$C$7:$C$36,0),MATCH($C43&"+"&L$5,Tape!$T$1:$ME$1,0)),0) -> 0 | M43: =IFERROR(L43/L$19,0) -> 0 | N43: =IFERROR(L43/L$8,0) -> 0 | O43: =IFERROR(L43/L$7,0) -> 0 | P43: =IFERROR(INDEX(Tape!$T$7:$ME$36,MATCH($C$3,Tape!$C$7:$C$36,0),MATCH($C43&"+"&P$5,Tape!$T$1:$ME$1,0)),0) -> 0 | Q43: =IFERROR(P43/P$19,0) -> 0 | R43: =IFERROR(P43/P$8,0) -> 0 | S43: =IFERROR(P43/P$7,0) -> 0 | T43: =IFERROR(INDEX(Tape!$T$7:$ME$36,MATCH($C$3,Tape!$C$7:$C$36,0),MATCH($C43&"+"&T$5,Tape!$T$1:$ME$1,0)),0) -> 0 | U43: =IFERROR(T43/T$19,0) -> 0 | V43: =IFERROR(T43/T$8,0) -> 0 | W43: =IFERROR(T43/T$7,0) -> 0 | X43: =IFERROR(INDEX(Tape!$T$7:$ME$36,MATCH($C$3,Tape!$C$7:$C$36,0),MATCH($C43&"+"&X$5,Tape!$T$1:$ME$1,0)),0) -> 0 | Y43: =IFERROR(X43/X$19,0) -> 0 | Z43: =IFERROR(X43/X$8,0) -> 0 | AA43: =IFERROR(X43/X$7,0) -> 0 | AB43: =IFERROR(INDEX(Tape!$T$7:$ME$36,MATCH($C$3,Tape!$C$7:$C$36,0),MATCH($C43&"+"&AB$5,Tape!$T$1:$ME$1,0)),0) -> 0 | AC43: =IFERROR(AB43/AB$19,0) -> 0 | AD43: =IFERROR(AB43/AB$8,0) -> 0 | AE43: =IFERROR(AB43/AB$7,0) -> 0 | AF43: =IFERROR(INDEX(Tape!$T$7:$ME$36,MATCH($C$3,Tape!$C$7:$C$36,0),MATCH($C43&"+"&AF$5,Tape!$T$1:$ME$1,0)),0) -> 0 | AG43: =IFERROR(AF43/AF$19,0) -> 0 | AH43: =IFERROR(AF43/AF$8,0) -> 0 | AI43: =IFERROR(AF43/AF$7,0) -> 0 | AJ43: =IFERROR(INDEX(Tape!$T$7:$ME$36,MATCH($C$3,Tape!$C$7:$C$36,0),MATCH($C43&"+"&AJ$5,Tape!$T$1:$ME$1,0)),0) -> 0 | AK43: =IFERROR(AJ43/AJ$19,0) -> 0 | AL43: =IFERROR(AJ43/AJ$8,0) -> 0 | AM43: =IFERROR(AJ43/AJ$7,0) -> 0 | AN43: =AO72 -> 0 | AO43: =IFERROR(AN43/AN$19,0) -> 0 | AP43: =IFERROR(AN43/AN$8,0) -> 0 | AQ43: =IFERROR(AN43/AN$7,0) -> 0
C44: Management Fee | D44: =SUM(D42:D43) -> 0 | E44: =IFERROR(D44/D$19,0) -> 0 | F44: =IFERROR(D44/D$8,0) -> 0 | G44: =IFERROR(D44/D$7,0) -> 0 | H44: =SUM(H42:H43) -> 0 | I44: =IFERROR(H44/H$19,0) -> 0 | J44: =IFERROR(H44/H$8,0) -> 0 | K44: =IFERROR(H44/H$7,0) -> 0 | L44: =SUM(L42:L43) -> 0 | M44: =IFERROR(L44/L$19,0) -> 0 | N44: =IFERROR(L44/L$8,0) -> 0 | O44: =IFERROR(L44/L$7,0) -> 0 | P44: =SUM(P42:P43) -> 0 | Q44: =IFERROR(P44/P$19,0) -> 0 | R44: =IFERROR(P44/P$8,0) -> 0 | S44: =IFERROR(P44/P$7,0) -> 0 | T44: =SUM(T42:T43) -> 0 | U44: =IFERROR(T44/T$19,0) -> 0 | V44: =IFERROR(T44/T$8,0) -> 0 | W44: =IFERROR(T44/T$7,0) -> 0 | X44: =SUM(X42:X43) -> 0 | Y44: =IFERROR(X44/X$19,0) -> 0 | Z44: =IFERROR(X44/X$8,0) -> 0 | AA44: =IFERROR(X44/X$7,0) -> 0 | AB44: =SUM(AB42:AB43) -> 0 | AC44: =IFERROR(AB44/AB$19,0) -> 0 | AD44: =IFERROR(AB44/AB$8,0) -> 0 | AE44: =IFERROR(AB44/AB$7,0) -> 0 | AF44: =SUM(AF42:AF43) -> 0 | AG44: =IFERROR(AF44/AF$19,0) -> 0 | AH44: =IFERROR(AF44/AF$8,0) -> 0 | AI44: =IFERROR(AF44/AF$7,0) -> 0 | AJ44: =SUM(AJ42:AJ43) -> 0 | AK44: =IFERROR(AJ44/AJ$19,0) -> 0 | AL44: =IFERROR(AJ44/AJ$8,0) -> 0 | AM44: =IFERROR(AJ44/AJ$7,0) -> 0 | AN44: =SUM(AN42:AN43) -> 0 | AO44: =IFERROR(AN44/AN$19,0) -> 0 | AP44: =IFERROR(AN44/AN$8,0) -> 0 | AQ44: =IFERROR(AN44/AN$7,0) -> 0
C46: Fixed Expenses
C47: Other Fixed Expense | D47: =IFERROR(INDEX(Tape!$T$7:$ME$36,MATCH($C$3,Tape!$C$7:$C$36,0),MATCH($C47&"+"&D$5,Tape!$T$1:$ME$1,0)),0) -> 0 | E47: =IFERROR(D47/D$19,0) -> 0 | F47: =IFERROR(D47/D$8,0) -> 0 | G47: =IFERROR(D47/D$7,0) -> 0 | H47: =IFERROR(INDEX(Tape!$T$7:$ME$36,MATCH($C$3,Tape!$C$7:$C$36,0),MATCH($C47&"+"&H$5,Tape!$T$1:$ME$1,0)),0) -> 0 | I47: =IFERROR(H47/H$19,0) -> 0 | J47: =IFERROR(H47/H$8,0) -> 0 | K47: =IFERROR(H47/H$7,0) -> 0 | L47: =IFERROR(INDEX(Tape!$T$7:$ME$36,MATCH($C$3,Tape!$C$7:$C$36,0),MATCH($C47&"+"&L$5,Tape!$T$1:$ME$1,0)),0) -> 0 | M47: =IFERROR(L47/L$19,0) -> 0 | N47: =IFERROR(L47/L$8,0) -> 0 | O47: =IFERROR(L47/L$7,0) -> 0 | P47: =IFERROR(INDEX(Tape!$T$7:$ME$36,MATCH($C$3,Tape!$C$7:$C$36,0),MATCH($C47&"+"&P$5,Tape!$T$1:$ME$1,0)),0) -> 0 | Q47: =IFERROR(P47/P$19,0) -> 0 | R47: =IFERROR(P47/P$8,0) -> 0 | S47: =IFERROR(P47/P$7,0) -> 0 | T47: =IFERROR(INDEX(Tape!$T$7:$ME$36,MATCH($C$3,Tape!$C$7:$C$36,0),MATCH($C47&"+"&T$5,Tape!$T$1:$ME$1,0)),0) -> 0 | U47: =IFERROR(T47/T$19,0) -> 0 | V47: =IFERROR(T47/T$8,0) -> 0 | W47: =IFERROR(T47/T$7,0) -> 0 | X47: =IFERROR(INDEX(Tape!$T$7:$ME$36,MATCH($C$3,Tape!$C$7:$C$36,0),MATCH($C47&"+"&X$5,Tape!$T$1:$ME$1,0)),0) -> 0 | Y47: =IFERROR(X47/X$19,0) -> 0 | Z47: =IFERROR(X47/X$8,0) -> 0 | AA47: =IFERROR(X47/X$7,0) -> 0 | AB47: =IFERROR(INDEX(Tape!$T$7:$ME$36,MATCH($C$3,Tape!$C$7:$C$36,0),MATCH($C47&"+"&AB$5,Tape!$T$1:$ME$1,0)),0) -> 0 | AC47: =IFERROR(AB47/AB$19,0) -> 0 | AD47: =IFERROR(AB47/AB$8,0) -> 0 | AE47: =IFERROR(AB47/AB$7,0) -> 0 | AF47: =IFERROR(INDEX(Tape!$T$7:$ME$36,MATCH($C$3,Tape!$C$7:$C$36,0),MATCH($C47&"+"&AF$5,Tape!$T$1:$ME$1,0)),0) -> 0 | AG47: =IFERROR(AF47/AF$19,0) -> 0 | AH47: =IFERROR(AF47/AF$8,0) -> 0 | AI47: =IFERROR(AF47/AF$7,0) -> 0 | AJ47: =IFERROR(INDEX(Tape!$T$7:$ME$36,MATCH($C$3,Tape!$C$7:$C$36,0),MATCH($C47&"+"&AJ$5,Tape!$T$1:$ME$1,0)),0) -> 0 | AK47: =IFERROR(AJ47/AJ$19,0) -> 0 | AL47: =IFERROR(AJ47/AJ$8,0) -> 0 | AM47: =IFERROR(AJ47/AJ$7,0) -> 0 | AN47: =AF47 -> 0 | AO47: =IFERROR(AN47/AN$19,0) -> 0 | AP47: =IFERROR(AN47/AN$8,0) -> 0 | AQ47: =IFERROR(AN47/AN$7,0) -> 0
C48: Rents | D48: =IFERROR(INDEX(Tape!$T$7:$ME$36,MATCH($C$3,Tape!$C$7:$C$36,0),MATCH($C48&"+"&D$5,Tape!$T$1:$ME$1,0)),0) -> 0 | E48: =IFERROR(D48/D$19,0) -> 0 | F48: =IFERROR(D48/D$8,0) -> 0 | G48: =IFERROR(D48/D$7,0) -> 0 | H48: =IFERROR(INDEX(Tape!$T$7:$ME$36,MATCH($C$3,Tape!$C$7:$C$36,0),MATCH($C48&"+"&H$5,Tape!$T$1:$ME$1,0)),0) -> 0 | I48: =IFERROR(H48/H$19,0) -> 0 | J48: =IFERROR(H48/H$8,0) -> 0 | K48: =IFERROR(H48/H$7,0) -> 0 | L48: =IFERROR(INDEX(Tape!$T$7:$ME$36,MATCH($C$3,Tape!$C$7:$C$36,0),MATCH($C48&"+"&L$5,Tape!$T$1:$ME$1,0)),0) -> 0 | M48: =IFERROR(L48/L$19,0) -> 0 | N48: =IFERROR(L48/L$8,0) -> 0 | O48: =IFERROR(L48/L$7,0) -> 0 | P48: =IFERROR(INDEX(Tape!$T$7:$ME$36,MATCH($C$3,Tape!$C$7:$C$36,0),MATCH($C48&"+"&P$5,Tape!$T$1:$ME$1,0)),0) -> 0 | Q48: =IFERROR(P48/P$19,0) -> 0 | R48: =IFERROR(P48/P$8,0) -> 0 | S48: =IFERROR(P48/P$7,0) -> 0 | T48: =IFERROR(INDEX(Tape!$T$7:$ME$36,MATCH($C$3,Tape!$C$7:$C$36,0),MATCH($C48&"+"&T$5,Tape!$T$1:$ME$1,0)),0) -> 0 | U48: =IFERROR(T48/T$19,0) -> 0 | V48: =IFERROR(T48/T$8,0) -> 0 | W48: =IFERROR(T48/T$7,0) -> 0 | X48: =IFERROR(INDEX(Tape!$T$7:$ME$36,MATCH($C$3,Tape!$C$7:$C$36,0),MATCH($C48&"+"&X$5,Tape!$T$1:$ME$1,0)),0) -> 0 | Y48: =IFERROR(X48/X$19,0) -> 0 | Z48: =IFERROR(X48/X$8,0) -> 0 | AA48: =IFERROR(X48/X$7,0) -> 0 | AB48: =IFERROR(INDEX(Tape!$T$7:$ME$36,MATCH($C$3,Tape!$C$7:$C$36,0),MATCH($C48&"+"&AB$5,Tape!$T$1:$ME$1,0)),0) -> 0 | AC48: =IFERROR(AB48/AB$19,0) -> 0 | AD48: =IFERROR(AB48/AB$8,0) -> 0 | AE48: =IFERROR(AB48/AB$7,0) -> 0 | AF48: =IFERROR(INDEX(Tape!$T$7:$ME$36,MATCH($C$3,Tape!$C$7:$C$36,0),MATCH($C48&"+"&AF$5,Tape!$T$1:$ME$1,0)),0) -> 0 | AG48: =IFERROR(AF48/AF$19,0) -> 0 | AH48: =IFERROR(AF48/AF$8,0) -> 0 | AI48: =IFERROR(AF48/AF$7,0) -> 0 | AJ48: =IFERROR(INDEX(Tape!$T$7:$ME$36,MATCH($C$3,Tape!$C$7:$C$36,0),MATCH($C48&"+"&AJ$5,Tape!$T$1:$ME$1,0)),0) -> 0 | AK48: =IFERROR(AJ48/AJ$19,0) -> 0 | AL48: =IFERROR(AJ48/AJ$8,0) -> 0 | AM48: =IFERROR(AJ48/AJ$7,0) -> 0 | AN48: =AF48 -> 0 | AO48: =IFERROR(AN48/AN$19,0) -> 0 | AP48: =IFERROR(AN48/AN$8,0) -> 0 | AQ48: =IFERROR(AN48/AN$7,0) -> 0 | AT48: GROWTH
C49: Property Taxes | D49: =IFERROR(INDEX(Tape!$T$7:$ME$36,MATCH($C$3,Tape!$C$7:$C$36,0),MATCH($C49&"+"&D$5,Tape!$T$1:$ME$1,0)),0) -> 0 | E49: =IFERROR(D49/D$19,0) -> 0 | F49: =IFERROR(D49/D$8,0) -> 0 | G49: =IFERROR(D49/D$7,0) -> 0 | H49: =IFERROR(INDEX(Tape!$T$7:$ME$36,MATCH($C$3,Tape!$C$7:$C$36,0),MATCH($C49&"+"&H$5,Tape!$T$1:$ME$1,0)),0) -> 0 | I49: =IFERROR(H49/H$19,0) -> 0 | J49: =IFERROR(H49/H$8,0) -> 0 | K49: =IFERROR(H49/H$7,0) -> 0 | L49: =IFERROR(INDEX(Tape!$T$7:$ME$36,MATCH($C$3,Tape!$C$7:$C$36,0),MATCH($C49&"+"&L$5,Tape!$T$1:$ME$1,0)),0) -> 0 | M49: =IFERROR(L49/L$19,0) -> 0 | N49: =IFERROR(L49/L$8,0) -> 0 | O49: =IFERROR(L49/L$7,0) -> 0 | P49: =IFERROR(INDEX(Tape!$T$7:$ME$36,MATCH($C$3,Tape!$C$7:$C$36,0),MATCH($C49&"+"&P$5,Tape!$T$1:$ME$1,0)),0) -> 0 | Q49: =IFERROR(P49/P$19,0) -> 0 | R49: =IFERROR(P49/P$8,0) -> 0 | S49: =IFERROR(P49/P$7,0) -> 0 | T49: =IFERROR(INDEX(Tape!$T$7:$ME$36,MATCH($C$3,Tape!$C$7:$C$36,0),MATCH($C49&"+"&T$5,Tape!$T$1:$ME$1,0)),0) -> 0 | U49: =IFERROR(T49/T$19,0) -> 0 | V49: =IFERROR(T49/T$8,0) -> 0 | W49: =IFERROR(T49/T$7,0) -> 0 | X49: =IFERROR(INDEX(Tape!$T$7:$ME$36,MATCH($C$3,Tape!$C$7:$C$36,0),MATCH($C49&"+"&X$5,Tape!$T$1:$ME$1,0)),0) -> 0 | Y49: =IFERROR(X49/X$19,0) -> 0 | Z49: =IFERROR(X49/X$8,0) -> 0 | AA49: =IFERROR(X49/X$7,0) -> 0 | AB49: =IFERROR(INDEX(Tape!$T$7:$ME$36,MATCH($C$3,Tape!$C$7:$C$36,0),MATCH($C49&"+"&AB$5,Tape!$T$1:$ME$1,0)),0) -> 0 | AC49: =IFERROR(AB49/AB$19,0) -> 0 | AD49: =IFERROR(AB49/AB$8,0) -> 0 | AE49: =IFERROR(AB49/AB$7,0) -> 0 | AF49: =IFERROR(INDEX(Tape!$T$7:$ME$36,MATCH($C$3,Tape!$C$7:$C$36,0),MATCH($C49&"+"&AF$5,Tape!$T$1:$ME$1,0)),0) -> 0 | AG49: =IFERROR(AF49/AF$19,0) -> 0 | AH49: =IFERROR(AF49/AF$8,0) -> 0 | AI49: =IFERROR(AF49/AF$7,0) -> 0 | AJ49: =IFERROR(INDEX(Tape!$T$7:$ME$36,MATCH($C$3,Tape!$C$7:$C$36,0),MATCH($C49&"+"&AJ$5,Tape!$T$1:$ME$1,0)),0) -> 0 | AK49: =IFERROR(AJ49/AJ$19,0) -> 0 | AL49: =IFERROR(AJ49/AJ$8,0) -> 0 | AM49: =IFERROR(AJ49/AJ$7,0) -> 0 | AN49: =X49*(1+AT49) -> 0 | AO49: =IFERROR(AN49/AN$19,0) -> 0 | AP49: =IFERROR(AN49/AN$8,0) -> 0 | AQ49: =IFERROR(AN49/AN$7,0) -> 0 | AT49: 0.03
C50: Property Insurance | D50: =IFERROR(INDEX(Tape!$T$7:$ME$36,MATCH($C$3,Tape!$C$7:$C$36,0),MATCH($C50&"+"&D$5,Tape!$T$1:$ME$1,0)),0) -> 0 | E50: =IFERROR(D50/D$19,0) -> 0 | F50: =IFERROR(D50/D$8,0) -> 0 | G50: =IFERROR(D50/D$7,0) -> 0 | H50: =IFERROR(INDEX(Tape!$T$7:$ME$36,MATCH($C$3,Tape!$C$7:$C$36,0),MATCH($C50&"+"&H$5,Tape!$T$1:$ME$1,0)),0) -> 0 | I50: =IFERROR(H50/H$19,0) -> 0 | J50: =IFERROR(H50/H$8,0) -> 0 | K50: =IFERROR(H50/H$7,0) -> 0 | L50: =IFERROR(INDEX(Tape!$T$7:$ME$36,MATCH($C$3,Tape!$C$7:$C$36,0),MATCH($C50&"+"&L$5,Tape!$T$1:$ME$1,0)),0) -> 0 | M50: =IFERROR(L50/L$19,0) -> 0 | N50: =IFERROR(L50/L$8,0) -> 0 | O50: =IFERROR(L50/L$7,0) -> 0 | P50: =IFERROR(INDEX(Tape!$T$7:$ME$36,MATCH($C$3,Tape!$C$7:$C$36,0),MATCH($C50&"+"&P$5,Tape!$T$1:$ME$1,0)),0) -> 0 | Q50: =IFERROR(P50/P$19,0) -> 0 | R50: =IFERROR(P50/P$8,0) -> 0 | S50: =IFERROR(P50/P$7,0) -> 0 | T50: =IFERROR(INDEX(Tape!$T$7:$ME$36,MATCH($C$3,Tape!$C$7:$C$36,0),MATCH($C50&"+"&T$5,Tape!$T$1:$ME$1,0)),0) -> 0 | U50: =IFERROR(T50/T$19,0) -> 0 | V50: =IFERROR(T50/T$8,0) -> 0 | W50: =IFERROR(T50/T$7,0) -> 0 | X50: =IFERROR(INDEX(Tape!$T$7:$ME$36,MATCH($C$3,Tape!$C$7:$C$36,0),MATCH($C50&"+"&X$5,Tape!$T$1:$ME$1,0)),0) -> 0 | Y50: =IFERROR(X50/X$19,0) -> 0 | Z50: =IFERROR(X50/X$8,0) -> 0 | AA50: =IFERROR(X50/X$7,0) -> 0 | AB50: =IFERROR(INDEX(Tape!$T$7:$ME$36,MATCH($C$3,Tape!$C$7:$C$36,0),MATCH($C50&"+"&AB$5,Tape!$T$1:$ME$1,0)),0) -> 0 | AC50: =IFERROR(AB50/AB$19,0) -> 0 | AD50: =IFERROR(AB50/AB$8,0) -> 0 | AE50: =IFERROR(AB50/AB$7,0) -> 0 | AF50: =IFERROR(INDEX(Tape!$T$7:$ME$36,MATCH($C$3,Tape!$C$7:$C$36,0),MATCH($C50&"+"&AF$5,Tape!$T$1:$ME$1,0)),0) -> 0 | AG50: =IFERROR(AF50/AF$19,0) -> 0 | AH50: =IFERROR(AF50/AF$8,0) -> 0 | AI50: =IFERROR(AF50/AF$7,0) -> 0 | AJ50: =IFERROR(INDEX(Tape!$T$7:$ME$36,MATCH($C$3,Tape!$C$7:$C$36,0),MATCH($C50&"+"&AJ$5,Tape!$T$1:$ME$1,0)),0) -> 0 | AK50: =IFERROR(AJ50/AJ$19,0) -> 0 | AL50: =IFERROR(AJ50/AJ$8,0) -> 0 | AM50: =IFERROR(AJ50/AJ$7,0) -> 0 | AN50: =X50*(1+AT50) -> 0 | AO50: =IFERROR(AN50/AN$19,0) -> 0 | AP50: =IFERROR(AN50/AN$8,0) -> 0 | AQ50: =IFERROR(AN50/AN$7,0) -> 0 | AT50: 0.03
C51: TOTAL FIXED EXPENSES | D51: =SUM(D47:D50) -> 0 | E51: =IFERROR(D51/D$19,0) -> 0 | F51: =IFERROR(D51/D$8,0) -> 0 | G51: =IFERROR(D51/D$7,0) -> 0 | H51: =SUM(H47:H50) -> 0 | I51: =IFERROR(H51/H$19,0) -> 0 | J51: =IFERROR(H51/H$8,0) -> 0 | K51: =IFERROR(H51/H$7,0) -> 0 | L51: =SUM(L47:L50) -> 0 | M51: =IFERROR(L51/L$19,0) -> 0 | N51: =IFERROR(L51/L$8,0) -> 0 | O51: =IFERROR(L51/L$7,0) -> 0 | P51: =SUM(P47:P50) -> 0 | Q51: =IFERROR(P51/P$19,0) -> 0 | R51: =IFERROR(P51/P$8,0) -> 0 | S51: =IFERROR(P51/P$7,0) -> 0 | T51: =SUM(T47:T50) -> 0 | U51: =IFERROR(T51/T$19,0) -> 0 | V51: =IFERROR(T51/T$8,0) -> 0 | W51: =IFERROR(T51/T$7,0) -> 0 | X51: =SUM(X47:X50) -> 0 | Y51: =IFERROR(X51/X$19,0) -> 0 | Z51: =IFERROR(X51/X$8,0) -> 0 | AA51: =IFERROR(X51/X$7,0) -> 0 | AB51: =SUM(AB47:AB50) -> 0 | AC51: =IFERROR(AB51/AB$19,0) -> 0 | AD51: =IFERROR(AB51/AB$8,0) -> 0 | AE51: =IFERROR(AB51/AB$7,0) -> 0 | AF51: =SUM(AF47:AF50) -> 0 | AG51: =IFERROR(AF51/AF$19,0) -> 0 | AH51: =IFERROR(AF51/AF$8,0) -> 0 | AI51: =IFERROR(AF51/AF$7,0) -> 0 | AJ51: =SUM(AJ47:AJ50) -> 0 | AK51: =IFERROR(AJ51/AJ$19,0) -> 0 | AL51: =IFERROR(AJ51/AJ$8,0) -> 0 | AM51: =IFERROR(AJ51/AJ$7,0) -> 0 | AN51: =SUM(AN47:AN50) -> 0 | AO51: =IFERROR(AN51/AN$19,0) -> 0 | AP51: =IFERROR(AN51/AN$8,0) -> 0 | AQ51: =IFERROR(AN51/AN$7,0) -> 0
C53: EBITDA | D53: =D39-D44-D51 -> 0 | E53: =IFERROR(D53/D$19,0) -> 0 | F53: =IFERROR(D53/D$8,0) -> 0 | G53: =IFERROR(D53/D$7,0) -> 0 | H53: =H39-H44-H51 -> 0 | I53: =IFERROR(H53/H$19,0) -> 0 | J53: =IFERROR(H53/H$8,0) -> 0 | K53: =IFERROR(H53/H$7,0) -> 0 | L53: =L39-L44-L51 -> 0 | M53: =IFERROR(L53/L$19,0) -> 0 | N53: =IFERROR(L53/L$8,0) -> 0 | O53: =IFERROR(L53/L$7,0) -> 0 | P53: =P39-P44-P51 -> 0 | Q53: =IFERROR(P53/P$19,0) -> 0 | R53: =IFERROR(P53/P$8,0) -> 0 | S53: =IFERROR(P53/P$7,0) -> 0 | T53: =T39-T44-T51 -> 0 | U53: =IFERROR(T53/T$19,0) -> 0 | V53: =IFERROR(T53/T$8,0) -> 0 | W53: =IFERROR(T53/T$7,0) -> 0 | X53: =X39-X44-X51 -> 0 | Y53: =IFERROR(X53/X$19,0) -> 0 | Z53: =IFERROR(X53/X$8,0) -> 0 | AA53: =IFERROR(X53/X$7,0) -> 0 | AB53: =AB39-AB44-AB51 -> 0 | AC53: =IFERROR(AB53/AB$19,0) -> 0 | AD53: =IFERROR(AB53/AB$8,0) -> 0 | AE53: =IFERROR(AB53/AB$7,0) -> 0 | AF53: =AF39-AF44-AF51 -> 0 | AG53: =IFERROR(AF53/AF$19,0) -> 0 | AH53: =IFERROR(AF53/AF$8,0) -> 0 | AI53: =IFERROR(AF53/AF$7,0) -> 0 | AJ53: =AJ39-AJ44-AJ51 -> 0 | AK53: =IFERROR(AJ53/AJ$19,0) -> 0 | AL53: =IFERROR(AJ53/AJ$8,0) -> 0 | AM53: =IFERROR(AJ53/AJ$7,0) -> 0 | AN53: =AN39-AN44-AN51 -> 0 | AO53: =IFERROR(AN53/AN$19,0) -> 0 | AP53: =IFERROR(AN53/AN$8,0) -> 0 | AQ53: =IFERROR(AN53/AN$7,0) -> 0
C54: FF&E Reserves | D54: =IFERROR(INDEX(Tape!$T$7:$ME$36,MATCH($C$3,Tape!$C$7:$C$36,0),MATCH($C54&"+"&D$5,Tape!$T$1:$ME$1,0)),0) -> 0 | E54: =IFERROR(D54/D$19,0) -> 0 | F54: =IFERROR(D54/D$8,0) -> 0 | G54: =IFERROR(D54/D$7,0) -> 0 | H54: =IFERROR(INDEX(Tape!$T$7:$ME$36,MATCH($C$3,Tape!$C$7:$C$36,0),MATCH($C54&"+"&H$5,Tape!$T$1:$ME$1,0)),0) -> 0 | I54: =IFERROR(H54/H$19,0) -> 0 | J54: =IFERROR(H54/H$8,0) -> 0 | K54: =IFERROR(H54/H$7,0) -> 0 | L54: =IFERROR(INDEX(Tape!$T$7:$ME$36,MATCH($C$3,Tape!$C$7:$C$36,0),MATCH($C54&"+"&L$5,Tape!$T$1:$ME$1,0)),0) -> 0 | M54: =IFERROR(L54/L$19,0) -> 0 | N54: =IFERROR(L54/L$8,0) -> 0 | O54: =IFERROR(L54/L$7,0) -> 0 | P54: =IFERROR(INDEX(Tape!$T$7:$ME$36,MATCH($C$3,Tape!$C$7:$C$36,0),MATCH($C54&"+"&P$5,Tape!$T$1:$ME$1,0)),0) -> 0 | Q54: =IFERROR(P54/P$19,0) -> 0 | R54: =IFERROR(P54/P$8,0) -> 0 | S54: =IFERROR(P54/P$7,0) -> 0 | T54: =IFERROR(INDEX(Tape!$T$7:$ME$36,MATCH($C$3,Tape!$C$7:$C$36,0),MATCH($C54&"+"&T$5,Tape!$T$1:$ME$1,0)),0) -> 0 | U54: =IFERROR(T54/T$19,0) -> 0 | V54: =IFERROR(T54/T$8,0) -> 0 | W54: =IFERROR(T54/T$7,0) -> 0 | X54: =IFERROR(INDEX(Tape!$T$7:$ME$36,MATCH($C$3,Tape!$C$7:$C$36,0),MATCH($C54&"+"&X$5,Tape!$T$1:$ME$1,0)),0) -> 0 | Y54: =IFERROR(X54/X$19,0) -> 0 | Z54: =IFERROR(X54/X$8,0) -> 0 | AA54: =IFERROR(X54/X$7,0) -> 0 | AB54: =IFERROR(INDEX(Tape!$T$7:$ME$36,MATCH($C$3,Tape!$C$7:$C$36,0),MATCH($C54&"+"&AB$5,Tape!$T$1:$ME$1,0)),0) -> 0 | AC54: =IFERROR(AB54/AB$19,0) -> 0 | AD54: =IFERROR(AB54/AB$8,0) -> 0 | AE54: =IFERROR(AB54/AB$7,0) -> 0 | AF54: =IFERROR(INDEX(Tape!$T$7:$ME$36,MATCH($C$3,Tape!$C$7:$C$36,0),MATCH($C54&"+"&AF$5,Tape!$T$1:$ME$1,0)),0) -> 0 | AG54: =IFERROR(AF54/AF$19,0) -> 0 | AH54: =IFERROR(AF54/AF$8,0) -> 0 | AI54: =IFERROR(AF54/AF$7,0) -> 0 | AJ54: =IFERROR(INDEX(Tape!$T$7:$ME$36,MATCH($C$3,Tape!$C$7:$C$36,0),MATCH($C54&"+"&AJ$5,Tape!$T$1:$ME$1,0)),0) -> 0 | AK54: =IFERROR(AJ54/AJ$19,0) -> 0 | AL54: =IFERROR(AJ54/AJ$8,0) -> 0 | AM54: =IFERROR(AJ54/AJ$7,0) -> 0 | AN54: =AO54*AN19 -> 0 | AO54: 0.04 | AP54: =IFERROR(AN54/AN$8,0) -> 0 | AQ54: =IFERROR(AN54/AN$7,0) -> 0
C55: NOI | D55: =D53-D54 -> 0 | E55: =IFERROR(D55/D$19,0) -> 0 | F55: =IFERROR(D55/D$8,0) -> 0 | G55: =IFERROR(D55/D$7,0) -> 0 | H55: =H53-H54 -> 0 | I55: =IFERROR(H55/H$19,0) -> 0 | J55: =IFERROR(H55/H$8,0) -> 0 | K55: =IFERROR(H55/H$7,0) -> 0 | L55: =L53-L54 -> 0 | M55: =IFERROR(L55/L$19,0) -> 0 | N55: =IFERROR(L55/L$8,0) -> 0 | O55: =IFERROR(L55/L$7,0) -> 0 | P55: =P53-P54 -> 0 | Q55: =IFERROR(P55/P$19,0) -> 0 | R55: =IFERROR(P55/P$8,0) -> 0 | S55: =IFERROR(P55/P$7,0) -> 0 | T55: =T53-T54 -> 0 | U55: =IFERROR(T55/T$19,0) -> 0 | V55: =IFERROR(T55/T$8,0) -> 0 | W55: =IFERROR(T55/T$7,0) -> 0 | X55: =X53-X54 -> 0 | Y55: =IFERROR(X55/X$19,0) -> 0 | Z55: =IFERROR(X55/X$8,0) -> 0 | AA55: =IFERROR(X55/X$7,0) -> 0 | AB55: =AB53-AB54 -> 0 | AC55: =IFERROR(AB55/AB$19,0) -> 0 | AD55: =IFERROR(AB55/AB$8,0) -> 0 | AE55: =IFERROR(AB55/AB$7,0) -> 0 | AF55: =AF53-AF54 -> 0 | AG55: =IFERROR(AF55/AF$19,0) -> 0 | AH55: =IFERROR(AF55/AF$8,0) -> 0 | AI55: =IFERROR(AF55/AF$7,0) -> 0 | AJ55: =AJ53-AJ54 -> 0 | AK55: =IFERROR(AJ55/AJ$19,0) -> 0 | AL55: =IFERROR(AJ55/AJ$8,0) -> 0 | AM55: =IFERROR(AJ55/AJ$7,0) -> 0 | AN55: =AN53-AN54 -> 0 | AO55: =IFERROR(AN55/AN$19,0) -> 0 | AP55: =IFERROR(AN55/AN$8,0) -> 0 | AQ55: =IFERROR(AN55/AN$7,0) -> 0
C56: Cap Rate (Applied to NOI) | D56: - | H56: - | L56: - | P56: - | T56: - | X56: - | AB56: - | AF56: - | AJ56: - | AN56: =SUMIFS('UW Drivers'!$AA$9:$AA$38,'UW Drivers'!$D$9:$D$38,$C$3) -> 0
C57: Natural Property Value | D57: - | F57: - | H57: - | J57: - | L57: - | N57: - | P57: - | R57: - | T57: - | V57: - | X57: - | Z57: - | AB57: - | AD57: - | AF57: - | AH57: - | AJ57: - | AL57: - | AN57: =IFERROR(ROUND(AN55/AN56,-4),0) -> 0 | AP57: =IFERROR(AN57/$AN$6,0) -> 0
C58: Expected Next Buyer CapEx | AN58: =SUMIFS('UW Drivers'!$AC$9:$AC$38,'UW Drivers'!$D$9:$D$38,$C$3)*$AN$6 -> 0 | AP58: =IFERROR(AN58/$AN$6,0) -> 0
C59: Net Property Value | D59: - | F59: - | H59: - | J59: - | L59: - | N59: - | P59: - | R59: - | T59: - | V59: - | X59: - | Z59: - | AB59: - | AD59: - | AF59: - | AH59: - | AJ59: - | AL59: - | AN59: =AN57-AN58 -> 0 | AP59: =IFERROR(AN59/$AN$6,0) -> 0
C64: Net Cash Flow | D64: =IFERROR(INDEX(Tape!$T$7:$ME$36,MATCH($C$3,Tape!$C$7:$C$36,0),MATCH($C64&"+"&D$5,Tape!$T$1:$ME$1,0)),0) -> 0 | H64: =IFERROR(INDEX(Tape!$T$7:$ME$36,MATCH($C$3,Tape!$C$7:$C$36,0),MATCH($C64&"+"&H$5,Tape!$T$1:$ME$1,0)),0) -> 0 | L64: =IFERROR(INDEX(Tape!$T$7:$ME$36,MATCH($C$3,Tape!$C$7:$C$36,0),MATCH($C64&"+"&L$5,Tape!$T$1:$ME$1,0)),0) -> 0 | P64: =IFERROR(INDEX(Tape!$T$7:$ME$36,MATCH($C$3,Tape!$C$7:$C$36,0),MATCH($C64&"+"&P$5,Tape!$T$1:$ME$1,0)),0) -> 0 | T64: =IFERROR(INDEX(Tape!$T$7:$ME$36,MATCH($C$3,Tape!$C$7:$C$36,0),MATCH($C64&"+"&T$5,Tape!$T$1:$ME$1,0)),0) -> 0 | X64: =IFERROR(INDEX(Tape!$T$7:$ME$36,MATCH($C$3,Tape!$C$7:$C$36,0),MATCH($C64&"+"&X$5,Tape!$T$1:$ME$1,0)),0) -> 0 | AB64: =IFERROR(INDEX(Tape!$T$7:$ME$36,MATCH($C$3,Tape!$C$7:$C$36,0),MATCH($C64&"+"&AB$5,Tape!$T$1:$ME$1,0)),0) -> 0 | AF64: =IFERROR(INDEX(Tape!$T$7:$ME$36,MATCH($C$3,Tape!$C$7:$C$36,0),MATCH($C64&"+"&AF$5,Tape!$T$1:$ME$1,0)),0) -> 0 | AJ64: =IFERROR(INDEX(Tape!$T$7:$ME$36,MATCH($C$3,Tape!$C$7:$C$36,0),MATCH($C64&"+"&AJ$5,Tape!$T$1:$ME$1,0)),0) -> 0
C65: ADD BACK: DISPLACEMENT | D65: =IFERROR(INDEX(Tape!$T$7:$ME$36,MATCH($C$3,Tape!$C$7:$C$36,0),MATCH($C65&"+"&D$5,Tape!$T$1:$ME$1,0)),0) -> 0 | H65: =IFERROR(INDEX(Tape!$T$7:$ME$36,MATCH($C$3,Tape!$C$7:$C$36,0),MATCH($C65&"+"&H$5,Tape!$T$1:$ME$1,0)),0) -> 0 | L65: =IFERROR(INDEX(Tape!$T$7:$ME$36,MATCH($C$3,Tape!$C$7:$C$36,0),MATCH($C65&"+"&L$5,Tape!$T$1:$ME$1,0)),0) -> 0 | P65: =IFERROR(INDEX(Tape!$T$7:$ME$36,MATCH($C$3,Tape!$C$7:$C$36,0),MATCH($C65&"+"&P$5,Tape!$T$1:$ME$1,0)),0) -> 0 | T65: =IFERROR(INDEX(Tape!$T$7:$ME$36,MATCH($C$3,Tape!$C$7:$C$36,0),MATCH($C65&"+"&T$5,Tape!$T$1:$ME$1,0)),0) -> 0 | X65: =IFERROR(INDEX(Tape!$T$7:$ME$36,MATCH($C$3,Tape!$C$7:$C$36,0),MATCH($C65&"+"&X$5,Tape!$T$1:$ME$1,0)),0) -> 0 | AB65: =IFERROR(INDEX(Tape!$T$7:$ME$36,MATCH($C$3,Tape!$C$7:$C$36,0),MATCH($C65&"+"&AB$5,Tape!$T$1:$ME$1,0)),0) -> 0 | AF65: =IFERROR(INDEX(Tape!$T$7:$ME$36,MATCH($C$3,Tape!$C$7:$C$36,0),MATCH($C65&"+"&AF$5,Tape!$T$1:$ME$1,0)),0) -> 0 | AJ65: =IFERROR(INDEX(Tape!$T$7:$ME$36,MATCH($C$3,Tape!$C$7:$C$36,0),MATCH($C65&"+"&AJ$5,Tape!$T$1:$ME$1,0)),0) -> 0
C66: CHECK | D66: =SUM(D64:D65)=D55 -> TRUE | H66: =SUM(H64:H65)=H55 -> TRUE | L66: =SUM(L64:L65)=L55 -> TRUE | P66: =SUM(P64:P65)=P55 -> TRUE | T66: =SUM(T64:T65)=T55 -> TRUE | X66: =SUM(X64:X65)=X55 -> TRUE | AB66: =SUM(AB64:AB65)=AB55 -> TRUE | AF66: =SUM(AF64:AF65)=AF55 -> TRUE | AJ66: =SUM(AJ64:AJ65)=AJ55 -> TRUE

Sheet 2
AB2: 2yr RevPAR Growth | AD2: =IFERROR((X11/P11)-1,0) -> 0
C3: =IF(INDEX(Tape!$C$7:$C$36,2)="","",INDEX(Tape!$C$7:$C$36,2)) | AB3: YOY RevPAR Growth | AD3: =IFERROR((X11/T11)-1,0) -> 0
D5: =Tape!$T$5 -> 2019 | H5: =Tape!$U$5 -> 2021 | L5: =Tape!$V$5 -> 2022 | P5: =Tape!$W$5 -> 2023 | T5: =Tape!$X$5 -> 2024 | X5: =Tape!$Y$5 -> 2025 | AB5: =Tape!$Z$5 -> TTM | AF5: =Tape!$AA$5 -> Reforecast | AJ5: =Tape!$AB$5 -> Lender UW | AN5: Sixth Street UW
C6: Keys | D6: =SUMIFS(Tape!$M$7:$M$36,Tape!$C$7:$C$36,$C$3) -> 0 | H6: =SUMIFS(Tape!$M$7:$M$36,Tape!$C$7:$C$36,$C$3) -> 0 | L6: =SUMIFS(Tape!$M$7:$M$36,Tape!$C$7:$C$36,$C$3) -> 0 | P6: =SUMIFS(Tape!$M$7:$M$36,Tape!$C$7:$C$36,$C$3) -> 0 | T6: =SUMIFS(Tape!$M$7:$M$36,Tape!$C$7:$C$36,$C$3) -> 0 | X6: =SUMIFS(Tape!$M$7:$M$36,Tape!$C$7:$C$36,$C$3) -> 0 | AB6: =SUMIFS(Tape!$M$7:$M$36,Tape!$C$7:$C$36,$C$3) -> 0 | AF6: =SUMIFS(Tape!$M$7:$M$36,Tape!$C$7:$C$36,$C$3) -> 0 | AJ6: =SUMIFS(Tape!$M$7:$M$36,Tape!$C$7:$C$36,$C$3) -> 0 | AN6: =AJ6 -> 0
C7: ROOMS AVAILABLE | D7: =IFERROR(INDEX(Tape!$T$7:$ME$36,MATCH($C$3,Tape!$C$7:$C$36,0),MATCH($C7&"+"&D$5,Tape!$T$1:$ME$1,0)),0) -> 0 | H7: =IFERROR(INDEX(Tape!$T$7:$ME$36,MATCH($C$3,Tape!$C$7:$C$36,0),MATCH($C7&"+"&H$5,Tape!$T$1:$ME$1,0)),0) -> 0 | L7: =IFERROR(INDEX(Tape!$T$7:$ME$36,MATCH($C$3,Tape!$C$7:$C$36,0),MATCH($C7&"+"&L$5,Tape!$T$1:$ME$1,0)),0) -> 0 | P7: =IFERROR(INDEX(Tape!$T$7:$ME$36,MATCH($C$3,Tape!$C$7:$C$36,0),MATCH($C7&"+"&P$5,Tape!$T$1:$ME$1,0)),0) -> 0 | T7: =IFERROR(INDEX(Tape!$T$7:$ME$36,MATCH($C$3,Tape!$C$7:$C$36,0),MATCH($C7&"+"&T$5,Tape!$T$1:$ME$1,0)),0) -> 0 | X7: =IFERROR(INDEX(Tape!$T$7:$ME$36,MATCH($C$3,Tape!$C$7:$C$36,0),MATCH($C7&"+"&X$5,Tape!$T$1:$ME$1,0)),0) -> 0 | AB7: =IFERROR(INDEX(Tape!$T$7:$ME$36,MATCH($C$3,Tape!$C$7:$C$36,0),MATCH($C7&"+"&AB$5,Tape!$T$1:$ME$1,0)),0) -> 0 | AF7: =IFERROR(INDEX(Tape!$T$7:$ME$36,MATCH($C$3,Tape!$C$7:$C$36,0),MATCH($C7&"+"&AF$5,Tape!$T$1:$ME$1,0)),0) -> 0 | AJ7: =IFERROR(INDEX(Tape!$T$7:$ME$36,MATCH($C$3,Tape!$C$7:$C$36,0),MATCH($C7&"+"&AJ$5,Tape!$T$1:$ME$1,0)),0) -> 0 | AN7: =AN6*365 -> 0
C8: ROOMS SOLD | D8: =IFERROR(INDEX(Tape!$T$7:$ME$36,MATCH($C$3,Tape!$C$7:$C$36,0),MATCH($C8&"+"&D$5,Tape!$T$1:$ME$1,0)),0) -> 0 | H8: =IFERROR(INDEX(Tape!$T$7:$ME$36,MATCH($C$3,Tape!$C$7:$C$36,0),MATCH($C8&"+"&H$5,Tape!$T$1:$ME$1,0)),0) -> 0 | L8: =IFERROR(INDEX(Tape!$T$7:$ME$36,MATCH($C$3,Tape!$C$7:$C$36,0),MATCH($C8&"+"&L$5,Tape!$T$1:$ME$1,0)),0) -> 0 | P8: =IFERROR(INDEX(Tape!$T$7:$ME$36,MATCH($C$3,Tape!$C$7:$C$36,0),MATCH($C8&"+"&P$5,Tape!$T$1:$ME$1,0)),0) -> 0 | T8: =IFERROR(INDEX(Tape!$T$7:$ME$36,MATCH($C$3,Tape!$C$7:$C$36,0),MATCH($C8&"+"&T$5,Tape!$T$1:$ME$1,0)),0) -> 0 | X8: =IFERROR(INDEX(Tape!$T$7:$ME$36,MATCH($C$3,Tape!$C$7:$C$36,0),MATCH($C8&"+"&X$5,Tape!$T$1:$ME$1,0)),0) -> 0 | AB8: =IFERROR(INDEX(Tape!$T$7:$ME$36,MATCH($C$3,Tape!$C$7:$C$36,0),MATCH($C8&"+"&AB$5,Tape!$T$1:$ME$1,0)),0) -> 0 | AF8: =IFERROR(INDEX(Tape!$T$7:$ME$36,MATCH($C$3,Tape!$C$7:$C$36,0),MATCH($C8&"+"&AF$5,Tape!$T$1:$ME$1,0)),0) -> 0 | AJ8: =IFERROR(INDEX(Tape!$T$7:$ME$36,MATCH($C$3,Tape!$C$7:$C$36,0),MATCH($C8&"+"&AJ$5,Tape!$T$1:$ME$1,0)),0) -> 0 | AN8: =AN9*AN7 -> 0
C9: OCCUPANCY | D9: =IFERROR(INDEX(Tape!$T$7:$ME$36,MATCH($C$3,Tape!$C$7:$C$36,0),MATCH($C9&"+"&D$5,Tape!$T$1:$ME$1,0)),0) -> 0 | H9: =IFERROR(INDEX(Tape!$T$7:$ME$36,MATCH($C$3,Tape!$C$7:$C$36,0),MATCH($C9&"+"&H$5,Tape!$T$1:$ME$1,0)),0) -> 0 | L9: =IFERROR(INDEX(Tape!$T$7:$ME$36,MATCH($C$3,Tape!$C$7:$C$36,0),MATCH($C9&"+"&L$5,Tape!$T$1:$ME$1,0)),0) -> 0 | P9: =IFERROR(INDEX(Tape!$T$7:$ME$36,MATCH($C$3,Tape!$C$7:$C$36,0),MATCH($C9&"+"&P$5,Tape!$T$1:$ME$1,0)),0) -> 0 | T9: =IFERROR(INDEX(Tape!$T$7:$ME$36,MATCH($C$3,Tape!$C$7:$C$36,0),MATCH($C9&"+"&T$5,Tape!$T$1:$ME$1,0)),0) -> 0 | X9: =IFERROR(INDEX(Tape!$T$7:$ME$36,MATCH($C$3,Tape!$C$7:$C$36,0),MATCH($C9&"+"&X$5,Tape!$T$1:$ME$1,0)),0) -> 0 | AB9: =IFERROR(INDEX(Tape!$T$7:$ME$36,MATCH($C$3,Tape!$C$7:$C$36,0),MATCH($C9&"+"&AB$5,Tape!$T$1:$ME$1,0)),0) -> 0 | AF9: =IFERROR(INDEX(Tape!$T$7:$ME$36,MATCH($C$3,Tape!$C$7:$C$36,0),MATCH($C9&"+"&AF$5,Tape!$T$1:$ME$1,0)),0) -> 0 | AJ9: =IFERROR(INDEX(Tape!$T$7:$ME$36,MATCH($C$3,Tape!$C$7:$C$36,0),MATCH($C9&"+"&AJ$5,Tape!$T$1:$ME$1,0)),0) -> 0 | AN9: =SUMIFS('UW Drivers'!$P$9:$P$38,'UW Drivers'!$D$9:$D$38,$C$3) -> 0
C10: ADR | D10: =IFERROR(INDEX(Tape!$T$7:$ME$36,MATCH($C$3,Tape!$C$7:$C$36,0),MATCH($C10&"+"&D$5,Tape!$T$1:$ME$1,0)),0) -> 0 | H10: =IFERROR(INDEX(Tape!$T$7:$ME$36,MATCH($C$3,Tape!$C$7:$C$36,0),MATCH($C10&"+"&H$5,Tape!$T$1:$ME$1,0)),0) -> 0 | L10: =IFERROR(INDEX(Tape!$T$7:$ME$36,MATCH($C$3,Tape!$C$7:$C$36,0),MATCH($C10&"+"&L$5,Tape!$T$1:$ME$1,0)),0) -> 0 | P10: =IFERROR(INDEX(Tape!$T$7:$ME$36,MATCH($C$3,Tape!$C$7:$C$36,0),MATCH($C10&"+"&P$5,Tape!$T$1:$ME$1,0)),0) -> 0 | T10: =IFERROR(INDEX(Tape!$T$7:$ME$36,MATCH($C$3,Tape!$C$7:$C$36,0),MATCH($C10&"+"&T$5,Tape!$T$1:$ME$1,0)),0) -> 0 | X10: =IFERROR(INDEX(Tape!$T$7:$ME$36,MATCH($C$3,Tape!$C$7:$C$36,0),MATCH($C10&"+"&X$5,Tape!$T$1:$ME$1,0)),0) -> 0 | AB10: =IFERROR(INDEX(Tape!$T$7:$ME$36,MATCH($C$3,Tape!$C$7:$C$36,0),MATCH($C10&"+"&AB$5,Tape!$T$1:$ME$1,0)),0) -> 0 | AF10: =IFERROR(INDEX(Tape!$T$7:$ME$36,MATCH($C$3,Tape!$C$7:$C$36,0),MATCH($C10&"+"&AF$5,Tape!$T$1:$ME$1,0)),0) -> 0 | AJ10: =IFERROR(INDEX(Tape!$T$7:$ME$36,MATCH($C$3,Tape!$C$7:$C$36,0),MATCH($C10&"+"&AJ$5,Tape!$T$1:$ME$1,0)),0) -> 0 | AN10: =SUMIFS('UW Drivers'!$Q$9:$Q$38,'UW Drivers'!$D$9:$D$38,$C$3) -> 0
C11: REVPAR | D11: =IFERROR(INDEX(Tape!$T$7:$ME$36,MATCH($C$3,Tape!$C$7:$C$36,0),MATCH($C11&"+"&D$5,Tape!$T$1:$ME$1,0)),0) -> 0 | H11: =IFERROR(INDEX(Tape!$T$7:$ME$36,MATCH($C$3,Tape!$C$7:$C$36,0),MATCH($C11&"+"&H$5,Tape!$T$1:$ME$1,0)),0) -> 0 | L11: =IFERROR(INDEX(Tape!$T$7:$ME$36,MATCH($C$3,Tape!$C$7:$C$36,0),MATCH($C11&"+"&L$5,Tape!$T$1:$ME$1,0)),0) -> 0 | P11: =IFERROR(INDEX(Tape!$T$7:$ME$36,MATCH($C$3,Tape!$C$7:$C$36,0),MATCH($C11&"+"&P$5,Tape!$T$1:$ME$1,0)),0) -> 0 | T11: =IFERROR(INDEX(Tape!$T$7:$ME$36,MATCH($C$3,Tape!$C$7:$C$36,0),MATCH($C11&"+"&T$5,Tape!$T$1:$ME$1,0)),0) -> 0 | X11: =IFERROR(INDEX(Tape!$T$7:$ME$36,MATCH($C$3,Tape!$C$7:$C$36,0),MATCH($C11&"+"&X$5,Tape!$T$1:$ME$1,0)),0) -> 0 | AB11: =IFERROR(INDEX(Tape!$T$7:$ME$36,MATCH($C$3,Tape!$C$7:$C$36,0),MATCH($C11&"+"&AB$5,Tape!$T$1:$ME$1,0)),0) -> 0 | AF11: =IFERROR(INDEX(Tape!$T$7:$ME$36,MATCH($C$3,Tape!$C$7:$C$36,0),MATCH($C11&"+"&AF$5,Tape!$T$1:$ME$1,0)),0) -> 0 | AJ11: =IFERROR(INDEX(Tape!$T$7:$ME$36,MATCH($C$3,Tape!$C$7:$C$36,0),MATCH($C11&"+"&AJ$5,Tape!$T$1:$ME$1,0)),0) -> 0 | AN11: =AN9*AN10 -> 0
C13: REVENUES | D13: $ | E13: % Total Rev. | F13: POR | G13: PAR | H13: $ | I13: % Total Rev. | J13: POR | K13: PAR | L13: $ | M13: % Total Rev. | N13: POR | O13: PAR | P13: $ | Q13: % Total Rev. | R13: POR | S13: PAR | T13: $ | U13: % Total Rev. | V13: POR | W13: PAR | X13: $ | Y13: % Total Rev. | Z13: POR | AA13: PAR | AB13: $ | AC13: % Total Rev. | AD13: POR | AE13: PAR | AF13: $ | AG13: % Total Rev. | AH13: POR | AI13: PAR | AJ13: $ | AK13: % Total Rev. | AL13: POR | AM13: PAR | AN13: $ | AO13: % Total Rev. | AP13: POR | AQ13: PAR
C14: Rooms Revenue | D14: =IFERROR(INDEX(Tape!$T$7:$ME$36,MATCH($C$3,Tape!$C$7:$C$36,0),MATCH($C14&"+"&D$5,Tape!$T$1:$ME$1,0)),0) -> 0 | E14: =IFERROR(D14/D$19,0) -> 0 | F14: =IFERROR(D14/D$8,0) -> 0 | G14: =IFERROR(D14/D$7,0) -> 0 | H14: =IFERROR(INDEX(Tape!$T$7:$ME$36,MATCH($C$3,Tape!$C$7:$C$36,0),MATCH($C14&"+"&H$5,Tape!$T$1:$ME$1,0)),0) -> 0 | I14: =IFERROR(H14/H$19,0) -> 0 | J14: =IFERROR(H14/H$8,0) -> 0 | K14: =IFERROR(H14/H$7,0) -> 0 | L14: =IFERROR(INDEX(Tape!$T$7:$ME$36,MATCH($C$3,Tape!$C$7:$C$36,0),MATCH($C14&"+"&L$5,Tape!$T$1:$ME$1,0)),0) -> 0 | M14: =IFERROR(L14/L$19,0) -> 0 | N14: =IFERROR(L14/L$8,0) -> 0 | O14: =IFERROR(L14/L$7,0) -> 0 | P14: =IFERROR(INDEX(Tape!$T$7:$ME$36,MATCH($C$3,Tape!$C$7:$C$36,0),MATCH($C14&"+"&P$5,Tape!$T$1:$ME$1,0)),0) -> 0 | Q14: =IFERROR(P14/P$19,0) -> 0 | R14: =IFERROR(P14/P$8,0) -> 0 | S14: =IFERROR(P14/P$7,0) -> 0 | T14: =IFERROR(INDEX(Tape!$T$7:$ME$36,MATCH($C$3,Tape!$C$7:$C$36,0),MATCH($C14&"+"&T$5,Tape!$T$1:$ME$1,0)),0) -> 0 | U14: =IFERROR(T14/T$19,0) -> 0 | V14: =IFERROR(T14/T$8,0) -> 0 | W14: =IFERROR(T14/T$7,0) -> 0 | X14: =IFERROR(INDEX(Tape!$T$7:$ME$36,MATCH($C$3,Tape!$C$7:$C$36,0),MATCH($C14&"+"&X$5,Tape!$T$1:$ME$1,0)),0) -> 0 | Y14: =IFERROR(X14/X$19,0) -> 0 | Z14: =IFERROR(X14/X$8,0) -> 0 | AA14: =IFERROR(X14/X$7,0) -> 0 | AB14: =IFERROR(INDEX(Tape!$T$7:$ME$36,MATCH($C$3,Tape!$C$7:$C$36,0),MATCH($C14&"+"&AB$5,Tape!$T$1:$ME$1,0)),0) -> 0 | AC14: =IFERROR(AB14/AB$19,0) -> 0 | AD14: =IFERROR(AB14/AB$8,0) -> 0 | AE14: =IFERROR(AB14/AB$7,0) -> 0 | AF14: =IFERROR(INDEX(Tape!$T$7:$ME$36,MATCH($C$3,Tape!$C$7:$C$36,0),MATCH($C14&"+"&AF$5,Tape!$T$1:$ME$1,0)),0) -> 0 | AG14: =IFERROR(AF14/AF$19,0) -> 0 | AH14: =IFERROR(AF14/AF$8,0) -> 0 | AI14: =IFERROR(AF14/AF$7,0) -> 0 | AJ14: =IFERROR(INDEX(Tape!$T$7:$ME$36,MATCH($C$3,Tape!$C$7:$C$36,0),MATCH($C14&"+"&AJ$5,Tape!$T$1:$ME$1,0)),0) -> 0 | AK14: =IFERROR(AJ14/AJ$19,0) -> 0 | AL14: =IFERROR(AJ14/AJ$8,0) -> 0 | AM14: =IFERROR(AJ14/AJ$7,0) -> 0 | AN14: =AN8*AN10 -> 0 | AO14: =IFERROR(AN14/AN$19,0) -> 0 | AP14: =IFERROR(AN14/AN$8,0) -> 0 | AQ14: =IFERROR(AN14/AN$7,0) -> 0
C15: Food & Beverage Revenue | D15: =IFERROR(INDEX(Tape!$T$7:$ME$36,MATCH($C$3,Tape!$C$7:$C$36,0),MATCH($C15&"+"&D$5,Tape!$T$1:$ME$1,0)),0) -> 0 | E15: =IFERROR(D15/D$19,0) -> 0 | F15: =IFERROR(D15/D$8,0) -> 0 | G15: =IFERROR(D15/D$7,0) -> 0 | H15: =IFERROR(INDEX(Tape!$T$7:$ME$36,MATCH($C$3,Tape!$C$7:$C$36,0),MATCH($C15&"+"&H$5,Tape!$T$1:$ME$1,0)),0) -> 0 | I15: =IFERROR(H15/H$19,0) -> 0 | J15: =IFERROR(H15/H$8,0) -> 0 | K15: =IFERROR(H15/H$7,0) -> 0 | L15: =IFERROR(INDEX(Tape!$T$7:$ME$36,MATCH($C$3,Tape!$C$7:$C$36,0),MATCH($C15&"+"&L$5,Tape!$T$1:$ME$1,0)),0) -> 0 | M15: =IFERROR(L15/L$19,0) -> 0 | N15: =IFERROR(L15/L$8,0) -> 0 | O15: =IFERROR(L15/L$7,0) -> 0 | P15: =IFERROR(INDEX(Tape!$T$7:$ME$36,MATCH($C$3,Tape!$C$7:$C$36,0),MATCH($C15&"+"&P$5,Tape!$T$1:$ME$1,0)),0) -> 0 | Q15: =IFERROR(P15/P$19,0) -> 0 | R15: =IFERROR(P15/P$8,0) -> 0 | S15: =IFERROR(P15/P$7,0) -> 0 | T15: =IFERROR(INDEX(Tape!$T$7:$ME$36,MATCH($C$3,Tape!$C$7:$C$36,0),MATCH($C15&"+"&T$5,Tape!$T$1:$ME$1,0)),0) -> 0 | U15: =IFERROR(T15/T$19,0) -> 0 | V15: =IFERROR(T15/T$8,0) -> 0 | W15: =IFERROR(T15/T$7,0) -> 0 | X15: =IFERROR(INDEX(Tape!$T$7:$ME$36,MATCH($C$3,Tape!$C$7:$C$36,0),MATCH($C15&"+"&X$5,Tape!$T$1:$ME$1,0)),0) -> 0 | Y15: =IFERROR(X15/X$19,0) -> 0 | Z15: =IFERROR(X15/X$8,0) -> 0 | AA15: =IFERROR(X15/X$7,0) -> 0 | AB15: =IFERROR(INDEX(Tape!$T$7:$ME$36,MATCH($C$3,Tape!$C$7:$C$36,0),MATCH($C15&"+"&AB$5,Tape!$T$1:$ME$1,0)),0) -> 0 | AC15: =IFERROR(AB15/AB$19,0) -> 0 | AD15: =IFERROR(AB15/AB$8,0) -> 0 | AE15: =IFERROR(AB15/AB$7,0) -> 0 | AF15: =IFERROR(INDEX(Tape!$T$7:$ME$36,MATCH($C$3,Tape!$C$7:$C$36,0),MATCH($C15&"+"&AF$5,Tape!$T$1:$ME$1,0)),0) -> 0 | AG15: =IFERROR(AF15/AF$19,0) -> 0 | AH15: =IFERROR(AF15/AF$8,0) -> 0 | AI15: =IFERROR(AF15/AF$7,0) -> 0 | AJ15: =IFERROR(INDEX(Tape!$T$7:$ME$36,MATCH($C$3,Tape!$C$7:$C$36,0),MATCH($C15&"+"&AJ$5,Tape!$T$1:$ME$1,0)),0) -> 0 | AK15: =IFERROR(AJ15/AJ$19,0) -> 0 | AL15: =IFERROR(AJ15/AJ$8,0) -> 0 | AM15: =IFERROR(AJ15/AJ$7,0) -> 0 | AN15: =AP15*AN$8 -> 0 | AO15: =IFERROR(AN15/AN$19,0) -> 0 | AP15: =AD15 -> 0 | AQ15: =IFERROR(AN15/AN$7,0) -> 0
C16: Other Departmental Revenue | D16: =IFERROR(INDEX(Tape!$T$7:$ME$36,MATCH($C$3,Tape!$C$7:$C$36,0),MATCH($C16&"+"&D$5,Tape!$T$1:$ME$1,0)),0) -> 0 | E16: =IFERROR(D16/D$19,0) -> 0 | F16: =IFERROR(D16/D$8,0) -> 0 | G16: =IFERROR(D16/D$7,0) -> 0 | H16: =IFERROR(INDEX(Tape!$T$7:$ME$36,MATCH($C$3,Tape!$C$7:$C$36,0),MATCH($C16&"+"&H$5,Tape!$T$1:$ME$1,0)),0) -> 0 | I16: =IFERROR(H16/H$19,0) -> 0 | J16: =IFERROR(H16/H$8,0) -> 0 | K16: =IFERROR(H16/H$7,0) -> 0 | L16: =IFERROR(INDEX(Tape!$T$7:$ME$36,MATCH($C$3,Tape!$C$7:$C$36,0),MATCH($C16&"+"&L$5,Tape!$T$1:$ME$1,0)),0) -> 0 | M16: =IFERROR(L16/L$19,0) -> 0 | N16: =IFERROR(L16/L$8,0) -> 0 | O16: =IFERROR(L16/L$7,0) -> 0 | P16: =IFERROR(INDEX(Tape!$T$7:$ME$36,MATCH($C$3,Tape!$C$7:$C$36,0),MATCH($C16&"+"&P$5,Tape!$T$1:$ME$1,0)),0) -> 0 | Q16: =IFERROR(P16/P$19,0) -> 0 | R16: =IFERROR(P16/P$8,0) -> 0 | S16: =IFERROR(P16/P$7,0) -> 0 | T16: =IFERROR(INDEX(Tape!$T$7:$ME$36,MATCH($C$3,Tape!$C$7:$C$36,0),MATCH($C16&"+"&T$5,Tape!$T$1:$ME$1,0)),0) -> 0 | U16: =IFERROR(T16/T$19,0) -> 0 | V16: =IFERROR(T16/T$8,0) -> 0 | W16: =IFERROR(T16/T$7,0) -> 0 | X16: =IFERROR(INDEX(Tape!$T$7:$ME$36,MATCH($C$3,Tape!$C$7:$C$36,0),MATCH($C16&"+"&X$5,Tape!$T$1:$ME$1,0)),0) -> 0 | Y16: =IFERROR(X16/X$19,0) -> 0 | Z16: =IFERROR(X16/X$8,0) -> 0 | AA16: =IFERROR(X16/X$7,0) -> 0 | AB16: =IFERROR(INDEX(Tape!$T$7:$ME$36,MATCH($C$3,Tape!$C$7:$C$36,0),MATCH($C16&"+"&AB$5,Tape!$T$1:$ME$1,0)),0) -> 0 | AC16: =IFERROR(AB16/AB$19,0) -> 0 | AD16: =IFERROR(AB16/AB$8,0) -> 0 | AE16: =IFERROR(AB16/AB$7,0) -> 0 | AF16: =IFERROR(INDEX(Tape!$T$7:$ME$36,MATCH($C$3,Tape!$C$7:$C$36,0),MATCH($C16&"+"&AF$5,Tape!$T$1:$ME$1,0)),0) -> 0 | AG16: =IFERROR(AF16/AF$19,0) -> 0 | AH16: =IFERROR(AF16/AF$8,0) -> 0 | AI16: =IFERROR(AF16/AF$7,0) -> 0 | AJ16: =IFERROR(INDEX(Tape!$T$7:$ME$36,MATCH($C$3,Tape!$C$7:$C$36,0),MATCH($C16&"+"&AJ$5,Tape!$T$1:$ME$1,0)),0) -> 0 | AK16: =IFERROR(AJ16/AJ$19,0) -> 0 | AL16: =IFERROR(AJ16/AJ$8,0) -> 0 | AM16: =IFERROR(AJ16/AJ$7,0) -> 0 | AN16: =AP16*AN$8 -> 0 | AO16: =IFERROR(AN16/AN$19,0) -> 0 | AP16: =AD16 -> 0 | AQ16: =IFERROR(AN16/AN$7,0) -> 0
C17: Parking Revenue | D17: =IFERROR(INDEX(Tape!$T$7:$ME$36,MATCH($C$3,Tape!$C$7:$C$36,0),MATCH($C17&"+"&D$5,Tape!$T$1:$ME$1,0)),0) -> 0 | E17: =IFERROR(D17/D$19,0) -> 0 | F17: =IFERROR(D17/D$8,0) -> 0 | G17: =IFERROR(D17/D$7,0) -> 0 | H17: =IFERROR(INDEX(Tape!$T$7:$ME$36,MATCH($C$3,Tape!$C$7:$C$36,0),MATCH($C17&"+"&H$5,Tape!$T$1:$ME$1,0)),0) -> 0 | I17: =IFERROR(H17/H$19,0) -> 0 | J17: =IFERROR(H17/H$8,0) -> 0 | K17: =IFERROR(H17/H$7,0) -> 0 | L17: =IFERROR(INDEX(Tape!$T$7:$ME$36,MATCH($C$3,Tape!$C$7:$C$36,0),MATCH($C17&"+"&L$5,Tape!$T$1:$ME$1,0)),0) -> 0 | M17: =IFERROR(L17/L$19,0) -> 0 | N17: =IFERROR(L17/L$8,0) -> 0 | O17: =IFERROR(L17/L$7,0) -> 0 | P17: =IFERROR(INDEX(Tape!$T$7:$ME$36,MATCH($C$3,Tape!$C$7:$C$36,0),MATCH($C17&"+"&P$5,Tape!$T$1:$ME$1,0)),0) -> 0 | Q17: =IFERROR(P17/P$19,0) -> 0 | R17: =IFERROR(P17/P$8,0) -> 0 | S17: =IFERROR(P17/P$7,0) -> 0 | T17: =IFERROR(INDEX(Tape!$T$7:$ME$36,MATCH($C$3,Tape!$C$7:$C$36,0),MATCH($C17&"+"&T$5,Tape!$T$1:$ME$1,0)),0) -> 0 | U17: =IFERROR(T17/T$19,0) -> 0 | V17: =IFERROR(T17/T$8,0) -> 0 | W17: =IFERROR(T17/T$7,0) -> 0 | X17: =IFERROR(INDEX(Tape!$T$7:$ME$36,MATCH($C$3,Tape!$C$7:$C$36,0),MATCH($C17&"+"&X$5,Tape!$T$1:$ME$1,0)),0) -> 0 | Y17: =IFERROR(X17/X$19,0) -> 0 | Z17: =IFERROR(X17/X$8,0) -> 0 | AA17: =IFERROR(X17/X$7,0) -> 0 | AB17: =IFERROR(INDEX(Tape!$T$7:$ME$36,MATCH($C$3,Tape!$C$7:$C$36,0),MATCH($C17&"+"&AB$5,Tape!$T$1:$ME$1,0)),0) -> 0 | AC17: =IFERROR(AB17/AB$19,0) -> 0 | AD17: =IFERROR(AB17/AB$8,0) -> 0 | AE17: =IFERROR(AB17/AB$7,0) -> 0 | AF17: =IFERROR(INDEX(Tape!$T$7:$ME$36,MATCH($C$3,Tape!$C$7:$C$36,0),MATCH($C17&"+"&AF$5,Tape!$T$1:$ME$1,0)),0) -> 0 | AG17: =IFERROR(AF17/AF$19,0) -> 0 | AH17: =IFERROR(AF17/AF$8,0) -> 0 | AI17: =IFERROR(AF17/AF$7,0) -> 0 | AJ17: =IFERROR(INDEX(Tape!$T$7:$ME$36,MATCH($C$3,Tape!$C$7:$C$36,0),MATCH($C17&"+"&AJ$5,Tape!$T$1:$ME$1,0)),0) -> 0 | AK17: =IFERROR(AJ17/AJ$19,0) -> 0 | AL17: =IFERROR(AJ17/AJ$8,0) -> 0 | AM17: =IFERROR(AJ17/AJ$7,0) -> 0 | AN17: =AP17*AN$8 -> 0 | AO17: =IFERROR(AN17/AN$19,0) -> 0 | AP17: =AD17 -> 0 | AQ17: =IFERROR(AN17/AN$7,0) -> 0
C18: Miscellaneous | D18: =IFERROR(INDEX(Tape!$T$7:$ME$36,MATCH($C$3,Tape!$C$7:$C$36,0),MATCH($C18&"+"&D$5,Tape!$T$1:$ME$1,0)),0) -> 0 | E18: =IFERROR(D18/D$19,0) -> 0 | F18: =IFERROR(D18/D$8,0) -> 0 | G18: =IFERROR(D18/D$7,0) -> 0 | H18: =IFERROR(INDEX(Tape!$T$7:$ME$36,MATCH($C$3,Tape!$C$7:$C$36,0),MATCH($C18&"+"&H$5,Tape!$T$1:$ME$1,0)),0) -> 0 | I18: =IFERROR(H18/H$19,0) -> 0 | J18: =IFERROR(H18/H$8,0) -> 0 | K18: =IFERROR(H18/H$7,0) -> 0 | L18: =IFERROR(INDEX(Tape!$T$7:$ME$36,MATCH($C$3,Tape!$C$7:$C$36,0),MATCH($C18&"+"&L$5,Tape!$T$1:$ME$1,0)),0) -> 0 | M18: =IFERROR(L18/L$19,0) -> 0 | N18: =IFERROR(L18/L$8,0) -> 0 | O18: =IFERROR(L18/L$7,0) -> 0 | P18: =IFERROR(INDEX(Tape!$T$7:$ME$36,MATCH($C$3,Tape!$C$7:$C$36,0),MATCH($C18&"+"&P$5,Tape!$T$1:$ME$1,0)),0) -> 0 | Q18: =IFERROR(P18/P$19,0) -> 0 | R18: =IFERROR(P18/P$8,0) -> 0 | S18: =IFERROR(P18/P$7,0) -> 0 | T18: =IFERROR(INDEX(Tape!$T$7:$ME$36,MATCH($C$3,Tape!$C$7:$C$36,0),MATCH($C18&"+"&T$5,Tape!$T$1:$ME$1,0)),0) -> 0 | U18: =IFERROR(T18/T$19,0) -> 0 | V18: =IFERROR(T18/T$8,0) -> 0 | W18: =IFERROR(T18/T$7,0) -> 0 | X18: =IFERROR(INDEX(Tape!$T$7:$ME$36,MATCH($C$3,Tape!$C$7:$C$36,0),MATCH($C18&"+"&X$5,Tape!$T$1:$ME$1,0)),0) -> 0 | Y18: =IFERROR(X18/X$19,0) -> 0 | Z18: =IFERROR(X18/X$8,0) -> 0 | AA18: =IFERROR(X18/X$7,0) -> 0 | AB18: =IFERROR(INDEX(Tape!$T$7:$ME$36,MATCH($C$3,Tape!$C$7:$C$36,0),MATCH($C18&"+"&AB$5,Tape!$T$1:$ME$1,0)),0) -> 0 | AC18: =IFERROR(AB18/AB$19,0) -> 0 | AD18: =IFERROR(AB18/AB$8,0) -> 0 | AE18: =IFERROR(AB18/AB$7,0) -> 0 | AF18: =IFERROR(INDEX(Tape!$T$7:$ME$36,MATCH($C$3,Tape!$C$7:$C$36,0),MATCH($C18&"+"&AF$5,Tape!$T$1:$ME$1,0)),0) -> 0 | AG18: =IFERROR(AF18/AF$19,0) -> 0 | AH18: =IFERROR(AF18/AF$8,0) -> 0 | AI18: =IFERROR(AF18/AF$7,0) -> 0 | AJ18: =IFERROR(INDEX(Tape!$T$7:$ME$36,MATCH($C$3,Tape!$C$7:$C$36,0),MATCH($C18&"+"&AJ$5,Tape!$T$1:$ME$1,0)),0) -> 0 | AK18: =IFERROR(AJ18/AJ$19,0) -> 0 | AL18: =IFERROR(AJ18/AJ$8,0) -> 0 | AM18: =IFERROR(AJ18/AJ$7,0) -> 0 | AN18: =AP18*AN$8 -> 0 | AO18: =IFERROR(AN18/AN$19,0) -> 0 | AP18: =AD18 -> 0 | AQ18: =IFERROR(AN18/AN$7,0) -> 0
C19: TOTAL REVENUES | D19: =SUM(D14:D18) -> 0 | E19: =IFERROR(D19/D$19,0) -> 0 | F19: =IFERROR(D19/D$8,0) -> 0 | G19: =IFERROR(D19/D$7,0) -> 0 | H19: =SUM(H14:H18) -> 0 | I19: =IFERROR(H19/H$19,0) -> 0 | J19: =IFERROR(H19/H$8,0) -> 0 | K19: =IFERROR(H19/H$7,0) -> 0 | L19: =SUM(L14:L18) -> 0 | M19: =IFERROR(L19/L$19,0) -> 0 | N19: =IFERROR(L19/L$8,0) -> 0 | O19: =IFERROR(L19/L$7,0) -> 0 | P19: =SUM(P14:P18) -> 0 | Q19: =IFERROR(P19/P$19,0) -> 0 | R19: =IFERROR(P19/P$8,0) -> 0 | S19: =IFERROR(P19/P$7,0) -> 0 | T19: =SUM(T14:T18) -> 0 | U19: =IFERROR(T19/T$19,0) -> 0 | V19: =IFERROR(T19/T$8,0) -> 0 | W19: =IFERROR(T19/T$7,0) -> 0 | X19: =SUM(X14:X18) -> 0 | Y19: =IFERROR(X19/X$19,0) -> 0 | Z19: =IFERROR(X19/X$8,0) -> 0 | AA19: =IFERROR(X19/X$7,0) -> 0 | AB19: =SUM(AB14:AB18) -> 0 | AC19: =IFERROR(AB19/AB$19,0) -> 0 | AD19: =IFERROR(AB19/AB$8,0) -> 0 | AE19: =IFERROR(AB19/AB$7,0) -> 0 | AF19: =SUM(AF14:AF18) -> 0 | AG19: =IFERROR(AF19/AF$19,0) -> 0 | AH19: =IFERROR(AF19/AF$8,0) -> 0 | AI19: =IFERROR(AF19/AF$7,0) -> 0 | AJ19: =SUM(AJ14:AJ18) -> 0 | AK19: =IFERROR(AJ19/AJ$19,0) -> 0 | AL19: =IFERROR(AJ19/AJ$8,0) -> 0 | AM19: =IFERROR(AJ19/AJ$7,0) -> 0 | AN19: =SUM(AN14:AN18) -> 0 | AO19: =IFERROR(AN19/AN$19,0) -> 0 | AP19: =IFERROR(AN19/AN$8,0) -> 0 | AQ19: =IFERROR(AN19/AN$7,0) -> 0
C21: DEPARTMENTAL EXPENSES
C22: Rooms Expense | D22: =IFERROR(INDEX(Tape!$T$7:$ME$36,MATCH($C$3,Tape!$C$7:$C$36,0),MATCH($C22&"+"&D$5,Tape!$T$1:$ME$1,0)),0) -> 0 | E22: =IFERROR(D22/D14,0) -> 0 | F22: =IFERROR(D22/D$8,0) -> 0 | G22: =IFERROR(D22/D$7,0) -> 0 | H22: =IFERROR(INDEX(Tape!$T$7:$ME$36,MATCH($C$3,Tape!$C$7:$C$36,0),MATCH($C22&"+"&H$5,Tape!$T$1:$ME$1,0)),0) -> 0 | I22: =IFERROR(H22/H14,0) -> 0 | J22: =IFERROR(H22/H$8,0) -> 0 | K22: =IFERROR(H22/H$7,0) -> 0 | L22: =IFERROR(INDEX(Tape!$T$7:$ME$36,MATCH($C$3,Tape!$C$7:$C$36,0),MATCH($C22&"+"&L$5,Tape!$T$1:$ME$1,0)),0) -> 0 | M22: =IFERROR(L22/L14,0) -> 0 | N22: =IFERROR(L22/L$8,0) -> 0 | O22: =IFERROR(L22/L$7,0) -> 0 | P22: =IFERROR(INDEX(Tape!$T$7:$ME$36,MATCH($C$3,Tape!$C$7:$C$36,0),MATCH($C22&"+"&P$5,Tape!$T$1:$ME$1,0)),0) -> 0 | Q22: =IFERROR(P22/P14,0) -> 0 | R22: =IFERROR(P22/P$8,0) -> 0 | S22: =IFERROR(P22/P$7,0) -> 0 | T22: =IFERROR(INDEX(Tape!$T$7:$ME$36,MATCH($C$3,Tape!$C$7:$C$36,0),MATCH($C22&"+"&T$5,Tape!$T$1:$ME$1,0)),0) -> 0 | U22: =IFERROR(T22/T14,0) -> 0 | V22: =IFERROR(T22/T$8,0) -> 0 | W22: =IFERROR(T22/T$7,0) -> 0 | X22: =IFERROR(INDEX(Tape!$T$7:$ME$36,MATCH($C$3,Tape!$C$7:$C$36,0),MATCH($C22&"+"&X$5,Tape!$T$1:$ME$1,0)),0) -> 0 | Y22: =IFERROR(X22/X14,0) -> 0 | Z22: =IFERROR(X22/X$8,0) -> 0 | AA22: =IFERROR(X22/X$7,0) -> 0 | AB22: =IFERROR(INDEX(Tape!$T$7:$ME$36,MATCH($C$3,Tape!$C$7:$C$36,0),MATCH($C22&"+"&AB$5,Tape!$T$1:$ME$1,0)),0) -> 0 | AC22: =IFERROR(AB22/AB14,0) -> 0 | AD22: =IFERROR(AB22/AB$8,0) -> 0 | AE22: =IFERROR(AB22/AB$7,0) -> 0 | AF22: =IFERROR(INDEX(Tape!$T$7:$ME$36,MATCH($C$3,Tape!$C$7:$C$36,0),MATCH($C22&"+"&AF$5,Tape!$T$1:$ME$1,0)),0) -> 0 | AG22: =IFERROR(AF22/AF14,0) -> 0 | AH22: =IFERROR(AF22/AF$8,0) -> 0 | AI22: =IFERROR(AF22/AF$7,0) -> 0 | AJ22: =IFERROR(INDEX(Tape!$T$7:$ME$36,MATCH($C$3,Tape!$C$7:$C$36,0),MATCH($C22&"+"&AJ$5,Tape!$T$1:$ME$1,0)),0) -> 0 | AK22: =IFERROR(AJ22/AJ14,0) -> 0 | AL22: =IFERROR(AJ22/AJ$8,0) -> 0 | AM22: =IFERROR(AJ22/AJ$7,0) -> 0 | AN22: =AO22*AN14 -> 0 | AO22: =AC22 -> 0 | AP22: =IFERROR(AN22/AN$8,0) -> 0 | AQ22: =IFERROR(AN22/AN$7,0) -> 0
