Workbook

Sheet Cover
B4: SSP LOAN POOL MODEL
B6: Stratification package, individual loan runs and levered returns
B8: Illustrative sample loan tape. Replace with the live deal data.
B12: HOW THE MODEL WORKS
B13: • | C13: The Loan Tape is the single source of data. Nothing else on the model holds loan level hardcodes.
B14: • | C14: The Assumptions tab holds every lever. One scenario switch moves purchase price, advance rate, financing spread, credit, prepayment and the index curve together.
B15: • | C15: The Loan CF tab runs each loan on its own through an annual cash flow, so the pool result is the sum of the individual loan runs rather than a weighted average approximation.
B16: • | C16: The Loan Runs tab shows the outcome of each loan run side by side and aggregates them. The Pool Returns tab layers pool level fees and the financing facility on top to give the levered equity return.
B17: • | C17: Six tie out checks at the foot of the Pool Returns tab prove the aggregation, the sources and uses and the balance roll forward.
B19: CONTENTS
B20: Tab | D20: What it does | E20: Type
B21: Assumptions | D21: Every lever in one place. Scenario grid with a downside, base and upside column and a single switch that drives the whole model, plus the forward index curve. | E21: Input
B22: Loan Tape | D22: Loan level data for up to 300 loans. Columns A to AM are the strat feed. Columns AN to BE are the pricing and financing feed the returns engine reads. | E22: Input and calculation
B23: Strats | D23: Portfolio wide stratification package across 27 dimensions with tie out checks. Unchanged in structure from the original build. | E23: Output
B24: Deal Strat | D24: The same package filtered to one underlying deal, selected on that tab. | E24: Output
B25: Loan Runs | D25: One row per loan: purchase price, basis, collections, credit loss, unlevered and levered IRR and MOIC, with a total and weighted average row. Includes a single loan drill down. | E25: Output
B26: Loan CF | D26: The engine. Annual cash flows for every loan, one block per line item, from beginning balance through levered equity cash flow. | E26: Calculation
B27: Pool Returns | D27: Sources and uses at close, the aggregated pool cash flow, unlevered and levered returns, three sensitivity grids and six tie out checks. | E27: Output
B29: LEGEND, FONT COLOR SHOWS HOW A NUMBER GOT INTO A CELL
B30: Color | D30: Meaning
B31: Green text | C31: 1,234 | D31: Hardcoded input typed on that sheet. These are the only cells to change.
B32: Blue text | C32: 1,234 | D32: Link to another cell or another tab.
B33: Purple text | C33: 1,234 | D33: Hardcode carried in from another schedule.
B34: Black text | C34: 1,234 | D34: Calculated on that sheet.
B36: LEGEND, FILL COLOR
B37: Color | D37: Meaning
B38: Dark navy | D38: Header rows, banner bars and total or weighted average rows.
B39: Light blue | D39: Section labels, the active case column and the live cell in a sensitivity grid.
B40: Light gray | D40: Row banding and label columns.
B41: Light red | D41: Downside sensitivity cells and failed checks.
B42: Light green | D42: Upside sensitivity cells and passed checks.
B45: Source: loan level fields are the illustrative sample tape carried over from the original strats file. Purchase price, financing terms, credit and prepayment assumptions are user inputs and carry no external source. Replace the forward index curve on the Assumptions tab with the live curve at pricing.

Sheet Assumptions
B2: TRANSACTION, FINANCING AND RETURN ASSUMPTIONS
B4: Active Scenario (1 = Downside, 2 = Base, 3 = Upside) | C4: 2
B5: Active Scenario | C5: =CHOOSE(Scen,"Downside","Base","Upside") -> Base
B6: Green cells are inputs. Black cells are calculated. Blue cells link to another tab. Every assumption below feeds the loan level engine on the Loan CF tab.
B8: Assumption | C8: Downside | D8: Base | E8: Upside | F8: Active Case | H8: Basis and Note
B9: TRANSACTION AND POOL SCOPE
B10: As-Of / Settlement Date | C10: n/a | D10: 46295 | E10: n/a | F10: =D10 -> 46295 | H10: Drives seasoning, remaining term and the strat tie outs on the Strats tab.
B11: Deal Scope Purchased | C11: n/a | D11: All Deals | E11: n/a | F11: =D11 -> All Deals | H11: All Deals buys the entire tape. Selecting a single deal restricts the purchase to that deal and reprices the pool accordingly.
B12: Hold Period (Years, integer 1 to 10) | C12: 5 | D12: 5 | E12: 5 | F12: =CHOOSE(Scen,C12,D12,E12) -> 5 | H12: Sets the exit year. Residual balance is sold at the exit price in this year.
B13: Purchase Price (% of Par) | C13: 0.9 | D13: 0.94 | E13: 0.97 | F13: =CHOOSE(Scen,C13,D13,E13) -> 0.94 | H13: Applied to Current UPB on every loan in scope. Discount to par accretes through the hold period.
B14: Accrued Interest Purchased (% of Par) | C14: n/a | D14: 0.0015 | E14: n/a | F14: =D14 -> 0.0015 | H14: Day count accrual paid to the seller at settlement. Part of basis, not of purchase price.
B15: Acquisition and Diligence Costs (% of Purchase Price) | C15: n/a | D15: 0.0075 | E15: n/a | F15: =D15 -> 0.0075 | H15: Legal, third party reports, servicer onboarding and transfer costs.
B16: Exit Price (% of Par on Residual Balance) | C16: 0.93 | D16: 0.97 | E16: 1 | F16: =CHOOSE(Scen,C16,D16,E16) -> 0.97 | H16: Applied to the performing balance still outstanding at the end of the hold period.
B17: Exit / Disposition Costs (% of Exit Proceeds) | C17: n/a | D17: 0.005 | E17: n/a | F17: =D17 -> 0.005 | H17: Broker, legal and transfer costs on the residual sale.
B18: FINANCING STRUCTURE
B19: Financing Used (Yes / No) | C19: n/a | D19: Yes | E19: n/a | F19: =D19 -> Yes | H19: Set to No for an all equity purchase. Levered and unlevered returns converge when this is No.
B20: Financing Structure | C20: n/a | D20: Repo Facility | E20: n/a | F20: =D20 -> Repo Facility | H20: Label only. The economics are driven by advance rate, spread, fees and sweep below.
B21: Advance Rate (% of Purchase Price) | C21: 0.5 | D21: 0.6 | E21: 0.65 | F21: =CHOOSE(Scen,C21,D21,E21) -> 0.6 | H21: Facility size at close. Advance is struck off purchase price, not par.
B22: Financing Spread over Index (bps) | C22: 325 | D22: 250 | E22: 225 | F22: =CHOOSE(Scen,C22,D22,E22) -> 250 | H22: Added to the active index curve to give the all in cost of debt by year.
B23: Upfront Financing Fee (% of Facility) | C23: n/a | D23: 0.005 | E23: n/a | F23: =D23 -> 0.005 | H23: Structuring and commitment fee funded at close out of equity.
B24: Exit / Termination Fee (% of Facility) | C24: n/a | D24: 0.0025 | E24: n/a | F24: =D24 -> 0.0025 | H24: Charged on facility amounts as they are repaid, so the whole fee is paid by the time the facility is retired.
B25: Cash Sweep to Debt (% of Principal Collections) | C25: 1 | D25: 1 | E25: 0.85 | F25: =CHOOSE(Scen,C25,D25,E25) -> 1 | H25: Share of principal, payoff and recovery proceeds applied to the facility before equity is released.
B26: Financing Term (Years) | C26: n/a | D26: 5 | E26: n/a | F26: =D26 -> 5 | H26: Facility must be fully repaid by the earlier of this year and the hold period.
B27: Debt Repayment Year (Model) | C27: n/a | D27: n/a | E27: n/a | F27: =MIN(Hold_Yrs,Fin_Term) -> 5 | H27: The facility is swept to zero in this year and the exit fee is charged.
B28: All in Cost of Debt, Year 1 (%) | C28: n/a | D28: n/a | E28: n/a | F28: =IF(Fin_Flag="Yes",INDEX(Fin_Curve,1,1),0) -> 0.07 | H28: Active index curve in Year 1 plus the financing spread.
B29: FEES AND ONGOING COSTS
B30: Servicing and Special Servicing Fee (bps on Avg. Balance) | C30: n/a | D30: 15 | E30: n/a | F30: =D30 -> 15 | H30: Charged at the pool level on the average performing balance each year.
B31: Asset Management Fee (bps on Invested Equity) | C31: n/a | D31: 100 | E31: n/a | F31: =D31 -> 100 | H31: Charged at the pool level on equity funded at close for each year of the hold period.
B32: Annual Fixed and Administrative Costs ($) | C32: n/a | D32: 250000 | E32: n/a | F32: =D32 -> 250000 | H32: Audit, admin, custody and reporting. Charged at the pool level.
B33: CREDIT
B34: CDR, Annual Default Rate (% of Performing Balance) | C34: 0.04 | D34: 0.02 | E34: 0.01 | F34: =CHOOSE(Scen,C34,D34,E34) -> 0.02 | H34: Applied to the beginning performing balance of each loan each year.
B35: Loss Severity (% of Defaulted Balance) | C35: 0.45 | D35: 0.3 | E35: 0.2 | F35: =CHOOSE(Scen,C35,D35,E35) -> 0.3 | H35: One minus severity is recovered in cash after the recovery lag below.
B36: Recovery Lag (Years, integer) | C36: n/a | D36: 1 | E36: n/a | F36: =D36 -> 1 | H36: Whole years between default and receipt of recovery proceeds. Recoveries still in the pipeline at exit are valued in the exit proceeds.
B37: PREPAYMENT AND EXTENSION
B38: CPR, Annual Prepayment Rate (% of Performing Balance) | C38: 0.05 | D38: 0.1 | E38: 0.15 | F38: =CHOOSE(Scen,C38,D38,E38) -> 0.1 | H38: Voluntary prepayment on the performing balance in each year before maturity.
B39: Prepayment Penalty Captured (% of Prepaid Balance) | C39: n/a | D39: 0.01 | E39: n/a | F39: =D39 -> 0.01 | H39: Blended yield maintenance and exit fee capture across the tape.
B40: Assume Extension Options Exercised (Yes / No) | C40: n/a | D40: Yes | E40: n/a | F40: =D40 -> Yes | H40: When Yes, every loan flagged with an extension option in the tape gets the extension length added to its remaining term.
B41: Extension Length (Months) | C41: n/a | D41: 12 | E41: n/a | F41: =D41 -> 12 | H41: Added to remaining term for loans with an extension option.
B42: AMORTIZATION
B43: Assumed Amortization Term for Amortizing Loans (Years) | C43: n/a | D43: 30 | E43: n/a | F43: =D43 -> 30 | H43: Full amortizing and partial IO loans amortize on this schedule once the IO period rolls off.
B44: Minimum Amortization Term Remaining (Years) | C44: n/a | D44: 5 | E44: n/a | F44: =D44 -> 5 | H44: Floor on the remaining amortization term so seasoned loans do not amortize implausibly fast.
B45: INDEX CURVE
B46: Scenario Index Shift (bps, parallel) | C46: 100 | D46: 0 | E46: -75 | F46: =CHOOSE(Scen,C46,D46,E46) -> 0 | H46: Parallel shift applied to the input forward curve below. Floating rate loans and the facility both reprice.
B48: FORWARD INDEX CURVE AND ALL IN COST OF DEBT
B49: Curve | C49: 1 | D49: 2 | E49: 3 | F49: 4 | G49: 5 | H49: 6 | I49: 7 | J49: 8 | K49: 9 | L49: 10
B50: Forward Index, Input Curve (%) | C50: 0.045 | D50: 0.04 | E50: 0.036 | F50: 0.034 | G50: 0.033 | H50: 0.033 | I50: 0.033 | J50: 0.033 | K50: 0.033 | L50: 0.033
B51: Active Index Curve (%) | C51: =MAX(0,C50+Idx_Shift/10000) -> 0.045 | D51: =MAX(0,D50+Idx_Shift/10000) -> 0.04 | E51: =MAX(0,E50+Idx_Shift/10000) -> 0.036 | F51: =MAX(0,F50+Idx_Shift/10000) -> 0.034 | G51: =MAX(0,G50+Idx_Shift/10000) -> 0.033 | H51: =MAX(0,H50+Idx_Shift/10000) -> 0.033 | I51: =MAX(0,I50+Idx_Shift/10000) -> 0.033 | J51: =MAX(0,J50+Idx_Shift/10000) -> 0.033 | ... L51: =MAX(0,L50+Idx_Shift/10000) -> 0.033
B52: All in Cost of Debt Curve (%) | C52: =C51+Fin_Spread/10000 -> 0.07 | D52: =D51+Fin_Spread/10000 -> 0.065 | E52: =E51+Fin_Spread/10000 -> 0.061 | F52: =F51+Fin_Spread/10000 -> 0.059 | G52: =G51+Fin_Spread/10000 -> 0.058 | H52: =H51+Fin_Spread/10000 -> 0.058 | I52: =I51+Fin_Spread/10000 -> 0.058 | J52: =J51+Fin_Spread/10000 -> 0.058 | ... L52: =L51+Fin_Spread/10000 -> 0.058
B54: Source: forward Term SOFR input curve is a user assumption. Replace the green input row with the live forward curve at pricing.

Sheet Loan Tape
A1: LOAN TAPE — [NEW DEAL NAME] (illustrative sample data shown)
A2: Rows 4-53 below are 50 illustrative sample loans for demonstration only — replace with your new deal's actual loan-level data. Green cells are hardcoded inputs; black cells are formulas (Seasoning, Coupon (Current), IO Remaining, Coupon at Reset) — leave them as is. If a loan sits in more than one underlying deal, tag it in the Underlying Deal column, then relabel the placeholder deal names on the Strats tab. | AN2: Columns AN to BE are the pricing and financing engine feed. Every one is a formula driven by the Assumptions tab. Do not type over them.
A3: Loan ID | B3: Loan / Property Name | C3: State | D3: Property Type | E3: Underlying Deal | F3: Number of Units | G3: Origination Date | H3: Maturity Date | I3: Original Term (Months) | J3: IO Term (Months) | K3: Rate Type | L3: Fixed Coupon (if Fixed) | M3: Floating Rate Spread | N3: Reset Frequency | O3: Next Reset Date | P3: Rate Cap (if Floating) | Q3: Rate Floor (if Floating) | R3: Current UPB | S3: Occupancy | T3: NOI Debt Yield (Most Recent) | U3: DSCR (Most Recent) | V3: LTV (Most Recent) | W3: SSP / Underwritten LTV | X3: Year Built | Y3: Year Renovated | Z3: Amortization Type | AA3: Extension Option | AB3: Prepayment Protection | AC3: Lien Position | AD3: Sponsor Type | AE3: Loan Purpose | AF3: Delinquency Status | AG3: Ownership Interest | AH3: Seasoning (Months) | AI3: Coupon (Current) | AJ3: IO Remaining (Months) | AK3: Coupon at Reset (Stress) | AL3: Rank within Selected Deal | AM3: Rank (by UPB) | AN3: Include in Purchase (1 / 0) | AO3: Purchase Price (% of Par) | AP3: Remaining Term to Maturity (Mos) | AQ3: Extension Months Added | AR3: Effective Term (Mos) | AS3: Effective Term (Yrs) | AT3: IO Remaining (Yrs) | AU3: Amort. Term Remaining (Yrs) | AV3: Model End Year (Maturity vs. Hold) | AW3: Maturity Year (Model) | AX3: Matures within Hold (1 / 0) | AY3: Purchase Price ($) | AZ3: Accrued Interest ($) | BA3: Acquisition Costs ($) | BB3: Total Basis ($) | BC3: Debt Allocated ($) | BD3: Financing Fees ($) | BE3: Equity Allocated ($)
A4: L-001 | B4: Oceanview Plaza | C4: TX | D4: Retail | E4: Deal 4 | G4: 42826 | H4: 45383 | I4: 83 | J4: 24 | K4: Floating | M4: 0.0373 | N4: Monthly | O4: 46325 | P4: 0.0956 | R4: 8155000 | S4: 0.99 | T4: 0.0792 | U4: 1.38 | V4: 0.556 | W4: 0.574 | X4: 2013 | Y4: 2020 | Z4: Partial IO | AA4: Yes | AB4: Freely Prepayable | AC4: First Lien | AD4: PE Fund | AE4: Acquisition | AF4: Current | AG4: Fee Simple | AH4: =IF(G4="",0,ROUND((Strats!$C$4-G4)/30.4375,1)) -> 114 | AI4: =IF(K4="",0,IF(K4="Floating",Strats!$C$10+M4,L4)) -> 0.0823 | AJ4: =IF(OR(Z4="",Z4="Full Amortizing"),"",MAX(J4-AH4,0)) -> 0 | AK4: =IF(K4="",0,IF(K4="Floating",IF(P4<>"",MIN(IF(Q4<>"",MAX((Strats!$C$10+Strats!$C$11+M4),Q4),(Strats!$C$10+Strats!$C$11+M4)),P4),IF(Q4<>"",MAX((Strats!$C$10+Strats!$C$11+M4),Q4),(Strats!$C$10+Strats!$C$11+M4))),AI4)) -> 0.0956 | AL4: =IF(OR(E4="",E4<>'Deal Strat'!$C$12,R4=""),"",SUMPRODUCT((E$4:E$303='Deal Strat'!$C$12)*(R$4:R$303>R4))+1+SUMPRODUCT((E$4:E$303='Deal Strat'!$C$12)*(R$4:R$303=R4)*(ROW(R$4:R$303)<ROW(R4)))) | AM4: =IF(R4="","",RANK(R4,$R$4:$R$303,0)+COUNTIF($R$4:R4,R4)-1) -> 42 | AN4: =IF(OR($A4="",$R4=""),0,IF(Deal_Scope="All Deals",1,IF($E4=Deal_Scope,1,0))) -> 1 | AO4: =IF($AN4=0,0,Px_Par) -> 0.94 | AP4: =IF($H4="",0,MAX(0,($H4-Set_Date)/30.4375)) -> 0 | AQ4: =IF(AND(Ext_Flag="Yes",$AA4="Yes"),Ext_Months,0) -> 12 | AR4: =$AP4+$AQ4 -> 12 | AS4: =$AR4/12 -> 1 | AT4: =IF($AJ4="",0,MAX(0,$AJ4/12)) -> 0 | AU4: =MAX(Amort_Min,Amort_Term-$AH4/12) -> 20.5 | AV4: =MIN($AS4,Hold_Yrs) -> 1 | AW4: =IF($AN4=0,0,CEILING(MAX($AS4,0.0001),1)) -> 1 | AX4: =IF(AND($AN4=1,MAX($AS4,0.0001)<=Hold_Yrs),1,0) -> 1 | AY4: =$R4*$AO4 -> 7665700 | AZ4: =$R4*Acc_Int*$AN4 -> 12232.5 | BA4: =$AY4*Acq_Cost -> 57492.75 | BB4: =$AY4+$AZ4+$BA4 -> 7735425.2 | BC4: =IF(Fin_Flag="Yes",$AY4*Adv_Rate,0) -> 4599420 | BD4: =$BC4*Fin_UpFee -> 22997.1 | BE4: =$BB4-$BC4+$BD4 -> 3159002.4
A5: L-002 | B5: Chandler Resort | C5: FL | D5: Hotel | E5: Deal 6 | G5: 42917 | H5: 46569 | I5: 121 | J5: 36 | K5: Floating | M5: 0.0224 | N5: Monthly | O5: 46355 | P5: 0.1078 | R5: 10687000 | S5: 0.857 | T5: 0.0834 | U5: 1.21 | V5: 0.589 | W5: 0.618 | X5: 2005 | Z5: Partial IO | AA5: Yes | AB5: Prepayable with Penalty | AC5: First Lien | AD5: PE Fund | AE5: Refinance | AF5: Current | AG5: Fee Simple | AH5: =IF(G5="",0,ROUND((Strats!$C$4-G5)/30.4375,1)) -> 111 | AI5: =IF(K5="",0,IF(K5="Floating",Strats!$C$10+M5,L5)) -> 0.0674 | AJ5: =IF(OR(Z5="",Z5="Full Amortizing"),"",MAX(J5-AH5,0)) -> 0 | AK5: =IF(K5="",0,IF(K5="Floating",IF(P5<>"",MIN(IF(Q5<>"",MAX((Strats!$C$10+Strats!$C$11+M5),Q5),(Strats!$C$10+Strats!$C$11+M5)),P5),IF(Q5<>"",MAX((Strats!$C$10+Strats!$C$11+M5),Q5),(Strats!$C$10+Strats!$C$11+M5))),AI5)) -> 0.0824 | AL5: =IF(OR(E5="",E5<>'Deal Strat'!$C$12,R5=""),"",SUMPRODUCT((E$4:E$303='Deal Strat'!$C$12)*(R$4:R$303>R5))+1+SUMPRODUCT((E$4:E$303='Deal Strat'!$C$12)*(R$4:R$303=R5)*(ROW(R$4:R$303)<ROW(R5)))) | AM5: =IF(R5="","",RANK(R5,$R$4:$R$303,0)+COUNTIF($R$4:R5,R5)-1) -> 38 | AN5: =IF(OR($A5="",$R5=""),0,IF(Deal_Scope="All Deals",1,IF($E5=Deal_Scope,1,0))) -> 1 | AO5: =IF($AN5=0,0,Px_Par) -> 0.94 | AP5: =IF($H5="",0,MAX(0,($H5-Set_Date)/30.4375)) -> 9.0020534 | AQ5: =IF(AND(Ext_Flag="Yes",$AA5="Yes"),Ext_Months,0) -> 12 | AR5: =$AP5+$AQ5 -> 21.002053 | AS5: =$AR5/12 -> 1.7501711 | AT5: =IF($AJ5="",0,MAX(0,$AJ5/12)) -> 0 | AU5: =MAX(Amort_Min,Amort_Term-$AH5/12) -> 20.75 | AV5: =MIN($AS5,Hold_Yrs) -> 1.7501711 | AW5: =IF($AN5=0,0,CEILING(MAX($AS5,0.0001),1)) -> 2 | AX5: =IF(AND($AN5=1,MAX($AS5,0.0001)<=Hold_Yrs),1,0) -> 1 | AY5: =$R5*$AO5 -> 10045780 | AZ5: =$R5*Acc_Int*$AN5 -> 16030.5 | BA5: =$AY5*Acq_Cost -> 75343.35 | BB5: =$AY5+$AZ5+$BA5 -> 10137154 | BC5: =IF(Fin_Flag="Yes",$AY5*Adv_Rate,0) -> 6027468 | BD5: =$BC5*Fin_UpFee -> 30137.34 | BE5: =$BB5-$BC5+$BD5 -> 4139823.2
A6: L-003 | B6: Deerfield Terrace | C6: CO | D6: Multifamily | E6: Deal 7 | F6: 409 | G6: 44713 | H6: 47270 | I6: 84 | J6: 12 | K6: Floating | M6: 0.0384 | N6: Quarterly | O6: 46295 | R6: 119229000 | S6: 0.871 | T6: 0.036 | U6: 1.41 | V6: 0.931 | W6: 0.967 | X6: 2000 | Z6: Partial IO | AA6: Yes | AB6: Defeasance | AC6: First Lien | AD6: Institutional Owner/Operator | AE6: Acquisition | AF6: Current | AG6: Fee Simple | AH6: =IF(G6="",0,ROUND((Strats!$C$4-G6)/30.4375,1)) -> 52 | AI6: =IF(K6="",0,IF(K6="Floating",Strats!$C$10+M6,L6)) -> 0.0834 | AJ6: =IF(OR(Z6="",Z6="Full Amortizing"),"",MAX(J6-AH6,0)) -> 0 | AK6: =IF(K6="",0,IF(K6="Floating",IF(P6<>"",MIN(IF(Q6<>"",MAX((Strats!$C$10+Strats!$C$11+M6),Q6),(Strats!$C$10+Strats!$C$11+M6)),P6),IF(Q6<>"",MAX((Strats!$C$10+Strats!$C$11+M6),Q6),(Strats!$C$10+Strats!$C$11+M6))),AI6)) -> 0.0984 | AL6: =IF(OR(E6="",E6<>'Deal Strat'!$C$12,R6=""),"",SUMPRODUCT((E$4:E$303='Deal Strat'!$C$12)*(R$4:R$303>R6))+1+SUMPRODUCT((E$4:E$303='Deal Strat'!$C$12)*(R$4:R$303=R6)*(ROW(R$4:R$303)<ROW(R6)))) | AM6: =IF(R6="","",RANK(R6,$R$4:$R$303,0)+COUNTIF($R$4:R6,R6)-1) -> 5 | AN6: =IF(OR($A6="",$R6=""),0,IF(Deal_Scope="All Deals",1,IF($E6=Deal_Scope,1,0))) -> 1 | AO6: =IF($AN6=0,0,Px_Par) -> 0.94 | AP6: =IF($H6="",0,MAX(0,($H6-Set_Date)/30.4375)) -> 32.032854 | AQ6: =IF(AND(Ext_Flag="Yes",$AA6="Yes"),Ext_Months,0) -> 12 | AR6: =$AP6+$AQ6 -> 44.032854 | AS6: =$AR6/12 -> 3.6694045 | AT6: =IF($AJ6="",0,MAX(0,$AJ6/12)) -> 0 | AU6: =MAX(Amort_Min,Amort_Term-$AH6/12) -> 25.666667 | AV6: =MIN($AS6,Hold_Yrs) -> 3.6694045 | AW6: =IF($AN6=0,0,CEILING(MAX($AS6,0.0001),1)) -> 4 | AX6: =IF(AND($AN6=1,MAX($AS6,0.0001)<=Hold_Yrs),1,0) -> 1 | AY6: =$R6*$AO6 -> 112075260 | AZ6: =$R6*Acc_Int*$AN6 -> 178843.5 | BA6: =$AY6*Acq_Cost -> 840564.45 | BB6: =$AY6+$AZ6+$BA6 -> 1.1309467e+08 | BC6: =IF(Fin_Flag="Yes",$AY6*Adv_Rate,0) -> 67245156 | BD6: =$BC6*Fin_UpFee -> 336225.78 | BE6: =$BB6-$BC6+$BD6 -> 46185738
A7: L-004 | B7: Riverwalk Plaza | C7: NV | D7: Office | E7: Deal 3 | G7: 43344 | H7: 46997 | I7: 120 | J7: 60 | K7: Floating | M7: 0.0185 | N7: Quarterly | O7: 46325 | P7: 0.0834 | R7: 46042000 | S7: 0.99 | T7: 0.1073 | U7: 1.62 | V7: 0.357 | W7: 0.394 | X7: 1973 | Y7: 1993 | Z7: Partial IO | AA7: No | AB7: Prepayable with Penalty | AC7: First Lien | AD7: Institutional Owner/Operator | AE7: Recapitalization | AF7: Matured | AG7: Fee Simple | AH7: =IF(G7="",0,ROUND((Strats!$C$4-G7)/30.4375,1)) -> 97 | AI7: =IF(K7="",0,IF(K7="Floating",Strats!$C$10+M7,L7)) -> 0.0635 | AJ7: =IF(OR(Z7="",Z7="Full Amortizing"),"",MAX(J7-AH7,0)) -> 0 | AK7: =IF(K7="",0,IF(K7="Floating",IF(P7<>"",MIN(IF(Q7<>"",MAX((Strats!$C$10+Strats!$C$11+M7),Q7),(Strats!$C$10+Strats!$C$11+M7)),P7),IF(Q7<>"",MAX((Strats!$C$10+Strats!$C$11+M7),Q7),(Strats!$C$10+Strats!$C$11+M7))),AI7)) -> 0.0785 | AL7: =IF(OR(E7="",E7<>'Deal Strat'!$C$12,R7=""),"",SUMPRODUCT((E$4:E$303='Deal Strat'!$C$12)*(R$4:R$303>R7))+1+SUMPRODUCT((E$4:E$303='Deal Strat'!$C$12)*(R$4:R$303=R7)*(ROW(R$4:R$303)<ROW(R7)))) | AM7: =IF(R7="","",RANK(R7,$R$4:$R$303,0)+COUNTIF($R$4:R7,R7)-1) -> 23 | AN7: =IF(OR($A7="",$R7=""),0,IF(Deal_Scope="All Deals",1,IF($E7=Deal_Scope,1,0))) -> 1 | AO7: =IF($AN7=0,0,Px_Par) -> 0.94 | AP7: =IF($H7="",0,MAX(0,($H7-Set_Date)/30.4375)) -> 23.063655 | AQ7: =IF(AND(Ext_Flag="Yes",$AA7="Yes"),Ext_Months,0) -> 0 | AR7: =$AP7+$AQ7 -> 23.063655 | AS7: =$AR7/12 -> 1.9219713 | AT7: =IF($AJ7="",0,MAX(0,$AJ7/12)) -> 0 | AU7: =MAX(Amort_Min,Amort_Term-$AH7/12) -> 21.916667 | AV7: =MIN($AS7,Hold_Yrs) -> 1.9219713 | AW7: =IF($AN7=0,0,CEILING(MAX($AS7,0.0001),1)) -> 2 | AX7: =IF(AND($AN7=1,MAX($AS7,0.0001)<=Hold_Yrs),1,0) -> 1 | AY7: =$R7*$AO7 -> 43279480 | AZ7: =$R7*Acc_Int*$AN7 -> 69063 | BA7: =$AY7*Acq_Cost -> 324596.1 | BB7: =$AY7+$AZ7+$BA7 -> 43673139 | BC7: =IF(Fin_Flag="Yes",$AY7*Adv_Rate,0) -> 25967688 | BD7: =$BC7*Fin_UpFee -> 129838.44 | BE7: =$BB7-$BC7+$BD7 -> 17835290
A8: L-005 | B8: Pinehurst Plaza | C8: WA | D8: Retail | E8: Deal 8 | G8: 43466 | H8: 45292 | I8: 60 | J8: 12 | K8: Fixed | L8: 0.0648 | N8: N/A | R8: 117696000 | S8: 0.96 | T8: 0.0782 | U8: 1.46 | V8: 0.587 | W8: 0.604 | X8: 2021 | Z8: Interest Only | AA8: Yes | AB8: Defeasance | AC8: First Lien | AD8: PE Fund | AE8: Refinance | AF8: Current | AG8: Fee Simple | AH8: =IF(G8="",0,ROUND((Strats!$C$4-G8)/30.4375,1)) -> 92.9 | AI8: =IF(K8="",0,IF(K8="Floating",Strats!$C$10+M8,L8)) -> 0.0648 | AJ8: =IF(OR(Z8="",Z8="Full Amortizing"),"",MAX(J8-AH8,0)) -> 0 | AK8: =IF(K8="",0,IF(K8="Floating",IF(P8<>"",MIN(IF(Q8<>"",MAX((Strats!$C$10+Strats!$C$11+M8),Q8),(Strats!$C$10+Strats!$C$11+M8)),P8),IF(Q8<>"",MAX((Strats!$C$10+Strats!$C$11+M8),Q8),(Strats!$C$10+Strats!$C$11+M8))),AI8)) -> 0.0648 | AL8: =IF(OR(E8="",E8<>'Deal Strat'!$C$12,R8=""),"",SUMPRODUCT((E$4:E$303='Deal Strat'!$C$12)*(R$4:R$303>R8))+1+SUMPRODUCT((E$4:E$303='Deal Strat'!$C$12)*(R$4:R$303=R8)*(ROW(R$4:R$303)<ROW(R8)))) | AM8: =IF(R8="","",RANK(R8,$R$4:$R$303,0)+COUNTIF($R$4:R8,R8)-1) -> 6 | AN8: =IF(OR($A8="",$R8=""),0,IF(Deal_Scope="All Deals",1,IF($E8=Deal_Scope,1,0))) -> 1 | AO8: =IF($AN8=0,0,Px_Par) -> 0.94 | AP8: =IF($H8="",0,MAX(0,($H8-Set_Date)/30.4375)) -> 0 | AQ8: =IF(AND(Ext_Flag="Yes",$AA8="Yes"),Ext_Months,0) -> 12 | AR8: =$AP8+$AQ8 -> 12 | AS8: =$AR8/12 -> 1 | AT8: =IF($AJ8="",0,MAX(0,$AJ8/12)) -> 0 | AU8: =MAX(Amort_Min,Amort_Term-$AH8/12) -> 22.258333 | AV8: =MIN($AS8,Hold_Yrs) -> 1 | AW8: =IF($AN8=0,0,CEILING(MAX($AS8,0.0001),1)) -> 1 | AX8: =IF(AND($AN8=1,MAX($AS8,0.0001)<=Hold_Yrs),1,0) -> 1 | AY8: =$R8*$AO8 -> 110634240 | AZ8: =$R8*Acc_Int*$AN8 -> 176544 | BA8: =$AY8*Acq_Cost -> 829756.8 | BB8: =$AY8+$AZ8+$BA8 -> 1.1164054e+08 | BC8: =IF(Fin_Flag="Yes",$AY8*Adv_Rate,0) -> 66380544 | BD8: =$BC8*Fin_UpFee -> 331902.72 | BE8: =$BB8-$BC8+$BD8 -> 45591900
A9: L-006 | B9: Keystone Distribution Center | C9: CA | D9: Industrial | E9: Deal 1 | G9: 43221 | H9: 46874 | I9: 120 | J9: 0 | K9: Floating | M9: 0.02 | N9: Quarterly | O9: 46355 | P9: 0.0978 | R9: 57608000 | S9: 0.94 | T9: 0.0853 | U9: 1.36 | V9: 0.572 | W9: 0.602 | X9: 1995 | Y9: 2012 | Z9: Full Amortizing | AA9: No | AB9: Prepayable with Penalty | AC9: First Lien | AD9: Institutional Owner/Operator | AE9: Recapitalization | AF9: Current | AG9: Fee Simple | AH9: =IF(G9="",0,ROUND((Strats!$C$4-G9)/30.4375,1)) -> 101 | AI9: =IF(K9="",0,IF(K9="Floating",Strats!$C$10+M9,L9)) -> 0.065 | AJ9: =IF(OR(Z9="",Z9="Full Amortizing"),"",MAX(J9-AH9,0)) | AK9: =IF(K9="",0,IF(K9="Floating",IF(P9<>"",MIN(IF(Q9<>"",MAX((Strats!$C$10+Strats!$C$11+M9),Q9),(Strats!$C$10+Strats!$C$11+M9)),P9),IF(Q9<>"",MAX((Strats!$C$10+Strats!$C$11+M9),Q9),(Strats!$C$10+Strats!$C$11+M9))),AI9)) -> 0.08 | AL9: =IF(OR(E9="",E9<>'Deal Strat'!$C$12,R9=""),"",SUMPRODUCT((E$4:E$303='Deal Strat'!$C$12)*(R$4:R$303>R9))+1+SUMPRODUCT((E$4:E$303='Deal Strat'!$C$12)*(R$4:R$303=R9)*(ROW(R$4:R$303)<ROW(R9)))) -> 4 | AM9: =IF(R9="","",RANK(R9,$R$4:$R$303,0)+COUNTIF($R$4:R9,R9)-1) -> 19 | AN9: =IF(OR($A9="",$R9=""),0,IF(Deal_Scope="All Deals",1,IF($E9=Deal_Scope,1,0))) -> 1 | AO9: =IF($AN9=0,0,Px_Par) -> 0.94 | AP9: =IF($H9="",0,MAX(0,($H9-Set_Date)/30.4375)) -> 19.022587 | AQ9: =IF(AND(Ext_Flag="Yes",$AA9="Yes"),Ext_Months,0) -> 0 | AR9: =$AP9+$AQ9 -> 19.022587 | AS9: =$AR9/12 -> 1.5852156 | AT9: =IF($AJ9="",0,MAX(0,$AJ9/12)) -> 0 | AU9: =MAX(Amort_Min,Amort_Term-$AH9/12) -> 21.583333 | AV9: =MIN($AS9,Hold_Yrs) -> 1.5852156 | AW9: =IF($AN9=0,0,CEILING(MAX($AS9,0.0001),1)) -> 2 | AX9: =IF(AND($AN9=1,MAX($AS9,0.0001)<=Hold_Yrs),1,0) -> 1 | AY9: =$R9*$AO9 -> 54151520 | AZ9: =$R9*Acc_Int*$AN9 -> 86412 | BA9: =$AY9*Acq_Cost -> 406136.4 | BB9: =$AY9+$AZ9+$BA9 -> 54644068 | BC9: =IF(Fin_Flag="Yes",$AY9*Adv_Rate,0) -> 32490912 | BD9: =$BC9*Fin_UpFee -> 162454.56 | BE9: =$BB9-$BC9+$BD9 -> 22315611
A10: L-007 | B10: Jasper Retail Center | C10: MD | D10: Retail | E10: Deal 3 | G10: 45170 | H10: 48823 | I10: 120 | J10: 120 | K10: Floating | M10: 0.0202 | N10: Monthly | O10: 46355 | P10: 0.1052 | R10: 4524000 | S10: 0.99 | T10: 0.08 | U10: 1.19 | V10: 0.644 | W10: 0.658 | X10: 2007 | Z10: Interest Only | AA10: Yes | AB10: Prepayable with Penalty | AC10: First Lien | AD10: Institutional Owner/Operator | AE10: Acquisition | AF10: Current | AG10: Fee Simple | AH10: =IF(G10="",0,ROUND((Strats!$C$4-G10)/30.4375,1)) -> 37 | AI10: =IF(K10="",0,IF(K10="Floating",Strats!$C$10+M10,L10)) -> 0.0652 | AJ10: =IF(OR(Z10="",Z10="Full Amortizing"),"",MAX(J10-AH10,0)) -> 83 | AK10: =IF(K10="",0,IF(K10="Floating",IF(P10<>"",MIN(IF(Q10<>"",MAX((Strats!$C$10+Strats!$C$11+M10),Q10),(Strats!$C$10+Strats!$C$11+M10)),P10),IF(Q10<>"",MAX((Strats!$C$10+Strats!$C$11+M10),Q10),(Strats!$C$10+Strats!$C$11+M10))),AI10)) -> 0.0802 | AL10: =IF(OR(E10="",E10<>'Deal Strat'!$C$12,R10=""),"",SUMPRODUCT((E$4:E$303='Deal Strat'!$C$12)*(R$4:R$303>R10))+1+SUMPRODUCT((E$4:E$303='Deal Strat'!$C$12)*(R$4:R$303=R10)*(ROW(R$4:R$303)<ROW(R10)))) | AM10: =IF(R10="","",RANK(R10,$R$4:$R$303,0)+COUNTIF($R$4:R10,R10)-1) -> 49 | AN10: =IF(OR($A10="",$R10=""),0,IF(Deal_Scope="All Deals",1,IF($E10=Deal_Scope,1,0))) -> 1 | AO10: =IF($AN10=0,0,Px_Par) -> 0.94 | AP10: =IF($H10="",0,MAX(0,($H10-Set_Date)/30.4375)) -> 83.055441 | AQ10: =IF(AND(Ext_Flag="Yes",$AA10="Yes"),Ext_Months,0) -> 12 | AR10: =$AP10+$AQ10 -> 95.055441 | AS10: =$AR10/12 -> 7.9212868 | AT10: =IF($AJ10="",0,MAX(0,$AJ10/12)) -> 6.9166667 | AU10: =MAX(Amort_Min,Amort_Term-$AH10/12) -> 26.916667 | AV10: =MIN($AS10,Hold_Yrs) -> 5 | AW10: =IF($AN10=0,0,CEILING(MAX($AS10,0.0001),1)) -> 8 | AX10: =IF(AND($AN10=1,MAX($AS10,0.0001)<=Hold_Yrs),1,0) -> 0 | AY10: =$R10*$AO10 -> 4252560 | AZ10: =$R10*Acc_Int*$AN10 -> 6786 | BA10: =$AY10*Acq_Cost -> 31894.2 | BB10: =$AY10+$AZ10+$BA10 -> 4291240.2 | BC10: =IF(Fin_Flag="Yes",$AY10*Adv_Rate,0) -> 2551536 | BD10: =$BC10*Fin_UpFee -> 12757.68 | BE10: =$BB10-$BC10+$BD10 -> 1752461.9
A11: L-008 | B11: Riverwalk Business Park | C11: FL | D11: Office | E11: Deal 2 | G11: 43891 | H11: 47543 | I11: 119 | J11: 12 | K11: Floating | M11: 0.036 | N11: Monthly | O11: 46355 | P11: 0.1057 | R11: 48331000 | S11: 0.99 | T11: 0.0941 | U11: 0.98 | V11: 0.741 | W11: 0.762 | X11: 1986 | Y11: 2011 | Z11: Partial IO | AA11: No | AB11: Defeasance | AC11: First Lien | AD11: Private REIT | AE11: Acquisition | AF11: Current | AG11: Fee Simple | AH11: =IF(G11="",0,ROUND((Strats!$C$4-G11)/30.4375,1)) -> 79 | AI11: =IF(K11="",0,IF(K11="Floating",Strats!$C$10+M11,L11)) -> 0.081 | AJ11: =IF(OR(Z11="",Z11="Full Amortizing"),"",MAX(J11-AH11,0)) -> 0 | AK11: =IF(K11="",0,IF(K11="Floating",IF(P11<>"",MIN(IF(Q11<>"",MAX((Strats!$C$10+Strats!$C$11+M11),Q11),(Strats!$C$10+Strats!$C$11+M11)),P11),IF(Q11<>"",MAX((Strats!$C$10+Strats!$C$11+M11),Q11),(Strats!$C$10+Strats!$C$11+M11))),AI11)) -> 0.096 | AL11: =IF(OR(E11="",E11<>'Deal Strat'!$C$12,R11=""),"",SUMPRODUCT((E$4:E$303='Deal Strat'!$C$12)*(R$4:R$303>R11))+1+SUMPRODUCT((E$4:E$303='Deal Strat'!$C$12)*(R$4:R$303=R11)*(ROW(R$4:R$303)<ROW(R11)))) | AM11: =IF(R11="","",RANK(R11,$R$4:$R$303,0)+COUNTIF($R$4:R11,R11)-1) -> 22 | AN11: =IF(OR($A11="",$R11=""),0,IF(Deal_Scope="All Deals",1,IF($E11=Deal_Scope,1,0))) -> 1 | AO11: =IF($AN11=0,0,Px_Par) -> 0.94 | AP11: =IF($H11="",0,MAX(0,($H11-Set_Date)/30.4375)) -> 41.002053 | AQ11: =IF(AND(Ext_Flag="Yes",$AA11="Yes"),Ext_Months,0) -> 0 | AR11: =$AP11+$AQ11 -> 41.002053 | AS11: =$AR11/12 -> 3.4168378 | AT11: =IF($AJ11="",0,MAX(0,$AJ11/12)) -> 0 | AU11: =MAX(Amort_Min,Amort_Term-$AH11/12) -> 23.416667 | AV11: =MIN($AS11,Hold_Yrs) -> 3.4168378 | AW11: =IF($AN11=0,0,CEILING(MAX($AS11,0.0001),1)) -> 4 | AX11: =IF(AND($AN11=1,MAX($AS11,0.0001)<=Hold_Yrs),1,0) -> 1 | AY11: =$R11*$AO11 -> 45431140 | AZ11: =$R11*Acc_Int*$AN11 -> 72496.5 | BA11: =$AY11*Acq_Cost -> 340733.55 | BB11: =$AY11+$AZ11+$BA11 -> 45844370 | BC11: =IF(Fin_Flag="Yes",$AY11*Adv_Rate,0) -> 27258684 | BD11: =$BC11*Fin_UpFee -> 136293.42 | BE11: =$BB11-$BC11+$BD11 -> 18721979
A12: L-009 | B12: Quarry Commons | C12: CO | D12: Multifamily | E12: Deal 5 | F12: 162 | G12: 45292 | H12: 48945 | I12: 119 | J12: 60 | K12: Fixed | L12: 0.0479 | N12: N/A | R12: 16415000 | S12: 0.831 | T12: 0.0963 | U12: 2.05 | V12: 0.432 | W12: 0.487 | X12: 1978 | Z12: Partial IO | AA12: No | AB12: Freely Prepayable | AC12: First Lien | AD12: HNW Investors | AE12: Recapitalization | AF12: Current | AG12: Fee & Leasehold | AH12: =IF(G12="",0,ROUND((Strats!$C$4-G12)/30.4375,1)) -> 33 | AI12: =IF(K12="",0,IF(K12="Floating",Strats!$C$10+M12,L12)) -> 0.0479 | AJ12: =IF(OR(Z12="",Z12="Full Amortizing"),"",MAX(J12-AH12,0)) -> 27 | AK12: =IF(K12="",0,IF(K12="Floating",IF(P12<>"",MIN(IF(Q12<>"",MAX((Strats!$C$10+Strats!$C$11+M12),Q12),(Strats!$C$10+Strats!$C$11+M12)),P12),IF(Q12<>"",MAX((Strats!$C$10+Strats!$C$11+M12),Q12),(Strats!$C$10+Strats!$C$11+M12))),AI12)) -> 0.0479 | AL12: =IF(OR(E12="",E12<>'Deal Strat'!$C$12,R12=""),"",SUMPRODUCT((E$4:E$303='Deal Strat'!$C$12)*(R$4:R$303>R12))+1+SUMPRODUCT((E$4:E$303='Deal Strat'!$C$12)*(R$4:R$303=R12)*(ROW(R$4:R$303)<ROW(R12)))) | AM12: =IF(R12="","",RANK(R12,$R$4:$R$303,0)+COUNTIF($R$4:R12,R12)-1) -> 33 | AN12: =IF(OR($A12="",$R12=""),0,IF(Deal_Scope="All Deals",1,IF($E12=Deal_Scope,1,0))) -> 1 | AO12: =IF($AN12=0,0,Px_Par) -> 0.94 | AP12: =IF($H12="",0,MAX(0,($H12-Set_Date)/30.4375)) -> 87.063655 | AQ12: =IF(AND(Ext_Flag="Yes",$AA12="Yes"),Ext_Months,0) -> 0 | AR12: =$AP12+$AQ12 -> 87.063655 | AS12: =$AR12/12 -> 7.2553046 | AT12: =IF($AJ12="",0,MAX(0,$AJ12/12)) -> 2.25 | AU12: =MAX(Amort_Min,Amort_Term-$AH12/12) -> 27.25 | AV12: =MIN($AS12,Hold_Yrs) -> 5 | AW12: =IF($AN12=0,0,CEILING(MAX($AS12,0.0001),1)) -> 8 | AX12: =IF(AND($AN12=1,MAX($AS12,0.0001)<=Hold_Yrs),1,0) -> 0 | AY12: =$R12*$AO12 -> 15430100 | AZ12: =$R12*Acc_Int*$AN12 -> 24622.5 | BA12: =$AY12*Acq_Cost -> 115725.75 | BB12: =$AY12+$AZ12+$BA12 -> 15570448 | BC12: =IF(Fin_Flag="Yes",$AY12*Adv_Rate,0) -> 9258060 | BD12: =$BC12*Fin_UpFee -> 46290.3 | BE12: =$BB12-$BC12+$BD12 -> 6358678.5
A13: L-010 | B13: Brookstone Landing | C13: NC | D13: Multifamily | E13: Deal 1 | F13: 171 | G13: 43435 | H13: 45261 | I13: 61 | J13: 0 | K13: Fixed | L13: 0.0647 | N13: N/A | R13: 45056000 | S13: 0.929 | T13: 0.0685 | U13: 1.98 | V13: 0.685 | W13: 0.735 | X13: 1979 | Y13: 1990 | Z13: Full Amortizing | AA13: Yes | AB13: Prepayable with Penalty | AC13: First Lien | AD13: HNW Investors | AE13: Acquisition | AF13: Current | AG13: Fee Simple | AH13: =IF(G13="",0,ROUND((Strats!$C$4-G13)/30.4375,1)) -> 94 | AI13: =IF(K13="",0,IF(K13="Floating",Strats!$C$10+M13,L13)) -> 0.0647 | AJ13: =IF(OR(Z13="",Z13="Full Amortizing"),"",MAX(J13-AH13,0)) | AK13: =IF(K13="",0,IF(K13="Floating",IF(P13<>"",MIN(IF(Q13<>"",MAX((Strats!$C$10+Strats!$C$11+M13),Q13),(Strats!$C$10+Strats!$C$11+M13)),P13),IF(Q13<>"",MAX((Strats!$C$10+Strats!$C$11+M13),Q13),(Strats!$C$10+Strats!$C$11+M13))),AI13)) -> 0.0647 | AL13: =IF(OR(E13="",E13<>'Deal Strat'!$C$12,R13=""),"",SUMPRODUCT((E$4:E$303='Deal Strat'!$C$12)*(R$4:R$303>R13))+1+SUMPRODUCT((E$4:E$303='Deal Strat'!$C$12)*(R$4:R$303=R13)*(ROW(R$4:R$303)<ROW(R13)))) -> 5 | AM13: =IF(R13="","",RANK(R13,$R$4:$R$303,0)+COUNTIF($R$4:R13,R13)-1) -> 24 | AN13: =IF(OR($A13="",$R13=""),0,IF(Deal_Scope="All Deals",1,IF($E13=Deal_Scope,1,0))) -> 1 | AO13: =IF($AN13=0,0,Px_Par) -> 0.94 | AP13: =IF($H13="",0,MAX(0,($H13-Set_Date)/30.4375)) -> 0 | AQ13: =IF(AND(Ext_Flag="Yes",$AA13="Yes"),Ext_Months,0) -> 12 | AR13: =$AP13+$AQ13 -> 12 | AS13: =$AR13/12 -> 1 | AT13: =IF($AJ13="",0,MAX(0,$AJ13/12)) -> 0 | AU13: =MAX(Amort_Min,Amort_Term-$AH13/12) -> 22.166667 | AV13: =MIN($AS13,Hold_Yrs) -> 1 | AW13: =IF($AN13=0,0,CEILING(MAX($AS13,0.0001),1)) -> 1 | AX13: =IF(AND($AN13=1,MAX($AS13,0.0001)<=Hold_Yrs),1,0) -> 1 | AY13: =$R13*$AO13 -> 42352640 | AZ13: =$R13*Acc_Int*$AN13 -> 67584 | BA13: =$AY13*Acq_Cost -> 317644.8 | BB13: =$AY13+$AZ13+$BA13 -> 42737869 | BC13: =IF(Fin_Flag="Yes",$AY13*Adv_Rate,0) -> 25411584 | BD13: =$BC13*Fin_UpFee -> 127057.92 | BE13: =$BB13-$BC13+$BD13 -> 17453343
A14: L-011 | B14: Summit Distribution Center | C14: CO | D14: Industrial | E14: Deal 5 | G14: 44835 | H14: 48488 | I14: 120 | J14: 24 | K14: Floating | M14: 0.0249 | N14: Monthly | O14: 46295 | R14: 27710000 | S14: 0.817 | T14: 0.0839 | U14: 0.58 | V14: 0.581 | W14: 0.613 | X14: 2007 | Z14: Partial IO | AA14: No | AB14: Defeasance | AC14: First Lien | AD14: Private REIT | AE14: Acquisition | AF14: Current | AG14: Fee Simple | AH14: =IF(G14="",0,ROUND((Strats!$C$4-G14)/30.4375,1)) -> 48 | AI14: =IF(K14="",0,IF(K14="Floating",Strats!$C$10+M14,L14)) -> 0.0699 | AJ14: =IF(OR(Z14="",Z14="Full Amortizing"),"",MAX(J14-AH14,0)) -> 0 | AK14: =IF(K14="",0,IF(K14="Floating",IF(P14<>"",MIN(IF(Q14<>"",MAX((Strats!$C$10+Strats!$C$11+M14),Q14),(Strats!$C$10+Strats!$C$11+M14)),P14),IF(Q14<>"",MAX((Strats!$C$10+Strats!$C$11+M14),Q14),(Strats!$C$10+Strats!$C$11+M14))),AI14)) -> 0.0849 | AL14: =IF(OR(E14="",E14<>'Deal Strat'!$C$12,R14=""),"",SUMPRODUCT((E$4:E$303='Deal Strat'!$C$12)*(R$4:R$303>R14))+1+SUMPRODUCT((E$4:E$303='Deal Strat'!$C$12)*(R$4:R$303=R14)*(ROW(R$4:R$303)<ROW(R14)))) | AM14: =IF(R14="","",RANK(R14,$R$4:$R$303,0)+COUNTIF($R$4:R14,R14)-1) -> 31 | AN14: =IF(OR($A14="",$R14=""),0,IF(Deal_Scope="All Deals",1,IF($E14=Deal_Scope,1,0))) -> 1 | AO14: =IF($AN14=0,0,Px_Par) -> 0.94 | AP14: =IF($H14="",0,MAX(0,($H14-Set_Date)/30.4375)) -> 72.049281 | AQ14: =IF(AND(Ext_Flag="Yes",$AA14="Yes"),Ext_Months,0) -> 0 | AR14: =$AP14+$AQ14 -> 72.049281 | AS14: =$AR14/12 -> 6.0041068 | AT14: =IF($AJ14="",0,MAX(0,$AJ14/12)) -> 0 | AU14: =MAX(Amort_Min,Amort_Term-$AH14/12) -> 26 | AV14: =MIN($AS14,Hold_Yrs) -> 5 | AW14: =IF($AN14=0,0,CEILING(MAX($AS14,0.0001),1)) -> 7 | AX14: =IF(AND($AN14=1,MAX($AS14,0.0001)<=Hold_Yrs),1,0) -> 0 | AY14: =$R14*$AO14 -> 26047400 | AZ14: =$R14*Acc_Int*$AN14 -> 41565 | BA14: =$AY14*Acq_Cost -> 195355.5 | BB14: =$AY14+$AZ14+$BA14 -> 26284320 | BC14: =IF(Fin_Flag="Yes",$AY14*Adv_Rate,0) -> 15628440 | BD14: =$BC14*Fin_UpFee -> 78142.2 | BE14: =$BB14-$BC14+$BD14 -> 10734023
A15: L-012 | B15: Parkside Marketplace | C15: MD | D15: Retail | E15: Deal 7 | G15: 43952 | H15: 46508 | I15: 85 | J15: 36 | K15: Fixed | L15: 0.0557 | N15: N/A | R15: 5654000 | S15: 0.842 | T15: 0.0426 | U15: 1.44 | V15: 0.703 | W15: 0.753 | X15: 1975 | Z15: Partial IO | AA15: Yes | AB15: Defeasance | AC15: First Lien | AD15: PE Fund | AE15: Recapitalization | AF15: Current | AG15: Fee Simple | AH15: =IF(G15="",0,ROUND((Strats!$C$4-G15)/30.4375,1)) -> 77 | AI15: =IF(K15="",0,IF(K15="Floating",Strats!$C$10+M15,L15)) -> 0.0557 | AJ15: =IF(OR(Z15="",Z15="Full Amortizing"),"",MAX(J15-AH15,0)) -> 0 | AK15: =IF(K15="",0,IF(K15="Floating",IF(P15<>"",MIN(IF(Q15<>"",MAX((Strats!$C$10+Strats!$C$11+M15),Q15),(Strats!$C$10+Strats!$C$11+M15)),P15),IF(Q15<>"",MAX((Strats!$C$10+Strats!$C$11+M15),Q15),(Strats!$C$10+Strats!$C$11+M15))),AI15)) -> 0.0557 | AL15: =IF(OR(E15="",E15<>'Deal Strat'!$C$12,R15=""),"",SUMPRODUCT((E$4:E$303='Deal Strat'!$C$12)*(R$4:R$303>R15))+1+SUMPRODUCT((E$4:E$303='Deal Strat'!$C$12)*(R$4:R$303=R15)*(ROW(R$4:R$303)<ROW(R15)))) | AM15: =IF(R15="","",RANK(R15,$R$4:$R$303,0)+COUNTIF($R$4:R15,R15)-1) -> 44 | AN15: =IF(OR($A15="",$R15=""),0,IF(Deal_Scope="All Deals",1,IF($E15=Deal_Scope,1,0))) -> 1 | AO15: =IF($AN15=0,0,Px_Par) -> 0.94 | AP15: =IF($H15="",0,MAX(0,($H15-Set_Date)/30.4375)) -> 6.9979466 | AQ15: =IF(AND(Ext_Flag="Yes",$AA15="Yes"),Ext_Months,0) -> 12 | AR15: =$AP15+$AQ15 -> 18.997947 | AS15: =$AR15/12 -> 1.5831622 | AT15: =IF($AJ15="",0,MAX(0,$AJ15/12)) -> 0 | AU15: =MAX(Amort_Min,Amort_Term-$AH15/12) -> 23.583333 | AV15: =MIN($AS15,Hold_Yrs) -> 1.5831622 | AW15: =IF($AN15=0,0,CEILING(MAX($AS15,0.0001),1)) -> 2 | AX15: =IF(AND($AN15=1,MAX($AS15,0.0001)<=Hold_Yrs),1,0) -> 1 | AY15: =$R15*$AO15 -> 5314760 | AZ15: =$R15*Acc_Int*$AN15 -> 8481 | BA15: =$AY15*Acq_Cost -> 39860.7 | BB15: =$AY15+$AZ15+$BA15 -> 5363101.7 | BC15: =IF(Fin_Flag="Yes",$AY15*Adv_Rate,0) -> 3188856 | BD15: =$BC15*Fin_UpFee -> 15944.28 | BE15: =$BB15-$BC15+$BD15 -> 2190190
A16: L-013 | B16: Summit Distribution Center | C16: GA | D16: Industrial | E16: Deal 4 | G16: 45108 | H16: 47665 | I16: 84 | J16: 12 | K16: Fixed | L16: 0.0655 | N16: N/A | R16: 85445000 | S16: 0.99 | T16: 0.0875 | U16: 0.79 | V16: 0.577 | W16: 0.627 | X16: 2009 | Y16: 2015 | Z16: Partial IO | AA16: Yes | AB16: Yield Maintenance | AC16: First Lien | AD16: PE Fund | AE16: Acquisition | AF16: Current | AG16: Fee Simple | AH16: =IF(G16="",0,ROUND((Strats!$C$4-G16)/30.4375,1)) -> 39 | AI16: =IF(K16="",0,IF(K16="Floating",Strats!$C$10+M16,L16)) -> 0.0655 | AJ16: =IF(OR(Z16="",Z16="Full Amortizing"),"",MAX(J16-AH16,0)) -> 0 | AK16: =IF(K16="",0,IF(K16="Floating",IF(P16<>"",MIN(IF(Q16<>"",MAX((Strats!$C$10+Strats!$C$11+M16),Q16),(Strats!$C$10+Strats!$C$11+M16)),P16),IF(Q16<>"",MAX((Strats!$C$10+Strats!$C$11+M16),Q16),(Strats!$C$10+Strats!$C$11+M16))),AI16)) -> 0.0655 | AL16: =IF(OR(E16="",E16<>'Deal Strat'!$C$12,R16=""),"",SUMPRODUCT((E$4:E$303='Deal Strat'!$C$12)*(R$4:R$303>R16))+1+SUMPRODUCT((E$4:E$303='Deal Strat'!$C$12)*(R$4:R$303=R16)*(ROW(R$4:R$303)<ROW(R16)))) | AM16: =IF(R16="","",RANK(R16,$R$4:$R$303,0)+COUNTIF($R$4:R16,R16)-1) -> 12 | AN16: =IF(OR($A16="",$R16=""),0,IF(Deal_Scope="All Deals",1,IF($E16=Deal_Scope,1,0))) -> 1 | AO16: =IF($AN16=0,0,Px_Par) -> 0.94 | AP16: =IF($H16="",0,MAX(0,($H16-Set_Date)/30.4375)) -> 45.010267 | AQ16: =IF(AND(Ext_Flag="Yes",$AA16="Yes"),Ext_Months,0) -> 12 | AR16: =$AP16+$AQ16 -> 57.010267 | AS16: =$AR16/12 -> 4.7508556 | AT16: =IF($AJ16="",0,MAX(0,$AJ16/12)) -> 0 | AU16: =MAX(Amort_Min,Amort_Term-$AH16/12) -> 26.75 | AV16: =MIN($AS16,Hold_Yrs) -> 4.7508556 | AW16: =IF($AN16=0,0,CEILING(MAX($AS16,0.0001),1)) -> 5 | AX16: =IF(AND($AN16=1,MAX($AS16,0.0001)<=Hold_Yrs),1,0) -> 1 | AY16: =$R16*$AO16 -> 80318300 | AZ16: =$R16*Acc_Int*$AN16 -> 128167.5 | BA16: =$AY16*Acq_Cost -> 602387.25 | BB16: =$AY16+$AZ16+$BA16 -> 81048855 | BC16: =IF(Fin_Flag="Yes",$AY16*Adv_Rate,0) -> 48190980 | BD16: =$BC16*Fin_UpFee -> 240954.9 | BE16: =$BB16-$BC16+$BD16 -> 33098830
A17: L-014 | B17: Glenwood Landing | C17: NV | D17: Multifamily | E17: Deal 8 | F17: 161 | G17: 45231 | H17: 47788 | I17: 84 | J17: 36 | K17: Fixed | L17: 0.0504 | N17: N/A | R17: 128291000 | S17: 0.802 | T17: 0.095 | U17: 1.98 | V17: 0.693 | W17: 0.722 | X17: 1974 | Z17: Partial IO | AA17: Yes | AB17: Freely Prepayable | AC17: First Lien | AD17: Institutional Owner/Operator | AE17: Acquisition | AF17: Current | AG17: Fee & Leasehold | AH17: =IF(G17="",0,ROUND((Strats!$C$4-G17)/30.4375,1)) -> 35 | AI17: =IF(K17="",0,IF(K17="Floating",Strats!$C$10+M17,L17)) -> 0.0504 | AJ17: =IF(OR(Z17="",Z17="Full Amortizing"),"",MAX(J17-AH17,0)) -> 1 | AK17: =IF(K17="",0,IF(K17="Floating",IF(P17<>"",MIN(IF(Q17<>"",MAX((Strats!$C$10+Strats!$C$11+M17),Q17),(Strats!$C$10+Strats!$C$11+M17)),P17),IF(Q17<>"",MAX((Strats!$C$10+Strats!$C$11+M17),Q17),(Strats!$C$10+Strats!$C$11+M17))),AI17)) -> 0.0504 | AL17: =IF(OR(E17="",E17<>'Deal Strat'!$C$12,R17=""),"",SUMPRODUCT((E$4:E$303='Deal Strat'!$C$12)*(R$4:R$303>R17))+1+SUMPRODUCT((E$4:E$303='Deal Strat'!$C$12)*(R$4:R$303=R17)*(ROW(R$4:R$303)<ROW(R17)))) | AM17: =IF(R17="","",RANK(R17,$R$4:$R$303,0)+COUNTIF($R$4:R17,R17)-1) -> 3 | AN17: =IF(OR($A17="",$R17=""),0,IF(Deal_Scope="All Deals",1,IF($E17=Deal_Scope,1,0))) -> 1 | AO17: =IF($AN17=0,0,Px_Par) -> 0.94 | AP17: =IF($H17="",0,MAX(0,($H17-Set_Date)/30.4375)) -> 49.051335 | AQ17: =IF(AND(Ext_Flag="Yes",$AA17="Yes"),Ext_Months,0) -> 12 | AR17: =$AP17+$AQ17 -> 61.051335 | AS17: =$AR17/12 -> 5.0876112 | AT17: =IF($AJ17="",0,MAX(0,$AJ17/12)) -> 0.083333333 | AU17: =MAX(Amort_Min,Amort_Term-$AH17/12) -> 27.083333 | AV17: =MIN($AS17,Hold_Yrs) -> 5 | AW17: =IF($AN17=0,0,CEILING(MAX($AS17,0.0001),1)) -> 6 | AX17: =IF(AND($AN17=1,MAX($AS17,0.0001)<=Hold_Yrs),1,0) -> 0 | AY17: =$R17*$AO17 -> 120593540 | AZ17: =$R17*Acc_Int*$AN17 -> 192436.5 | BA17: =$AY17*Acq_Cost -> 904451.55 | BB17: =$AY17+$AZ17+$BA17 -> 1.2169043e+08 | BC17: =IF(Fin_Flag="Yes",$AY17*Adv_Rate,0) -> 72356124 | BD17: =$BC17*Fin_UpFee -> 361780.62 | BE17: =$BB17-$BC17+$BD17 -> 49696085
A18: L-015 | B18: Palisades Exchange | C18: TX | D18: Office | E18: Deal 7 | G18: 45566 | H18: 48122 | I18: 85 | J18: 60 | K18: Floating | M18: 0.0311 | N18: Monthly | O18: 46355 | R18: 131786000 | S18: 0.951 | T18: 0.1044 | U18: 1.69 | V18: 0.78 | W18: 0.791 | X18: 1990 | Y18: 1995 | Z18: Interest Only | AA18: Yes | AB18: Freely Prepayable | AC18: First Lien | AD18: PE Fund | AE18: Acquisition | AF18: Current | AG18: Fee Simple | AH18: =IF(G18="",0,ROUND((Strats!$C$4-G18)/30.4375,1)) -> 24 | AI18: =IF(K18="",0,IF(K18="Floating",Strats!$C$10+M18,L18)) -> 0.0761 | AJ18: =IF(OR(Z18="",Z18="Full Amortizing"),"",MAX(J18-AH18,0)) -> 36 | AK18: =IF(K18="",0,IF(K18="Floating",IF(P18<>"",MIN(IF(Q18<>"",MAX((Strats!$C$10+Strats!$C$11+M18),Q18),(Strats!$C$10+Strats!$C$11+M18)),P18),IF(Q18<>"",MAX((Strats!$C$10+Strats!$C$11+M18),Q18),(Strats!$C$10+Strats!$C$11+M18))),AI18)) -> 0.0911 | AL18: =IF(OR(E18="",E18<>'Deal Strat'!$C$12,R18=""),"",SUMPRODUCT((E$4:E$303='Deal Strat'!$C$12)*(R$4:R$303>R18))+1+SUMPRODUCT((E$4:E$303='Deal Strat'!$C$12)*(R$4:R$303=R18)*(ROW(R$4:R$303)<ROW(R18)))) | AM18: =IF(R18="","",RANK(R18,$R$4:$R$303,0)+COUNTIF($R$4:R18,R18)-1) -> 2 | AN18: =IF(OR($A18="",$R18=""),0,IF(Deal_Scope="All Deals",1,IF($E18=Deal_Scope,1,0))) -> 1 | AO18: =IF($AN18=0,0,Px_Par) -> 0.94 | AP18: =IF($H18="",0,MAX(0,($H18-Set_Date)/30.4375)) -> 60.024641 | AQ18: =IF(AND(Ext_Flag="Yes",$AA18="Yes"),Ext_Months,0) -> 12 | AR18: =$AP18+$AQ18 -> 72.024641 | AS18: =$AR18/12 -> 6.0020534 | AT18: =IF($AJ18="",0,MAX(0,$AJ18/12)) -> 3 | AU18: =MAX(Amort_Min,Amort_Term-$AH18/12) -> 28 | AV18: =MIN($AS18,Hold_Yrs) -> 5 | AW18: =IF($AN18=0,0,CEILING(MAX($AS18,0.0001),1)) -> 7 | AX18: =IF(AND($AN18=1,MAX($AS18,0.0001)<=Hold_Yrs),1,0) -> 0 | AY18: =$R18*$AO18 -> 123878840 | AZ18: =$R18*Acc_Int*$AN18 -> 197679 | BA18: =$AY18*Acq_Cost -> 929091.3 | BB18: =$AY18+$AZ18+$BA18 -> 1.2500561e+08 | BC18: =IF(Fin_Flag="Yes",$AY18*Adv_Rate,0) -> 74327304 | BD18: =$BC18*Fin_UpFee -> 371636.52 | BE18: =$BB18-$BC18+$BD18 -> 51049943
A19: L-016 | B19: Harborview Landing | C19: TN | D19: Multifamily | E19: Deal 5 | F19: 121 | G19: 42461 | H19: 45017 | I19: 84 | J19: 24 | K19: Floating | M19: 0.0214 | N19: Monthly | O19: 46355 | R19: 8243000 | S19: 0.897 | T19: 0.0445 | U19: 1.69 | V19: 0.469 | W19: 0.515 | X19: 2014 | Z19: Partial IO | AA19: No | AB19: Prepayable with Penalty | AC19: First Lien | AD19: Institutional Owner/Operator | AE19: Refinance | AF19: Matured | AG19: Fee Simple | AH19: =IF(G19="",0,ROUND((Strats!$C$4-G19)/30.4375,1)) -> 126 | AI19: =IF(K19="",0,IF(K19="Floating",Strats!$C$10+M19,L19)) -> 0.0664 | AJ19: =IF(OR(Z19="",Z19="Full Amortizing"),"",MAX(J19-AH19,0)) -> 0 | AK19: =IF(K19="",0,IF(K19="Floating",IF(P19<>"",MIN(IF(Q19<>"",MAX((Strats!$C$10+Strats!$C$11+M19),Q19),(Strats!$C$10+Strats!$C$11+M19)),P19),IF(Q19<>"",MAX((Strats!$C$10+Strats!$C$11+M19),Q19),(Strats!$C$10+Strats!$C$11+M19))),AI19)) -> 0.0814 | AL19: =IF(OR(E19="",E19<>'Deal Strat'!$C$12,R19=""),"",SUMPRODUCT((E$4:E$303='Deal Strat'!$C$12)*(R$4:R$303>R19))+1+SUMPRODUCT((E$4:E$303='Deal Strat'!$C$12)*(R$4:R$303=R19)*(ROW(R$4:R$303)<ROW(R19)))) | AM19: =IF(R19="","",RANK(R19,$R$4:$R$303,0)+COUNTIF($R$4:R19,R19)-1) -> 40 | AN19: =IF(OR($A19="",$R19=""),0,IF(Deal_Scope="All Deals",1,IF($E19=Deal_Scope,1,0))) -> 1 | AO19: =IF($AN19=0,0,Px_Par) -> 0.94 | AP19: =IF($H19="",0,MAX(0,($H19-Set_Date)/30.4375)) -> 0 | AQ19: =IF(AND(Ext_Flag="Yes",$AA19="Yes"),Ext_Months,0) -> 0 | AR19: =$AP19+$AQ19 -> 0 | AS19: =$AR19/12 -> 0 | AT19: =IF($AJ19="",0,MAX(0,$AJ19/12)) -> 0 | AU19: =MAX(Amort_Min,Amort_Term-$AH19/12) -> 19.5 | AV19: =MIN($AS19,Hold_Yrs) -> 0 | AW19: =IF($AN19=0,0,CEILING(MAX($AS19,0.0001),1)) -> 1 | AX19: =IF(AND($AN19=1,MAX($AS19,0.0001)<=Hold_Yrs),1,0) -> 1 | AY19: =$R19*$AO19 -> 7748420 | AZ19: =$R19*Acc_Int*$AN19 -> 12364.5 | BA19: =$AY19*Acq_Cost -> 58113.15 | BB19: =$AY19+$AZ19+$BA19 -> 7818897.7 | BC19: =IF(Fin_Flag="Yes",$AY19*Adv_Rate,0) -> 4649052 | BD19: =$BC19*Fin_UpFee -> 23245.26 | BE19: =$BB19-$BC19+$BD19 -> 3193090.9
A20: L-017 | B20: Emerson Marketplace | C20: FL | D20: Retail | E20: Deal 2 | G20: 44440 | H20: 48092 | I20: 120 | J20: 36 | K20: Fixed | L20: 0.0453 | N20: N/A | R20: 5111000 | S20: 0.808 | T20: 0.0677 | U20: 1.55 | V20: 0.706 | W20: 0.761 | X20: 1994 | Z20: Interest Only | AA20: Yes | AB20: Defeasance | AC20: Second Lien | AD20: PE Fund | AE20: Refinance | AF20: Current | AG20: Fee Simple | AH20: =IF(G20="",0,ROUND((Strats!$C$4-G20)/30.4375,1)) -> 60.9 | AI20: =IF(K20="",0,IF(K20="Floating",Strats!$C$10+M20,L20)) -> 0.0453 | AJ20: =IF(OR(Z20="",Z20="Full Amortizing"),"",MAX(J20-AH20,0)) -> 0 | AK20: =IF(K20="",0,IF(K20="Floating",IF(P20<>"",MIN(IF(Q20<>"",MAX((Strats!$C$10+Strats!$C$11+M20),Q20),(Strats!$C$10+Strats!$C$11+M20)),P20),IF(Q20<>"",MAX((Strats!$C$10+Strats!$C$11+M20),Q20),(Strats!$C$10+Strats!$C$11+M20))),AI20)) -> 0.0453 | AL20: =IF(OR(E20="",E20<>'Deal Strat'!$C$12,R20=""),"",SUMPRODUCT((E$4:E$303='Deal Strat'!$C$12)*(R$4:R$303>R20))+1+SUMPRODUCT((E$4:E$303='Deal Strat'!$C$12)*(R$4:R$303=R20)*(ROW(R$4:R$303)<ROW(R20)))) | AM20: =IF(R20="","",RANK(R20,$R$4:$R$303,0)+COUNTIF($R$4:R20,R20)-1) -> 47 | AN20: =IF(OR($A20="",$R20=""),0,IF(Deal_Scope="All Deals",1,IF($E20=Deal_Scope,1,0))) -> 1 | AO20: =IF($AN20=0,0,Px_Par) -> 0.94 | AP20: =IF($H20="",0,MAX(0,($H20-Set_Date)/30.4375)) -> 59.039014 | AQ20: =IF(AND(Ext_Flag="Yes",$AA20="Yes"),Ext_Months,0) -> 12 | AR20: =$AP20+$AQ20 -> 71.039014 | AS20: =$AR20/12 -> 5.9199179 | AT20: =IF($AJ20="",0,MAX(0,$AJ20/12)) -> 0 | AU20: =MAX(Amort_Min,Amort_Term-$AH20/12) -> 24.925 | AV20: =MIN($AS20,Hold_Yrs) -> 5 | AW20: =IF($AN20=0,0,CEILING(MAX($AS20,0.0001),1)) -> 6 | AX20: =IF(AND($AN20=1,MAX($AS20,0.0001)<=Hold_Yrs),1,0) -> 0 | AY20: =$R20*$AO20 -> 4804340 | AZ20: =$R20*Acc_Int*$AN20 -> 7666.5 | BA20: =$AY20*Acq_Cost -> 36032.55 | BB20: =$AY20+$AZ20+$BA20 -> 4848039 | BC20: =IF(Fin_Flag="Yes",$AY20*Adv_Rate,0) -> 2882604 | BD20: =$BC20*Fin_UpFee -> 14413.02 | BE20: =$BB20-$BC20+$BD20 -> 1979848.1
A21: L-018 | B21: Kingston Corporate Center | C21: IL | D21: Office | E21: Deal 2 | G21: 44256 | H21: 47908 | I21: 120 | J21: 36 | K21: Floating | M21: 0.0272 | N21: Quarterly | O21: 46355 | R21: 76728000 | S21: 0.842 | T21: 0.0861 | U21: 1.33 | V21: 0.782 | W21: 0.82 | X21: 1980 | Z21: Partial IO | AA21: No | AB21: Defeasance | AC21: First Lien | AD21: PE Fund | AE21: Acquisition | AF21: Current | AG21: Fee Simple | AH21: =IF(G21="",0,ROUND((Strats!$C$4-G21)/30.4375,1)) -> 67 | AI21: =IF(K21="",0,IF(K21="Floating",Strats!$C$10+M21,L21)) -> 0.0722 | AJ21: =IF(OR(Z21="",Z21="Full Amortizing"),"",MAX(J21-AH21,0)) -> 0 | AK21: =IF(K21="",0,IF(K21="Floating",IF(P21<>"",MIN(IF(Q21<>"",MAX((Strats!$C$10+Strats!$C$11+M21),Q21),(Strats!$C$10+Strats!$C$11+M21)),P21),IF(Q21<>"",MAX((Strats!$C$10+Strats!$C$11+M21),Q21),(Strats!$C$10+Strats!$C$11+M21))),AI21)) -> 0.0872 | AL21: =IF(OR(E21="",E21<>'Deal Strat'!$C$12,R21=""),"",SUMPRODUCT((E$4:E$303='Deal Strat'!$C$12)*(R$4:R$303>R21))+1+SUMPRODUCT((E$4:E$303='Deal Strat'!$C$12)*(R$4:R$303=R21)*(ROW(R$4:R$303)<ROW(R21)))) | AM21: =IF(R21="","",RANK(R21,$R$4:$R$303,0)+COUNTIF($R$4:R21,R21)-1) -> 15 | AN21: =IF(OR($A21="",$R21=""),0,IF(Deal_Scope="All Deals",1,IF($E21=Deal_Scope,1,0))) -> 1 | AO21: =IF($AN21=0,0,Px_Par) -> 0.94 | AP21: =IF($H21="",0,MAX(0,($H21-Set_Date)/30.4375)) -> 52.99384 | AQ21: =IF(AND(Ext_Flag="Yes",$AA21="Yes"),Ext_Months,0) -> 0 | AR21: =$AP21+$AQ21 -> 52.99384 | AS21: =$AR21/12 -> 4.4161533 | AT21: =IF($AJ21="",0,MAX(0,$AJ21/12)) -> 0 | AU21: =MAX(Amort_Min,Amort_Term-$AH21/12) -> 24.416667 | AV21: =MIN($AS21,Hold_Yrs) -> 4.4161533 | AW21: =IF($AN21=0,0,CEILING(MAX($AS21,0.0001),1)) -> 5 | AX21: =IF(AND($AN21=1,MAX($AS21,0.0001)<=Hold_Yrs),1,0) -> 1 | AY21: =$R21*$AO21 -> 72124320 | AZ21: =$R21*Acc_Int*$AN21 -> 115092 | BA21: =$AY21*Acq_Cost -> 540932.4 | BB21: =$AY21+$AZ21+$BA21 -> 72780344 | BC21: =IF(Fin_Flag="Yes",$AY21*Adv_Rate,0) -> 43274592 | BD21: =$BC21*Fin_UpFee -> 216372.96 | BE21: =$BB21-$BC21+$BD21 -> 29722125
A22: L-019 | B22: Chandler Exchange | C22: OR | D22: Office | E22: Deal 6 | G22: 43617 | H22: 45444 | I22: 59 | J22: 0 | K22: Floating | M22: 0.0366 | N22: Monthly | O22: 46355 | P22: 0.1004 | R22: 8222000 | S22: 0.827 | T22: 0.0956 | U22: 1.31 | V22: 0.707 | W22: 0.728 | X22: 1976 | Y22: 1998 | Z22: Full Amortizing | AA22: Yes | AB22: Prepayable with Penalty | AC22: First Lien | AD22: PE Fund | AE22: Recapitalization | AF22: Current | AG22: Fee Simple | AH22: =IF(G22="",0,ROUND((Strats!$C$4-G22)/30.4375,1)) -> 88 | AI22: =IF(K22="",0,IF(K22="Floating",Strats!$C$10+M22,L22)) -> 0.0816 | AJ22: =IF(OR(Z22="",Z22="Full Amortizing"),"",MAX(J22-AH22,0)) | AK22: =IF(K22="",0,IF(K22="Floating",IF(P22<>"",MIN(IF(Q22<>"",MAX((Strats!$C$10+Strats!$C$11+M22),Q22),(Strats!$C$10+Strats!$C$11+M22)),P22),IF(Q22<>"",MAX((Strats!$C$10+Strats!$C$11+M22),Q22),(Strats!$C$10+Strats!$C$11+M22))),AI22)) -> 0.0966 | AL22: =IF(OR(E22="",E22<>'Deal Strat'!$C$12,R22=""),"",SUMPRODUCT((E$4:E$303='Deal Strat'!$C$12)*(R$4:R$303>R22))+1+SUMPRODUCT((E$4:E$303='Deal Strat'!$C$12)*(R$4:R$303=R22)*(ROW(R$4:R$303)<ROW(R22)))) | AM22: =IF(R22="","",RANK(R22,$R$4:$R$303,0)+COUNTIF($R$4:R22,R22)-1) -> 41 | AN22: =IF(OR($A22="",$R22=""),0,IF(Deal_Scope="All Deals",1,IF($E22=Deal_Scope,1,0))) -> 1 | AO22: =IF($AN22=0,0,Px_Par) -> 0.94 | AP22: =IF($H22="",0,MAX(0,($H22-Set_Date)/30.4375)) -> 0 | AQ22: =IF(AND(Ext_Flag="Yes",$AA22="Yes"),Ext_Months,0) -> 12 | AR22: =$AP22+$AQ22 -> 12 | AS22: =$AR22/12 -> 1 | AT22: =IF($AJ22="",0,MAX(0,$AJ22/12)) -> 0 | AU22: =MAX(Amort_Min,Amort_Term-$AH22/12) -> 22.666667 | AV22: =MIN($AS22,Hold_Yrs) -> 1 | AW22: =IF($AN22=0,0,CEILING(MAX($AS22,0.0001),1)) -> 1 | AX22: =IF(AND($AN22=1,MAX($AS22,0.0001)<=Hold_Yrs),1,0) -> 1 | AY22: =$R22*$AO22 -> 7728680 | AZ22: =$R22*Acc_Int*$AN22 -> 12333 | BA22: =$AY22*Acq_Cost -> 57965.1 | BB22: =$AY22+$AZ22+$BA22 -> 7798978.1 | BC22: =IF(Fin_Flag="Yes",$AY22*Adv_Rate,0) -> 4637208 | BD22: =$BC22*Fin_UpFee -> 23186.04 | BE22: =$BB22-$BC22+$BD22 -> 3184956.1
A23: L-020 | B23: Dogwood Pointe | C23: TX | D23: Multifamily | E23: Deal 8 | F23: 325 | G23: 44958 | H23: 48611 | I23: 120 | J23: 120 | K23: Floating | M23: 0.0436 | N23: Monthly | O23: 46295 | P23: 0.1018 | R23: 69109000 | S23: 0.916 | T23: 0.0633 | U23: 1.11 | V23: 0.641 | W23: 0.673 | X23: 2020 | Z23: Interest Only | AA23: Yes | AB23: Defeasance | AC23: First Lien | AD23: Institutional Owner/Operator | AE23: Recapitalization | AF23: Current | AG23: Fee Simple | AH23: =IF(G23="",0,ROUND((Strats!$C$4-G23)/30.4375,1)) -> 43.9 | AI23: =IF(K23="",0,IF(K23="Floating",Strats!$C$10+M23,L23)) -> 0.0886 | AJ23: =IF(OR(Z23="",Z23="Full Amortizing"),"",MAX(J23-AH23,0)) -> 76.1 | AK23: =IF(K23="",0,IF(K23="Floating",IF(P23<>"",MIN(IF(Q23<>"",MAX((Strats!$C$10+Strats!$C$11+M23),Q23),(Strats!$C$10+Strats!$C$11+M23)),P23),IF(Q23<>"",MAX((Strats!$C$10+Strats!$C$11+M23),Q23),(Strats!$C$10+Strats!$C$11+M23))),AI23)) -> 0.1018 | AL23: =IF(OR(E23="",E23<>'Deal Strat'!$C$12,R23=""),"",SUMPRODUCT((E$4:E$303='Deal Strat'!$C$12)*(R$4:R$303>R23))+1+SUMPRODUCT((E$4:E$303='Deal Strat'!$C$12)*(R$4:R$303=R23)*(ROW(R$4:R$303)<ROW(R23)))) | AM23: =IF(R23="","",RANK(R23,$R$4:$R$303,0)+COUNTIF($R$4:R23,R23)-1) -> 17 | AN23: =IF(OR($A23="",$R23=""),0,IF(Deal_Scope="All Deals",1,IF($E23=Deal_Scope,1,0))) -> 1 | AO23: =IF($AN23=0,0,Px_Par) -> 0.94 | AP23: =IF($H23="",0,MAX(0,($H23-Set_Date)/30.4375)) -> 76.090349 | AQ23: =IF(AND(Ext_Flag="Yes",$AA23="Yes"),Ext_Months,0) -> 12 | AR23: =$AP23+$AQ23 -> 88.090349 | AS23: =$AR23/12 -> 7.3408624 | AT23: =IF($AJ23="",0,MAX(0,$AJ23/12)) -> 6.3416667 | AU23: =MAX(Amort_Min,Amort_Term-$AH23/12) -> 26.341667 | AV23: =MIN($AS23,Hold_Yrs) -> 5 | AW23: =IF($AN23=0,0,CEILING(MAX($AS23,0.0001),1)) -> 8 | AX23: =IF(AND($AN23=1,MAX($AS23,0.0001)<=Hold_Yrs),1,0) -> 0 | AY23: =$R23*$AO23 -> 64962460 | AZ23: =$R23*Acc_Int*$AN23 -> 103663.5 | BA23: =$AY23*Acq_Cost -> 487218.45 | BB23: =$AY23+$AZ23+$BA23 -> 65553342 | BC23: =IF(Fin_Flag="Yes",$AY23*Adv_Rate,0) -> 38977476 | BD23: =$BC23*Fin_UpFee -> 194887.38 | BE23: =$BB23-$BC23+$BD23 -> 26770753
A24: L-021 | B24: Fairhaven Marketplace | C24: NC | D24: Retail | E24: Deal 2 | G24: 44958 | H24: 47515 | I24: 84 | J24: 24 | K24: Floating | M24: 0.0295 | N24: Monthly | O24: 46355 | P24: 0.0843 | Q24: 0.0309 | R24: 36748000 | S24: 0.932 | T24: 0.1053 | U24: 0.9 | V24: 0.418 | W24: 0.45 | X24: 1994 | Z24: Partial IO | AA24: No | AB24: Yield Maintenance | AC24: First Lien | AD24: Institutional Owner/Operator | AE24: Acquisition | AF24: Current | AG24: Fee Simple | AH24: =IF(G24="",0,ROUND((Strats!$C$4-G24)/30.4375,1)) -> 43.9 | AI24: =IF(K24="",0,IF(K24="Floating",Strats!$C$10+M24,L24)) -> 0.0745 | AJ24: =IF(OR(Z24="",Z24="Full Amortizing"),"",MAX(J24-AH24,0)) -> 0 | AK24: =IF(K24="",0,IF(K24="Floating",IF(P24<>"",MIN(IF(Q24<>"",MAX((Strats!$C$10+Strats!$C$11+M24),Q24),(Strats!$C$10+Strats!$C$11+M24)),P24),IF(Q24<>"",MAX((Strats!$C$10+Strats!$C$11+M24),Q24),(Strats!$C$10+Strats!$C$11+M24))),AI24)) -> 0.0843 | AL24: =IF(OR(E24="",E24<>'Deal Strat'!$C$12,R24=""),"",SUMPRODUCT((E$4:E$303='Deal Strat'!$C$12)*(R$4:R$303>R24))+1+SUMPRODUCT((E$4:E$303='Deal Strat'!$C$12)*(R$4:R$303=R24)*(ROW(R$4:R$303)<ROW(R24)))) | AM24: =IF(R24="","",RANK(R24,$R$4:$R$303,0)+COUNTIF($R$4:R24,R24)-1) -> 28 | AN24: =IF(OR($A24="",$R24=""),0,IF(Deal_Scope="All Deals",1,IF($E24=Deal_Scope,1,0))) -> 1 | AO24: =IF($AN24=0,0,Px_Par) -> 0.94 | AP24: =IF($H24="",0,MAX(0,($H24-Set_Date)/30.4375)) -> 40.082136 | AQ24: =IF(AND(Ext_Flag="Yes",$AA24="Yes"),Ext_Months,0) -> 0 | AR24: =$AP24+$AQ24 -> 40.082136 | AS24: =$AR24/12 -> 3.340178 | AT24: =IF($AJ24="",0,MAX(0,$AJ24/12)) -> 0 | AU24: =MAX(Amort_Min,Amort_Term-$AH24/12) -> 26.341667 | AV24: =MIN($AS24,Hold_Yrs) -> 3.340178 | AW24: =IF($AN24=0,0,CEILING(MAX($AS24,0.0001),1)) -> 4 | AX24: =IF(AND($AN24=1,MAX($AS24,0.0001)<=Hold_Yrs),1,0) -> 1 | AY24: =$R24*$AO24 -> 34543120 | AZ24: =$R24*Acc_Int*$AN24 -> 55122 | BA24: =$AY24*Acq_Cost -> 259073.4 | BB24: =$AY24+$AZ24+$BA24 -> 34857315 | BC24: =IF(Fin_Flag="Yes",$AY24*Adv_Rate,0) -> 20725872 | BD24: =$BC24*Fin_UpFee -> 103629.36 | BE24: =$BB24-$BC24+$BD24 -> 14235073
A25: L-022 | B25: Summit Residences | C25: IL | D25: Multifamily | E25: Deal 4 | F25: 425 | G25: 43313 | H25: 46966 | I25: 121 | J25: 0 | K25: Fixed | L25: 0.0492 | N25: N/A | R25: 7026000 | S25: 0.79 | T25: 0.0763 | U25: 1.1 | V25: 0.663 | W25: 0.69 | X25: 1986 | Y25: 1994 | Z25: Full Amortizing | AA25: No | AB25: Prepayable with Penalty | AC25: First Lien | AD25: PE Fund | AE25: Recapitalization | AF25: Current | AG25: Fee Simple | AH25: =IF(G25="",0,ROUND((Strats!$C$4-G25)/30.4375,1)) -> 98 | AI25: =IF(K25="",0,IF(K25="Floating",Strats!$C$10+M25,L25)) -> 0.0492 | AJ25: =IF(OR(Z25="",Z25="Full Amortizing"),"",MAX(J25-AH25,0)) | AK25: =IF(K25="",0,IF(K25="Floating",IF(P25<>"",MIN(IF(Q25<>"",MAX((Strats!$C$10+Strats!$C$11+M25),Q25),(Strats!$C$10+Strats!$C$11+M25)),P25),IF(Q25<>"",MAX((Strats!$C$10+Strats!$C$11+M25),Q25),(Strats!$C$10+Strats!$C$11+M25))),AI25)) -> 0.0492 | AL25: =IF(OR(E25="",E25<>'Deal Strat'!$C$12,R25=""),"",SUMPRODUCT((E$4:E$303='Deal Strat'!$C$12)*(R$4:R$303>R25))+1+SUMPRODUCT((E$4:E$303='Deal Strat'!$C$12)*(R$4:R$303=R25)*(ROW(R$4:R$303)<ROW(R25)))) | AM25: =IF(R25="","",RANK(R25,$R$4:$R$303,0)+COUNTIF($R$4:R25,R25)-1) -> 43 | AN25: =IF(OR($A25="",$R25=""),0,IF(Deal_Scope="All Deals",1,IF($E25=Deal_Scope,1,0))) -> 1 | AO25: =IF($AN25=0,0,Px_Par) -> 0.94 | AP25: =IF($H25="",0,MAX(0,($H25-Set_Date)/30.4375)) -> 22.045175 | AQ25: =IF(AND(Ext_Flag="Yes",$AA25="Yes"),Ext_Months,0) -> 0 | AR25: =$AP25+$AQ25 -> 22.045175 | AS25: =$AR25/12 -> 1.8370979 | AT25: =IF($AJ25="",0,MAX(0,$AJ25/12)) -> 0 | AU25: =MAX(Amort_Min,Amort_Term-$AH25/12) -> 21.833333 | AV25: =MIN($AS25,Hold_Yrs) -> 1.8370979 | AW25: =IF($AN25=0,0,CEILING(MAX($AS25,0.0001),1)) -> 2 | AX25: =IF(AND($AN25=1,MAX($AS25,0.0001)<=Hold_Yrs),1,0) -> 1 | AY25: =$R25*$AO25 -> 6604440 | AZ25: =$R25*Acc_Int*$AN25 -> 10539 | BA25: =$AY25*Acq_Cost -> 49533.3 | BB25: =$AY25+$AZ25+$BA25 -> 6664512.3 | BC25: =IF(Fin_Flag="Yes",$AY25*Adv_Rate,0) -> 3962664 | BD25: =$BC25*Fin_UpFee -> 19813.32 | BE25: =$BB25-$BC25+$BD25 -> 2721661.6
A26: L-023 | B26: Grandview Plaza | C26: CO | D26: Office | E26: Deal 2 | G26: 42461 | H26: 46113 | I26: 120 | J26: 60 | K26: Fixed | L26: 0.0594 | N26: N/A | R26: 76306000 | S26: 0.904 | T26: 0.0413 | U26: 1.11 | V26: 0.576 | W26: 0.608 | X26: 2009 | Y26: 2014 | Z26: Partial IO | AA26: No | AB26: Defeasance | AC26: First Lien | AD26: PE Fund | AE26: Refinance | AF26: Current | AG26: Fee Simple | AH26: =IF(G26="",0,ROUND((Strats!$C$4-G26)/30.4375,1)) -> 126 | AI26: =IF(K26="",0,IF(K26="Floating",Strats!$C$10+M26,L26)) -> 0.0594 | AJ26: =IF(OR(Z26="",Z26="Full Amortizing"),"",MAX(J26-AH26,0)) -> 0 | AK26: =IF(K26="",0,IF(K26="Floating",IF(P26<>"",MIN(IF(Q26<>"",MAX((Strats!$C$10+Strats!$C$11+M26),Q26),(Strats!$C$10+Strats!$C$11+M26)),P26),IF(Q26<>"",MAX((Strats!$C$10+Strats!$C$11+M26),Q26),(Strats!$C$10+Strats!$C$11+M26))),AI26)) -> 0.0594 | AL26: =IF(OR(E26="",E26<>'Deal Strat'!$C$12,R26=""),"",SUMPRODUCT((E$4:E$303='Deal Strat'!$C$12)*(R$4:R$303>R26))+1+SUMPRODUCT((E$4:E$303='Deal Strat'!$C$12)*(R$4:R$303=R26)*(ROW(R$4:R$303)<ROW(R26)))) | AM26: =IF(R26="","",RANK(R26,$R$4:$R$303,0)+COUNTIF($R$4:R26,R26)-1) -> 16 | AN26: =IF(OR($A26="",$R26=""),0,IF(Deal_Scope="All Deals",1,IF($E26=Deal_Scope,1,0))) -> 1 | AO26: =IF($AN26=0,0,Px_Par) -> 0.94 | AP26: =IF($H26="",0,MAX(0,($H26-Set_Date)/30.4375)) -> 0 | AQ26: =IF(AND(Ext_Flag="Yes",$AA26="Yes"),Ext_Months,0) -> 0 | AR26: =$AP26+$AQ26 -> 0 | AS26: =$AR26/12 -> 0 | AT26: =IF($AJ26="",0,MAX(0,$AJ26/12)) -> 0 | AU26: =MAX(Amort_Min,Amort_Term-$AH26/12) -> 19.5 | AV26: =MIN($AS26,Hold_Yrs) -> 0 | AW26: =IF($AN26=0,0,CEILING(MAX($AS26,0.0001),1)) -> 1 | AX26: =IF(AND($AN26=1,MAX($AS26,0.0001)<=Hold_Yrs),1,0) -> 1 | AY26: =$R26*$AO26 -> 71727640 | AZ26: =$R26*Acc_Int*$AN26 -> 114459 | BA26: =$AY26*Acq_Cost -> 537957.3 | BB26: =$AY26+$AZ26+$BA26 -> 72380056 | BC26: =IF(Fin_Flag="Yes",$AY26*Adv_Rate,0) -> 43036584 | BD26: =$BC26*Fin_UpFee -> 215182.92 | BE26: =$BB26-$BC26+$BD26 -> 29558655
A27: L-024 | B27: Union Square Mixed-Use Development | C27: NY | D27: Mixed-Use | E27: Deal 3 | G27: 45170 | H27: 47727 | I27: 85 | J27: 120 | K27: Floating | M27: 0.0317 | N27: Quarterly | O27: 46295 | P27: 0.1027 | R27: 17633000 | S27: 0.99 | T27: 0.092 | U27: 1.18 | V27: 0.572 | W27: 0.597 | X27: 2002 | Y27: 2022 | Z27: Interest Only | AA27: No | AB27: Freely Prepayable | AC27: First Lien | AD27: Institutional Owner/Operator | AE27: Refinance | AF27: Current | AG27: Fee & Leasehold | AH27: =IF(G27="",0,ROUND((Strats!$C$4-G27)/30.4375,1)) -> 37 | AI27: =IF(K27="",0,IF(K27="Floating",Strats!$C$10+M27,L27)) -> 0.0767 | AJ27: =IF(OR(Z27="",Z27="Full Amortizing"),"",MAX(J27-AH27,0)) -> 83 | AK27: =IF(K27="",0,IF(K27="Floating",IF(P27<>"",MIN(IF(Q27<>"",MAX((Strats!$C$10+Strats!$C$11+M27),Q27),(Strats!$C$10+Strats!$C$11+M27)),P27),IF(Q27<>"",MAX((Strats!$C$10+Strats!$C$11+M27),Q27),(Strats!$C$10+Strats!$C$11+M27))),AI27)) -> 0.0917 | AL27: =IF(OR(E27="",E27<>'Deal Strat'!$C$12,R27=""),"",SUMPRODUCT((E$4:E$303='Deal Strat'!$C$12)*(R$4:R$303>R27))+1+SUMPRODUCT((E$4:E$303='Deal Strat'!$C$12)*(R$4:R$303=R27)*(ROW(R$4:R$303)<ROW(R27)))) | AM27: =IF(R27="","",RANK(R27,$R$4:$R$303,0)+COUNTIF($R$4:R27,R27)-1) -> 32 | AN27: =IF(OR($A27="",$R27=""),0,IF(Deal_Scope="All Deals",1,IF($E27=Deal_Scope,1,0))) -> 1 | AO27: =IF($AN27=0,0,Px_Par) -> 0.94 | AP27: =IF($H27="",0,MAX(0,($H27-Set_Date)/30.4375)) -> 47.047228 | AQ27: =IF(AND(Ext_Flag="Yes",$AA27="Yes"),Ext_Months,0) -> 0 | AR27: =$AP27+$AQ27 -> 47.047228 | AS27: =$AR27/12 -> 3.9206023 | AT27: =IF($AJ27="",0,MAX(0,$AJ27/12)) -> 6.9166667 | AU27: =MAX(Amort_Min,Amort_Term-$AH27/12) -> 26.916667 | AV27: =MIN($AS27,Hold_Yrs) -> 3.9206023 | AW27: =IF($AN27=0,0,CEILING(MAX($AS27,0.0001),1)) -> 4 | AX27: =IF(AND($AN27=1,MAX($AS27,0.0001)<=Hold_Yrs),1,0) -> 1 | AY27: =$R27*$AO27 -> 16575020 | AZ27: =$R27*Acc_Int*$AN27 -> 26449.5 | BA27: =$AY27*Acq_Cost -> 124312.65 | BB27: =$AY27+$AZ27+$BA27 -> 16725782 | BC27: =IF(Fin_Flag="Yes",$AY27*Adv_Rate,0) -> 9945012 | BD27: =$BC27*Fin_UpFee -> 49725.06 | BE27: =$BB27-$BC27+$BD27 -> 6830495.2
A28: L-025 | B28: Dogwood Warehouse | C28: VA | D28: Industrial | E28: Deal 4 | G28: 44927 | H28: 47484 | I28: 83 | J28: 0 | K28: Fixed | L28: 0.0526 | N28: N/A | R28: 14773000 | S28: 0.99 | T28: 0.1206 | U28: 1.75 | V28: 0.815 | W28: 0.826 | X28: 1974 | Y28: 1999 | Z28: Full Amortizing | AA28: No | AB28: Prepayable with Penalty | AC28: First Lien | AD28: PE Fund | AE28: Refinance | AF28: Current | AG28: Fee Simple | AH28: =IF(G28="",0,ROUND((Strats!$C$4-G28)/30.4375,1)) -> 44.9 | AI28: =IF(K28="",0,IF(K28="Floating",Strats!$C$10+M28,L28)) -> 0.0526 | AJ28: =IF(OR(Z28="",Z28="Full Amortizing"),"",MAX(J28-AH28,0)) | AK28: =IF(K28="",0,IF(K28="Floating",IF(P28<>"",MIN(IF(Q28<>"",MAX((Strats!$C$10+Strats!$C$11+M28),Q28),(Strats!$C$10+Strats!$C$11+M28)),P28),IF(Q28<>"",MAX((Strats!$C$10+Strats!$C$11+M28),Q28),(Strats!$C$10+Strats!$C$11+M28))),AI28)) -> 0.0526 | AL28: =IF(OR(E28="",E28<>'Deal Strat'!$C$12,R28=""),"",SUMPRODUCT((E$4:E$303='Deal Strat'!$C$12)*(R$4:R$303>R28))+1+SUMPRODUCT((E$4:E$303='Deal Strat'!$C$12)*(R$4:R$303=R28)*(ROW(R$4:R$303)<ROW(R28)))) | AM28: =IF(R28="","",RANK(R28,$R$4:$R$303,0)+COUNTIF($R$4:R28,R28)-1) -> 34 | AN28: =IF(OR($A28="",$R28=""),0,IF(Deal_Scope="All Deals",1,IF($E28=Deal_Scope,1,0))) -> 1 | AO28: =IF($AN28=0,0,Px_Par) -> 0.94 | AP28: =IF($H28="",0,MAX(0,($H28-Set_Date)/30.4375)) -> 39.063655 | AQ28: =IF(AND(Ext_Flag="Yes",$AA28="Yes"),Ext_Months,0) -> 0 | AR28: =$AP28+$AQ28 -> 39.063655 | AS28: =$AR28/12 -> 3.2553046 | AT28: =IF($AJ28="",0,MAX(0,$AJ28/12)) -> 0 | AU28: =MAX(Amort_Min,Amort_Term-$AH28/12) -> 26.258333 | AV28: =MIN($AS28,Hold_Yrs) -> 3.2553046 | AW28: =IF($AN28=0,0,CEILING(MAX($AS28,0.0001),1)) -> 4 | AX28: =IF(AND($AN28=1,MAX($AS28,0.0001)<=Hold_Yrs),1,0) -> 1 | AY28: =$R28*$AO28 -> 13886620 | AZ28: =$R28*Acc_Int*$AN28 -> 22159.5 | BA28: =$AY28*Acq_Cost -> 104149.65 | BB28: =$AY28+$AZ28+$BA28 -> 14012929 | BC28: =IF(Fin_Flag="Yes",$AY28*Adv_Rate,0) -> 8331972 | BD28: =$BC28*Fin_UpFee -> 41659.86 | BE28: =$BB28-$BC28+$BD28 -> 5722617
A29: L-026 | B29: Oakmont Village | C29: MD | D29: Multifamily | E29: Deal 8 | F29: 357 | G29: 43040 | H29: 44866 | I29: 61 | J29: 36 | K29: Floating | M29: 0.0424 | N29: Monthly | O29: 46295 | P29: 0.0881 | Q29: 0.038 | R29: 89897000 | S29: 0.754 | T29: 0.0889 | U29: 1.1 | V29: 0.703 | W29: 0.757 | X29: 2004 | Z29: Interest Only | AA29: Yes | AB29: Defeasance | AC29: First Lien | AD29: Institutional Owner/Operator | AE29: Acquisition | AF29: Current | AG29: Fee & Leasehold | AH29: =IF(G29="",0,ROUND((Strats!$C$4-G29)/30.4375,1)) -> 106.9 | AI29: =IF(K29="",0,IF(K29="Floating",Strats!$C$10+M29,L29)) -> 0.0874 | AJ29: =IF(OR(Z29="",Z29="Full Amortizing"),"",MAX(J29-AH29,0)) -> 0 | AK29: =IF(K29="",0,IF(K29="Floating",IF(P29<>"",MIN(IF(Q29<>"",MAX((Strats!$C$10+Strats!$C$11+M29),Q29),(Strats!$C$10+Strats!$C$11+M29)),P29),IF(Q29<>"",MAX((Strats!$C$10+Strats!$C$11+M29),Q29),(Strats!$C$10+Strats!$C$11+M29))),AI29)) -> 0.0881 | AL29: =IF(OR(E29="",E29<>'Deal Strat'!$C$12,R29=""),"",SUMPRODUCT((E$4:E$303='Deal Strat'!$C$12)*(R$4:R$303>R29))+1+SUMPRODUCT((E$4:E$303='Deal Strat'!$C$12)*(R$4:R$303=R29)*(ROW(R$4:R$303)<ROW(R29)))) | AM29: =IF(R29="","",RANK(R29,$R$4:$R$303,0)+COUNTIF($R$4:R29,R29)-1) -> 9 | AN29: =IF(OR($A29="",$R29=""),0,IF(Deal_Scope="All Deals",1,IF($E29=Deal_Scope,1,0))) -> 1 | AO29: =IF($AN29=0,0,Px_Par) -> 0.94 | AP29: =IF($H29="",0,MAX(0,($H29-Set_Date)/30.4375)) -> 0 | AQ29: =IF(AND(Ext_Flag="Yes",$AA29="Yes"),Ext_Months,0) -> 12 | AR29: =$AP29+$AQ29 -> 12 | AS29: =$AR29/12 -> 1 | AT29: =IF($AJ29="",0,MAX(0,$AJ29/12)) -> 0 | AU29: =MAX(Amort_Min,Amort_Term-$AH29/12) -> 21.091667 | AV29: =MIN($AS29,Hold_Yrs) -> 1 | AW29: =IF($AN29=0,0,CEILING(MAX($AS29,0.0001),1)) -> 1 | AX29: =IF(AND($AN29=1,MAX($AS29,0.0001)<=Hold_Yrs),1,0) -> 1 | AY29: =$R29*$AO29 -> 84503180 | AZ29: =$R29*Acc_Int*$AN29 -> 134845.5 | BA29: =$AY29*Acq_Cost -> 633773.85 | BB29: =$AY29+$AZ29+$BA29 -> 85271799 | BC29: =IF(Fin_Flag="Yes",$AY29*Adv_Rate,0) -> 50701908 | BD29: =$BC29*Fin_UpFee -> 253509.54 | BE29: =$BB29-$BC29+$BD29 -> 34823401
A30: L-027 | B30: Keystone Exchange | C30: WA | D30: Office | E30: Deal 3 | G30: 43922 | H30: 47574 | I30: 121 | J30: 60 | K30: Floating | M30: 0.0334 | N30: Monthly | O30: 46355 | P30: 0.1092 | R30: 88481000 | S30: 0.882 | T30: 0.072 | U30: 1.8 | V30: 0.478 | W30: 0.49 | X30: 2003 | Z30: Interest Only | AA30: No | AB30: Yield Maintenance | AC30: First Lien | AD30: PE Fund | AE30: Refinance | AF30: Current | AG30: Fee Simple | AH30: =IF(G30="",0,ROUND((Strats!$C$4-G30)/30.4375,1)) -> 78 | AI30: =IF(K30="",0,IF(K30="Floating",Strats!$C$10+M30,L30)) -> 0.0784 | AJ30: =IF(OR(Z30="",Z30="Full Amortizing"),"",MAX(J30-AH30,0)) -> 0 | AK30: =IF(K30="",0,IF(K30="Floating",IF(P30<>"",MIN(IF(Q30<>"",MAX((Strats!$C$10+Strats!$C$11+M30),Q30),(Strats!$C$10+Strats!$C$11+M30)),P30),IF(Q30<>"",MAX((Strats!$C$10+Strats!$C$11+M30),Q30),(Strats!$C$10+Strats!$C$11+M30))),AI30)) -> 0.0934 | AL30: =IF(OR(E30="",E30<>'Deal Strat'!$C$12,R30=""),"",SUMPRODUCT((E$4:E$303='Deal Strat'!$C$12)*(R$4:R$303>R30))+1+SUMPRODUCT((E$4:E$303='Deal Strat'!$C$12)*(R$4:R$303=R30)*(ROW(R$4:R$303)<ROW(R30)))) | AM30: =IF(R30="","",RANK(R30,$R$4:$R$303,0)+COUNTIF($R$4:R30,R30)-1) -> 10 | AN30: =IF(OR($A30="",$R30=""),0,IF(Deal_Scope="All Deals",1,IF($E30=Deal_Scope,1,0))) -> 1 | AO30: =IF($AN30=0,0,Px_Par) -> 0.94 | AP30: =IF($H30="",0,MAX(0,($H30-Set_Date)/30.4375)) -> 42.020534 | AQ30: =IF(AND(Ext_Flag="Yes",$AA30="Yes"),Ext_Months,0) -> 0 | AR30: =$AP30+$AQ30 -> 42.020534 | AS30: =$AR30/12 -> 3.5017112 | AT30: =IF($AJ30="",0,MAX(0,$AJ30/12)) -> 0 | AU30: =MAX(Amort_Min,Amort_Term-$AH30/12) -> 23.5 | AV30: =MIN($AS30,Hold_Yrs) -> 3.5017112 | AW30: =IF($AN30=0,0,CEILING(MAX($AS30,0.0001),1)) -> 4 | AX30: =IF(AND($AN30=1,MAX($AS30,0.0001)<=Hold_Yrs),1,0) -> 1 | AY30: =$R30*$AO30 -> 83172140 | AZ30: =$R30*Acc_Int*$AN30 -> 132721.5 | BA30: =$AY30*Acq_Cost -> 623791.05 | BB30: =$AY30+$AZ30+$BA30 -> 83928653 | BC30: =IF(Fin_Flag="Yes",$AY30*Adv_Rate,0) -> 49903284 | BD30: =$BC30*Fin_UpFee -> 249516.42 | BE30: =$BB30-$BC30+$BD30 -> 34274885
A31: L-028 | B31: Hillcrest Residences | C31: GA | D31: Multifamily | E31: Deal 1 | F31: 238 | G31: 43191 | H31: 45748 | I31: 83 | J31: 0 | K31: Fixed | L31: 0.0534 | N31: N/A | R31: 86385000 | S31: 0.828 | T31: 0.1077 | U31: 1.35 | V31: 0.888 | W31: 0.945 | X31: 2016 | Z31: Full Amortizing | AA31: No | AB31: Defeasance | AC31: First Lien | AD31: HNW Investors | AE31: Acquisition | AF31: Current | AG31: Fee Simple | AH31: =IF(G31="",0,ROUND((Strats!$C$4-G31)/30.4375,1)) -> 102 | AI31: =IF(K31="",0,IF(K31="Floating",Strats!$C$10+M31,L31)) -> 0.0534 | AJ31: =IF(OR(Z31="",Z31="Full Amortizing"),"",MAX(J31-AH31,0)) | AK31: =IF(K31="",0,IF(K31="Floating",IF(P31<>"",MIN(IF(Q31<>"",MAX((Strats!$C$10+Strats!$C$11+M31),Q31),(Strats!$C$10+Strats!$C$11+M31)),P31),IF(Q31<>"",MAX((Strats!$C$10+Strats!$C$11+M31),Q31),(Strats!$C$10+Strats!$C$11+M31))),AI31)) -> 0.0534 | AL31: =IF(OR(E31="",E31<>'Deal Strat'!$C$12,R31=""),"",SUMPRODUCT((E$4:E$303='Deal Strat'!$C$12)*(R$4:R$303>R31))+1+SUMPRODUCT((E$4:E$303='Deal Strat'!$C$12)*(R$4:R$303=R31)*(ROW(R$4:R$303)<ROW(R31)))) -> 2 | AM31: =IF(R31="","",RANK(R31,$R$4:$R$303,0)+COUNTIF($R$4:R31,R31)-1) -> 11 | AN31: =IF(OR($A31="",$R31=""),0,IF(Deal_Scope="All Deals",1,IF($E31=Deal_Scope,1,0))) -> 1 | AO31: =IF($AN31=0,0,Px_Par) -> 0.94 | AP31: =IF($H31="",0,MAX(0,($H31-Set_Date)/30.4375)) -> 0 | AQ31: =IF(AND(Ext_Flag="Yes",$AA31="Yes"),Ext_Months,0) -> 0 | AR31: =$AP31+$AQ31 -> 0 | AS31: =$AR31/12 -> 0 | AT31: =IF($AJ31="",0,MAX(0,$AJ31/12)) -> 0 | AU31: =MAX(Amort_Min,Amort_Term-$AH31/12) -> 21.5 | AV31: =MIN($AS31,Hold_Yrs) -> 0 | AW31: =IF($AN31=0,0,CEILING(MAX($AS31,0.0001),1)) -> 1 | AX31: =IF(AND($AN31=1,MAX($AS31,0.0001)<=Hold_Yrs),1,0) -> 1 | AY31: =$R31*$AO31 -> 81201900 | AZ31: =$R31*Acc_Int*$AN31 -> 129577.5 | BA31: =$AY31*Acq_Cost -> 609014.25 | BB31: =$AY31+$AZ31+$BA31 -> 81940492 | BC31: =IF(Fin_Flag="Yes",$AY31*Adv_Rate,0) -> 48721140 | BD31: =$BC31*Fin_UpFee -> 243605.7 | BE31: =$BB31-$BC31+$BD31 -> 33462957
A32: L-029 | B32: Northgate Residences | C32: MD | D32: Multifamily | E32: Deal 7 | F32: 87 | G32: 43040 | H32: 45597 | I32: 85 | J32: 120 | K32: Floating | M32: 0.0269 | N32: Monthly | O32: 46355 | P32: 0.1038 | R32: 43725000 | S32: 0.87 | T32: 0.1159 | U32: 1.69 | V32: 0.883 | W32: 0.908 | X32: 1996 | Y32: 2008 | Z32: Interest Only | AA32: No | AB32: Prepayable with Penalty | AC32: First Lien | AD32: Institutional Owner/Operator | AE32: Refinance | AF32: Matured | AG32: Fee Simple | AH32: =IF(G32="",0,ROUND((Strats!$C$4-G32)/30.4375,1)) -> 106.9 | AI32: =IF(K32="",0,IF(K32="Floating",Strats!$C$10+M32,L32)) -> 0.0719 | AJ32: =IF(OR(Z32="",Z32="Full Amortizing"),"",MAX(J32-AH32,0)) -> 13.1 | AK32: =IF(K32="",0,IF(K32="Floating",IF(P32<>"",MIN(IF(Q32<>"",MAX((Strats!$C$10+Strats!$C$11+M32),Q32),(Strats!$C$10+Strats!$C$11+M32)),P32),IF(Q32<>"",MAX((Strats!$C$10+Strats!$C$11+M32),Q32),(Strats!$C$10+Strats!$C$11+M32))),AI32)) -> 0.0869 | AL32: =IF(OR(E32="",E32<>'Deal Strat'!$C$12,R32=""),"",SUMPRODUCT((E$4:E$303='Deal Strat'!$C$12)*(R$4:R$303>R32))+1+SUMPRODUCT((E$4:E$303='Deal Strat'!$C$12)*(R$4:R$303=R32)*(ROW(R$4:R$303)<ROW(R32)))) | AM32: =IF(R32="","",RANK(R32,$R$4:$R$303,0)+COUNTIF($R$4:R32,R32)-1) -> 26 | AN32: =IF(OR($A32="",$R32=""),0,IF(Deal_Scope="All Deals",1,IF($E32=Deal_Scope,1,0))) -> 1 | AO32: =IF($AN32=0,0,Px_Par) -> 0.94 | AP32: =IF($H32="",0,MAX(0,($H32-Set_Date)/30.4375)) -> 0 | AQ32: =IF(AND(Ext_Flag="Yes",$AA32="Yes"),Ext_Months,0) -> 0 | AR32: =$AP32+$AQ32 -> 0 | AS32: =$AR32/12 -> 0 | AT32: =IF($AJ32="",0,MAX(0,$AJ32/12)) -> 1.0916667 | AU32: =MAX(Amort_Min,Amort_Term-$AH32/12) -> 21.091667 | AV32: =MIN($AS32,Hold_Yrs) -> 0 | AW32: =IF($AN32=0,0,CEILING(MAX($AS32,0.0001),1)) -> 1 | AX32: =IF(AND($AN32=1,MAX($AS32,0.0001)<=Hold_Yrs),1,0) -> 1 | AY32: =$R32*$AO32 -> 41101500 | AZ32: =$R32*Acc_Int*$AN32 -> 65587.5 | BA32: =$AY32*Acq_Cost -> 308261.25 | BB32: =$AY32+$AZ32+$BA32 -> 41475349 | BC32: =IF(Fin_Flag="Yes",$AY32*Adv_Rate,0) -> 24660900 | BD32: =$BC32*Fin_UpFee -> 123304.5 | BE32: =$BB32-$BC32+$BD32 -> 16937753
A33: L-030 | B33: Ridgeline Distribution Center | C33: GA | D33: Industrial | E33: Deal 8 | G33: 44228 | H33: 47880 | I33: 119 | J33: 0 | K33: Floating | M33: 0.0354 | N33: Monthly | O33: 46325 | P33: 0.0793 | R33: 14196000 | S33: 0.773 | T33: 0.068 | U33: 1.49 | V33: 0.534 | W33: 0.545 | X33: 2015 | Y33: 2024 | Z33: Full Amortizing | AA33: No | AB33: Prepayable with Penalty | AC33: First Lien | AD33: Institutional Owner/Operator | AE33: Refinance | AF33: Current | AG33: Fee Simple | AH33: =IF(G33="",0,ROUND((Strats!$C$4-G33)/30.4375,1)) -> 67.9 | AI33: =IF(K33="",0,IF(K33="Floating",Strats!$C$10+M33,L33)) -> 0.0804 | AJ33: =IF(OR(Z33="",Z33="Full Amortizing"),"",MAX(J33-AH33,0)) | AK33: =IF(K33="",0,IF(K33="Floating",IF(P33<>"",MIN(IF(Q33<>"",MAX((Strats!$C$10+Strats!$C$11+M33),Q33),(Strats!$C$10+Strats!$C$11+M33)),P33),IF(Q33<>"",MAX((Strats!$C$10+Strats!$C$11+M33),Q33),(Strats!$C$10+Strats!$C$11+M33))),AI33)) -> 0.0793 | AL33: =IF(OR(E33="",E33<>'Deal Strat'!$C$12,R33=""),"",SUMPRODUCT((E$4:E$303='Deal Strat'!$C$12)*(R$4:R$303>R33))+1+SUMPRODUCT((E$4:E$303='Deal Strat'!$C$12)*(R$4:R$303=R33)*(ROW(R$4:R$303)<ROW(R33)))) | AM33: =IF(R33="","",RANK(R33,$R$4:$R$303,0)+COUNTIF($R$4:R33,R33)-1) -> 35 | AN33: =IF(OR($A33="",$R33=""),0,IF(Deal_Scope="All Deals",1,IF($E33=Deal_Scope,1,0))) -> 1 | AO33: =IF($AN33=0,0,Px_Par) -> 0.94 | AP33: =IF($H33="",0,MAX(0,($H33-Set_Date)/30.4375)) -> 52.073922 | AQ33: =IF(AND(Ext_Flag="Yes",$AA33="Yes"),Ext_Months,0) -> 0 | AR33: =$AP33+$AQ33 -> 52.073922 | AS33: =$AR33/12 -> 4.3394935 | AT33: =IF($AJ33="",0,MAX(0,$AJ33/12)) -> 0 | AU33: =MAX(Amort_Min,Amort_Term-$AH33/12) -> 24.341667 | AV33: =MIN($AS33,Hold_Yrs) -> 4.3394935 | AW33: =IF($AN33=0,0,CEILING(MAX($AS33,0.0001),1)) -> 5 | AX33: =IF(AND($AN33=1,MAX($AS33,0.0001)<=Hold_Yrs),1,0) -> 1 | AY33: =$R33*$AO33 -> 13344240 | AZ33: =$R33*Acc_Int*$AN33 -> 21294 | BA33: =$AY33*Acq_Cost -> 100081.8 | BB33: =$AY33+$AZ33+$BA33 -> 13465616 | BC33: =IF(Fin_Flag="Yes",$AY33*Adv_Rate,0) -> 8006544 | BD33: =$BC33*Fin_UpFee -> 40032.72 | BE33: =$BB33-$BC33+$BD33 -> 5499104.5
A34: L-031 | B34: Harborview Logistics Park | C34: TX | D34: Industrial | E34: Deal 3 | G34: 44197 | H34: 46753 | I34: 84 | J34: 60 | K34: Floating | M34: 0.0322 | N34: Monthly | O34: 46325 | P34: 0.0877 | R34: 11649000 | S34: 0.839 | T34: 0.0608 | U34: 1.42 | V34: 0.532 | W34: 0.587 | X34: 2007 | Y34: 2026 | Z34: Interest Only | AA34: No | AB34: Prepayable with Penalty | AC34: Second Lien | AD34: HNW Investors | AE34: Acquisition | AF34: Current | AG34: Fee Simple | AH34: =IF(G34="",0,ROUND((Strats!$C$4-G34)/30.4375,1)) -> 68.9 | AI34: =IF(K34="",0,IF(K34="Floating",Strats!$C$10+M34,L34)) -> 0.0772 | AJ34: =IF(OR(Z34="",Z34="Full Amortizing"),"",MAX(J34-AH34,0)) -> 0 | AK34: =IF(K34="",0,IF(K34="Floating",IF(P34<>"",MIN(IF(Q34<>"",MAX((Strats!$C$10+Strats!$C$11+M34),Q34),(Strats!$C$10+Strats!$C$11+M34)),P34),IF(Q34<>"",MAX((Strats!$C$10+Strats!$C$11+M34),Q34),(Strats!$C$10+Strats!$C$11+M34))),AI34)) -> 0.0877 | AL34: =IF(OR(E34="",E34<>'Deal Strat'!$C$12,R34=""),"",SUMPRODUCT((E$4:E$303='Deal Strat'!$C$12)*(R$4:R$303>R34))+1+SUMPRODUCT((E$4:E$303='Deal Strat'!$C$12)*(R$4:R$303=R34)*(ROW(R$4:R$303)<ROW(R34)))) | AM34: =IF(R34="","",RANK(R34,$R$4:$R$303,0)+COUNTIF($R$4:R34,R34)-1) -> 36 | AN34: =IF(OR($A34="",$R34=""),0,IF(Deal_Scope="All Deals",1,IF($E34=Deal_Scope,1,0))) -> 1 | AO34: =IF($AN34=0,0,Px_Par) -> 0.94 | AP34: =IF($H34="",0,MAX(0,($H34-Set_Date)/30.4375)) -> 15.047228 | AQ34: =IF(AND(Ext_Flag="Yes",$AA34="Yes"),Ext_Months,0) -> 0 | AR34: =$AP34+$AQ34 -> 15.047228 | AS34: =$AR34/12 -> 1.2539357 | AT34: =IF($AJ34="",0,MAX(0,$AJ34/12)) -> 0 | AU34: =MAX(Amort_Min,Amort_Term-$AH34/12) -> 24.258333 | AV34: =MIN($AS34,Hold_Yrs) -> 1.2539357 | AW34: =IF($AN34=0,0,CEILING(MAX($AS34,0.0001),1)) -> 2 | AX34: =IF(AND($AN34=1,MAX($AS34,0.0001)<=Hold_Yrs),1,0) -> 1 | AY34: =$R34*$AO34 -> 10950060 | AZ34: =$R34*Acc_Int*$AN34 -> 17473.5 | BA34: =$AY34*Acq_Cost -> 82125.45 | BB34: =$AY34+$AZ34+$BA34 -> 11049659 | BC34: =IF(Fin_Flag="Yes",$AY34*Adv_Rate,0) -> 6570036 | BD34: =$BC34*Fin_UpFee -> 32850.18 | BE34: =$BB34-$BC34+$BD34 -> 4512473.1
A35: L-032 | B35: Kingston Exchange | C35: FL | D35: Office | E35: Deal 3 | G35: 44044 | H35: 47696 | I35: 119 | J35: 12 | K35: Floating | M35: 0.041 | N35: Monthly | O35: 46355 | R35: 139731000 | S35: 0.838 | T35: 0.0733 | U35: 1.43 | V35: 0.772 | W35: 0.803 | X35: 1971 | Y35: 1986 | Z35: Partial IO | AA35: No | AB35: Freely Prepayable | AC35: First Lien | AD35: Private REIT | AE35: Acquisition | AF35: Current | AG35: Fee Simple | AH35: =IF(G35="",0,ROUND((Strats!$C$4-G35)/30.4375,1)) -> 74 | AI35: =IF(K35="",0,IF(K35="Floating",Strats!$C$10+M35,L35)) -> 0.086 | AJ35: =IF(OR(Z35="",Z35="Full Amortizing"),"",MAX(J35-AH35,0)) -> 0 | AK35: =IF(K35="",0,IF(K35="Floating",IF(P35<>"",MIN(IF(Q35<>"",MAX((Strats!$C$10+Strats!$C$11+M35),Q35),(Strats!$C$10+Strats!$C$11+M35)),P35),IF(Q35<>"",MAX((Strats!$C$10+Strats!$C$11+M35),Q35),(Strats!$C$10+Strats!$C$11+M35))),AI35)) -> 0.101 | AL35: =IF(OR(E35="",E35<>'Deal Strat'!$C$12,R35=""),"",SUMPRODUCT((E$4:E$303='Deal Strat'!$C$12)*(R$4:R$303>R35))+1+SUMPRODUCT((E$4:E$303='Deal Strat'!$C$12)*(R$4:R$303=R35)*(ROW(R$4:R$303)<ROW(R35)))) | AM35: =IF(R35="","",RANK(R35,$R$4:$R$303,0)+COUNTIF($R$4:R35,R35)-1) -> 1 | AN35: =IF(OR($A35="",$R35=""),0,IF(Deal_Scope="All Deals",1,IF($E35=Deal_Scope,1,0))) -> 1 | AO35: =IF($AN35=0,0,Px_Par) -> 0.94 | AP35: =IF($H35="",0,MAX(0,($H35-Set_Date)/30.4375)) -> 46.028747 | AQ35: =IF(AND(Ext_Flag="Yes",$AA35="Yes"),Ext_Months,0) -> 0 | AR35: =$AP35+$AQ35 -> 46.028747 | AS35: =$AR35/12 -> 3.835729 | AT35: =IF($AJ35="",0,MAX(0,$AJ35/12)) -> 0 | AU35: =MAX(Amort_Min,Amort_Term-$AH35/12) -> 23.833333 | AV35: =MIN($AS35,Hold_Yrs) -> 3.835729 | AW35: =IF($AN35=0,0,CEILING(MAX($AS35,0.0001),1)) -> 4 | AX35: =IF(AND($AN35=1,MAX($AS35,0.0001)<=Hold_Yrs),1,0) -> 1 | AY35: =$R35*$AO35 -> 131347140 | AZ35: =$R35*Acc_Int*$AN35 -> 209596.5 | BA35: =$AY35*Acq_Cost -> 985103.55 | BB35: =$AY35+$AZ35+$BA35 -> 1.3254184e+08 | BC35: =IF(Fin_Flag="Yes",$AY35*Adv_Rate,0) -> 78808284 | BD35: =$BC35*Fin_UpFee -> 394041.42 | BE35: =$BB35-$BC35+$BD35 -> 54127597
A36: L-033 | B36: Parkside Apartments | C36: OH | D36: Multifamily | E36: Deal 6 | F36: 423 | G36: 43983 | H36: 45809 | I36: 59 | J36: 24 | K36: Floating | M36: 0.0357 | N36: Monthly | O36: 46295 | P36: 0.0945 | Q36: 0.0342 | R36: 43757000 | S36: 0.914 | T36: 0.0533 | U36: 1.72 | V36: 0.583 | W36: 0.624 | X36: 2008 | Y36: 2013 | Z36: Partial IO | AA36: No | AB36: Defeasance | AC36: First Lien | AD36: PE Fund | AE36: Acquisition | AF36: Current | AG36: Fee & Leasehold | AH36: =IF(G36="",0,ROUND((Strats!$C$4-G36)/30.4375,1)) -> 76 | AI36: =IF(K36="",0,IF(K36="Floating",Strats!$C$10+M36,L36)) -> 0.0807 | AJ36: =IF(OR(Z36="",Z36="Full Amortizing"),"",MAX(J36-AH36,0)) -> 0 | AK36: =IF(K36="",0,IF(K36="Floating",IF(P36<>"",MIN(IF(Q36<>"",MAX((Strats!$C$10+Strats!$C$11+M36),Q36),(Strats!$C$10+Strats!$C$11+M36)),P36),IF(Q36<>"",MAX((Strats!$C$10+Strats!$C$11+M36),Q36),(Strats!$C$10+Strats!$C$11+M36))),AI36)) -> 0.0945 | AL36: =IF(OR(E36="",E36<>'Deal Strat'!$C$12,R36=""),"",SUMPRODUCT((E$4:E$303='Deal Strat'!$C$12)*(R$4:R$303>R36))+1+SUMPRODUCT((E$4:E$303='Deal Strat'!$C$12)*(R$4:R$303=R36)*(ROW(R$4:R$303)<ROW(R36)))) | AM36: =IF(R36="","",RANK(R36,$R$4:$R$303,0)+COUNTIF($R$4:R36,R36)-1) -> 25 | AN36: =IF(OR($A36="",$R36=""),0,IF(Deal_Scope="All Deals",1,IF($E36=Deal_Scope,1,0))) -> 1 | AO36: =IF($AN36=0,0,Px_Par) -> 0.94 | AP36: =IF($H36="",0,MAX(0,($H36-Set_Date)/30.4375)) -> 0 | AQ36: =IF(AND(Ext_Flag="Yes",$AA36="Yes"),Ext_Months,0) -> 0 | AR36: =$AP36+$AQ36 -> 0 | AS36: =$AR36/12 -> 0 | AT36: =IF($AJ36="",0,MAX(0,$AJ36/12)) -> 0 | AU36: =MAX(Amort_Min,Amort_Term-$AH36/12) -> 23.666667 | AV36: =MIN($AS36,Hold_Yrs) -> 0 | AW36: =IF($AN36=0,0,CEILING(MAX($AS36,0.0001),1)) -> 1 | AX36: =IF(AND($AN36=1,MAX($AS36,0.0001)<=Hold_Yrs),1,0) -> 1 | AY36: =$R36*$AO36 -> 41131580 | AZ36: =$R36*Acc_Int*$AN36 -> 65635.5 | BA36: =$AY36*Acq_Cost -> 308486.85 | BB36: =$AY36+$AZ36+$BA36 -> 41505702 | BC36: =IF(Fin_Flag="Yes",$AY36*Adv_Rate,0) -> 24678948 | BD36: =$BC36*Fin_UpFee -> 123394.74 | BE36: =$BB36-$BC36+$BD36 -> 16950149
A37: L-034 | B37: Meridian Landing | C37: NC | D37: Multifamily | E37: Deal 2 | F37: 152 | G37: 44317 | H37: 47969 | I37: 119 | J37: 12 | K37: Fixed | L37: 0.0486 | N37: N/A | R37: 11376000 | S37: 0.901 | T37: 0.1039 | U37: 1.24 | V37: 0.724 | W37: 0.755 | X37: 2003 | Y37: 2016 | Z37: Partial IO | AA37: Yes | AB37: Defeasance | AC37: First Lien | AD37: PE Fund | AE37: Refinance | AF37: Current | AG37: Fee Simple | AH37: =IF(G37="",0,ROUND((Strats!$C$4-G37)/30.4375,1)) -> 65 | AI37: =IF(K37="",0,IF(K37="Floating",Strats!$C$10+M37,L37)) -> 0.0486 | AJ37: =IF(OR(Z37="",Z37="Full Amortizing"),"",MAX(J37-AH37,0)) -> 0 | AK37: =IF(K37="",0,IF(K37="Floating",IF(P37<>"",MIN(IF(Q37<>"",MAX((Strats!$C$10+Strats!$C$11+M37),Q37),(Strats!$C$10+Strats!$C$11+M37)),P37),IF(Q37<>"",MAX((Strats!$C$10+Strats!$C$11+M37),Q37),(Strats!$C$10+Strats!$C$11+M37))),AI37)) -> 0.0486 | AL37: =IF(OR(E37="",E37<>'Deal Strat'!$C$12,R37=""),"",SUMPRODUCT((E$4:E$303='Deal Strat'!$C$12)*(R$4:R$303>R37))+1+SUMPRODUCT((E$4:E$303='Deal Strat'!$C$12)*(R$4:R$303=R37)*(ROW(R$4:R$303)<ROW(R37)))) | AM37: =IF(R37="","",RANK(R37,$R$4:$R$303,0)+COUNTIF($R$4:R37,R37)-1) -> 37 | AN37: =IF(OR($A37="",$R37=""),0,IF(Deal_Scope="All Deals",1,IF($E37=Deal_Scope,1,0))) -> 1 | AO37: =IF($AN37=0,0,Px_Par) -> 0.94 | AP37: =IF($H37="",0,MAX(0,($H37-Set_Date)/30.4375)) -> 54.997947 | AQ37: =IF(AND(Ext_Flag="Yes",$AA37="Yes"),Ext_Months,0) -> 12 | AR37: =$AP37+$AQ37 -> 66.997947 | AS37: =$AR37/12 -> 5.5831622 | AT37: =IF($AJ37="",0,MAX(0,$AJ37/12)) -> 0 | AU37: =MAX(Amort_Min,Amort_Term-$AH37/12) -> 24.583333 | AV37: =MIN($AS37,Hold_Yrs) -> 5 | AW37: =IF($AN37=0,0,CEILING(MAX($AS37,0.0001),1)) -> 6 | AX37: =IF(AND($AN37=1,MAX($AS37,0.0001)<=Hold_Yrs),1,0) -> 0 | AY37: =$R37*$AO37 -> 10693440 | AZ37: =$R37*Acc_Int*$AN37 -> 17064 | BA37: =$AY37*Acq_Cost -> 80200.8 | BB37: =$AY37+$AZ37+$BA37 -> 10790705 | BC37: =IF(Fin_Flag="Yes",$AY37*Adv_Rate,0) -> 6416064 | BD37: =$BC37*Fin_UpFee -> 32080.32 | BE37: =$BB37-$BC37+$BD37 -> 4406721.1
A38: L-035 | B38: Pinehurst Apartments | C38: VA | D38: Multifamily | E38: Deal 1 | F38: 184 | G38: 43160 | H38: 46813 | I38: 119 | J38: 36 | K38: Floating | M38: 0.0199 | N38: Quarterly | O38: 46295 | P38: 0.0911 | Q38: 0.0347 | R38: 63125000 | S38: 0.817 | T38: 0.0745 | U38: 1.5 | V38: 0.583 | W38: 0.613 | X38: 1985 | Y38: 2009 | Z38: Partial IO | AA38: Yes | AB38: Defeasance | AC38: First Lien | AD38: Institutional Owner/Operator | AE38: Acquisition | AF38: Current | AG38: Fee Simple | AH38: =IF(G38="",0,ROUND((Strats!$C$4-G38)/30.4375,1)) -> 103 | AI38: =IF(K38="",0,IF(K38="Floating",Strats!$C$10+M38,L38)) -> 0.0649 | AJ38: =IF(OR(Z38="",Z38="Full Amortizing"),"",MAX(J38-AH38,0)) -> 0 | AK38: =IF(K38="",0,IF(K38="Floating",IF(P38<>"",MIN(IF(Q38<>"",MAX((Strats!$C$10+Strats!$C$11+M38),Q38),(Strats!$C$10+Strats!$C$11+M38)),P38),IF(Q38<>"",MAX((Strats!$C$10+Strats!$C$11+M38),Q38),(Strats!$C$10+Strats!$C$11+M38))),AI38)) -> 0.0799 | AL38: =IF(OR(E38="",E38<>'Deal Strat'!$C$12,R38=""),"",SUMPRODUCT((E$4:E$303='Deal Strat'!$C$12)*(R$4:R$303>R38))+1+SUMPRODUCT((E$4:E$303='Deal Strat'!$C$12)*(R$4:R$303=R38)*(ROW(R$4:R$303)<ROW(R38)))) -> 3 | AM38: =IF(R38="","",RANK(R38,$R$4:$R$303,0)+COUNTIF($R$4:R38,R38)-1) -> 18 | AN38: =IF(OR($A38="",$R38=""),0,IF(Deal_Scope="All Deals",1,IF($E38=Deal_Scope,1,0))) -> 1 | AO38: =IF($AN38=0,0,Px_Par) -> 0.94 | AP38: =IF($H38="",0,MAX(0,($H38-Set_Date)/30.4375)) -> 17.01848 | AQ38: =IF(AND(Ext_Flag="Yes",$AA38="Yes"),Ext_Months,0) -> 12 | AR38: =$AP38+$AQ38 -> 29.01848 | AS38: =$AR38/12 -> 2.4182067 | AT38: =IF($AJ38="",0,MAX(0,$AJ38/12)) -> 0 | AU38: =MAX(Amort_Min,Amort_Term-$AH38/12) -> 21.416667 | AV38: =MIN($AS38,Hold_Yrs) -> 2.4182067 | AW38: =IF($AN38=0,0,CEILING(MAX($AS38,0.0001),1)) -> 3 | AX38: =IF(AND($AN38=1,MAX($AS38,0.0001)<=Hold_Yrs),1,0) -> 1 | AY38: =$R38*$AO38 -> 59337500 | AZ38: =$R38*Acc_Int*$AN38 -> 94687.5 | BA38: =$AY38*Acq_Cost -> 445031.25 | BB38: =$AY38+$AZ38+$BA38 -> 59877219 | BC38: =IF(Fin_Flag="Yes",$AY38*Adv_Rate,0) -> 35602500 | BD38: =$BC38*Fin_UpFee -> 178012.5 | BE38: =$BB38-$BC38+$BD38 -> 24452731
A39: L-036 | B39: Oceanview Village | C39: WA | D39: Multifamily | E39: Deal 4 | F39: 250 | G39: 43191 | H39: 45017 | I39: 60 | J39: 24 | K39: Fixed | L39: 0.0589 | N39: N/A | R39: 38265000 | S39: 0.908 | T39: 0.1002 | U39: 0.84 | V39: 0.845 | W39: 0.88 | X39: 2013 | Z39: Partial IO | AA39: Yes | AB39: Yield Maintenance | AC39: First Lien | AD39: Institutional Owner/Operator | AE39: Refinance | AF39: Delinquent | AG39: Fee Simple | AH39: =IF(G39="",0,ROUND((Strats!$C$4-G39)/30.4375,1)) -> 102 | AI39: =IF(K39="",0,IF(K39="Floating",Strats!$C$10+M39,L39)) -> 0.0589 | AJ39: =IF(OR(Z39="",Z39="Full Amortizing"),"",MAX(J39-AH39,0)) -> 0 | AK39: =IF(K39="",0,IF(K39="Floating",IF(P39<>"",MIN(IF(Q39<>"",MAX((Strats!$C$10+Strats!$C$11+M39),Q39),(Strats!$C$10+Strats!$C$11+M39)),P39),IF(Q39<>"",MAX((Strats!$C$10+Strats!$C$11+M39),Q39),(Strats!$C$10+Strats!$C$11+M39))),AI39)) -> 0.0589 | AL39: =IF(OR(E39="",E39<>'Deal Strat'!$C$12,R39=""),"",SUMPRODUCT((E$4:E$303='Deal Strat'!$C$12)*(R$4:R$303>R39))+1+SUMPRODUCT((E$4:E$303='Deal Strat'!$C$12)*(R$4:R$303=R39)*(ROW(R$4:R$303)<ROW(R39)))) | AM39: =IF(R39="","",RANK(R39,$R$4:$R$303,0)+COUNTIF($R$4:R39,R39)-1) -> 27 | AN39: =IF(OR($A39="",$R39=""),0,IF(Deal_Scope="All Deals",1,IF($E39=Deal_Scope,1,0))) -> 1 | AO39: =IF($AN39=0,0,Px_Par) -> 0.94 | AP39: =IF($H39="",0,MAX(0,($H39-Set_Date)/30.4375)) -> 0 | AQ39: =IF(AND(Ext_Flag="Yes",$AA39="Yes"),Ext_Months,0) -> 12 | AR39: =$AP39+$AQ39 -> 12 | AS39: =$AR39/12 -> 1 | AT39: =IF($AJ39="",0,MAX(0,$AJ39/12)) -> 0 | AU39: =MAX(Amort_Min,Amort_Term-$AH39/12) -> 21.5 | AV39: =MIN($AS39,Hold_Yrs) -> 1 | AW39: =IF($AN39=0,0,CEILING(MAX($AS39,0.0001),1)) -> 1 | AX39: =IF(AND($AN39=1,MAX($AS39,0.0001)<=Hold_Yrs),1,0) -> 1 | AY39: =$R39*$AO39 -> 35969100 | AZ39: =$R39*Acc_Int*$AN39 -> 57397.5 | BA39: =$AY39*Acq_Cost -> 269768.25 | BB39: =$AY39+$AZ39+$BA39 -> 36296266 | BC39: =IF(Fin_Flag="Yes",$AY39*Adv_Rate,0) -> 21581460 | BD39: =$BC39*Fin_UpFee -> 107907.3 | BE39: =$BB39-$BC39+$BD39 -> 14822713
A40: L-037 | B40: Vista Terrace | C40: FL | D40: Multifamily | E40: Deal 5 | F40: 487 | G40: 43040 | H40: 44866 | I40: 59 | J40: 60 | K40: Floating | M40: 0.0305 | N40: Monthly | O40: 46355 | R40: 32760000 | S40: 0.948 | T40: 0.0751 | U40: 0.88 | V40: 0.783 | W40: 0.801 | X40: 1968 | Y40: 1983 | Z40: Partial IO | AA40: No | AB40: Prepayable with Penalty | AC40: First Lien | AD40: PE Fund | AE40: Refinance | AF40: REO | AG40: Fee Simple | AH40: =IF(G40="",0,ROUND((Strats!$C$4-G40)/30.4375,1)) -> 106.9 | AI40: =IF(K40="",0,IF(K40="Floating",Strats!$C$10+M40,L40)) -> 0.0755 | AJ40: =IF(OR(Z40="",Z40="Full Amortizing"),"",MAX(J40-AH40,0)) -> 0 | AK40: =IF(K40="",0,IF(K40="Floating",IF(P40<>"",MIN(IF(Q40<>"",MAX((Strats!$C$10+Strats!$C$11+M40),Q40),(Strats!$C$10+Strats!$C$11+M40)),P40),IF(Q40<>"",MAX((Strats!$C$10+Strats!$C$11+M40),Q40),(Strats!$C$10+Strats!$C$11+M40))),AI40)) -> 0.0905 | AL40: =IF(OR(E40="",E40<>'Deal Strat'!$C$12,R40=""),"",SUMPRODUCT((E$4:E$303='Deal Strat'!$C$12)*(R$4:R$303>R40))+1+SUMPRODUCT((E$4:E$303='Deal Strat'!$C$12)*(R$4:R$303=R40)*(ROW(R$4:R$303)<ROW(R40)))) | AM40: =IF(R40="","",RANK(R40,$R$4:$R$303,0)+COUNTIF($R$4:R40,R40)-1) -> 29 | AN40: =IF(OR($A40="",$R40=""),0,IF(Deal_Scope="All Deals",1,IF($E40=Deal_Scope,1,0))) -> 1 | AO40: =IF($AN40=0,0,Px_Par) -> 0.94 | AP40: =IF($H40="",0,MAX(0,($H40-Set_Date)/30.4375)) -> 0 | AQ40: =IF(AND(Ext_Flag="Yes",$AA40="Yes"),Ext_Months,0) -> 0 | AR40: =$AP40+$AQ40 -> 0 | AS40: =$AR40/12 -> 0 | AT40: =IF($AJ40="",0,MAX(0,$AJ40/12)) -> 0 | AU40: =MAX(Amort_Min,Amort_Term-$AH40/12) -> 21.091667 | AV40: =MIN($AS40,Hold_Yrs) -> 0 | AW40: =IF($AN40=0,0,CEILING(MAX($AS40,0.0001),1)) -> 1 | AX40: =IF(AND($AN40=1,MAX($AS40,0.0001)<=Hold_Yrs),1,0) -> 1 | AY40: =$R40*$AO40 -> 30794400 | AZ40: =$R40*Acc_Int*$AN40 -> 49140 | BA40: =$AY40*Acq_Cost -> 230958 | BB40: =$AY40+$AZ40+$BA40 -> 31074498 | BC40: =IF(Fin_Flag="Yes",$AY40*Adv_Rate,0) -> 18476640 | BD40: =$BC40*Fin_UpFee -> 92383.2 | BE40: =$BB40-$BC40+$BD40 -> 12690241
A41: L-038 | B41: Northgate Plaza | C41: OH | D41: Retail | E41: Deal 7 | G41: 45597 | H41: 49249 | I41: 120 | J41: 24 | K41: Floating | M41: 0.027 | N41: Monthly | O41: 46295 | R41: 5369000 | S41: 0.826 | T41: 0.1067 | U41: 0.92 | V41: 0.797 | W41: 0.811 | X41: 2000 | Y41: 2015 | Z41: Partial IO | AA41: No | AB41: Defeasance | AC41: First Lien | AD41: Institutional Owner/Operator | AE41: Refinance | AF41: Current | AG41: Fee Simple | AH41: =IF(G41="",0,ROUND((Strats!$C$4-G41)/30.4375,1)) -> 22.9 | AI41: =IF(K41="",0,IF(K41="Floating",Strats!$C$10+M41,L41)) -> 0.072 | AJ41: =IF(OR(Z41="",Z41="Full Amortizing"),"",MAX(J41-AH41,0)) -> 1.1 | AK41: =IF(K41="",0,IF(K41="Floating",IF(P41<>"",MIN(IF(Q41<>"",MAX((Strats!$C$10+Strats!$C$11+M41),Q41),(Strats!$C$10+Strats!$C$11+M41)),P41),IF(Q41<>"",MAX((Strats!$C$10+Strats!$C$11+M41),Q41),(Strats!$C$10+Strats!$C$11+M41))),AI41)) -> 0.087 | AL41: =IF(OR(E41="",E41<>'Deal Strat'!$C$12,R41=""),"",SUMPRODUCT((E$4:E$303='Deal Strat'!$C$12)*(R$4:R$303>R41))+1+SUMPRODUCT((E$4:E$303='Deal Strat'!$C$12)*(R$4:R$303=R41)*(ROW(R$4:R$303)<ROW(R41)))) | AM41: =IF(R41="","",RANK(R41,$R$4:$R$303,0)+COUNTIF($R$4:R41,R41)-1) -> 45 | AN41: =IF(OR($A41="",$R41=""),0,IF(Deal_Scope="All Deals",1,IF($E41=Deal_Scope,1,0))) -> 1 | AO41: =IF($AN41=0,0,Px_Par) -> 0.94 | AP41: =IF($H41="",0,MAX(0,($H41-Set_Date)/30.4375)) -> 97.051335 | AQ41: =IF(AND(Ext_Flag="Yes",$AA41="Yes"),Ext_Months,0) -> 0 | AR41: =$AP41+$AQ41 -> 97.051335 | AS41: =$AR41/12 -> 8.0876112 | AT41: =IF($AJ41="",0,MAX(0,$AJ41/12)) -> 0.091666667 | AU41: =MAX(Amort_Min,Amort_Term-$AH41/12) -> 28.091667 | AV41: =MIN($AS41,Hold_Yrs) -> 5 | AW41: =IF($AN41=0,0,CEILING(MAX($AS41,0.0001),1)) -> 9 | AX41: =IF(AND($AN41=1,MAX($AS41,0.0001)<=Hold_Yrs),1,0) -> 0 | AY41: =$R41*$AO41 -> 5046860 | AZ41: =$R41*Acc_Int*$AN41 -> 8053.5 | BA41: =$AY41*Acq_Cost -> 37851.45 | BB41: =$AY41+$AZ41+$BA41 -> 5092765 | BC41: =IF(Fin_Flag="Yes",$AY41*Adv_Rate,0) -> 3028116 | BD41: =$BC41*Fin_UpFee -> 15140.58 | BE41: =$BB41-$BC41+$BD41 -> 2079789.5
A42: L-039 | B42: Summit Plaza | C42: OH | D42: Office | E42: Deal 5 | G42: 43862 | H42: 47515 | I42: 119 | J42: 0 | K42: Floating | M42: 0.0419 | N42: Monthly | O42: 46325 | R42: 4499000 | S42: 0.857 | T42: 0.0979 | U42: 1.23 | V42: 0.827 | W42: 0.868 | X42: 2022 | Z42: Full Amortizing | AA42: Yes | AB42: Freely Prepayable | AC42: First Lien | AD42: Private REIT | AE42: Refinance | AF42: Current | AG42: Fee Simple | AH42: =IF(G42="",0,ROUND((Strats!$C$4-G42)/30.4375,1)) -> 79.9 | AI42: =IF(K42="",0,IF(K42="Floating",Strats!$C$10+M42,L42)) -> 0.0869 | AJ42: =IF(OR(Z42="",Z42="Full Amortizing"),"",MAX(J42-AH42,0)) | AK42: =IF(K42="",0,IF(K42="Floating",IF(P42<>"",MIN(IF(Q42<>"",MAX((Strats!$C$10+Strats!$C$11+M42),Q42),(Strats!$C$10+Strats!$C$11+M42)),P42),IF(Q42<>"",MAX((Strats!$C$10+Strats!$C$11+M42),Q42),(Strats!$C$10+Strats!$C$11+M42))),AI42)) -> 0.1019 | AL42: =IF(OR(E42="",E42<>'Deal Strat'!$C$12,R42=""),"",SUMPRODUCT((E$4:E$303='Deal Strat'!$C$12)*(R$4:R$303>R42))+1+SUMPRODUCT((E$4:E$303='Deal Strat'!$C$12)*(R$4:R$303=R42)*(ROW(R$4:R$303)<ROW(R42)))) | AM42: =IF(R42="","",RANK(R42,$R$4:$R$303,0)+COUNTIF($R$4:R42,R42)-1) -> 50 | AN42: =IF(OR($A42="",$R42=""),0,IF(Deal_Scope="All Deals",1,IF($E42=Deal_Scope,1,0))) -> 1 | AO42: =IF($AN42=0,0,Px_Par) -> 0.94 | AP42: =IF($H42="",0,MAX(0,($H42-Set_Date)/30.4375)) -> 40.082136 | AQ42: =IF(AND(Ext_Flag="Yes",$AA42="Yes"),Ext_Months,0) -> 12 | AR42: =$AP42+$AQ42 -> 52.082136 | AS42: =$AR42/12 -> 4.340178 | AT42: =IF($AJ42="",0,MAX(0,$AJ42/12)) -> 0 | AU42: =MAX(Amort_Min,Amort_Term-$AH42/12) -> 23.341667 | AV42: =MIN($AS42,Hold_Yrs) -> 4.340178 | AW42: =IF($AN42=0,0,CEILING(MAX($AS42,0.0001),1)) -> 5 | AX42: =IF(AND($AN42=1,MAX($AS42,0.0001)<=Hold_Yrs),1,0) -> 1 | AY42: =$R42*$AO42 -> 4229060 | AZ42: =$R42*Acc_Int*$AN42 -> 6748.5 | BA42: =$AY42*Acq_Cost -> 31717.95 | BB42: =$AY42+$AZ42+$BA42 -> 4267526.5 | BC42: =IF(Fin_Flag="Yes",$AY42*Adv_Rate,0) -> 2537436 | BD42: =$BC42*Fin_UpFee -> 12687.18 | BE42: =$BB42-$BC42+$BD42 -> 1742777.6
A43: L-040 | B43: Juniper Terrace | C43: VA | D43: Multifamily | E43: Deal 4 | F43: 268 | G43: 43191 | H43: 46844 | I43: 120 | J43: 0 | K43: Fixed | L43: 0.0462 | N43: N/A | R43: 81125000 | S43: 0.814 | T43: 0.1139 | U43: 1.39 | V43: 0.584 | W43: 0.62 | X43: 1972 | Y43: 1982 | Z43: Full Amortizing | AA43: Yes | AB43: Yield Maintenance | AC43: First Lien | AD43: Institutional Owner/Operator | AE43: Recapitalization | AF43: Current | AG43: Fee Simple | AH43: =IF(G43="",0,ROUND((Strats!$C$4-G43)/30.4375,1)) -> 102 | AI43: =IF(K43="",0,IF(K43="Floating",Strats!$C$10+M43,L43)) -> 0.0462 | AJ43: =IF(OR(Z43="",Z43="Full Amortizing"),"",MAX(J43-AH43,0)) | AK43: =IF(K43="",0,IF(K43="Floating",IF(P43<>"",MIN(IF(Q43<>"",MAX((Strats!$C$10+Strats!$C$11+M43),Q43),(Strats!$C$10+Strats!$C$11+M43)),P43),IF(Q43<>"",MAX((Strats!$C$10+Strats!$C$11+M43),Q43),(Strats!$C$10+Strats!$C$11+M43))),AI43)) -> 0.0462 | AL43: =IF(OR(E43="",E43<>'Deal Strat'!$C$12,R43=""),"",SUMPRODUCT((E$4:E$303='Deal Strat'!$C$12)*(R$4:R$303>R43))+1+SUMPRODUCT((E$4:E$303='Deal Strat'!$C$12)*(R$4:R$303=R43)*(ROW(R$4:R$303)<ROW(R43)))) | AM43: =IF(R43="","",RANK(R43,$R$4:$R$303,0)+COUNTIF($R$4:R43,R43)-1) -> 13 | AN43: =IF(OR($A43="",$R43=""),0,IF(Deal_Scope="All Deals",1,IF($E43=Deal_Scope,1,0))) -> 1 | AO43: =IF($AN43=0,0,Px_Par) -> 0.94 | AP43: =IF($H43="",0,MAX(0,($H43-Set_Date)/30.4375)) -> 18.036961 | AQ43: =IF(AND(Ext_Flag="Yes",$AA43="Yes"),Ext_Months,0) -> 12 | AR43: =$AP43+$AQ43 -> 30.036961 | AS43: =$AR43/12 -> 2.5030801 | AT43: =IF($AJ43="",0,MAX(0,$AJ43/12)) -> 0 | AU43: =MAX(Amort_Min,Amort_Term-$AH43/12) -> 21.5 | AV43: =MIN($AS43,Hold_Yrs) -> 2.5030801 | AW43: =IF($AN43=0,0,CEILING(MAX($AS43,0.0001),1)) -> 3 | AX43: =IF(AND($AN43=1,MAX($AS43,0.0001)<=Hold_Yrs),1,0) -> 1 | AY43: =$R43*$AO43 -> 76257500 | AZ43: =$R43*Acc_Int*$AN43 -> 121687.5 | BA43: =$AY43*Acq_Cost -> 571931.25 | BB43: =$AY43+$AZ43+$BA43 -> 76951119 | BC43: =IF(Fin_Flag="Yes",$AY43*Adv_Rate,0) -> 45754500 | BD43: =$BC43*Fin_UpFee -> 228772.5 | BE43: =$BB43-$BC43+$BD43 -> 31425391
A44: L-041 | B44: Ridgeline Apartments | C44: TX | D44: Multifamily | E44: Deal 7 | F44: 337 | G44: 43160 | H44: 44986 | I44: 60 | J44: 0 | K44: Floating | M44: 0.0308 | N44: Quarterly | O44: 46355 | P44: 0.0965 | R44: 30613000 | S44: 0.962 | T44: 0.113 | U44: 1.38 | V44: 0.89 | W44: 0.93 | X44: 1992 | Y44: 2006 | Z44: Full Amortizing | AA44: Yes | AB44: Prepayable with Penalty | AC44: First Lien | AD44: Institutional Owner/Operator | AE44: Refinance | AF44: Current | AG44: Fee Simple | AH44: =IF(G44="",0,ROUND((Strats!$C$4-G44)/30.4375,1)) -> 103 | AI44: =IF(K44="",0,IF(K44="Floating",Strats!$C$10+M44,L44)) -> 0.0758 | AJ44: =IF(OR(Z44="",Z44="Full Amortizing"),"",MAX(J44-AH44,0)) | AK44: =IF(K44="",0,IF(K44="Floating",IF(P44<>"",MIN(IF(Q44<>"",MAX((Strats!$C$10+Strats!$C$11+M44),Q44),(Strats!$C$10+Strats!$C$11+M44)),P44),IF(Q44<>"",MAX((Strats!$C$10+Strats!$C$11+M44),Q44),(Strats!$C$10+Strats!$C$11+M44))),AI44)) -> 0.0908 | AL44: =IF(OR(E44="",E44<>'Deal Strat'!$C$12,R44=""),"",SUMPRODUCT((E$4:E$303='Deal Strat'!$C$12)*(R$4:R$303>R44))+1+SUMPRODUCT((E$4:E$303='Deal Strat'!$C$12)*(R$4:R$303=R44)*(ROW(R$4:R$303)<ROW(R44)))) | AM44: =IF(R44="","",RANK(R44,$R$4:$R$303,0)+COUNTIF($R$4:R44,R44)-1) -> 30 | AN44: =IF(OR($A44="",$R44=""),0,IF(Deal_Scope="All Deals",1,IF($E44=Deal_Scope,1,0))) -> 1 | AO44: =IF($AN44=0,0,Px_Par) -> 0.94 | AP44: =IF($H44="",0,MAX(0,($H44-Set_Date)/30.4375)) -> 0 | AQ44: =IF(AND(Ext_Flag="Yes",$AA44="Yes"),Ext_Months,0) -> 12 | AR44: =$AP44+$AQ44 -> 12 | AS44: =$AR44/12 -> 1 | AT44: =IF($AJ44="",0,MAX(0,$AJ44/12)) -> 0 | AU44: =MAX(Amort_Min,Amort_Term-$AH44/12) -> 21.416667 | AV44: =MIN($AS44,Hold_Yrs) -> 1 | AW44: =IF($AN44=0,0,CEILING(MAX($AS44,0.0001),1)) -> 1 | AX44: =IF(AND($AN44=1,MAX($AS44,0.0001)<=Hold_Yrs),1,0) -> 1 | AY44: =$R44*$AO44 -> 28776220 | AZ44: =$R44*Acc_Int*$AN44 -> 45919.5 | BA44: =$AY44*Acq_Cost -> 215821.65 | BB44: =$AY44+$AZ44+$BA44 -> 29037961 | BC44: =IF(Fin_Flag="Yes",$AY44*Adv_Rate,0) -> 17265732 | BD44: =$BC44*Fin_UpFee -> 86328.66 | BE44: =$BB44-$BC44+$BD44 -> 11858558
A45: L-042 | B45: Summit Exchange | C45: MD | D45: Office | E45: Deal 4 | G45: 45444 | H45: 47270 | I45: 59 | J45: 12 | K45: Fixed | L45: 0.054 | N45: N/A | R45: 5039000 | S45: 0.774 | T45: 0.1002 | U45: 1.44 | V45: 0.649 | W45: 0.66 | X45: 2015 | Z45: Partial IO | AA45: No | AB45: Defeasance | AC45: First Lien | AD45: Institutional Owner/Operator | AE45: Acquisition | AF45: Current | AG45: Fee Simple | AH45: =IF(G45="",0,ROUND((Strats!$C$4-G45)/30.4375,1)) -> 28 | AI45: =IF(K45="",0,IF(K45="Floating",Strats!$C$10+M45,L45)) -> 0.054 | AJ45: =IF(OR(Z45="",Z45="Full Amortizing"),"",MAX(J45-AH45,0)) -> 0 | AK45: =IF(K45="",0,IF(K45="Floating",IF(P45<>"",MIN(IF(Q45<>"",MAX((Strats!$C$10+Strats!$C$11+M45),Q45),(Strats!$C$10+Strats!$C$11+M45)),P45),IF(Q45<>"",MAX((Strats!$C$10+Strats!$C$11+M45),Q45),(Strats!$C$10+Strats!$C$11+M45))),AI45)) -> 0.054 | AL45: =IF(OR(E45="",E45<>'Deal Strat'!$C$12,R45=""),"",SUMPRODUCT((E$4:E$303='Deal Strat'!$C$12)*(R$4:R$303>R45))+1+SUMPRODUCT((E$4:E$303='Deal Strat'!$C$12)*(R$4:R$303=R45)*(ROW(R$4:R$303)<ROW(R45)))) | AM45: =IF(R45="","",RANK(R45,$R$4:$R$303,0)+COUNTIF($R$4:R45,R45)-1) -> 48 | AN45: =IF(OR($A45="",$R45=""),0,IF(Deal_Scope="All Deals",1,IF($E45=Deal_Scope,1,0))) -> 1 | AO45: =IF($AN45=0,0,Px_Par) -> 0.94 | AP45: =IF($H45="",0,MAX(0,($H45-Set_Date)/30.4375)) -> 32.032854 | AQ45: =IF(AND(Ext_Flag="Yes",$AA45="Yes"),Ext_Months,0) -> 0 | AR45: =$AP45+$AQ45 -> 32.032854 | AS45: =$AR45/12 -> 2.6694045 | AT45: =IF($AJ45="",0,MAX(0,$AJ45/12)) -> 0 | AU45: =MAX(Amort_Min,Amort_Term-$AH45/12) -> 27.666667 | AV45: =MIN($AS45,Hold_Yrs) -> 2.6694045 | AW45: =IF($AN45=0,0,CEILING(MAX($AS45,0.0001),1)) -> 3 | AX45: =IF(AND($AN45=1,MAX($AS45,0.0001)<=Hold_Yrs),1,0) -> 1 | AY45: =$R45*$AO45 -> 4736660 | AZ45: =$R45*Acc_Int*$AN45 -> 7558.5 | BA45: =$AY45*Acq_Cost -> 35524.95 | BB45: =$AY45+$AZ45+$BA45 -> 4779743.5 | BC45: =IF(Fin_Flag="Yes",$AY45*Adv_Rate,0) -> 2841996 | BD45: =$BC45*Fin_UpFee -> 14209.98 | BE45: =$BB45-$BC45+$BD45 -> 1951957.4
A46: L-043 | B46: Quarry Warehouse | C46: NC | D46: Industrial | E46: Deal 8 | G46: 43466 | H46: 47119 | I46: 120 | J46: 60 | K46: Floating | M46: 0.0248 | N46: Monthly | O46: 46295 | P46: 0.1052 | Q46: 0.0398 | R46: 8680000 | S46: 0.877 | T46: 0.0663 | U46: 1.97 | V46: 0.707 | W46: 0.739 | X46: 1989 | Y46: 1999 | Z46: Partial IO | AA46: Yes | AB46: Defeasance | AC46: Second Lien | AD46: Institutional Owner/Operator | AE46: Refinance | AF46: Current | AG46: Fee Simple | AH46: =IF(G46="",0,ROUND((Strats!$C$4-G46)/30.4375,1)) -> 92.9 | AI46: =IF(K46="",0,IF(K46="Floating",Strats!$C$10+M46,L46)) -> 0.0698 | AJ46: =IF(OR(Z46="",Z46="Full Amortizing"),"",MAX(J46-AH46,0)) -> 0 | AK46: =IF(K46="",0,IF(K46="Floating",IF(P46<>"",MIN(IF(Q46<>"",MAX((Strats!$C$10+Strats!$C$11+M46),Q46),(Strats!$C$10+Strats!$C$11+M46)),P46),IF(Q46<>"",MAX((Strats!$C$10+Strats!$C$11+M46),Q46),(Strats!$C$10+Strats!$C$11+M46))),AI46)) -> 0.0848 | AL46: =IF(OR(E46="",E46<>'Deal Strat'!$C$12,R46=""),"",SUMPRODUCT((E$4:E$303='Deal Strat'!$C$12)*(R$4:R$303>R46))+1+SUMPRODUCT((E$4:E$303='Deal Strat'!$C$12)*(R$4:R$303=R46)*(ROW(R$4:R$303)<ROW(R46)))) | AM46: =IF(R46="","",RANK(R46,$R$4:$R$303,0)+COUNTIF($R$4:R46,R46)-1) -> 39 | AN46: =IF(OR($A46="",$R46=""),0,IF(Deal_Scope="All Deals",1,IF($E46=Deal_Scope,1,0))) -> 1 | AO46: =IF($AN46=0,0,Px_Par) -> 0.94 | AP46: =IF($H46="",0,MAX(0,($H46-Set_Date)/30.4375)) -> 27.071869 | AQ46: =IF(AND(Ext_Flag="Yes",$AA46="Yes"),Ext_Months,0) -> 12 | AR46: =$AP46+$AQ46 -> 39.071869 | AS46: =$AR46/12 -> 3.255989 | AT46: =IF($AJ46="",0,MAX(0,$AJ46/12)) -> 0 | AU46: =MAX(Amort_Min,Amort_Term-$AH46/12) -> 22.258333 | AV46: =MIN($AS46,Hold_Yrs) -> 3.255989 | AW46: =IF($AN46=0,0,CEILING(MAX($AS46,0.0001),1)) -> 4 | AX46: =IF(AND($AN46=1,MAX($AS46,0.0001)<=Hold_Yrs),1,0) -> 1 | AY46: =$R46*$AO46 -> 8159200 | AZ46: =$R46*Acc_Int*$AN46 -> 13020 | BA46: =$AY46*Acq_Cost -> 61194 | BB46: =$AY46+$AZ46+$BA46 -> 8233414 | BC46: =IF(Fin_Flag="Yes",$AY46*Adv_Rate,0) -> 4895520 | BD46: =$BC46*Fin_UpFee -> 24477.6 | BE46: =$BB46-$BC46+$BD46 -> 3362371.6
A47: L-044 | B47: Belmont Plaza | C47: NC | D47: Retail | E47: Deal 6 | G47: 44409 | H47: 46235 | I47: 60 | J47: 60 | K47: Floating | M47: 0.0254 | N47: Quarterly | O47: 46295 | P47: 0.0973 | R47: 78707000 | S47: 0.943 | T47: 0.0956 | U47: 0.85 | V47: 0.641 | W47: 0.681 | X47: 2015 | Y47: 2024 | Z47: Partial IO | AA47: Yes | AB47: Yield Maintenance | AC47: First Lien | AD47: Institutional Owner/Operator | AE47: Refinance | AF47: Current | AG47: Fee Simple | AH47: =IF(G47="",0,ROUND((Strats!$C$4-G47)/30.4375,1)) -> 62 | AI47: =IF(K47="",0,IF(K47="Floating",Strats!$C$10+M47,L47)) -> 0.0704 | AJ47: =IF(OR(Z47="",Z47="Full Amortizing"),"",MAX(J47-AH47,0)) -> 0 | AK47: =IF(K47="",0,IF(K47="Floating",IF(P47<>"",MIN(IF(Q47<>"",MAX((Strats!$C$10+Strats!$C$11+M47),Q47),(Strats!$C$10+Strats!$C$11+M47)),P47),IF(Q47<>"",MAX((Strats!$C$10+Strats!$C$11+M47),Q47),(Strats!$C$10+Strats!$C$11+M47))),AI47)) -> 0.0854 | AL47: =IF(OR(E47="",E47<>'Deal Strat'!$C$12,R47=""),"",SUMPRODUCT((E$4:E$303='Deal Strat'!$C$12)*(R$4:R$303>R47))+1+SUMPRODUCT((E$4:E$303='Deal Strat'!$C$12)*(R$4:R$303=R47)*(ROW(R$4:R$303)<ROW(R47)))) | AM47: =IF(R47="","",RANK(R47,$R$4:$R$303,0)+COUNTIF($R$4:R47,R47)-1) -> 14 | AN47: =IF(OR($A47="",$R47=""),0,IF(Deal_Scope="All Deals",1,IF($E47=Deal_Scope,1,0))) -> 1 | AO47: =IF($AN47=0,0,Px_Par) -> 0.94 | AP47: =IF($H47="",0,MAX(0,($H47-Set_Date)/30.4375)) -> 0 | AQ47: =IF(AND(Ext_Flag="Yes",$AA47="Yes"),Ext_Months,0) -> 12 | AR47: =$AP47+$AQ47 -> 12 | AS47: =$AR47/12 -> 1 | AT47: =IF($AJ47="",0,MAX(0,$AJ47/12)) -> 0 | AU47: =MAX(Amort_Min,Amort_Term-$AH47/12) -> 24.833333 | AV47: =MIN($AS47,Hold_Yrs) -> 1 | AW47: =IF($AN47=0,0,CEILING(MAX($AS47,0.0001),1)) -> 1 | AX47: =IF(AND($AN47=1,MAX($AS47,0.0001)<=Hold_Yrs),1,0) -> 1 | AY47: =$R47*$AO47 -> 73984580 | AZ47: =$R47*Acc_Int*$AN47 -> 118060.5 | BA47: =$AY47*Acq_Cost -> 554884.35 | BB47: =$AY47+$AZ47+$BA47 -> 74657525 | BC47: =IF(Fin_Flag="Yes",$AY47*Adv_Rate,0) -> 44390748 | BD47: =$BC47*Fin_UpFee -> 221953.74 | BE47: =$BB47-$BC47+$BD47 -> 30488731
A48: L-045 | B48: Timberline Hotel & Suites | C48: OH | D48: Hotel | E48: Deal 3 | G48: 45474 | H48: 49126 | I48: 120 | J48: 36 | K48: Floating | M48: 0.037 | N48: Monthly | O48: 46355 | P48: 0.1071 | R48: 54538000 | S48: 0.99 | T48: 0.0441 | U48: 1.83 | V48: 0.736 | W48: 0.768 | X48: 1970 | Z48: Partial IO | AA48: No | AB48: Yield Maintenance | AC48: First Lien | AD48: Institutional Owner/Operator | AE48: Acquisition | AF48: Current | AG48: Fee Simple | AH48: =IF(G48="",0,ROUND((Strats!$C$4-G48)/30.4375,1)) -> 27 | AI48: =IF(K48="",0,IF(K48="Floating",Strats!$C$10+M48,L48)) -> 0.082 | AJ48: =IF(OR(Z48="",Z48="Full Amortizing"),"",MAX(J48-AH48,0)) -> 9 | AK48: =IF(K48="",0,IF(K48="Floating",IF(P48<>"",MIN(IF(Q48<>"",MAX((Strats!$C$10+Strats!$C$11+M48),Q48),(Strats!$C$10+Strats!$C$11+M48)),P48),IF(Q48<>"",MAX((Strats!$C$10+Strats!$C$11+M48),Q48),(Strats!$C$10+Strats!$C$11+M48))),AI48)) -> 0.097 | AL48: =IF(OR(E48="",E48<>'Deal Strat'!$C$12,R48=""),"",SUMPRODUCT((E$4:E$303='Deal Strat'!$C$12)*(R$4:R$303>R48))+1+SUMPRODUCT((E$4:E$303='Deal Strat'!$C$12)*(R$4:R$303=R48)*(ROW(R$4:R$303)<ROW(R48)))) | AM48: =IF(R48="","",RANK(R48,$R$4:$R$303,0)+COUNTIF($R$4:R48,R48)-1) -> 20 | AN48: =IF(OR($A48="",$R48=""),0,IF(Deal_Scope="All Deals",1,IF($E48=Deal_Scope,1,0))) -> 1 | AO48: =IF($AN48=0,0,Px_Par) -> 0.94 | AP48: =IF($H48="",0,MAX(0,($H48-Set_Date)/30.4375)) -> 93.010267 | AQ48: =IF(AND(Ext_Flag="Yes",$AA48="Yes"),Ext_Months,0) -> 0 | AR48: =$AP48+$AQ48 -> 93.010267 | AS48: =$AR48/12 -> 7.7508556 | AT48: =IF($AJ48="",0,MAX(0,$AJ48/12)) -> 0.75 | AU48: =MAX(Amort_Min,Amort_Term-$AH48/12) -> 27.75 | AV48: =MIN($AS48,Hold_Yrs) -> 5 | AW48: =IF($AN48=0,0,CEILING(MAX($AS48,0.0001),1)) -> 8 | AX48: =IF(AND($AN48=1,MAX($AS48,0.0001)<=Hold_Yrs),1,0) -> 0 | AY48: =$R48*$AO48 -> 51265720 | AZ48: =$R48*Acc_Int*$AN48 -> 81807 | BA48: =$AY48*Acq_Cost -> 384492.9 | BB48: =$AY48+$AZ48+$BA48 -> 51732020 | BC48: =IF(Fin_Flag="Yes",$AY48*Adv_Rate,0) -> 30759432 | BD48: =$BC48*Fin_UpFee -> 153797.16 | BE48: =$BB48-$BC48+$BD48 -> 21126385
A49: L-046 | B49: Northgate Flats | C49: NC | D49: Multifamily | E49: Deal 2 | F49: 182 | G49: 43374 | H49: 45200 | I49: 60 | J49: 60 | K49: Fixed | L49: 0.0571 | N49: N/A | R49: 113370000 | S49: 0.92 | T49: 0.1329 | U49: 0.7 | V49: 0.804 | W49: 0.846 | X49: 1993 | Y49: 2014 | Z49: Partial IO | AA49: Yes | AB49: Yield Maintenance | AC49: First Lien | AD49: Institutional Owner/Operator | AE49: Acquisition | AF49: Matured | AG49: Fee Simple | AH49: =IF(G49="",0,ROUND((Strats!$C$4-G49)/30.4375,1)) -> 96 | AI49: =IF(K49="",0,IF(K49="Floating",Strats!$C$10+M49,L49)) -> 0.0571 | AJ49: =IF(OR(Z49="",Z49="Full Amortizing"),"",MAX(J49-AH49,0)) -> 0 | AK49: =IF(K49="",0,IF(K49="Floating",IF(P49<>"",MIN(IF(Q49<>"",MAX((Strats!$C$10+Strats!$C$11+M49),Q49),(Strats!$C$10+Strats!$C$11+M49)),P49),IF(Q49<>"",MAX((Strats!$C$10+Strats!$C$11+M49),Q49),(Strats!$C$10+Strats!$C$11+M49))),AI49)) -> 0.0571 | AL49: =IF(OR(E49="",E49<>'Deal Strat'!$C$12,R49=""),"",SUMPRODUCT((E$4:E$303='Deal Strat'!$C$12)*(R$4:R$303>R49))+1+SUMPRODUCT((E$4:E$303='Deal Strat'!$C$12)*(R$4:R$303=R49)*(ROW(R$4:R$303)<ROW(R49)))) | AM49: =IF(R49="","",RANK(R49,$R$4:$R$303,0)+COUNTIF($R$4:R49,R49)-1) -> 7 | AN49: =IF(OR($A49="",$R49=""),0,IF(Deal_Scope="All Deals",1,IF($E49=Deal_Scope,1,0))) -> 1 | AO49: =IF($AN49=0,0,Px_Par) -> 0.94 | AP49: =IF($H49="",0,MAX(0,($H49-Set_Date)/30.4375)) -> 0 | AQ49: =IF(AND(Ext_Flag="Yes",$AA49="Yes"),Ext_Months,0) -> 12 | AR49: =$AP49+$AQ49 -> 12 | AS49: =$AR49/12 -> 1 | AT49: =IF($AJ49="",0,MAX(0,$AJ49/12)) -> 0 | AU49: =MAX(Amort_Min,Amort_Term-$AH49/12) -> 22 | AV49: =MIN($AS49,Hold_Yrs) -> 1 | AW49: =IF($AN49=0,0,CEILING(MAX($AS49,0.0001),1)) -> 1 | AX49: =IF(AND($AN49=1,MAX($AS49,0.0001)<=Hold_Yrs),1,0) -> 1 | AY49: =$R49*$AO49 -> 106567800 | AZ49: =$R49*Acc_Int*$AN49 -> 170055 | BA49: =$AY49*Acq_Cost -> 799258.5 | BB49: =$AY49+$AZ49+$BA49 -> 1.0753711e+08 | BC49: =IF(Fin_Flag="Yes",$AY49*Adv_Rate,0) -> 63940680 | BD49: =$BC49*Fin_UpFee -> 319703.4 | BE49: =$BB49-$BC49+$BD49 -> 43916137
A50: L-047 | B50: Willow Inn | C50: CA | D50: Hotel | E50: Deal 5 | G50: 43922 | H50: 47574 | I50: 120 | J50: 36 | K50: Floating | M50: 0.0346 | N50: Monthly | O50: 46355 | P50: 0.108 | Q50: 0.0399 | R50: 5259000 | S50: 0.877 | T50: 0.0991 | U50: 0.88 | V50: 0.531 | W50: 0.582 | X50: 1966 | Y50: 1991 | Z50: Interest Only | AA50: No | AB50: Prepayable with Penalty | AC50: First Lien | AD50: Institutional Owner/Operator | AE50: Refinance | AF50: Current | AG50: Fee & Leasehold | AH50: =IF(G50="",0,ROUND((Strats!$C$4-G50)/30.4375,1)) -> 78 | AI50: =IF(K50="",0,IF(K50="Floating",Strats!$C$10+M50,L50)) -> 0.0796 | AJ50: =IF(OR(Z50="",Z50="Full Amortizing"),"",MAX(J50-AH50,0)) -> 0 | AK50: =IF(K50="",0,IF(K50="Floating",IF(P50<>"",MIN(IF(Q50<>"",MAX((Strats!$C$10+Strats!$C$11+M50),Q50),(Strats!$C$10+Strats!$C$11+M50)),P50),IF(Q50<>"",MAX((Strats!$C$10+Strats!$C$11+M50),Q50),(Strats!$C$10+Strats!$C$11+M50))),AI50)) -> 0.0946 | AL50: =IF(OR(E50="",E50<>'Deal Strat'!$C$12,R50=""),"",SUMPRODUCT((E$4:E$303='Deal Strat'!$C$12)*(R$4:R$303>R50))+1+SUMPRODUCT((E$4:E$303='Deal Strat'!$C$12)*(R$4:R$303=R50)*(ROW(R$4:R$303)<ROW(R50)))) | AM50: =IF(R50="","",RANK(R50,$R$4:$R$303,0)+COUNTIF($R$4:R50,R50)-1) -> 46 | AN50: =IF(OR($A50="",$R50=""),0,IF(Deal_Scope="All Deals",1,IF($E50=Deal_Scope,1,0))) -> 1 | AO50: =IF($AN50=0,0,Px_Par) -> 0.94 | AP50: =IF($H50="",0,MAX(0,($H50-Set_Date)/30.4375)) -> 42.020534 | AQ50: =IF(AND(Ext_Flag="Yes",$AA50="Yes"),Ext_Months,0) -> 0 | AR50: =$AP50+$AQ50 -> 42.020534 | AS50: =$AR50/12 -> 3.5017112 | AT50: =IF($AJ50="",0,MAX(0,$AJ50/12)) -> 0 | AU50: =MAX(Amort_Min,Amort_Term-$AH50/12) -> 23.5 | AV50: =MIN($AS50,Hold_Yrs) -> 3.5017112 | AW50: =IF($AN50=0,0,CEILING(MAX($AS50,0.0001),1)) -> 4 | AX50: =IF(AND($AN50=1,MAX($AS50,0.0001)<=Hold_Yrs),1,0) -> 1 | AY50: =$R50*$AO50 -> 4943460 | AZ50: =$R50*Acc_Int*$AN50 -> 7888.5 | BA50: =$AY50*Acq_Cost -> 37075.95 | BB50: =$AY50+$AZ50+$BA50 -> 4988424.5 | BC50: =IF(Fin_Flag="Yes",$AY50*Adv_Rate,0) -> 2966076 | BD50: =$BC50*Fin_UpFee -> 14830.38 | BE50: =$BB50-$BC50+$BD50 -> 2037178.8
A51: L-048 | B51: Vista Corporate Center | C51: WA | D51: Office | E51: Deal 7 | G51: 43252 | H51: 46905 | I51: 120 | J51: 0 | K51: Floating | M51: 0.0215 | N51: Monthly | O51: 46355 | P51: 0.0835 | Q51: 0.0367 | R51: 100201000 | S51: 0.918 | T51: 0.1226 | U51: 1.44 | V51: 0.579 | W51: 0.61 | X51: 2020 | Z51: Full Amortizing | AA51: No | AB51: Yield Maintenance | AC51: First Lien | AD51: PE Fund | AE51: Acquisition | AF51: REO | AG51: Fee Simple | AH51: =IF(G51="",0,ROUND((Strats!$C$4-G51)/30.4375,1)) -> 100 | AI51: =IF(K51="",0,IF(K51="Floating",Strats!$C$10+M51,L51)) -> 0.0665 | AJ51: =IF(OR(Z51="",Z51="Full Amortizing"),"",MAX(J51-AH51,0)) | AK51: =IF(K51="",0,IF(K51="Floating",IF(P51<>"",MIN(IF(Q51<>"",MAX((Strats!$C$10+Strats!$C$11+M51),Q51),(Strats!$C$10+Strats!$C$11+M51)),P51),IF(Q51<>"",MAX((Strats!$C$10+Strats!$C$11+M51),Q51),(Strats!$C$10+Strats!$C$11+M51))),AI51)) -> 0.0815 | AL51: =IF(OR(E51="",E51<>'Deal Strat'!$C$12,R51=""),"",SUMPRODUCT((E$4:E$303='Deal Strat'!$C$12)*(R$4:R$303>R51))+1+SUMPRODUCT((E$4:E$303='Deal Strat'!$C$12)*(R$4:R$303=R51)*(ROW(R$4:R$303)<ROW(R51)))) | AM51: =IF(R51="","",RANK(R51,$R$4:$R$303,0)+COUNTIF($R$4:R51,R51)-1) -> 8 | AN51: =IF(OR($A51="",$R51=""),0,IF(Deal_Scope="All Deals",1,IF($E51=Deal_Scope,1,0))) -> 1 | AO51: =IF($AN51=0,0,Px_Par) -> 0.94 | AP51: =IF($H51="",0,MAX(0,($H51-Set_Date)/30.4375)) -> 20.041068 | AQ51: =IF(AND(Ext_Flag="Yes",$AA51="Yes"),Ext_Months,0) -> 0 | AR51: =$AP51+$AQ51 -> 20.041068 | AS51: =$AR51/12 -> 1.670089 | AT51: =IF($AJ51="",0,MAX(0,$AJ51/12)) -> 0 | AU51: =MAX(Amort_Min,Amort_Term-$AH51/12) -> 21.666667 | AV51: =MIN($AS51,Hold_Yrs) -> 1.670089 | AW51: =IF($AN51=0,0,CEILING(MAX($AS51,0.0001),1)) -> 2 | AX51: =IF(AND($AN51=1,MAX($AS51,0.0001)<=Hold_Yrs),1,0) -> 1 | AY51: =$R51*$AO51 -> 94188940 | AZ51: =$R51*Acc_Int*$AN51 -> 150301.5 | BA51: =$AY51*Acq_Cost -> 706417.05 | BB51: =$AY51+$AZ51+$BA51 -> 95045659 | BC51: =IF(Fin_Flag="Yes",$AY51*Adv_Rate,0) -> 56513364 | BD51: =$BC51*Fin_UpFee -> 282566.82 | BE51: =$BB51-$BC51+$BD51 -> 38814861
A52: L-049 | B52: Summit Hotel & Suites | C52: OR | D52: Hotel | E52: Deal 7 | G52: 44075 | H52: 45901 | I52: 60 | J52: 36 | K52: Floating | M52: 0.0376 | N52: Monthly | O52: 46325 | P52: 0.0768 | R52: 52022000 | S52: 0.852 | T52: 0.0685 | U52: 1.57 | V52: 0.746 | W52: 0.783 | X52: 2017 | Z52: Partial IO | AA52: No | AB52: Prepayable with Penalty | AC52: Second Lien | AD52: Institutional Owner/Operator | AE52: Refinance | AF52: Current | AG52: Fee & Leasehold | AH52: =IF(G52="",0,ROUND((Strats!$C$4-G52)/30.4375,1)) -> 72.9 | AI52: =IF(K52="",0,IF(K52="Floating",Strats!$C$10+M52,L52)) -> 0.0826 | AJ52: =IF(OR(Z52="",Z52="Full Amortizing"),"",MAX(J52-AH52,0)) -> 0 | AK52: =IF(K52="",0,IF(K52="Floating",IF(P52<>"",MIN(IF(Q52<>"",MAX((Strats!$C$10+Strats!$C$11+M52),Q52),(Strats!$C$10+Strats!$C$11+M52)),P52),IF(Q52<>"",MAX((Strats!$C$10+Strats!$C$11+M52),Q52),(Strats!$C$10+Strats!$C$11+M52))),AI52)) -> 0.0768 | AL52: =IF(OR(E52="",E52<>'Deal Strat'!$C$12,R52=""),"",SUMPRODUCT((E$4:E$303='Deal Strat'!$C$12)*(R$4:R$303>R52))+1+SUMPRODUCT((E$4:E$303='Deal Strat'!$C$12)*(R$4:R$303=R52)*(ROW(R$4:R$303)<ROW(R52)))) | AM52: =IF(R52="","",RANK(R52,$R$4:$R$303,0)+COUNTIF($R$4:R52,R52)-1) -> 21 | AN52: =IF(OR($A52="",$R52=""),0,IF(Deal_Scope="All Deals",1,IF($E52=Deal_Scope,1,0))) -> 1 | AO52: =IF($AN52=0,0,Px_Par) -> 0.94 | AP52: =IF($H52="",0,MAX(0,($H52-Set_Date)/30.4375)) -> 0 | AQ52: =IF(AND(Ext_Flag="Yes",$AA52="Yes"),Ext_Months,0) -> 0 | AR52: =$AP52+$AQ52 -> 0 | AS52: =$AR52/12 -> 0 | AT52: =IF($AJ52="",0,MAX(0,$AJ52/12)) -> 0 | AU52: =MAX(Amort_Min,Amort_Term-$AH52/12) -> 23.925 | AV52: =MIN($AS52,Hold_Yrs) -> 0 | AW52: =IF($AN52=0,0,CEILING(MAX($AS52,0.0001),1)) -> 1 | AX52: =IF(AND($AN52=1,MAX($AS52,0.0001)<=Hold_Yrs),1,0) -> 1 | AY52: =$R52*$AO52 -> 48900680 | AZ52: =$R52*Acc_Int*$AN52 -> 78033 | BA52: =$AY52*Acq_Cost -> 366755.1 | BB52: =$AY52+$AZ52+$BA52 -> 49345468 | BC52: =IF(Fin_Flag="Yes",$AY52*Adv_Rate,0) -> 29340408 | BD52: =$BC52*Fin_UpFee -> 146702.04 | BE52: =$BB52-$BC52+$BD52 -> 20151762
A53: L-050 | B53: Foxhollow Warehouse | C53: AZ | D53: Industrial | E53: Deal 1 | G53: 43252 | H53: 46905 | I53: 120 | J53: 120 | K53: Floating | M53: 0.038 | N53: Monthly | O53: 46325 | R53: 120313000 | S53: 0.784 | T53: 0.0814 | U53: 1.38 | V53: 0.663 | W53: 0.69 | X53: 1972 | Z53: Interest Only | AA53: Yes | AB53: Yield Maintenance | AC53: First Lien | AD53: Institutional Owner/Operator | AE53: Acquisition | AF53: Current | AG53: Leasehold | AH53: =IF(G53="",0,ROUND((Strats!$C$4-G53)/30.4375,1)) -> 100 | AI53: =IF(K53="",0,IF(K53="Floating",Strats!$C$10+M53,L53)) -> 0.083 | AJ53: =IF(OR(Z53="",Z53="Full Amortizing"),"",MAX(J53-AH53,0)) -> 20 | AK53: =IF(K53="",0,IF(K53="Floating",IF(P53<>"",MIN(IF(Q53<>"",MAX((Strats!$C$10+Strats!$C$11+M53),Q53),(Strats!$C$10+Strats!$C$11+M53)),P53),IF(Q53<>"",MAX((Strats!$C$10+Strats!$C$11+M53),Q53),(Strats!$C$10+Strats!$C$11+M53))),AI53)) -> 0.098 | AL53: =IF(OR(E53="",E53<>'Deal Strat'!$C$12,R53=""),"",SUMPRODUCT((E$4:E$303='Deal Strat'!$C$12)*(R$4:R$303>R53))+1+SUMPRODUCT((E$4:E$303='Deal Strat'!$C$12)*(R$4:R$303=R53)*(ROW(R$4:R$303)<ROW(R53)))) -> 1 | AM53: =IF(R53="","",RANK(R53,$R$4:$R$303,0)+COUNTIF($R$4:R53,R53)-1) -> 4 | AN53: =IF(OR($A53="",$R53=""),0,IF(Deal_Scope="All Deals",1,IF($E53=Deal_Scope,1,0))) -> 1 | AO53: =IF($AN53=0,0,Px_Par) -> 0.94 | AP53: =IF($H53="",0,MAX(0,($H53-Set_Date)/30.4375)) -> 20.041068 | AQ53: =IF(AND(Ext_Flag="Yes",$AA53="Yes"),Ext_Months,0) -> 12 | AR53: =$AP53+$AQ53 -> 32.041068 | AS53: =$AR53/12 -> 2.670089 | AT53: =IF($AJ53="",0,MAX(0,$AJ53/12)) -> 1.6666667 | AU53: =MAX(Amort_Min,Amort_Term-$AH53/12) -> 21.666667 | AV53: =MIN($AS53,Hold_Yrs) -> 2.670089 | AW53: =IF($AN53=0,0,CEILING(MAX($AS53,0.0001),1)) -> 3 | AX53: =IF(AND($AN53=1,MAX($AS53,0.0001)<=Hold_Yrs),1,0) -> 1 | AY53: =$R53*$AO53 -> 113094220 | AZ53: =$R53*Acc_Int*$AN53 -> 180469.5 | BA53: =$AY53*Acq_Cost -> 848206.65 | BB53: =$AY53+$AZ53+$BA53 -> 1.141229e+08 | BC53: =IF(Fin_Flag="Yes",$AY53*Adv_Rate,0) -> 67856532 | BD53: =$BC53*Fin_UpFee -> 339282.66 | BE53: =$BB53-$BC53+$BD53 -> 46605647
AH54: =IF(G54="",0,ROUND((Strats!$C$4-G54)/30.4375,1)) -> 0 | AI54: =IF(K54="",0,IF(K54="Floating",Strats!$C$10+M54,L54)) -> 0 | AJ54: =IF(OR(Z54="",Z54="Full Amortizing"),"",MAX(J54-AH54,0)) | AK54: =IF(K54="",0,IF(K54="Floating",IF(P54<>"",MIN(IF(Q54<>"",MAX((Strats!$C$10+Strats!$C$11+M54),Q54),(Strats!$C$10+Strats!$C$11+M54)),P54),IF(Q54<>"",MAX((Strats!$C$10+Strats!$C$11+M54),Q54),(Strats!$C$10+Strats!$C$11+M54))),AI54)) -> 0 | AL54: =IF(OR(E54="",E54<>'Deal Strat'!$C$12,R54=""),"",SUMPRODUCT((E$4:E$303='Deal Strat'!$C$12)*(R$4:R$303>R54))+1+SUMPRODUCT((E$4:E$303='Deal Strat'!$C$12)*(R$4:R$303=R54)*(ROW(R$4:R$303)<ROW(R54)))) | AM54: =IF(R54="","",RANK(R54,$R$4:$R$303,0)+COUNTIF($R$4:R54,R54)-1) | AN54: =IF(OR($A54="",$R54=""),0,IF(Deal_Scope="All Deals",1,IF($E54=Deal_Scope,1,0))) -> 0 | AO54: =IF($AN54=0,0,Px_Par) -> 0 | AP54: =IF($H54="",0,MAX(0,($H54-Set_Date)/30.4375)) -> 0 | AQ54: =IF(AND(Ext_Flag="Yes",$AA54="Yes"),Ext_Months,0) -> 0 | AR54: =$AP54+$AQ54 -> 0 | AS54: =$AR54/12 -> 0 | AT54: =IF($AJ54="",0,MAX(0,$AJ54/12)) -> 0 | AU54: =MAX(Amort_Min,Amort_Term-$AH54/12) -> 30 | AV54: =MIN($AS54,Hold_Yrs) -> 0 | AW54: =IF($AN54=0,0,CEILING(MAX($AS54,0.0001),1)) -> 0 | AX54: =IF(AND($AN54=1,MAX($AS54,0.0001)<=Hold_Yrs),1,0) -> 0 | AY54: =$R54*$AO54 -> 0 | AZ54: =$R54*Acc_Int*$AN54 -> 0 | BA54: =$AY54*Acq_Cost -> 0 | BB54: =$AY54+$AZ54+$BA54 -> 0 | BC54: =IF(Fin_Flag="Yes",$AY54*Adv_Rate,0) -> 0 | BD54: =$BC54*Fin_UpFee -> 0 | BE54: =$BB54-$BC54+$BD54 -> 0
AH55: =IF(G55="",0,ROUND((Strats!$C$4-G55)/30.4375,1)) -> 0 | AI55: =IF(K55="",0,IF(K55="Floating",Strats!$C$10+M55,L55)) -> 0 | AJ55: =IF(OR(Z55="",Z55="Full Amortizing"),"",MAX(J55-AH55,0)) | AK55: =IF(K55="",0,IF(K55="Floating",IF(P55<>"",MIN(IF(Q55<>"",MAX((Strats!$C$10+Strats!$C$11+M55),Q55),(Strats!$C$10+Strats!$C$11+M55)),P55),IF(Q55<>"",MAX((Strats!$C$10+Strats!$C$11+M55),Q55),(Strats!$C$10+Strats!$C$11+M55))),AI55)) -> 0 | AL55: =IF(OR(E55="",E55<>'Deal Strat'!$C$12,R55=""),"",SUMPRODUCT((E$4:E$303='Deal Strat'!$C$12)*(R$4:R$303>R55))+1+SUMPRODUCT((E$4:E$303='Deal Strat'!$C$12)*(R$4:R$303=R55)*(ROW(R$4:R$303)<ROW(R55)))) | AM55: =IF(R55="","",RANK(R55,$R$4:$R$303,0)+COUNTIF($R$4:R55,R55)-1) | AN55: =IF(OR($A55="",$R55=""),0,IF(Deal_Scope="All Deals",1,IF($E55=Deal_Scope,1,0))) -> 0 | AO55: =IF($AN55=0,0,Px_Par) -> 0 | AP55: =IF($H55="",0,MAX(0,($H55-Set_Date)/30.4375)) -> 0 | AQ55: =IF(AND(Ext_Flag="Yes",$AA55="Yes"),Ext_Months,0) -> 0 | AR55: =$AP55+$AQ55 -> 0 | AS55: =$AR55/12 -> 0 | AT55: =IF($AJ55="",0,MAX(0,$AJ55/12)) -> 0 | AU55: =MAX(Amort_Min,Amort_Term-$AH55/12) -> 30 | AV55: =MIN($AS55,Hold_Yrs) -> 0 | AW55: =IF($AN55=0,0,CEILING(MAX($AS55,0.0001),1)) -> 0 | AX55: =IF(AND($AN55=1,MAX($AS55,0.0001)<=Hold_Yrs),1,0) -> 0 | AY55: =$R55*$AO55 -> 0 | AZ55: =$R55*Acc_Int*$AN55 -> 0 | BA55: =$AY55*Acq_Cost -> 0 | BB55: =$AY55+$AZ55+$BA55 -> 0 | BC55: =IF(Fin_Flag="Yes",$AY55*Adv_Rate,0) -> 0 | BD55: =$BC55*Fin_UpFee -> 0 | BE55: =$BB55-$BC55+$BD55 -> 0
AH56: =IF(G56="",0,ROUND((Strats!$C$4-G56)/30.4375,1)) -> 0 | AI56: =IF(K56="",0,IF(K56="Floating",Strats!$C$10+M56,L56)) -> 0 | AJ56: =IF(OR(Z56="",Z56="Full Amortizing"),"",MAX(J56-AH56,0)) | AK56: =IF(K56="",0,IF(K56="Floating",IF(P56<>"",MIN(IF(Q56<>"",MAX((Strats!$C$10+Strats!$C$11+M56),Q56),(Strats!$C$10+Strats!$C$11+M56)),P56),IF(Q56<>"",MAX((Strats!$C$10+Strats!$C$11+M56),Q56),(Strats!$C$10+Strats!$C$11+M56))),AI56)) -> 0 | AL56: =IF(OR(E56="",E56<>'Deal Strat'!$C$12,R56=""),"",SUMPRODUCT((E$4:E$303='Deal Strat'!$C$12)*(R$4:R$303>R56))+1+SUMPRODUCT((E$4:E$303='Deal Strat'!$C$12)*(R$4:R$303=R56)*(ROW(R$4:R$303)<ROW(R56)))) | AM56: =IF(R56="","",RANK(R56,$R$4:$R$303,0)+COUNTIF($R$4:R56,R56)-1) | AN56: =IF(OR($A56="",$R56=""),0,IF(Deal_Scope="All Deals",1,IF($E56=Deal_Scope,1,0))) -> 0 | AO56: =IF($AN56=0,0,Px_Par) -> 0 | AP56: =IF($H56="",0,MAX(0,($H56-Set_Date)/30.4375)) -> 0 | AQ56: =IF(AND(Ext_Flag="Yes",$AA56="Yes"),Ext_Months,0) -> 0 | AR56: =$AP56+$AQ56 -> 0 | AS56: =$AR56/12 -> 0 | AT56: =IF($AJ56="",0,MAX(0,$AJ56/12)) -> 0 | AU56: =MAX(Amort_Min,Amort_Term-$AH56/12) -> 30 | AV56: =MIN($AS56,Hold_Yrs) -> 0 | AW56: =IF($AN56=0,0,CEILING(MAX($AS56,0.0001),1)) -> 0 | AX56: =IF(AND($AN56=1,MAX($AS56,0.0001)<=Hold_Yrs),1,0) -> 0 | AY56: =$R56*$AO56 -> 0 | AZ56: =$R56*Acc_Int*$AN56 -> 0 | BA56: =$AY56*Acq_Cost -> 0 | BB56: =$AY56+$AZ56+$BA56 -> 0 | BC56: =IF(Fin_Flag="Yes",$AY56*Adv_Rate,0) -> 0 | BD56: =$BC56*Fin_UpFee -> 0 | BE56: =$BB56-$BC56+$BD56 -> 0
AH57: =IF(G57="",0,ROUND((Strats!$C$4-G57)/30.4375,1)) -> 0 | AI57: =IF(K57="",0,IF(K57="Floating",Strats!$C$10+M57,L57)) -> 0 | AJ57: =IF(OR(Z57="",Z57="Full Amortizing"),"",MAX(J57-AH57,0)) | AK57: =IF(K57="",0,IF(K57="Floating",IF(P57<>"",MIN(IF(Q57<>"",MAX((Strats!$C$10+Strats!$C$11+M57),Q57),(Strats!$C$10+Strats!$C$11+M57)),P57),IF(Q57<>"",MAX((Strats!$C$10+Strats!$C$11+M57),Q57),(Strats!$C$10+Strats!$C$11+M57))),AI57)) -> 0 | AL57: =IF(OR(E57="",E57<>'Deal Strat'!$C$12,R57=""),"",SUMPRODUCT((E$4:E$303='Deal Strat'!$C$12)*(R$4:R$303>R57))+1+SUMPRODUCT((E$4:E$303='Deal Strat'!$C$12)*(R$4:R$303=R57)*(ROW(R$4:R$303)<ROW(R57)))) | AM57: =IF(R57="","",RANK(R57,$R$4:$R$303,0)+COUNTIF($R$4:R57,R57)-1) | AN57: =IF(OR($A57="",$R57=""),0,IF(Deal_Scope="All Deals",1,IF($E57=Deal_Scope,1,0))) -> 0 | AO57: =IF($AN57=0,0,Px_Par) -> 0 | AP57: =IF($H57="",0,MAX(0,($H57-Set_Date)/30.4375)) -> 0 | AQ57: =IF(AND(Ext_Flag="Yes",$AA57="Yes"),Ext_Months,0) -> 0 | AR57: =$AP57+$AQ57 -> 0 | AS57: =$AR57/12 -> 0 | AT57: =IF($AJ57="",0,MAX(0,$AJ57/12)) -> 0 | AU57: =MAX(Amort_Min,Amort_Term-$AH57/12) -> 30 | AV57: =MIN($AS57,Hold_Yrs) -> 0 | AW57: =IF($AN57=0,0,CEILING(MAX($AS57,0.0001),1)) -> 0 | AX57: =IF(AND($AN57=1,MAX($AS57,0.0001)<=Hold_Yrs),1,0) -> 0 | AY57: =$R57*$AO57 -> 0 | AZ57: =$R57*Acc_Int*$AN57 -> 0 | BA57: =$AY57*Acq_Cost -> 0 | BB57: =$AY57+$AZ57+$BA57 -> 0 | BC57: =IF(Fin_Flag="Yes",$AY57*Adv_Rate,0) -> 0 | BD57: =$BC57*Fin_UpFee -> 0 | BE57: =$BB57-$BC57+$BD57 -> 0
AH58: =IF(G58="",0,ROUND((Strats!$C$4-G58)/30.4375,1)) -> 0 | AI58: =IF(K58="",0,IF(K58="Floating",Strats!$C$10+M58,L58)) -> 0 | AJ58: =IF(OR(Z58="",Z58="Full Amortizing"),"",MAX(J58-AH58,0)) | AK58: =IF(K58="",0,IF(K58="Floating",IF(P58<>"",MIN(IF(Q58<>"",MAX((Strats!$C$10+Strats!$C$11+M58),Q58),(Strats!$C$10+Strats!$C$11+M58)),P58),IF(Q58<>"",MAX((Strats!$C$10+Strats!$C$11+M58),Q58),(Strats!$C$10+Strats!$C$11+M58))),AI58)) -> 0 | AL58: =IF(OR(E58="",E58<>'Deal Strat'!$C$12,R58=""),"",SUMPRODUCT((E$4:E$303='Deal Strat'!$C$12)*(R$4:R$303>R58))+1+SUMPRODUCT((E$4:E$303='Deal Strat'!$C$12)*(R$4:R$303=R58)*(ROW(R$4:R$303)<ROW(R58)))) | AM58: =IF(R58="","",RANK(R58,$R$4:$R$303,0)+COUNTIF($R$4:R58,R58)-1) | AN58: =IF(OR($A58="",$R58=""),0,IF(Deal_Scope="All Deals",1,IF($E58=Deal_Scope,1,0))) -> 0 | AO58: =IF($AN58=0,0,Px_Par) -> 0 | AP58: =IF($H58="",0,MAX(0,($H58-Set_Date)/30.4375)) -> 0 | AQ58: =IF(AND(Ext_Flag="Yes",$AA58="Yes"),Ext_Months,0) -> 0 | AR58: =$AP58+$AQ58 -> 0 | AS58: =$AR58/12 -> 0 | AT58: =IF($AJ58="",0,MAX(0,$AJ58/12)) -> 0 | AU58: =MAX(Amort_Min,Amort_Term-$AH58/12) -> 30 | AV58: =MIN($AS58,Hold_Yrs) -> 0 | AW58: =IF($AN58=0,0,CEILING(MAX($AS58,0.0001),1)) -> 0 | AX58: =IF(AND($AN58=1,MAX($AS58,0.0001)<=Hold_Yrs),1,0) -> 0 | AY58: =$R58*$AO58 -> 0 | AZ58: =$R58*Acc_Int*$AN58 -> 0 | BA58: =$AY58*Acq_Cost -> 0 | BB58: =$AY58+$AZ58+$BA58 -> 0 | BC58: =IF(Fin_Flag="Yes",$AY58*Adv_Rate,0) -> 0 | BD58: =$BC58*Fin_UpFee -> 0 | BE58: =$BB58-$BC58+$BD58 -> 0
AH59: =IF(G59="",0,ROUND((Strats!$C$4-G59)/30.4375,1)) -> 0 | AI59: =IF(K59="",0,IF(K59="Floating",Strats!$C$10+M59,L59)) -> 0 | AJ59: =IF(OR(Z59="",Z59="Full Amortizing"),"",MAX(J59-AH59,0)) | AK59: =IF(K59="",0,IF(K59="Floating",IF(P59<>"",MIN(IF(Q59<>"",MAX((Strats!$C$10+Strats!$C$11+M59),Q59),(Strats!$C$10+Strats!$C$11+M59)),P59),IF(Q59<>"",MAX((Strats!$C$10+Strats!$C$11+M59),Q59),(Strats!$C$10+Strats!$C$11+M59))),AI59)) -> 0 | AL59: =IF(OR(E59="",E59<>'Deal Strat'!$C$12,R59=""),"",SUMPRODUCT((E$4:E$303='Deal Strat'!$C$12)*(R$4:R$303>R59))+1+SUMPRODUCT((E$4:E$303='Deal Strat'!$C$12)*(R$4:R$303=R59)*(ROW(R$4:R$303)<ROW(R59)))) | AM59: =IF(R59="","",RANK(R59,$R$4:$R$303,0)+COUNTIF($R$4:R59,R59)-1) | AN59: =IF(OR($A59="",$R59=""),0,IF(Deal_Scope="All Deals",1,IF($E59=Deal_Scope,1,0))) -> 0 | AO59: =IF($AN59=0,0,Px_Par) -> 0 | AP59: =IF($H59="",0,MAX(0,($H59-Set_Date)/30.4375)) -> 0 | AQ59: =IF(AND(Ext_Flag="Yes",$AA59="Yes"),Ext_Months,0) -> 0 | AR59: =$AP59+$AQ59 -> 0 | AS59: =$AR59/12 -> 0 | AT59: =IF($AJ59="",0,MAX(0,$AJ59/12)) -> 0 | AU59: =MAX(Amort_Min,Amort_Term-$AH59/12) -> 30 | AV59: =MIN($AS59,Hold_Yrs) -> 0 | AW59: =IF($AN59=0,0,CEILING(MAX($AS59,0.0001),1)) -> 0 | AX59: =IF(AND($AN59=1,MAX($AS59,0.0001)<=Hold_Yrs),1,0) -> 0 | AY59: =$R59*$AO59 -> 0 | AZ59: =$R59*Acc_Int*$AN59 -> 0 | BA59: =$AY59*Acq_Cost -> 0 | BB59: =$AY59+$AZ59+$BA59 -> 0 | BC59: =IF(Fin_Flag="Yes",$AY59*Adv_Rate,0) -> 0 | BD59: =$BC59*Fin_UpFee -> 0 | BE59: =$BB59-$BC59+$BD59 -> 0
AH60: =IF(G60="",0,ROUND((Strats!$C$4-G60)/30.4375,1)) -> 0 | AI60: =IF(K60="",0,IF(K60="Floating",Strats!$C$10+M60,L60)) -> 0 | AJ60: =IF(OR(Z60="",Z60="Full Amortizing"),"",MAX(J60-AH60,0)) | AK60: =IF(K60="",0,IF(K60="Floating",IF(P60<>"",MIN(IF(Q60<>"",MAX((Strats!$C$10+Strats!$C$11+M60),Q60),(Strats!$C$10+Strats!$C$11+M60)),P60),IF(Q60<>"",MAX((Strats!$C$10+Strats!$C$11+M60),Q60),(Strats!$C$10+Strats!$C$11+M60))),AI60)) -> 0 | AL60: =IF(OR(E60="",E60<>'Deal Strat'!$C$12,R60=""),"",SUMPRODUCT((E$4:E$303='Deal Strat'!$C$12)*(R$4:R$303>R60))+1+SUMPRODUCT((E$4:E$303='Deal Strat'!$C$12)*(R$4:R$303=R60)*(ROW(R$4:R$303)<ROW(R60)))) | AM60: =IF(R60="","",RANK(R60,$R$4:$R$303,0)+COUNTIF($R$4:R60,R60)-1) | AN60: =IF(OR($A60="",$R60=""),0,IF(Deal_Scope="All Deals",1,IF($E60=Deal_Scope,1,0))) -> 0 | AO60: =IF($AN60=0,0,Px_Par) -> 0 | AP60: =IF($H60="",0,MAX(0,($H60-Set_Date)/30.4375)) -> 0 | AQ60: =IF(AND(Ext_Flag="Yes",$AA60="Yes"),Ext_Months,0) -> 0 | AR60: =$AP60+$AQ60 -> 0 | AS60: =$AR60/12 -> 0 | AT60: =IF($AJ60="",0,MAX(0,$AJ60/12)) -> 0 | AU60: =MAX(Amort_Min,Amort_Term-$AH60/12) -> 30 | AV60: =MIN($AS60,Hold_Yrs) -> 0 | AW60: =IF($AN60=0,0,CEILING(MAX($AS60,0.0001),1)) -> 0 | AX60: =IF(AND($AN60=1,MAX($AS60,0.0001)<=Hold_Yrs),1,0) -> 0 | AY60: =$R60*$AO60 -> 0 | AZ60: =$R60*Acc_Int*$AN60 -> 0 | BA60: =$AY60*Acq_Cost -> 0 | BB60: =$AY60+$AZ60+$BA60 -> 0 | BC60: =IF(Fin_Flag="Yes",$AY60*Adv_Rate,0) -> 0 | BD60: =$BC60*Fin_UpFee -> 0 | BE60: =$BB60-$BC60+$BD60 -> 0
AH61: =IF(G61="",0,ROUND((Strats!$C$4-G61)/30.4375,1)) -> 0 | AI61: =IF(K61="",0,IF(K61="Floating",Strats!$C$10+M61,L61)) -> 0 | AJ61: =IF(OR(Z61="",Z61="Full Amortizing"),"",MAX(J61-AH61,0)) | AK61: =IF(K61="",0,IF(K61="Floating",IF(P61<>"",MIN(IF(Q61<>"",MAX((Strats!$C$10+Strats!$C$11+M61),Q61),(Strats!$C$10+Strats!$C$11+M61)),P61),IF(Q61<>"",MAX((Strats!$C$10+Strats!$C$11+M61),Q61),(Strats!$C$10+Strats!$C$11+M61))),AI61)) -> 0 | AL61: =IF(OR(E61="",E61<>'Deal Strat'!$C$12,R61=""),"",SUMPRODUCT((E$4:E$303='Deal Strat'!$C$12)*(R$4:R$303>R61))+1+SUMPRODUCT((E$4:E$303='Deal Strat'!$C$12)*(R$4:R$303=R61)*(ROW(R$4:R$303)<ROW(R61)))) | AM61: =IF(R61="","",RANK(R61,$R$4:$R$303,0)+COUNTIF($R$4:R61,R61)-1) | AN61: =IF(OR($A61="",$R61=""),0,IF(Deal_Scope="All Deals",1,IF($E61=Deal_Scope,1,0))) -> 0 | AO61: =IF($AN61=0,0,Px_Par) -> 0 | AP61: =IF($H61="",0,MAX(0,($H61-Set_Date)/30.4375)) -> 0 | AQ61: =IF(AND(Ext_Flag="Yes",$AA61="Yes"),Ext_Months,0) -> 0 | AR61: =$AP61+$AQ61 -> 0 | AS61: =$AR61/12 -> 0 | AT61: =IF($AJ61="",0,MAX(0,$AJ61/12)) -> 0 | AU61: =MAX(Amort_Min,Amort_Term-$AH61/12) -> 30 | AV61: =MIN($AS61,Hold_Yrs) -> 0 | AW61: =IF($AN61=0,0,CEILING(MAX($AS61,0.0001),1)) -> 0 | AX61: =IF(AND($AN61=1,MAX($AS61,0.0001)<=Hold_Yrs),1,0) -> 0 | AY61: =$R61*$AO61 -> 0 | AZ61: =$R61*Acc_Int*$AN61 -> 0 | BA61: =$AY61*Acq_Cost -> 0 | BB61: =$AY61+$AZ61+$BA61 -> 0 | BC61: =IF(Fin_Flag="Yes",$AY61*Adv_Rate,0) -> 0 | BD61: =$BC61*Fin_UpFee -> 0 | BE61: =$BB61-$BC61+$BD61 -> 0
AH62: =IF(G62="",0,ROUND((Strats!$C$4-G62)/30.4375,1)) -> 0 | AI62: =IF(K62="",0,IF(K62="Floating",Strats!$C$10+M62,L62)) -> 0 | AJ62: =IF(OR(Z62="",Z62="Full Amortizing"),"",MAX(J62-AH62,0)) | AK62: =IF(K62="",0,IF(K62="Floating",IF(P62<>"",MIN(IF(Q62<>"",MAX((Strats!$C$10+Strats!$C$11+M62),Q62),(Strats!$C$10+Strats!$C$11+M62)),P62),IF(Q62<>"",MAX((Strats!$C$10+Strats!$C$11+M62),Q62),(Strats!$C$10+Strats!$C$11+M62))),AI62)) -> 0 | AL62: =IF(OR(E62="",E62<>'Deal Strat'!$C$12,R62=""),"",SUMPRODUCT((E$4:E$303='Deal Strat'!$C$12)*(R$4:R$303>R62))+1+SUMPRODUCT((E$4:E$303='Deal Strat'!$C$12)*(R$4:R$303=R62)*(ROW(R$4:R$303)<ROW(R62)))) | AM62: =IF(R62="","",RANK(R62,$R$4:$R$303,0)+COUNTIF($R$4:R62,R62)-1) | AN62: =IF(OR($A62="",$R62=""),0,IF(Deal_Scope="All Deals",1,IF($E62=Deal_Scope,1,0))) -> 0 | AO62: =IF($AN62=0,0,Px_Par) -> 0 | AP62: =IF($H62="",0,MAX(0,($H62-Set_Date)/30.4375)) -> 0 | AQ62: =IF(AND(Ext_Flag="Yes",$AA62="Yes"),Ext_Months,0) -> 0 | AR62: =$AP62+$AQ62 -> 0 | AS62: =$AR62/12 -> 0 | AT62: =IF($AJ62="",0,MAX(0,$AJ62/12)) -> 0 | AU62: =MAX(Amort_Min,Amort_Term-$AH62/12) -> 30 | AV62: =MIN($AS62,Hold_Yrs) -> 0 | AW62: =IF($AN62=0,0,CEILING(MAX($AS62,0.0001),1)) -> 0 | AX62: =IF(AND($AN62=1,MAX($AS62,0.0001)<=Hold_Yrs),1,0) -> 0 | AY62: =$R62*$AO62 -> 0 | AZ62: =$R62*Acc_Int*$AN62 -> 0 | BA62: =$AY62*Acq_Cost -> 0 | BB62: =$AY62+$AZ62+$BA62 -> 0 | BC62: =IF(Fin_Flag="Yes",$AY62*Adv_Rate,0) -> 0 | BD62: =$BC62*Fin_UpFee -> 0 | BE62: =$BB62-$BC62+$BD62 -> 0
AH63: =IF(G63="",0,ROUND((Strats!$C$4-G63)/30.4375,1)) -> 0 | AI63: =IF(K63="",0,IF(K63="Floating",Strats!$C$10+M63,L63)) -> 0 | AJ63: =IF(OR(Z63="",Z63="Full Amortizing"),"",MAX(J63-AH63,0)) | AK63: =IF(K63="",0,IF(K63="Floating",IF(P63<>"",MIN(IF(Q63<>"",MAX((Strats!$C$10+Strats!$C$11+M63),Q63),(Strats!$C$10+Strats!$C$11+M63)),P63),IF(Q63<>"",MAX((Strats!$C$10+Strats!$C$11+M63),Q63),(Strats!$C$10+Strats!$C$11+M63))),AI63)) -> 0 | AL63: =IF(OR(E63="",E63<>'Deal Strat'!$C$12,R63=""),"",SUMPRODUCT((E$4:E$303='Deal Strat'!$C$12)*(R$4:R$303>R63))+1+SUMPRODUCT((E$4:E$303='Deal Strat'!$C$12)*(R$4:R$303=R63)*(ROW(R$4:R$303)<ROW(R63)))) | AM63: =IF(R63="","",RANK(R63,$R$4:$R$303,0)+COUNTIF($R$4:R63,R63)-1) | AN63: =IF(OR($A63="",$R63=""),0,IF(Deal_Scope="All Deals",1,IF($E63=Deal_Scope,1,0))) -> 0 | AO63: =IF($AN63=0,0,Px_Par) -> 0 | AP63: =IF($H63="",0,MAX(0,($H63-Set_Date)/30.4375)) -> 0 | AQ63: =IF(AND(Ext_Flag="Yes",$AA63="Yes"),Ext_Months,0) -> 0 | AR63: =$AP63+$AQ63 -> 0 | AS63: =$AR63/12 -> 0 | AT63: =IF($AJ63="",0,MAX(0,$AJ63/12)) -> 0 | AU63: =MAX(Amort_Min,Amort_Term-$AH63/12) -> 30 | AV63: =MIN($AS63,Hold_Yrs) -> 0 | AW63: =IF($AN63=0,0,CEILING(MAX($AS63,0.0001),1)) -> 0 | AX63: =IF(AND($AN63=1,MAX($AS63,0.0001)<=Hold_Yrs),1,0) -> 0 | AY63: =$R63*$AO63 -> 0 | AZ63: =$R63*Acc_Int*$AN63 -> 0 | BA63: =$AY63*Acq_Cost -> 0 | BB63: =$AY63+$AZ63+$BA63 -> 0 | BC63: =IF(Fin_Flag="Yes",$AY63*Adv_Rate,0) -> 0 | BD63: =$BC63*Fin_UpFee -> 0 | BE63: =$BB63-$BC63+$BD63 -> 0
AH64: =IF(G64="",0,ROUND((Strats!$C$4-G64)/30.4375,1)) -> 0 | AI64: =IF(K64="",0,IF(K64="Floating",Strats!$C$10+M64,L64)) -> 0 | AJ64: =IF(OR(Z64="",Z64="Full Amortizing"),"",MAX(J64-AH64,0)) | AK64: =IF(K64="",0,IF(K64="Floating",IF(P64<>"",MIN(IF(Q64<>"",MAX((Strats!$C$10+Strats!$C$11+M64),Q64),(Strats!$C$10+Strats!$C$11+M64)),P64),IF(Q64<>"",MAX((Strats!$C$10+Strats!$C$11+M64),Q64),(Strats!$C$10+Strats!$C$11+M64))),AI64)) -> 0 | AL64: =IF(OR(E64="",E64<>'Deal Strat'!$C$12,R64=""),"",SUMPRODUCT((E$4:E$303='Deal Strat'!$C$12)*(R$4:R$303>R64))+1+SUMPRODUCT((E$4:E$303='Deal Strat'!$C$12)*(R$4:R$303=R64)*(ROW(R$4:R$303)<ROW(R64)))) | AM64: =IF(R64="","",RANK(R64,$R$4:$R$303,0)+COUNTIF($R$4:R64,R64)-1) | AN64: =IF(OR($A64="",$R64=""),0,IF(Deal_Scope="All Deals",1,IF($E64=Deal_Scope,1,0))) -> 0 | AO64: =IF($AN64=0,0,Px_Par) -> 0 | AP64: =IF($H64="",0,MAX(0,($H64-Set_Date)/30.4375)) -> 0 | AQ64: =IF(AND(Ext_Flag="Yes",$AA64="Yes"),Ext_Months,0) -> 0 | AR64: =$AP64+$AQ64 -> 0 | AS64: =$AR64/12 -> 0 | AT64: =IF($AJ64="",0,MAX(0,$AJ64/12)) -> 0 | AU64: =MAX(Amort_Min,Amort_Term-$AH64/12) -> 30 | AV64: =MIN($AS64,Hold_Yrs) -> 0 | AW64: =IF($AN64=0,0,CEILING(MAX($AS64,0.0001),1)) -> 0 | AX64: =IF(AND($AN64=1,MAX($AS64,0.0001)<=Hold_Yrs),1,0) -> 0 | AY64: =$R64*$AO64 -> 0 | AZ64: =$R64*Acc_Int*$AN64 -> 0 | BA64: =$AY64*Acq_Cost -> 0 | BB64: =$AY64+$AZ64+$BA64 -> 0 | BC64: =IF(Fin_Flag="Yes",$AY64*Adv_Rate,0) -> 0 | BD64: =$BC64*Fin_UpFee -> 0 | BE64: =$BB64-$BC64+$BD64 -> 0
AH65: =IF(G65="",0,ROUND((Strats!$C$4-G65)/30.4375,1)) -> 0 | AI65: =IF(K65="",0,IF(K65="Floating",Strats!$C$10+M65,L65)) -> 0 | AJ65: =IF(OR(Z65="",Z65="Full Amortizing"),"",MAX(J65-AH65,0)) | AK65: =IF(K65="",0,IF(K65="Floating",IF(P65<>"",MIN(IF(Q65<>"",MAX((Strats!$C$10+Strats!$C$11+M65),Q65),(Strats!$C$10+Strats!$C$11+M65)),P65),IF(Q65<>"",MAX((Strats!$C$10+Strats!$C$11+M65),Q65),(Strats!$C$10+Strats!$C$11+M65))),AI65)) -> 0 | AL65: =IF(OR(E65="",E65<>'Deal Strat'!$C$12,R65=""),"",SUMPRODUCT((E$4:E$303='Deal Strat'!$C$12)*(R$4:R$303>R65))+1+SUMPRODUCT((E$4:E$303='Deal Strat'!$C$12)*(R$4:R$303=R65)*(ROW(R$4:R$303)<ROW(R65)))) | AM65: =IF(R65="","",RANK(R65,$R$4:$R$303,0)+COUNTIF($R$4:R65,R65)-1) | AN65: =IF(OR($A65="",$R65=""),0,IF(Deal_Scope="All Deals",1,IF($E65=Deal_Scope,1,0))) -> 0 | AO65: =IF($AN65=0,0,Px_Par) -> 0 | AP65: =IF($H65="",0,MAX(0,($H65-Set_Date)/30.4375)) -> 0 | AQ65: =IF(AND(Ext_Flag="Yes",$AA65="Yes"),Ext_Months,0) -> 0 | AR65: =$AP65+$AQ65 -> 0 | AS65: =$AR65/12 -> 0 | AT65: =IF($AJ65="",0,MAX(0,$AJ65/12)) -> 0 | AU65: =MAX(Amort_Min,Amort_Term-$AH65/12) -> 30 | AV65: =MIN($AS65,Hold_Yrs) -> 0 | AW65: =IF($AN65=0,0,CEILING(MAX($AS65,0.0001),1)) -> 0 | AX65: =IF(AND($AN65=1,MAX($AS65,0.0001)<=Hold_Yrs),1,0) -> 0 | AY65: =$R65*$AO65 -> 0 | AZ65: =$R65*Acc_Int*$AN65 -> 0 | BA65: =$AY65*Acq_Cost -> 0 | BB65: =$AY65+$AZ65+$BA65 -> 0 | BC65: =IF(Fin_Flag="Yes",$AY65*Adv_Rate,0) -> 0 | BD65: =$BC65*Fin_UpFee -> 0 | BE65: =$BB65-$BC65+$BD65 -> 0
... AH303: =IF(G303="",0,ROUND((Strats!$C$4-G303)/30.4375,1)) -> 0 | AI303: =IF(K303="",0,IF(K303="Floating",Strats!$C$10+M303,L303)) -> 0 | AJ303: =IF(OR(Z303="",Z303="Full Amortizing"),"",MAX(J303-AH303,0)) | AK303: =IF(K303="",0,IF(K303="Floating",IF(P303<>"",MIN(IF(Q303<>"",MAX((Strats!$C$10+Strats!$C$11+M303),Q303),(Strats!$C$10+Strats!$C$11+M303)),P303),IF(Q303<>"",MAX((Strats!$C$10+Strats!$C$11+M303),Q303),(Strats!$C$10+Strats!$C$11+M303))),AI303)) -> 0 | AL303: =IF(OR(E303="",E303<>'Deal Strat'!$C$12,R303=""),"",SUMPRODUCT((E$4:E$303='Deal Strat'!$C$12)*(R$4:R$303>R303))+1+SUMPRODUCT((E$4:E$303='Deal Strat'!$C$12)*(R$4:R$303=R303)*(ROW(R$4:R$303)<ROW(R303)))) | AM303: =IF(R303="","",RANK(R303,$R$4:$R$303,0)+COUNTIF($R$4:R303,R303)-1) | AN303: =IF(OR($A303="",$R303=""),0,IF(Deal_Scope="All Deals",1,IF($E303=Deal_Scope,1,0))) -> 0 | AO303: =IF($AN303=0,0,Px_Par) -> 0 | AP303: =IF($H303="",0,MAX(0,($H303-Set_Date)/30.4375)) -> 0 | AQ303: =IF(AND(Ext_Flag="Yes",$AA303="Yes"),Ext_Months,0) -> 0 | AR303: =$AP303+$AQ303 -> 0 | AS303: =$AR303/12 -> 0 | AT303: =IF($AJ303="",0,MAX(0,$AJ303/12)) -> 0 | AU303: =MAX(Amort_Min,Amort_Term-$AH303/12) -> 30 | AV303: =MIN($AS303,Hold_Yrs) -> 0 | AW303: =IF($AN303=0,0,CEILING(MAX($AS303,0.0001),1)) -> 0 | AX303: =IF(AND($AN303=1,MAX($AS303,0.0001)<=Hold_Yrs),1,0) -> 0 | AY303: =$R303*$AO303 -> 0 | AZ303: =$R303*Acc_Int*$AN303 -> 0 | BA303: =$AY303*Acq_Cost -> 0 | BB303: =$AY303+$AZ303+$BA303 -> 0 | BC303: =IF(Fin_Flag="Yes",$AY303*Adv_Rate,0) -> 0 | BD303: =$BC303*Fin_UpFee -> 0 | BE303: =$BB303-$BC303+$BD303 -> 0

Sheet Strats
R1: Bucket boundaries & category labels (adjustable, green) sit in columns R/S next to each table
B2: PORTFOLIO OVERVIEW
B4: As-Of / Pricing Date | C4: =Set_Date -> 46295 | D4: Wtd. Avg. Occupancy | E4: =IFERROR(SUMPRODUCT('Loan Tape'!$S$4:$S$303*'Loan Tape'!$R$4:$R$303)/C5,0) -> 0.88668714
B5: Cut-off Date UPB | C5: =SUM('Loan Tape'!$R$4:$R$303) -> 2495610000 | D5: Wtd. Avg. NOI Debt Yield | E5: =IFERROR(SUMPRODUCT('Loan Tape'!$T$4:$T$303*'Loan Tape'!$R$4:$R$303)/C5,0) -> 0.086154057
B6: Number of Loans | C6: =COUNT('Loan Tape'!$R$4:$R$303) -> 50 | D6: Wtd. Avg. DSCR | E6: =IFERROR(SUMPRODUCT('Loan Tape'!$U$4:$U$303*'Loan Tape'!$R$4:$R$303)/C5,0) -> 1.3657594
B7: Average Loan Size | C7: =IFERROR(C5/C6,0) -> 49912200 | D7: Wtd. Avg. LTV (Most Recent) | E7: =IFERROR(SUMPRODUCT('Loan Tape'!$V$4:$V$303*'Loan Tape'!$R$4:$R$303)/C5,0) -> 0.68355926
B8: Wtd. Avg. Coupon (Current) | C8: =IFERROR(SUMPRODUCT('Loan Tape'!$AI$4:$AI$303*'Loan Tape'!$R$4:$R$303)/C5,0) -> 0.070457452 | D8: Wtd. Avg. SSP / Underwritten LTV | E8: =IFERROR(SUMPRODUCT('Loan Tape'!$W$4:$W$303*'Loan Tape'!$R$4:$R$303)/C5,0) -> 0.71616446
B9: Wtd. Avg. Original Term (Months) | C9: =IFERROR(SUMPRODUCT('Loan Tape'!$I$4:$I$303*'Loan Tape'!$R$4:$R$303)/C5,0) -> 94.155082 | D9: % Floating / % Fixed Rate | E9: =IFERROR(TEXT(SUMIF('Loan Tape'!$K$4:$K$303,"Floating",'Loan Tape'!$R$4:$R$303)/C5,"0.0%"),"0.0%")&" / "&IFERROR(TEXT(SUMIF('Loan Tape'!$K$4:$K$303,"Fixed",'Loan Tape'!$R$4:$R$303)/C5,"0.0%"),"0.0%") -> 66.4% / 33.6%
B10: Current Index Rate (e.g. 1-Mo Term SOFR) | C10: =INDEX(Idx_Curve,1,1) -> 0.045 | D10: Wtd. Avg. Coupon at Reset (Stress) | E10: =IFERROR(SUMPRODUCT('Loan Tape'!$AK$4:$AK$303*'Loan Tape'!$R$4:$R$303)/C5,0) -> 0.079210317
B11: Rate Shock for Stress Test (+bps, e.g. 0.015 = +150bps) | C11: 0.015 | D11: Coupon Change Under Stress (bps) | E11: =(E10-C8)*10000 -> 87.528646
B12: Deal Filter | C12: All Deals (Portfolio-Wide View)
B15: TEN LARGEST LOANS
B16: Loan Name | C16: State | D16: Deal | E16: UPB | F16: % of UPB | G16: DSCR | H16: Debt Yield | I16: LTV
B17: =IFERROR(INDEX('Loan Tape'!$B$4:$B$303,MATCH(1,'Loan Tape'!$AM$4:$AM$303,0)),"") -> Kingston Exchange | C17: =IFERROR(INDEX('Loan Tape'!$C$4:$C$303,MATCH(1,'Loan Tape'!$AM$4:$AM$303,0)),"") -> FL | D17: =IFERROR(INDEX('Loan Tape'!$E$4:$E$303,MATCH(1,'Loan Tape'!$AM$4:$AM$303,0)),"") -> Deal 3 | E17: =IFERROR(INDEX('Loan Tape'!$R$4:$R$303,MATCH(1,'Loan Tape'!$AM$4:$AM$303,0)),"") -> 139731000 | F17: =IFERROR(E17/C5,"") -> 0.05599072 | G17: =IFERROR(INDEX('Loan Tape'!$U$4:$U$303,MATCH(1,'Loan Tape'!$AM$4:$AM$303,0)),"") -> 1.43 | H17: =IFERROR(INDEX('Loan Tape'!$T$4:$T$303,MATCH(1,'Loan Tape'!$AM$4:$AM$303,0)),"") -> 0.0733 | I17: =IFERROR(INDEX('Loan Tape'!$V$4:$V$303,MATCH(1,'Loan Tape'!$AM$4:$AM$303,0)),"") -> 0.772
B18: =IFERROR(INDEX('Loan Tape'!$B$4:$B$303,MATCH(2,'Loan Tape'!$AM$4:$AM$303,0)),"") -> Palisades Exchange | C18: =IFERROR(INDEX('Loan Tape'!$C$4:$C$303,MATCH(2,'Loan Tape'!$AM$4:$AM$303,0)),"") -> TX | D18: =IFERROR(INDEX('Loan Tape'!$E$4:$E$303,MATCH(2,'Loan Tape'!$AM$4:$AM$303,0)),"") -> Deal 7 | E18: =IFERROR(INDEX('Loan Tape'!$R$4:$R$303,MATCH(2,'Loan Tape'!$AM$4:$AM$303,0)),"") -> 131786000 | F18: =IFERROR(E18/C5,"") -> 0.052807129 | G18: =IFERROR(INDEX('Loan Tape'!$U$4:$U$303,MATCH(2,'Loan Tape'!$AM$4:$AM$303,0)),"") -> 1.69 | H18: =IFERROR(INDEX('Loan Tape'!$T$4:$T$303,MATCH(2,'Loan Tape'!$AM$4:$AM$303,0)),"") -> 0.1044 | I18: =IFERROR(INDEX('Loan Tape'!$V$4:$V$303,MATCH(2,'Loan Tape'!$AM$4:$AM$303,0)),"") -> 0.78
B19: =IFERROR(INDEX('Loan Tape'!$B$4:$B$303,MATCH(3,'Loan Tape'!$AM$4:$AM$303,0)),"") -> Glenwood Landing | C19: =IFERROR(INDEX('Loan Tape'!$C$4:$C$303,MATCH(3,'Loan Tape'!$AM$4:$AM$303,0)),"") -> NV | D19: =IFERROR(INDEX('Loan Tape'!$E$4:$E$303,MATCH(3,'Loan Tape'!$AM$4:$AM$303,0)),"") -> Deal 8 | E19: =IFERROR(INDEX('Loan Tape'!$R$4:$R$303,MATCH(3,'Loan Tape'!$AM$4:$AM$303,0)),"") -> 128291000 | F19: =IFERROR(E19/C5,"") -> 0.05140667 | G19: =IFERROR(INDEX('Loan Tape'!$U$4:$U$303,MATCH(3,'Loan Tape'!$AM$4:$AM$303,0)),"") -> 1.98 | H19: =IFERROR(INDEX('Loan Tape'!$T$4:$T$303,MATCH(3,'Loan Tape'!$AM$4:$AM$303,0)),"") -> 0.095 | I19: =IFERROR(INDEX('Loan Tape'!$V$4:$V$303,MATCH(3,'Loan Tape'!$AM$4:$AM$303,0)),"") -> 0.693
B20: =IFERROR(INDEX('Loan Tape'!$B$4:$B$303,MATCH(4,'Loan Tape'!$AM$4:$AM$303,0)),"") -> Foxhollow Warehouse | C20: =IFERROR(INDEX('Loan Tape'!$C$4:$C$303,MATCH(4,'Loan Tape'!$AM$4:$AM$303,0)),"") -> AZ | D20: =IFERROR(INDEX('Loan Tape'!$E$4:$E$303,MATCH(4,'Loan Tape'!$AM$4:$AM$303,0)),"") -> Deal 1 | E20: =IFERROR(INDEX('Loan Tape'!$R$4:$R$303,MATCH(4,'Loan Tape'!$AM$4:$AM$303,0)),"") -> 120313000 | F20: =IFERROR(E20/C5,"") -> 0.048209857 | G20: =IFERROR(INDEX('Loan Tape'!$U$4:$U$303,MATCH(4,'Loan Tape'!$AM$4:$AM$303,0)),"") -> 1.38 | H20: =IFERROR(INDEX('Loan Tape'!$T$4:$T$303,MATCH(4,'Loan Tape'!$AM$4:$AM$303,0)),"") -> 0.0814 | I20: =IFERROR(INDEX('Loan Tape'!$V$4:$V$303,MATCH(4,'Loan Tape'!$AM$4:$AM$303,0)),"") -> 0.663
B21: =IFERROR(INDEX('Loan Tape'!$B$4:$B$303,MATCH(5,'Loan Tape'!$AM$4:$AM$303,0)),"") -> Deerfield Terrace | C21: =IFERROR(INDEX('Loan Tape'!$C$4:$C$303,MATCH(5,'Loan Tape'!$AM$4:$AM$303,0)),"") -> CO | D21: =IFERROR(INDEX('Loan Tape'!$E$4:$E$303,MATCH(5,'Loan Tape'!$AM$4:$AM$303,0)),"") -> Deal 7 | E21: =IFERROR(INDEX('Loan Tape'!$R$4:$R$303,MATCH(5,'Loan Tape'!$AM$4:$AM$303,0)),"") -> 119229000 | F21: =IFERROR(E21/C5,"") -> 0.047775494 | G21: =IFERROR(INDEX('Loan Tape'!$U$4:$U$303,MATCH(5,'Loan Tape'!$AM$4:$AM$303,0)),"") -> 1.41 | H21: =IFERROR(INDEX('Loan Tape'!$T$4:$T$303,MATCH(5,'Loan Tape'!$AM$4:$AM$303,0)),"") -> 0.036 | I21: =IFERROR(INDEX('Loan Tape'!$V$4:$V$303,MATCH(5,'Loan Tape'!$AM$4:$AM$303,0)),"") -> 0.931
B22: =IFERROR(INDEX('Loan Tape'!$B$4:$B$303,MATCH(6,'Loan Tape'!$AM$4:$AM$303,0)),"") -> Pinehurst Plaza | C22: =IFERROR(INDEX('Loan Tape'!$C$4:$C$303,MATCH(6,'Loan Tape'!$AM$4:$AM$303,0)),"") -> WA | D22: =IFERROR(INDEX('Loan Tape'!$E$4:$E$303,MATCH(6,'Loan Tape'!$AM$4:$AM$303,0)),"") -> Deal 8 | E22: =IFERROR(INDEX('Loan Tape'!$R$4:$R$303,MATCH(6,'Loan Tape'!$AM$4:$AM$303,0)),"") -> 117696000 | F22: =IFERROR(E22/C5,"") -> 0.047161215 | G22: =IFERROR(INDEX('Loan Tape'!$U$4:$U$303,MATCH(6,'Loan Tape'!$AM$4:$AM$303,0)),"") -> 1.46 | H22: =IFERROR(INDEX('Loan Tape'!$T$4:$T$303,MATCH(6,'Loan Tape'!$AM$4:$AM$303,0)),"") -> 0.0782 | I22: =IFERROR(INDEX('Loan Tape'!$V$4:$V$303,MATCH(6,'Loan Tape'!$AM$4:$AM$303,0)),"") -> 0.587
B23: =IFERROR(INDEX('Loan Tape'!$B$4:$B$303,MATCH(7,'Loan Tape'!$AM$4:$AM$303,0)),"") -> Northgate Flats | C23: =IFERROR(INDEX('Loan Tape'!$C$4:$C$303,MATCH(7,'Loan Tape'!$AM$4:$AM$303,0)),"") -> NC | D23: =IFERROR(INDEX('Loan Tape'!$E$4:$E$303,MATCH(7,'Loan Tape'!$AM$4:$AM$303,0)),"") -> Deal 2 | E23: =IFERROR(INDEX('Loan Tape'!$R$4:$R$303,MATCH(7,'Loan Tape'!$AM$4:$AM$303,0)),"") -> 113370000 | F23: =IFERROR(E23/C5,"") -> 0.045427771 | G23: =IFERROR(INDEX('Loan Tape'!$U$4:$U$303,MATCH(7,'Loan Tape'!$AM$4:$AM$303,0)),"") -> 0.7 | H23: =IFERROR(INDEX('Loan Tape'!$T$4:$T$303,MATCH(7,'Loan Tape'!$AM$4:$AM$303,0)),"") -> 0.1329 | I23: =IFERROR(INDEX('Loan Tape'!$V$4:$V$303,MATCH(7,'Loan Tape'!$AM$4:$AM$303,0)),"") -> 0.804
B24: =IFERROR(INDEX('Loan Tape'!$B$4:$B$303,MATCH(8,'Loan Tape'!$AM$4:$AM$303,0)),"") -> Vista Corporate Center | C24: =IFERROR(INDEX('Loan Tape'!$C$4:$C$303,MATCH(8,'Loan Tape'!$AM$4:$AM$303,0)),"") -> WA | D24: =IFERROR(INDEX('Loan Tape'!$E$4:$E$303,MATCH(8,'Loan Tape'!$AM$4:$AM$303,0)),"") -> Deal 7 | E24: =IFERROR(INDEX('Loan Tape'!$R$4:$R$303,MATCH(8,'Loan Tape'!$AM$4:$AM$303,0)),"") -> 100201000 | F24: =IFERROR(E24/C5,"") -> 0.040150905 | G24: =IFERROR(INDEX('Loan Tape'!$U$4:$U$303,MATCH(8,'Loan Tape'!$AM$4:$AM$303,0)),"") -> 1.44 | H24: =IFERROR(INDEX('Loan Tape'!$T$4:$T$303,MATCH(8,'Loan Tape'!$AM$4:$AM$303,0)),"") -> 0.1226 | I24: =IFERROR(INDEX('Loan Tape'!$V$4:$V$303,MATCH(8,'Loan Tape'!$AM$4:$AM$303,0)),"") -> 0.579
B25: =IFERROR(INDEX('Loan Tape'!$B$4:$B$303,MATCH(9,'Loan Tape'!$AM$4:$AM$303,0)),"") -> Oakmont Village | C25: =IFERROR(INDEX('Loan Tape'!$C$4:$C$303,MATCH(9,'Loan Tape'!$AM$4:$AM$303,0)),"") -> MD | D25: =IFERROR(INDEX('Loan Tape'!$E$4:$E$303,MATCH(9,'Loan Tape'!$AM$4:$AM$303,0)),"") -> Deal 8 | E25: =IFERROR(INDEX('Loan Tape'!$R$4:$R$303,MATCH(9,'Loan Tape'!$AM$4:$AM$303,0)),"") -> 89897000 | F25: =IFERROR(E25/C5,"") -> 0.036022055 | G25: =IFERROR(INDEX('Loan Tape'!$U$4:$U$303,MATCH(9,'Loan Tape'!$AM$4:$AM$303,0)),"") -> 1.1 | H25: =IFERROR(INDEX('Loan Tape'!$T$4:$T$303,MATCH(9,'Loan Tape'!$AM$4:$AM$303,0)),"") -> 0.0889 | I25: =IFERROR(INDEX('Loan Tape'!$V$4:$V$303,MATCH(9,'Loan Tape'!$AM$4:$AM$303,0)),"") -> 0.703
B26: =IFERROR(INDEX('Loan Tape'!$B$4:$B$303,MATCH(10,'Loan Tape'!$AM$4:$AM$303,0)),"") -> Keystone Exchange | C26: =IFERROR(INDEX('Loan Tape'!$C$4:$C$303,MATCH(10,'Loan Tape'!$AM$4:$AM$303,0)),"") -> WA | D26: =IFERROR(INDEX('Loan Tape'!$E$4:$E$303,MATCH(10,'Loan Tape'!$AM$4:$AM$303,0)),"") -> Deal 3 | E26: =IFERROR(INDEX('Loan Tape'!$R$4:$R$303,MATCH(10,'Loan Tape'!$AM$4:$AM$303,0)),"") -> 88481000 | F26: =IFERROR(E26/C5,"") -> 0.035454658 | G26: =IFERROR(INDEX('Loan Tape'!$U$4:$U$303,MATCH(10,'Loan Tape'!$AM$4:$AM$303,0)),"") -> 1.8 | H26: =IFERROR(INDEX('Loan Tape'!$T$4:$T$303,MATCH(10,'Loan Tape'!$AM$4:$AM$303,0)),"") -> 0.072 | I26: =IFERROR(INDEX('Loan Tape'!$V$4:$V$303,MATCH(10,'Loan Tape'!$AM$4:$AM$303,0)),"") -> 0.478
B27: Top 10 Total / Wtd. Avg. | E27: =SUM(E17:E26) -> 1148995000 | F27: =IFERROR(E27/C5,0) -> 0.46040647 | G27: =IFERROR(SUMPRODUCT(E17:E26,G17:G26)/E27,"-") -> 1.4485109 | H27: =IFERROR(SUMPRODUCT(E17:E26,H17:H26)/E27,"-") -> 0.088069945 | I27: =IFERROR(SUMPRODUCT(E17:E26,I17:I26)/E27,"-") -> 0.7085198
B29: RATE TYPE
B30: Category | C30: Number of Loans | D30: Number of Units | E30: Current Principal Balance | F30: % of Current Principal Balance | G30: Wtd. Avg. Most Recent DSCR | H30: Wtd. Avg. Seasoning | I30: Wtd. Avg. Remaining Term | J30: % UPB Floating | K30: Wtd. Avg. Most Recent NOI Debt Yield | L30: Wtd. Avg. Most Recent LTV Ratio | M30: Wtd. Avg. SSP / UW LTV Ratio | N30: Wtd. Avg. Coupon | O30: Wtd. Avg. Coupon at Reset | P30: Wtd. Avg. Occupancy
B31: =R31 -> Floating | C31: =COUNTIF('Loan Tape'!$K$4:$K$303,R31) -> 34 | D31: =SUMPRODUCT((('Loan Tape'!$R$4:$R$303<>"")*('Loan Tape'!$K$4:$K$303=R31))*'Loan Tape'!$F$4:$F$303) -> 2730 | E31: =SUMIF('Loan Tape'!$K$4:$K$303,R31,'Loan Tape'!$R$4:$R$303) -> 1658277000 | F31: =IFERROR(E31/C5,0) -> 0.66447762 | G31: =IFERROR(SUMPRODUCT((('Loan Tape'!$R$4:$R$303<>"")*('Loan Tape'!$K$4:$K$303=R31))*'Loan Tape'!$U$4:$U$303*'Loan Tape'!$R$4:$R$303)/E31,"-") -> 1.3843255 | H31: =IFERROR(SUMPRODUCT((('Loan Tape'!$R$4:$R$303<>"")*('Loan Tape'!$K$4:$K$303=R31))*'Loan Tape'!$AH$4:$AH$303*'Loan Tape'!$R$4:$R$303)/E31,"-") -> 74.144035 | I31: =IFERROR(SUMPRODUCT((('Loan Tape'!$R$4:$R$303<>"")*('Loan Tape'!$K$4:$K$303=R31))*(('Loan Tape'!$H$4:$H$303-$C$4)/30.4375)*'Loan Tape'!$R$4:$R$303)/E31,"-") -> 25.524713 | J31: =IFERROR(SUMPRODUCT((('Loan Tape'!$R$4:$R$303<>"")*('Loan Tape'!$K$4:$K$303=R31))*('Loan Tape'!$K$4:$K$303="Floating")*'Loan Tape'!$R$4:$R$303)/E31,"-") -> 1 | K31: =IFERROR(SUMPRODUCT((('Loan Tape'!$R$4:$R$303<>"")*('Loan Tape'!$K$4:$K$303=R31))*'Loan Tape'!$T$4:$T$303*'Loan Tape'!$R$4:$R$303)/E31,"-") -> 0.082184215 | L31: =IFERROR(SUMPRODUCT((('Loan Tape'!$R$4:$R$303<>"")*('Loan Tape'!$K$4:$K$303=R31))*'Loan Tape'!$V$4:$V$303*'Loan Tape'!$R$4:$R$303)/E31,"-") -> 0.68344267 | M31: =IFERROR(SUMPRODUCT((('Loan Tape'!$R$4:$R$303<>"")*('Loan Tape'!$K$4:$K$303=R31))*'Loan Tape'!$W$4:$W$303*'Loan Tape'!$R$4:$R$303)/E31,"-") -> 0.71390174 | N31: =IFERROR(SUMPRODUCT((('Loan Tape'!$R$4:$R$303<>"")*('Loan Tape'!$K$4:$K$303=R31))*'Loan Tape'!$AI$4:$AI$303*'Loan Tape'!$R$4:$R$303)/E31,"-") -> 0.077386821 | O31: =IFERROR(SUMPRODUCT((('Loan Tape'!$R$4:$R$303<>"")*('Loan Tape'!$K$4:$K$303=R31))*'Loan Tape'!$AK$4:$AK$303*'Loan Tape'!$R$4:$R$303)/E31,"-") -> 0.090559371 | P31: =IFERROR(SUMPRODUCT((('Loan Tape'!$R$4:$R$303<>"")*('Loan Tape'!$K$4:$K$303=R31))*'Loan Tape'!$S$4:$S$303*'Loan Tape'!$R$4:$R$303)/E31,"-") -> 0.88528938 | R31: Floating
B32: =R32 -> Fixed | C32: =COUNTIF('Loan Tape'!$K$4:$K$303,R32) -> 16 | D32: =SUMPRODUCT((('Loan Tape'!$R$4:$R$303<>"")*('Loan Tape'!$K$4:$K$303=R32))*'Loan Tape'!$F$4:$F$303) -> 2009 | E32: =SUMIF('Loan Tape'!$K$4:$K$303,R32,'Loan Tape'!$R$4:$R$303) -> 837333000 | F32: =IFERROR(E32/C5,0) -> 0.33552238 | G32: =IFERROR(SUMPRODUCT((('Loan Tape'!$R$4:$R$303<>"")*('Loan Tape'!$K$4:$K$303=R32))*'Loan Tape'!$U$4:$U$303*'Loan Tape'!$R$4:$R$303)/E32,"-") -> 1.3289908 | H32: =IFERROR(SUMPRODUCT((('Loan Tape'!$R$4:$R$303<>"")*('Loan Tape'!$K$4:$K$303=R32))*'Loan Tape'!$AH$4:$AH$303*'Loan Tape'!$R$4:$R$303)/E32,"-") -> 81.209733 | I32: =IFERROR(SUMPRODUCT((('Loan Tape'!$R$4:$R$303<>"")*('Loan Tape'!$K$4:$K$303=R32))*(('Loan Tape'!$H$4:$H$303-$C$4)/30.4375)*'Loan Tape'!$R$4:$R$303)/E32,"-") -> 2.1360535 | J32: =IFERROR(SUMPRODUCT((('Loan Tape'!$R$4:$R$303<>"")*('Loan Tape'!$K$4:$K$303=R32))*('Loan Tape'!$K$4:$K$303="Floating")*'Loan Tape'!$R$4:$R$303)/E32,"-") -> 0 | K32: =IFERROR(SUMPRODUCT((('Loan Tape'!$R$4:$R$303<>"")*('Loan Tape'!$K$4:$K$303=R32))*'Loan Tape'!$T$4:$T$303*'Loan Tape'!$R$4:$R$303)/E32,"-") -> 0.09401604 | L32: =IFERROR(SUMPRODUCT((('Loan Tape'!$R$4:$R$303<>"")*('Loan Tape'!$K$4:$K$303=R32))*'Loan Tape'!$V$4:$V$303*'Loan Tape'!$R$4:$R$303)/E32,"-") -> 0.68379015 | M32: =IFERROR(SUMPRODUCT((('Loan Tape'!$R$4:$R$303<>"")*('Loan Tape'!$K$4:$K$303=R32))*'Loan Tape'!$W$4:$W$303*'Loan Tape'!$R$4:$R$303)/E32,"-") -> 0.72064561 | N32: =IFERROR(SUMPRODUCT((('Loan Tape'!$R$4:$R$303<>"")*('Loan Tape'!$K$4:$K$303=R32))*'Loan Tape'!$AI$4:$AI$303*'Loan Tape'!$R$4:$R$303)/E32,"-") -> 0.056734342 | O32: =IFERROR(SUMPRODUCT((('Loan Tape'!$R$4:$R$303<>"")*('Loan Tape'!$K$4:$K$303=R32))*'Loan Tape'!$AK$4:$AK$303*'Loan Tape'!$R$4:$R$303)/E32,"-") -> 0.056734342 | P32: =IFERROR(SUMPRODUCT((('Loan Tape'!$R$4:$R$303<>"")*('Loan Tape'!$K$4:$K$303=R32))*'Loan Tape'!$S$4:$S$303*'Loan Tape'!$R$4:$R$303)/E32,"-") -> 0.88945531 | R32: Fixed
B33: Other / Unspecified | C33: =C6-SUM(C31:C32) -> 0 | D33: =SUM('Loan Tape'!$F$4:$F$303)-SUM(D31:D32) -> 0 | E33: =C5-SUM(E31:E32) -> 0 | F33: =IFERROR(E33/C5,0) -> 0 | G33: =IFERROR(SUMPRODUCT((('Loan Tape'!$R$4:$R$303<>"")*(1-(('Loan Tape'!$K$4:$K$303=R31)+('Loan Tape'!$K$4:$K$303=R32))))*'Loan Tape'!$U$4:$U$303*'Loan Tape'!$R$4:$R$303)/E33,"-") -> - | H33: =IFERROR(SUMPRODUCT((('Loan Tape'!$R$4:$R$303<>"")*(1-(('Loan Tape'!$K$4:$K$303=R31)+('Loan Tape'!$K$4:$K$303=R32))))*'Loan Tape'!$AH$4:$AH$303*'Loan Tape'!$R$4:$R$303)/E33,"-") -> - | I33: =IFERROR(SUMPRODUCT((('Loan Tape'!$R$4:$R$303<>"")*(1-(('Loan Tape'!$K$4:$K$303=R31)+('Loan Tape'!$K$4:$K$303=R32))))*(('Loan Tape'!$H$4:$H$303-$C$4)/30.4375)*'Loan Tape'!$R$4:$R$303)/E33,"-") -> - | J33: =IFERROR(SUMPRODUCT((('Loan Tape'!$R$4:$R$303<>"")*(1-(('Loan Tape'!$K$4:$K$303=R31)+('Loan Tape'!$K$4:$K$303=R32))))*('Loan Tape'!$K$4:$K$303="Floating")*'Loan Tape'!$R$4:$R$303)/E33,"-") -> - | K33: =IFERROR(SUMPRODUCT((('Loan Tape'!$R$4:$R$303<>"")*(1-(('Loan Tape'!$K$4:$K$303=R31)+('Loan Tape'!$K$4:$K$303=R32))))*'Loan Tape'!$T$4:$T$303*'Loan Tape'!$R$4:$R$303)/E33,"-") -> - | L33: =IFERROR(SUMPRODUCT((('Loan Tape'!$R$4:$R$303<>"")*(1-(('Loan Tape'!$K$4:$K$303=R31)+('Loan Tape'!$K$4:$K$303=R32))))*'Loan Tape'!$V$4:$V$303*'Loan Tape'!$R$4:$R$303)/E33,"-") -> - | M33: =IFERROR(SUMPRODUCT((('Loan Tape'!$R$4:$R$303<>"")*(1-(('Loan Tape'!$K$4:$K$303=R31)+('Loan Tape'!$K$4:$K$303=R32))))*'Loan Tape'!$W$4:$W$303*'Loan Tape'!$R$4:$R$303)/E33,"-") -> - | N33: =IFERROR(SUMPRODUCT((('Loan Tape'!$R$4:$R$303<>"")*(1-(('Loan Tape'!$K$4:$K$303=R31)+('Loan Tape'!$K$4:$K$303=R32))))*'Loan Tape'!$AI$4:$AI$303*'Loan Tape'!$R$4:$R$303)/E33,"-") -> - | O33: =IFERROR(SUMPRODUCT((('Loan Tape'!$R$4:$R$303<>"")*(1-(('Loan Tape'!$K$4:$K$303=R31)+('Loan Tape'!$K$4:$K$303=R32))))*'Loan Tape'!$AK$4:$AK$303*'Loan Tape'!$R$4:$R$303)/E33,"-") -> - | P33: =IFERROR(SUMPRODUCT((('Loan Tape'!$R$4:$R$303<>"")*(1-(('Loan Tape'!$K$4:$K$303=R31)+('Loan Tape'!$K$4:$K$303=R32))))*'Loan Tape'!$S$4:$S$303*'Loan Tape'!$R$4:$R$303)/E33,"-") -> -
B34: Total / Wtd. Avg. | C34: =C6 -> 50 | D34: =SUM('Loan Tape'!$F$4:$F$303) -> 4739 | E34: =C5 -> 2495610000 | F34: =1 -> 1 | G34: =IFERROR(SUMPRODUCT((('Loan Tape'!$R$4:$R$303<>""))*'Loan Tape'!$U$4:$U$303*'Loan Tape'!$R$4:$R$303)/E34,"-") -> 1.3657594 | H34: =IFERROR(SUMPRODUCT((('Loan Tape'!$R$4:$R$303<>""))*'Loan Tape'!$AH$4:$AH$303*'Loan Tape'!$R$4:$R$303)/E34,"-") -> 76.514735 | I34: =IFERROR(SUMPRODUCT((('Loan Tape'!$R$4:$R$303<>""))*(('Loan Tape'!$H$4:$H$303-$C$4)/30.4375)*'Loan Tape'!$R$4:$R$303)/E34,"-") -> 17.677294 | J34: =IFERROR(SUMPRODUCT((('Loan Tape'!$R$4:$R$303<>""))*('Loan Tape'!$K$4:$K$303="Floating")*'Loan Tape'!$R$4:$R$303)/E34,"-") -> 0.66447762 | K34: =IFERROR(SUMPRODUCT((('Loan Tape'!$R$4:$R$303<>""))*'Loan Tape'!$T$4:$T$303*'Loan Tape'!$R$4:$R$303)/E34,"-") -> 0.086154057 | L34: =IFERROR(SUMPRODUCT((('Loan Tape'!$R$4:$R$303<>""))*'Loan Tape'!$V$4:$V$303*'Loan Tape'!$R$4:$R$303)/E34,"-") -> 0.68355926 | M34: =IFERROR(SUMPRODUCT((('Loan Tape'!$R$4:$R$303<>""))*'Loan Tape'!$W$4:$W$303*'Loan Tape'!$R$4:$R$303)/E34,"-") -> 0.71616446 | N34: =IFERROR(SUMPRODUCT((('Loan Tape'!$R$4:$R$303<>""))*'Loan Tape'!$AI$4:$AI$303*'Loan Tape'!$R$4:$R$303)/E34,"-") -> 0.070457452 | O34: =IFERROR(SUMPRODUCT((('Loan Tape'!$R$4:$R$303<>""))*'Loan Tape'!$AK$4:$AK$303*'Loan Tape'!$R$4:$R$303)/E34,"-") -> 0.079210317 | P34: =IFERROR(SUMPRODUCT((('Loan Tape'!$R$4:$R$303<>""))*'Loan Tape'!$S$4:$S$303*'Loan Tape'!$R$4:$R$303)/E34,"-") -> 0.88668714
B36: LIEN POSITION / SENIORITY
B37: Category | C37: Number of Loans | D37: Number of Units | E37: Current Principal Balance | F37: % of Current Principal Balance | G37: Wtd. Avg. Most Recent DSCR | H37: Wtd. Avg. Seasoning | I37: Wtd. Avg. Remaining Term | J37: % UPB Floating | K37: Wtd. Avg. Most Recent NOI Debt Yield | L37: Wtd. Avg. Most Recent LTV Ratio | M37: Wtd. Avg. SSP / UW LTV Ratio | N37: Wtd. Avg. Coupon | O37: Wtd. Avg. Coupon at Reset | P37: Wtd. Avg. Occupancy
B38: =R38 -> First Lien | C38: =COUNTIF('Loan Tape'!$AC$4:$AC$303,R38) -> 46 | D38: =SUMPRODUCT((('Loan Tape'!$R$4:$R$303<>"")*('Loan Tape'!$AC$4:$AC$303=R38))*'Loan Tape'!$F$4:$F$303) -> 4739 | E38: =SUMIF('Loan Tape'!$AC$4:$AC$303,R38,'Loan Tape'!$R$4:$R$303) -> 2418148000 | F38: =IFERROR(E38/C5,0) -> 0.96896069 | G38: =IFERROR(SUMPRODUCT((('Loan Tape'!$R$4:$R$303<>"")*('Loan Tape'!$AC$4:$AC$303=R38))*'Loan Tape'!$U$4:$U$303*'Loan Tape'!$R$4:$R$303)/E38,"-") -> 1.3585459 | H38: =IFERROR(SUMPRODUCT((('Loan Tape'!$R$4:$R$303<>"")*('Loan Tape'!$AC$4:$AC$303=R38))*'Loan Tape'!$AH$4:$AH$303*'Loan Tape'!$R$4:$R$303)/E38,"-") -> 76.60337 | I38: =IFERROR(SUMPRODUCT((('Loan Tape'!$R$4:$R$303<>"")*('Loan Tape'!$AC$4:$AC$303=R38))*(('Loan Tape'!$H$4:$H$303-$C$4)/30.4375)*'Loan Tape'!$R$4:$R$303)/E38,"-") -> 18.227593 | J38: =IFERROR(SUMPRODUCT((('Loan Tape'!$R$4:$R$303<>"")*('Loan Tape'!$AC$4:$AC$303=R38))*('Loan Tape'!$K$4:$K$303="Floating")*'Loan Tape'!$R$4:$R$303)/E38,"-") -> 0.65584323 | K38: =IFERROR(SUMPRODUCT((('Loan Tape'!$R$4:$R$303<>"")*('Loan Tape'!$AC$4:$AC$303=R38))*'Loan Tape'!$T$4:$T$303*'Loan Tape'!$R$4:$R$303)/E38,"-") -> 0.086766261 | L38: =IFERROR(SUMPRODUCT((('Loan Tape'!$R$4:$R$303<>"")*('Loan Tape'!$AC$4:$AC$303=R38))*'Loan Tape'!$V$4:$V$303*'Loan Tape'!$R$4:$R$303)/E38,"-") -> 0.6828145 | M38: =IFERROR(SUMPRODUCT((('Loan Tape'!$R$4:$R$303<>"")*('Loan Tape'!$AC$4:$AC$303=R38))*'Loan Tape'!$W$4:$W$303*'Loan Tape'!$R$4:$R$303)/E38,"-") -> 0.71517211 | N38: =IFERROR(SUMPRODUCT((('Loan Tape'!$R$4:$R$303<>"")*('Loan Tape'!$AC$4:$AC$303=R38))*'Loan Tape'!$AI$4:$AI$303*'Loan Tape'!$R$4:$R$303)/E38,"-") -> 0.070219279 | O38: =IFERROR(SUMPRODUCT((('Loan Tape'!$R$4:$R$303<>"")*('Loan Tape'!$AC$4:$AC$303=R38))*'Loan Tape'!$AK$4:$AK$303*'Loan Tape'!$R$4:$R$303)/E38,"-") -> 0.079272881 | P38: =IFERROR(SUMPRODUCT((('Loan Tape'!$R$4:$R$303<>"")*('Loan Tape'!$AC$4:$AC$303=R38))*'Loan Tape'!$S$4:$S$303*'Loan Tape'!$R$4:$R$303)/E38,"-") -> 0.88786418 | R38: First Lien
B39: =R39 -> Second Lien | C39: =COUNTIF('Loan Tape'!$AC$4:$AC$303,R39) -> 4 | D39: =SUMPRODUCT((('Loan Tape'!$R$4:$R$303<>"")*('Loan Tape'!$AC$4:$AC$303=R39))*'Loan Tape'!$F$4:$F$303) -> 0 | E39: =SUMIF('Loan Tape'!$AC$4:$AC$303,R39,'Loan Tape'!$R$4:$R$303) -> 77462000 | F39: =IFERROR(E39/C5,0) -> 0.031039305 | G39: =IFERROR(SUMPRODUCT((('Loan Tape'!$R$4:$R$303<>"")*('Loan Tape'!$AC$4:$AC$303=R39))*'Loan Tape'!$U$4:$U$303*'Loan Tape'!$R$4:$R$303)/E39,"-") -> 1.5909449 | H39: =IFERROR(SUMPRODUCT((('Loan Tape'!$R$4:$R$303<>"")*('Loan Tape'!$AC$4:$AC$303=R39))*'Loan Tape'!$AH$4:$AH$303*'Loan Tape'!$R$4:$R$303)/E39,"-") -> 73.747796 | I39: =IFERROR(SUMPRODUCT((('Loan Tape'!$R$4:$R$303<>"")*('Loan Tape'!$AC$4:$AC$303=R39))*(('Loan Tape'!$H$4:$H$303-$C$4)/30.4375)*'Loan Tape'!$R$4:$R$303)/E39,"-") -> 0.49850968 | J39: =IFERROR(SUMPRODUCT((('Loan Tape'!$R$4:$R$303<>"")*('Loan Tape'!$AC$4:$AC$303=R39))*('Loan Tape'!$K$4:$K$303="Floating")*'Loan Tape'!$R$4:$R$303)/E39,"-") -> 0.93401926 | K39: =IFERROR(SUMPRODUCT((('Loan Tape'!$R$4:$R$303<>"")*('Loan Tape'!$AC$4:$AC$303=R39))*'Loan Tape'!$T$4:$T$303*'Loan Tape'!$R$4:$R$303)/E39,"-") -> 0.067042742 | L39: =IFERROR(SUMPRODUCT((('Loan Tape'!$R$4:$R$303<>"")*('Loan Tape'!$AC$4:$AC$303=R39))*'Loan Tape'!$V$4:$V$303*'Loan Tape'!$R$4:$R$303)/E39,"-") -> 0.70680858 | M39: =IFERROR(SUMPRODUCT((('Loan Tape'!$R$4:$R$303<>"")*('Loan Tape'!$AC$4:$AC$303=R39))*'Loan Tape'!$W$4:$W$303*'Loan Tape'!$R$4:$R$303)/E39,"-") -> 0.74714286 | N39: =IFERROR(SUMPRODUCT((('Loan Tape'!$R$4:$R$303<>"")*('Loan Tape'!$AC$4:$AC$303=R39))*'Loan Tape'!$AI$4:$AI$303*'Loan Tape'!$R$4:$R$303)/E39,"-") -> 0.077892545 | O39: =IFERROR(SUMPRODUCT((('Loan Tape'!$R$4:$R$303<>"")*('Loan Tape'!$AC$4:$AC$303=R39))*'Loan Tape'!$AK$4:$AK$303*'Loan Tape'!$R$4:$R$303)/E39,"-") -> 0.077257225 | P39: =IFERROR(SUMPRODUCT((('Loan Tape'!$R$4:$R$303<>"")*('Loan Tape'!$AC$4:$AC$303=R39))*'Loan Tape'!$S$4:$S$303*'Loan Tape'!$R$4:$R$303)/E39,"-") -> 0.84994324 | R39: Second Lien
B40: Other | C40: =C6-SUM(C38:C39) -> 0 | D40: =SUM('Loan Tape'!$F$4:$F$303)-SUM(D38:D39) -> 0 | E40: =C5-SUM(E38:E39) -> 0 | F40: =IFERROR(E40/C5,0) -> 0 | G40: =IFERROR(SUMPRODUCT((('Loan Tape'!$R$4:$R$303<>"")*(1-(('Loan Tape'!$AC$4:$AC$303=R38)+('Loan Tape'!$AC$4:$AC$303=R39))))*'Loan Tape'!$U$4:$U$303*'Loan Tape'!$R$4:$R$303)/E40,"-") -> - | H40: =IFERROR(SUMPRODUCT((('Loan Tape'!$R$4:$R$303<>"")*(1-(('Loan Tape'!$AC$4:$AC$303=R38)+('Loan Tape'!$AC$4:$AC$303=R39))))*'Loan Tape'!$AH$4:$AH$303*'Loan Tape'!$R$4:$R$303)/E40,"-") -> - | I40: =IFERROR(SUMPRODUCT((('Loan Tape'!$R$4:$R$303<>"")*(1-(('Loan Tape'!$AC$4:$AC$303=R38)+('Loan Tape'!$AC$4:$AC$303=R39))))*(('Loan Tape'!$H$4:$H$303-$C$4)/30.4375)*'Loan Tape'!$R$4:$R$303)/E40,"-") -> - | J40: =IFERROR(SUMPRODUCT((('Loan Tape'!$R$4:$R$303<>"")*(1-(('Loan Tape'!$AC$4:$AC$303=R38)+('Loan Tape'!$AC$4:$AC$303=R39))))*('Loan Tape'!$K$4:$K$303="Floating")*'Loan Tape'!$R$4:$R$303)/E40,"-") -> - | K40: =IFERROR(SUMPRODUCT((('Loan Tape'!$R$4:$R$303<>"")*(1-(('Loan Tape'!$AC$4:$AC$303=R38)+('Loan Tape'!$AC$4:$AC$303=R39))))*'Loan Tape'!$T$4:$T$303*'Loan Tape'!$R$4:$R$303)/E40,"-") -> - | L40: =IFERROR(SUMPRODUCT((('Loan Tape'!$R$4:$R$303<>"")*(1-(('Loan Tape'!$AC$4:$AC$303=R38)+('Loan Tape'!$AC$4:$AC$303=R39))))*'Loan Tape'!$V$4:$V$303*'Loan Tape'!$R$4:$R$303)/E40,"-") -> - | M40: =IFERROR(SUMPRODUCT((('Loan Tape'!$R$4:$R$303<>"")*(1-(('Loan Tape'!$AC$4:$AC$303=R38)+('Loan Tape'!$AC$4:$AC$303=R39))))*'Loan Tape'!$W$4:$W$303*'Loan Tape'!$R$4:$R$303)/E40,"-") -> - | N40: =IFERROR(SUMPRODUCT((('Loan Tape'!$R$4:$R$303<>"")*(1-(('Loan Tape'!$AC$4:$AC$303=R38)+('Loan Tape'!$AC$4:$AC$303=R39))))*'Loan Tape'!$AI$4:$AI$303*'Loan Tape'!$R$4:$R$303)/E40,"-") -> - | O40: =IFERROR(SUMPRODUCT((('Loan Tape'!$R$4:$R$303<>"")*(1-(('Loan Tape'!$AC$4:$AC$303=R38)+('Loan Tape'!$AC$4:$AC$303=R39))))*'Loan Tape'!$AK$4:$AK$303*'Loan Tape'!$R$4:$R$303)/E40,"-") -> - | P40: =IFERROR(SUMPRODUCT((('Loan Tape'!$R$4:$R$303<>"")*(1-(('Loan Tape'!$AC$4:$AC$303=R38)+('Loan Tape'!$AC$4:$AC$303=R39))))*'Loan Tape'!$S$4:$S$303*'Loan Tape'!$R$4:$R$303)/E40,"-") -> -
B41: Total / Wtd. Avg. | C41: =C6 -> 50 | D41: =SUM('Loan Tape'!$F$4:$F$303) -> 4739 | E41: =C5 -> 2495610000 | F41: =1 -> 1 | G41: =IFERROR(SUMPRODUCT((('Loan Tape'!$R$4:$R$303<>""))*'Loan Tape'!$U$4:$U$303*'Loan Tape'!$R$4:$R$303)/E41,"-") -> 1.3657594 | H41: =IFERROR(SUMPRODUCT((('Loan Tape'!$R$4:$R$303<>""))*'Loan Tape'!$AH$4:$AH$303*'Loan Tape'!$R$4:$R$303)/E41,"-") -> 76.514735 | I41: =IFERROR(SUMPRODUCT((('Loan Tape'!$R$4:$R$303<>""))*(('Loan Tape'!$H$4:$H$303-$C$4)/30.4375)*'Loan Tape'!$R$4:$R$303)/E41,"-") -> 17.677294 | J41: =IFERROR(SUMPRODUCT((('Loan Tape'!$R$4:$R$303<>""))*('Loan Tape'!$K$4:$K$303="Floating")*'Loan Tape'!$R$4:$R$303)/E41,"-") -> 0.66447762 | K41: =IFERROR(SUMPRODUCT((('Loan Tape'!$R$4:$R$303<>""))*'Loan Tape'!$T$4:$T$303*'Loan Tape'!$R$4:$R$303)/E41,"-") -> 0.086154057 | L41: =IFERROR(SUMPRODUCT((('Loan Tape'!$R$4:$R$303<>""))*'Loan Tape'!$V$4:$V$303*'Loan Tape'!$R$4:$R$303)/E41,"-") -> 0.68355926 | M41: =IFERROR(SUMPRODUCT((('Loan Tape'!$R$4:$R$303<>""))*'Loan Tape'!$W$4:$W$303*'Loan Tape'!$R$4:$R$303)/E41,"-") -> 0.71616446 | N41: =IFERROR(SUMPRODUCT((('Loan Tape'!$R$4:$R$303<>""))*'Loan Tape'!$AI$4:$AI$303*'Loan Tape'!$R$4:$R$303)/E41,"-") -> 0.070457452 | O41: =IFERROR(SUMPRODUCT((('Loan Tape'!$R$4:$R$303<>""))*'Loan Tape'!$AK$4:$AK$303*'Loan Tape'!$R$4:$R$303)/E41,"-") -> 0.079210317 | P41: =IFERROR(SUMPRODUCT((('Loan Tape'!$R$4:$R$303<>""))*'Loan Tape'!$S$4:$S$303*'Loan Tape'!$R$4:$R$303)/E41,"-") -> 0.88668714
B43: GEOGRAPHIC DISTRIBUTION (STATE)
B44: Category | C44: Number of Loans | D44: Number of Units | E44: Current Principal Balance | F44: % of Current Principal Balance | G44: Wtd. Avg. Most Recent DSCR | H44: Wtd. Avg. Seasoning | I44: Wtd. Avg. Remaining Term | J44: % UPB Floating | K44: Wtd. Avg. Most Recent NOI Debt Yield | L44: Wtd. Avg. Most Recent LTV Ratio | M44: Wtd. Avg. SSP / UW LTV Ratio | N44: Wtd. Avg. Coupon | O44: Wtd. Avg. Coupon at Reset | P44: Wtd. Avg. Occupancy
B45: =R45 -> TX | C45: =COUNTIF('Loan Tape'!$C$4:$C$303,R45) -> 5 | D45: =SUMPRODUCT((('Loan Tape'!$R$4:$R$303<>"")*('Loan Tape'!$C$4:$C$303=R45))*'Loan Tape'!$F$4:$F$303) -> 662 | E45: =SUMIF('Loan Tape'!$C$4:$C$303,R45,'Loan Tape'!$R$4:$R$303) -> 251312000 | F45: =IFERROR(E45/C5,0) -> 0.10070163 | G45: =IFERROR(SUMPRODUCT((('Loan Tape'!$R$4:$R$303<>"")*('Loan Tape'!$C$4:$C$303=R45))*'Loan Tape'!$U$4:$U$303*'Loan Tape'!$R$4:$R$303)/E45,"-") -> 1.4701676 | H45: =IFERROR(SUMPRODUCT((('Loan Tape'!$R$4:$R$303<>"")*('Loan Tape'!$C$4:$C$303=R45))*'Loan Tape'!$AH$4:$AH$303*'Loan Tape'!$R$4:$R$303)/E45,"-") -> 44.097274 | I45: =IFERROR(SUMPRODUCT((('Loan Tape'!$R$4:$R$303<>"")*('Loan Tape'!$C$4:$C$303=R45))*(('Loan Tape'!$H$4:$H$303-$C$4)/30.4375)*'Loan Tape'!$R$4:$R$303)/E45,"-") -> 46.887233 | J45: =IFERROR(SUMPRODUCT((('Loan Tape'!$R$4:$R$303<>"")*('Loan Tape'!$C$4:$C$303=R45))*('Loan Tape'!$K$4:$K$303="Floating")*'Loan Tape'!$R$4:$R$303)/E45,"-") -> 1 | K45: =IFERROR(SUMPRODUCT((('Loan Tape'!$R$4:$R$303<>"")*('Loan Tape'!$C$4:$C$303=R45))*'Loan Tape'!$T$4:$T$303*'Loan Tape'!$R$4:$R$303)/E45,"-") -> 0.091306672 | L45: =IFERROR(SUMPRODUCT((('Loan Tape'!$R$4:$R$303<>"")*('Loan Tape'!$C$4:$C$303=R45))*'Loan Tape'!$V$4:$V$303*'Loan Tape'!$R$4:$R$303)/E45,"-") -> 0.73641118 | M45: =IFERROR(SUMPRODUCT((('Loan Tape'!$R$4:$R$303<>"")*('Loan Tape'!$C$4:$C$303=R45))*'Loan Tape'!$W$4:$W$303*'Loan Tape'!$R$4:$R$303)/E45,"-") -> 0.75898527 | N45: =IFERROR(SUMPRODUCT((('Loan Tape'!$R$4:$R$303<>"")*('Loan Tape'!$C$4:$C$303=R45))*'Loan Tape'!$AI$4:$AI$303*'Loan Tape'!$R$4:$R$303)/E45,"-") -> 0.079753043 | O45: =IFERROR(SUMPRODUCT((('Loan Tape'!$R$4:$R$303<>"")*('Loan Tape'!$C$4:$C$303=R45))*'Loan Tape'!$AK$4:$AK$303*'Loan Tape'!$R$4:$R$303)/E45,"-") -> 0.093994304 | P45: =IFERROR(SUMPRODUCT((('Loan Tape'!$R$4:$R$303<>"")*('Loan Tape'!$C$4:$C$303=R45))*'Loan Tape'!$S$4:$S$303*'Loan Tape'!$R$4:$R$303)/E45,"-") -> 0.93878922 | R45: TX
B46: =R46 -> CA | C46: =COUNTIF('Loan Tape'!$C$4:$C$303,R46) -> 2 | D46: =SUMPRODUCT((('Loan Tape'!$R$4:$R$303<>"")*('Loan Tape'!$C$4:$C$303=R46))*'Loan Tape'!$F$4:$F$303) -> 0 | E46: =SUMIF('Loan Tape'!$C$4:$C$303,R46,'Loan Tape'!$R$4:$R$303) -> 62867000 | F46: =IFERROR(E46/C5,0) -> 0.025191035 | G46: =IFERROR(SUMPRODUCT((('Loan Tape'!$R$4:$R$303<>"")*('Loan Tape'!$C$4:$C$303=R46))*'Loan Tape'!$U$4:$U$303*'Loan Tape'!$R$4:$R$303)/E46,"-") -> 1.3198467 | H46: =IFERROR(SUMPRODUCT((('Loan Tape'!$R$4:$R$303<>"")*('Loan Tape'!$C$4:$C$303=R46))*'Loan Tape'!$AH$4:$AH$303*'Loan Tape'!$R$4:$R$303)/E46,"-") -> 99.075986 | I46: =IFERROR(SUMPRODUCT((('Loan Tape'!$R$4:$R$303<>"")*('Loan Tape'!$C$4:$C$303=R46))*(('Loan Tape'!$H$4:$H$303-$C$4)/30.4375)*'Loan Tape'!$R$4:$R$303)/E46,"-") -> 20.94643 | J46: =IFERROR(SUMPRODUCT((('Loan Tape'!$R$4:$R$303<>"")*('Loan Tape'!$C$4:$C$303=R46))*('Loan Tape'!$K$4:$K$303="Floating")*'Loan Tape'!$R$4:$R$303)/E46,"-") -> 1 | K46: =IFERROR(SUMPRODUCT((('Loan Tape'!$R$4:$R$303<>"")*('Loan Tape'!$C$4:$C$303=R46))*'Loan Tape'!$T$4:$T$303*'Loan Tape'!$R$4:$R$303)/E46,"-") -> 0.086454409 | L46: =IFERROR(SUMPRODUCT((('Loan Tape'!$R$4:$R$303<>"")*('Loan Tape'!$C$4:$C$303=R46))*'Loan Tape'!$V$4:$V$303*'Loan Tape'!$R$4:$R$303)/E46,"-") -> 0.56857024 | M46: =IFERROR(SUMPRODUCT((('Loan Tape'!$R$4:$R$303<>"")*('Loan Tape'!$C$4:$C$303=R46))*'Loan Tape'!$W$4:$W$303*'Loan Tape'!$R$4:$R$303)/E46,"-") -> 0.60032694 | N46: =IFERROR(SUMPRODUCT((('Loan Tape'!$R$4:$R$303<>"")*('Loan Tape'!$C$4:$C$303=R46))*'Loan Tape'!$AI$4:$AI$303*'Loan Tape'!$R$4:$R$303)/E46,"-") -> 0.066221331 | O46: =IFERROR(SUMPRODUCT((('Loan Tape'!$R$4:$R$303<>"")*('Loan Tape'!$C$4:$C$303=R46))*'Loan Tape'!$AK$4:$AK$303*'Loan Tape'!$R$4:$R$303)/E46,"-") -> 0.081221331 | P46: =IFERROR(SUMPRODUCT((('Loan Tape'!$R$4:$R$303<>"")*('Loan Tape'!$C$4:$C$303=R46))*'Loan Tape'!$S$4:$S$303*'Loan Tape'!$R$4:$R$303)/E46,"-") -> 0.93472987 | R46: CA
B47: =R47 -> FL | C47: =COUNTIF('Loan Tape'!$C$4:$C$303,R47) -> 5 | D47: =SUMPRODUCT((('Loan Tape'!$R$4:$R$303<>"")*('Loan Tape'!$C$4:$C$303=R47))*'Loan Tape'!$F$4:$F$303) -> 487 | E47: =SUMIF('Loan Tape'!$C$4:$C$303,R47,'Loan Tape'!$R$4:$R$303) -> 236620000 | F47: =IFERROR(E47/C5,0) -> 0.094814494 | G47: =IFERROR(SUMPRODUCT((('Loan Tape'!$R$4:$R$303<>"")*('Loan Tape'!$C$4:$C$303=R47))*'Loan Tape'!$U$4:$U$303*'Loan Tape'!$R$4:$R$303)/E47,"-") -> 1.2545931 | H47: =IFERROR(SUMPRODUCT((('Loan Tape'!$R$4:$R$303<>"")*('Loan Tape'!$C$4:$C$303=R47))*'Loan Tape'!$AH$4:$AH$303*'Loan Tape'!$R$4:$R$303)/E47,"-") -> 80.964432 | I47: =IFERROR(SUMPRODUCT((('Loan Tape'!$R$4:$R$303<>"")*('Loan Tape'!$C$4:$C$303=R47))*(('Loan Tape'!$H$4:$H$303-$C$4)/30.4375)*'Loan Tape'!$R$4:$R$303)/E47,"-") -> 30.738011 | J47: =IFERROR(SUMPRODUCT((('Loan Tape'!$R$4:$R$303<>"")*('Loan Tape'!$C$4:$C$303=R47))*('Loan Tape'!$K$4:$K$303="Floating")*'Loan Tape'!$R$4:$R$303)/E47,"-") -> 0.97839997 | K47: =IFERROR(SUMPRODUCT((('Loan Tape'!$R$4:$R$303<>"")*('Loan Tape'!$C$4:$C$303=R47))*'Loan Tape'!$T$4:$T$303*'Loan Tape'!$R$4:$R$303)/E47,"-") -> 0.078132938 | L47: =IFERROR(SUMPRODUCT((('Loan Tape'!$R$4:$R$303<>"")*('Loan Tape'!$C$4:$C$303=R47))*'Loan Tape'!$V$4:$V$303*'Loan Tape'!$R$4:$R$303)/E47,"-") -> 0.75750018 | M47: =IFERROR(SUMPRODUCT((('Loan Tape'!$R$4:$R$303<>"")*('Loan Tape'!$C$4:$C$303=R47))*'Loan Tape'!$W$4:$W$303*'Loan Tape'!$R$4:$R$303)/E47,"-") -> 0.78508584 | N47: =IFERROR(SUMPRODUCT((('Loan Tape'!$R$4:$R$303<>"")*('Loan Tape'!$C$4:$C$303=R47))*'Loan Tape'!$AI$4:$AI$303*'Loan Tape'!$R$4:$R$303)/E47,"-") -> 0.081805803 | O47: =IFERROR(SUMPRODUCT((('Loan Tape'!$R$4:$R$303<>"")*('Loan Tape'!$C$4:$C$303=R47))*'Loan Tape'!$AK$4:$AK$303*'Loan Tape'!$R$4:$R$303)/E47,"-") -> 0.096481802 | P47: =IFERROR(SUMPRODUCT((('Loan Tape'!$R$4:$R$303<>"")*('Loan Tape'!$C$4:$C$303=R47))*'Loan Tape'!$S$4:$S$303*'Loan Tape'!$R$4:$R$303)/E47,"-") -> 0.8844865 | R47: FL
B48: =R48 -> NY | C48: =COUNTIF('Loan Tape'!$C$4:$C$303,R48) -> 1 | D48: =SUMPRODUCT((('Loan Tape'!$R$4:$R$303<>"")*('Loan Tape'!$C$4:$C$303=R48))*'Loan Tape'!$F$4:$F$303) -> 0 | E48: =SUMIF('Loan Tape'!$C$4:$C$303,R48,'Loan Tape'!$R$4:$R$303) -> 17633000 | F48: =IFERROR(E48/C5,0) -> 0.0070656072 | G48: =IFERROR(SUMPRODUCT((('Loan Tape'!$R$4:$R$303<>"")*('Loan Tape'!$C$4:$C$303=R48))*'Loan Tape'!$U$4:$U$303*'Loan Tape'!$R$4:$R$303)/E48,"-") -> 1.18 | H48: =IFERROR(SUMPRODUCT((('Loan Tape'!$R$4:$R$303<>"")*('Loan Tape'!$C$4:$C$303=R48))*'Loan Tape'!$AH$4:$AH$303*'Loan Tape'!$R$4:$R$303)/E48,"-") -> 37 | I48: =IFERROR(SUMPRODUCT((('Loan Tape'!$R$4:$R$303<>"")*('Loan Tape'!$C$4:$C$303=R48))*(('Loan Tape'!$H$4:$H$303-$C$4)/30.4375)*'Loan Tape'!$R$4:$R$303)/E48,"-") -> 47.047228 | J48: =IFERROR(SUMPRODUCT((('Loan Tape'!$R$4:$R$303<>"")*('Loan Tape'!$C$4:$C$303=R48))*('Loan Tape'!$K$4:$K$303="Floating")*'Loan Tape'!$R$4:$R$303)/E48,"-") -> 1 | K48: =IFERROR(SUMPRODUCT((('Loan Tape'!$R$4:$R$303<>"")*('Loan Tape'!$C$4:$C$303=R48))*'Loan Tape'!$T$4:$T$303*'Loan Tape'!$R$4:$R$303)/E48,"-") -> 0.092 | L48: =IFERROR(SUMPRODUCT((('Loan Tape'!$R$4:$R$303<>"")*('Loan Tape'!$C$4:$C$303=R48))*'Loan Tape'!$V$4:$V$303*'Loan Tape'!$R$4:$R$303)/E48,"-") -> 0.572 | M48: =IFERROR(SUMPRODUCT((('Loan Tape'!$R$4:$R$303<>"")*('Loan Tape'!$C$4:$C$303=R48))*'Loan Tape'!$W$4:$W$303*'Loan Tape'!$R$4:$R$303)/E48,"-") -> 0.597 | N48: =IFERROR(SUMPRODUCT((('Loan Tape'!$R$4:$R$303<>"")*('Loan Tape'!$C$4:$C$303=R48))*'Loan Tape'!$AI$4:$AI$303*'Loan Tape'!$R$4:$R$303)/E48,"-") -> 0.0767 | O48: =IFERROR(SUMPRODUCT((('Loan Tape'!$R$4:$R$303<>"")*('Loan Tape'!$C$4:$C$303=R48))*'Loan Tape'!$AK$4:$AK$303*'Loan Tape'!$R$4:$R$303)/E48,"-") -> 0.0917 | P48: =IFERROR(SUMPRODUCT((('Loan Tape'!$R$4:$R$303<>"")*('Loan Tape'!$C$4:$C$303=R48))*'Loan Tape'!$S$4:$S$303*'Loan Tape'!$R$4:$R$303)/E48,"-") -> 0.99 | R48: NY
B49: =R49 -> GA | C49: =COUNTIF('Loan Tape'!$C$4:$C$303,R49) -> 3 | D49: =SUMPRODUCT((('Loan Tape'!$R$4:$R$303<>"")*('Loan Tape'!$C$4:$C$303=R49))*'Loan Tape'!$F$4:$F$303) -> 238 | E49: =SUMIF('Loan Tape'!$C$4:$C$303,R49,'Loan Tape'!$R$4:$R$303) -> 186026000 | F49: =IFERROR(E49/C5,0) -> 0.074541295 | G49: =IFERROR(SUMPRODUCT((('Loan Tape'!$R$4:$R$303<>"")*('Loan Tape'!$C$4:$C$303=R49))*'Loan Tape'!$U$4:$U$303*'Loan Tape'!$R$4:$R$303)/E49,"-") -> 1.1034659 | H49: =IFERROR(SUMPRODUCT((('Loan Tape'!$R$4:$R$303<>"")*('Loan Tape'!$C$4:$C$303=R49))*'Loan Tape'!$AH$4:$AH$303*'Loan Tape'!$R$4:$R$303)/E49,"-") -> 70.46076 | I49: =IFERROR(SUMPRODUCT((('Loan Tape'!$R$4:$R$303<>"")*('Loan Tape'!$C$4:$C$303=R49))*(('Loan Tape'!$H$4:$H$303-$C$4)/30.4375)*'Loan Tape'!$R$4:$R$303)/E49,"-") -> 16.302544 | J49: =IFERROR(SUMPRODUCT((('Loan Tape'!$R$4:$R$303<>"")*('Loan Tape'!$C$4:$C$303=R49))*('Loan Tape'!$K$4:$K$303="Floating")*'Loan Tape'!$R$4:$R$303)/E49,"-") -> 0.076311913 | K49: =IFERROR(SUMPRODUCT((('Loan Tape'!$R$4:$R$303<>"")*('Loan Tape'!$C$4:$C$303=R49))*'Loan Tape'!$T$4:$T$303*'Loan Tape'!$R$4:$R$303)/E49,"-") -> 0.095392203 | L49: =IFERROR(SUMPRODUCT((('Loan Tape'!$R$4:$R$303<>"")*('Loan Tape'!$C$4:$C$303=R49))*'Loan Tape'!$V$4:$V$303*'Loan Tape'!$R$4:$R$303)/E49,"-") -> 0.71813784 | M49: =IFERROR(SUMPRODUCT((('Loan Tape'!$R$4:$R$303<>"")*('Loan Tape'!$C$4:$C$303=R49))*'Loan Tape'!$W$4:$W$303*'Loan Tape'!$R$4:$R$303)/E49,"-") -> 0.76841226 | N49: =IFERROR(SUMPRODUCT((('Loan Tape'!$R$4:$R$303<>"")*('Loan Tape'!$C$4:$C$303=R49))*'Loan Tape'!$AI$4:$AI$303*'Loan Tape'!$R$4:$R$303)/E49,"-") -> 0.061018164 | O49: =IFERROR(SUMPRODUCT((('Loan Tape'!$R$4:$R$303<>"")*('Loan Tape'!$C$4:$C$303=R49))*'Loan Tape'!$AK$4:$AK$303*'Loan Tape'!$R$4:$R$303)/E49,"-") -> 0.06093422 | P49: =IFERROR(SUMPRODUCT((('Loan Tape'!$R$4:$R$303<>"")*('Loan Tape'!$C$4:$C$303=R49))*'Loan Tape'!$S$4:$S$303*'Loan Tape'!$R$4:$R$303)/E49,"-") -> 0.89821228 | R49: GA
B50: =R50 -> NC | C50: =COUNTIF('Loan Tape'!$C$4:$C$303,R50) -> 6 | D50: =SUMPRODUCT((('Loan Tape'!$R$4:$R$303<>"")*('Loan Tape'!$C$4:$C$303=R50))*'Loan Tape'!$F$4:$F$303) -> 505 | E50: =SUMIF('Loan Tape'!$C$4:$C$303,R50,'Loan Tape'!$R$4:$R$303) -> 293937000 | F50: =IFERROR(E50/C5,0) -> 0.11778162 | G50: =IFERROR(SUMPRODUCT((('Loan Tape'!$R$4:$R$303<>"")*('Loan Tape'!$C$4:$C$303=R50))*'Loan Tape'!$U$4:$U$303*'Loan Tape'!$R$4:$R$303)/E50,"-") -> 1.0197759 | H50: =IFERROR(SUMPRODUCT((('Loan Tape'!$R$4:$R$303<>"")*('Loan Tape'!$C$4:$C$303=R50))*'Loan Tape'!$AH$4:$AH$303*'Loan Tape'!$R$4:$R$303)/E50,"-") -> 78.784458 | I50: =IFERROR(SUMPRODUCT((('Loan Tape'!$R$4:$R$303<>"")*('Loan Tape'!$C$4:$C$303=R50))*(('Loan Tape'!$H$4:$H$303-$C$4)/30.4375)*'Loan Tape'!$R$4:$R$303)/E50,"-") -> -11.671575 | J50: =IFERROR(SUMPRODUCT((('Loan Tape'!$R$4:$R$303<>"")*('Loan Tape'!$C$4:$C$303=R50))*('Loan Tape'!$K$4:$K$303="Floating")*'Loan Tape'!$R$4:$R$303)/E50,"-") -> 0.42231839 | K50: =IFERROR(SUMPRODUCT((('Loan Tape'!$R$4:$R$303<>"")*('Loan Tape'!$C$4:$C$303=R50))*'Loan Tape'!$T$4:$T$303*'Loan Tape'!$R$4:$R$303)/E50,"-") -> 0.1065011 | L50: =IFERROR(SUMPRODUCT((('Loan Tape'!$R$4:$R$303<>"")*('Loan Tape'!$C$4:$C$303=R50))*'Loan Tape'!$V$4:$V$303*'Loan Tape'!$R$4:$R$303)/E50,"-") -> 0.6878946 | M50: =IFERROR(SUMPRODUCT((('Loan Tape'!$R$4:$R$303<>"")*('Loan Tape'!$C$4:$C$303=R50))*'Loan Tape'!$W$4:$W$303*'Loan Tape'!$R$4:$R$303)/E50,"-") -> 0.72861411 | N50: =IFERROR(SUMPRODUCT((('Loan Tape'!$R$4:$R$303<>"")*('Loan Tape'!$C$4:$C$303=R50))*'Loan Tape'!$AI$4:$AI$303*'Loan Tape'!$R$4:$R$303)/E50,"-") -> 0.064047693 | O50: =IFERROR(SUMPRODUCT((('Loan Tape'!$R$4:$R$303<>"")*('Loan Tape'!$C$4:$C$303=R50))*'Loan Tape'!$AK$4:$AK$303*'Loan Tape'!$R$4:$R$303)/E50,"-") -> 0.069732364 | P50: =IFERROR(SUMPRODUCT((('Loan Tape'!$R$4:$R$303<>"")*('Loan Tape'!$C$4:$C$303=R50))*'Loan Tape'!$S$4:$S$303*'Loan Tape'!$R$4:$R$303)/E50,"-") -> 0.92703333 | R50: NC
B51: =R51 -> AZ | C51: =COUNTIF('Loan Tape'!$C$4:$C$303,R51) -> 1 | D51: =SUMPRODUCT((('Loan Tape'!$R$4:$R$303<>"")*('Loan Tape'!$C$4:$C$303=R51))*'Loan Tape'!$F$4:$F$303) -> 0 | E51: =SUMIF('Loan Tape'!$C$4:$C$303,R51,'Loan Tape'!$R$4:$R$303) -> 120313000 | F51: =IFERROR(E51/C5,0) -> 0.048209857 | G51: =IFERROR(SUMPRODUCT((('Loan Tape'!$R$4:$R$303<>"")*('Loan Tape'!$C$4:$C$303=R51))*'Loan Tape'!$U$4:$U$303*'Loan Tape'!$R$4:$R$303)/E51,"-") -> 1.38 | H51: =IFERROR(SUMPRODUCT((('Loan Tape'!$R$4:$R$303<>"")*('Loan Tape'!$C$4:$C$303=R51))*'Loan Tape'!$AH$4:$AH$303*'Loan Tape'!$R$4:$R$303)/E51,"-") -> 100 | I51: =IFERROR(SUMPRODUCT((('Loan Tape'!$R$4:$R$303<>"")*('Loan Tape'!$C$4:$C$303=R51))*(('Loan Tape'!$H$4:$H$303-$C$4)/30.4375)*'Loan Tape'!$R$4:$R$303)/E51,"-") -> 20.041068 | J51: =IFERROR(SUMPRODUCT((('Loan Tape'!$R$4:$R$303<>"")*('Loan Tape'!$C$4:$C$303=R51))*('Loan Tape'!$K$4:$K$303="Floating")*'Loan Tape'!$R$4:$R$303)/E51,"-") -> 1 | K51: =IFERROR(SUMPRODUCT((('Loan Tape'!$R$4:$R$303<>"")*('Loan Tape'!$C$4:$C$303=R51))*'Loan Tape'!$T$4:$T$303*'Loan Tape'!$R$4:$R$303)/E51,"-") -> 0.0814 | L51: =IFERROR(SUMPRODUCT((('Loan Tape'!$R$4:$R$303<>"")*('Loan Tape'!$C$4:$C$303=R51))*'Loan Tape'!$V$4:$V$303*'Loan Tape'!$R$4:$R$303)/E51,"-") -> 0.663 | M51: =IFERROR(SUMPRODUCT((('Loan Tape'!$R$4:$R$303<>"")*('Loan Tape'!$C$4:$C$303=R51))*'Loan Tape'!$W$4:$W$303*'Loan Tape'!$R$4:$R$303)/E51,"-") -> 0.69 | N51: =IFERROR(SUMPRODUCT((('Loan Tape'!$R$4:$R$303<>"")*('Loan Tape'!$C$4:$C$303=R51))*'Loan Tape'!$AI$4:$AI$303*'Loan Tape'!$R$4:$R$303)/E51,"-") -> 0.083 | O51: =IFERROR(SUMPRODUCT((('Loan Tape'!$R$4:$R$303<>"")*('Loan Tape'!$C$4:$C$303=R51))*'Loan Tape'!$AK$4:$AK$303*'Loan Tape'!$R$4:$R$303)/E51,"-") -> 0.098 | P51: =IFERROR(SUMPRODUCT((('Loan Tape'!$R$4:$R$303<>"")*('Loan Tape'!$C$4:$C$303=R51))*'Loan Tape'!$S$4:$S$303*'Loan Tape'!$R$4:$R$303)/E51,"-") -> 0.784 | R51: AZ
B52: =R52 -> VA | C52: =COUNTIF('Loan Tape'!$C$4:$C$303,R52) -> 3 | D52: =SUMPRODUCT((('Loan Tape'!$R$4:$R$303<>"")*('Loan Tape'!$C$4:$C$303=R52))*'Loan Tape'!$F$4:$F$303) -> 452 | E52: =SUMIF('Loan Tape'!$C$4:$C$303,R52,'Loan Tape'!$R$4:$R$303) -> 159023000 | F52: =IFERROR(E52/C5,0) -> 0.063721094 | G52: =IFERROR(SUMPRODUCT((('Loan Tape'!$R$4:$R$303<>"")*('Loan Tape'!$C$4:$C$303=R52))*'Loan Tape'!$U$4:$U$303*'Loan Tape'!$R$4:$R$303)/E52,"-") -> 1.4671085 | H52: =IFERROR(SUMPRODUCT((('Loan Tape'!$R$4:$R$303<>"")*('Loan Tape'!$C$4:$C$303=R52))*'Loan Tape'!$AH$4:$AH$303*'Loan Tape'!$R$4:$R$303)/E52,"-") -> 97.09245 | I52: =IFERROR(SUMPRODUCT((('Loan Tape'!$R$4:$R$303<>"")*('Loan Tape'!$C$4:$C$303=R52))*(('Loan Tape'!$H$4:$H$303-$C$4)/30.4375)*'Loan Tape'!$R$4:$R$303)/E52,"-") -> 19.586018 | J52: =IFERROR(SUMPRODUCT((('Loan Tape'!$R$4:$R$303<>"")*('Loan Tape'!$C$4:$C$303=R52))*('Loan Tape'!$K$4:$K$303="Floating")*'Loan Tape'!$R$4:$R$303)/E52,"-") -> 0.39695516 | K52: =IFERROR(SUMPRODUCT((('Loan Tape'!$R$4:$R$303<>"")*('Loan Tape'!$C$4:$C$303=R52))*'Loan Tape'!$T$4:$T$303*'Loan Tape'!$R$4:$R$303)/E52,"-") -> 0.098882387 | L52: =IFERROR(SUMPRODUCT((('Loan Tape'!$R$4:$R$303<>"")*('Loan Tape'!$C$4:$C$303=R52))*'Loan Tape'!$V$4:$V$303*'Loan Tape'!$R$4:$R$303)/E52,"-") -> 0.6050626 | M52: =IFERROR(SUMPRODUCT((('Loan Tape'!$R$4:$R$303<>"")*('Loan Tape'!$C$4:$C$303=R52))*'Loan Tape'!$W$4:$W$303*'Loan Tape'!$R$4:$R$303)/E52,"-") -> 0.63635841 | N52: =IFERROR(SUMPRODUCT((('Loan Tape'!$R$4:$R$303<>"")*('Loan Tape'!$C$4:$C$303=R52))*'Loan Tape'!$AI$4:$AI$303*'Loan Tape'!$R$4:$R$303)/E52,"-") -> 0.054217612 | O52: =IFERROR(SUMPRODUCT((('Loan Tape'!$R$4:$R$303<>"")*('Loan Tape'!$C$4:$C$303=R52))*'Loan Tape'!$AK$4:$AK$303*'Loan Tape'!$R$4:$R$303)/E52,"-") -> 0.060171939 | P52: =IFERROR(SUMPRODUCT((('Loan Tape'!$R$4:$R$303<>"")*('Loan Tape'!$C$4:$C$303=R52))*'Loan Tape'!$S$4:$S$303*'Loan Tape'!$R$4:$R$303)/E52,"-") -> 0.831541 | R52: VA
B53: =R53 -> IL | C53: =COUNTIF('Loan Tape'!$C$4:$C$303,R53) -> 2 | D53: =SUMPRODUCT((('Loan Tape'!$R$4:$R$303<>"")*('Loan Tape'!$C$4:$C$303=R53))*'Loan Tape'!$F$4:$F$303) -> 425 | E53: =SUMIF('Loan Tape'!$C$4:$C$303,R53,'Loan Tape'!$R$4:$R$303) -> 83754000 | F53: =IFERROR(E53/C5,0) -> 0.033560532 | G53: =IFERROR(SUMPRODUCT((('Loan Tape'!$R$4:$R$303<>"")*('Loan Tape'!$C$4:$C$303=R53))*'Loan Tape'!$U$4:$U$303*'Loan Tape'!$R$4:$R$303)/E53,"-") -> 1.3107056 | H53: =IFERROR(SUMPRODUCT((('Loan Tape'!$R$4:$R$303<>"")*('Loan Tape'!$C$4:$C$303=R53))*'Loan Tape'!$AH$4:$AH$303*'Loan Tape'!$R$4:$R$303)/E53,"-") -> 69.600544 | I53: =IFERROR(SUMPRODUCT((('Loan Tape'!$R$4:$R$303<>"")*('Loan Tape'!$C$4:$C$303=R53))*(('Loan Tape'!$H$4:$H$303-$C$4)/30.4375)*'Loan Tape'!$R$4:$R$303)/E53,"-") -> 50.397602 | J53: =IFERROR(SUMPRODUCT((('Loan Tape'!$R$4:$R$303<>"")*('Loan Tape'!$C$4:$C$303=R53))*('Loan Tape'!$K$4:$K$303="Floating")*'Loan Tape'!$R$4:$R$303)/E53,"-") -> 0.91611147 | K53: =IFERROR(SUMPRODUCT((('Loan Tape'!$R$4:$R$303<>"")*('Loan Tape'!$C$4:$C$303=R53))*'Loan Tape'!$T$4:$T$303*'Loan Tape'!$R$4:$R$303)/E53,"-") -> 0.085277892 | L53: =IFERROR(SUMPRODUCT((('Loan Tape'!$R$4:$R$303<>"")*('Loan Tape'!$C$4:$C$303=R53))*'Loan Tape'!$V$4:$V$303*'Loan Tape'!$R$4:$R$303)/E53,"-") -> 0.77201726 | M53: =IFERROR(SUMPRODUCT((('Loan Tape'!$R$4:$R$303<>"")*('Loan Tape'!$C$4:$C$303=R53))*'Loan Tape'!$W$4:$W$303*'Loan Tape'!$R$4:$R$303)/E53,"-") -> 0.80909449 | N53: =IFERROR(SUMPRODUCT((('Loan Tape'!$R$4:$R$303<>"")*('Loan Tape'!$C$4:$C$303=R53))*'Loan Tape'!$AI$4:$AI$303*'Loan Tape'!$R$4:$R$303)/E53,"-") -> 0.070270564 | O53: =IFERROR(SUMPRODUCT((('Loan Tape'!$R$4:$R$303<>"")*('Loan Tape'!$C$4:$C$303=R53))*'Loan Tape'!$AK$4:$AK$303*'Loan Tape'!$R$4:$R$303)/E53,"-") -> 0.084012236 | P53: =IFERROR(SUMPRODUCT((('Loan Tape'!$R$4:$R$303<>"")*('Loan Tape'!$C$4:$C$303=R53))*'Loan Tape'!$S$4:$S$303*'Loan Tape'!$R$4:$R$303)/E53,"-") -> 0.8376378 | R53: IL
B54: =R54 -> WA | C54: =COUNTIF('Loan Tape'!$C$4:$C$303,R54) -> 4 | D54: =SUMPRODUCT((('Loan Tape'!$R$4:$R$303<>"")*('Loan Tape'!$C$4:$C$303=R54))*'Loan Tape'!$F$4:$F$303) -> 250 | E54: =SUMIF('Loan Tape'!$C$4:$C$303,R54,'Loan Tape'!$R$4:$R$303) -> 344643000 | F54: =IFERROR(E54/C5,0) -> 0.1380997 | G54: =IFERROR(SUMPRODUCT((('Loan Tape'!$R$4:$R$303<>"")*('Loan Tape'!$C$4:$C$303=R54))*'Loan Tape'!$U$4:$U$303*'Loan Tape'!$R$4:$R$303)/E54,"-") -> 1.4726369 | H54: =IFERROR(SUMPRODUCT((('Loan Tape'!$R$4:$R$303<>"")*('Loan Tape'!$C$4:$C$303=R54))*'Loan Tape'!$AH$4:$AH$303*'Loan Tape'!$R$4:$R$303)/E54,"-") -> 92.149286 | I54: =IFERROR(SUMPRODUCT((('Loan Tape'!$R$4:$R$303<>"")*('Loan Tape'!$C$4:$C$303=R54))*(('Loan Tape'!$H$4:$H$303-$C$4)/30.4375)*'Loan Tape'!$R$4:$R$303)/E54,"-") -> 0.69952346 | J54: =IFERROR(SUMPRODUCT((('Loan Tape'!$R$4:$R$303<>"")*('Loan Tape'!$C$4:$C$303=R54))*('Loan Tape'!$K$4:$K$303="Floating")*'Loan Tape'!$R$4:$R$303)/E54,"-") -> 0.54747086 | K54: =IFERROR(SUMPRODUCT((('Loan Tape'!$R$4:$R$303<>"")*('Loan Tape'!$C$4:$C$303=R54))*'Loan Tape'!$T$4:$T$303*'Loan Tape'!$R$4:$R$303)/E54,"-") -> 0.091959665 | L54: =IFERROR(SUMPRODUCT((('Loan Tape'!$R$4:$R$303<>"")*('Loan Tape'!$C$4:$C$303=R54))*'Loan Tape'!$V$4:$V$303*'Loan Tape'!$R$4:$R$303)/E54,"-") -> 0.58533547 | M54: =IFERROR(SUMPRODUCT((('Loan Tape'!$R$4:$R$303<>"")*('Loan Tape'!$C$4:$C$303=R54))*'Loan Tape'!$W$4:$W$303*'Loan Tape'!$R$4:$R$303)/E54,"-") -> 0.60712066 | N54: =IFERROR(SUMPRODUCT((('Loan Tape'!$R$4:$R$303<>"")*('Loan Tape'!$C$4:$C$303=R54))*'Loan Tape'!$AI$4:$AI$303*'Loan Tape'!$R$4:$R$303)/E54,"-") -> 0.06813075 | O54: =IFERROR(SUMPRODUCT((('Loan Tape'!$R$4:$R$303<>"")*('Loan Tape'!$C$4:$C$303=R54))*'Loan Tape'!$AK$4:$AK$303*'Loan Tape'!$R$4:$R$303)/E54,"-") -> 0.076342813 | P54: =IFERROR(SUMPRODUCT((('Loan Tape'!$R$4:$R$303<>"")*('Loan Tape'!$C$4:$C$303=R54))*'Loan Tape'!$S$4:$S$303*'Loan Tape'!$R$4:$R$303)/E54,"-") -> 0.92199041 | R54: WA
B55: =R55 -> CO | C55: =COUNTIF('Loan Tape'!$C$4:$C$303,R55) -> 4 | D55: =SUMPRODUCT((('Loan Tape'!$R$4:$R$303<>"")*('Loan Tape'!$C$4:$C$303=R55))*'Loan Tape'!$F$4:$F$303) -> 571 | E55: =SUMIF('Loan Tape'!$C$4:$C$303,R55,'Loan Tape'!$R$4:$R$303) -> 239660000 | F55: =IFERROR(E55/C5,0) -> 0.096032633 | G55: =IFERROR(SUMPRODUCT((('Loan Tape'!$R$4:$R$303<>"")*('Loan Tape'!$C$4:$C$303=R55))*'Loan Tape'!$U$4:$U$303*'Loan Tape'!$R$4:$R$303)/E55,"-") -> 1.2623512 | H55: =IFERROR(SUMPRODUCT((('Loan Tape'!$R$4:$R$303<>"")*('Loan Tape'!$C$4:$C$303=R55))*'Loan Tape'!$AH$4:$AH$303*'Loan Tape'!$R$4:$R$303)/E55,"-") -> 73.797209 | I55: =IFERROR(SUMPRODUCT((('Loan Tape'!$R$4:$R$303<>"")*('Loan Tape'!$C$4:$C$303=R55))*(('Loan Tape'!$H$4:$H$303-$C$4)/30.4375)*'Loan Tape'!$R$4:$R$303)/E55,"-") -> 28.32601 | J55: =IFERROR(SUMPRODUCT((('Loan Tape'!$R$4:$R$303<>"")*('Loan Tape'!$C$4:$C$303=R55))*('Loan Tape'!$K$4:$K$303="Floating")*'Loan Tape'!$R$4:$R$303)/E55,"-") -> 0.61311441 | K55: =IFERROR(SUMPRODUCT((('Loan Tape'!$R$4:$R$303<>"")*('Loan Tape'!$C$4:$C$303=R55))*'Loan Tape'!$T$4:$T$303*'Loan Tape'!$R$4:$R$303)/E55,"-") -> 0.047355901 | L55: =IFERROR(SUMPRODUCT((('Loan Tape'!$R$4:$R$303<>"")*('Loan Tape'!$C$4:$C$303=R55))*'Loan Tape'!$V$4:$V$303*'Loan Tape'!$R$4:$R$303)/E55,"-") -> 0.7433249 | M55: =IFERROR(SUMPRODUCT((('Loan Tape'!$R$4:$R$303<>"")*('Loan Tape'!$C$4:$C$303=R55))*'Loan Tape'!$W$4:$W$303*'Loan Tape'!$R$4:$R$303)/E55,"-") -> 0.7788902 | N55: =IFERROR(SUMPRODUCT((('Loan Tape'!$R$4:$R$303<>"")*('Loan Tape'!$C$4:$C$303=R55))*'Loan Tape'!$AI$4:$AI$303*'Loan Tape'!$R$4:$R$303)/E55,"-") -> 0.071766179 | O55: =IFERROR(SUMPRODUCT((('Loan Tape'!$R$4:$R$303<>"")*('Loan Tape'!$C$4:$C$303=R55))*'Loan Tape'!$AK$4:$AK$303*'Loan Tape'!$R$4:$R$303)/E55,"-") -> 0.080962895 | P55: =IFERROR(SUMPRODUCT((('Loan Tape'!$R$4:$R$303<>"")*('Loan Tape'!$C$4:$C$303=R55))*'Loan Tape'!$S$4:$S$303*'Loan Tape'!$R$4:$R$303)/E55,"-") -> 0.87252365 | R55: CO
B56: =R56 -> OH | C56: =COUNTIF('Loan Tape'!$C$4:$C$303,R56) -> 4 | D56: =SUMPRODUCT((('Loan Tape'!$R$4:$R$303<>"")*('Loan Tape'!$C$4:$C$303=R56))*'Loan Tape'!$F$4:$F$303) -> 423 | E56: =SUMIF('Loan Tape'!$C$4:$C$303,R56,'Loan Tape'!$R$4:$R$303) -> 108163000 | F56: =IFERROR(E56/C5,0) -> 0.043341307 | G56: =IFERROR(SUMPRODUCT((('Loan Tape'!$R$4:$R$303<>"")*('Loan Tape'!$C$4:$C$303=R56))*'Loan Tape'!$U$4:$U$303*'Loan Tape'!$R$4:$R$303)/E56,"-") -> 1.7153724 | H56: =IFERROR(SUMPRODUCT((('Loan Tape'!$R$4:$R$303<>"")*('Loan Tape'!$C$4:$C$303=R56))*'Loan Tape'!$AH$4:$AH$303*'Loan Tape'!$R$4:$R$303)/E56,"-") -> 48.819635 | I56: =IFERROR(SUMPRODUCT((('Loan Tape'!$R$4:$R$303<>"")*('Loan Tape'!$C$4:$C$303=R56))*(('Loan Tape'!$H$4:$H$303-$C$4)/30.4375)*'Loan Tape'!$R$4:$R$303)/E56,"-") -> 46.922863 | J56: =IFERROR(SUMPRODUCT((('Loan Tape'!$R$4:$R$303<>"")*('Loan Tape'!$C$4:$C$303=R56))*('Loan Tape'!$K$4:$K$303="Floating")*'Loan Tape'!$R$4:$R$303)/E56,"-") -> 1 | K56: =IFERROR(SUMPRODUCT((('Loan Tape'!$R$4:$R$303<>"")*('Loan Tape'!$C$4:$C$303=R56))*'Loan Tape'!$T$4:$T$303*'Loan Tape'!$R$4:$R$303)/E56,"-") -> 0.053166964 | L56: =IFERROR(SUMPRODUCT((('Loan Tape'!$R$4:$R$303<>"")*('Loan Tape'!$C$4:$C$303=R56))*'Loan Tape'!$V$4:$V$303*'Loan Tape'!$R$4:$R$303)/E56,"-") -> 0.68091737 | M56: =IFERROR(SUMPRODUCT((('Loan Tape'!$R$4:$R$303<>"")*('Loan Tape'!$C$4:$C$303=R56))*'Loan Tape'!$W$4:$W$303*'Loan Tape'!$R$4:$R$303)/E56,"-") -> 0.71603915 | N56: =IFERROR(SUMPRODUCT((('Loan Tape'!$R$4:$R$303<>"")*('Loan Tape'!$C$4:$C$303=R56))*'Loan Tape'!$AI$4:$AI$303*'Loan Tape'!$R$4:$R$303)/E56,"-") -> 0.081181522 | O56: =IFERROR(SUMPRODUCT((('Loan Tape'!$R$4:$R$303<>"")*('Loan Tape'!$C$4:$C$303=R56))*'Loan Tape'!$AK$4:$AK$303*'Loan Tape'!$R$4:$R$303)/E56,"-") -> 0.095696066 | P56: =IFERROR(SUMPRODUCT((('Loan Tape'!$R$4:$R$303<>"")*('Loan Tape'!$C$4:$C$303=R56))*'Loan Tape'!$S$4:$S$303*'Loan Tape'!$R$4:$R$303)/E56,"-") -> 0.94558171 | R56: OH
B57: =R57 -> TN | C57: =COUNTIF('Loan Tape'!$C$4:$C$303,R57) -> 1 | D57: =SUMPRODUCT((('Loan Tape'!$R$4:$R$303<>"")*('Loan Tape'!$C$4:$C$303=R57))*'Loan Tape'!$F$4:$F$303) -> 121 | E57: =SUMIF('Loan Tape'!$C$4:$C$303,R57,'Loan Tape'!$R$4:$R$303) -> 8243000 | F57: =IFERROR(E57/C5,0) -> 0.0033030001 | G57: =IFERROR(SUMPRODUCT((('Loan Tape'!$R$4:$R$303<>"")*('Loan Tape'!$C$4:$C$303=R57))*'Loan Tape'!$U$4:$U$303*'Loan Tape'!$R$4:$R$303)/E57,"-") -> 1.69 | H57: =IFERROR(SUMPRODUCT((('Loan Tape'!$R$4:$R$303<>"")*('Loan Tape'!$C$4:$C$303=R57))*'Loan Tape'!$AH$4:$AH$303*'Loan Tape'!$R$4:$R$303)/E57,"-") -> 126 | I57: =IFERROR(SUMPRODUCT((('Loan Tape'!$R$4:$R$303<>"")*('Loan Tape'!$C$4:$C$303=R57))*(('Loan Tape'!$H$4:$H$303-$C$4)/30.4375)*'Loan Tape'!$R$4:$R$303)/E57,"-") -> -41.98768 | J57: =IFERROR(SUMPRODUCT((('Loan Tape'!$R$4:$R$303<>"")*('Loan Tape'!$C$4:$C$303=R57))*('Loan Tape'!$K$4:$K$303="Floating")*'Loan Tape'!$R$4:$R$303)/E57,"-") -> 1 | K57: =IFERROR(SUMPRODUCT((('Loan Tape'!$R$4:$R$303<>"")*('Loan Tape'!$C$4:$C$303=R57))*'Loan Tape'!$T$4:$T$303*'Loan Tape'!$R$4:$R$303)/E57,"-") -> 0.0445 | L57: =IFERROR(SUMPRODUCT((('Loan Tape'!$R$4:$R$303<>"")*('Loan Tape'!$C$4:$C$303=R57))*'Loan Tape'!$V$4:$V$303*'Loan Tape'!$R$4:$R$303)/E57,"-") -> 0.469 | M57: =IFERROR(SUMPRODUCT((('Loan Tape'!$R$4:$R$303<>"")*('Loan Tape'!$C$4:$C$303=R57))*'Loan Tape'!$W$4:$W$303*'Loan Tape'!$R$4:$R$303)/E57,"-") -> 0.515 | N57: =IFERROR(SUMPRODUCT((('Loan Tape'!$R$4:$R$303<>"")*('Loan Tape'!$C$4:$C$303=R57))*'Loan Tape'!$AI$4:$AI$303*'Loan Tape'!$R$4:$R$303)/E57,"-") -> 0.0664 | O57: =IFERROR(SUMPRODUCT((('Loan Tape'!$R$4:$R$303<>"")*('Loan Tape'!$C$4:$C$303=R57))*'Loan Tape'!$AK$4:$AK$303*'Loan Tape'!$R$4:$R$303)/E57,"-") -> 0.0814 | P57: =IFERROR(SUMPRODUCT((('Loan Tape'!$R$4:$R$303<>"")*('Loan Tape'!$C$4:$C$303=R57))*'Loan Tape'!$S$4:$S$303*'Loan Tape'!$R$4:$R$303)/E57,"-") -> 0.897 | R57: TN
B58: =R58 -> MA | C58: =COUNTIF('Loan Tape'!$C$4:$C$303,R58) -> 0 | D58: =SUMPRODUCT((('Loan Tape'!$R$4:$R$303<>"")*('Loan Tape'!$C$4:$C$303=R58))*'Loan Tape'!$F$4:$F$303) -> 0 | E58: =SUMIF('Loan Tape'!$C$4:$C$303,R58,'Loan Tape'!$R$4:$R$303) -> 0 | F58: =IFERROR(E58/C5,0) -> 0 | G58: =IFERROR(SUMPRODUCT((('Loan Tape'!$R$4:$R$303<>"")*('Loan Tape'!$C$4:$C$303=R58))*'Loan Tape'!$U$4:$U$303*'Loan Tape'!$R$4:$R$303)/E58,"-") -> - | H58: =IFERROR(SUMPRODUCT((('Loan Tape'!$R$4:$R$303<>"")*('Loan Tape'!$C$4:$C$303=R58))*'Loan Tape'!$AH$4:$AH$303*'Loan Tape'!$R$4:$R$303)/E58,"-") -> - | I58: =IFERROR(SUMPRODUCT((('Loan Tape'!$R$4:$R$303<>"")*('Loan Tape'!$C$4:$C$303=R58))*(('Loan Tape'!$H$4:$H$303-$C$4)/30.4375)*'Loan Tape'!$R$4:$R$303)/E58,"-") -> - | J58: =IFERROR(SUMPRODUCT((('Loan Tape'!$R$4:$R$303<>"")*('Loan Tape'!$C$4:$C$303=R58))*('Loan Tape'!$K$4:$K$303="Floating")*'Loan Tape'!$R$4:$R$303)/E58,"-") -> - | K58: =IFERROR(SUMPRODUCT((('Loan Tape'!$R$4:$R$303<>"")*('Loan Tape'!$C$4:$C$303=R58))*'Loan Tape'!$T$4:$T$303*'Loan Tape'!$R$4:$R$303)/E58,"-") -> - | L58: =IFERROR(SUMPRODUCT((('Loan Tape'!$R$4:$R$303<>"")*('Loan Tape'!$C$4:$C$303=R58))*'Loan Tape'!$V$4:$V$303*'Loan Tape'!$R$4:$R$303)/E58,"-") -> - | M58: =IFERROR(SUMPRODUCT((('Loan Tape'!$R$4:$R$303<>"")*('Loan Tape'!$C$4:$C$303=R58))*'Loan Tape'!$W$4:$W$303*'Loan Tape'!$R$4:$R$303)/E58,"-") -> - | N58: =IFERROR(SUMPRODUCT((('Loan Tape'!$R$4:$R$303<>"")*('Loan Tape'!$C$4:$C$303=R58))*'Loan Tape'!$AI$4:$AI$303*'Loan Tape'!$R$4:$R$303)/E58,"-") -> - | O58: =IFERROR(SUMPRODUCT((('Loan Tape'!$R$4:$R$303<>"")*('Loan Tape'!$C$4:$C$303=R58))*'Loan Tape'!$AK$4:$AK$303*'Loan Tape'!$R$4:$R$303)/E58,"-") -> - | P58: =IFERROR(SUMPRODUCT((('Loan Tape'!$R$4:$R$303<>"")*('Loan Tape'!$C$4:$C$303=R58))*'Loan Tape'!$S$4:$S$303*'Loan Tape'!$R$4:$R$303)/E58,"-") -> - | R58: MA
B59: =R59 -> NV | C59: =COUNTIF('Loan Tape'!$C$4:$C$303,R59) -> 2 | D59: =SUMPRODUCT((('Loan Tape'!$R$4:$R$303<>"")*('Loan Tape'!$C$4:$C$303=R59))*'Loan Tape'!$F$4:$F$303) -> 161 | E59: =SUMIF('Loan Tape'!$C$4:$C$303,R59,'Loan Tape'!$R$4:$R$303) -> 174333000 | F59: =IFERROR(E59/C5,0) -> 0.069855867 | G59: =IFERROR(SUMPRODUCT((('Loan Tape'!$R$4:$R$303<>"")*('Loan Tape'!$C$4:$C$303=R59))*'Loan Tape'!$U$4:$U$303*'Loan Tape'!$R$4:$R$303)/E59,"-") -> 1.8849226 | H59: =IFERROR(SUMPRODUCT((('Loan Tape'!$R$4:$R$303<>"")*('Loan Tape'!$C$4:$C$303=R59))*'Loan Tape'!$AH$4:$AH$303*'Loan Tape'!$R$4:$R$303)/E59,"-") -> 51.374433 | I59: =IFERROR(SUMPRODUCT((('Loan Tape'!$R$4:$R$303<>"")*('Loan Tape'!$C$4:$C$303=R59))*(('Loan Tape'!$H$4:$H$303-$C$4)/30.4375)*'Loan Tape'!$R$4:$R$303)/E59,"-") -> 42.187891 | J59: =IFERROR(SUMPRODUCT((('Loan Tape'!$R$4:$R$303<>"")*('Loan Tape'!$C$4:$C$303=R59))*('Loan Tape'!$K$4:$K$303="Floating")*'Loan Tape'!$R$4:$R$303)/E59,"-") -> 0.26410376 | K59: =IFERROR(SUMPRODUCT((('Loan Tape'!$R$4:$R$303<>"")*('Loan Tape'!$C$4:$C$303=R59))*'Loan Tape'!$T$4:$T$303*'Loan Tape'!$R$4:$R$303)/E59,"-") -> 0.098248476 | L59: =IFERROR(SUMPRODUCT((('Loan Tape'!$R$4:$R$303<>"")*('Loan Tape'!$C$4:$C$303=R59))*'Loan Tape'!$V$4:$V$303*'Loan Tape'!$R$4:$R$303)/E59,"-") -> 0.60426114 | M59: =IFERROR(SUMPRODUCT((('Loan Tape'!$R$4:$R$303<>"")*('Loan Tape'!$C$4:$C$303=R59))*'Loan Tape'!$W$4:$W$303*'Loan Tape'!$R$4:$R$303)/E59,"-") -> 0.63537397 | N59: =IFERROR(SUMPRODUCT((('Loan Tape'!$R$4:$R$303<>"")*('Loan Tape'!$C$4:$C$303=R59))*'Loan Tape'!$AI$4:$AI$303*'Loan Tape'!$R$4:$R$303)/E59,"-") -> 0.053859759 | O59: =IFERROR(SUMPRODUCT((('Loan Tape'!$R$4:$R$303<>"")*('Loan Tape'!$C$4:$C$303=R59))*'Loan Tape'!$AK$4:$AK$303*'Loan Tape'!$R$4:$R$303)/E59,"-") -> 0.057821316 | P59: =IFERROR(SUMPRODUCT((('Loan Tape'!$R$4:$R$303<>"")*('Loan Tape'!$C$4:$C$303=R59))*'Loan Tape'!$S$4:$S$303*'Loan Tape'!$R$4:$R$303)/E59,"-") -> 0.85165151 | R59: NV
B60: Other | C60: =C6-SUM(C45:C59) -> 7 | D60: =SUM('Loan Tape'!$F$4:$F$303)-SUM(D45:D59) -> 444 | E60: =C5-SUM(E45:E59) -> 209083000 | F60: =IFERROR(E60/C5,0) -> 0.083780318 | G60: =IFERROR(SUMPRODUCT((('Loan Tape'!$R$4:$R$303<>"")*(1-(('Loan Tape'!$C$4:$C$303=R45)+('Loan Tape'!$C$4:$C$303=R46)+('Loan Tape'!$C$4:$C$303=R47)+('Loan Tape'!$C$4:$C$303=R48)+('Loan Tape'!$C$4:$C$303=R49)+('Loan Tape'!$C$4:$C$303=R50)+('Loan Tape'!$C$4:$C$303=R51)+('Loan Tape'!$C$4:$C$303=R52)+('Loan Tape'!$C$4:$C$303=R53)+('Loan Tape'!$C$4:$C$303=R54)+('Loan Tape'!$C$4:$C$303=R55)+('Loan Tape'!$C$4:$C$303=R56)+('Loan Tape'!$C$4:$C$303=R57)+('Loan Tape'!$C$4:$C$303=R58)+('Loan Tape'!$C$4:$C$303=R59))))*'Loan Tape'!$U$4:$U$303*'Loan Tape'!$R$4:$R$303)/E60,"-") -> 1.3679199 | H60: =IFERROR(SUMPRODUCT((('Loan Tape'!$R$4:$R$303<>"")*(1-(('Loan Tape'!$C$4:$C$303=R45)+('Loan Tape'!$C$4:$C$303=R46)+('Loan Tape'!$C$4:$C$303=R47)+('Loan Tape'!$C$4:$C$303=R48)+('Loan Tape'!$C$4:$C$303=R49)+('Loan Tape'!$C$4:$C$303=R50)+('Loan Tape'!$C$4:$C$303=R51)+('Loan Tape'!$C$4:$C$303=R52)+('Loan Tape'!$C$4:$C$303=R53)+('Loan Tape'!$C$4:$C$303=R54)+('Loan Tape'!$C$4:$C$303=R55)+('Loan Tape'!$C$4:$C$303=R56)+('Loan Tape'!$C$4:$C$303=R57)+('Loan Tape'!$C$4:$C$303=R58)+('Loan Tape'!$C$4:$C$303=R59))))*'Loan Tape'!$AH$4:$AH$303*'Loan Tape'!$R$4:$R$303)/E60,"-") -> 93.474695 | I60: =IFERROR(SUMPRODUCT((('Loan Tape'!$R$4:$R$303<>"")*(1-(('Loan Tape'!$C$4:$C$303=R45)+('Loan Tape'!$C$4:$C$303=R46)+('Loan Tape'!$C$4:$C$303=R47)+('Loan Tape'!$C$4:$C$303=R48)+('Loan Tape'!$C$4:$C$303=R49)+('Loan Tape'!$C$4:$C$303=R50)+('Loan Tape'!$C$4:$C$303=R51)+('Loan Tape'!$C$4:$C$303=R52)+('Loan Tape'!$C$4:$C$303=R53)+('Loan Tape'!$C$4:$C$303=R54)+('Loan Tape'!$C$4:$C$303=R55)+('Loan Tape'!$C$4:$C$303=R56)+('Loan Tape'!$C$4:$C$303=R57)+('Loan Tape'!$C$4:$C$303=R58)+('Loan Tape'!$C$4:$C$303=R59))))*(('Loan Tape'!$H$4:$H$303-$C$4)/30.4375)*'Loan Tape'!$R$4:$R$303)/E60,"-") -> -26.543591 | J60: =IFERROR(SUMPRODUCT((('Loan Tape'!$R$4:$R$303<>"")*(1-(('Loan Tape'!$C$4:$C$303=R45)+('Loan Tape'!$C$4:$C$303=R46)+('Loan Tape'!$C$4:$C$303=R47)+('Loan Tape'!$C$4:$C$303=R48)+('Loan Tape'!$C$4:$C$303=R49)+('Loan Tape'!$C$4:$C$303=R50)+('Loan Tape'!$C$4:$C$303=R51)+('Loan Tape'!$C$4:$C$303=R52)+('Loan Tape'!$C$4:$C$303=R53)+('Loan Tape'!$C$4:$C$303=R54)+('Loan Tape'!$C$4:$C$303=R55)+('Loan Tape'!$C$4:$C$303=R56)+('Loan Tape'!$C$4:$C$303=R57)+('Loan Tape'!$C$4:$C$303=R58)+('Loan Tape'!$C$4:$C$303=R59))))*('Loan Tape'!$K$4:$K$303="Floating")*'Loan Tape'!$R$4:$R$303)/E60,"-") -> 0.94885763 | K60: =IFERROR(SUMPRODUCT((('Loan Tape'!$R$4:$R$303<>"")*(1-(('Loan Tape'!$C$4:$C$303=R45)+('Loan Tape'!$C$4:$C$303=R46)+('Loan Tape'!$C$4:$C$303=R47)+('Loan Tape'!$C$4:$C$303=R48)+('Loan Tape'!$C$4:$C$303=R49)+('Loan Tape'!$C$4:$C$303=R50)+('Loan Tape'!$C$4:$C$303=R51)+('Loan Tape'!$C$4:$C$303=R52)+('Loan Tape'!$C$4:$C$303=R53)+('Loan Tape'!$C$4:$C$303=R54)+('Loan Tape'!$C$4:$C$303=R55)+('Loan Tape'!$C$4:$C$303=R56)+('Loan Tape'!$C$4:$C$303=R57)+('Loan Tape'!$C$4:$C$303=R58)+('Loan Tape'!$C$4:$C$303=R59))))*'Loan Tape'!$T$4:$T$303*'Loan Tape'!$R$4:$R$303)/E60,"-") -> 0.088561907 | L60: =IFERROR(SUMPRODUCT((('Loan Tape'!$R$4:$R$303<>"")*(1-(('Loan Tape'!$C$4:$C$303=R45)+('Loan Tape'!$C$4:$C$303=R46)+('Loan Tape'!$C$4:$C$303=R47)+('Loan Tape'!$C$4:$C$303=R48)+('Loan Tape'!$C$4:$C$303=R49)+('Loan Tape'!$C$4:$C$303=R50)+('Loan Tape'!$C$4:$C$303=R51)+('Loan Tape'!$C$4:$C$303=R52)+('Loan Tape'!$C$4:$C$303=R53)+('Loan Tape'!$C$4:$C$303=R54)+('Loan Tape'!$C$4:$C$303=R55)+('Loan Tape'!$C$4:$C$303=R56)+('Loan Tape'!$C$4:$C$303=R57)+('Loan Tape'!$C$4:$C$303=R58)+('Loan Tape'!$C$4:$C$303=R59))))*'Loan Tape'!$V$4:$V$303*'Loan Tape'!$R$4:$R$303)/E60,"-") -> 0.74892106 | M60: =IFERROR(SUMPRODUCT((('Loan Tape'!$R$4:$R$303<>"")*(1-(('Loan Tape'!$C$4:$C$303=R45)+('Loan Tape'!$C$4:$C$303=R46)+('Loan Tape'!$C$4:$C$303=R47)+('Loan Tape'!$C$4:$C$303=R48)+('Loan Tape'!$C$4:$C$303=R49)+('Loan Tape'!$C$4:$C$303=R50)+('Loan Tape'!$C$4:$C$303=R51)+('Loan Tape'!$C$4:$C$303=R52)+('Loan Tape'!$C$4:$C$303=R53)+('Loan Tape'!$C$4:$C$303=R54)+('Loan Tape'!$C$4:$C$303=R55)+('Loan Tape'!$C$4:$C$303=R56)+('Loan Tape'!$C$4:$C$303=R57)+('Loan Tape'!$C$4:$C$303=R58)+('Loan Tape'!$C$4:$C$303=R59))))*'Loan Tape'!$W$4:$W$303*'Loan Tape'!$R$4:$R$303)/E60,"-") -> 0.78931891 | N60: =IFERROR(SUMPRODUCT((('Loan Tape'!$R$4:$R$303<>"")*(1-(('Loan Tape'!$C$4:$C$303=R45)+('Loan Tape'!$C$4:$C$303=R46)+('Loan Tape'!$C$4:$C$303=R47)+('Loan Tape'!$C$4:$C$303=R48)+('Loan Tape'!$C$4:$C$303=R49)+('Loan Tape'!$C$4:$C$303=R50)+('Loan Tape'!$C$4:$C$303=R51)+('Loan Tape'!$C$4:$C$303=R52)+('Loan Tape'!$C$4:$C$303=R53)+('Loan Tape'!$C$4:$C$303=R54)+('Loan Tape'!$C$4:$C$303=R55)+('Loan Tape'!$C$4:$C$303=R56)+('Loan Tape'!$C$4:$C$303=R57)+('Loan Tape'!$C$4:$C$303=R58)+('Loan Tape'!$C$4:$C$303=R59))))*'Loan Tape'!$AI$4:$AI$303*'Loan Tape'!$R$4:$R$303)/E60,"-") -> 0.080593622 | O60: =IFERROR(SUMPRODUCT((('Loan Tape'!$R$4:$R$303<>"")*(1-(('Loan Tape'!$C$4:$C$303=R45)+('Loan Tape'!$C$4:$C$303=R46)+('Loan Tape'!$C$4:$C$303=R47)+('Loan Tape'!$C$4:$C$303=R48)+('Loan Tape'!$C$4:$C$303=R49)+('Loan Tape'!$C$4:$C$303=R50)+('Loan Tape'!$C$4:$C$303=R51)+('Loan Tape'!$C$4:$C$303=R52)+('Loan Tape'!$C$4:$C$303=R53)+('Loan Tape'!$C$4:$C$303=R54)+('Loan Tape'!$C$4:$C$303=R55)+('Loan Tape'!$C$4:$C$303=R56)+('Loan Tape'!$C$4:$C$303=R57)+('Loan Tape'!$C$4:$C$303=R58)+('Loan Tape'!$C$4:$C$303=R59))))*'Loan Tape'!$AK$4:$AK$303*'Loan Tape'!$R$4:$R$303)/E60,"-") -> 0.083502827 | P60: =IFERROR(SUMPRODUCT((('Loan Tape'!$R$4:$R$303<>"")*(1-(('Loan Tape'!$C$4:$C$303=R45)+('Loan Tape'!$C$4:$C$303=R46)+('Loan Tape'!$C$4:$C$303=R47)+('Loan Tape'!$C$4:$C$303=R48)+('Loan Tape'!$C$4:$C$303=R49)+('Loan Tape'!$C$4:$C$303=R50)+('Loan Tape'!$C$4:$C$303=R51)+('Loan Tape'!$C$4:$C$303=R52)+('Loan Tape'!$C$4:$C$303=R53)+('Loan Tape'!$C$4:$C$303=R54)+('Loan Tape'!$C$4:$C$303=R55)+('Loan Tape'!$C$4:$C$303=R56)+('Loan Tape'!$C$4:$C$303=R57)+('Loan Tape'!$C$4:$C$303=R58)+('Loan Tape'!$C$4:$C$303=R59))))*'Loan Tape'!$S$4:$S$303*'Loan Tape'!$R$4:$R$303)/E60,"-") -> 0.81348096
B61: Total / Wtd. Avg. | C61: =C6 -> 50 | D61: =SUM('Loan Tape'!$F$4:$F$303) -> 4739 | E61: =C5 -> 2495610000 | F61: =1 -> 1 | G61: =IFERROR(SUMPRODUCT((('Loan Tape'!$R$4:$R$303<>""))*'Loan Tape'!$U$4:$U$303*'Loan Tape'!$R$4:$R$303)/E61,"-") -> 1.3657594 | H61: =IFERROR(SUMPRODUCT((('Loan Tape'!$R$4:$R$303<>""))*'Loan Tape'!$AH$4:$AH$303*'Loan Tape'!$R$4:$R$303)/E61,"-") -> 76.514735 | I61: =IFERROR(SUMPRODUCT((('Loan Tape'!$R$4:$R$303<>""))*(('Loan Tape'!$H$4:$H$303-$C$4)/30.4375)*'Loan Tape'!$R$4:$R$303)/E61,"-") -> 17.677294 | J61: =IFERROR(SUMPRODUCT((('Loan Tape'!$R$4:$R$303<>""))*('Loan Tape'!$K$4:$K$303="Floating")*'Loan Tape'!$R$4:$R$303)/E61,"-") -> 0.66447762 | K61: =IFERROR(SUMPRODUCT((('Loan Tape'!$R$4:$R$303<>""))*'Loan Tape'!$T$4:$T$303*'Loan Tape'!$R$4:$R$303)/E61,"-") -> 0.086154057 | L61: =IFERROR(SUMPRODUCT((('Loan Tape'!$R$4:$R$303<>""))*'Loan Tape'!$V$4:$V$303*'Loan Tape'!$R$4:$R$303)/E61,"-") -> 0.68355926 | M61: =IFERROR(SUMPRODUCT((('Loan Tape'!$R$4:$R$303<>""))*'Loan Tape'!$W$4:$W$303*'Loan Tape'!$R$4:$R$303)/E61,"-") -> 0.71616446 | N61: =IFERROR(SUMPRODUCT((('Loan Tape'!$R$4:$R$303<>""))*'Loan Tape'!$AI$4:$AI$303*'Loan Tape'!$R$4:$R$303)/E61,"-") -> 0.070457452 | O61: =IFERROR(SUMPRODUCT((('Loan Tape'!$R$4:$R$303<>""))*'Loan Tape'!$AK$4:$AK$303*'Loan Tape'!$R$4:$R$303)/E61,"-") -> 0.079210317 | P61: =IFERROR(SUMPRODUCT((('Loan Tape'!$R$4:$R$303<>""))*'Loan Tape'!$S$4:$S$303*'Loan Tape'!$R$4:$R$303)/E61,"-") -> 0.88668714
B63: UNDERLYING DEALS
B64: Category | C64: Number of Loans | D64: Number of Units | E64: Current Principal Balance | F64: % of Current Principal Balance | G64: Wtd. Avg. Most Recent DSCR | H64: Wtd. Avg. Seasoning | I64: Wtd. Avg. Remaining Term | J64: % UPB Floating | K64: Wtd. Avg. Most Recent NOI Debt Yield | L64: Wtd. Avg. Most Recent LTV Ratio | M64: Wtd. Avg. SSP / UW LTV Ratio | N64: Wtd. Avg. Coupon | O64: Wtd. Avg. Coupon at Reset | P64: Wtd. Avg. Occupancy
B65: =R65 -> Deal 1 | C65: =COUNTIF('Loan Tape'!$E$4:$E$303,R65) -> 5 | D65: =SUMPRODUCT((('Loan Tape'!$R$4:$R$303<>"")*('Loan Tape'!$E$4:$E$303=R65))*'Loan Tape'!$F$4:$F$303) -> 593 | E65: =SUMIF('Loan Tape'!$E$4:$E$303,R65,'Loan Tape'!$R$4:$R$303) -> 372487000 | F65: =IFERROR(E65/C5,0) -> 0.1492569 | G65: =IFERROR(SUMPRODUCT((('Loan Tape'!$R$4:$R$303<>"")*('Loan Tape'!$E$4:$E$303=R65))*'Loan Tape'!$U$4:$U$303*'Loan Tape'!$R$4:$R$303)/E65,"-") -> 1.4628617 | H65: =IFERROR(SUMPRODUCT((('Loan Tape'!$R$4:$R$303<>"")*('Loan Tape'!$E$4:$E$303=R65))*'Loan Tape'!$AH$4:$AH$303*'Loan Tape'!$R$4:$R$303)/E65,"-") -> 100.40113 | I65: =IFERROR(SUMPRODUCT((('Loan Tape'!$R$4:$R$303<>"")*('Loan Tape'!$E$4:$E$303=R65))*(('Loan Tape'!$H$4:$H$303-$C$4)/30.4375)*'Loan Tape'!$R$4:$R$303)/E65,"-") -> 4.0223964 | J65: =IFERROR(SUMPRODUCT((('Loan Tape'!$R$4:$R$303<>"")*('Loan Tape'!$E$4:$E$303=R65))*('Loan Tape'!$K$4:$K$303="Floating")*'Loan Tape'!$R$4:$R$303)/E65,"-") -> 0.64712594 | K65: =IFERROR(SUMPRODUCT((('Loan Tape'!$R$4:$R$303<>"")*('Loan Tape'!$E$4:$E$303=R65))*'Loan Tape'!$T$4:$T$303*'Loan Tape'!$R$4:$R$303)/E65,"-") -> 0.085372788 | L65: =IFERROR(SUMPRODUCT((('Loan Tape'!$R$4:$R$303<>"")*('Loan Tape'!$E$4:$E$303=R65))*'Loan Tape'!$V$4:$V$303*'Loan Tape'!$R$4:$R$303)/E65,"-") -> 0.69021042 | M65: =IFERROR(SUMPRODUCT((('Loan Tape'!$R$4:$R$303<>"")*('Loan Tape'!$E$4:$E$303=R65))*'Loan Tape'!$W$4:$W$303*'Loan Tape'!$R$4:$R$303)/E65,"-") -> 0.72792231 | N65: =IFERROR(SUMPRODUCT((('Loan Tape'!$R$4:$R$303<>"")*('Loan Tape'!$E$4:$E$303=R65))*'Loan Tape'!$AI$4:$AI$303*'Loan Tape'!$R$4:$R$303)/E65,"-") -> 0.068070547 | O65: =IFERROR(SUMPRODUCT((('Loan Tape'!$R$4:$R$303<>"")*('Loan Tape'!$E$4:$E$303=R65))*'Loan Tape'!$AK$4:$AK$303*'Loan Tape'!$R$4:$R$303)/E65,"-") -> 0.077777436 | P65: =IFERROR(SUMPRODUCT((('Loan Tape'!$R$4:$R$303<>"")*('Loan Tape'!$E$4:$E$303=R65))*'Loan Tape'!$S$4:$S$303*'Loan Tape'!$R$4:$R$303)/E65,"-") -> 0.8414625 | R65: Deal 1
